{
  "type": "Feature",
  "properties": {
    "iso:country":"US",
    "sg:address":"159 Hogan Rd",
    "sg:city":"Bangor",
    "sg:classifiers":[
        {
            "category":"Government",
            "subcategory":"Office",
            "type":"Public Place"
        }
    ],
    "sg:phone":"+1 207 941 4400",
    "sg:postcode":"04401",
    "sg:province":"ME",
    "wof:name":"Elizabeth Levinson Ctr",
    "wof:placetype":"venue"
},
  "geometry": {"coordinates":[-68.738009,44.815518],"type":"Point"}
}