{
  "type": "Feature",
  "properties": {
    "iso:country":"US",
    "sg:address":"5 Summer Pl",
    "sg:city":"Portland",
    "sg:classifiers":[
        {
            "category":"Utilities",
            "subcategory":"Telephone",
            "type":"Services"
        }
    ],
    "sg:phone":"+1 207 347 7360",
    "sg:postcode":"04103",
    "sg:province":"ME",
    "sg:tags":[
        "development",
        "application",
        "internet"
    ],
    "wof:name":"Dirigo Design & Dev Inc",
    "wof:placetype":"venue"
},
  "geometry": {"coordinates":[-70.26172099999999,43.695318],"type":"Point"}
}