{
  "type": "Feature",
  "properties": {
    "iso:country":"US",
    "sg:address":"18 Tampa St",
    "sg:city":"Lewiston",
    "sg:classifiers":[
        {
            "category":"Organizations",
            "subcategory":"Religious Organization",
            "type":"Services"
        }
    ],
    "sg:phone":"+1 207 782 7480",
    "sg:postcode":"04240",
    "sg:province":"ME",
    "wof:name":"Dominican Sisters",
    "wof:placetype":"venue"
},
  "geometry": {"coordinates":[-70.197506,44.097654],"type":"Point"}
}