{
  "type": "Feature",
  "properties": {
    "iso:country":"US",
    "sg:address":"10 Church St",
    "sg:city":"Bethel",
    "sg:classifiers":[
        {
            "category":"Professional",
            "subcategory":"Computer Services",
            "type":"Services"
        }
    ],
    "sg:phone":"+1 207 824 3970",
    "sg:postcode":"04217",
    "sg:province":"ME",
    "sg:tags":[
        "datum"
    ],
    "wof:name":"Harry H Dresser & Sons",
    "wof:placetype":"venue"
},
  "geometry": {"coordinates":[-70.793639,44.408536],"type":"Point"}
}