{
  "type": "Feature",
  "properties": {
    "addr:full":"443 Main St Norway ME 04268",
    "addr:housenumber":"443",
    "addr:postcode":"04268",
    "addr:street":"Main St",
    "iso:country":"US",
    "sg:address":"443 Main St",
    "sg:city":"Norway",
    "sg:classifiers":[
        {
            "category":"Food & Beverages",
            "subcategory":"Specialty",
            "type":"Retail Goods"
        }
    ],
    "sg:phone":"+1 207 743 9044",
    "sg:postcode":"04268",
    "sg:province":"ME",
    "sg:tags":[
        "health",
        "diet"
    ],
    "wof:name":"Fare Share Co-Op Store",
    "wof:placetype":"venue"
},
  "geometry": {"coordinates":[-70.542931,44.213792],"type":"Point"}
}