{
  "type": "Feature",
  "properties": {
    "addr:full":"190 Hill St Biddeford ME 04005",
    "addr:housenumber":"190",
    "addr:postcode":"04005",
    "addr:street":"Hill St",
    "iso:country":"US",
    "sg:address":"190 Hill St",
    "sg:city":"Biddeford",
    "sg:classifiers":[
        {
            "category":"Arena",
            "subcategory":"Sports Club",
            "type":"Entertainment"
        }
    ],
    "sg:phone":"+1 207 283 0636",
    "sg:postcode":"04005",
    "sg:province":"ME",
    "sg:tags":[
        "athletic",
        "fields",
        "stadium"
    ],
    "wof:name":"East Biddeford Little League",
    "wof:placetype":"venue"
},
  "geometry": {"coordinates":[-70.457082,43.485138],"type":"Point"}
}