{
  "type": "Feature",
  "properties": {
    "iso:country":"US",
    "sg:address":"86 Winthrop St",
    "sg:city":"Augusta",
    "sg:classifiers":[
        {
            "category":"Professional",
            "subcategory":"Management & Consulting",
            "type":"Services"
        }
    ],
    "sg:phone":"+1 207 622 2727",
    "sg:postcode":"04330",
    "sg:province":"ME",
    "sg:tags":[
        "consultant"
    ],
    "wof:name":"Premiere It Solution Inc",
    "wof:placetype":"venue"
},
  "geometry": {"coordinates":[-69.781618,44.315792],"type":"Point"}
}