{
  "type": "Feature",
  "properties": {
    "addr:full":"37 Cotton Rd Lisbon ME 04250",
    "addr:housenumber":"37",
    "addr:postcode":"04250",
    "addr:street":"Cotton Rd",
    "iso:country":"US",
    "sg:address":"37 Cotton Rd",
    "sg:city":"Lisbon",
    "sg:classifiers":[
        {
            "category":"Government",
            "subcategory":"Office",
            "type":"Public Place"
        }
    ],
    "sg:phone":"+1 207 353 9075",
    "sg:postcode":"04250",
    "sg:province":"ME",
    "sg:tags":[
        "conservation"
    ],
    "wof:name":"Beaver Park",
    "wof:placetype":"venue"
},
  "geometry": {"coordinates":[-70.13279199999999,44.026381],"type":"Point"}
}