{
  "type": "Feature",
  "properties": {
    "addr:full":"181 Purple Heart Hwy Brooks ME 04921",
    "addr:housenumber":"181",
    "addr:postcode":"04921",
    "addr:street":"Purple Heart Hwy",
    "iso:country":"US",
    "sg:address":"181 Purple Heart Hwy",
    "sg:city":"Brooks",
    "sg:classifiers":[
        {
            "category":"Manufacturing",
            "subcategory":"Tools & Machinery",
            "type":"Manufacturing & Wholesale Goods"
        }
    ],
    "sg:phone":"+1 207 722 3040",
    "sg:postcode":"04921",
    "sg:province":"ME",
    "sg:tags":[
        "machine",
        "shop"
    ],
    "wof:name":"Norturn Inc",
    "wof:placetype":"venue"
},
  "geometry": {"coordinates":[-69.130813,44.552295],"type":"Point"}
}