{
  "type": "Feature",
  "properties": {
    "addr:full":"30 Scituate Rd York ME 03909",
    "addr:housenumber":"30",
    "addr:postcode":"03909",
    "addr:street":"Scituate Rd",
    "iso:country":"US",
    "sg:address":"30 Scituate Rd",
    "sg:city":"York",
    "sg:classifiers":[
        {
            "category":"Building & Trades",
            "subcategory":"Construction",
            "type":"Services"
        }
    ],
    "sg:phone":"+1 207 363 6599",
    "sg:postcode":"03909",
    "sg:province":"ME",
    "sg:tags":[
        "painter",
        "contractor"
    ],
    "sg:website":"www.atlanticapplicators.com",
    "wof:name":"Atlantic Applicators",
    "wof:placetype":"venue"
},
  "geometry": {"coordinates":[-70.668404,43.1665],"type":"Point"}
}