{
  "type": "Feature",
  "properties": {
    "addr:full":"80 Pine Hill Rd Cape Neddick ME 03902",
    "addr:housenumber":"80",
    "addr:postcode":"03902",
    "addr:street":"Pine Hill Rd",
    "iso:country":"US",
    "sg:address":"80 Pine Hill Rd",
    "sg:city":"Cape Neddick",
    "sg:classifiers":[
        {
            "category":"Cinema",
            "subcategory":"Movie Theater",
            "type":"Entertainment"
        }
    ],
    "sg:phone":"+1 207 363 9983",
    "sg:postcode":"03902",
    "sg:province":"ME",
    "sg:tags":[
        "motion",
        "picture"
    ],
    "wof:name":"Cinema Management",
    "wof:placetype":"venue"
},
  "geometry": {"coordinates":[-70.602752,43.232924],"type":"Point"}
}