{
  "type": "Feature",
  "properties": {
    "iso:country":"US",
    "sg:address":"344 River Rd",
    "sg:city":"Mexico",
    "sg:classifiers":[
        {
            "category":"Freight",
            "type":"Transportation"
        }
    ],
    "sg:phone":"+1 207 364 8948",
    "sg:postcode":"04257",
    "sg:province":"ME",
    "sg:tags":[
        "trucking"
    ],
    "sg:website":"www.archies.net",
    "wof:name":"Aulenback Trucking Inc",
    "wof:placetype":"venue"
},
  "geometry": {"coordinates":[-70.510329,44.536131],"type":"Point"}
}