{
  "type": "Feature",
  "properties": {
    "addr:full":"200 Kennedy Memorial Dr Waterville ME 04901",
    "addr:housenumber":"200",
    "addr:postcode":"04901",
    "addr:street":"Kennedy Memorial Dr",
    "iso:country":"US",
    "sg:address":"200 Kennedy Memorial Dr",
    "sg:city":"Waterville",
    "sg:classifiers":[
        {
            "category":"Health Services",
            "subcategory":"Hospital",
            "type":"Services"
        }
    ],
    "sg:phone":"+1 207 861 3000",
    "sg:postcode":"04901",
    "sg:province":"ME",
    "wof:name":"Inland Hospital",
    "wof:placetype":"venue"
},
  "geometry": {"coordinates":[-69.663994,44.543049],"type":"Point"}
}