{
  "type": "Feature",
  "properties": {
    "addr:full":"244 Center Line Rd Presque Isle ME 04769",
    "addr:housenumber":"244",
    "addr:postcode":"04769",
    "addr:street":"Center Line Rd;Isle",
    "iso:country":"US",
    "sg:address":"244 Center Line Rd",
    "sg:city":"Presque Isle",
    "sg:classifiers":[
        {
            "category":"Home & Garden",
            "subcategory":"Carpets & Floor Coverings",
            "type":"Retail Goods"
        }
    ],
    "sg:phone":"+1 207 768 8851",
    "sg:postcode":"04769",
    "sg:province":"ME",
    "sg:tags":[
        "dealer",
        "rug"
    ],
    "wof:name":"Hutchings Flooring",
    "wof:placetype":"venue"
},
  "geometry": {"coordinates":[-67.984987,46.656582],"type":"Point"}
}