{
  "type": "Feature",
  "properties": {
    "addr:full":"159 Roosevelt Trl Windham ME 04062",
    "addr:housenumber":"159",
    "addr:postcode":"04062",
    "addr:street":"Roosevelt Trl",
    "iso:country":"US",
    "sg:address":"159 Roosevelt Trl",
    "sg:city":"Windham",
    "sg:classifiers":[
        {
            "category":"Retail",
            "subcategory":"Repair Shop",
            "type":"Services"
        }
    ],
    "sg:phone":"+1 207 892 2908",
    "sg:postcode":"04062",
    "sg:province":"ME",
    "sg:tags":[
        "radio",
        "television",
        "electrical"
    ],
    "wof:name":"W E Fixxit",
    "wof:placetype":"venue"
},
  "geometry": {"coordinates":[-70.39823199999999,43.792998],"type":"Point"}
}