{
  "type": "Feature",
  "properties": {
    "addr:full":"240 Hills Beach Rd Biddeford ME 04005",
    "addr:housenumber":"240",
    "addr:postcode":"04005",
    "addr:street":"Hills Beach Rd",
    "iso:country":"US",
    "sg:address":"240 Hills Beach Rd",
    "sg:city":"Biddeford",
    "sg:classifiers":[
        {
            "category":"Building & Trades",
            "subcategory":"Plumbing",
            "type":"Services"
        }
    ],
    "sg:phone":"+1 207 283 1112",
    "sg:postcode":"04005",
    "sg:province":"ME",
    "sg:tags":[
        "plumbing",
        "contractor"
    ],
    "wof:name":"Apex Plumbing Heating & Gas",
    "wof:placetype":"venue"
},
  "geometry": {"coordinates":[-70.357372,43.448045],"type":"Point"}
}