{
  "type": "Feature",
  "properties": {
    "addr:full":"2 Stephen King Dr Augusta ME 04330",
    "addr:housenumber":"2",
    "addr:postcode":"04330",
    "addr:street":"Stephen King Dr",
    "iso:country":"US",
    "sg:address":"2 Stephen King Dr",
    "sg:city":"Augusta",
    "sg:classifiers":[
        {
            "category":"Wholesale",
            "subcategory":"Groceries",
            "type":"Manufacturing & Wholesale Goods"
        }
    ],
    "sg:phone":"+1 207 622 5127",
    "sg:postcode":"04330",
    "sg:province":"ME",
    "sg:tags":[
        "food",
        "product",
        "health"
    ],
    "sg:website":"www.gnc.com",
    "wof:name":"General Nutrition Ctr",
    "wof:placetype":"venue"
},
  "geometry": {"coordinates":[-69.787599,44.343317],"type":"Point"}
}