{
  "type": "Feature",
  "properties": {
    "addr:full":"10 Grove St Norway ME 04268",
    "addr:housenumber":"10",
    "addr:postcode":"04268",
    "addr:street":"Grove St",
    "iso:country":"US",
    "sg:address":"10 Grove St",
    "sg:city":"Norway",
    "sg:classifiers":[
        {
            "category":"Organizations",
            "subcategory":"Religious Organization",
            "type":"Services"
        }
    ],
    "sg:phone":"+1 207 743 8172",
    "sg:postcode":"04268",
    "sg:province":"ME",
    "wof:name":"Church of Nazarene Inc",
    "wof:placetype":"venue"
},
  "geometry": {"coordinates":[-70.5301,44.208658],"type":"Point"}
}