{
  "type": "Feature",
  "properties": {
    "addr:full":"1070 US Hwy 1 York ME 03909",
    "addr:housenumber":"1070",
    "addr:postcode":"03909",
    "addr:street":"Us Hwy 1",
    "iso:country":"US",
    "sg:address":"1070 US Hwy 1",
    "sg:city":"York",
    "sg:classifiers":[
        {
            "category":"Manufacturing",
            "subcategory":"Printing",
            "type":"Manufacturing & Wholesale Goods"
        }
    ],
    "sg:phone":"+1 207 363 9363",
    "sg:postcode":"03909",
    "sg:province":"ME",
    "sg:tags":[
        "screen"
    ],
    "wof:name":"Bullshirt Screen Printing",
    "wof:placetype":"venue"
},
  "geometry": {"coordinates":[-70.621317,43.187364],"type":"Point"}
}