{
  "type": "Feature",
  "properties": {
    "addr:full":"131 Main St Bangor ME 04401",
    "addr:housenumber":"131",
    "addr:postcode":"04401",
    "addr:street":"Main St",
    "iso:country":"US",
    "sg:address":"131 Main St",
    "sg:city":"Bangor",
    "sg:classifiers":[
        {
            "category":"Arts & Performance",
            "subcategory":"Theater",
            "type":"Entertainment"
        }
    ],
    "sg:phone":"+1 207 942 3333",
    "sg:postcode":"04401",
    "sg:province":"ME",
    "wof:name":"Maine Shakespeare Feastival",
    "wof:placetype":"venue"
},
  "geometry": {"coordinates":[-68.772655,44.799055],"type":"Point"}
}