{
  "type": "Feature",
  "properties": {
    "addr:full":"1693 Bennoch Rd Old Town ME 04468",
    "addr:housenumber":"1693",
    "addr:postcode":"04468",
    "addr:street":"Bennoch Rd",
    "iso:country":"US",
    "sg:address":"1693 Bennoch Rd",
    "sg:city":"Old Town",
    "sg:classifiers":[
        {
            "category":"Building & Trades",
            "subcategory":"Construction",
            "type":"Services"
        }
    ],
    "sg:phone":"+1 207 745 5463",
    "sg:postcode":"04468",
    "sg:province":"ME",
    "sg:tags":[
        "paving",
        "contractor"
    ],
    "wof:name":"Maine Sealcoating",
    "wof:placetype":"venue"
},
  "geometry": {"coordinates":[-68.694917,44.986618],"type":"Point"}
}