{
  "type": "Feature",
  "properties": {
    "iso:country":"US",
    "sg:address":"223 Sugar Hill Rd",
    "sg:city":"Harmony",
    "sg:classifiers":[
        {
            "category":"Manufacturing",
            "subcategory":"Printing",
            "type":"Manufacturing & Wholesale Goods"
        }
    ],
    "sg:phone":"+1 207 683 2959",
    "sg:postcode":"04942",
    "sg:province":"ME",
    "sg:tags":[
        "publisher"
    ],
    "sg:website":"www.smallarms.com",
    "wof:name":"Mooselake Publishing",
    "wof:placetype":"venue"
},
  "geometry": {"coordinates":[-69.499986,45.021008],"type":"Point"}
}