{
  "type": "Feature",
  "properties": {
    "addr:full":"162 Haskell Rd Bangor ME 04401",
    "addr:housenumber":"162",
    "addr:postcode":"04401",
    "addr:street":"Haskell Rd",
    "iso:country":"US",
    "sg:address":"162 Haskell Rd",
    "sg:city":"Bangor",
    "sg:classifiers":[
        {
            "category":"Autos & Motor Vehicles",
            "subcategory":"Automobile Sales",
            "type":"Retail Goods"
        }
    ],
    "sg:phone":"+1 207 947 0097",
    "sg:postcode":"04401",
    "sg:province":"ME",
    "sg:tags":[
        "car",
        "dealer"
    ],
    "wof:name":"Quirk Hyundai",
    "wof:placetype":"venue"
},
  "geometry": {"coordinates":[-68.739619,44.828921],"type":"Point"}
}