{
  "type": "Feature",
  "properties": {
    "addr:full":"64 Swetts Bridge Rd Alfred ME 04002",
    "addr:housenumber":"64",
    "addr:postcode":"04002",
    "addr:street":"Swetts Bridge Rd",
    "iso:country":"US",
    "sg:address":"64 Swetts Bridge Rd",
    "sg:city":"Alfred",
    "sg:classifiers":[
        {
            "category":"Manufacturing",
            "subcategory":"Motor Vehicles & Parts",
            "type":"Manufacturing & Wholesale Goods"
        }
    ],
    "sg:phone":"+1 207 324 2245",
    "sg:postcode":"04002",
    "sg:province":"ME",
    "sg:tags":[
        "automobile",
        "wrecker"
    ],
    "wof:name":"Daney's Auto Salvage",
    "wof:placetype":"venue"
},
  "geometry": {"coordinates":[-70.71776,43.457122],"type":"Point"}
}