{
  "type": "Feature",
  "properties": {
    "iso:country":"US",
    "sg:address":"3 Madison St",
    "sg:city":"Eastport",
    "sg:classifiers":[
        {
            "category":"Government",
            "subcategory":"Office",
            "type":"Public Place"
        }
    ],
    "sg:phone":"+1 207 853 4614",
    "sg:postcode":"04631",
    "sg:province":"ME",
    "sg:tags":[
        "city",
        "program"
    ],
    "wof:name":"Port Authority",
    "wof:placetype":"venue"
},
  "geometry": {"coordinates":[-66.984247,44.907956],"type":"Point"}
}