{
  "type": "Feature",
  "properties": {
    "iso:country":"US",
    "sg:address":"105 Mount Auburn Ave",
    "sg:city":"Auburn",
    "sg:classifiers":[
        {
            "category":"Utilities",
            "subcategory":"Mobile Phone",
            "type":"Services"
        }
    ],
    "sg:phone":"+1 207 557 2211",
    "sg:postcode":"04210",
    "sg:province":"ME",
    "sg:tags":[
        "telephone",
        "cellular"
    ],
    "wof:name":"US Cellular",
    "wof:placetype":"venue"
},
  "geometry": {"coordinates":[-70.24205000000001,44.122659],"type":"Point"}
}