{
  "type": "Feature",
  "properties": {
    "iso:country":"US",
    "sg:address":"70 Clover Ln",
    "sg:city":"Turner",
    "sg:classifiers":[
        {
            "category":"Retail",
            "subcategory":"Laundry & Dry Cleaning",
            "type":"Services"
        }
    ],
    "sg:phone":"+1 207 225 3345",
    "sg:postcode":"04210",
    "sg:province":"ME",
    "sg:tags":[
        "cleaners",
        "rug",
        "carpet"
    ],
    "wof:name":"Labbe's Carpet Care",
    "wof:placetype":"venue"
},
  "geometry": {"coordinates":[-70.261912,44.09408],"type":"Point"}
}