{
  "type": "Feature",
  "properties": {
    "iso:country":"US",
    "sg:address":"160 Veranda St",
    "sg:city":"Portland",
    "sg:classifiers":[
        {
            "category":"Recreation",
            "type":"Entertainment"
        }
    ],
    "sg:phone":"+1 207 775 3866",
    "sg:postcode":"04103",
    "sg:province":"ME",
    "sg:tags":[
        "martial",
        "arts",
        "instruction"
    ],
    "wof:name":"Jujitsu Judo Training Ctr",
    "wof:placetype":"venue"
},
  "geometry": {"coordinates":[-70.25278400000001,43.685364],"type":"Point"}
}