{
  "type": "Feature",
  "properties": {
    "addr:full":"2 Merrill Rd Westbrook ME 04092",
    "addr:housenumber":"2",
    "addr:postcode":"04092",
    "addr:street":"Merrill Rd",
    "iso:country":"US",
    "sg:address":"2 Merrill Rd",
    "sg:city":"Westbrook",
    "sg:classifiers":[
        {
            "category":"Professional",
            "subcategory":"Secretarial Services",
            "type":"Services"
        }
    ],
    "sg:phone":"+1 207 854 2721",
    "sg:postcode":"04092",
    "sg:province":"ME",
    "sg:tags":[
        "convention",
        "court",
        "reporter"
    ],
    "wof:name":"Duvernay Reporting",
    "wof:placetype":"venue"
},
  "geometry": {"coordinates":[-70.364041,43.739053],"type":"Point"}
}