{
  "type": "Feature",
  "properties": {
    "addr:full":"130 Spiller Rd Gorham ME 04038",
    "addr:housenumber":"130",
    "addr:postcode":"04038",
    "addr:street":"Spiller Rd",
    "iso:country":"US",
    "sg:address":"130 Spiller Rd",
    "sg:city":"Gorham",
    "sg:classifiers":[
        {
            "category":"Building & Trades",
            "subcategory":"Construction",
            "type":"Services"
        }
    ],
    "sg:phone":"+1 207 839 4027",
    "sg:postcode":"04038",
    "sg:province":"ME",
    "sg:tags":[
        "general",
        "contractor"
    ],
    "wof:name":"Gorham Ground Works",
    "wof:placetype":"venue"
},
  "geometry": {"coordinates":[-70.500152,43.726336],"type":"Point"}
}