{
  "type": "Feature",
  "properties": {
    "addr:full":"14 Airport Rd Waterville ME 04901",
    "addr:housenumber":"14",
    "addr:postcode":"04901",
    "addr:street":"Airport Rd",
    "iso:country":"US",
    "sg:address":"14 Airport Rd",
    "sg:city":"Waterville",
    "sg:classifiers":[
        {
            "category":"Recreation",
            "subcategory":"Amusement Park",
            "type":"Entertainment"
        }
    ],
    "sg:phone":"+1 207 877 7665",
    "sg:postcode":"04901",
    "sg:province":"ME",
    "wof:name":"T J's Classic Billiards",
    "wof:placetype":"venue"
},
  "geometry": {"coordinates":[-69.674198,44.543416],"type":"Point"}
}