{
  "type": "Feature",
  "properties": {
    "iso:country":"US",
    "sg:address":"2 Old Brunswick Rd",
    "sg:city":"Bath",
    "sg:classifiers":[
        {
            "category":"Social Services",
            "type":"Services"
        }
    ],
    "sg:phone":"+1 207 442 0181",
    "sg:postcode":"04530",
    "sg:province":"ME",
    "sg:tags":[
        "organization",
        "welfare"
    ],
    "wof:name":"Volunteers-America N New Engld",
    "wof:placetype":"venue"
},
  "geometry": {"coordinates":[-69.829448,43.920207],"type":"Point"}
}