{
  "type": "Feature",
  "properties": {
    "addr:full":"425 Fore St Portland ME 04101",
    "addr:housenumber":"425",
    "addr:postcode":"04101",
    "addr:street":"Fore St",
    "iso:country":"US",
    "sg:address":"425 Fore St",
    "sg:city":"Portland",
    "sg:classifiers":[
        {
            "category":"Restaurant",
            "type":"Food & Drink"
        }
    ],
    "sg:phone":"+1 207 773 3222",
    "sg:postcode":"04101",
    "sg:province":"ME",
    "sg:tags":[
        "parlor",
        "ice",
        "cream"
    ],
    "wof:name":"Ben & Jerry's",
    "wof:placetype":"venue"
},
  "geometry": {"coordinates":[-70.254746,43.655948],"type":"Point"}
}