{
  "type": "Feature",
  "properties": {
    "iso:country":"US",
    "sg:address":"28 Washington St",
    "sg:city":"Pittsfield",
    "sg:classifiers":[
        {
            "category":"Personal",
            "subcategory":"Beauty Salon",
            "type":"Services"
        }
    ],
    "sg:phone":"+1 207 487 5591",
    "sg:postcode":"04967",
    "sg:province":"ME",
    "sg:tags":[
        "shop"
    ],
    "wof:name":"Holly's Place",
    "wof:placetype":"venue"
},
  "geometry": {"coordinates":[-69.379167,44.787885],"type":"Point"}
}