{
  "type": "Feature",
  "properties": {
    "addr:full":"1093 Ridge Rd Windsor ME 04008",
    "addr:housenumber":"1093",
    "addr:postcode":"04008",
    "addr:street":"Ridge Rd",
    "iso:country":"US",
    "sg:address":"1093 Ridge Rd",
    "sg:city":"Windsor",
    "sg:classifiers":[
        {
            "category":"Professional",
            "subcategory":"Detective & Security Services",
            "type":"Services"
        }
    ],
    "sg:phone":"+1 207 445 2228",
    "sg:postcode":"04008",
    "sg:province":"ME",
    "sg:tags":[
        "system"
    ],
    "wof:name":"Netco Inc",
    "wof:placetype":"venue"
},
  "geometry": {"coordinates":[-69.875919,44.070004],"type":"Point"}
}