{
  "type": "Feature",
  "properties": {
    "iso:country":"US",
    "sg:address":"110 Hildreth St",
    "sg:city":"Bangor",
    "sg:classifiers":[
        {
            "category":"Autos & Motor Vehicles",
            "subcategory":"Boat Sales",
            "type":"Retail Goods"
        }
    ],
    "sg:phone":"+1 207 947 4800",
    "sg:postcode":"04401",
    "sg:province":"ME",
    "sg:tags":[
        "canoe"
    ],
    "wof:name":"Old Town Canoe",
    "wof:placetype":"venue"
},
  "geometry": {"coordinates":[-68.836514,44.789735],"type":"Point"}
}