{
  "type": "Feature",
  "properties": {
    "iso:country":"US",
    "sg:address":"14 Winslow St",
    "sg:city":"Sanford",
    "sg:classifiers":[
        {
            "category":"Building & Trades",
            "subcategory":"Construction",
            "type":"Services"
        }
    ],
    "sg:phone":"+1 207 651 1757",
    "sg:postcode":"04073",
    "sg:province":"ME",
    "sg:tags":[
        "residential"
    ],
    "wof:name":"From Ground Up",
    "wof:placetype":"venue"
},
  "geometry": {"coordinates":[-70.77230900000001,43.431366],"type":"Point"}
}