{
  "type": "Feature",
  "properties": {
    "iso:country":"US",
    "sg:address":"189 Alfred St",
    "sg:city":"Biddeford",
    "sg:classifiers":[
        {
            "category":"Professional",
            "subcategory":"Management & Consulting",
            "type":"Services"
        }
    ],
    "sg:phone":"+1 207 283 2954",
    "sg:postcode":"04005",
    "sg:province":"ME",
    "sg:tags":[
        "business"
    ],
    "wof:name":"Literacy Volunteers America",
    "wof:placetype":"venue"
},
  "geometry": {"coordinates":[-70.460124,43.487847],"type":"Point"}
}