{
  "type": "Feature",
  "properties": {
    "addr:full":"501 Cottage Rd South Portland ME 04106",
    "addr:housenumber":"501",
    "addr:postcode":"04106",
    "addr:street":"Cottage Rd",
    "iso:country":"US",
    "sg:address":"501 Cottage Rd",
    "sg:city":"South Portland",
    "sg:classifiers":[
        {
            "category":"Ice Cream",
            "type":"Food & Drink"
        }
    ],
    "sg:menulink":"http://www.allmenus.com/me/south-portland/224866-dels-frozen-lemonade/menu/",
    "sg:postcode":"04106",
    "sg:province":"ME",
    "sg:tags":[
        "smoothy",
        "juice",
        "american"
    ],
    "wof:name":"Del's Frozen Lemonade",
    "wof:placetype":"venue"
},
  "geometry": {"coordinates":[-70.230011,43.634593],"type":"Point"}
}