{
  "type": "Feature",
  "properties": {
    "iso:country":"US",
    "sg:address":"321 Gray Rd",
    "sg:city":"Falmouth",
    "sg:classifiers":[
        {
            "category":"Freight",
            "type":"Transportation"
        }
    ],
    "sg:phone":"+1 207 878 8718",
    "sg:postcode":"04105",
    "sg:province":"ME",
    "sg:tags":[
        "operator",
        "local",
        "trucking"
    ],
    "wof:name":"J B Macmaster Truck Lines",
    "wof:placetype":"venue"
},
  "geometry": {"coordinates":[-70.300719,43.76831],"type":"Point"}
}