{
  "type": "Feature",
  "properties": {
    "iso:country":"US",
    "sg:address":"56 Plains Rd",
    "sg:city":"Litchfield",
    "sg:classifiers":[
        {
            "category":"Organizations",
            "subcategory":"Religious Organization",
            "type":"Services"
        }
    ],
    "sg:phone":"+1 207 268 4794",
    "sg:postcode":"04355",
    "sg:province":"ME",
    "sg:tags":[
        "church"
    ],
    "wof:name":"Litchfield Plains Baptist Chr",
    "wof:placetype":"venue"
},
  "geometry": {"coordinates":[-69.911531,44.362345],"type":"Point"}
}