{
  "type": "Feature",
  "properties": {
    "iso:country":"US",
    "sg:address":"15 W Lebanon Rd",
    "sg:city":"East Lebanon",
    "sg:classifiers":[
        {
            "category":"Building & Trades",
            "subcategory":"Construction",
            "type":"Services"
        }
    ],
    "sg:phone":"+1 207 457 1565",
    "sg:postcode":"04027",
    "sg:province":"ME",
    "sg:tags":[
        "house"
    ],
    "wof:name":"Jh Millette & Son Builders",
    "wof:placetype":"venue"
},
  "geometry": {"coordinates":[-70.941267,43.37407],"type":"Point"}
}