{
  "type": "Feature",
  "properties": {
    "iso:country":"US",
    "sg:address":"251 Kennedy Memorial Dr",
    "sg:city":"Waterville",
    "sg:classifiers":[
        {
            "category":"Home & Garden",
            "subcategory":"Home Furnishings",
            "type":"Retail Goods"
        }
    ],
    "sg:phone":"+1 207 872 5634",
    "sg:postcode":"04901",
    "sg:province":"ME",
    "sg:tags":[
        "curtain",
        "made",
        "drapery"
    ],
    "wof:name":"Curtainshop",
    "wof:placetype":"venue"
},
  "geometry": {"coordinates":[-69.668828,44.543848],"type":"Point"}
}