{
  "type": "Feature",
  "properties": {
    "iso:country":"US",
    "sg:address":"134 Centre St",
    "sg:city":"Bath",
    "sg:classifiers":[
        {
            "category":"Personal",
            "type":"Services"
        }
    ],
    "sg:phone":"+1 207 841 9601",
    "sg:postcode":"04530",
    "sg:province":"ME",
    "sg:tags":[
        "therapist",
        "massage"
    ],
    "wof:name":"Sue Redwine",
    "wof:placetype":"venue"
},
  "geometry": {"coordinates":[-69.81862099999999,43.911851],"type":"Point"}
}