{
  "type": "Feature",
  "properties": {
    "addr:full":"18 Therrien Ave Saco ME 04072",
    "addr:housenumber":"18",
    "addr:postcode":"04072",
    "addr:street":"Therrien Ave",
    "iso:country":"US",
    "sg:address":"18 Therrien Ave",
    "sg:city":"Saco",
    "sg:classifiers":[
        {
            "category":"Professional",
            "subcategory":"Management & Consulting",
            "type":"Services"
        }
    ],
    "sg:phone":"+1 207 284 0100",
    "sg:postcode":"04072",
    "sg:province":"ME",
    "sg:tags":[
        "food"
    ],
    "wof:name":"First Class Catering Svc",
    "wof:placetype":"venue"
},
  "geometry": {"coordinates":[-70.447158,43.511265],"type":"Point"}
}