{
  "type": "Feature",
  "properties": {
    "iso:country":"US",
    "sg:address":"41 Village St",
    "sg:city":"Lisbon",
    "sg:classifiers":[
        {
            "category":"Government",
            "subcategory":"Office",
            "type":"Public Place"
        }
    ],
    "sg:phone":"+1 207 353 2821",
    "sg:postcode":"04250",
    "sg:province":"ME",
    "sg:tags":[
        "village"
    ],
    "wof:name":"E T Smith Hose Co",
    "wof:placetype":"venue"
},
  "geometry": {"coordinates":[-70.106343,44.029709],"type":"Point"}
}