{
  "type": "Feature",
  "properties": {
    "addr:full":"960 Ocean Ave Portland ME 04103",
    "addr:housenumber":"960",
    "addr:postcode":"04103",
    "addr:street":"Ocean Ave",
    "iso:country":"US",
    "sg:address":"960 Ocean Ave",
    "sg:city":"Portland",
    "sg:classifiers":[
        {
            "category":"Home & Garden",
            "subcategory":"Building Materials",
            "type":"Retail Goods"
        }
    ],
    "sg:phone":"+1 207 879 2328",
    "sg:postcode":"04103",
    "sg:province":"ME",
    "sg:tags":[
        "mixed",
        "concrete"
    ],
    "wof:name":"Dragon Products Co Inc",
    "wof:placetype":"venue"
},
  "geometry": {"coordinates":[-70.260525,43.697432],"type":"Point"}
}