{
  "type": "Feature",
  "properties": {
    "addr:full":"23 Water St Newport ME 04953",
    "addr:housenumber":"23",
    "addr:postcode":"04953",
    "addr:street":"Water St",
    "iso:country":"US",
    "sg:address":"23 Water St",
    "sg:city":"Newport",
    "sg:classifiers":[
        {
            "category":"Government",
            "subcategory":"Office",
            "type":"Public Place"
        }
    ],
    "sg:phone":"+1 207 368 5077",
    "sg:postcode":"04953",
    "sg:province":"ME",
    "sg:tags":[
        "village"
    ],
    "wof:name":"Newport Transfer Station",
    "wof:placetype":"venue"
},
  "geometry": {"coordinates":[-69.273832,44.835848],"type":"Point"}
}