{
  "type": "Feature",
  "properties": {
    "addr:full":"21 Elm St Camden ME 04843",
    "addr:housenumber":"21",
    "addr:postcode":"04843",
    "addr:street":"Elm St",
    "iso:country":"US",
    "sg:address":"21 Elm St",
    "sg:city":"Camden",
    "sg:classifiers":[
        {
            "category":"Professional",
            "subcategory":"Computer Services",
            "type":"Services"
        }
    ],
    "sg:phone":"+1 207 236 8468",
    "sg:postcode":"04843",
    "sg:province":"ME",
    "sg:tags":[
        "internet"
    ],
    "sg:website":"www.villagetech.com",
    "wof:name":"VILLAGESOUP.COM",
    "wof:placetype":"venue"
},
  "geometry": {"coordinates":[-69.06651599999999,44.208468],"type":"Point"}
}