{
  "type": "Feature",
  "properties": {
    "addr:full":"166 Camden St Rockland ME 04841",
    "addr:housenumber":"166",
    "addr:postcode":"04841",
    "addr:street":"Camden St",
    "iso:country":"US",
    "sg:address":"166 Camden St",
    "sg:city":"Rockland",
    "sg:classifiers":[
        {
            "category":"Restaurant",
            "type":"Food & Drink"
        }
    ],
    "sg:phone":"+1 207 594 0038",
    "sg:postcode":"04841",
    "sg:province":"ME",
    "wof:name":"Wendy's",
    "wof:placetype":"venue"
},
  "geometry": {"coordinates":[-69.10054599999999,44.121708],"type":"Point"}
}