{
  "type": "Feature",
  "properties": {
    "iso:country":"US",
    "sg:address":"390 Brunswick Ave",
    "sg:city":"Gardiner",
    "sg:classifiers":[
        {
            "category":"Restaurant",
            "type":"Food & Drink"
        }
    ],
    "sg:phone":"+1 207 588 0022",
    "sg:postcode":"04345",
    "sg:province":"ME",
    "wof:name":"Dave's Diner",
    "wof:placetype":"venue"
},
  "geometry": {"coordinates":[-69.786181,44.209644],"type":"Point"}
}