{
  "type": "Feature",
  "properties": {
    "addr:full":"136 US Hwy 1 Scarborough ME 04074",
    "addr:housenumber":"136",
    "addr:postcode":"04074",
    "addr:street":"Us Hwy 1",
    "iso:country":"US",
    "sg:address":"136 US Hwy 1",
    "sg:city":"Scarborough",
    "sg:classifiers":[
        {
            "category":"Organizations",
            "subcategory":"Non-profit Organization",
            "type":"Services"
        }
    ],
    "sg:phone":"+1 207 396 6500",
    "sg:postcode":"04074",
    "sg:province":"ME",
    "sg:website":"www.seniorinfolink.org",
    "wof:name":"Southern Maine Agency-Aging",
    "wof:placetype":"venue"
},
  "geometry": {"coordinates":[-70.32403100000001,43.597207],"type":"Point"}
}