{
  "type": "Feature",
  "properties": {
    "addr:full":"73 Reynolds Rd Unity ME 04921",
    "addr:housenumber":"73",
    "addr:postcode":"04921",
    "addr:street":"Reynolds Rd",
    "iso:country":"US",
    "sg:address":"73 Reynolds Rd",
    "sg:city":"Unity",
    "sg:classifiers":[
        {
            "category":"Professional",
            "subcategory":"Business Services",
            "type":"Services"
        }
    ],
    "sg:phone":"+1 207 948 3071",
    "sg:postcode":"04921",
    "sg:province":"ME",
    "wof:name":"Hawkridge Compost Facility",
    "wof:placetype":"venue"
},
  "geometry": {"coordinates":[-69.129713,44.543216],"type":"Point"}
}