{
  "type": "Feature",
  "properties": {
    "iso:country":"US",
    "sg:address":"149 Front St",
    "sg:city":"Bath",
    "sg:classifiers":[
        {
            "category":"Professional",
            "type":"Services"
        }
    ],
    "sg:phone":"+1 207 442 8088",
    "sg:postcode":"04530",
    "sg:province":"ME",
    "sg:tags":[
        "establishment"
    ],
    "wof:name":"Logicon Syscon Corp",
    "wof:placetype":"venue"
},
  "geometry": {"coordinates":[-69.814204,43.914231],"type":"Point"}
}