{
  "type": "Feature",
  "properties": {
    "iso:country":"US",
    "sg:address":"633 Gardiner Rd",
    "sg:city":"Dresden",
    "sg:classifiers":[
        {
            "category":"Organizations",
            "subcategory":"Religious Organization",
            "type":"Services"
        }
    ],
    "sg:phone":"+1 207 737 8578",
    "sg:postcode":"04342",
    "sg:province":"ME",
    "sg:tags":[
        "church"
    ],
    "wof:name":"Dresden Community Church",
    "wof:placetype":"venue"
},
  "geometry": {"coordinates":[-69.72910400000001,44.110778],"type":"Point"}
}