{
  "type": "Feature",
  "properties": {
    "iso:country":"US",
    "sg:address":"126 Rockland Ave",
    "sg:city":"Portland",
    "sg:classifiers":[
        {
            "category":"Shopping",
            "subcategory":"Department Store",
            "type":"Retail Goods"
        }
    ],
    "sg:phone":"+1 207 773 6367",
    "sg:postcode":"04102",
    "sg:province":"ME",
    "wof:name":"Donna M Somma",
    "wof:placetype":"venue"
},
  "geometry": {"coordinates":[-70.30398,43.667454],"type":"Point"}
}