{
  "type": "Feature",
  "properties": {
    "addr:full":"117 Pond Rd South Berwick ME 03908",
    "addr:housenumber":"117",
    "addr:postcode":"03908",
    "addr:street":"Pond Rd",
    "iso:country":"US",
    "sg:address":"117 Pond Rd",
    "sg:city":"South Berwick",
    "sg:classifiers":[
        {
            "category":"Restaurant",
            "type":"Food & Drink"
        }
    ],
    "sg:menulink":"http://www.allmenus.com/me/south-berwick/236761-the-lodge-restaurant-at-spring-hill/menu/",
    "sg:phone":"+1 207 384 2693",
    "sg:postcode":"03908",
    "sg:province":"ME",
    "sg:tags":[
        "american"
    ],
    "wof:name":"The Lodge Restaurant At Spring Hill",
    "wof:placetype":"venue"
},
  "geometry": {"coordinates":[-70.769773,43.252988],"type":"Point"}
}