{
  "type": "Feature",
  "properties": {
    "addr:full":"16 Spring St Kennebunkport ME 04046",
    "addr:housenumber":"16",
    "addr:postcode":"04046",
    "addr:street":"Spring St",
    "iso:country":"US",
    "sg:address":"16 Spring St",
    "sg:city":"Kennebunkport",
    "sg:classifiers":[
        {
            "category":"Restaurant",
            "type":"Food & Drink"
        }
    ],
    "sg:phone":"+1 207 967 5115",
    "sg:postcode":"04046",
    "sg:province":"ME",
    "wof:name":"Eatz",
    "wof:placetype":"venue"
},
  "geometry": {"coordinates":[-70.47669999999999,43.361599],"type":"Point"}
}