{
  "type": "Feature",
  "properties": {
    "addr:full":"325 Kennedy Memorial Dr Waterville ME 04901",
    "addr:housenumber":"325",
    "addr:postcode":"04901",
    "addr:street":"Kennedy Memorial Dr",
    "iso:country":"US",
    "sg:address":"325 Kennedy Memorial Dr",
    "sg:city":"Waterville",
    "sg:classifiers":[
        {
            "category":"Shopping",
            "type":"Retail Goods"
        }
    ],
    "sg:phone":"+1 207 873 7191",
    "sg:postcode":"04901",
    "sg:province":"ME",
    "sg:tags":[
        "hearing",
        "equipment",
        "supply",
        "impaired"
    ],
    "wof:name":"Audiology & Hearing Aid Svc",
    "wof:placetype":"venue"
},
  "geometry": {"coordinates":[-69.674065,44.544578],"type":"Point"}
}