{
  "type": "Feature",
  "properties": {
    "iso:country":"US",
    "sg:address":"395 N Main St",
    "sg:city":"Brewer",
    "sg:classifiers":[
        {
            "category":"Shopping",
            "subcategory":"Department Store",
            "type":"Retail Goods"
        }
    ],
    "sg:phone":"+1 207 989 5682",
    "sg:postcode":"04412",
    "sg:province":"ME",
    "sg:tags":[
        "shop"
    ],
    "wof:name":"Bob's Discount Inc",
    "wof:placetype":"venue"
},
  "geometry": {"coordinates":[-68.75447,44.800261],"type":"Point"}
}