{
  "type": "Feature",
  "properties": {
    "addr:full":"765 Webster St Lewiston ME 04240",
    "addr:housenumber":"765",
    "addr:postcode":"04240",
    "addr:street":"Webster St",
    "iso:country":"US",
    "sg:address":"765 Webster St",
    "sg:city":"Lewiston",
    "sg:classifiers":[
        {
            "category":"Manufacturing",
            "subcategory":"Rubber & Plastics",
            "type":"Manufacturing & Wholesale Goods"
        }
    ],
    "sg:phone":"+1 207 784 3547",
    "sg:postcode":"04240",
    "sg:province":"ME",
    "sg:tags":[
        "product"
    ],
    "sg:website":"www.jvmaine.com",
    "wof:name":"Jones & Vining Of Maine Inc",
    "wof:placetype":"venue"
},
  "geometry": {"coordinates":[-70.17072400000001,44.082264],"type":"Point"}
}