{
  "type": "Feature",
  "properties": {
    "addr:full":"51 Dow Hwy Eliot ME 03903",
    "addr:housenumber":"51",
    "addr:postcode":"03903",
    "addr:street":"Dow Hwy",
    "iso:country":"US",
    "sg:address":"51 Dow Hwy",
    "sg:city":"Eliot",
    "sg:classifiers":[
        {
            "category":"Restaurant",
            "type":"Food & Drink"
        }
    ],
    "sg:phone":"+1 207 439 2555",
    "sg:postcode":"03903",
    "sg:province":"ME",
    "wof:name":"Pizza Market",
    "wof:placetype":"venue"
},
  "geometry": {"coordinates":[-70.80538900000001,43.165066],"type":"Point"}
}