{
  "type": "Feature",
  "properties": {
    "addr:full":"80 Airport Rd Waterville ME 04901",
    "addr:housenumber":"80",
    "addr:postcode":"04901",
    "addr:street":"Airport Rd",
    "iso:country":"US",
    "sg:address":"80 Airport Rd",
    "sg:city":"Waterville",
    "sg:classifiers":[
        {
            "category":"Local Transit",
            "type":"Transportation"
        }
    ],
    "sg:phone":"+1 207 872 5000",
    "sg:postcode":"04901",
    "sg:province":"ME",
    "sg:tags":[
        "bus",
        "line"
    ],
    "wof:name":"Vermont Transit Lines",
    "wof:placetype":"venue"
},
  "geometry": {"coordinates":[-69.675229,44.539001],"type":"Point"}
}