{
  "type": "Feature",
  "properties": {
    "iso:country":"US",
    "sg:address":"15 Old Logging Rd",
    "sg:city":"York",
    "sg:classifiers":[
        {
            "category":"Retail",
            "subcategory":"Auto Repair",
            "type":"Services"
        }
    ],
    "sg:phone":"+1 207 351 1061",
    "sg:postcode":"03906",
    "sg:province":"ME",
    "sg:tags":[
        "repairing",
        "automobile"
    ],
    "wof:name":"Bob's Automotive",
    "wof:placetype":"venue"
},
  "geometry": {"coordinates":[-70.767424,43.325012],"type":"Point"}
}