{
  "type": "Feature",
  "properties": {
    "iso:country":"US",
    "sg:address":"192 Northport Ave",
    "sg:city":"Belfast",
    "sg:classifiers":[
        {
            "category":"Travel",
            "subcategory":"Hotels & Motels",
            "type":"Entertainment"
        }
    ],
    "sg:phone":"+1 207 338 5715",
    "sg:postcode":"04915",
    "sg:province":"ME",
    "sg:tags":[
        "breakfast",
        "accommodation",
        "bed"
    ],
    "wof:name":"Belfast Bay Meadows Inn",
    "wof:placetype":"venue"
},
  "geometry": {"coordinates":[-68.989221,44.402757],"type":"Point"}
}