{
  "type": "Feature",
  "properties": {
    "iso:country":"US",
    "sg:address":"24 Mill Pond Rd",
    "sg:city":"Beals",
    "sg:classifiers":[
        {
            "category":"Education",
            "subcategory":"School",
            "type":"Public Place"
        }
    ],
    "sg:phone":"+1 207 497 5449",
    "sg:postcode":"04611",
    "sg:province":"ME",
    "wof:name":"Beals Elementary School",
    "wof:placetype":"venue"
},
  "geometry": {"coordinates":[-67.617558,44.516657],"type":"Point"}
}