{
  "type": "Feature",
  "properties": {
    "addr:full":"27 Pike St Biddeford ME 04005",
    "addr:housenumber":"27",
    "addr:postcode":"04005",
    "addr:street":"Pike St",
    "iso:country":"US",
    "sg:address":"27 Pike St",
    "sg:city":"Biddeford",
    "sg:classifiers":[
        {
            "category":"Building & Trades",
            "subcategory":"Construction",
            "type":"Services"
        }
    ],
    "sg:phone":"+1 207 286 9990",
    "sg:postcode":"04005",
    "sg:province":"ME",
    "sg:tags":[
        "general",
        "contractor"
    ],
    "wof:name":"B & M Contracting",
    "wof:placetype":"venue"
},
  "geometry": {"coordinates":[-70.448691,43.49061],"type":"Point"}
}