{
  "type": "Feature",
  "properties": {
    "iso:country":"US",
    "sg:address":"59 Mayville Rd",
    "sg:city":"Bethel",
    "sg:classifiers":[
        {
            "category":"Food & Beverages",
            "subcategory":"Groceries & Convenience Stores",
            "type":"Retail Goods"
        }
    ],
    "sg:phone":"+1 207 824 2000",
    "sg:postcode":"04217",
    "sg:province":"ME",
    "wof:name":"Big Apple",
    "wof:placetype":"venue"
},
  "geometry": {"coordinates":[-70.795848,44.413238],"type":"Point"}
}