{
  "type": "Feature",
  "properties": {
    "addr:full":"8 Western Ave Kennebunkport ME 04046",
    "addr:housenumber":"8",
    "addr:postcode":"04046",
    "addr:street":"Western Ave",
    "iso:country":"US",
    "sg:address":"8 Western Ave",
    "sg:city":"Kennebunkport",
    "sg:classifiers":[
        {
            "category":"Restaurant",
            "type":"Food & Drink"
        }
    ],
    "sg:phone":"+1 207 967 4322",
    "sg:postcode":"04046",
    "sg:province":"ME",
    "sg:website":"www.federaljacks.com",
    "wof:name":"Federal Jack's Brew Pub",
    "wof:placetype":"venue"
},
  "geometry": {"coordinates":[-70.479421,43.360474],"type":"Point"}
}