{
  "type": "Feature",
  "properties": {
    "iso:country":"US",
    "sg:address":"12 Morse Rd",
    "sg:city":"North Monmouth",
    "sg:classifiers":[
        {
            "category":"Retail",
            "subcategory":"Animal Services",
            "type":"Services"
        }
    ],
    "sg:phone":"+1 207 933 4062",
    "sg:postcode":"04265",
    "sg:province":"ME",
    "sg:tags":[
        "pet",
        "grooming",
        "washing"
    ],
    "wof:name":"Pet Boutique",
    "wof:placetype":"venue"
},
  "geometry": {"coordinates":[-70.032127,44.278336],"type":"Point"}
}