{
  "type": "Feature",
  "properties": {
    "iso:country":"US",
    "sg:address":"24 Leisure Ln",
    "sg:city":"Durham",
    "sg:classifiers":[
        {
            "category":"Travel",
            "subcategory":"Campground",
            "type":"Entertainment"
        }
    ],
    "sg:phone":"+1 207 353 4353",
    "sg:postcode":"04222",
    "sg:province":"ME",
    "wof:name":"Durham Leisure Ctr",
    "wof:placetype":"venue"
},
  "geometry": {"coordinates":[-70.10877000000001,43.938296],"type":"Point"}
}