{
  "type": "Feature",
  "properties": {
    "addr:full":"118 Verrill Rd Minot ME 04258",
    "addr:housenumber":"118",
    "addr:postcode":"04258",
    "addr:street":"Verrill Rd",
    "iso:country":"US",
    "sg:address":"118 Verrill Rd",
    "sg:city":"Minot",
    "sg:classifiers":[
        {
            "category":"Building & Trades",
            "subcategory":"Construction",
            "type":"Services"
        }
    ],
    "sg:phone":"+1 207 345 4791",
    "sg:postcode":"04258",
    "sg:province":"ME",
    "sg:tags":[
        "excavating",
        "contractor"
    ],
    "wof:name":"Peter Hemond Excavating Inc",
    "wof:placetype":"venue"
},
  "geometry": {"coordinates":[-70.34508599999999,44.116382],"type":"Point"}
}