{
  "type": "Feature",
  "properties": {
    "iso:country":"US",
    "sg:address":"507 Western Ave",
    "sg:city":"Augusta",
    "sg:classifiers":[
        {
            "category":"Personal",
            "subcategory":"Tanning Parlor",
            "type":"Services"
        }
    ],
    "sg:phone":"+1 207 622 4097",
    "sg:postcode":"04330",
    "sg:province":"ME",
    "sg:tags":[
        "salon"
    ],
    "wof:name":"Wicked Good Tanning",
    "wof:placetype":"venue"
},
  "geometry": {"coordinates":[-69.827181,44.320685],"type":"Point"}
}