{
  "type": "Feature",
  "properties": {
    "addr:full":"58 Brewster St Rockland ME 04841",
    "addr:housenumber":"58",
    "addr:postcode":"04841",
    "addr:street":"Brewster St",
    "iso:country":"US",
    "sg:address":"58 Brewster St",
    "sg:city":"Rockland",
    "sg:classifiers":[
        {
            "category":"Social Services",
            "type":"Services"
        }
    ],
    "sg:phone":"+1 207 594 4452",
    "sg:postcode":"04841",
    "sg:province":"ME",
    "sg:tags":[
        "counseling"
    ],
    "wof:name":"Home Counselors",
    "wof:placetype":"venue"
},
  "geometry": {"coordinates":[-69.10757,44.114388],"type":"Point"}
}