{
  "type": "Feature",
  "properties": {
    "addr:full":"222 Riverside St Portland ME 04103",
    "addr:housenumber":"222",
    "addr:postcode":"04103",
    "addr:street":"Riverside St",
    "iso:country":"US",
    "sg:address":"222 Riverside St",
    "sg:city":"Portland",
    "sg:classifiers":[
        {
            "category":"Wholesale",
            "subcategory":"Construction Materials",
            "type":"Manufacturing & Wholesale Goods"
        }
    ],
    "sg:phone":"+1 207 874 1995",
    "sg:postcode":"04103",
    "sg:province":"ME",
    "sg:tags":[
        "concrete",
        "product"
    ],
    "wof:name":"Madawaska Hardscape Products",
    "wof:placetype":"venue"
},
  "geometry": {"coordinates":[-70.328199,43.685824],"type":"Point"}
}