{
  "type": "Feature",
  "properties": {
    "addr:full":"31 Market St Fort Kent ME 04743",
    "addr:housenumber":"31",
    "addr:postcode":"04743",
    "addr:street":"Market St",
    "iso:country":"US",
    "sg:address":"31 Market St",
    "sg:city":"Fort Kent",
    "sg:classifiers":[
        {
            "category":"Retail",
            "subcategory":"Portrait Studio",
            "type":"Services"
        }
    ],
    "sg:phone":"+1 207 834 3983",
    "sg:postcode":"04743",
    "sg:province":"ME",
    "sg:tags":[
        "photographer"
    ],
    "wof:name":"Photography By Jalbert",
    "wof:placetype":"venue"
},
  "geometry": {"coordinates":[-68.584232,47.254906],"type":"Point"}
}