{
  "type": "Feature",
  "properties": {
    "addr:full":"21 Grand St South Portland ME 04106",
    "addr:housenumber":"21",
    "addr:postcode":"04106",
    "addr:street":"Grand St",
    "iso:country":"US",
    "sg:address":"21 Grand St",
    "sg:city":"South Portland",
    "sg:classifiers":[
        {
            "category":"Professional",
            "type":"Services"
        }
    ],
    "sg:phone":"+1 207 767 1600",
    "sg:postcode":"04106",
    "sg:province":"ME",
    "wof:name":"Rjs Property Services",
    "wof:placetype":"venue"
},
  "geometry": {"coordinates":[-70.23506,43.644248],"type":"Point"}
}