{
  "type": "Feature",
  "properties": {
    "iso:country":"US",
    "sg:address":"901 Main St",
    "sg:city":"Oxford",
    "sg:classifiers":[
        {
            "category":"Restaurant",
            "type":"Food & Drink"
        }
    ],
    "sg:phone":"+1 207 539 8100",
    "sg:postcode":"04270",
    "sg:province":"ME",
    "wof:name":"Viddles & Griddles Cafe",
    "wof:placetype":"venue"
},
  "geometry": {"coordinates":[-70.48951,44.154994],"type":"Point"}
}