{
  "type": "Feature",
  "properties": {
    "iso:country":"US",
    "sg:address":"15 Skiway Rd",
    "sg:city":"Bethel",
    "sg:classifiers":[
        {
            "category":"Real Estate",
            "subcategory":"Real Estate Agent",
            "type":"Services"
        }
    ],
    "sg:phone":"+1 207 824 5051",
    "sg:postcode":"04261",
    "sg:province":"ME",
    "wof:name":"Sunday River Real Estate",
    "wof:placetype":"venue"
},
  "geometry": {"coordinates":[-70.833224,44.472132],"type":"Point"}
}