{
  "type": "Feature",
  "properties": {
    "addr:full":"651 Riverside St Portland ME 04103",
    "addr:housenumber":"651",
    "addr:postcode":"04103",
    "addr:street":"Riverside St",
    "iso:country":"US",
    "sg:address":"651 Riverside St",
    "sg:city":"Portland",
    "sg:classifiers":[
        {
            "category":"Building & Trades",
            "subcategory":"Construction",
            "type":"Services"
        }
    ],
    "sg:phone":"+1 207 797 6899",
    "sg:postcode":"04103",
    "sg:province":"ME",
    "sg:tags":[
        "maker",
        "cabinet"
    ],
    "wof:name":"North Star Woodworking Inc",
    "wof:placetype":"venue"
},
  "geometry": {"coordinates":[-70.32491400000001,43.693828],"type":"Point"}
}