{
  "type": "Feature",
  "properties": {
    "addr:full":"99 Loop Rd Wells ME 04090",
    "addr:housenumber":"99",
    "addr:postcode":"04090",
    "addr:street":"Loop Rd",
    "iso:country":"US",
    "sg:address":"99 Loop Rd",
    "sg:city":"Wells",
    "sg:classifiers":[
        {
            "category":"Professional",
            "subcategory":"Computer Services",
            "type":"Services"
        }
    ],
    "sg:phone":"+1 207 646 6134",
    "sg:postcode":"04090",
    "sg:province":"ME",
    "sg:tags":[
        "administrator",
        "system"
    ],
    "wof:name":"Elizabeth Howarth",
    "wof:placetype":"venue"
},
  "geometry": {"coordinates":[-70.639943,43.293129],"type":"Point"}
}