{
  "type": "Feature",
  "properties": {
    "iso:country":"US",
    "sg:address":"10 Roundabout Ln",
    "sg:city":"Cape Elizabeth",
    "sg:classifiers":[
        {
            "category":"Shopping",
            "subcategory":"Computers & Home Electronics",
            "type":"Retail Goods"
        }
    ],
    "sg:phone":"+1 207 741 2835",
    "sg:postcode":"04107",
    "sg:province":"ME",
    "sg:tags":[
        "software"
    ],
    "wof:name":"D C Systems Inc",
    "wof:placetype":"venue"
},
  "geometry": {"coordinates":[-70.21019699999999,43.574842],"type":"Point"}
}