{
  "type": "Feature",
  "properties": {
    "iso:country":"US",
    "sg:address":"75 E Elm St",
    "sg:city":"Yarmouth",
    "sg:classifiers":[
        {
            "category":"Professional",
            "type":"Services"
        }
    ],
    "sg:phone":"+1 207 846 9690",
    "sg:postcode":"04096",
    "sg:province":"ME",
    "sg:tags":[
        "establishment"
    ],
    "wof:name":"Toller Co",
    "wof:placetype":"venue"
},
  "geometry": {"coordinates":[-70.19143200000001,43.806249],"type":"Point"}
}