{
  "type": "Feature",
  "properties": {
    "iso:country":"US",
    "sg:address":"45 Beechnut Ridge Ln",
    "sg:city":"Bowdoinham",
    "sg:classifiers":[
        {
            "category":"Professional",
            "subcategory":"Computer Services",
            "type":"Services"
        }
    ],
    "sg:phone":"+1 207 737 4517",
    "sg:postcode":"04008",
    "sg:province":"ME",
    "sg:tags":[
        "home",
        "consulting",
        "page",
        "dev",
        "internet"
    ],
    "wof:name":"ATF",
    "wof:placetype":"venue"
},
  "geometry": {"coordinates":[-69.888336,44.092986],"type":"Point"}
}