{
  "type": "Feature",
  "properties": {
    "iso:country":"US",
    "sg:address":"1 Bartlett Rd",
    "sg:city":"Kittery Point",
    "sg:classifiers":[
        {
            "category":"Professional",
            "subcategory":"Management & Consulting",
            "type":"Services"
        }
    ],
    "sg:phone":"+1 207 439 7866",
    "sg:postcode":"03905",
    "sg:province":"ME",
    "sg:tags":[
        "business"
    ],
    "wof:name":"Jom Consulting Inc",
    "wof:placetype":"venue"
},
  "geometry": {"coordinates":[-70.70493999999999,43.096697],"type":"Point"}
}