{
  "type": "Feature",
  "properties": {
    "iso:country":"US",
    "sg:address":"744 Lake Shore Rd",
    "sg:city":"St David",
    "sg:classifiers":[
        {
            "category":"Sports & Exercise",
            "subcategory":"Golf",
            "type":"Entertainment"
        }
    ],
    "sg:phone":"+1 207 895 6957",
    "sg:postcode":"04756",
    "sg:province":"ME",
    "sg:tags":[
        "course"
    ],
    "wof:name":"Birch Point Golf Club",
    "wof:placetype":"venue"
},
  "geometry": {"coordinates":[-68.247511,47.220197],"type":"Point"}
}