{
  "type": "Feature",
  "properties": {
    "addr:full":"672 Memorial Dr Winthrop ME 04364",
    "addr:housenumber":"672",
    "addr:postcode":"04364",
    "addr:street":"Memorial Dr",
    "iso:country":"US",
    "sg:address":"672 Memorial Dr",
    "sg:city":"Winthrop",
    "sg:classifiers":[
        {
            "category":"Social Services",
            "type":"Services"
        }
    ],
    "sg:phone":"+1 207 377 4914",
    "sg:postcode":"04364",
    "sg:province":"ME",
    "wof:name":"Gloria Giroux",
    "wof:placetype":"venue"
},
  "geometry": {"coordinates":[-69.945025,44.337534],"type":"Point"}
}