{
  "type": "Feature",
  "properties": {
    "iso:country":"US",
    "sg:address":"51 Lexington St",
    "sg:city":"Lewiston",
    "sg:classifiers":[
        {
            "category":"Home & Garden",
            "subcategory":"Building Materials",
            "type":"Retail Goods"
        }
    ],
    "sg:phone":"+1 207 777 6800",
    "sg:postcode":"04240",
    "sg:province":"ME",
    "sg:tags":[
        "roofing"
    ],
    "sg:website":"www.jm.com",
    "wof:name":"Johns Manville Corp",
    "wof:placetype":"venue"
},
  "geometry": {"coordinates":[-70.169176,44.077852],"type":"Point"}
}