{
  "type": "Feature",
  "properties": {
    "iso:country":"US",
    "sg:address":"100 Airport Rd",
    "sg:city":"Waterville",
    "sg:classifiers":[
        {
            "category":"Education",
            "subcategory":"Special Training",
            "type":"Public Place"
        }
    ],
    "sg:phone":"+1 207 873 0033",
    "sg:postcode":"04901",
    "sg:province":"ME",
    "sg:tags":[
        "aircraft",
        "school"
    ],
    "wof:name":"Kennebec Air",
    "wof:placetype":"venue"
},
  "geometry": {"coordinates":[-69.675666,44.537746],"type":"Point"}
}