{
  "type": "Feature",
  "properties": {
    "iso:country":"US",
    "sg:address":"24 Main Rd",
    "sg:city":"Charleston",
    "sg:classifiers":[
        {
            "category":"Wholesale",
            "subcategory":"Farm Supplies",
            "type":"Manufacturing & Wholesale Goods"
        }
    ],
    "sg:phone":"+1 207 285 3404",
    "sg:postcode":"04422",
    "sg:province":"ME",
    "sg:tags":[
        "feed"
    ],
    "wof:name":"H A Higgins & Son Inc",
    "wof:placetype":"venue"
},
  "geometry": {"coordinates":[-69.03912699999999,45.081248],"type":"Point"}
}