{
  "type": "Feature",
  "properties": {
    "addr:full":"392 US Hwy 202 Monmouth ME 04259",
    "addr:housenumber":"392",
    "addr:postcode":"04259",
    "addr:street":"Us Hwy 202",
    "iso:country":"US",
    "sg:address":"392 US Hwy 202",
    "sg:city":"Monmouth",
    "sg:classifiers":[
        {
            "category":"Health Services",
            "subcategory":"Health Practitioner",
            "type":"Services"
        }
    ],
    "sg:phone":"+1 207 933 2499",
    "sg:postcode":"04259",
    "sg:province":"ME",
    "sg:tags":[
        "occupational",
        "therapist"
    ],
    "wof:name":"Spectrum Occupational Thrpy",
    "wof:placetype":"venue"
},
  "geometry": {"coordinates":[-70.06874999999999,44.238999],"type":"Point"}
}