{
  "type": "Feature",
  "properties": {
    "addr:full":"84 Kelley Rd Orono ME 04473",
    "addr:housenumber":"84",
    "addr:postcode":"04473",
    "addr:street":"Kelley Rd",
    "iso:country":"US",
    "sg:address":"84 Kelley Rd",
    "sg:city":"Orono",
    "sg:classifiers":[
        {
            "category":"Real Estate",
            "subcategory":"Developer",
            "type":"Services"
        }
    ],
    "sg:phone":"+1 207 947 3500",
    "sg:postcode":"04473",
    "sg:province":"ME",
    "sg:website":"www.dirigopines.com",
    "wof:name":"Dirigo Pines Development",
    "wof:placetype":"venue"
},
  "geometry": {"coordinates":[-68.691458,44.867937],"type":"Point"}
}