{
  "type": "Feature",
  "properties": {
    "addr:full":"350 Townsend Ave Boothbay Harbor ME 04538",
    "addr:housenumber":"350",
    "addr:postcode":"04538",
    "addr:street":"Townsend Ave",
    "iso:country":"US",
    "sg:address":"350 Townsend Ave",
    "sg:city":"Boothbay Harbor",
    "sg:classifiers":[
        {
            "category":"Restaurant",
            "type":"Food & Drink"
        }
    ],
    "sg:phone":"+1 207 633 6656",
    "sg:postcode":"04538",
    "sg:province":"ME",
    "sg:tags":[
        "caterer"
    ],
    "wof:name":"Baggettes",
    "wof:placetype":"venue"
},
  "geometry": {"coordinates":[-69.627066,43.861523],"type":"Point"}
}