{
  "type": "Feature",
  "properties": {
    "addr:full":"40 Wildwood Dr Saco ME 04072",
    "addr:housenumber":"40",
    "addr:postcode":"04072",
    "addr:street":"Wildwood Dr",
    "iso:country":"US",
    "sg:address":"40 Wildwood Dr",
    "sg:city":"Saco",
    "sg:classifiers":[
        {
            "category":"Building & Trades",
            "subcategory":"Construction",
            "type":"Services"
        }
    ],
    "sg:phone":"+1 207 283 1735",
    "sg:postcode":"04072",
    "sg:province":"ME",
    "sg:tags":[
        "house"
    ],
    "wof:name":"Days Off Contracting",
    "wof:placetype":"venue"
},
  "geometry": {"coordinates":[-70.404003,43.484114],"type":"Point"}
}