{
  "type": "Feature",
  "properties": {
    "addr:full":"2 1st St Waterville ME 04901",
    "addr:housenumber":"2",
    "addr:postcode":"04901",
    "addr:street":"1St St",
    "iso:country":"US",
    "sg:address":"2 1st St",
    "sg:city":"Waterville",
    "sg:classifiers":[
        {
            "category":"Health Services",
            "subcategory":"Doctor",
            "type":"Services"
        }
    ],
    "sg:phone":"+1 207 872 5252",
    "sg:postcode":"04901",
    "sg:province":"ME",
    "sg:tags":[
        "dentist"
    ],
    "wof:name":"John D Koons DDS",
    "wof:placetype":"venue"
},
  "geometry": {"coordinates":[-69.61772999999999,44.557365],"type":"Point"}
}