{
  "type": "Feature",
  "properties": {
    "iso:country":"US",
    "sg:address":"155 Dairy Ln",
    "sg:city":"Guilford",
    "sg:classifiers":[
        {
            "category":"Building & Trades",
            "subcategory":"Construction",
            "type":"Services"
        }
    ],
    "sg:phone":"+1 207 876 3713",
    "sg:postcode":"04443",
    "sg:province":"ME",
    "sg:tags":[
        "house"
    ],
    "wof:name":"Santos Builders",
    "wof:placetype":"venue"
},
  "geometry": {"coordinates":[-69.371394,45.079209],"type":"Point"}
}