{
  "type": "Feature",
  "properties": {
    "addr:full":"464 Western Rd Warren ME 04864",
    "addr:housenumber":"464",
    "addr:postcode":"04864",
    "addr:street":"Western Rd",
    "iso:country":"US",
    "sg:address":"464 Western Rd",
    "sg:city":"Warren",
    "sg:classifiers":[
        {
            "category":"Retail",
            "subcategory":"Auto Repair",
            "type":"Services"
        }
    ],
    "sg:phone":"+1 207 273 4097",
    "sg:postcode":"04864",
    "sg:province":"ME",
    "sg:tags":[
        "repairing",
        "automobile"
    ],
    "wof:name":"Copeland's Garage",
    "wof:placetype":"venue"
},
  "geometry": {"coordinates":[-69.25286699999999,44.121312],"type":"Point"}
}