{
  "type": "Feature",
  "properties": {
    "iso:country":"US",
    "sg:address":"96 Bristol Rd",
    "sg:city":"Damariscotta",
    "sg:classifiers":[
        {
            "category":"Insurance",
            "subcategory":"Insurance Agent",
            "type":"Services"
        }
    ],
    "sg:phone":"+1 207 563 8005",
    "sg:postcode":"04543",
    "sg:province":"ME",
    "wof:name":"Planning Services Of Maine",
    "wof:placetype":"venue"
},
  "geometry": {"coordinates":[-69.527036,44.02648],"type":"Point"}
}