{
  "type": "Feature",
  "properties": {
    "addr:full":"173 Main St Biddeford ME 04005",
    "addr:housenumber":"173",
    "addr:postcode":"04005",
    "addr:street":"Main St",
    "iso:country":"US",
    "sg:address":"173 Main St",
    "sg:city":"Biddeford",
    "sg:classifiers":[
        {
            "category":"Restaurant",
            "type":"Food & Drink"
        }
    ],
    "sg:phone":"+1 207 283 0003",
    "sg:postcode":"04005",
    "sg:province":"ME",
    "wof:name":"Pizza City",
    "wof:placetype":"venue"
},
  "geometry": {"coordinates":[-70.45515399999999,43.493269],"type":"Point"}
}