{
  "type": "Feature",
  "properties": {
    "iso:country":"US",
    "sg:address":"81 Elm St",
    "sg:city":"Biddeford",
    "sg:classifiers":[
        {
            "category":"Autos & Motor Vehicles",
            "subcategory":"Auto Supplies",
            "type":"Retail Goods"
        }
    ],
    "sg:phone":"+1 207 284 4501",
    "sg:postcode":"04005",
    "sg:province":"ME",
    "sg:tags":[
        "automobile",
        "parts"
    ],
    "wof:name":"Carquest Auto Supply",
    "wof:placetype":"venue"
},
  "geometry": {"coordinates":[-70.456474,43.496598],"type":"Point"}
}