{
  "type": "Feature",
  "properties": {
    "addr:full":"1053 Forest Ave Portland ME 04103",
    "addr:housenumber":"1053",
    "addr:postcode":"04103",
    "addr:street":"Forest Ave",
    "iso:country":"US",
    "sg:address":"1053 Forest Ave",
    "sg:city":"Portland",
    "sg:classifiers":[
        {
            "category":"Restaurant",
            "type":"Food & Drink"
        }
    ],
    "sg:phone":"+1 207 797 8411",
    "sg:postcode":"04103",
    "sg:province":"ME",
    "wof:name":"Blimpie Subs & Salads",
    "wof:placetype":"venue"
},
  "geometry": {"coordinates":[-70.290744,43.683092],"type":"Point"}
}