{
  "type": "Feature",
  "properties": {
    "addr:full":"278 State St Brewer ME 04412",
    "addr:housenumber":"278",
    "addr:postcode":"04412",
    "addr:street":"State St",
    "iso:country":"US",
    "sg:address":"278 State St",
    "sg:city":"Brewer",
    "sg:classifiers":[
        {
            "category":"Shopping",
            "subcategory":"Department Store",
            "type":"Retail Goods"
        }
    ],
    "sg:phone":"+1 207 989 4075",
    "sg:postcode":"04412",
    "sg:province":"ME",
    "sg:tags":[
        "shop"
    ],
    "wof:name":"Dollar Tree",
    "wof:placetype":"venue"
},
  "geometry": {"coordinates":[-68.752228,44.784927],"type":"Point"}
}