{
  "type": "Feature",
  "properties": {
    "iso:country":"US",
    "sg:address":"260 Smithville Rd",
    "sg:city":"Steuben",
    "sg:classifiers":[
        {
            "category":"Building & Trades",
            "subcategory":"Construction",
            "type":"Services"
        }
    ],
    "sg:phone":"+1 207 546 2858",
    "sg:postcode":"04680",
    "sg:province":"ME",
    "sg:tags":[
        "carpentry",
        "contractor"
    ],
    "wof:name":"Benedict Woodworking",
    "wof:placetype":"venue"
},
  "geometry": {"coordinates":[-67.969865,44.51475],"type":"Point"}
}