{
  "type": "Feature",
  "properties": {
    "addr:full":"74 Tompkins Rd Presque Isle ME 04769",
    "addr:housenumber":"74",
    "addr:postcode":"04769",
    "addr:street":"Tompkins Rd",
    "iso:country":"US",
    "sg:address":"74 Tompkins Rd",
    "sg:city":"Presque Isle",
    "sg:classifiers":[
        {
            "category":"Retail",
            "subcategory":"Repair Shop",
            "type":"Services"
        }
    ],
    "sg:phone":"+1 207 764 6863",
    "sg:postcode":"04769",
    "sg:province":"ME",
    "sg:tags":[
        "lock",
        "locksmith"
    ],
    "wof:name":"William Givens Locksmith",
    "wof:placetype":"venue"
},
  "geometry": {"coordinates":[-67.984442,46.596022],"type":"Point"}
}