{
  "type": "Feature",
  "properties": {
    "addr:full":"4 Campus St Lisbon Falls ME 04252",
    "addr:housenumber":"4",
    "addr:postcode":"04252",
    "addr:street":"Campus St",
    "iso:country":"US",
    "sg:address":"4 Campus St",
    "sg:city":"Lisbon Falls",
    "sg:classifiers":[
        {
            "category":"Education",
            "subcategory":"School",
            "type":"Public Place"
        }
    ],
    "sg:phone":"+1 207 353 3060",
    "sg:postcode":"04252",
    "sg:province":"ME",
    "wof:name":"Lisbon Special Education",
    "wof:placetype":"venue"
},
  "geometry": {"coordinates":[-70.058978,44.0012],"type":"Point"}
}