{
  "type": "Feature",
  "properties": {
    "addr:full":"316 Johnson Mill Rd Orrington ME 04474",
    "addr:housenumber":"316",
    "addr:postcode":"04474",
    "addr:street":"Johnson Mill Rd",
    "iso:country":"US",
    "sg:address":"316 Johnson Mill Rd",
    "sg:city":"Orrington",
    "sg:classifiers":[
        {
            "category":"Building & Trades",
            "subcategory":"Plumbing",
            "type":"Services"
        }
    ],
    "sg:phone":"+1 207 825 3140",
    "sg:postcode":"04474",
    "sg:province":"ME",
    "sg:tags":[
        "septic"
    ],
    "wof:name":"Gus' Septic Svc",
    "wof:placetype":"venue"
},
  "geometry": {"coordinates":[-68.789726,44.732874],"type":"Point"}
}