{
  "type": "Feature",
  "properties": {
    "addr:full":"206 Main St Mattawamkeag ME 04401",
    "addr:housenumber":"206",
    "addr:postcode":"04401",
    "addr:street":"Main St",
    "iso:country":"US",
    "sg:address":"206 Main St",
    "sg:city":"Mattawamkeag",
    "sg:classifiers":[
        {
            "category":"Organizations",
            "subcategory":"Religious Organization",
            "type":"Services"
        }
    ],
    "sg:phone":"+1 207 736 4791",
    "sg:postcode":"04401",
    "sg:province":"ME",
    "sg:tags":[
        "church"
    ],
    "wof:name":"Mattawankeag Bible Baptist",
    "wof:placetype":"venue"
},
  "geometry": {"coordinates":[-68.773675,44.797132],"type":"Point"}
}