{
  "type": "Feature",
  "properties": {
    "iso:country":"US",
    "sg:address":"19 Bridge St",
    "sg:city":"Benton",
    "sg:classifiers":[
        {
            "category":"Health Services",
            "subcategory":"Health Practitioner",
            "type":"Services"
        }
    ],
    "sg:phone":"+1 207 453 4708",
    "sg:postcode":"04901",
    "sg:province":"ME",
    "sg:tags":[
        "nurse",
        "registry"
    ],
    "wof:name":"Assistance Plus",
    "wof:placetype":"venue"
},
  "geometry": {"coordinates":[-69.587327,44.586806],"type":"Point"}
}