{
  "type": "Feature",
  "properties": {
    "addr:full":"141 Passaconaway Rd Waterford ME 04088",
    "addr:housenumber":"141",
    "addr:postcode":"04088",
    "addr:street":"Passaconaway Rd",
    "iso:country":"US",
    "sg:address":"141 Passaconaway Rd",
    "sg:city":"Waterford",
    "sg:classifiers":[
        {
            "category":"Professional",
            "subcategory":"Computer Services",
            "type":"Services"
        }
    ],
    "sg:phone":"+1 207 583 2724",
    "sg:postcode":"04088",
    "sg:province":"ME",
    "wof:name":"Compu Net",
    "wof:placetype":"venue"
},
  "geometry": {"coordinates":[-70.69547799999999,44.189175],"type":"Point"}
}