{
  "type": "Feature",
  "properties": {
    "addr:full":"220 Warrenton St Rockport ME 04856",
    "addr:housenumber":"220",
    "addr:postcode":"04856",
    "addr:street":"Warrenton St",
    "iso:country":"US",
    "sg:address":"220 Warrenton St",
    "sg:city":"Rockport",
    "sg:classifiers":[
        {
            "category":"Restaurant",
            "type":"Food & Drink"
        }
    ],
    "sg:menulink":"http://www.allmenus.com/me/rockport/268188-marcels-at-the-samoset-resort/menu/",
    "sg:phone":"+1 207 593 1529",
    "sg:postcode":"04856",
    "sg:province":"ME",
    "wof:name":"Marcel's at The Samoset Resort",
    "wof:placetype":"venue"
},
  "geometry": {"coordinates":[-69.087874,44.125142],"type":"Point"}
}