{
  "type": "Feature",
  "properties": {
    "iso:country":"US",
    "sg:address":"4 Main St",
    "sg:city":"Jay",
    "sg:classifiers":[
        {
            "category":"Restaurant",
            "type":"Food & Drink"
        }
    ],
    "sg:phone":"+1 207 897 2200",
    "sg:postcode":"04239",
    "sg:province":"ME",
    "wof:name":"Franchetti's Home Town Variety",
    "wof:placetype":"venue"
},
  "geometry": {"coordinates":[-70.196698,44.479448],"type":"Point"}
}