{
  "type": "Feature",
  "properties": {
    "iso:country":"US",
    "sg:address":"429 Mill Rd",
    "sg:city":"Edgecomb",
    "sg:classifiers":[
        {
            "category":"Professional",
            "type":"Services"
        }
    ],
    "sg:phone":"+1 207 882 5003",
    "sg:postcode":"04556",
    "sg:province":"ME",
    "wof:name":"Barry L Arsenault",
    "wof:placetype":"venue"
},
  "geometry": {"coordinates":[-69.656741,43.940085],"type":"Point"}
}