{
  "type": "Feature",
  "properties": {
    "addr:full":"64 Totte Rd Shapleigh ME 04076",
    "addr:housenumber":"64",
    "addr:postcode":"04076",
    "addr:street":"Totte Rd",
    "iso:country":"US",
    "sg:address":"64 Totte Rd",
    "sg:city":"Shapleigh",
    "sg:classifiers":[
        {
            "category":"Wholesale",
            "subcategory":"Vending Machines",
            "type":"Manufacturing & Wholesale Goods"
        }
    ],
    "sg:phone":"+1 207 636 3286",
    "sg:postcode":"04076",
    "sg:province":"ME",
    "wof:name":"Curran Associates Inc",
    "wof:placetype":"venue"
},
  "geometry": {"coordinates":[-70.86560299999999,43.555445],"type":"Point"}
}