{
  "type": "Feature",
  "properties": {
    "iso:country":"US",
    "sg:address":"302 Stevens Ave",
    "sg:city":"Portland",
    "sg:classifiers":[
        {
            "category":"Organizations",
            "subcategory":"Religious Organization",
            "type":"Services"
        }
    ],
    "sg:phone":"+1 207 772 8277",
    "sg:postcode":"04103",
    "sg:province":"ME",
    "sg:tags":[
        "church"
    ],
    "wof:name":"Portland Soc of New Jerusalem",
    "wof:placetype":"venue"
},
  "geometry": {"coordinates":[-70.295062,43.669096],"type":"Point"}
}