{
  "type": "Feature",
  "properties": {
    "addr:full":"133 Elm St Camden ME 04843",
    "addr:housenumber":"133",
    "addr:postcode":"04843",
    "addr:street":"Elm St",
    "iso:country":"US",
    "sg:address":"133 Elm St",
    "sg:city":"Camden",
    "sg:classifiers":[
        {
            "category":"Personal",
            "subcategory":"Beauty Salon",
            "type":"Services"
        }
    ],
    "sg:phone":"+1 207 236 9988",
    "sg:postcode":"04843",
    "sg:province":"ME",
    "wof:name":"Four Seasons Beauty & Wellness",
    "wof:placetype":"venue"
},
  "geometry": {"coordinates":[-69.076831,44.201073],"type":"Point"}
}