{
  "type": "Feature",
  "properties": {
    "iso:country":"US",
    "sg:address":"5 Ray Ave",
    "sg:city":"York",
    "sg:classifiers":[
        {
            "category":"Shopping",
            "type":"Retail Goods"
        }
    ],
    "sg:phone":"+1 207 363 7336",
    "sg:postcode":"03910",
    "sg:province":"ME",
    "sg:tags":[
        "art",
        "gallery",
        "dealer"
    ],
    "wof:name":"Blue Stocking Studio",
    "wof:placetype":"venue"
},
  "geometry": {"coordinates":[-70.608223,43.18297],"type":"Point"}
}