{
  "type": "Feature",
  "properties": {
    "addr:full":"4 Market Place Dr York ME 03909",
    "addr:housenumber":"4",
    "addr:postcode":"03909",
    "addr:street":"Market Place Dr",
    "iso:country":"US",
    "sg:address":"4 Market Place Dr",
    "sg:city":"York",
    "sg:classifiers":[
        {
            "category":"Personal",
            "subcategory":"Beauty Salon",
            "type":"Services"
        }
    ],
    "sg:phone":"+1 207 363 3611",
    "sg:postcode":"03909",
    "sg:province":"ME",
    "sg:tags":[
        "hair"
    ],
    "sg:website":"www.sarajjones.com",
    "wof:name":"Sara Jones",
    "wof:placetype":"venue"
},
  "geometry": {"coordinates":[-70.67392,43.149178],"type":"Point"}
}