{
  "type": "Feature",
  "properties": {
    "iso:country":"US",
    "sg:address":"406 Montello St",
    "sg:city":"Lewiston",
    "sg:classifiers":[
        {
            "category":"Social Services",
            "subcategory":"Child Care",
            "type":"Services"
        }
    ],
    "sg:phone":"+1 207 783 4371",
    "sg:postcode":"04240",
    "sg:province":"ME",
    "sg:tags":[
        "day"
    ],
    "wof:name":"Jensen Diane C Day Care",
    "wof:placetype":"venue"
},
  "geometry": {"coordinates":[-70.174435,44.104335],"type":"Point"}
}