{
  "type": "Feature",
  "properties": {
    "addr:full":"527 Ocean Ave Portland ME 04103",
    "addr:housenumber":"527",
    "addr:postcode":"04103",
    "addr:street":"Ocean Ave",
    "iso:country":"US",
    "sg:address":"527 Ocean Ave",
    "sg:city":"Portland",
    "sg:classifiers":[
        {
            "category":"Health Services",
            "subcategory":"Doctor",
            "type":"Services"
        }
    ],
    "sg:phone":"+1 207 774 3070",
    "sg:postcode":"04103",
    "sg:province":"ME",
    "sg:tags":[
        "physician",
        "surgeon"
    ],
    "sg:website":"www.bowdoinmedicalgroup.com",
    "wof:name":"Bowdoin Medical Group",
    "wof:placetype":"venue"
},
  "geometry": {"coordinates":[-70.270448,43.684329],"type":"Point"}
}