{
  "type": "Feature",
  "properties": {
    "addr:full":"26 Main St Ogunquit ME 03907",
    "addr:housenumber":"26",
    "addr:postcode":"03907",
    "addr:street":"Main St",
    "iso:country":"US",
    "sg:address":"26 Main St",
    "sg:city":"Ogunquit",
    "sg:classifiers":[
        {
            "category":"Shopping",
            "subcategory":"Gifts & Souvenirs",
            "type":"Retail Goods"
        }
    ],
    "sg:phone":"+1 207 646 5597",
    "sg:postcode":"03907",
    "sg:province":"ME",
    "sg:tags":[
        "shop"
    ],
    "wof:name":"Barrel Stave",
    "wof:placetype":"venue"
},
  "geometry": {"coordinates":[-70.599969,43.25007],"type":"Point"}
}