{
  "type": "Feature",
  "properties": {
    "addr:full":"54 Front St Bath ME 04530",
    "addr:housenumber":"54",
    "addr:postcode":"04530",
    "addr:street":"Front St",
    "iso:country":"US",
    "sg:address":"54 Front St",
    "sg:city":"Bath",
    "sg:classifiers":[
        {
            "category":"Personal",
            "subcategory":"Barber",
            "type":"Services"
        }
    ],
    "sg:phone":"+1 207 443 9039",
    "sg:postcode":"04530",
    "sg:province":"ME",
    "wof:name":"Ben's Barber Shop",
    "wof:placetype":"venue"
},
  "geometry": {"coordinates":[-69.814145,43.912516],"type":"Point"}
}