{
  "type": "Feature",
  "properties": {
    "iso:country":"US",
    "sg:address":"53 Broad St",
    "sg:city":"Auburn",
    "sg:classifiers":[
        {
            "category":"Food & Beverages",
            "subcategory":"Groceries & Convenience Stores",
            "type":"Retail Goods"
        }
    ],
    "sg:phone":"+1 207 795 0959",
    "sg:postcode":"04210",
    "sg:province":"ME",
    "wof:name":"Norm's KWIK Stop",
    "wof:placetype":"venue"
},
  "geometry": {"coordinates":[-70.222587,44.087813],"type":"Point"}
}