{
  "type": "Feature",
  "properties": {
    "iso:country":"US",
    "sg:address":"76 Weld Rd",
    "sg:city":"Wilton",
    "sg:classifiers":[
        {
            "category":"Shopping",
            "type":"Retail Goods"
        }
    ],
    "sg:phone":"+1 207 645 9555",
    "sg:postcode":"04294",
    "sg:province":"ME",
    "sg:tags":[
        "monument"
    ],
    "wof:name":"Wiles Granite Co",
    "wof:placetype":"venue"
},
  "geometry": {"coordinates":[-70.229692,44.593516],"type":"Point"}
}