{
  "type": "Feature",
  "properties": {
    "iso:country":"US",
    "sg:address":"821 Main St",
    "sg:city":"Westbrook",
    "sg:classifiers":[
        {
            "category":"Professional",
            "subcategory":"Business Services",
            "type":"Services"
        }
    ],
    "sg:phone":"+1 207 828 2700",
    "sg:postcode":"04092",
    "sg:province":"ME",
    "sg:tags":[
        "paging",
        "answering"
    ],
    "wof:name":"Appletree Answering Svc",
    "wof:placetype":"venue"
},
  "geometry": {"coordinates":[-70.36316600000001,43.676463],"type":"Point"}
}