{
  "type": "Feature",
  "properties": {
    "iso:country":"US",
    "sg:address":"75 Baston Rd",
    "sg:city":"North Yarmouth",
    "sg:classifiers":[
        {
            "category":"Professional",
            "subcategory":"Management & Consulting",
            "type":"Services"
        }
    ],
    "sg:phone":"+1 207 829 5113",
    "sg:postcode":"04097",
    "sg:province":"ME",
    "sg:tags":[
        "international",
        "consultant"
    ],
    "wof:name":"Lee International Business Dev",
    "wof:placetype":"venue"
},
  "geometry": {"coordinates":[-70.236676,43.821528],"type":"Point"}
}