{
  "type": "Feature",
  "properties": {
    "addr:full":"7 Main St Bar Harbor ME 04609",
    "addr:housenumber":"7",
    "addr:postcode":"04609",
    "addr:street":"Main St",
    "iso:country":"US",
    "sg:address":"7 Main St",
    "sg:city":"Bar Harbor",
    "sg:classifiers":[
        {
            "category":"Shopping",
            "subcategory":"Gifts & Souvenirs",
            "type":"Retail Goods"
        }
    ],
    "sg:phone":"+1 207 288 4120",
    "sg:postcode":"04609",
    "sg:province":"ME",
    "sg:tags":[
        "shop"
    ],
    "wof:name":"Blueberry Patch",
    "wof:placetype":"venue"
},
  "geometry": {"coordinates":[-68.205029,44.390773],"type":"Point"}
}