{
  "type": "Feature",
  "properties": {
    "addr:full":"340 Main St Rockland ME 04841",
    "addr:housenumber":"340",
    "addr:postcode":"04841",
    "addr:street":"Main St",
    "iso:country":"US",
    "sg:address":"340 Main St",
    "sg:city":"Rockland",
    "sg:classifiers":[
        {
            "category":"Professional",
            "subcategory":"Business Services",
            "type":"Services"
        }
    ],
    "sg:phone":"+1 207 594 1976",
    "sg:postcode":"04841",
    "sg:province":"ME",
    "wof:name":"Andrew Reichline",
    "wof:placetype":"venue"
},
  "geometry": {"coordinates":[-69.109194,44.10309],"type":"Point"}
}