{
  "type": "Feature",
  "properties": {
    "addr:full":"59 Mountain St Camden ME 04843",
    "addr:housenumber":"59",
    "addr:postcode":"04843",
    "addr:street":"Mountain St",
    "iso:country":"US",
    "sg:address":"59 Mountain St",
    "sg:city":"Camden",
    "sg:classifiers":[
        {
            "category":"Food & Beverages",
            "subcategory":"Bakery",
            "type":"Retail Goods"
        }
    ],
    "sg:phone":"+1 207 236 2226",
    "sg:postcode":"04843",
    "sg:province":"ME",
    "sg:tags":[
        "baker"
    ],
    "wof:name":"Camden Baking Co",
    "wof:placetype":"venue"
},
  "geometry": {"coordinates":[-69.074085,44.21944],"type":"Point"}
}