{
  "type": "Feature",
  "properties": {
    "addr:full":"125 North St Kennebunkport ME 04046",
    "addr:housenumber":"125",
    "addr:postcode":"04046",
    "addr:street":"North St",
    "iso:country":"US",
    "sg:address":"125 North St",
    "sg:city":"Kennebunkport",
    "sg:classifiers":[
        {
            "category":"Museum",
            "type":"Entertainment"
        }
    ],
    "sg:phone":"+1 207 967 8180",
    "sg:postcode":"04046",
    "sg:province":"ME",
    "wof:name":"Kennebunkport Historical Society",
    "wof:placetype":"venue"
},
  "geometry": {"coordinates":[-70.476607,43.379622],"type":"Point"}
}