{
  "type": "Feature",
  "properties": {
    "addr:city":"Kennebunkport",
    "addr:full":"125 North St Kennebunkport, Me 04046",
    "addr:house_number":"125",
    "addr:housenumber":"125",
    "addr:phone":"+1 207-967-2751",
    "addr:postcode":"04046",
    "addr:road":"North St",
    "addr:state":"ME",
    "addr:street":"North St",
    "iso:country":"US",
    "sg:address":"125 North St",
    "sg:city":"Kennebunkport",
    "sg:classifiers":[
        {
            "category":"Museum",
            "type":"Entertainment"
        }
    ],
    "sg:phone":"+1 207 967 8180",
    "sg:postcode":"04046",
    "sg:province":"ME",
    "wof:airports":[
        102527407
    ],
    "wof:name":"Kennebunkport Historical Society",
    "wof:placetype":"venue"
},
  "geometry": {"coordinates":[-70.47683000000001,43.38005],"type":"Point"}
}