{
  "type": "Feature",
  "properties": {
    "iso:country":"US",
    "sg:address":"47 Ottercreek Dr",
    "sg:city":"Otter Creek",
    "sg:classifiers":[
        {
            "category":"Travel",
            "subcategory":"Hotels & Motels",
            "type":"Entertainment"
        }
    ],
    "sg:phone":"+1 207 288 5151",
    "sg:postcode":"04660",
    "sg:province":"ME",
    "sg:website":"www.ottercreekinn.com",
    "wof:name":"Otter Creek Inn",
    "wof:placetype":"venue"
},
  "geometry": {"coordinates":[-68.211721,44.314348],"type":"Point"}
}