{
  "type": "Feature",
  "properties": {
    "addr:full":"2 Pine Ave Livermore Falls ME 04254",
    "addr:housenumber":"2",
    "addr:postcode":"04254",
    "addr:street":"Pine Ave",
    "iso:country":"US",
    "sg:address":"2 Pine Ave",
    "sg:city":"Livermore Falls",
    "sg:classifiers":[
        {
            "category":"Organizations",
            "subcategory":"Professional Association",
            "type":"Services"
        }
    ],
    "sg:phone":"+1 207 897 6755",
    "sg:postcode":"04254",
    "sg:province":"ME",
    "sg:tags":[
        "chambers",
        "commerce"
    ],
    "wof:name":"Jay Livermore & Livermore Flls",
    "wof:placetype":"venue"
},
  "geometry": {"coordinates":[-70.183013,44.473406],"type":"Point"}
}