{
  "type": "Feature",
  "properties": {
    "addr:full":"30 Libby Hill Rd Oakland ME 04963",
    "addr:housenumber":"30",
    "addr:postcode":"04963",
    "addr:street":"Libby Hill Rd",
    "iso:country":"US",
    "sg:address":"30 Libby Hill Rd",
    "sg:city":"Oakland",
    "sg:classifiers":[
        {
            "category":"Building & Trades",
            "subcategory":"Construction",
            "type":"Services"
        }
    ],
    "sg:phone":"+1 207 465 3350",
    "sg:postcode":"04963",
    "sg:province":"ME",
    "sg:tags":[
        "general",
        "contractor"
    ],
    "wof:name":"Mayberry Builders",
    "wof:placetype":"venue"
},
  "geometry": {"coordinates":[-69.72132499999999,44.538727],"type":"Point"}
}