{
  "type": "Feature",
  "properties": {
    "addr:full":"68 Roosevelt Trl Naples ME 04084",
    "addr:housenumber":"68",
    "addr:postcode":"04084",
    "addr:street":"Roosevelt Trl",
    "iso:country":"US",
    "sg:address":"68 Roosevelt Trl",
    "sg:city":"Naples",
    "sg:classifiers":[
        {
            "category":"Professional",
            "subcategory":"Lawyer & Legal Services",
            "type":"Services"
        }
    ],
    "sg:phone":"+1 207 693 3030",
    "sg:postcode":"04084",
    "sg:province":"ME",
    "sg:tags":[
        "attorney"
    ],
    "wof:name":"Robert M Neault & Assoc",
    "wof:placetype":"venue"
},
  "geometry": {"coordinates":[-70.46584799999999,43.866709],"type":"Point"}
}