{
  "type": "Feature",
  "properties": {
    "addr:full":"408 Brighton Ave Portland ME 04102",
    "addr:housenumber":"408",
    "addr:postcode":"04102",
    "addr:street":"Brighton Ave",
    "iso:country":"US",
    "sg:address":"408 Brighton Ave",
    "sg:city":"Portland",
    "sg:classifiers":[
        {
            "category":"Social Services",
            "subcategory":"Adult Care",
            "type":"Services"
        }
    ],
    "sg:phone":"+1 207 774 3281",
    "sg:postcode":"04102",
    "sg:province":"ME",
    "sg:tags":[
        "home",
        "group"
    ],
    "wof:name":"Group Main Stream",
    "wof:placetype":"venue"
},
  "geometry": {"coordinates":[-70.29573000000001,43.666498],"type":"Point"}
}