{
  "type": "Feature",
  "properties": {
    "addr:full":"PO Box 10020 Portland ME 04104",
    "addr:housenumber":"po box 10020",
    "addr:postcode":"04104",
    "iso:country":"US",
    "sg:address":"PO Box 10020",
    "sg:city":"Portland",
    "sg:classifiers":[
        {
            "category":"Professional",
            "subcategory":"Computer Services",
            "type":"Services"
        }
    ],
    "sg:phone":"+1 207 857 3003",
    "sg:postcode":"04104",
    "sg:province":"ME",
    "sg:tags":[
        "maine",
        "technology-association",
        "council",
        "association"
    ],
    "sg:website":"http://www.techmaine.com",
    "wof:name":"TechMaine",
    "wof:placetype":"venue"
},
  "geometry": {"coordinates":[-70.464839,43.84649],"type":"Point"}
}