{
  "type": "Feature",
  "properties": {
    "addr:full":"451 Alfred St Biddeford ME 04005",
    "addr:housenumber":"451",
    "addr:postcode":"04005",
    "addr:street":"Alfred St",
    "iso:country":"US",
    "sg:address":"451 Alfred St",
    "sg:city":"Biddeford",
    "sg:classifiers":[
        {
            "category":"Autos & Motor Vehicles",
            "subcategory":"Automobile Sales",
            "type":"Retail Goods"
        }
    ],
    "sg:phone":"+1 207 283 1777",
    "sg:postcode":"04005",
    "sg:province":"ME",
    "sg:tags":[
        "repair",
        "used",
        "dealer",
        "car",
        "general"
    ],
    "wof:name":"Five Star Auto Sales",
    "wof:placetype":"venue"
},
  "geometry": {"coordinates":[-70.482024,43.480627],"type":"Point"}
}