{
  "type": "Feature",
  "properties": {
    "iso:country":"US",
    "sg:address":"11 Yates St",
    "sg:city":"Biddeford Pool",
    "sg:classifiers":[
        {
            "category":"Real Estate",
            "subcategory":"Real Estate Agent",
            "type":"Services"
        }
    ],
    "sg:phone":"+1 207 282 1732",
    "sg:postcode":"04006",
    "sg:province":"ME",
    "wof:name":"Ocean View Properties",
    "wof:placetype":"venue"
},
  "geometry": {"coordinates":[-70.354028,43.445737],"type":"Point"}
}