{
  "type": "Feature",
  "properties": {
    "addr:full":"262 Bomarc Rd Bangor ME 04401",
    "addr:housenumber":"262",
    "addr:postcode":"04401",
    "addr:street":"Bomarc Rd",
    "iso:country":"US",
    "sg:address":"262 Bomarc Rd",
    "sg:city":"Bangor",
    "sg:classifiers":[
        {
            "category":"Freight",
            "type":"Transportation"
        }
    ],
    "sg:phone":"+1 207 947 1106",
    "sg:postcode":"04401",
    "sg:province":"ME",
    "sg:tags":[
        "trucking"
    ],
    "sg:website":"www.hartt-trans.com",
    "wof:name":"Hartt Transportation Systems",
    "wof:placetype":"venue"
},
  "geometry": {"coordinates":[-68.78425799999999,44.849724],"type":"Point"}
}