{
  "type": "Feature",
  "properties": {
    "addr:full":"571 Broadway Bangor ME 04401",
    "addr:housenumber":"571",
    "addr:postcode":"04401",
    "addr:street":"Broadway",
    "iso:country":"US",
    "sg:address":"571 Broadway",
    "sg:city":"Bangor",
    "sg:classifiers":[
        {
            "category":"Restaurant",
            "type":"Food & Drink"
        }
    ],
    "sg:phone":"+1 207 947 6759",
    "sg:postcode":"04401",
    "sg:province":"ME",
    "wof:name":"China Light Fast Foods",
    "wof:placetype":"venue"
},
  "geometry": {"coordinates":[-68.776066,44.820137],"type":"Point"}
}