{
  "type": "Feature",
  "properties": {
    "iso:country":"US",
    "sg:address":"16 Godfrey Dr",
    "sg:city":"Orono",
    "sg:classifiers":[
        {
            "category":"Banks & Credit Unions",
            "subcategory":"Bank",
            "type":"Services"
        }
    ],
    "sg:phone":"+1 207 866 0700",
    "sg:postcode":"04473",
    "sg:province":"ME",
    "wof:name":"MBNA New England",
    "wof:placetype":"venue"
},
  "geometry": {"coordinates":[-68.68286,44.90008],"type":"Point"}
}