{
  "type": "Feature",
  "properties": {
    "iso:country":"US",
    "sg:address":"145 Newbury St",
    "sg:city":"Portland",
    "sg:classifiers":[
        {
            "category":"Professional",
            "subcategory":"Art Services",
            "type":"Services"
        }
    ],
    "sg:phone":"+1 207 774 4558",
    "sg:postcode":"04101",
    "sg:province":"ME",
    "sg:tags":[
        "graphic",
        "designer"
    ],
    "sg:website":"www.woodandcompany.com",
    "wof:name":"Wood & Co",
    "wof:placetype":"venue"
},
  "geometry": {"coordinates":[-70.251578,43.660437],"type":"Point"}
}