{
  "type": "Feature",
  "properties": {
    "addr:full":"669 Intervale Rd Jay ME 04239",
    "addr:housenumber":"669",
    "addr:postcode":"04239",
    "addr:street":"Intervale Rd",
    "iso:country":"US",
    "sg:address":"669 Intervale Rd",
    "sg:city":"Jay",
    "sg:classifiers":[
        {
            "category":"Building & Trades",
            "subcategory":"Landscaping Services",
            "type":"Services"
        }
    ],
    "sg:phone":"+1 207 897 4700",
    "sg:postcode":"04239",
    "sg:province":"ME",
    "sg:tags":[
        "landscape"
    ],
    "wof:name":"Green Bear Services",
    "wof:placetype":"venue"
},
  "geometry": {"coordinates":[-70.253396,44.505283],"type":"Point"}
}