{
  "type": "Feature",
  "properties": {
    "addr:full":"145 River Rd Lewiston ME 04240",
    "addr:housenumber":"145",
    "addr:postcode":"04240",
    "addr:street":"River Rd",
    "iso:country":"US",
    "sg:address":"145 River Rd",
    "sg:city":"Lewiston",
    "sg:classifiers":[
        {
            "category":"Home & Garden",
            "subcategory":"Building Materials",
            "type":"Retail Goods"
        }
    ],
    "sg:phone":"+1 207 782 9515",
    "sg:postcode":"04240",
    "sg:province":"ME",
    "sg:tags":[
        "mixed",
        "concrete"
    ],
    "wof:name":"Dragon Products Co",
    "wof:placetype":"venue"
},
  "geometry": {"coordinates":[-70.19934600000001,44.06677],"type":"Point"}
}