{
  "type": "Feature",
  "properties": {
    "addr:full":"23 Water St Bangor ME 04401",
    "addr:housenumber":"23",
    "addr:postcode":"04401",
    "addr:street":"Water St",
    "iso:country":"US",
    "sg:address":"23 Water St",
    "sg:city":"Bangor",
    "sg:classifiers":[
        {
            "category":"Banks & Credit Unions",
            "subcategory":"Bank",
            "type":"Services"
        }
    ],
    "sg:phone":"+1 207 945 0600",
    "sg:postcode":"04401",
    "sg:province":"ME",
    "sg:website":"www.key.com",
    "wof:name":"Key Bank",
    "wof:placetype":"venue"
},
  "geometry": {"coordinates":[-68.77084499999999,44.799617],"type":"Point"}
}