{
  "type": "Feature",
  "properties": {
    "iso:country":"US",
    "sg:address":"941 Federal Rd",
    "sg:city":"Livermore",
    "sg:classifiers":[
        {
            "category":"Shopping",
            "subcategory":"Bicycles & Sporting Goods",
            "type":"Retail Goods"
        }
    ],
    "sg:phone":"+1 207 897 4754",
    "sg:postcode":"04253",
    "sg:province":"ME",
    "sg:tags":[
        "gun",
        "gunsmith"
    ],
    "wof:name":"Center Fire Gun Shop",
    "wof:placetype":"venue"
},
  "geometry": {"coordinates":[-70.220473,44.421747],"type":"Point"}
}