{
  "type": "Feature",
  "properties": {
    "addr:full":"9 Grand St South Portland ME 04106",
    "addr:housenumber":"9",
    "addr:postcode":"04106",
    "addr:street":"Grand St",
    "iso:country":"US",
    "sg:address":"9 Grand St",
    "sg:city":"South Portland",
    "sg:classifiers":[
        {
            "category":"Professional",
            "subcategory":"Art Services",
            "type":"Services"
        }
    ],
    "sg:phone":"+1 207 767 2295",
    "sg:postcode":"04106",
    "sg:province":"ME",
    "sg:tags":[
        "graphic",
        "designer"
    ],
    "wof:name":"Good Works",
    "wof:placetype":"venue"
},
  "geometry": {"coordinates":[-70.234776,43.644603],"type":"Point"}
}