{
  "type": "Feature",
  "properties": {
    "iso:country":"US",
    "sg:address":"354 State Rte 133",
    "sg:city":"Wilton",
    "sg:classifiers":[
        {
            "category":"Retail",
            "subcategory":"Auto Repair",
            "type":"Services"
        }
    ],
    "sg:phone":"+1 207 779 0689",
    "sg:postcode":"04294",
    "sg:province":"ME",
    "sg:tags":[
        "repairing",
        "automobile"
    ],
    "wof:name":"A Tec Auto Svc",
    "wof:placetype":"venue"
},
  "geometry": {"coordinates":[-70.163398,44.609398],"type":"Point"}
}