{
  "type": "Feature",
  "properties": {
    "iso:country":"US",
    "sg:address":"24 Shaker Rd",
    "sg:city":"Gray",
    "sg:classifiers":[
        {
            "category":"Retail",
            "subcategory":"Funeral Services",
            "type":"Services"
        }
    ],
    "sg:phone":"+1 207 657 3204",
    "sg:postcode":"04039",
    "sg:province":"ME",
    "sg:tags":[
        "director"
    ],
    "wof:name":"Wilson Funeral Home",
    "wof:placetype":"venue"
},
  "geometry": {"coordinates":[-70.332915,43.888335],"type":"Point"}
}