{
  "type": "Feature",
  "properties": {
    "addr:full":"357 McCrillis Corner Rd Wilton ME 04294",
    "addr:housenumber":"357",
    "addr:postcode":"04294",
    "addr:street":"Mccrillis Corner Rd",
    "iso:country":"US",
    "sg:address":"357 McCrillis Corner Rd",
    "sg:city":"Wilton",
    "sg:classifiers":[
        {
            "category":"Farming",
            "subcategory":"Farm",
            "type":"Manufacturing & Wholesale Goods"
        }
    ],
    "sg:phone":"+1 207 778 2685",
    "sg:postcode":"04294",
    "sg:province":"ME",
    "wof:name":"Whitehill Farm",
    "wof:placetype":"venue"
},
  "geometry": {"coordinates":[-70.151974,44.602661],"type":"Point"}
}