{
  "type": "Feature",
  "properties": {
    "addr:full":"Bridgton Rd Fryeburg ME 04037",
    "addr:postcode":"04037",
    "addr:street":"Bridgton Rd",
    "iso:country":"US",
    "sg:address":"Bridgton Rd",
    "sg:city":"Fryeburg",
    "sg:classifiers":[
        {
            "category":"Ice Cream",
            "type":"Food & Drink"
        }
    ],
    "sg:phone":"+1 207 935 2669",
    "sg:postcode":"04037",
    "sg:province":"ME",
    "sg:tags":[
        "frozen",
        "yogurt"
    ],
    "wof:name":"Froagie's Ice Cream",
    "wof:placetype":"venue"
},
  "geometry": {"coordinates":[-70.975601,44.008999],"type":"Point"}
}