{
  "type": "Feature",
  "properties": {
    "iso:country":"US",
    "sg:address":"500 Ossipee Trl E",
    "sg:city":"Gorham",
    "sg:classifiers":[
        {
            "category":"Wholesale",
            "subcategory":"Machinery & Supplies",
            "type":"Manufacturing & Wholesale Goods"
        }
    ],
    "sg:phone":"+1 207 839 4500",
    "sg:postcode":"04038",
    "sg:province":"ME",
    "sg:tags":[
        "tractor"
    ],
    "sg:website":"www.wescotts.com",
    "wof:name":"Wescott & Sons",
    "wof:placetype":"venue"
},
  "geometry": {"coordinates":[-70.51503599999999,43.711923],"type":"Point"}
}