{
  "type": "Feature",
  "properties": {
    "addr:full":"1 North St Kennebunkport ME 04046",
    "addr:housenumber":"1",
    "addr:postcode":"04046",
    "addr:street":"North St",
    "iso:country":"US",
    "sg:address":"1 North St",
    "sg:city":"Kennebunkport",
    "sg:classifiers":[
        {
            "category":"Organizations",
            "subcategory":"Community Association",
            "type":"Services"
        }
    ],
    "sg:phone":"+1 207 967 5620",
    "sg:postcode":"04046",
    "sg:province":"ME",
    "sg:tags":[
        "club"
    ],
    "wof:name":"Masonic Lodge",
    "wof:placetype":"venue"
},
  "geometry": {"coordinates":[-70.47704899999999,43.363364],"type":"Point"}
}