{
  "type": "Feature",
  "properties": {
    "addr:full":"20 Water St Winterport ME 04496",
    "addr:housenumber":"20",
    "addr:postcode":"04496",
    "addr:street":"Water St",
    "iso:country":"US",
    "sg:address":"20 Water St",
    "sg:city":"Winterport",
    "sg:classifiers":[
        {
            "category":"Arts & Performance",
            "subcategory":"Theater",
            "type":"Entertainment"
        }
    ],
    "sg:phone":"+1 207 223 4953",
    "sg:postcode":"04496",
    "sg:province":"ME",
    "sg:tags":[
        "live",
        "music"
    ],
    "wof:name":"AAA-DJ Rich Howard",
    "wof:placetype":"venue"
},
  "geometry": {"coordinates":[-68.843002,44.636079],"type":"Point"}
}