{
  "type": "Feature",
  "properties": {
    "addr:full":"170 Ocean St South Portland ME 04106",
    "addr:housenumber":"170",
    "addr:postcode":"04106",
    "addr:street":"Ocean St",
    "iso:country":"US",
    "sg:address":"170 Ocean St",
    "sg:city":"South Portland",
    "sg:classifiers":[
        {
            "category":"Professional",
            "subcategory":"Lawyer & Legal Services",
            "type":"Services"
        }
    ],
    "sg:phone":"+1 207 799 8485",
    "sg:postcode":"04106",
    "sg:province":"ME",
    "sg:tags":[
        "attorney"
    ],
    "sg:website":"www.mainecounsel.com",
    "wof:name":"Metropolitan Legal Ctr",
    "wof:placetype":"venue"
},
  "geometry": {"coordinates":[-70.25264799999999,43.636705],"type":"Point"}
}