{
  "type": "Feature",
  "properties": {
    "iso:country":"US",
    "sg:address":"32 Cummings Rd",
    "sg:city":"Buxton",
    "sg:classifiers":[
        {
            "category":"Building & Trades",
            "subcategory":"Construction",
            "type":"Services"
        }
    ],
    "sg:phone":"+1 207 642 3754",
    "sg:postcode":"04106",
    "sg:province":"ME",
    "sg:tags":[
        "general",
        "contractor"
    ],
    "wof:name":"Done With Care Construction",
    "wof:placetype":"venue"
},
  "geometry": {"coordinates":[-70.349419,43.63352],"type":"Point"}
}