{
  "type": "Feature",
  "properties": {
    "addr:full":"559 New Sweden Rd New Sweden ME 04762",
    "addr:housenumber":"559",
    "addr:postcode":"04762",
    "addr:street":"New Sweden Rd",
    "iso:country":"US",
    "sg:address":"559 New Sweden Rd",
    "sg:city":"New Sweden",
    "sg:classifiers":[
        {
            "category":"Autos & Motor Vehicles",
            "subcategory":"Automobile Sales",
            "type":"Retail Goods"
        }
    ],
    "sg:phone":"+1 207 492 5281",
    "sg:postcode":"04762",
    "sg:province":"ME",
    "sg:tags":[
        "snowmobile"
    ],
    "wof:name":"Red's Recreational Rentals",
    "wof:placetype":"venue"
},
  "geometry": {"coordinates":[-68.13308600000001,46.942108],"type":"Point"}
}