{
  "type": "Feature",
  "properties": {
    "addr:full":"379 Limestone Rd Fort Fairfield ME 04742",
    "addr:housenumber":"379",
    "addr:postcode":"04742",
    "addr:street":"Limestone Rd",
    "iso:country":"US",
    "sg:address":"379 Limestone Rd",
    "sg:city":"Fort Fairfield",
    "sg:phone":"+1 207 472 3632",
    "sg:postcode":"04742",
    "sg:province":"ME",
    "sg:tags":[
        "grower",
        "potato"
    ],
    "wof:name":"Steve Bubar Potato House",
    "wof:placetype":"venue"
},
  "geometry": {"coordinates":[-67.81188899999999,46.816494],"type":"Point"}
}