{
  "type": "Feature",
  "properties": {
    "addr:full":"639 Riverside St Portland ME 04103",
    "addr:housenumber":"639",
    "addr:postcode":"04103",
    "addr:street":"Riverside St",
    "iso:country":"US",
    "sg:address":"639 Riverside St",
    "sg:city":"Portland",
    "sg:classifiers":[
        {
            "category":"Real Estate",
            "subcategory":"Real Estate Agent",
            "type":"Services"
        }
    ],
    "sg:phone":"+1 207 797 0743",
    "sg:postcode":"04103",
    "sg:province":"ME",
    "sg:tags":[
        "management"
    ],
    "wof:name":"Klearview Properties",
    "wof:placetype":"venue"
},
  "geometry": {"coordinates":[-70.324732,43.694149],"type":"Point"}
}