{
  "type": "Feature",
  "properties": {
    "addr:full":"7 Falcon Ridge Biddeford ME 04005",
    "addr:housenumber":"7",
    "addr:postcode":"04005",
    "addr:street":"Falcon Ridge",
    "iso:country":"US",
    "sg:address":"7 Falcon Ridge",
    "sg:city":"Biddeford",
    "sg:classifiers":[
        {
            "category":"Building & Trades",
            "subcategory":"Plumbing",
            "type":"Services"
        }
    ],
    "sg:phone":"+1 207 284 1705",
    "sg:postcode":"04005",
    "sg:province":"ME",
    "sg:tags":[
        "heating",
        "contractor"
    ],
    "wof:name":"Four Seasons Plumbing & Htg",
    "wof:placetype":"venue"
},
  "geometry": {"coordinates":[-70.524519,43.48114],"type":"Point"}
}