{
  "type": "Feature",
  "properties": {
    "addr:full":"86 Summit St Baileyville ME 04694",
    "addr:housenumber":"86",
    "addr:postcode":"04694",
    "addr:street":"Summit St",
    "iso:country":"US",
    "sg:address":"86 Summit St",
    "sg:city":"Baileyville",
    "sg:classifiers":[
        {
            "category":"Organizations",
            "subcategory":"Religious Organization",
            "type":"Services"
        }
    ],
    "sg:phone":"+1 207 427 6672",
    "sg:postcode":"04694",
    "sg:province":"ME",
    "wof:name":"Methodist Church Parsng",
    "wof:placetype":"venue"
},
  "geometry": {"coordinates":[-67.40899899999999,45.156872],"type":"Point"}
}