{
  "type": "Feature",
  "properties": {
    "iso:country":"US",
    "sg:address":"96 Highland Ter",
    "sg:city":"Mexico",
    "sg:classifiers":[
        {
            "category":"Shopping",
            "subcategory":"Discount & Variety Stores",
            "type":"Retail Goods"
        }
    ],
    "sg:phone":"+1 207 364 3372",
    "sg:postcode":"04257",
    "sg:province":"ME",
    "sg:tags":[
        "merchandise",
        "general"
    ],
    "wof:name":"Watkins Products",
    "wof:placetype":"venue"
},
  "geometry": {"coordinates":[-70.525004,44.553931],"type":"Point"}
}