{
  "type": "Feature",
  "properties": {
    "iso:country":"US",
    "sg:address":"6 Evening Pl",
    "sg:city":"Kennebunkport",
    "sg:classifiers":[
        {
            "category":"Building & Trades",
            "subcategory":"Construction",
            "type":"Services"
        }
    ],
    "sg:phone":"+1 207 284 5541",
    "sg:postcode":"04046",
    "sg:province":"ME",
    "sg:tags":[
        "painter"
    ],
    "wof:name":"Dave Labonte Painting Contr",
    "wof:placetype":"venue"
},
  "geometry": {"coordinates":[-70.45455,43.370271],"type":"Point"}
}