{
  "type": "Feature",
  "properties": {
    "addr:full":"88 McSheffery Rd Houlton ME 04730",
    "addr:housenumber":"88",
    "addr:postcode":"04730",
    "addr:street":"Mcsheffery Rd",
    "iso:country":"US",
    "sg:address":"88 McSheffery Rd",
    "sg:city":"Houlton",
    "sg:classifiers":[
        {
            "category":"Health Services",
            "subcategory":"Doctor",
            "type":"Services"
        }
    ],
    "sg:phone":"+1 207 532 4747",
    "sg:postcode":"04730",
    "sg:province":"ME",
    "sg:tags":[
        "dentist"
    ],
    "wof:name":"Karl P Woods DDS",
    "wof:placetype":"venue"
},
  "geometry": {"coordinates":[-67.862256,46.144819],"type":"Point"}
}