{
  "type": "Feature",
  "properties": {
    "addr:full":"100 Main St Winthrop ME 04364",
    "addr:housenumber":"100",
    "addr:postcode":"04364",
    "addr:street":"Main St",
    "iso:country":"US",
    "sg:address":"100 Main St",
    "sg:city":"Winthrop",
    "sg:classifiers":[
        {
            "category":"Shopping",
            "subcategory":"Hobbies, Toys, & Games",
            "type":"Retail Goods"
        }
    ],
    "sg:phone":"+1 207 377 8697",
    "sg:postcode":"04364",
    "sg:province":"ME",
    "wof:name":"K & M Toys Collectible Hobbies",
    "wof:placetype":"venue"
},
  "geometry": {"coordinates":[-69.960803,44.307409],"type":"Point"}
}