{
  "type": "Feature",
  "properties": {
    "addr:full":"208 Kittredge Rd Bangor ME 04401",
    "addr:housenumber":"208",
    "addr:postcode":"04401",
    "addr:street":"Kittredge Rd",
    "iso:country":"US",
    "sg:address":"208 Kittredge Rd",
    "sg:city":"Bangor",
    "sg:phone":"+1 207 947 8103",
    "sg:postcode":"04401",
    "sg:province":"ME",
    "sg:tags":[
        "oil"
    ],
    "wof:name":"Davis Oil",
    "wof:placetype":"venue"
},
  "geometry": {"coordinates":[-68.743351,44.853575],"type":"Point"}
}