{
  "type": "Feature",
  "properties": {
    "addr:full":"243 Brownfield Rd Hiram ME 04041",
    "addr:housenumber":"243",
    "addr:postcode":"04041",
    "addr:street":"Brownfield Rd",
    "iso:country":"US",
    "sg:address":"243 Brownfield Rd",
    "sg:city":"Hiram",
    "sg:classifiers":[
        {
            "category":"Building & Trades",
            "subcategory":"Construction",
            "type":"Services"
        }
    ],
    "sg:phone":"+1 207 625 3339",
    "sg:postcode":"04041",
    "sg:province":"ME",
    "sg:tags":[
        "excavation",
        "contractor"
    ],
    "wof:name":"B & G Construction",
    "wof:placetype":"venue"
},
  "geometry": {"coordinates":[-70.88434100000001,43.828225],"type":"Point"}
}