{
  "type": "Feature",
  "properties": {
    "addr:full":"620 Main St South Portland ME 04106",
    "addr:housenumber":"620",
    "addr:postcode":"04106",
    "addr:street":"Main St",
    "iso:country":"US",
    "sg:address":"620 Main St",
    "sg:city":"South Portland",
    "sg:classifiers":[
        {
            "category":"Retail",
            "subcategory":"Auto Repair",
            "type":"Services"
        }
    ],
    "sg:phone":"+1 207 772 4979",
    "sg:postcode":"04106",
    "sg:province":"ME",
    "wof:name":"Waterman's Exxon Service Center",
    "wof:placetype":"venue"
},
  "geometry": {"coordinates":[-70.303596,43.621498],"type":"Point"}
}