{
  "type": "Feature",
  "properties": {
    "addr:full":"28 Wing Rd Bingham ME 04926",
    "addr:housenumber":"28",
    "addr:postcode":"04926",
    "addr:street":"Wing Rd",
    "iso:country":"US",
    "sg:address":"28 Wing Rd",
    "sg:city":"Bingham",
    "sg:classifiers":[
        {
            "category":"Manufacturing",
            "subcategory":"Lumber",
            "type":"Manufacturing & Wholesale Goods"
        }
    ],
    "sg:phone":"+1 207 672 5533",
    "sg:postcode":"04926",
    "sg:province":"ME",
    "sg:tags":[
        "planing",
        "mills",
        "sawmill"
    ],
    "wof:name":"Morgan Lumber Inc",
    "wof:placetype":"venue"
},
  "geometry": {"coordinates":[-69.504088,44.353568],"type":"Point"}
}