{
  "type": "Feature",
  "properties": {
    "addr:full":"150 Riverside Industrial Pkwy Portland ME 04103",
    "addr:housenumber":"150",
    "addr:postcode":"04103",
    "addr:street":"Riverside Industrial Pkwy",
    "iso:country":"US",
    "sg:address":"150 Riverside Industrial Pkwy",
    "sg:city":"Portland",
    "sg:classifiers":[
        {
            "category":"Autos & Motor Vehicles",
            "subcategory":"Recreational Vehicle Sales",
            "type":"Retail Goods"
        }
    ],
    "sg:phone":"+1 207 797 0323",
    "sg:postcode":"04103",
    "sg:province":"ME",
    "sg:tags":[
        "canopy",
        "shell",
        "truck",
        "cap"
    ],
    "wof:name":"R H Scales Co",
    "wof:placetype":"venue"
},
  "geometry": {"coordinates":[-70.309325,43.70551],"type":"Point"}
}