{
  "type": "Feature",
  "properties": {
    "addr:full":"16 Court St Machias ME 04654",
    "addr:housenumber":"16",
    "addr:postcode":"04654",
    "addr:street":"Court St",
    "iso:country":"US",
    "sg:address":"16 Court St",
    "sg:city":"Machias",
    "sg:classifiers":[
        {
            "category":"Organizations",
            "subcategory":"Community Association",
            "type":"Services"
        }
    ],
    "sg:phone":"+1 207 255 8665",
    "sg:postcode":"04654",
    "sg:province":"ME",
    "sg:tags":[
        "military"
    ],
    "wof:name":"American Legion",
    "wof:placetype":"venue"
},
  "geometry": {"coordinates":[-67.455714,44.717078],"type":"Point"}
}