{
  "type": "Feature",
  "properties": {
    "addr:full":"20 Park St Milo ME 04463",
    "addr:housenumber":"20",
    "addr:postcode":"04463",
    "addr:street":"Park St",
    "iso:country":"US",
    "sg:address":"20 Park St",
    "sg:city":"Milo",
    "sg:classifiers":[
        {
            "category":"Restaurant",
            "type":"Food & Drink"
        }
    ],
    "sg:phone":"+1 207 943 2006",
    "sg:postcode":"04463",
    "sg:province":"ME",
    "sg:tags":[
        "pizza"
    ],
    "wof:name":"Pats Pizza",
    "wof:placetype":"venue"
},
  "geometry": {"coordinates":[-68.98675900000001,45.254898],"type":"Point"}
}