{
  "type": "Feature",
  "properties": {
    "iso:country":"US",
    "sg:address":"241 Commercial St",
    "sg:city":"Portland",
    "sg:classifiers":[
        {
            "category":"Travel",
            "subcategory":"Travel Agent",
            "type":"Entertainment"
        }
    ],
    "sg:phone":"+1 207 775 2626",
    "sg:postcode":"04101",
    "sg:province":"ME",
    "sg:tags":[
        "agency",
        "steamship"
    ],
    "sg:website":"www.portlandsteamship.com",
    "wof:name":"Portland Steamship Agency",
    "wof:placetype":"venue"
},
  "geometry": {"coordinates":[-70.254869,43.654605],"type":"Point"}
}