{
  "type": "Feature",
  "properties": {
    "addr:full":"46 Clark Rd Bangor ME 04401",
    "addr:housenumber":"46",
    "addr:postcode":"04401",
    "addr:street":"Clark Rd",
    "iso:country":"US",
    "sg:address":"46 Clark Rd",
    "sg:city":"Bangor",
    "sg:classifiers":[
        {
            "category":"Manufacturing",
            "subcategory":"Lumber",
            "type":"Manufacturing & Wholesale Goods"
        }
    ],
    "sg:phone":"+1 207 884 8699",
    "sg:postcode":"04401",
    "sg:province":"ME",
    "sg:tags":[
        "logging"
    ],
    "wof:name":"Allards Logging",
    "wof:placetype":"venue"
},
  "geometry": {"coordinates":[-68.913588,44.859574],"type":"Point"}
}