{
  "type": "Feature",
  "properties": {
    "addr:full":"132 Main St Bridgton ME 04009",
    "addr:housenumber":"132",
    "addr:postcode":"04009",
    "addr:street":"Main St",
    "iso:country":"US",
    "sg:address":"132 Main St",
    "sg:city":"Bridgton",
    "sg:classifiers":[
        {
            "category":"Banks & Credit Unions",
            "subcategory":"Investment Brokerage",
            "type":"Services"
        }
    ],
    "sg:phone":"+1 207 647 3804",
    "sg:postcode":"04009",
    "sg:province":"ME",
    "sg:tags":[
        "advisory",
        "financial"
    ],
    "wof:name":"Freedom Financial",
    "wof:placetype":"venue"
},
  "geometry": {"coordinates":[-70.702033,44.054156],"type":"Point"}
}