{
  "type": "Feature",
  "properties": {
    "addr:full":"24 Curtis Rd Yarmouth ME 04096",
    "addr:housenumber":"24",
    "addr:postcode":"04096",
    "addr:street":"Curtis Rd",
    "iso:country":"US",
    "sg:address":"24 Curtis Rd",
    "sg:city":"Yarmouth",
    "sg:classifiers":[
        {
            "category":"Professional",
            "type":"Services"
        }
    ],
    "sg:phone":"+1 207 846 6990",
    "sg:postcode":"04096",
    "sg:province":"ME",
    "sg:tags":[
        "establishment"
    ],
    "wof:name":"X-Ray Co Affiliated",
    "wof:placetype":"venue"
},
  "geometry": {"coordinates":[-70.167074,43.771147],"type":"Point"}
}