{
  "type": "Feature",
  "properties": {
    "iso:country":"US",
    "sg:address":"2 Washington Ave",
    "sg:city":"Scarborough",
    "sg:classifiers":[
        {
            "category":"Manufacturing",
            "subcategory":"Metals",
            "type":"Manufacturing & Wholesale Goods"
        }
    ],
    "sg:phone":"+1 207 883 3877",
    "sg:postcode":"04074",
    "sg:province":"ME",
    "sg:tags":[
        "fabricator",
        "sheet"
    ],
    "wof:name":"Zeke's Sheet Metal",
    "wof:placetype":"venue"
},
  "geometry": {"coordinates":[-70.358278,43.579443],"type":"Point"}
}