{
  "type": "Feature",
  "properties": {
    "addr:full":"36 Two Lights Rd Cape Elizabeth ME 04107",
    "addr:housenumber":"36",
    "addr:postcode":"04107",
    "addr:street":"Two Lights Rd",
    "iso:country":"US",
    "sg:address":"36 Two Lights Rd",
    "sg:city":"Cape Elizabeth",
    "sg:classifiers":[
        {
            "category":"Organizations",
            "subcategory":"Non-profit Organization",
            "type":"Services"
        }
    ],
    "sg:phone":"+1 207 767 1225",
    "sg:postcode":"04107",
    "sg:province":"ME",
    "sg:tags":[
        "consulting",
        "management",
        "social"
    ],
    "wof:name":"Lodestar Inc",
    "wof:placetype":"venue"
},
  "geometry": {"coordinates":[-70.217187,43.567392],"type":"Point"}
}