{
  "type": "Feature",
  "properties": {
    "iso:country":"US",
    "sg:address":"268 Pinkham Brook Rd",
    "sg:city":"Durham",
    "sg:classifiers":[
        {
            "category":"Retail",
            "subcategory":"Auto Repair",
            "type":"Services"
        }
    ],
    "sg:phone":"+1 207 353 6043",
    "sg:postcode":"04222",
    "sg:province":"ME",
    "sg:tags":[
        "body",
        "automobile",
        "painting"
    ],
    "wof:name":"Glenn's Body Shop",
    "wof:placetype":"venue"
},
  "geometry": {"coordinates":[-70.059943,43.976947],"type":"Point"}
}