{
  "type": "Feature",
  "properties": {
    "iso:country":"US",
    "sg:address":"95 Bayview Rd",
    "sg:city":"Saco",
    "sg:classifiers":[
        {
            "category":"Recreation",
            "type":"Entertainment"
        }
    ],
    "sg:phone":"+1 207 283 0067",
    "sg:postcode":"04072",
    "sg:province":"ME",
    "sg:tags":[
        "parks"
    ],
    "wof:name":"Ferry Beach State Park",
    "wof:placetype":"venue"
},
  "geometry": {"coordinates":[-70.393187,43.481483],"type":"Point"}
}