{
  "type": "Feature",
  "properties": {
    "addr:full":"18 Hancock St Ellsworth ME 04605",
    "addr:housenumber":"18",
    "addr:postcode":"04605",
    "addr:street":"Hancock St",
    "iso:country":"US",
    "sg:address":"18 Hancock St",
    "sg:city":"Ellsworth",
    "sg:classifiers":[
        {
            "category":"Restaurant",
            "type":"Food & Drink"
        }
    ],
    "sg:phone":"+1 207 667 3189",
    "sg:postcode":"04605",
    "sg:province":"ME",
    "sg:tags":[
        "pizza"
    ],
    "wof:name":"Charlie's Pizza & Sub Shop",
    "wof:placetype":"venue"
},
  "geometry": {"coordinates":[-68.421993,44.541142],"type":"Point"}
}