{
  "type": "Feature",
  "properties": {
    "addr:full":"402 Mitchell Rd Cape Elizabeth ME 04107",
    "addr:housenumber":"402",
    "addr:postcode":"04107",
    "addr:street":"Mitchell Rd",
    "iso:country":"US",
    "sg:address":"402 Mitchell Rd",
    "sg:city":"Cape Elizabeth",
    "sg:classifiers":[
        {
            "category":"Professional",
            "subcategory":"Secretarial Services",
            "type":"Services"
        }
    ],
    "sg:phone":"+1 207 741 5174",
    "sg:postcode":"04107",
    "sg:province":"ME",
    "sg:tags":[
        "reporting"
    ],
    "wof:name":"Transcription & Word Proc",
    "wof:placetype":"venue"
},
  "geometry": {"coordinates":[-70.23051100000001,43.614696],"type":"Point"}
}