{
  "type": "Feature",
  "properties": {
    "iso:country":"US",
    "sg:address":"39 Main St",
    "sg:city":"Lincolnville",
    "sg:classifiers":[
        {
            "category":"Home & Garden",
            "subcategory":"Garden Supply",
            "type":"Retail Goods"
        }
    ],
    "sg:phone":"+1 207 236 8536",
    "sg:postcode":"04849",
    "sg:province":"ME",
    "wof:name":"Janis A Kay",
    "wof:placetype":"venue"
},
  "geometry": {"coordinates":[-68.96932200000001,44.378844],"type":"Point"}
}