{
  "type": "Feature",
  "properties": {
    "addr:full":"31 Main St Stonington ME 04694",
    "addr:housenumber":"31",
    "addr:postcode":"04694",
    "addr:street":"Main St",
    "iso:country":"US",
    "sg:address":"31 Main St",
    "sg:city":"Stonington",
    "sg:classifiers":[
        {
            "category":"Shopping",
            "subcategory":"Used Merchandise",
            "type":"Retail Goods"
        }
    ],
    "sg:phone":"+1 207 367 5821",
    "sg:postcode":"04694",
    "sg:province":"ME",
    "sg:tags":[
        "book",
        "rare",
        "dealer"
    ],
    "wof:name":"Prints & Reprints",
    "wof:placetype":"venue"
},
  "geometry": {"coordinates":[-67.405028,45.154948],"type":"Point"}
}