{
  "type": "Feature",
  "properties": {
    "addr:full":"3 Osgood Farm Rd Easton ME 04740",
    "addr:housenumber":"3",
    "addr:postcode":"04740",
    "addr:street":"Osgood Farm Rd",
    "iso:country":"US",
    "sg:address":"3 Osgood Farm Rd",
    "sg:city":"Easton",
    "sg:classifiers":[
        {
            "category":"Professional",
            "subcategory":"Computer Services",
            "type":"Services"
        }
    ],
    "sg:phone":"+1 207 488 6098",
    "sg:postcode":"04740",
    "sg:province":"ME",
    "sg:tags":[
        "repair"
    ],
    "wof:name":"Computer Things",
    "wof:placetype":"venue"
},
  "geometry": {"coordinates":[-67.911981,46.637254],"type":"Point"}
}