{
  "type": "Feature",
  "properties": {
    "addr:full":"34 Western Ave Fairfield ME 04937",
    "addr:housenumber":"34",
    "addr:postcode":"04937",
    "addr:street":"Western Ave",
    "iso:country":"US",
    "sg:address":"34 Western Ave",
    "sg:city":"Fairfield",
    "sg:classifiers":[
        {
            "category":"Shopping",
            "subcategory":"Used Merchandise",
            "type":"Retail Goods"
        }
    ],
    "sg:phone":"+1 207 453 9022",
    "sg:postcode":"04937",
    "sg:province":"ME",
    "wof:name":"88 Pieces of Eight",
    "wof:placetype":"venue"
},
  "geometry": {"coordinates":[-69.598472,44.591319],"type":"Point"}
}