{
  "type": "Feature",
  "properties": {
    "addr:full":"41 W Main St Milo ME 04463",
    "addr:housenumber":"41",
    "addr:postcode":"04463",
    "addr:street":"W Main St",
    "iso:country":"US",
    "sg:address":"41 W Main St",
    "sg:city":"Milo",
    "sg:classifiers":[
        {
            "category":"Organizations",
            "subcategory":"Community Association",
            "type":"Services"
        }
    ],
    "sg:phone":"+1 207 943 2542",
    "sg:postcode":"04463",
    "sg:province":"ME",
    "sg:tags":[
        "military"
    ],
    "wof:name":"American Legion",
    "wof:placetype":"venue"
},
  "geometry": {"coordinates":[-68.993788,45.24941],"type":"Point"}
}