{
  "type": "Feature",
  "properties": {
    "addr:full":"12 Airport Dr Caribou ME 04769",
    "addr:housenumber":"12",
    "addr:postcode":"04769",
    "addr:street":"Airport Dr",
    "iso:country":"US",
    "sg:address":"12 Airport Dr",
    "sg:city":"Caribou",
    "sg:classifiers":[
        {
            "category":"Airport",
            "type":"Transportation"
        }
    ],
    "sg:phone":"+1 207 493 4237",
    "sg:postcode":"04769",
    "sg:province":"ME",
    "wof:name":"Fresh Air LLC",
    "wof:placetype":"venue"
},
  "geometry": {"coordinates":[-68.03046999999999,46.692373],"type":"Point"}
}