{
  "type": "Feature",
  "properties": {
    "iso:country":"US",
    "sg:address":"667 Civic Center Dr",
    "sg:city":"Augusta",
    "sg:classifiers":[
        {
            "category":"Building & Trades",
            "subcategory":"Construction",
            "type":"Services"
        }
    ],
    "sg:phone":"+1 207 623 2372",
    "sg:postcode":"04330",
    "sg:province":"ME",
    "sg:tags":[
        "contractor"
    ],
    "wof:name":"Paradis Builders",
    "wof:placetype":"venue"
},
  "geometry": {"coordinates":[-69.793907,44.372232],"type":"Point"}
}