{
  "type": "Feature",
  "properties": {
    "addr:full":"544 Congress St Portland ME 04101",
    "addr:housenumber":"544",
    "addr:postcode":"04101",
    "addr:street":"Congress St",
    "iso:country":"US",
    "sg:address":"544 Congress St",
    "sg:city":"Portland",
    "sg:classifiers":[
        {
            "category":"Shopping",
            "subcategory":"Bicycles & Sporting Goods",
            "type":"Retail Goods"
        }
    ],
    "sg:phone":"+1 207 772 7828",
    "sg:postcode":"04101",
    "sg:province":"ME",
    "wof:name":"Olympia Sports",
    "wof:placetype":"venue"
},
  "geometry": {"coordinates":[-70.26133400000001,43.655781],"type":"Point"}
}