{
  "type": "Feature",
  "properties": {
    "addr:full":"45 Middle Rd Falmouth ME 04105",
    "addr:housenumber":"45",
    "addr:postcode":"04105",
    "addr:street":"Middle Rd",
    "iso:country":"US",
    "sg:address":"45 Middle Rd",
    "sg:city":"Falmouth",
    "sg:classifiers":[
        {
            "category":"Home & Garden",
            "subcategory":"Carpets & Floor Coverings",
            "type":"Retail Goods"
        }
    ],
    "sg:phone":"+1 207 775 1600",
    "sg:postcode":"04105",
    "sg:province":"ME",
    "sg:tags":[
        "dealer",
        "rug"
    ],
    "sg:website":"www.hardciderfarm.com",
    "wof:name":"Hard Cider Farm Oriental Rugs",
    "wof:placetype":"venue"
},
  "geometry": {"coordinates":[-70.25885599999999,43.706381],"type":"Point"}
}