{
  "type": "Feature",
  "properties": {
    "iso:country":"US",
    "sg:address":"55 Herschel St",
    "sg:city":"Caribou",
    "sg:classifiers":[
        {
            "category":"Retail",
            "subcategory":"Auto Repair",
            "type":"Services"
        }
    ],
    "sg:phone":"+1 207 496 6431",
    "sg:postcode":"04736",
    "sg:province":"ME",
    "sg:tags":[
        "wrecker"
    ],
    "wof:name":"Roland's Auto Repair Ctr",
    "wof:placetype":"venue"
},
  "geometry": {"coordinates":[-68.013903,46.861064],"type":"Point"}
}