{
  "type": "Feature",
  "properties": {
    "iso:country":"US",
    "sg:address":"297 Main St",
    "sg:city":"Greenwood",
    "sg:classifiers":[
        {
            "category":"Manufacturing",
            "subcategory":"Pottery",
            "type":"Manufacturing & Wholesale Goods"
        }
    ],
    "sg:phone":"+1 207 875 2522",
    "sg:postcode":"04252",
    "sg:province":"ME",
    "sg:website":"www.mainelineproducts.com",
    "wof:name":"Maine Line Products",
    "wof:placetype":"venue"
},
  "geometry": {"coordinates":[-70.037701,44.030507],"type":"Point"}
}