{
  "type": "Feature",
  "properties": {
    "addr:full":"26 Lower Beach Rd Saco ME 04072",
    "addr:housenumber":"26",
    "addr:postcode":"04072",
    "addr:street":"Lower Beach Rd",
    "iso:country":"US",
    "sg:address":"26 Lower Beach Rd",
    "sg:city":"Saco",
    "sg:classifiers":[
        {
            "category":"Professional",
            "subcategory":"Engineering",
            "type":"Services"
        }
    ],
    "sg:phone":"+1 207 282 2135",
    "sg:postcode":"04072",
    "sg:province":"ME",
    "sg:tags":[
        "management"
    ],
    "wof:name":"Saco Technolgy Corporation",
    "wof:placetype":"venue"
},
  "geometry": {"coordinates":[-70.382526,43.466616],"type":"Point"}
}