{
  "type": "Feature",
  "properties": {
    "addr:full":"144 Puddledock Rd Charleston ME 04422",
    "addr:housenumber":"144",
    "addr:postcode":"04422",
    "addr:street":"Puddledock Rd",
    "iso:country":"US",
    "sg:address":"144 Puddledock Rd",
    "sg:city":"Charleston",
    "sg:classifiers":[
        {
            "category":"Travel",
            "subcategory":"Campground",
            "type":"Entertainment"
        }
    ],
    "sg:phone":"+1 207 285 3535",
    "sg:postcode":"04422",
    "sg:province":"ME",
    "wof:name":"Penobscot Valley Acres Cmpgrnd",
    "wof:placetype":"venue"
},
  "geometry": {"coordinates":[-68.978872,45.049022],"type":"Point"}
}