{
  "type": "Feature",
  "properties": {
    "iso:country":"US",
    "sg:address":"366 Water St",
    "sg:city":"Gardiner",
    "sg:classifiers":[
        {
            "category":"Retail",
            "subcategory":"Portrait Studio",
            "type":"Services"
        }
    ],
    "sg:phone":"+1 207 582 0516",
    "sg:postcode":"04345",
    "sg:province":"ME",
    "sg:tags":[
        "photographer"
    ],
    "sg:website":"www.lifetouch.com",
    "wof:name":"Lifetouch National Schl Studio",
    "wof:placetype":"venue"
},
  "geometry": {"coordinates":[-69.774829,44.229874],"type":"Point"}
}