{
  "type": "Feature",
  "properties": {
    "addr:full":"14 Maine St Brunswick ME 04011",
    "addr:housenumber":"14",
    "addr:postcode":"04011",
    "addr:street":"Maine St",
    "iso:country":"US",
    "sg:address":"14 Maine St",
    "sg:city":"Brunswick",
    "sg:classifiers":[
        {
            "category":"Utilities",
            "subcategory":"Electric",
            "type":"Services"
        }
    ],
    "sg:phone":"+1 207 729 0420",
    "sg:postcode":"04011",
    "sg:province":"ME",
    "sg:tags":[
        "company"
    ],
    "sg:website":"www.mainenaturalgas.com",
    "wof:name":"Maine Natural Gas",
    "wof:placetype":"venue"
},
  "geometry": {"coordinates":[-69.96648,43.919475],"type":"Point"}
}