{
  "type": "Feature",
  "properties": {
    "iso:country":"US",
    "sg:address":"13 River St",
    "sg:city":"Sanford",
    "sg:classifiers":[
        {
            "category":"Building & Trades",
            "subcategory":"Construction",
            "type":"Services"
        }
    ],
    "sg:phone":"+1 207 459 7955",
    "sg:postcode":"04073",
    "sg:province":"ME",
    "sg:tags":[
        "hanging",
        "contractor"
    ],
    "wof:name":"J & J Finishing",
    "wof:placetype":"venue"
},
  "geometry": {"coordinates":[-70.773455,43.44185],"type":"Point"}
}