{
  "type": "Feature",
  "properties": {
    "iso:country":"US",
    "sg:address":"42 Turtle Cove Rd",
    "sg:city":"Raymond",
    "sg:classifiers":[
        {
            "category":"Building & Trades",
            "subcategory":"Electrical",
            "type":"Services"
        }
    ],
    "sg:phone":"+1 207 655 3282",
    "sg:postcode":"04071",
    "sg:province":"ME",
    "sg:tags":[
        "electric",
        "contractor"
    ],
    "wof:name":"Bennett Electric Inc",
    "wof:placetype":"venue"
},
  "geometry": {"coordinates":[-70.498688,43.895661],"type":"Point"}
}