{
  "type": "Feature",
  "properties": {
    "iso:country":"US",
    "sg:address":"76 Bryant Rd",
    "sg:city":"Buckfield",
    "sg:classifiers":[
        {
            "category":"Retail",
            "subcategory":"Auto Repair",
            "type":"Services"
        }
    ],
    "sg:phone":"+1 207 336 3881",
    "sg:postcode":"04220",
    "sg:province":"ME",
    "sg:tags":[
        "wrecker"
    ],
    "wof:name":"Douglass 24 Hr Towing",
    "wof:placetype":"venue"
},
  "geometry": {"coordinates":[-70.324274,44.268972],"type":"Point"}
}