{
  "type": "Feature",
  "properties": {
    "iso:country":"US",
    "sg:address":"86 Main St",
    "sg:city":"Mars Hill",
    "sg:classifiers":[
        {
            "category":"Personal",
            "subcategory":"Beauty Salon",
            "type":"Services"
        }
    ],
    "sg:phone":"+1 207 425 4283",
    "sg:postcode":"04743",
    "sg:province":"ME",
    "wof:name":"Hair By Design",
    "wof:placetype":"venue"
},
  "geometry": {"coordinates":[-68.582224,47.244299],"type":"Point"}
}