{
  "type": "Feature",
  "properties": {
    "iso:country":"US",
    "sg:address":"366 Turner St",
    "sg:city":"Buckfield",
    "sg:classifiers":[
        {
            "category":"Professional",
            "subcategory":"Computer Services",
            "type":"Services"
        }
    ],
    "sg:phone":"+1 207 336 3659",
    "sg:postcode":"04220",
    "sg:province":"ME",
    "sg:tags":[
        "repair"
    ],
    "wof:name":"Computer This",
    "wof:placetype":"venue"
},
  "geometry": {"coordinates":[-70.33600199999999,44.278839],"type":"Point"}
}