{
  "type": "Feature",
  "properties": {
    "iso:country":"US",
    "sg:address":"40 Mountain View Dr",
    "sg:city":"Oxford",
    "sg:classifiers":[
        {
            "category":"Building & Trades",
            "subcategory":"Pest Control",
            "type":"Services"
        }
    ],
    "sg:phone":"+1 207 583 4221",
    "sg:postcode":"04270",
    "sg:province":"ME",
    "wof:name":"H & G Pest Control",
    "wof:placetype":"venue"
},
  "geometry": {"coordinates":[-70.595398,44.103225],"type":"Point"}
}