{
  "type": "Feature",
  "properties": {
    "iso:country":"US",
    "sg:address":"136 Main St",
    "sg:city":"Winterport",
    "sg:classifiers":[
        {
            "category":"Banks & Credit Unions",
            "subcategory":"Bank",
            "type":"Services"
        }
    ],
    "sg:phone":"+1 207 223 5403",
    "sg:postcode":"04496",
    "sg:province":"ME",
    "sg:tags":[
        "loan"
    ],
    "wof:name":"United Kingfield Bank",
    "wof:placetype":"venue"
},
  "geometry": {"coordinates":[-68.84541900000001,44.637505],"type":"Point"}
}