{
  "type": "Feature",
  "properties": {
    "addr:full":"35 North St Houlton ME 04730",
    "addr:housenumber":"35",
    "addr:postcode":"04730",
    "addr:street":"North St",
    "iso:country":"US",
    "sg:address":"35 North St",
    "sg:city":"Houlton",
    "sg:classifiers":[
        {
            "category":"Restaurant",
            "type":"Food & Drink"
        }
    ],
    "sg:menulink":"http://www.allmenus.com/me/houlton/119817-subway/menu/",
    "sg:phone":"+1 207 532 6233",
    "sg:postcode":"04730",
    "sg:province":"ME",
    "sg:tags":[
        "american",
        "sandwich"
    ],
    "wof:name":"Subway",
    "wof:placetype":"venue"
},
  "geometry": {"coordinates":[-67.84195800000001,46.12842],"type":"Point"}
}