{
  "type": "Feature",
  "properties": {
    "addr:full":"305 Main St East Waterboro ME 04072",
    "addr:housenumber":"305",
    "addr:postcode":"04072",
    "addr:street":"Main St",
    "iso:country":"US",
    "sg:address":"305 Main St",
    "sg:city":"East Waterboro",
    "sg:classifiers":[
        {
            "category":"Personal",
            "subcategory":"Barber",
            "type":"Services"
        }
    ],
    "sg:phone":"+1 207 247 5747",
    "sg:postcode":"04072",
    "sg:province":"ME",
    "wof:name":"Barbershop",
    "wof:placetype":"venue"
},
  "geometry": {"coordinates":[-70.438,43.506018],"type":"Point"}
}