{
  "type": "Feature",
  "properties": {
    "iso:country":"US",
    "sg:address":"1672 Ohio St",
    "sg:city":"Bangor",
    "sg:classifiers":[
        {
            "category":"Building & Trades",
            "subcategory":"Electrical",
            "type":"Services"
        }
    ],
    "sg:phone":"+1 207 942 3719",
    "sg:postcode":"04401",
    "sg:province":"ME",
    "sg:tags":[
        "electrical",
        "contractor"
    ],
    "wof:name":"Rek Electric",
    "wof:placetype":"venue"
},
  "geometry": {"coordinates":[-68.833429,44.843133],"type":"Point"}
}