{
  "type": "Feature",
  "properties": {
    "addr:full":"5 Riverside Ave Mexico ME 04257",
    "addr:housenumber":"5",
    "addr:postcode":"04257",
    "addr:street":"Riverside Ave",
    "iso:country":"US",
    "sg:address":"5 Riverside Ave",
    "sg:city":"Mexico",
    "sg:classifiers":[
        {
            "category":"Government",
            "subcategory":"Post Office",
            "type":"Public Place"
        }
    ],
    "sg:phone":"+1 207 364 8302",
    "sg:postcode":"04257",
    "sg:province":"ME",
    "wof:name":"US Post Office",
    "wof:placetype":"venue"
},
  "geometry": {"coordinates":[-70.543403,44.556629],"type":"Point"}
}