{
  "type": "Feature",
  "properties": {
    "iso:country":"US",
    "sg:address":"41 Millett Dr",
    "sg:city":"Auburn",
    "sg:classifiers":[
        {
            "category":"Retail",
            "subcategory":"Auto Repair",
            "type":"Services"
        }
    ],
    "sg:phone":"+1 207 783 4263",
    "sg:postcode":"04210",
    "sg:province":"ME",
    "sg:tags":[
        "repairing",
        "automobile"
    ],
    "sg:website":"www.hebertsauto.com",
    "wof:name":"Hebert's Auto Svc",
    "wof:placetype":"venue"
},
  "geometry": {"coordinates":[-70.252881,44.082947],"type":"Point"}
}