{
  "type": "Feature",
  "properties": {
    "addr:full":"771 Narragansett Trl Buxton ME 04093",
    "addr:housenumber":"771",
    "addr:postcode":"04093",
    "addr:street":"Narragansett Trl",
    "iso:country":"US",
    "sg:address":"771 Narragansett Trl",
    "sg:city":"Buxton",
    "sg:classifiers":[
        {
            "category":"Building & Trades",
            "subcategory":"Construction",
            "type":"Services"
        }
    ],
    "sg:phone":"+1 207 929 5558",
    "sg:postcode":"04093",
    "sg:province":"ME",
    "sg:tags":[
        "contractor"
    ],
    "sg:website":"www.countryland.net",
    "wof:name":"Country Properties Of Maine",
    "wof:placetype":"venue"
},
  "geometry": {"coordinates":[-70.513773,43.627377],"type":"Point"}
}