{
  "type": "Feature",
  "properties": {
    "addr:full":"46 Hayward St Ashland ME 04732",
    "addr:housenumber":"46",
    "addr:postcode":"04732",
    "addr:street":"Hayward St",
    "iso:country":"US",
    "sg:address":"46 Hayward St",
    "sg:city":"Ashland",
    "sg:classifiers":[
        {
            "category":"Education",
            "subcategory":"School",
            "type":"Public Place"
        }
    ],
    "sg:phone":"+1 207 435 3661",
    "sg:postcode":"04732",
    "sg:province":"ME",
    "wof:name":"School Admin District 32",
    "wof:placetype":"venue"
},
  "geometry": {"coordinates":[-68.39558700000001,46.629478],"type":"Point"}
}