{
  "type": "Feature",
  "properties": {
    "addr:full":"40 Waterville Rd Skowhegan ME 04976",
    "addr:housenumber":"40",
    "addr:postcode":"04976",
    "addr:street":"Waterville Rd",
    "iso:country":"US",
    "sg:address":"40 Waterville Rd",
    "sg:city":"Skowhegan",
    "sg:classifiers":[
        {
            "category":"Shopping",
            "subcategory":"Used Merchandise",
            "type":"Retail Goods"
        }
    ],
    "sg:phone":"+1 207 474 3972",
    "sg:postcode":"04976",
    "sg:province":"ME",
    "wof:name":"Hilltop Antiques",
    "wof:placetype":"venue"
},
  "geometry": {"coordinates":[-69.714033,44.762895],"type":"Point"}
}