{
  "type": "Feature",
  "properties": {
    "iso:country":"US",
    "sg:address":"22 South St",
    "sg:city":"Biddeford",
    "sg:classifiers":[
        {
            "category":"Real Estate",
            "subcategory":"Real Estate Agent",
            "type":"Services"
        }
    ],
    "sg:phone":"+1 207 282 6537",
    "sg:postcode":"04005",
    "sg:province":"ME",
    "sg:tags":[
        "authorities",
        "housing"
    ],
    "wof:name":"Biddeford Housing Authority",
    "wof:placetype":"venue"
},
  "geometry": {"coordinates":[-70.45653,43.492853],"type":"Point"}
}