{
  "type": "Feature",
  "properties": {
    "addr:full":"247 Clement Point Rd Warren ME 04864",
    "addr:housenumber":"247",
    "addr:postcode":"04864",
    "addr:street":"Clement Point Rd",
    "iso:country":"US",
    "sg:address":"247 Clement Point Rd",
    "sg:city":"Warren",
    "sg:classifiers":[
        {
            "category":"Building & Trades",
            "subcategory":"Landscaping Services",
            "type":"Services"
        }
    ],
    "sg:phone":"+1 207 273 2225",
    "sg:postcode":"04864",
    "sg:province":"ME",
    "wof:name":"Robert Bradstreet",
    "wof:placetype":"venue"
},
  "geometry": {"coordinates":[-69.240942,44.106345],"type":"Point"}
}