{
  "type": "Feature",
  "properties": {
    "addr:full":"9 Depot St Alfred ME 04002",
    "addr:housenumber":"9",
    "addr:postcode":"04002",
    "addr:street":"Depot St",
    "iso:country":"US",
    "sg:address":"9 Depot St",
    "sg:city":"Alfred",
    "sg:classifiers":[
        {
            "category":"Real Estate",
            "subcategory":"Real Estate Services",
            "type":"Services"
        }
    ],
    "sg:phone":"+1 207 324 0335",
    "sg:postcode":"04002",
    "sg:province":"ME",
    "sg:tags":[
        "company",
        "title"
    ],
    "wof:name":"Atlantic Title Co",
    "wof:placetype":"venue"
},
  "geometry": {"coordinates":[-70.717315,43.474456],"type":"Point"}
}