{
  "type": "Feature",
  "properties": {
    "addr:full":"250 Elm St Biddeford ME 04005",
    "addr:housenumber":"250",
    "addr:postcode":"04005",
    "addr:street":"Elm St",
    "iso:country":"US",
    "sg:address":"250 Elm St",
    "sg:city":"Biddeford",
    "sg:classifiers":[
        {
            "category":"Education",
            "subcategory":"Dance Studio",
            "type":"Public Place"
        }
    ],
    "sg:phone":"+1 207 282 4940",
    "sg:postcode":"04005",
    "sg:province":"ME",
    "wof:name":"Turning Point Dance Center",
    "wof:placetype":"venue"
},
  "geometry": {"coordinates":[-70.463134,43.491167],"type":"Point"}
}