{
  "type": "Feature",
  "properties": {
    "addr:full":"539 Congress St Portland ME 04101",
    "addr:housenumber":"539",
    "addr:postcode":"04101",
    "addr:street":"Congress St",
    "iso:country":"US",
    "sg:address":"539 Congress St",
    "sg:city":"Portland",
    "sg:classifiers":[
        {
            "category":"Food & Beverages",
            "subcategory":"Bakery",
            "type":"Retail Goods"
        },
        {
            "category":"Bakery",
            "type":"Food & Drink"
        }
    ],
    "sg:menulink":"http://www.allmenus.com/me/portland/35739-mr-bagel/menu/",
    "sg:phone":"+1 207 774 8582",
    "sg:postcode":"04101",
    "sg:province":"ME",
    "sg:tags":[
        "american",
        "bakery",
        "pastry"
    ],
    "wof:name":"Mr. Bagel",
    "wof:placetype":"venue"
},
  "geometry": {"coordinates":[-70.26159800000001,43.655605],"type":"Point"}
}