{
  "type": "Feature",
  "properties": {
    "iso:country":"US",
    "sg:address":"1135 Hammond St",
    "sg:city":"Bangor",
    "sg:classifiers":[
        {
            "category":"Wholesale",
            "subcategory":"Books, Periodicals, & Newspapers",
            "type":"Manufacturing & Wholesale Goods"
        }
    ],
    "sg:phone":"+1 207 942 8237",
    "sg:postcode":"04401",
    "sg:province":"ME",
    "sg:tags":[
        "magazine"
    ],
    "wof:name":"Magazines Inc",
    "wof:placetype":"venue"
},
  "geometry": {"coordinates":[-68.819422,44.788548],"type":"Point"}
}