{
  "type": "Feature",
  "properties": {
    "addr:full":"2 2nd St Gardiner ME 04346",
    "addr:housenumber":"2",
    "addr:postcode":"04346",
    "addr:street":"2Nd St",
    "iso:country":"US",
    "sg:address":"2 2nd St",
    "sg:city":"Gardiner",
    "sg:phone":"+1 207 582 5152",
    "sg:postcode":"04346",
    "sg:province":"ME",
    "sg:tags":[
        "oil"
    ],
    "wof:name":"Chapman Oil Co",
    "wof:placetype":"venue"
},
  "geometry": {"coordinates":[-69.76700599999999,44.232601],"type":"Point"}
}