{
  "type": "Feature",
  "properties": {
    "addr:full":"1255 Roosevelt Trl Raymond ME 04071",
    "addr:housenumber":"1255",
    "addr:postcode":"04071",
    "addr:street":"Roosevelt Trl",
    "iso:country":"US",
    "sg:address":"1255 Roosevelt Trl",
    "sg:city":"Raymond",
    "sg:classifiers":[
        {
            "category":"Retail",
            "subcategory":"Auto Repair",
            "type":"Services"
        }
    ],
    "sg:phone":"+1 207 655 3101",
    "sg:postcode":"04071",
    "sg:province":"ME",
    "sg:tags":[
        "repairing",
        "automobile"
    ],
    "wof:name":"Auto Werke",
    "wof:placetype":"venue"
},
  "geometry": {"coordinates":[-70.465388,43.881787],"type":"Point"}
}