{
  "type": "Feature",
  "properties": {
    "addr:full":"90 Lewiston St Mechanic Falls ME 04256",
    "addr:housenumber":"90",
    "addr:postcode":"04256",
    "addr:street":"Lewiston St",
    "iso:country":"US",
    "sg:address":"90 Lewiston St",
    "sg:city":"Mechanic Falls",
    "sg:classifiers":[
        {
            "category":"Professional",
            "subcategory":"Management & Consulting",
            "type":"Services"
        }
    ],
    "sg:phone":"+1 207 345 3047",
    "sg:postcode":"04256",
    "sg:province":"ME",
    "sg:tags":[
        "development",
        "industrial"
    ],
    "wof:name":"Mechanic Falls Town",
    "wof:placetype":"venue"
},
  "geometry": {"coordinates":[-70.367322,44.104572],"type":"Point"}
}