{
  "type": "Feature",
  "properties": {
    "addr:full":"231 Main St Bar Harbor ME 04609",
    "addr:housenumber":"231",
    "addr:postcode":"04609",
    "addr:street":"Main St",
    "iso:country":"US",
    "sg:address":"231 Main St",
    "sg:city":"Bar Harbor",
    "sg:classifiers":[
        {
            "category":"Bars & Pubs",
            "type":"Food & Drink"
        }
    ],
    "sg:menulink":"http://www.allmenus.com/me/bar-harbor/236733-mckays-public-house/menu/",
    "sg:phone":"+1 207 288 2002",
    "sg:postcode":"04609",
    "sg:province":"ME",
    "sg:tags":[
        "american"
    ],
    "wof:name":"Mckays Public House",
    "wof:placetype":"venue"
},
  "geometry": {"coordinates":[-68.2041,44.386733],"type":"Point"}
}