{
  "type": "Feature",
  "properties": {
    "iso:country":"US",
    "sg:address":"106 Pine St",
    "sg:city":"Bangor",
    "sg:classifiers":[
        {
            "category":"Social Services",
            "type":"Services"
        }
    ],
    "sg:phone":"+1 207 990 5070",
    "sg:postcode":"04401",
    "sg:province":"ME",
    "wof:name":"Polly M Karris",
    "wof:placetype":"venue"
},
  "geometry": {"coordinates":[-68.766859,44.803873],"type":"Point"}
}