{
  "type": "Feature",
  "properties": {
    "addr:full":"30 Cleveland St Bangor ME 04401",
    "addr:housenumber":"30",
    "addr:postcode":"04401",
    "addr:street":"Cleveland St",
    "iso:country":"US",
    "sg:address":"30 Cleveland St",
    "sg:city":"Bangor",
    "sg:classifiers":[
        {
            "category":"Education",
            "subcategory":"Special Training",
            "type":"Public Place"
        }
    ],
    "sg:phone":"+1 207 990 2900",
    "sg:postcode":"04401",
    "sg:province":"ME",
    "sg:tags":[
        "center"
    ],
    "wof:name":"Challenger Learning Ctr-Mn",
    "wof:placetype":"venue"
},
  "geometry": {"coordinates":[-68.803251,44.805169],"type":"Point"}
}