{
  "type": "Feature",
  "properties": {
    "iso:country":"US",
    "sg:address":"167 Fortunes Rocks Rd",
    "sg:city":"Biddeford",
    "sg:classifiers":[
        {
            "category":"Building & Trades",
            "subcategory":"Construction",
            "type":"Services"
        }
    ],
    "sg:phone":"+1 207 284 5717",
    "sg:postcode":"04005",
    "sg:province":"ME",
    "sg:tags":[
        "general",
        "contractor"
    ],
    "wof:name":"Donald Allie Properties Inc",
    "wof:placetype":"venue"
},
  "geometry": {"coordinates":[-70.387418,43.424158],"type":"Point"}
}