{
  "type": "Feature",
  "properties": {
    "iso:country":"US",
    "sg:address":"80 Waterville Rd",
    "sg:city":"Waterville",
    "sg:classifiers":[
        {
            "category":"Shopping",
            "subcategory":"Pharmacy",
            "type":"Retail Goods"
        }
    ],
    "sg:phone":"+1 207 877 9161",
    "sg:postcode":"04976",
    "sg:province":"ME",
    "wof:name":"Wal Mart Pharmacy",
    "wof:placetype":"venue"
},
  "geometry": {"coordinates":[-69.711805,44.763245],"type":"Point"}
}