{
  "type": "Feature",
  "properties": {
    "addr:full":"69 Ottercreek Dr Otter Creek ME 04660",
    "addr:housenumber":"69",
    "addr:postcode":"04660",
    "addr:street":"Ottercreek Dr",
    "iso:country":"US",
    "sg:address":"69 Ottercreek Dr",
    "sg:city":"Otter Creek",
    "sg:classifiers":[
        {
            "category":"Restaurant",
            "type":"Food & Drink"
        }
    ],
    "sg:phone":"+1 207 288 9331",
    "sg:postcode":"04660",
    "sg:province":"ME",
    "wof:name":"Burning Tree Restaurant",
    "wof:placetype":"venue"
},
  "geometry": {"coordinates":[-68.206896,44.321052],"type":"Point"}
}