{
  "type": "Feature",
  "properties": {
    "iso:country":"US",
    "sg:address":"119 Lisbon St",
    "sg:city":"Lisbon",
    "sg:classifiers":[
        {
            "category":"Manufacturing",
            "subcategory":"Printing",
            "type":"Manufacturing & Wholesale Goods"
        }
    ],
    "sg:phone":"+1 207 353 4151",
    "sg:postcode":"04250",
    "sg:province":"ME",
    "sg:tags":[
        "printer"
    ],
    "sg:website":"www.dingley.com",
    "wof:name":"Dingley Press",
    "wof:placetype":"venue"
},
  "geometry": {"coordinates":[-70.11117299999999,44.039626],"type":"Point"}
}