{
  "type": "Feature",
  "properties": {
    "addr:full":"36 N Berwick Rd Wells ME 04090",
    "addr:housenumber":"36",
    "addr:postcode":"04090",
    "addr:street":"N Berwick Rd",
    "iso:country":"US",
    "sg:address":"36 N Berwick Rd",
    "sg:city":"Wells",
    "sg:classifiers":[
        {
            "category":"Building & Trades",
            "subcategory":"Cleaning & Sanitation",
            "type":"Services"
        }
    ],
    "sg:phone":"+1 207 646 4994",
    "sg:postcode":"04090",
    "sg:province":"ME",
    "sg:tags":[
        "janitor"
    ],
    "wof:name":"Complete Cleaning Svc",
    "wof:placetype":"venue"
},
  "geometry": {"coordinates":[-70.63183100000001,43.325073],"type":"Point"}
}