{
  "type": "Feature",
  "properties": {
    "iso:country":"US",
    "sg:address":"136 Pleasant Hill Rd",
    "sg:city":"Scarborough",
    "sg:classifiers":[
        {
            "category":"Retail",
            "subcategory":"Auto Repair",
            "type":"Services"
        }
    ],
    "sg:phone":"+1 207 885 9009",
    "sg:postcode":"04074",
    "sg:province":"ME",
    "sg:tags":[
        "repairing",
        "automobile"
    ],
    "wof:name":"Elite Motors",
    "wof:placetype":"venue"
},
  "geometry": {"coordinates":[-70.297698,43.597028],"type":"Point"}
}