{
  "type": "Feature",
  "properties": {
    "addr:full":"77 Winthrop Rd Readfield ME 04355",
    "addr:housenumber":"77",
    "addr:postcode":"04355",
    "addr:street":"Winthrop Rd",
    "iso:country":"US",
    "sg:address":"77 Winthrop Rd",
    "sg:city":"Readfield",
    "sg:classifiers":[
        {
            "category":"Retail",
            "subcategory":"Auto Repair",
            "type":"Services"
        }
    ],
    "sg:phone":"+1 207 623 7647",
    "sg:postcode":"04355",
    "sg:province":"ME",
    "sg:tags":[
        "repairing",
        "automobile"
    ],
    "wof:name":"Beaulieu's Upright Auto Repair",
    "wof:placetype":"venue"
},
  "geometry": {"coordinates":[-69.965255,44.380847],"type":"Point"}
}