{
  "type": "Feature",
  "properties": {
    "iso:country":"US",
    "sg:address":"6 Water St",
    "sg:city":"Searsport",
    "sg:classifiers":[
        {
            "category":"Government",
            "subcategory":"Post Office",
            "type":"Public Place"
        }
    ],
    "sg:phone":"+1 207 548 2703",
    "sg:postcode":"04974",
    "sg:province":"ME",
    "wof:name":"US Post Office",
    "wof:placetype":"venue"
},
  "geometry": {"coordinates":[-68.92603099999999,44.457422],"type":"Point"}
}