{
  "type": "Feature",
  "properties": {
    "iso:country":"US",
    "sg:address":"32 Delan Rd",
    "sg:city":"Waterboro",
    "sg:classifiers":[
        {
            "category":"Retail",
            "subcategory":"Repair Shop",
            "type":"Services"
        }
    ],
    "sg:phone":"+1 207 247 2880",
    "sg:postcode":"04039",
    "sg:province":"ME",
    "sg:tags":[
        "upholsterer"
    ],
    "wof:name":"Alfred Upholstery Shop",
    "wof:placetype":"venue"
},
  "geometry": {"coordinates":[-70.36180400000001,43.868726],"type":"Point"}
}