{
  "type": "Feature",
  "properties": {
    "addr:full":"118 Bartlett St Lewiston ME 04240",
    "addr:housenumber":"118",
    "addr:postcode":"04240",
    "addr:street":"Bartlett St",
    "iso:country":"US",
    "sg:address":"118 Bartlett St",
    "sg:city":"Lewiston",
    "sg:classifiers":[
        {
            "category":"Building & Trades",
            "subcategory":"Cleaning & Sanitation",
            "type":"Services"
        }
    ],
    "sg:phone":"+1 207 782 8619",
    "sg:postcode":"04240",
    "sg:province":"ME",
    "sg:tags":[
        "house"
    ],
    "wof:name":"Chrystal's Cleaning Svc",
    "wof:placetype":"venue"
},
  "geometry": {"coordinates":[-70.21087799999999,44.096714],"type":"Point"}
}