{
  "type": "Feature",
  "properties": {
    "iso:country":"US",
    "sg:address":"2 Lois Ln",
    "sg:city":"Gorham",
    "sg:classifiers":[
        {
            "category":"Building & Trades",
            "subcategory":"Landscaping Services",
            "type":"Services"
        }
    ],
    "sg:phone":"+1 207 839 5224",
    "sg:postcode":"04038",
    "sg:province":"ME",
    "sg:tags":[
        "landscape",
        "contractor"
    ],
    "wof:name":"Morong Landscaping Svc Inc",
    "wof:placetype":"venue"
},
  "geometry": {"coordinates":[-70.445349,43.63589],"type":"Point"}
}