{
  "type": "Feature",
  "properties": {
    "addr:full":"4 Crescent Ave Kennebunkport ME 04046",
    "addr:housenumber":"4",
    "addr:postcode":"04046",
    "addr:street":"Crescent Ave",
    "iso:country":"US",
    "sg:address":"4 Crescent Ave",
    "sg:city":"Kennebunkport",
    "sg:classifiers":[
        {
            "category":"Building & Trades",
            "subcategory":"Construction",
            "type":"Services"
        }
    ],
    "sg:phone":"+1 207 967 5404",
    "sg:postcode":"04046",
    "sg:province":"ME",
    "sg:tags":[
        "work",
        "carpentry"
    ],
    "wof:name":"Tom Muse",
    "wof:placetype":"venue"
},
  "geometry": {"coordinates":[-70.414512,43.399029],"type":"Point"}
}