{
  "type": "Feature",
  "properties": {
    "iso:country":"US",
    "sg:address":"4 Pierce Dr",
    "sg:city":"Buxton",
    "sg:classifiers":[
        {
            "category":"Food & Beverages",
            "subcategory":"Bakery",
            "type":"Retail Goods"
        }
    ],
    "sg:phone":"+1 207 929 5060",
    "sg:postcode":"04055",
    "sg:province":"ME",
    "sg:tags":[
        "doughnut"
    ],
    "wof:name":"Donut Hole",
    "wof:placetype":"venue"
},
  "geometry": {"coordinates":[-70.60339,43.991293],"type":"Point"}
}