{
  "type": "Feature",
  "properties": {
    "addr:full":"10 High St Augusta ME 04330",
    "addr:housenumber":"10",
    "addr:postcode":"04330",
    "addr:street":"High St",
    "iso:country":"US",
    "sg:address":"10 High St",
    "sg:city":"Augusta",
    "sg:classifiers":[
        {
            "category":"Professional",
            "subcategory":"Computer Services",
            "type":"Services"
        }
    ],
    "sg:phone":"+1 207 622 4190",
    "sg:postcode":"04330",
    "sg:province":"ME",
    "sg:tags":[
        "related"
    ],
    "wof:name":"Upnrunninnet Web Solutions",
    "wof:placetype":"venue"
},
  "geometry": {"coordinates":[-69.784418,44.318162],"type":"Point"}
}