{
  "type": "Feature",
  "properties": {
    "addr:full":"79 Robertson Blvd Brewer ME 04412",
    "addr:housenumber":"79",
    "addr:postcode":"04412",
    "addr:street":"Robertson Blvd",
    "iso:country":"US",
    "sg:address":"79 Robertson Blvd",
    "sg:city":"Brewer",
    "sg:classifiers":[
        {
            "category":"Wholesale",
            "subcategory":"Machinery & Supplies",
            "type":"Manufacturing & Wholesale Goods"
        }
    ],
    "sg:phone":"+1 207 989 1890",
    "sg:postcode":"04412",
    "sg:province":"ME",
    "sg:tags":[
        "contractor"
    ],
    "sg:website":"www.southworth-milton.com",
    "wof:name":"Southworth-Milton Inc",
    "wof:placetype":"venue"
},
  "geometry": {"coordinates":[-68.76481099999999,44.783379],"type":"Point"}
}