{
  "type": "Feature",
  "properties": {
    "addr:full":"86 Penn Ave Portland ME 04103",
    "addr:housenumber":"86",
    "addr:postcode":"04103",
    "addr:street":"Penn Ave",
    "iso:country":"US",
    "sg:address":"86 Penn Ave",
    "sg:city":"Portland",
    "sg:classifiers":[
        {
            "category":"Retail",
            "subcategory":"Repair Shop",
            "type":"Services"
        }
    ],
    "sg:phone":"+1 207 749 9098",
    "sg:postcode":"04103",
    "sg:province":"ME",
    "wof:name":"Housewife4hire",
    "wof:placetype":"venue"
},
  "geometry": {"coordinates":[-70.275841,43.701872],"type":"Point"}
}