{
  "type": "Feature",
  "properties": {
    "addr:full":"126 Connecticut Ave Millinocket ME 04462",
    "addr:housenumber":"126",
    "addr:postcode":"04462",
    "addr:street":"Connecticut Ave",
    "iso:country":"US",
    "sg:address":"126 Connecticut Ave",
    "sg:city":"Millinocket",
    "sg:classifiers":[
        {
            "category":"Health Services",
            "subcategory":"Podiatrist",
            "type":"Services"
        }
    ],
    "sg:phone":"+1 207 723 4025",
    "sg:postcode":"04462",
    "sg:province":"ME",
    "wof:name":"Jil Beaupain DPM",
    "wof:placetype":"venue"
},
  "geometry": {"coordinates":[-68.693923,45.664617],"type":"Point"}
}