{
  "type": "Feature",
  "properties": {
    "addr:full":"187 Main St Calais ME 04619",
    "addr:housenumber":"187",
    "addr:postcode":"04619",
    "addr:street":"Main St",
    "iso:country":"US",
    "sg:address":"187 Main St",
    "sg:city":"Calais",
    "sg:classifiers":[
        {
            "category":"Restaurant",
            "type":"Food & Drink"
        }
    ],
    "sg:phone":"+1 207 454 8055",
    "sg:postcode":"04619",
    "sg:province":"ME",
    "wof:name":"Schooner Restaurant",
    "wof:placetype":"venue"
},
  "geometry": {"coordinates":[-67.276279,45.188839],"type":"Point"}
}