{
  "type": "Feature",
  "properties": {
    "addr:full":"334 Forest Ave Portland ME 04101",
    "addr:housenumber":"334",
    "addr:postcode":"04101",
    "addr:street":"Forest Ave",
    "iso:country":"US",
    "sg:address":"334 Forest Ave",
    "sg:city":"Portland",
    "sg:classifiers":[
        {
            "category":"Restaurant",
            "type":"Food & Drink"
        }
    ],
    "sg:phone":"+1 207 772 9229",
    "sg:postcode":"04101",
    "sg:province":"ME",
    "sg:website":"www.bleachersportland.com",
    "wof:name":"Bleachers Sports Bar & Rstrnt",
    "wof:placetype":"venue"
},
  "geometry": {"coordinates":[-70.27361399999999,43.66417],"type":"Point"}
}