{
  "type": "Feature",
  "properties": {
    "iso:country":"US",
    "sg:address":"114 River Rd",
    "sg:city":"Arundel",
    "sg:classifiers":[
        {
            "category":"Retail",
            "subcategory":"Auto Repair",
            "type":"Services"
        }
    ],
    "sg:phone":"+1 207 967 2504",
    "sg:postcode":"04046",
    "sg:province":"ME",
    "sg:tags":[
        "repairing",
        "automobile"
    ],
    "wof:name":"Leyland English Auto",
    "wof:placetype":"venue"
},
  "geometry": {"coordinates":[-70.489818,43.377954],"type":"Point"}
}