{
  "type": "Feature",
  "properties": {
    "addr:full":"80 Alfred St Biddeford ME 04005",
    "addr:housenumber":"80",
    "addr:postcode":"04005",
    "addr:street":"Alfred St",
    "iso:country":"US",
    "sg:address":"80 Alfred St",
    "sg:city":"Biddeford",
    "sg:classifiers":[
        {
            "category":"Shopping",
            "subcategory":"Discount & Variety Stores",
            "type":"Retail Goods"
        }
    ],
    "sg:phone":"+1 207 282 6821",
    "sg:postcode":"04005",
    "sg:province":"ME",
    "wof:name":"Paul's Variety",
    "wof:placetype":"venue"
},
  "geometry": {"coordinates":[-70.455569,43.491089],"type":"Point"}
}