{
  "type": "Feature",
  "properties": {
    "addr:full":"753 Stillwater Ave Bangor ME 04401",
    "addr:housenumber":"753",
    "addr:postcode":"04401",
    "addr:street":"Stillwater Ave",
    "iso:country":"US",
    "sg:address":"753 Stillwater Ave",
    "sg:city":"Bangor",
    "sg:classifiers":[
        {
            "category":"Banks & Credit Unions",
            "subcategory":"Investment Brokerage",
            "type":"Services"
        }
    ],
    "sg:phone":"+1 207 262 0144",
    "sg:postcode":"04401",
    "sg:province":"ME",
    "sg:tags":[
        "advisory",
        "financial"
    ],
    "wof:name":"American General Financial",
    "wof:placetype":"venue"
},
  "geometry": {"coordinates":[-68.749644,44.834575],"type":"Point"}
}