{
  "type": "Feature",
  "properties": {
    "addr:full":"55 Main St Livermore Falls ME 04254",
    "addr:housenumber":"55",
    "addr:postcode":"04254",
    "addr:street":"Main St",
    "iso:country":"US",
    "sg:address":"55 Main St",
    "sg:city":"Livermore Falls",
    "sg:classifiers":[
        {
            "category":"Restaurant",
            "type":"Food & Drink"
        }
    ],
    "sg:phone":"+1 207 897 1133",
    "sg:postcode":"04254",
    "sg:province":"ME",
    "wof:name":"China Chef Restaurant",
    "wof:placetype":"venue"
},
  "geometry": {"coordinates":[-70.19031699999999,44.474399],"type":"Point"}
}