{
  "type": "Feature",
  "properties": {
    "iso:country":"US",
    "sg:address":"357 Main St",
    "sg:city":"Southwest Harbor",
    "sg:classifiers":[
        {
            "category":"Personal",
            "subcategory":"Tanning Parlor",
            "type":"Services"
        }
    ],
    "sg:phone":"+1 207 244 5842",
    "sg:postcode":"04679",
    "sg:province":"ME",
    "sg:tags":[
        "salon"
    ],
    "wof:name":"Periwinkle's Tanning Shop",
    "wof:placetype":"venue"
},
  "geometry": {"coordinates":[-68.325556,44.278225],"type":"Point"}
}