{
  "type": "Feature",
  "properties": {
    "iso:country":"US",
    "sg:address":"366 Tuttle Rd",
    "sg:city":"Cumberland Ctr",
    "sg:classifiers":[
        {
            "category":"Government",
            "subcategory":"Fire Station",
            "type":"Public Place"
        }
    ],
    "sg:phone":"+1 207 829 4573",
    "sg:postcode":"04021",
    "sg:province":"ME",
    "sg:tags":[
        "department"
    ],
    "sg:website":"www.cumberlandmaine.com",
    "wof:name":"Cumberland Fire Dept",
    "wof:placetype":"venue"
},
  "geometry": {"coordinates":[-70.256096,43.795309],"type":"Point"}
}