{
  "type": "Feature",
  "properties": {
    "iso:country":"US",
    "sg:address":"10 Bow St",
    "sg:city":"Freeport",
    "sg:classifiers":[
        {
            "category":"Shopping",
            "subcategory":"Clothing, Apparel, & Fashions",
            "type":"Retail Goods"
        }
    ],
    "sg:phone":"+1 207 865 3180",
    "sg:postcode":"04032",
    "sg:province":"ME",
    "wof:name":"J Crew Factory Store",
    "wof:placetype":"venue"
},
  "geometry": {"coordinates":[-70.10171699999999,43.856868],"type":"Point"}
}