{
  "type": "Feature",
  "properties": {
    "addr:full":"285 Forest Ave Portland ME 04101",
    "addr:housenumber":"285",
    "addr:postcode":"04101",
    "addr:street":"Forest Ave",
    "iso:country":"US",
    "sg:address":"285 Forest Ave",
    "sg:city":"Portland",
    "sg:classifiers":[
        {
            "category":"Restaurant",
            "type":"Food & Drink"
        }
    ],
    "sg:menulink":"http://www.allmenus.com/me/portland/210660-arbys/menu/",
    "sg:phone":"+1 207 773 7769",
    "sg:postcode":"04101",
    "sg:province":"ME",
    "sg:tags":[
        "burger",
        "american"
    ],
    "wof:name":"Arby's",
    "wof:placetype":"venue"
},
  "geometry": {"coordinates":[-70.27210100000001,43.663218],"type":"Point"}
}