{
  "type": "Feature",
  "properties": {
    "iso:country":"US",
    "sg:address":"35 Pleasant St",
    "sg:city":"Fort Kent",
    "sg:classifiers":[
        {
            "category":"Organizations",
            "subcategory":"Religious Organization",
            "type":"Services"
        }
    ],
    "sg:phone":"+1 207 834 5555",
    "sg:postcode":"04743",
    "sg:province":"ME",
    "sg:tags":[
        "church"
    ],
    "wof:name":"Christ Church Congregational",
    "wof:placetype":"venue"
},
  "geometry": {"coordinates":[-68.58945900000001,47.249487],"type":"Point"}
}