{
  "type": "Feature",
  "properties": {
    "addr:full":"142 Main St Ogunquit ME 03907",
    "addr:housenumber":"142",
    "addr:postcode":"03907",
    "addr:street":"Main St",
    "iso:country":"US",
    "sg:address":"142 Main St",
    "sg:city":"Ogunquit",
    "sg:classifiers":[
        {
            "category":"Banks & Credit Unions",
            "subcategory":"Bank",
            "type":"Services"
        },
        {
            "category":"Banks & Credit Unions",
            "subcategory":"Financial Services",
            "type":"Services"
        }
    ],
    "sg:phone":"+1 207 646 9991",
    "sg:postcode":"03907",
    "sg:province":"ME",
    "sg:tags":[
        "broker",
        "mortgage"
    ],
    "sg:website":"www.kennebunksavings.com",
    "wof:name":"Kennebunk Savings Bank",
    "wof:placetype":"venue"
},
  "geometry": {"coordinates":[-70.601799,43.243301],"type":"Point"}
}