{
  "type": "Feature",
  "properties": {
    "iso:country":"US",
    "sg:address":"3 Mechanic St",
    "sg:city":"Bridgton",
    "sg:classifiers":[
        {
            "category":"Professional",
            "subcategory":"Business Services",
            "type":"Services"
        }
    ],
    "sg:phone":"+1 207 647 3234",
    "sg:postcode":"04009",
    "sg:province":"ME",
    "wof:name":"Mark A Butler",
    "wof:placetype":"venue"
},
  "geometry": {"coordinates":[-70.700463,44.05499],"type":"Point"}
}