{
  "type": "Feature",
  "properties": {
    "iso:country":"US",
    "sg:address":"15 Monument Sq",
    "sg:city":"Portland",
    "sg:classifiers":[
        {
            "category":"Health Services",
            "subcategory":"Doctor",
            "type":"Services"
        }
    ],
    "sg:phone":"+1 207 253 1515",
    "sg:postcode":"04101",
    "sg:province":"ME",
    "sg:tags":[
        "physician",
        "surgeon"
    ],
    "wof:name":"Madeline Goodman DO",
    "wof:placetype":"venue"
},
  "geometry": {"coordinates":[-70.25865400000001,43.657757],"type":"Point"}
}