{
  "type": "Feature",
  "properties": {
    "iso:country":"US",
    "sg:address":"12 Foss Rd",
    "sg:city":"Lewiston",
    "sg:classifiers":[
        {
            "category":"Communications",
            "type":"Services"
        }
    ],
    "sg:phone":"+1 207 795 0610",
    "sg:postcode":"04240",
    "sg:province":"ME",
    "wof:name":"Bogen Communications Inc",
    "wof:placetype":"venue"
},
  "geometry": {"coordinates":[-70.138631,44.059053],"type":"Point"}
}