{
  "type": "Feature",
  "properties": {
    "iso:country":"US",
    "sg:address":"270 Main St",
    "sg:city":"Gorham",
    "sg:classifiers":[
        {
            "category":"Government",
            "subcategory":"Office",
            "type":"Public Place"
        }
    ],
    "sg:phone":"+1 207 839 3346",
    "sg:postcode":"04038",
    "sg:province":"ME",
    "sg:tags":[
        "village"
    ],
    "wof:name":"Motor Vehicle Registration",
    "wof:placetype":"venue"
},
  "geometry": {"coordinates":[-70.427661,43.684331],"type":"Point"}
}