{
  "type": "Feature",
  "properties": {
    "addr:full":"11 Medical Center Dr Biddeford ME 04005",
    "addr:housenumber":"11",
    "addr:postcode":"04005",
    "addr:street":"Medical Center Dr",
    "iso:country":"US",
    "sg:address":"11 Medical Center Dr",
    "sg:city":"Biddeford",
    "sg:classifiers":[
        {
            "category":"Health Services",
            "subcategory":"Doctor",
            "type":"Services"
        }
    ],
    "sg:phone":"+1 207 721 1110",
    "sg:postcode":"04005",
    "sg:province":"ME",
    "sg:tags":[
        "medical",
        "imaging"
    ],
    "wof:name":"Brunswick Open Mri",
    "wof:placetype":"venue"
},
  "geometry": {"coordinates":[-70.492261,43.478206],"type":"Point"}
}