{
  "type": "Feature",
  "properties": {
    "addr:full":"95 Campus Ave Lewiston ME 04240",
    "addr:housenumber":"95",
    "addr:postcode":"04240",
    "addr:street":"Campus Ave",
    "iso:country":"US",
    "sg:address":"95 Campus Ave",
    "sg:city":"Lewiston",
    "sg:classifiers":[
        {
            "category":"Health Services",
            "subcategory":"Doctor",
            "type":"Services"
        }
    ],
    "sg:phone":"+1 207 755 3340",
    "sg:postcode":"04240",
    "sg:province":"ME",
    "sg:tags":[
        "physician",
        "surgeon"
    ],
    "wof:name":"North Atlantic Urology",
    "wof:placetype":"venue"
},
  "geometry": {"coordinates":[-70.197941,44.101324],"type":"Point"}
}