{
  "type": "Feature",
  "properties": {
    "addr:full":"59 Spring Valley Rd Raymond ME 04071",
    "addr:housenumber":"59",
    "addr:postcode":"04071",
    "addr:street":"Spring Valley Rd",
    "iso:country":"US",
    "sg:address":"59 Spring Valley Rd",
    "sg:city":"Raymond",
    "sg:classifiers":[
        {
            "category":"Government",
            "subcategory":"Office",
            "type":"Public Place"
        }
    ],
    "sg:phone":"+1 207 655 2617",
    "sg:postcode":"04071",
    "sg:province":"ME",
    "sg:tags":[
        "policy"
    ],
    "wof:name":"Property Tax Solutions",
    "wof:placetype":"venue"
},
  "geometry": {"coordinates":[-70.42325099999999,43.972947],"type":"Point"}
}