{
  "type": "Feature",
  "properties": {
    "iso:country":"US",
    "sg:address":"816 Roosevelt Trl",
    "sg:city":"Windham",
    "sg:classifiers":[
        {
            "category":"Organizations",
            "subcategory":"Professional Association",
            "type":"Services"
        }
    ],
    "sg:phone":"+1 207 892 8265",
    "sg:postcode":"04062",
    "sg:province":"ME",
    "sg:tags":[
        "chambers",
        "commerce"
    ],
    "wof:name":"Sebago Lakes Region Chamber",
    "wof:placetype":"venue"
},
  "geometry": {"coordinates":[-70.449604,43.850105],"type":"Point"}
}