{
  "type": "Feature",
  "properties": {
    "addr:full":"63 Portland Rd Ste 3 Kennebunk ME 04043",
    "addr:housenumber":"63",
    "addr:postcode":"04043",
    "addr:street":"Portland Rd Ste 3",
    "iso:country":"US",
    "sg:address":"63 Portland Rd Ste 3",
    "sg:city":"Kennebunk",
    "sg:classifiers":[
        {
            "category":"Personal",
            "subcategory":"Barber",
            "type":"Services"
        }
    ],
    "sg:phone":"+1 207 985 6501",
    "sg:postcode":"04043",
    "sg:province":"ME",
    "wof:name":"Razor's Edge",
    "wof:placetype":"venue"
},
  "geometry": {"coordinates":[-70.536903,43.388699],"type":"Point"}
}