{
  "type": "Feature",
  "properties": {
    "iso:country":"US",
    "sg:address":"75 State St",
    "sg:city":"Ellsworth",
    "sg:classifiers":[
        {
            "category":"Government",
            "subcategory":"Office",
            "type":"Public Place"
        }
    ],
    "sg:phone":"+1 207 664 0508",
    "sg:postcode":"04605",
    "sg:province":"ME",
    "sg:tags":[
        "federal"
    ],
    "wof:name":"National Marine Fisheries",
    "wof:placetype":"venue"
},
  "geometry": {"coordinates":[-68.425394,44.544431],"type":"Point"}
}