{
  "type": "Feature",
  "properties": {
    "iso:country":"US",
    "sg:address":"13 N High St",
    "sg:city":"Bangor",
    "sg:classifiers":[
        {
            "category":"Social Services",
            "type":"Services"
        }
    ],
    "sg:phone":"+1 207 947 7990",
    "sg:postcode":"04401",
    "sg:province":"ME",
    "sg:tags":[
        "counselor",
        "marriage",
        "family"
    ],
    "wof:name":"Bangor Therapy Institute",
    "wof:placetype":"venue"
},
  "geometry": {"coordinates":[-68.773599,44.801084],"type":"Point"}
}