{
  "type": "Feature",
  "properties": {
    "addr:full":"51 Water St Wiscasset ME 04578",
    "addr:housenumber":"51",
    "addr:postcode":"04578",
    "addr:street":"Water St",
    "iso:country":"US",
    "sg:address":"51 Water St",
    "sg:city":"Wiscasset",
    "sg:classifiers":[
        {
            "category":"Shopping",
            "subcategory":"Used Merchandise",
            "type":"Retail Goods"
        }
    ],
    "sg:phone":"+1 207 882 9700",
    "sg:postcode":"04578",
    "sg:province":"ME",
    "sg:tags":[
        "antique"
    ],
    "wof:name":"Water Street Antiques",
    "wof:placetype":"venue"
},
  "geometry": {"coordinates":[-69.664176,44.002931],"type":"Point"}
}