{
  "type": "Feature",
  "properties": {
    "iso:country":"US",
    "sg:address":"203 Blanchard Rd",
    "sg:city":"Cumberland Center",
    "sg:classifiers":[
        {
            "category":"Freight",
            "type":"Transportation"
        }
    ],
    "sg:phone":"+1 207 829 3097",
    "sg:postcode":"04021",
    "sg:province":"ME",
    "sg:tags":[
        "operator",
        "local",
        "trucking"
    ],
    "wof:name":"Stephen Morin",
    "wof:placetype":"venue"
},
  "geometry": {"coordinates":[-70.28877,43.813198],"type":"Point"}
}