{
  "type": "Feature",
  "properties": {
    "addr:full":"108 Fairbanks Rd Farmington ME 04938",
    "addr:housenumber":"108",
    "addr:postcode":"04938",
    "addr:street":"Fairbanks Rd",
    "iso:country":"US",
    "sg:address":"108 Fairbanks Rd",
    "sg:city":"Farmington",
    "sg:classifiers":[
        {
            "category":"Shopping",
            "subcategory":"Bicycles & Sporting Goods",
            "type":"Retail Goods"
        }
    ],
    "sg:phone":"+1 207 778 3330",
    "sg:postcode":"04938",
    "sg:province":"ME",
    "sg:tags":[
        "tackle",
        "fishing"
    ],
    "wof:name":"Aardvark Outfitters",
    "wof:placetype":"venue"
},
  "geometry": {"coordinates":[-70.157791,44.691873],"type":"Point"}
}