{
  "type": "Feature",
  "properties": {
    "addr:full":"1 Commercial Dr Scarborough ME 04074",
    "addr:housenumber":"1",
    "addr:postcode":"04074",
    "addr:street":"Commercial Dr",
    "iso:country":"US",
    "sg:address":"1 Commercial Dr",
    "sg:city":"Scarborough",
    "sg:classifiers":[
        {
            "category":"Retail",
            "subcategory":"Auto Rental",
            "type":"Services"
        }
    ],
    "sg:phone":"+1 207 883 5181",
    "sg:postcode":"04074",
    "sg:province":"ME",
    "sg:tags":[
        "renting",
        "leasing",
        "trailer"
    ],
    "wof:name":"KCV Trailer Rentals",
    "wof:placetype":"venue"
},
  "geometry": {"coordinates":[-70.297719,43.603638],"type":"Point"}
}