{
  "type": "Feature",
  "properties": {
    "addr:full":"76 Sumner Rd Leeds ME 04263",
    "addr:housenumber":"76",
    "addr:postcode":"04263",
    "addr:street":"Sumner Rd",
    "iso:country":"US",
    "sg:address":"76 Sumner Rd",
    "sg:city":"Leeds",
    "sg:classifiers":[
        {
            "category":"Autos & Motor Vehicles",
            "subcategory":"Automobile Sales",
            "type":"Retail Goods"
        }
    ],
    "sg:phone":"+1 207 946 3023",
    "sg:postcode":"04263",
    "sg:province":"ME",
    "sg:tags":[
        "car",
        "dealer"
    ],
    "wof:name":"Allen Pond Auto Sales",
    "wof:placetype":"venue"
},
  "geometry": {"coordinates":[-70.094195,44.223002],"type":"Point"}
}