{
  "type": "Feature",
  "properties": {
    "addr:full":"125 Shore Rd Ogunquit ME 03907",
    "addr:housenumber":"125",
    "addr:postcode":"03907",
    "addr:street":"Shore Rd",
    "iso:country":"US",
    "sg:address":"125 Shore Rd",
    "sg:city":"Ogunquit",
    "sg:classifiers":[
        {
            "category":"Travel",
            "subcategory":"Hotels & Motels",
            "type":"Entertainment"
        }
    ],
    "sg:phone":"+1 207 646 9384",
    "sg:postcode":"03907",
    "sg:province":"ME",
    "sg:website":"www.anchoragebythesea.com/",
    "wof:name":"Anchorage by the Sea",
    "wof:placetype":"venue"
},
  "geometry": {"coordinates":[-70.596802,43.245399],"type":"Point"}
}