{
  "type": "Feature",
  "properties": {
    "iso:country":"US",
    "sg:address":"65 Front St",
    "sg:city":"Bath",
    "sg:classifiers":[
        {
            "category":"Organizations",
            "subcategory":"Non-profit Organization",
            "type":"Services"
        }
    ],
    "sg:phone":"+1 207 443 3431",
    "sg:postcode":"04530",
    "sg:province":"ME",
    "sg:tags":[
        "charitable",
        "institution"
    ],
    "wof:name":"Davenport Trustees",
    "wof:placetype":"venue"
},
  "geometry": {"coordinates":[-69.814135,43.913301],"type":"Point"}
}