{
  "type": "Feature",
  "properties": {
    "iso:country":"US",
    "sg:address":"57 State Rd",
    "sg:city":"Kittery",
    "sg:classifiers":[
        {
            "category":"Health Services",
            "subcategory":"Doctor",
            "type":"Services"
        }
    ],
    "sg:phone":"+1 207 439 4958",
    "sg:postcode":"03904",
    "sg:province":"ME",
    "sg:tags":[
        "physician",
        "surgeon"
    ],
    "wof:name":"Kittery Ophthalmic Consultants",
    "wof:placetype":"venue"
},
  "geometry": {"coordinates":[-70.748624,43.089834],"type":"Point"}
}