{
  "type": "Feature",
  "properties": {
    "addr:full":"16 Lunn Ln Eddington ME 04428",
    "addr:housenumber":"16",
    "addr:postcode":"04428",
    "addr:street":"Lunn Ln",
    "iso:country":"US",
    "sg:address":"16 Lunn Ln",
    "sg:city":"Eddington",
    "sg:classifiers":[
        {
            "category":"Home & Garden",
            "subcategory":"Mobile Homes",
            "type":"Retail Goods"
        }
    ],
    "sg:phone":"+1 207 843 5942",
    "sg:postcode":"04428",
    "sg:province":"ME",
    "wof:name":"Imperial Homes",
    "wof:placetype":"venue"
},
  "geometry": {"coordinates":[-68.649575,44.821213],"type":"Point"}
}