{
  "type": "Feature",
  "properties": {
    "addr:full":"12 Pike St Augusta ME 04330",
    "addr:housenumber":"12",
    "addr:postcode":"04330",
    "addr:street":"Pike St",
    "iso:country":"US",
    "sg:address":"12 Pike St",
    "sg:city":"Augusta",
    "sg:classifiers":[
        {
            "category":"Professional",
            "type":"Services"
        }
    ],
    "sg:phone":"+1 207 623 4896",
    "sg:postcode":"04330",
    "sg:province":"ME",
    "sg:tags":[
        "establishment"
    ],
    "wof:name":"Broadfusion Inc",
    "wof:placetype":"venue"
},
  "geometry": {"coordinates":[-69.790031,44.312286],"type":"Point"}
}