{
  "type": "Feature",
  "properties": {
    "iso:country":"US",
    "sg:address":"21 Russell Ave",
    "sg:city":"Auburn",
    "sg:classifiers":[
        {
            "category":"Building & Trades",
            "subcategory":"Construction",
            "type":"Services"
        }
    ],
    "sg:phone":"+1 207 784 1874",
    "sg:postcode":"04210",
    "sg:province":"ME",
    "sg:tags":[
        "tile",
        "dealer"
    ],
    "wof:name":"Ronald Nichols",
    "wof:placetype":"venue"
},
  "geometry": {"coordinates":[-70.243101,44.094703],"type":"Point"}
}