{
  "type": "Feature",
  "properties": {
    "iso:country":"US",
    "sg:address":"20 E Ridge Rd",
    "sg:city":"Blue Hill",
    "sg:classifiers":[
        {
            "category":"Education",
            "subcategory":"School",
            "type":"Public Place"
        }
    ],
    "sg:phone":"+1 207 374 9927",
    "sg:postcode":"04679",
    "sg:province":"ME",
    "wof:name":"Blue Hill Superintendent-Schl",
    "wof:placetype":"venue"
},
  "geometry": {"coordinates":[-68.335535,44.285907],"type":"Point"}
}