{
  "type": "Feature",
  "properties": {
    "addr:full":"40 Old Union Rd Washington ME 04574",
    "addr:housenumber":"40",
    "addr:postcode":"04574",
    "addr:street":"Old Union Rd",
    "iso:country":"US",
    "sg:address":"40 Old Union Rd",
    "sg:city":"Washington",
    "sg:classifiers":[
        {
            "category":"Government",
            "subcategory":"Office",
            "type":"Public Place"
        }
    ],
    "sg:phone":"+1 207 845 2897",
    "sg:postcode":"04574",
    "sg:province":"ME",
    "sg:tags":[
        "village"
    ],
    "wof:name":"Washington Town Office",
    "wof:placetype":"venue"
},
  "geometry": {"coordinates":[-69.353336,44.264782],"type":"Point"}
}