{
  "type": "Feature",
  "properties": {
    "addr:full":"24 Windy St Augusta ME 04330",
    "addr:housenumber":"24",
    "addr:postcode":"04330",
    "addr:street":"Windy St",
    "iso:country":"US",
    "sg:address":"24 Windy St",
    "sg:city":"Augusta",
    "sg:classifiers":[
        {
            "category":"Building & Trades",
            "subcategory":"Construction",
            "type":"Services"
        }
    ],
    "sg:phone":"+1 207 622 2772",
    "sg:postcode":"04330",
    "sg:province":"ME",
    "sg:tags":[
        "painter"
    ],
    "wof:name":"Sid Pare & Son Painters",
    "wof:placetype":"venue"
},
  "geometry": {"coordinates":[-69.78783300000001,44.334308],"type":"Point"}
}