{
  "type": "Feature",
  "properties": {
    "addr:full":"125 Front St Bath ME 04530",
    "addr:housenumber":"125",
    "addr:postcode":"04530",
    "addr:street":"Front St",
    "iso:country":"US",
    "sg:address":"125 Front St",
    "sg:city":"Bath",
    "sg:classifiers":[
        {
            "category":"Banks & Credit Unions",
            "subcategory":"Bank",
            "type":"Services"
        }
    ],
    "sg:phone":"+1 207 442 8711",
    "sg:postcode":"04530",
    "sg:province":"ME",
    "sg:tags":[
        "savings",
        "loan",
        "association"
    ],
    "wof:name":"First Federal Savings & Loan",
    "wof:placetype":"venue"
},
  "geometry": {"coordinates":[-69.814296,43.9145],"type":"Point"}
}