{
  "type": "Feature",
  "properties": {
    "iso:country":"US",
    "sg:address":"570 Main Rd",
    "sg:city":"Holden",
    "sg:classifiers":[
        {
            "category":"Government",
            "subcategory":"Office",
            "type":"Public Place"
        }
    ],
    "sg:phone":"+1 207 843 5151",
    "sg:postcode":"04429",
    "sg:province":"ME",
    "sg:tags":[
        "village"
    ],
    "wof:name":"Holden Town Office",
    "wof:placetype":"venue"
},
  "geometry": {"coordinates":[-68.712636,44.76752],"type":"Point"}
}