{
  "type": "Feature",
  "properties": {
    "iso:country":"US",
    "sg:address":"541 Ocean House Rd",
    "sg:city":"Cape Elizabeth",
    "sg:classifiers":[
        {
            "category":"Home & Garden",
            "subcategory":"Garden Supply",
            "type":"Retail Goods"
        }
    ],
    "sg:phone":"+1 207 799 5140",
    "sg:postcode":"04107",
    "sg:province":"ME",
    "sg:tags":[
        "lawn",
        "mower"
    ],
    "wof:name":"Jordan's Lawn & Garden Ctr",
    "wof:placetype":"venue"
},
  "geometry": {"coordinates":[-70.222617,43.570291],"type":"Point"}
}