{
  "type": "Feature",
  "properties": {
    "addr:full":"19 Horn Hill Rd Fairfield ME 04937",
    "addr:housenumber":"19",
    "addr:postcode":"04937",
    "addr:street":"Horn Hill Rd",
    "iso:country":"US",
    "sg:address":"19 Horn Hill Rd",
    "sg:city":"Fairfield",
    "sg:classifiers":[
        {
            "category":"Building & Trades",
            "subcategory":"Construction",
            "type":"Services"
        }
    ],
    "sg:phone":"+1 207 465 9618",
    "sg:postcode":"04937",
    "sg:province":"ME",
    "sg:tags":[
        "masonry",
        "contractor"
    ],
    "wof:name":"Fairfield Masonry",
    "wof:placetype":"venue"
},
  "geometry": {"coordinates":[-69.71526900000001,44.611989],"type":"Point"}
}