{
  "type": "Feature",
  "properties": {
    "iso:country":"US",
    "sg:address":"146 Ocean St",
    "sg:city":"South Portland",
    "sg:classifiers":[
        {
            "category":"Education",
            "subcategory":"Special Training",
            "type":"Public Place"
        }
    ],
    "sg:phone":"+1 207 767 3900",
    "sg:postcode":"04106",
    "sg:province":"ME",
    "sg:tags":[
        "instruction",
        "driving"
    ],
    "wof:name":"Best-Way Driving School",
    "wof:placetype":"venue"
},
  "geometry": {"coordinates":[-70.25271600000001,43.637791],"type":"Point"}
}