{
  "type": "Feature",
  "properties": {
    "addr:full":"137 S Belfast Ave Augusta ME 04330",
    "addr:housenumber":"137",
    "addr:postcode":"04330",
    "addr:street":"S Belfast Ave",
    "iso:country":"US",
    "sg:address":"137 S Belfast Ave",
    "sg:city":"Augusta",
    "sg:classifiers":[
        {
            "category":"Arts & Performance",
            "subcategory":"Theater",
            "type":"Entertainment"
        }
    ],
    "sg:phone":"+1 207 622 1053",
    "sg:postcode":"04330",
    "sg:province":"ME",
    "sg:tags":[
        "group"
    ],
    "wof:name":"Mrks Music",
    "wof:placetype":"venue"
},
  "geometry": {"coordinates":[-69.751783,44.320002],"type":"Point"}
}