{
  "type": "Feature",
  "properties": {
    "iso:country":"US",
    "sg:address":"125 Cony St",
    "sg:city":"Augusta",
    "sg:classifiers":[
        {
            "category":"Professional",
            "subcategory":"Computer Services",
            "type":"Services"
        }
    ],
    "sg:phone":"+1 207 626 0647",
    "sg:postcode":"04330",
    "sg:province":"ME",
    "sg:tags":[
        "datum"
    ],
    "wof:name":"Disflux Internet Services",
    "wof:placetype":"venue"
},
  "geometry": {"coordinates":[-69.765193,44.31635],"type":"Point"}
}