{
  "type": "Feature",
  "properties": {
    "addr:full":"412 State St Bangor ME 04401",
    "addr:housenumber":"412",
    "addr:postcode":"04401",
    "addr:street":"State St",
    "iso:country":"US",
    "sg:address":"412 State St",
    "sg:city":"Bangor",
    "sg:classifiers":[
        {
            "category":"Social Services",
            "subcategory":"Child Care",
            "type":"Services"
        }
    ],
    "sg:phone":"+1 207 973 4994",
    "sg:postcode":"04401",
    "sg:province":"ME",
    "wof:name":"Wing Park Children's Ctr",
    "wof:placetype":"venue"
},
  "geometry": {"coordinates":[-68.75490499999999,44.807947],"type":"Point"}
}