{
  "type": "Feature",
  "properties": {
    "addr:full":"169 Hartland Ave Pittsfield ME 04967",
    "addr:housenumber":"169",
    "addr:postcode":"04967",
    "addr:street":"Hartland Ave",
    "iso:country":"US",
    "sg:address":"169 Hartland Ave",
    "sg:city":"Pittsfield",
    "sg:classifiers":[
        {
            "category":"Autos & Motor Vehicles",
            "subcategory":"Automobile Sales",
            "type":"Retail Goods"
        }
    ],
    "sg:phone":"+1 207 487 5465",
    "sg:postcode":"04967",
    "sg:province":"ME",
    "sg:tags":[
        "used"
    ],
    "wof:name":"Folsom Used Cars",
    "wof:placetype":"venue"
},
  "geometry": {"coordinates":[-69.392732,44.799449],"type":"Point"}
}