{
  "type": "Feature",
  "properties": {
    "addr:full":"7 Ocean St South Portland ME 04106",
    "addr:housenumber":"7",
    "addr:postcode":"04106",
    "addr:street":"Ocean St",
    "iso:country":"US",
    "sg:address":"7 Ocean St",
    "sg:city":"South Portland",
    "sg:classifiers":[
        {
            "category":"Professional",
            "type":"Services"
        }
    ],
    "sg:phone":"+1 207 879 9200",
    "sg:postcode":"04106",
    "sg:province":"ME",
    "sg:tags":[
        "actuary"
    ],
    "sg:website":"www.adsbenefits.com",
    "wof:name":"Actuarial Designs & Solutions",
    "wof:placetype":"venue"
},
  "geometry": {"coordinates":[-70.25543,43.641609],"type":"Point"}
}