{
  "type": "Feature",
  "properties": {
    "iso:country":"US",
    "sg:address":"188 State St",
    "sg:city":"Portland",
    "sg:classifiers":[
        {
            "category":"Food & Beverages",
            "subcategory":"Fruits & Vegetables",
            "type":"Retail Goods"
        }
    ],
    "sg:phone":"+1 207 761 0345",
    "sg:postcode":"04101",
    "sg:province":"ME",
    "sg:tags":[
        "produce"
    ],
    "wof:name":"Farm Fresh Connections",
    "wof:placetype":"venue"
},
  "geometry": {"coordinates":[-70.267037,43.653024],"type":"Point"}
}