{
  "type": "Feature",
  "properties": {
    "iso:country":"US",
    "sg:address":"235 Pond Rd",
    "sg:city":"Lewiston",
    "sg:classifiers":[
        {
            "category":"Banks & Credit Unions",
            "subcategory":"Investment Brokerage",
            "type":"Services"
        }
    ],
    "sg:phone":"+1 207 795 7954",
    "sg:postcode":"04240",
    "sg:province":"ME",
    "sg:tags":[
        "consultant",
        "planning",
        "financial"
    ],
    "wof:name":"James Jackson IV",
    "wof:placetype":"venue"
},
  "geometry": {"coordinates":[-70.157552,44.096151],"type":"Point"}
}