{
  "type": "Feature",
  "properties": {
    "addr:full":"95 Warren Ave Westbrook ME 04092",
    "addr:housenumber":"95",
    "addr:postcode":"04092",
    "addr:street":"Warren Ave",
    "iso:country":"US",
    "sg:address":"95 Warren Ave",
    "sg:city":"Westbrook",
    "sg:classifiers":[
        {
            "category":"Building & Trades",
            "subcategory":"Construction",
            "type":"Services"
        }
    ],
    "sg:phone":"+1 207 854 0436",
    "sg:postcode":"04092",
    "sg:province":"ME",
    "sg:tags":[
        "general",
        "contractor"
    ],
    "wof:name":"White Brothers Inc",
    "wof:placetype":"venue"
},
  "geometry": {"coordinates":[-70.343909,43.685185],"type":"Point"}
}