{
  "type": "Feature",
  "properties": {
    "addr:full":"300 North St Houlton ME 04730",
    "addr:housenumber":"300",
    "addr:postcode":"04730",
    "addr:street":"North St",
    "iso:country":"US",
    "sg:address":"300 North St",
    "sg:city":"Houlton",
    "sg:classifiers":[
        {
            "category":"Shopping",
            "subcategory":"Jewelry",
            "type":"Retail Goods"
        }
    ],
    "sg:phone":"+1 207 532 3047",
    "sg:postcode":"04730",
    "sg:province":"ME",
    "sg:tags":[
        "jeweler"
    ],
    "sg:website":"www.goodrichjewelry.com",
    "wof:name":"Goodrich Jewelry",
    "wof:placetype":"venue"
},
  "geometry": {"coordinates":[-67.840413,46.144121],"type":"Point"}
}