{
  "type": "Feature",
  "properties": {
    "iso:country":"US",
    "sg:address":"326 Main St",
    "sg:city":"Cumberland Ctr",
    "sg:classifiers":[
        {
            "category":"Health Services",
            "subcategory":"Podiatrist",
            "type":"Services"
        }
    ],
    "sg:phone":"+1 207 829 6463",
    "sg:postcode":"04021",
    "sg:province":"ME",
    "wof:name":"Bayside Podiatry",
    "wof:placetype":"venue"
},
  "geometry": {"coordinates":[-70.255423,43.800425],"type":"Point"}
}