{
  "type": "Feature",
  "properties": {
    "addr:full":"4c Hamilton Ct Topsham ME 04086",
    "addr:housenumber":"4c",
    "addr:postcode":"04086",
    "addr:street":"Hamilton Ct",
    "iso:country":"US",
    "sg:address":"4c Hamilton Ct",
    "sg:city":"Topsham",
    "sg:classifiers":[
        {
            "category":"Bakery",
            "type":"Food & Drink"
        },
        {
            "category":"Coffee & Tea",
            "type":"Food & Drink"
        },
        {
            "category":"Bagels",
            "type":"Food & Drink"
        },
        {
            "category":"Donuts",
            "type":"Food & Drink"
        }
    ],
    "sg:menulink":"http://www.allmenus.com/me/topsham/149075-dunkin-donuts/menu/",
    "sg:phone":"+1 207 373 0837",
    "sg:postcode":"04086",
    "sg:province":"ME",
    "sg:tags":[
        "wrap",
        "american",
        "sandwich",
        "pastry"
    ],
    "wof:name":"Dunkin' Donuts",
    "wof:placetype":"venue"
},
  "geometry": {"coordinates":[-69.971475,43.937735],"type":"Point"}
}