{
  "type": "Feature",
  "properties": {
    "addr:full":"41 Lawrence Rd Gray ME 04039",
    "addr:housenumber":"41",
    "addr:postcode":"04039",
    "addr:street":"Lawrence Rd",
    "iso:country":"US",
    "sg:address":"41 Lawrence Rd",
    "sg:city":"Gray",
    "sg:classifiers":[
        {
            "category":"Building & Trades",
            "subcategory":"Construction",
            "type":"Services"
        }
    ],
    "sg:phone":"+1 207 428 3462",
    "sg:postcode":"04039",
    "sg:province":"ME",
    "sg:tags":[
        "hanging",
        "contractor"
    ],
    "wof:name":"Chets Painting",
    "wof:placetype":"venue"
},
  "geometry": {"coordinates":[-70.353934,43.851697],"type":"Point"}
}