{
  "type": "Feature",
  "properties": {
    "addr:full":"40 Western Ave Augusta ME 04330",
    "addr:housenumber":"40",
    "addr:postcode":"04330",
    "addr:street":"Western Ave",
    "iso:country":"US",
    "sg:address":"40 Western Ave",
    "sg:city":"Augusta",
    "sg:classifiers":[
        {
            "category":"Professional",
            "subcategory":"Management & Consulting",
            "type":"Services"
        }
    ],
    "sg:phone":"+1 207 622 8509",
    "sg:postcode":"04330",
    "sg:province":"ME",
    "sg:tags":[
        "consultant",
        "business"
    ],
    "wof:name":"Score",
    "wof:placetype":"venue"
},
  "geometry": {"coordinates":[-69.784486,44.311363],"type":"Point"}
}