{
  "type": "Feature",
  "properties": {
    "addr:full":"84 Ridley Rd Sanford ME 04073",
    "addr:housenumber":"84",
    "addr:postcode":"04073",
    "addr:street":"Ridley Rd",
    "iso:country":"US",
    "sg:address":"84 Ridley Rd",
    "sg:city":"Sanford",
    "sg:classifiers":[
        {
            "category":"Professional",
            "subcategory":"Business Services",
            "type":"Services"
        }
    ],
    "sg:phone":"+1 207 651 3146",
    "sg:postcode":"04073",
    "sg:province":"ME",
    "wof:name":"Mary Jane Grant",
    "wof:placetype":"venue"
},
  "geometry": {"coordinates":[-70.770954,43.467351],"type":"Point"}
}