{
  "type": "Feature",
  "properties": {
    "iso:country":"US",
    "sg:address":"34 Cherryfield Ave",
    "sg:city":"Saco",
    "sg:classifiers":[
        {
            "category":"Building & Trades",
            "subcategory":"Construction",
            "type":"Services"
        }
    ],
    "sg:phone":"+1 207 282 9207",
    "sg:postcode":"04072",
    "sg:province":"ME",
    "sg:tags":[
        "general",
        "contractor"
    ],
    "wof:name":"Maine Roads & Driveways",
    "wof:placetype":"venue"
},
  "geometry": {"coordinates":[-70.459511,43.512931],"type":"Point"}
}