{
  "type": "Feature",
  "properties": {
    "iso:country":"US",
    "sg:address":"4 Union St",
    "sg:city":"Bangor",
    "sg:classifiers":[
        {
            "category":"Home & Garden",
            "subcategory":"Carpets & Floor Coverings",
            "type":"Retail Goods"
        }
    ],
    "sg:phone":"+1 207 942 4447",
    "sg:postcode":"04401",
    "sg:province":"ME",
    "sg:tags":[
        "dealer",
        "rug"
    ],
    "wof:name":"Expert Flooring",
    "wof:placetype":"venue"
},
  "geometry": {"coordinates":[-68.771219,44.79808],"type":"Point"}
}