{
  "type": "Feature",
  "properties": {
    "iso:country":"US",
    "sg:address":"6 Arbor Rd",
    "sg:city":"Falmouth",
    "sg:classifiers":[
        {
            "category":"Manufacturing",
            "subcategory":"Tools & Machinery",
            "type":"Manufacturing & Wholesale Goods"
        }
    ],
    "sg:phone":"+1 207 781 2313",
    "sg:postcode":"04105",
    "sg:province":"ME",
    "sg:tags":[
        "oil",
        "gas"
    ],
    "wof:name":"J M Huber Corp",
    "wof:placetype":"venue"
},
  "geometry": {"coordinates":[-70.245506,43.757408],"type":"Point"}
}