{
  "type": "Feature",
  "properties": {
    "iso:country":"US",
    "sg:address":"337 Commercial St",
    "sg:city":"Rockport",
    "sg:classifiers":[
        {
            "category":"Travel",
            "subcategory":"Hotels & Motels",
            "type":"Entertainment"
        }
    ],
    "sg:phone":"+1 207 236 2205",
    "sg:postcode":"04856",
    "sg:province":"ME",
    "wof:name":"Schooner Bay Motor Inn",
    "wof:placetype":"venue"
},
  "geometry": {"coordinates":[-69.080508,44.178978],"type":"Point"}
}