{
  "type": "Feature",
  "properties": {
    "addr:full":"757 Congress St Portland ME 04102",
    "addr:housenumber":"757",
    "addr:postcode":"04102",
    "addr:street":"Congress St",
    "iso:country":"US",
    "sg:address":"757 Congress St",
    "sg:city":"Portland",
    "sg:classifiers":[
        {
            "category":"Real Estate",
            "subcategory":"Architect",
            "type":"Services"
        }
    ],
    "sg:phone":"+1 207 787 4393",
    "sg:postcode":"04102",
    "sg:province":"ME",
    "wof:name":"Leslie Davis Architect",
    "wof:placetype":"venue"
},
  "geometry": {"coordinates":[-70.270291,43.653292],"type":"Point"}
}