{
  "type": "Feature",
  "properties": {
    "iso:country":"US",
    "sg:address":"34 Turner Ave",
    "sg:city":"Skowhegan",
    "sg:classifiers":[
        {
            "category":"Shopping",
            "subcategory":"Used Merchandise",
            "type":"Retail Goods"
        },
        {
            "category":"Wholesale",
            "subcategory":"Durable Goods & Equipment",
            "type":"Manufacturing & Wholesale Goods"
        }
    ],
    "sg:phone":"+1 207 474 9676",
    "sg:postcode":"04976",
    "sg:province":"ME",
    "sg:tags":[
        "antique"
    ],
    "wof:name":"David L Jewell Sr",
    "wof:placetype":"venue"
},
  "geometry": {"coordinates":[-69.723253,44.762229],"type":"Point"}
}