{
  "type": "Feature",
  "properties": {
    "iso:country":"US",
    "sg:address":"50 Forest Falls Dr",
    "sg:city":"Yarmouth",
    "sg:classifiers":[
        {
            "category":"Insurance",
            "subcategory":"Insurance Agent",
            "type":"Services"
        }
    ],
    "sg:phone":"+1 207 846 4910",
    "sg:postcode":"04096",
    "sg:province":"ME",
    "wof:name":"Homewood Benefits",
    "wof:placetype":"venue"
},
  "geometry": {"coordinates":[-70.184642,43.804776],"type":"Point"}
}