{
  "type": "Feature",
  "properties": {
    "addr:full":"23 Burrill Hill Rd Norridgewock ME 04957",
    "addr:housenumber":"23",
    "addr:postcode":"04957",
    "addr:street":"Burrill Hill Rd",
    "iso:country":"US",
    "sg:address":"23 Burrill Hill Rd",
    "sg:city":"Norridgewock",
    "sg:classifiers":[
        {
            "category":"Personal",
            "subcategory":"Beauty Salon",
            "type":"Services"
        }
    ],
    "sg:phone":"+1 207 634 3274",
    "sg:postcode":"04957",
    "sg:province":"ME",
    "wof:name":"Jean's Hair Fashions",
    "wof:placetype":"venue"
},
  "geometry": {"coordinates":[-69.773083,44.71308],"type":"Point"}
}