{
  "type": "Feature",
  "properties": {
    "iso:country":"US",
    "sg:address":"1172 State Rte 32",
    "sg:city":"Round Pond",
    "sg:classifiers":[
        {
            "category":"Shopping",
            "subcategory":"Used Merchandise",
            "type":"Retail Goods"
        }
    ],
    "sg:phone":"+1 207 529 5555",
    "sg:postcode":"04564",
    "sg:province":"ME",
    "sg:tags":[
        "book",
        "rare",
        "dealer"
    ],
    "wof:name":"Jean Gillespie",
    "wof:placetype":"venue"
},
  "geometry": {"coordinates":[-69.480494,43.92686],"type":"Point"}
}