{
  "type": "Feature",
  "properties": {
    "addr:full":"239 Pearl St Bangor ME 04401",
    "addr:housenumber":"239",
    "addr:postcode":"04401",
    "addr:street":"Pearl St",
    "iso:country":"US",
    "sg:address":"239 Pearl St",
    "sg:city":"Bangor",
    "sg:classifiers":[
        {
            "category":"Social Services",
            "subcategory":"Child Care",
            "type":"Services"
        }
    ],
    "sg:phone":"+1 207 947 6128",
    "sg:postcode":"04401",
    "sg:province":"ME",
    "wof:name":"Home Away From Home",
    "wof:placetype":"venue"
},
  "geometry": {"coordinates":[-68.75762,44.810683],"type":"Point"}
}