{
  "type": "Feature",
  "properties": {
    "addr:full":"13 Pari Pl Portland ME 04103",
    "addr:housenumber":"13",
    "addr:postcode":"04103",
    "addr:street":"Pari Pl",
    "iso:country":"US",
    "sg:address":"13 Pari Pl",
    "sg:city":"Portland",
    "sg:classifiers":[
        {
            "category":"Building & Trades",
            "subcategory":"Electrical",
            "type":"Services"
        }
    ],
    "sg:phone":"+1 207 797 2773",
    "sg:postcode":"04103",
    "sg:province":"ME",
    "sg:tags":[
        "electric",
        "contractor"
    ],
    "wof:name":"Greg Gould Electric Inc",
    "wof:placetype":"venue"
},
  "geometry": {"coordinates":[-70.312432,43.696754],"type":"Point"}
}