{
  "type": "Feature",
  "properties": {
    "iso:country":"US",
    "sg:address":"70 Main Rd S",
    "sg:city":"Hampden",
    "sg:classifiers":[
        {
            "category":"Banks & Credit Unions",
            "subcategory":"Investment Brokerage",
            "type":"Services"
        }
    ],
    "sg:phone":"+1 207 862 2952",
    "sg:postcode":"04444",
    "sg:province":"ME",
    "sg:tags":[
        "security"
    ],
    "wof:name":"Norumbega Financial Svc",
    "wof:placetype":"venue"
},
  "geometry": {"coordinates":[-68.840931,44.735946],"type":"Point"}
}