{
  "type": "Feature",
  "properties": {
    "addr:full":"3 Candy Ln Brunswick ME 04011",
    "addr:housenumber":"3",
    "addr:postcode":"04011",
    "addr:street":"Candy Ln",
    "iso:country":"US",
    "sg:address":"3 Candy Ln",
    "sg:city":"Brunswick",
    "sg:classifiers":[
        {
            "category":"Education",
            "subcategory":"School",
            "type":"Public Place"
        }
    ],
    "sg:phone":"+1 207 443 2251",
    "sg:postcode":"04011",
    "sg:province":"ME",
    "wof:name":"P Macarthur Barry",
    "wof:placetype":"venue"
},
  "geometry": {"coordinates":[-69.879807,43.934846],"type":"Point"}
}