{
  "type": "Feature",
  "properties": {
    "iso:country":"US",
    "sg:address":"545 Main St",
    "sg:city":"Waterboro",
    "sg:classifiers":[
        {
            "category":"Professional",
            "subcategory":"Art Services",
            "type":"Services"
        }
    ],
    "sg:phone":"+1 207 247 4300",
    "sg:postcode":"04038",
    "sg:province":"ME",
    "sg:tags":[
        "photographer"
    ],
    "wof:name":"Cynthia Gilmore Photographer",
    "wof:placetype":"venue"
},
  "geometry": {"coordinates":[-70.404658,43.690671],"type":"Point"}
}