{
  "type": "Feature",
  "properties": {
    "addr:full":"27 Main St Machias ME 04654",
    "addr:housenumber":"27",
    "addr:postcode":"04654",
    "addr:street":"Main St",
    "iso:country":"US",
    "sg:address":"27 Main St",
    "sg:city":"Machias",
    "sg:classifiers":[
        {
            "category":"Shopping",
            "subcategory":"Used Merchandise",
            "type":"Retail Goods"
        }
    ],
    "sg:phone":"+1 207 255 6035",
    "sg:postcode":"04654",
    "sg:province":"ME",
    "sg:tags":[
        "antique"
    ],
    "wof:name":"Main Street Discount",
    "wof:placetype":"venue"
},
  "geometry": {"coordinates":[-67.457516,44.715098],"type":"Point"}
}