{
  "type": "Feature",
  "properties": {
    "iso:country":"US",
    "sg:address":"51 Depot St",
    "sg:city":"Bridgton",
    "sg:classifiers":[
        {
            "category":"Social Services",
            "type":"Services"
        }
    ],
    "sg:phone":"+1 207 647 0954",
    "sg:postcode":"04009",
    "sg:province":"ME",
    "sg:tags":[
        "counselor",
        "marriage",
        "family"
    ],
    "wof:name":"Colleen Danley",
    "wof:placetype":"venue"
},
  "geometry": {"coordinates":[-70.70500199999999,44.052859],"type":"Point"}
}