{
  "type": "Feature",
  "properties": {
    "iso:country":"US",
    "sg:address":"16 Northbrook Dr",
    "sg:city":"Falmouth",
    "sg:classifiers":[
        {
            "category":"Professional",
            "subcategory":"Accounting & Tax Preparation",
            "type":"Services"
        }
    ],
    "sg:phone":"+1 207 781 3391",
    "sg:postcode":"04105",
    "sg:province":"ME",
    "sg:tags":[
        "accountant"
    ],
    "wof:name":"Harris & Vickers",
    "wof:placetype":"venue"
},
  "geometry": {"coordinates":[-70.220204,43.73593],"type":"Point"}
}