{
  "type": "Feature",
  "properties": {
    "addr:full":"711 Main St Moose River ME 04965",
    "addr:housenumber":"711",
    "addr:postcode":"04965",
    "addr:street":"Main St",
    "iso:country":"US",
    "sg:address":"711 Main St",
    "sg:city":"Moose River",
    "sg:classifiers":[
        {
            "category":"Organizations",
            "subcategory":"Religious Organization",
            "type":"Services"
        }
    ],
    "sg:phone":"+1 207 668 7719",
    "sg:postcode":"04965",
    "sg:province":"ME",
    "sg:tags":[
        "church"
    ],
    "wof:name":"Fellowship Alliance Church",
    "wof:placetype":"venue"
},
  "geometry": {"coordinates":[-69.376946,44.846215],"type":"Point"}
}