{
  "type": "Feature",
  "properties": {
    "iso:country":"US",
    "sg:address":"415 Lisbon St",
    "sg:city":"Lewiston",
    "sg:classifiers":[
        {
            "category":"Professional",
            "type":"Services"
        }
    ],
    "sg:phone":"+1 207 784 1857",
    "sg:postcode":"04240",
    "sg:province":"ME",
    "sg:tags":[
        "establishment"
    ],
    "wof:name":"Hebert Danl Inc",
    "wof:placetype":"venue"
},
  "geometry": {"coordinates":[-70.213594,44.090641],"type":"Point"}
}