{
  "type": "Feature",
  "properties": {
    "addr:full":"144 N Newcastle Rd Newcastle ME 04553",
    "addr:housenumber":"144",
    "addr:postcode":"04553",
    "addr:street":"N Newcastle Rd",
    "iso:country":"US",
    "sg:address":"144 N Newcastle Rd",
    "sg:city":"Newcastle",
    "sg:classifiers":[
        {
            "category":"Building & Trades",
            "subcategory":"Construction",
            "type":"Services"
        }
    ],
    "sg:phone":"+1 207 586 5997",
    "sg:postcode":"04553",
    "sg:province":"ME",
    "sg:tags":[
        "excavating",
        "contractor"
    ],
    "wof:name":"Fowler Excavation",
    "wof:placetype":"venue"
},
  "geometry": {"coordinates":[-69.59231200000001,44.061834],"type":"Point"}
}