{
  "type": "Feature",
  "properties": {
    "iso:country":"US",
    "sg:address":"276 Townsend Ave",
    "sg:city":"Boothbay Harbor",
    "sg:classifiers":[
        {
            "category":"Home & Garden",
            "subcategory":"Building Materials",
            "type":"Retail Goods"
        }
    ],
    "sg:phone":"+1 207 633 4474",
    "sg:postcode":"04538",
    "sg:province":"ME",
    "sg:tags":[
        "lumber"
    ],
    "wof:name":"Poole Brothers Lumber",
    "wof:placetype":"venue"
},
  "geometry": {"coordinates":[-69.627422,43.862215],"type":"Point"}
}