{
  "type": "Feature",
  "properties": {
    "addr:full":"59 Court St Augusta ME 04330",
    "addr:housenumber":"59",
    "addr:postcode":"04330",
    "addr:street":"Court St",
    "iso:country":"US",
    "sg:address":"59 Court St",
    "sg:city":"Augusta",
    "sg:classifiers":[
        {
            "category":"Government",
            "subcategory":"Office",
            "type":"Public Place"
        }
    ],
    "sg:phone":"+1 207 623 2464",
    "sg:postcode":"04330",
    "sg:province":"ME",
    "wof:name":"Maine Board Of Bar Examiners",
    "wof:placetype":"venue"
},
  "geometry": {"coordinates":[-69.7812,44.315095],"type":"Point"}
}