{
  "type": "Feature",
  "properties": {
    "addr:full":"640 Elm St Biddeford ME 04005",
    "addr:housenumber":"640",
    "addr:postcode":"04005",
    "addr:street":"Elm St",
    "iso:country":"US",
    "sg:address":"640 Elm St",
    "sg:city":"Biddeford",
    "sg:classifiers":[
        {
            "category":"Autos & Motor Vehicles",
            "subcategory":"Auto Supplies",
            "type":"Retail Goods"
        }
    ],
    "sg:phone":"+1 207 282 5192",
    "sg:postcode":"04005",
    "sg:province":"ME",
    "sg:tags":[
        "tire"
    ],
    "wof:name":"Discount Tire & Alignment",
    "wof:placetype":"venue"
},
  "geometry": {"coordinates":[-70.49137899999999,43.4616],"type":"Point"}
}