{
  "type": "Feature",
  "properties": {
    "addr:full":"140 S Richland St South Portland ME 04106",
    "addr:housenumber":"140",
    "addr:postcode":"04106",
    "addr:street":"S Richland St",
    "iso:country":"US",
    "sg:address":"140 S Richland St",
    "sg:city":"South Portland",
    "sg:classifiers":[
        {
            "category":"Professional",
            "subcategory":"Secretarial Services",
            "type":"Services"
        }
    ],
    "sg:phone":"+1 207 252 5787",
    "sg:postcode":"04106",
    "sg:province":"ME",
    "sg:tags":[
        "reporting",
        "court"
    ],
    "wof:name":"Michael Torrusio",
    "wof:placetype":"venue"
},
  "geometry": {"coordinates":[-70.24562899999999,43.634273],"type":"Point"}
}