{
  "type": "Feature",
  "properties": {
    "addr:full":"100 Campus Ave Lewiston ME 04240",
    "addr:housenumber":"100",
    "addr:postcode":"04240",
    "addr:street":"Campus Ave",
    "iso:country":"US",
    "sg:address":"100 Campus Ave",
    "sg:city":"Lewiston",
    "sg:classifiers":[
        {
            "category":"Bakery",
            "type":"Food & Drink"
        },
        {
            "category":"Coffee & Tea",
            "type":"Food & Drink"
        },
        {
            "category":"Bagels",
            "type":"Food & Drink"
        },
        {
            "category":"Donuts",
            "type":"Food & Drink"
        }
    ],
    "sg:menulink":"http://www.allmenus.com/me/lewiston/149102-dunkin-donuts/menu/",
    "sg:phone":"+1 207 783 8600",
    "sg:postcode":"04240",
    "sg:province":"ME",
    "sg:tags":[
        "wrap",
        "american",
        "sandwich",
        "pastry"
    ],
    "wof:name":"Dunkin' Donuts",
    "wof:placetype":"venue"
},
  "geometry": {"coordinates":[-70.201015,44.10277],"type":"Point"}
}