{
  "type": "Feature",
  "properties": {
    "addr:full":"36 Waldron Way Portland ME 04103",
    "addr:housenumber":"36",
    "addr:postcode":"04103",
    "addr:street":"Waldron Way",
    "iso:country":"US",
    "sg:address":"36 Waldron Way",
    "sg:city":"Portland",
    "sg:classifiers":[
        {
            "category":"Professional",
            "subcategory":"Business Services",
            "type":"Services"
        }
    ],
    "sg:phone":"+1 207 797 5028",
    "sg:postcode":"04103",
    "sg:province":"ME",
    "sg:tags":[
        "embroidery"
    ],
    "sg:website":"www.atlanticsportswear.com",
    "wof:name":"Atlantic Sportswear",
    "wof:placetype":"venue"
},
  "geometry": {"coordinates":[-70.321528,43.696717],"type":"Point"}
}