{
  "type": "Feature",
  "properties": {
    "addr:full":"15 Elizabeth Ln Kittery Point ME 03905",
    "addr:housenumber":"15",
    "addr:postcode":"03905",
    "addr:street":"Elizabeth Ln",
    "iso:country":"US",
    "sg:address":"15 Elizabeth Ln",
    "sg:city":"Kittery Point",
    "sg:classifiers":[
        {
            "category":"Social Services",
            "subcategory":"Job Training",
            "type":"Services"
        }
    ],
    "sg:phone":"+1 207 438 9983",
    "sg:postcode":"03905",
    "sg:province":"ME",
    "sg:tags":[
        "rehabilitation"
    ],
    "wof:name":"Pediatric Physical Therapy Svc",
    "wof:placetype":"venue"
},
  "geometry": {"coordinates":[-70.706031,43.101219],"type":"Point"}
}