{
  "type": "Feature",
  "properties": {
    "iso:country":"US",
    "sg:address":"56 Thadeus St",
    "sg:city":"South Portland",
    "sg:classifiers":[
        {
            "category":"Professional",
            "type":"Services"
        }
    ],
    "sg:phone":"+1 207 767 4598",
    "sg:postcode":"04106",
    "sg:province":"ME",
    "sg:tags":[
        "establishment"
    ],
    "wof:name":"Abacus Technical Solutions",
    "wof:placetype":"venue"
},
  "geometry": {"coordinates":[-70.28499,43.626942],"type":"Point"}
}