{
  "type": "Feature",
  "properties": {
    "addr:full":"28 Burnham Rd Scarborough ME 04074",
    "addr:housenumber":"28",
    "addr:postcode":"04074",
    "addr:street":"Burnham Rd",
    "iso:country":"US",
    "sg:address":"28 Burnham Rd",
    "sg:city":"Scarborough",
    "sg:classifiers":[
        {
            "category":"Building & Trades",
            "subcategory":"Construction",
            "type":"Services"
        }
    ],
    "sg:phone":"+1 207 883 4547",
    "sg:postcode":"04074",
    "sg:province":"ME",
    "sg:tags":[
        "contractor"
    ],
    "wof:name":"Malcolm Pottle",
    "wof:placetype":"venue"
},
  "geometry": {"coordinates":[-70.468873,43.6047],"type":"Point"}
}