{
  "type": "Feature",
  "properties": {
    "addr:full":"75 John Roberts Rd South Portland ME 04106",
    "addr:housenumber":"75",
    "addr:postcode":"04106",
    "addr:street":"John Roberts Rd",
    "iso:country":"US",
    "sg:address":"75 John Roberts Rd",
    "sg:city":"South Portland",
    "sg:classifiers":[
        {
            "category":"Health Services",
            "subcategory":"Clinic",
            "type":"Services"
        }
    ],
    "sg:phone":"+1 207 761 0801",
    "sg:postcode":"04106",
    "sg:province":"ME",
    "sg:tags":[
        "rehabilitation",
        "outpatient",
        "facility"
    ],
    "wof:name":"HealthSouth",
    "wof:placetype":"venue"
},
  "geometry": {"coordinates":[-70.330111,43.630256],"type":"Point"}
}