{
  "type": "Feature",
  "properties": {
    "addr:full":"1844 N Lisbon Rd Lewiston ME 04240",
    "addr:housenumber":"1844",
    "addr:postcode":"04240",
    "addr:street":"N Lisbon Rd",
    "iso:country":"US",
    "sg:address":"1844 N Lisbon Rd",
    "sg:city":"Lewiston",
    "sg:classifiers":[
        {
            "category":"Autos & Motor Vehicles",
            "subcategory":"Automobile Sales",
            "type":"Retail Goods"
        }
    ],
    "sg:phone":"+1 207 777 1965",
    "sg:postcode":"04240",
    "sg:province":"ME",
    "sg:tags":[
        "car",
        "dealer"
    ],
    "wof:name":"Rotary Auto Sales",
    "wof:placetype":"venue"
},
  "geometry": {"coordinates":[-70.157324,44.0644],"type":"Point"}
}