{
  "type": "Feature",
  "properties": {
    "addr:full":"86 Davis St South Portland ME 04106",
    "addr:housenumber":"86",
    "addr:postcode":"04106",
    "addr:street":"Davis St",
    "iso:country":"US",
    "sg:address":"86 Davis St",
    "sg:city":"South Portland",
    "sg:classifiers":[
        {
            "category":"Building & Trades",
            "subcategory":"Construction",
            "type":"Services"
        }
    ],
    "sg:phone":"+1 207 799 0059",
    "sg:postcode":"04106",
    "sg:province":"ME",
    "sg:tags":[
        "contractor"
    ],
    "wof:name":"Rosewood Design & Construction",
    "wof:placetype":"venue"
},
  "geometry": {"coordinates":[-70.235901,43.634102],"type":"Point"}
}