{
  "type": "Feature",
  "properties": {
    "addr:full":"1504 Atlantic Hwy Waldoboro ME 04572",
    "addr:housenumber":"1504",
    "addr:postcode":"04572",
    "addr:street":"Atlantic Hwy",
    "iso:country":"US",
    "sg:address":"1504 Atlantic Hwy",
    "sg:city":"Waldoboro",
    "sg:classifiers":[
        {
            "category":"Real Estate",
            "subcategory":"Real Estate Agent",
            "type":"Services"
        }
    ],
    "sg:phone":"+1 207 832 5219",
    "sg:postcode":"04572",
    "sg:province":"ME",
    "wof:name":"Jaret & Cohn",
    "wof:placetype":"venue"
},
  "geometry": {"coordinates":[-69.382075,44.101808],"type":"Point"}
}