{
  "type": "Feature",
  "properties": {
    "addr:full":"79 Bradley Dr Westbrook ME 04092",
    "addr:housenumber":"79",
    "addr:postcode":"04092",
    "addr:street":"Bradley Dr",
    "iso:country":"US",
    "sg:address":"79 Bradley Dr",
    "sg:city":"Westbrook",
    "sg:classifiers":[
        {
            "category":"Retail",
            "subcategory":"Auto Repair",
            "type":"Services"
        }
    ],
    "sg:phone":"+1 207 780 0789",
    "sg:postcode":"04092",
    "sg:province":"ME",
    "sg:tags":[
        "repairing",
        "automobile"
    ],
    "wof:name":"Electric Motorworks",
    "wof:placetype":"venue"
},
  "geometry": {"coordinates":[-70.37138899999999,43.663748],"type":"Point"}
}