{
  "type": "Feature",
  "properties": {
    "addr:full":"400 Seawall Rd Southwest Harbor ME 04679",
    "addr:housenumber":"400",
    "addr:postcode":"04679",
    "addr:street":"Seawall Rd",
    "iso:country":"US",
    "sg:address":"400 Seawall Rd",
    "sg:city":"Southwest Harbor",
    "sg:classifiers":[
        {
            "category":"Manufacturing",
            "subcategory":"Printing",
            "type":"Manufacturing & Wholesale Goods"
        }
    ],
    "sg:phone":"+1 207 244 3106",
    "sg:postcode":"04679",
    "sg:province":"ME",
    "sg:tags":[
        "periodical"
    ],
    "wof:name":"International Trade Info Svc",
    "wof:placetype":"venue"
},
  "geometry": {"coordinates":[-68.323114,44.269509],"type":"Point"}
}