{
  "type": "Feature",
  "properties": {
    "iso:country":"US",
    "sg:address":"9 Grist Mill Ln",
    "sg:city":"Falmouth",
    "sg:classifiers":[
        {
            "category":"Restaurant",
            "type":"Food & Drink"
        }
    ],
    "sg:phone":"+1 207 878 5511",
    "sg:postcode":"04105",
    "sg:province":"ME",
    "sg:tags":[
        "caterer"
    ],
    "wof:name":"Professional Catering Svc",
    "wof:placetype":"venue"
},
  "geometry": {"coordinates":[-70.334775,43.801567],"type":"Point"}
}