{
  "type": "Feature",
  "properties": {
    "addr:full":"317 Main St Westbrook ME 04092",
    "addr:housenumber":"317",
    "addr:postcode":"04092",
    "addr:street":"Main St",
    "iso:country":"US",
    "sg:address":"317 Main St",
    "sg:city":"Westbrook",
    "sg:classifiers":[
        {
            "category":"Manufacturing",
            "subcategory":"Lumber",
            "type":"Manufacturing & Wholesale Goods"
        }
    ],
    "sg:phone":"+1 207 854 0090",
    "sg:postcode":"04092",
    "sg:province":"ME",
    "sg:tags":[
        "company",
        "logging"
    ],
    "wof:name":"Colonial Tree & Landscaping",
    "wof:placetype":"venue"
},
  "geometry": {"coordinates":[-70.34421500000001,43.680429],"type":"Point"}
}