{
  "type": "Feature",
  "properties": {
    "addr:full":"69 Maine St Brunswick ME 04011",
    "addr:housenumber":"69",
    "addr:postcode":"04011",
    "addr:street":"Maine St",
    "iso:country":"US",
    "sg:address":"69 Maine St",
    "sg:city":"Brunswick",
    "sg:classifiers":[
        {
            "category":"Retail",
            "subcategory":"Laundry & Dry Cleaning",
            "type":"Services"
        }
    ],
    "sg:phone":"+1 207 729 0176",
    "sg:postcode":"04011",
    "sg:province":"ME",
    "sg:tags":[
        "cleaners"
    ],
    "wof:name":"J & J Cleaners",
    "wof:placetype":"venue"
},
  "geometry": {"coordinates":[-69.966106,43.916982],"type":"Point"}
}