{
  "type": "Feature",
  "properties": {
    "iso:country":"US",
    "sg:address":"39 Maple St",
    "sg:city":"Knox",
    "sg:classifiers":[
        {
            "category":"Real Estate",
            "subcategory":"Real Estate Operator",
            "type":"Services"
        }
    ],
    "sg:phone":"+1 207 568 3683",
    "sg:postcode":"04963",
    "sg:province":"ME",
    "sg:tags":[
        "building",
        "parks"
    ],
    "sg:website":"www.kinneycompost.com",
    "wof:name":"Royal River Offices Inc",
    "wof:placetype":"venue"
},
  "geometry": {"coordinates":[-69.72072300000001,44.543864],"type":"Point"}
}