{
  "type": "Feature",
  "properties": {
    "addr:full":"271 State St Brewer ME 04412",
    "addr:housenumber":"271",
    "addr:postcode":"04412",
    "addr:street":"State St",
    "iso:country":"US",
    "sg:address":"271 State St",
    "sg:city":"Brewer",
    "sg:classifiers":[
        {
            "category":"Bakery",
            "type":"Food & Drink"
        },
        {
            "category":"Coffee & Tea",
            "type":"Food & Drink"
        },
        {
            "category":"Bagels",
            "type":"Food & Drink"
        },
        {
            "category":"Donuts",
            "type":"Food & Drink"
        }
    ],
    "sg:menulink":"http://www.allmenus.com/me/brewer/149123-dunkin-donuts/menu/",
    "sg:phone":"+1 207 989 7521",
    "sg:postcode":"04412",
    "sg:province":"ME",
    "sg:tags":[
        "wrap",
        "american",
        "sandwich",
        "pastry"
    ],
    "wof:name":"Dunkin' Donuts",
    "wof:placetype":"venue"
},
  "geometry": {"coordinates":[-68.753398,44.786161],"type":"Point"}
}