{
  "type": "Feature",
  "properties": {
    "iso:country":"US",
    "sg:address":"34 Scribner Cir",
    "sg:city":"Lewiston",
    "sg:classifiers":[
        {
            "category":"Home & Garden",
            "subcategory":"Garden Supply",
            "type":"Retail Goods"
        }
    ],
    "sg:phone":"+1 207 782 3397",
    "sg:postcode":"04240",
    "sg:province":"ME",
    "sg:tags":[
        "engine"
    ],
    "wof:name":"Shop",
    "wof:placetype":"venue"
},
  "geometry": {"coordinates":[-70.189987,44.079965],"type":"Point"}
}