{
  "type": "Feature",
  "properties": {
    "addr:full":"11 Williams St Boothbay Harbor ME 04538",
    "addr:housenumber":"11",
    "addr:postcode":"04538",
    "addr:street":"Williams St",
    "iso:country":"US",
    "sg:address":"11 Williams St",
    "sg:city":"Boothbay Harbor",
    "sg:phone":"+1 207 633 2486",
    "sg:postcode":"04538",
    "sg:province":"ME",
    "sg:tags":[
        "gas"
    ],
    "wof:name":"Carter's Propane Svc",
    "wof:placetype":"venue"
},
  "geometry": {"coordinates":[-69.638577,43.854887],"type":"Point"}
}