{
  "type": "Feature",
  "properties": {
    "iso:country":"US",
    "sg:address":"102 Brackett Ave",
    "sg:city":"Peaks Island",
    "sg:classifiers":[
        {
            "category":"Utilities",
            "subcategory":"Water",
            "type":"Services"
        }
    ],
    "sg:phone":"+1 207 766 4450",
    "sg:postcode":"04108",
    "sg:province":"ME",
    "sg:tags":[
        "company",
        "sewage"
    ],
    "wof:name":"Portland Water District Peaks",
    "wof:placetype":"venue"
},
  "geometry": {"coordinates":[-70.186757,43.658254],"type":"Point"}
}