{
  "type": "Feature",
  "properties": {
    "addr:full":"898 Main St Lewiston ME 04240",
    "addr:housenumber":"898",
    "addr:postcode":"04240",
    "addr:street":"Main St",
    "iso:country":"US",
    "sg:address":"898 Main St",
    "sg:city":"Lewiston",
    "sg:classifiers":[
        {
            "category":"Retail",
            "subcategory":"Auto Repair",
            "type":"Services"
        }
    ],
    "sg:phone":"+1 207 783 4933",
    "sg:postcode":"04240",
    "sg:province":"ME",
    "sg:tags":[
        "automobile",
        "electric"
    ],
    "wof:name":"Major Automotive",
    "wof:placetype":"venue"
},
  "geometry": {"coordinates":[-70.19576600000001,44.133794],"type":"Point"}
}