{
  "type": "Feature",
  "properties": {
    "iso:country":"US",
    "sg:address":"16 Libby Ln",
    "sg:city":"Randolph",
    "sg:classifiers":[
        {
            "category":"Building & Trades",
            "subcategory":"Construction",
            "type":"Services"
        }
    ],
    "sg:phone":"+1 207 588 2095",
    "sg:postcode":"04345",
    "sg:province":"ME",
    "sg:tags":[
        "hanging",
        "contractor"
    ],
    "wof:name":"Stuarts Custom Painting",
    "wof:placetype":"venue"
},
  "geometry": {"coordinates":[-69.76244,44.228483],"type":"Point"}
}