{
  "type": "Feature",
  "properties": {
    "addr:full":"89 Main St Bridgton ME 04009",
    "addr:housenumber":"89",
    "addr:postcode":"04009",
    "addr:street":"Main St",
    "iso:country":"US",
    "sg:address":"89 Main St",
    "sg:city":"Bridgton",
    "sg:classifiers":[
        {
            "category":"Manufacturing",
            "subcategory":"Furniture",
            "type":"Manufacturing & Wholesale Goods"
        }
    ],
    "sg:phone":"+1 207 647 4321",
    "sg:postcode":"04009",
    "sg:province":"ME",
    "sg:tags":[
        "pr",
        "mfg",
        "house",
        "household",
        "wood",
        "furn"
    ],
    "wof:name":"Maine Cedar Saunas",
    "wof:placetype":"venue"
},
  "geometry": {"coordinates":[-70.70772700000001,44.054424],"type":"Point"}
}