{
  "type": "Feature",
  "properties": {
    "addr:full":"34 Dow Rd Gorham ME 04038",
    "addr:housenumber":"34",
    "addr:postcode":"04038",
    "addr:street":"Dow Rd",
    "iso:country":"US",
    "sg:address":"34 Dow Rd",
    "sg:city":"Gorham",
    "sg:classifiers":[
        {
            "category":"Banks & Credit Unions",
            "subcategory":"Investment Brokerage",
            "type":"Services"
        }
    ],
    "sg:phone":"+1 207 839 4114",
    "sg:postcode":"04038",
    "sg:province":"ME",
    "sg:tags":[
        "consultant",
        "planning",
        "financial"
    ],
    "wof:name":"John J Godfrey Jr",
    "wof:placetype":"venue"
},
  "geometry": {"coordinates":[-70.50218,43.694848],"type":"Point"}
}