{
  "type": "Feature",
  "properties": {
    "addr:full":"339 Husson Ave Bangor ME 04401",
    "addr:housenumber":"339",
    "addr:postcode":"04401",
    "addr:street":"Husson Ave",
    "iso:country":"US",
    "sg:address":"339 Husson Ave",
    "sg:city":"Bangor",
    "sg:classifiers":[
        {
            "category":"Retail",
            "subcategory":"Laundry & Dry Cleaning",
            "type":"Services"
        }
    ],
    "sg:phone":"+1 207 990 1208",
    "sg:postcode":"04401",
    "sg:province":"ME",
    "sg:tags":[
        "cleaners"
    ],
    "wof:name":"Laundry Basket",
    "wof:placetype":"venue"
},
  "geometry": {"coordinates":[-68.78265,44.825317],"type":"Point"}
}