{
  "type": "Feature",
  "properties": {
    "iso:country":"US",
    "sg:address":"340 Allen Ave",
    "sg:city":"Portland",
    "sg:classifiers":[
        {
            "category":"Restaurant",
            "type":"Food & Drink"
        }
    ],
    "sg:phone":"+1 207 797 5533",
    "sg:postcode":"04103",
    "sg:province":"ME",
    "wof:name":"Chau Lin",
    "wof:placetype":"venue"
},
  "geometry": {"coordinates":[-70.288712,43.699175],"type":"Point"}
}