{
  "type": "Feature",
  "properties": {
    "addr:full":"86 Beach Ave Kennebunk ME 04043",
    "addr:housenumber":"86",
    "addr:postcode":"04043",
    "addr:street":"Beach Ave",
    "iso:country":"US",
    "sg:address":"86 Beach Ave",
    "sg:city":"Kennebunk",
    "sg:classifiers":[
        {
            "category":"Banks & Credit Unions",
            "subcategory":"Bank",
            "type":"Services"
        }
    ],
    "sg:phone":"+1 207 967 0506",
    "sg:postcode":"04043",
    "sg:province":"ME",
    "sg:tags":[
        "loan",
        "real estate"
    ],
    "wof:name":"Burns & Simon",
    "wof:placetype":"venue"
},
  "geometry": {"coordinates":[-70.47971699999999,43.348929],"type":"Point"}
}