{
  "type": "Feature",
  "properties": {
    "iso:country":"US",
    "sg:address":"34 Harpswell Neck Rd",
    "sg:city":"South Harpswell",
    "sg:classifiers":[
        {
            "category":"Retail",
            "subcategory":"Auto Repair",
            "type":"Services"
        }
    ],
    "sg:phone":"+1 207 729 6848",
    "sg:postcode":"04079",
    "sg:province":"ME",
    "wof:name":"Lucas Auto Repair",
    "wof:placetype":"venue"
},
  "geometry": {"coordinates":[-69.954582,43.844112],"type":"Point"}
}