{
  "type": "Feature",
  "properties": {
    "addr:full":"170 Shore rd Cape Neddick ME 03902",
    "addr:housenumber":"170",
    "addr:postcode":"03902",
    "addr:street":"Shore Rd",
    "iso:country":"US",
    "sg:address":"170 Shore rd",
    "sg:city":"Cape Neddick",
    "sg:classifiers":[
        {
            "category":"Building & Trades",
            "subcategory":"Construction",
            "type":"Services"
        }
    ],
    "sg:phone":"+1 207 361 4084",
    "sg:postcode":"03902",
    "sg:province":"ME",
    "sg:tags":[
        "painter",
        "contractor"
    ],
    "sg:website":"mandipainting.com",
    "wof:name":"M and I PAINTING Inc",
    "wof:placetype":"venue"
},
  "geometry": {"coordinates":[-70.59475399999999,43.198507],"type":"Point"}
}