{
  "type": "Feature",
  "properties": {
    "iso:country":"US",
    "sg:address":"105 Harmons Beach Rd",
    "sg:city":"Standish",
    "sg:classifiers":[
        {
            "category":"Home & Garden",
            "subcategory":"Building Materials",
            "type":"Retail Goods"
        }
    ],
    "sg:phone":"+1 207 939 6096",
    "sg:postcode":"04084",
    "sg:province":"ME",
    "sg:tags":[
        "door"
    ],
    "wof:name":"ABS Garage Doors",
    "wof:placetype":"venue"
},
  "geometry": {"coordinates":[-70.549053,43.804323],"type":"Point"}
}