{
  "type": "Feature",
  "properties": {
    "addr:full":"45 High St Eastport ME 04631",
    "addr:housenumber":"45",
    "addr:postcode":"04631",
    "addr:street":"High St",
    "iso:country":"US",
    "sg:address":"45 High St",
    "sg:city":"Eastport",
    "sg:classifiers":[
        {
            "category":"Professional",
            "subcategory":"Management & Consulting",
            "type":"Services"
        }
    ],
    "sg:phone":"+1 207 853 2644",
    "sg:postcode":"04631",
    "sg:province":"ME",
    "sg:tags":[
        "educational",
        "author"
    ],
    "wof:name":"Celestial Engineering",
    "wof:placetype":"venue"
},
  "geometry": {"coordinates":[-66.989636,44.90435],"type":"Point"}
}