{
  "type": "Feature",
  "properties": {
    "addr:full":"262 Upper Sumner Hill Rd Sumner ME 04292",
    "addr:housenumber":"262",
    "addr:postcode":"04292",
    "addr:street":"Upper Sumner Hill Rd",
    "iso:country":"US",
    "sg:address":"262 Upper Sumner Hill Rd",
    "sg:city":"Sumner",
    "sg:classifiers":[
        {
            "category":"Freight",
            "type":"Transportation"
        }
    ],
    "sg:phone":"+1 207 388 2446",
    "sg:postcode":"04292",
    "sg:province":"ME",
    "sg:tags":[
        "operator",
        "local",
        "trucking"
    ],
    "wof:name":"Christopher P Zak",
    "wof:placetype":"venue"
},
  "geometry": {"coordinates":[-70.424747,44.369128],"type":"Point"}
}