{
  "type": "Feature",
  "properties": {
    "iso:country":"US",
    "sg:address":"14 Portland Street Pier",
    "sg:city":"South Portland",
    "sg:classifiers":[
        {
            "category":"Building & Trades",
            "subcategory":"Construction",
            "type":"Services"
        }
    ],
    "sg:phone":"+1 207 774 9200",
    "sg:postcode":"04106",
    "sg:province":"ME",
    "sg:tags":[
        "contractor"
    ],
    "wof:name":"David J Deschaine Instltns",
    "wof:placetype":"venue"
},
  "geometry": {"coordinates":[-70.242524,43.650156],"type":"Point"}
}