{
  "type": "Feature",
  "properties": {
    "iso:country":"US",
    "sg:address":"30 Main St",
    "sg:city":"Cornish",
    "sg:classifiers":[
        {
            "category":"Shopping",
            "subcategory":"Used Merchandise",
            "type":"Retail Goods"
        }
    ],
    "sg:phone":"+1 207 625 3577",
    "sg:postcode":"04010",
    "sg:province":"ME",
    "sg:tags":[
        "antique"
    ],
    "wof:name":"Plain & Fancy",
    "wof:placetype":"venue"
},
  "geometry": {"coordinates":[-70.890559,43.943687],"type":"Point"}
}