{
  "type": "Feature",
  "properties": {
    "iso:country":"US",
    "sg:address":"2514 Western Ave",
    "sg:city":"Hampden",
    "sg:classifiers":[
        {
            "category":"Shopping",
            "subcategory":"Used Merchandise",
            "type":"Retail Goods"
        }
    ],
    "sg:phone":"+1 207 234 4931",
    "sg:postcode":"04444",
    "sg:province":"ME",
    "wof:name":"Gary W Woolson",
    "wof:placetype":"venue"
},
  "geometry": {"coordinates":[-69.004474,44.720717],"type":"Point"}
}