{
  "type": "Feature",
  "properties": {
    "iso:country":"US",
    "sg:address":"57 N Cove Rd",
    "sg:city":"Stonington",
    "sg:classifiers":[
        {
            "category":"Real Estate",
            "subcategory":"Real Estate Operator",
            "type":"Services"
        }
    ],
    "sg:phone":"+1 207 367 6550",
    "sg:postcode":"04605",
    "sg:province":"ME",
    "sg:tags":[
        "property",
        "lessor"
    ],
    "wof:name":"Oakhill Estates",
    "wof:placetype":"venue"
},
  "geometry": {"coordinates":[-68.278648,44.460213],"type":"Point"}
}