{
  "type": "Feature",
  "properties": {
    "iso:country":"US",
    "sg:address":"608 Bridgton Rd",
    "sg:city":"Westbrook",
    "sg:classifiers":[
        {
            "category":"Retail",
            "subcategory":"Auto Repair",
            "type":"Services"
        }
    ],
    "sg:phone":"+1 207 797 9153",
    "sg:postcode":"04092",
    "sg:province":"ME",
    "sg:tags":[
        "repairing",
        "automobile"
    ],
    "sg:website":"www.lakeregionimports.com",
    "wof:name":"Lake Region Imports Inc",
    "wof:placetype":"venue"
},
  "geometry": {"coordinates":[-70.338276,43.720099],"type":"Point"}
}