{
  "type": "Feature",
  "properties": {
    "addr:full":"10 Harlow St Bangor ME 04401",
    "addr:housenumber":"10",
    "addr:postcode":"04401",
    "addr:street":"Harlow St",
    "iso:country":"US",
    "sg:address":"10 Harlow St",
    "sg:city":"Bangor",
    "sg:classifiers":[
        {
            "category":"Home & Garden",
            "subcategory":"Furniture",
            "type":"Retail Goods"
        }
    ],
    "sg:phone":"+1 207 947 0077",
    "sg:postcode":"04401",
    "sg:province":"ME",
    "sg:tags":[
        "equipment",
        "kitchen",
        "cabinet"
    ],
    "wof:name":"Art Gallery",
    "wof:placetype":"venue"
},
  "geometry": {"coordinates":[-68.770579,44.803265],"type":"Point"}
}