{
  "type": "Feature",
  "properties": {
    "addr:full":"44 Cliff Rd Northport ME 04849",
    "addr:housenumber":"44",
    "addr:postcode":"04849",
    "addr:street":"Cliff Rd",
    "iso:country":"US",
    "sg:address":"44 Cliff Rd",
    "sg:city":"Northport",
    "sg:classifiers":[
        {
            "category":"Shopping",
            "subcategory":"Clothing, Apparel, & Fashions",
            "type":"Retail Goods"
        }
    ],
    "sg:phone":"+1 207 338 0628",
    "sg:postcode":"04849",
    "sg:province":"ME",
    "sg:tags":[
        "fur"
    ],
    "wof:name":"Imperial Bear Factory",
    "wof:placetype":"venue"
},
  "geometry": {"coordinates":[-68.954004,44.335646],"type":"Point"}
}