{
  "type": "Feature",
  "properties": {
    "addr:full":"189 Exchange St Bangor ME 04401",
    "addr:housenumber":"189",
    "addr:postcode":"04401",
    "addr:street":"Exchange St",
    "iso:country":"US",
    "sg:address":"189 Exchange St",
    "sg:city":"Bangor",
    "sg:classifiers":[
        {
            "category":"Professional",
            "subcategory":"Management & Consulting",
            "type":"Services"
        }
    ],
    "sg:phone":"+1 207 942 0977",
    "sg:postcode":"04401",
    "sg:province":"ME",
    "sg:tags":[
        "consultant",
        "business"
    ],
    "wof:name":"Twin City Corporate Svc",
    "wof:placetype":"venue"
},
  "geometry": {"coordinates":[-68.76910100000001,44.802348],"type":"Point"}
}