{
  "type": "Feature",
  "properties": {
    "addr:full":"323 Broadway South Portland ME 04106",
    "addr:housenumber":"323",
    "addr:postcode":"04106",
    "addr:street":"Broadway",
    "iso:country":"US",
    "sg:address":"323 Broadway",
    "sg:city":"South Portland",
    "sg:classifiers":[
        {
            "category":"Food & Beverages",
            "subcategory":"Bakery",
            "type":"Retail Goods"
        }
    ],
    "sg:phone":"+1 207 347 7450",
    "sg:postcode":"04106",
    "sg:province":"ME",
    "sg:tags":[
        "sandwich"
    ],
    "wof:name":"Anania's Variety",
    "wof:placetype":"venue"
},
  "geometry": {"coordinates":[-70.24357500000001,43.639819],"type":"Point"}
}