{
  "type": "Feature",
  "properties": {
    "addr:full":"23 Hammond St Bangor ME 04401",
    "addr:housenumber":"23",
    "addr:postcode":"04401",
    "addr:street":"Hammond St",
    "iso:country":"US",
    "sg:address":"23 Hammond St",
    "sg:city":"Bangor",
    "sg:classifiers":[
        {
            "category":"Manufacturing",
            "subcategory":"Metals",
            "type":"Manufacturing & Wholesale Goods"
        }
    ],
    "sg:phone":"+1 207 990 0073",
    "sg:postcode":"04401",
    "sg:province":"ME",
    "sg:tags":[
        "valve",
        "rebuilds",
        "reconditions",
        "gear"
    ],
    "wof:name":"Monarch Valve Corp",
    "wof:placetype":"venue"
},
  "geometry": {"coordinates":[-68.77068199999999,44.801854],"type":"Point"}
}