{
  "type": "Feature",
  "properties": {
    "addr:full":"3 Hill Dr Eliot ME 03903",
    "addr:housenumber":"3",
    "addr:postcode":"03903",
    "addr:street":"Hill Dr",
    "iso:country":"US",
    "sg:address":"3 Hill Dr",
    "sg:city":"Eliot",
    "sg:classifiers":[
        {
            "category":"Professional",
            "type":"Services"
        }
    ],
    "sg:phone":"+1 207 439 0139",
    "sg:postcode":"03903",
    "sg:province":"ME",
    "wof:name":"Covington Co",
    "wof:placetype":"venue"
},
  "geometry": {"coordinates":[-70.82334,43.138944],"type":"Point"}
}