{
  "type": "Feature",
  "properties": {
    "iso:country":"US",
    "sg:address":"2 Water St",
    "sg:city":"Houlton",
    "sg:classifiers":[
        {
            "category":"Health Services",
            "subcategory":"Health Practitioner",
            "type":"Services"
        }
    ],
    "sg:phone":"+1 207 532 9261",
    "sg:postcode":"04730",
    "sg:province":"ME",
    "sg:tags":[
        "nurse",
        "registry"
    ],
    "wof:name":"Visiting Nurses Of Aroostook",
    "wof:placetype":"venue"
},
  "geometry": {"coordinates":[-67.83971,46.125776],"type":"Point"}
}