{
  "type": "Feature",
  "properties": {
    "addr:full":"47 Centre St Bath ME 04530",
    "addr:housenumber":"47",
    "addr:postcode":"04530",
    "addr:street":"Centre St",
    "iso:country":"US",
    "sg:address":"47 Centre St",
    "sg:city":"Bath",
    "sg:classifiers":[
        {
            "category":"Retail",
            "subcategory":"Laundry & Dry Cleaning",
            "type":"Services"
        }
    ],
    "sg:phone":"+1 207 443 4851",
    "sg:postcode":"04530",
    "sg:province":"ME",
    "sg:tags":[
        "cleaners"
    ],
    "wof:name":"Smith Cleaners",
    "wof:placetype":"venue"
},
  "geometry": {"coordinates":[-69.81538999999999,43.912608],"type":"Point"}
}