{
  "type": "Feature",
  "properties": {
    "iso:country":"US",
    "sg:address":"391 Pond Rd",
    "sg:city":"Lewiston",
    "sg:classifiers":[
        {
            "category":"Building & Trades",
            "subcategory":"Landscaping Services",
            "type":"Services"
        }
    ],
    "sg:phone":"+1 207 777 3469",
    "sg:postcode":"04240",
    "sg:province":"ME",
    "sg:tags":[
        "landscape",
        "contractor"
    ],
    "wof:name":"Mike's Lawn Care & Plowing",
    "wof:placetype":"venue"
},
  "geometry": {"coordinates":[-70.153879,44.100564],"type":"Point"}
}