{
  "type": "Feature",
  "properties": {
    "addr:full":"15 Main St Belfast ME 04915",
    "addr:housenumber":"15",
    "addr:postcode":"04915",
    "addr:street":"Main St",
    "iso:country":"US",
    "sg:address":"15 Main St",
    "sg:city":"Belfast",
    "sg:classifiers":[
        {
            "category":"Professional",
            "subcategory":"Printing & Photocopies",
            "type":"Services"
        }
    ],
    "sg:phone":"+1 207 338 5411",
    "sg:postcode":"04915",
    "sg:province":"ME",
    "sg:tags":[
        "duplicating",
        "copying"
    ],
    "wof:name":"County Copy Ctr",
    "wof:placetype":"venue"
},
  "geometry": {"coordinates":[-69.00575000000001,44.427149],"type":"Point"}
}