{
  "type": "Feature",
  "properties": {
    "iso:country":"US",
    "sg:address":"3 Green St",
    "sg:city":"Norway",
    "sg:classifiers":[
        {
            "category":"Wholesale",
            "subcategory":"Construction Materials",
            "type":"Manufacturing & Wholesale Goods"
        }
    ],
    "sg:phone":"+1 207 743 8885",
    "sg:postcode":"04268",
    "sg:province":"ME",
    "sg:tags":[
        "roofing",
        "waterproof",
        "membrane"
    ],
    "wof:name":"Soprema Inc",
    "wof:placetype":"venue"
},
  "geometry": {"coordinates":[-70.531334,44.211872],"type":"Point"}
}