{
  "type": "Feature",
  "properties": {
    "addr:full":"4 Lombard Rd Caribou ME 04736",
    "addr:housenumber":"4",
    "addr:postcode":"04736",
    "addr:street":"Lombard Rd",
    "iso:country":"US",
    "sg:address":"4 Lombard Rd",
    "sg:city":"Caribou",
    "sg:classifiers":[
        {
            "category":"Social Services",
            "type":"Services"
        }
    ],
    "sg:phone":"+1 207 498 2575",
    "sg:postcode":"04736",
    "sg:province":"ME",
    "sg:tags":[
        "organization",
        "welfare"
    ],
    "sg:website":"www.ccmaine.org",
    "wof:name":"Northeastern Maine Homemaker",
    "wof:placetype":"venue"
},
  "geometry": {"coordinates":[-68.044451,46.867867],"type":"Point"}
}