{
  "type": "Feature",
  "properties": {
    "iso:country":"US",
    "sg:address":"647 Gurnet Rd",
    "sg:city":"Brunswick",
    "sg:classifiers":[
        {
            "category":"Building & Trades",
            "subcategory":"Construction",
            "type":"Services"
        }
    ],
    "sg:phone":"+1 207 725 4318",
    "sg:postcode":"04011",
    "sg:province":"ME",
    "sg:tags":[
        "well",
        "drilling"
    ],
    "wof:name":"Brunswick Well & Pump Co",
    "wof:placetype":"venue"
},
  "geometry": {"coordinates":[-69.913499,43.862048],"type":"Point"}
}