{
  "type": "Feature",
  "properties": {
    "iso:country":"US",
    "sg:address":"94 Wescott Rd",
    "sg:city":"Gorham",
    "sg:classifiers":[
        {
            "category":"Building & Trades",
            "subcategory":"Plumbing",
            "type":"Services"
        }
    ],
    "sg:phone":"+1 207 892 3030",
    "sg:postcode":"04038",
    "sg:province":"ME",
    "sg:tags":[
        "contractor"
    ],
    "wof:name":"Joseph Cerny III",
    "wof:placetype":"venue"
},
  "geometry": {"coordinates":[-70.484708,43.752552],"type":"Point"}
}