{
  "type": "Feature",
  "properties": {
    "iso:country":"US",
    "sg:address":"369 US Hwy 1",
    "sg:city":"Freeport",
    "sg:classifiers":[
        {
            "category":"Professional",
            "subcategory":"Business Services",
            "type":"Services"
        }
    ],
    "sg:phone":"+1 207 865 4948",
    "sg:postcode":"04032",
    "sg:province":"ME",
    "sg:tags":[
        "repair",
        "boat"
    ],
    "wof:name":"Casey Yacht Enterprises",
    "wof:placetype":"venue"
},
  "geometry": {"coordinates":[-70.087241,43.874396],"type":"Point"}
}