{
  "type": "Feature",
  "properties": {
    "iso:country":"US",
    "sg:address":"57 Labre Ln",
    "sg:city":"Greene",
    "sg:classifiers":[
        {
            "category":"Professional",
            "type":"Services"
        }
    ],
    "sg:phone":"+1 207 946 4282",
    "sg:postcode":"04236",
    "sg:province":"ME",
    "sg:tags":[
        "establishment"
    ],
    "wof:name":"Tom Sled Co",
    "wof:placetype":"venue"
},
  "geometry": {"coordinates":[-70.193154,44.172232],"type":"Point"}
}