{
  "type": "Feature",
  "properties": {
    "addr:full":"114 State St Ellsworth ME 04605",
    "addr:housenumber":"114",
    "addr:postcode":"04605",
    "addr:street":"State St",
    "iso:country":"US",
    "sg:address":"114 State St",
    "sg:city":"Ellsworth",
    "sg:classifiers":[
        {
            "category":"Social Services",
            "type":"Services"
        }
    ],
    "sg:phone":"+1 207 667 4334",
    "sg:postcode":"04605",
    "sg:province":"ME",
    "sg:tags":[
        "counselor",
        "marriage",
        "family"
    ],
    "wof:name":"Lucia Young PHD",
    "wof:placetype":"venue"
},
  "geometry": {"coordinates":[-68.425656,44.544999],"type":"Point"}
}