{
  "type": "Feature",
  "properties": {
    "iso:country":"US",
    "sg:address":"145 River Rd",
    "sg:city":"Lewiston",
    "sg:classifiers":[
        {
            "category":"Building & Trades",
            "subcategory":"Construction",
            "type":"Services"
        }
    ],
    "sg:phone":"+1 207 782 2411",
    "sg:postcode":"04240",
    "sg:province":"ME",
    "sg:tags":[
        "product",
        "asphalt"
    ],
    "wof:name":"Pike Industries Inc",
    "wof:placetype":"venue"
},
  "geometry": {"coordinates":[-70.19934600000001,44.06677],"type":"Point"}
}