{
  "type": "Feature",
  "properties": {
    "addr:full":"17 Hudson Rd Corinth ME 04427",
    "addr:housenumber":"17",
    "addr:postcode":"04427",
    "addr:street":"Hudson Rd",
    "iso:country":"US",
    "sg:address":"17 Hudson Rd",
    "sg:city":"Corinth",
    "sg:classifiers":[
        {
            "category":"Retail",
            "subcategory":"Funeral Services",
            "type":"Services"
        }
    ],
    "sg:phone":"+1 207 285 3377",
    "sg:postcode":"04427",
    "sg:province":"ME",
    "sg:tags":[
        "director"
    ],
    "wof:name":"Thompson Funeral Home",
    "wof:placetype":"venue"
},
  "geometry": {"coordinates":[-69.02144800000001,45.005218],"type":"Point"}
}