{
  "type": "Feature",
  "properties": {
    "iso:country":"US",
    "sg:address":"6 Bennett Rd",
    "sg:city":"Yarmouth",
    "sg:classifiers":[
        {
            "category":"Health Services",
            "subcategory":"Health Practitioner",
            "type":"Services"
        }
    ],
    "sg:phone":"+1 207 846 4433",
    "sg:postcode":"04096",
    "sg:province":"ME",
    "sg:tags":[
        "acupuncture"
    ],
    "wof:name":"Acupuncture Associates",
    "wof:placetype":"venue"
},
  "geometry": {"coordinates":[-70.18696,43.792238],"type":"Point"}
}