{
  "type": "Feature",
  "properties": {
    "addr:full":"48 Dillingham St Bangor ME 04401",
    "addr:housenumber":"48",
    "addr:postcode":"04401",
    "addr:street":"Dillingham St",
    "iso:country":"US",
    "sg:address":"48 Dillingham St",
    "sg:city":"Bangor",
    "sg:classifiers":[
        {
            "category":"Shopping",
            "subcategory":"Hobbies, Toys, & Games",
            "type":"Retail Goods"
        }
    ],
    "sg:phone":"+1 207 942 2579",
    "sg:postcode":"04401",
    "sg:province":"ME",
    "sg:tags":[
        "model",
        "supply"
    ],
    "wof:name":"Union Station Hobby",
    "wof:placetype":"venue"
},
  "geometry": {"coordinates":[-68.782191,44.783727],"type":"Point"}
}