{
  "type": "Feature",
  "properties": {
    "addr:full":"475 Pleasant St Lewiston ME 04240",
    "addr:housenumber":"475",
    "addr:postcode":"04240",
    "addr:street":"Pleasant St",
    "iso:country":"US",
    "sg:address":"475 Pleasant St",
    "sg:city":"Lewiston",
    "sg:classifiers":[
        {
            "category":"Recreation",
            "type":"Entertainment"
        }
    ],
    "sg:phone":"+1 207 777 1394",
    "sg:postcode":"04240",
    "sg:province":"ME",
    "sg:tags":[
        "bingo",
        "hall"
    ],
    "wof:name":"Pleasant Street Bingo",
    "wof:placetype":"venue"
},
  "geometry": {"coordinates":[-70.18131,44.078039],"type":"Point"}
}