{
  "type": "Feature",
  "properties": {
    "addr:full":"100 Main St Warren ME 04864",
    "addr:housenumber":"100",
    "addr:postcode":"04864",
    "addr:street":"Main St",
    "iso:country":"US",
    "sg:address":"100 Main St",
    "sg:city":"Warren",
    "sg:classifiers":[
        {
            "category":"Building & Trades",
            "subcategory":"Electrical",
            "type":"Services"
        }
    ],
    "sg:phone":"+1 207 273 3237",
    "sg:postcode":"04864",
    "sg:province":"ME",
    "sg:tags":[
        "electric",
        "contractor"
    ],
    "wof:name":"Alley Electric & Electronics",
    "wof:placetype":"venue"
},
  "geometry": {"coordinates":[-69.253075,44.118732],"type":"Point"}
}