{
  "type": "Feature",
  "properties": {
    "iso:country":"US",
    "sg:address":"359 Sanford Rd",
    "sg:city":"Alfred",
    "sg:classifiers":[
        {
            "category":"Retail",
            "subcategory":"Auto Repair",
            "type":"Services"
        }
    ],
    "sg:phone":"+1 207 490 5565",
    "sg:postcode":"04002",
    "sg:province":"ME",
    "sg:tags":[
        "road"
    ],
    "wof:name":"A J's Towing & Roadside",
    "wof:placetype":"venue"
},
  "geometry": {"coordinates":[-70.75730799999999,43.463125],"type":"Point"}
}