{
  "type": "Feature",
  "properties": {
    "iso:country":"US",
    "sg:address":"250 Jagger Mill Rd",
    "sg:city":"Sanford",
    "sg:classifiers":[
        {
            "category":"Wholesale",
            "subcategory":"Motor Vehicles",
            "type":"Manufacturing & Wholesale Goods"
        }
    ],
    "sg:phone":"+1 207 324 3300",
    "sg:postcode":"04073",
    "sg:province":"ME",
    "wof:name":"Sanford Auto Sales",
    "wof:placetype":"venue"
},
  "geometry": {"coordinates":[-70.740048,43.416094],"type":"Point"}
}