{
  "type": "Feature",
  "properties": {
    "addr:full":"307 Main St Cumberland Ctr ME 04021",
    "addr:housenumber":"307",
    "addr:postcode":"04021",
    "addr:street":"Main St",
    "iso:country":"US",
    "sg:address":"307 Main St",
    "sg:city":"Cumberland Ctr",
    "sg:classifiers":[
        {
            "category":"Education",
            "subcategory":"School",
            "type":"Public Place"
        }
    ],
    "sg:phone":"+1 207 829 4820",
    "sg:postcode":"04021",
    "sg:province":"ME",
    "wof:name":"School Administrative District",
    "wof:placetype":"venue"
},
  "geometry": {"coordinates":[-70.257096,43.798354],"type":"Point"}
}