{
  "type": "Feature",
  "properties": {
    "addr:full":"86 Champeon Rd Exeter ME 04435",
    "addr:housenumber":"86",
    "addr:postcode":"04435",
    "addr:street":"Champeon Rd",
    "iso:country":"US",
    "sg:address":"86 Champeon Rd",
    "sg:city":"Exeter",
    "sg:classifiers":[
        {
            "category":"Recreation",
            "type":"Entertainment"
        }
    ],
    "sg:phone":"+1 207 379 2776",
    "sg:postcode":"04435",
    "sg:province":"ME",
    "sg:tags":[
        "stable"
    ],
    "wof:name":"Sir Sarg Stables",
    "wof:placetype":"venue"
},
  "geometry": {"coordinates":[-69.145549,44.992993],"type":"Point"}
}