{
  "type": "Feature",
  "properties": {
    "addr:full":"7 Cleaves St Yarmouth ME 04096",
    "addr:housenumber":"7",
    "addr:postcode":"04096",
    "addr:street":"Cleaves St",
    "iso:country":"US",
    "sg:address":"7 Cleaves St",
    "sg:city":"Yarmouth",
    "sg:classifiers":[
        {
            "category":"Manufacturing",
            "subcategory":"Apparel",
            "type":"Manufacturing & Wholesale Goods"
        }
    ],
    "sg:phone":"+1 207 846 0915",
    "sg:postcode":"04096",
    "sg:province":"ME",
    "sg:tags":[
        "flag",
        "banner"
    ],
    "wof:name":"Banner Source",
    "wof:placetype":"venue"
},
  "geometry": {"coordinates":[-70.18980500000001,43.798968],"type":"Point"}
}