{
  "type": "Feature",
  "properties": {
    "addr:full":"6 State St Bangor ME 04401",
    "addr:housenumber":"6",
    "addr:postcode":"04401",
    "addr:street":"State St",
    "iso:country":"US",
    "sg:address":"6 State St",
    "sg:city":"Bangor",
    "sg:classifiers":[
        {
            "category":"Wholesale",
            "subcategory":"Stationery",
            "type":"Manufacturing & Wholesale Goods"
        }
    ],
    "sg:phone":"+1 207 942 5200",
    "sg:postcode":"04401",
    "sg:province":"ME",
    "sg:tags":[
        "mapping"
    ],
    "wof:name":"Kappa Mapping Inc",
    "wof:placetype":"venue"
},
  "geometry": {"coordinates":[-68.769291,44.802387],"type":"Point"}
}