{
  "type": "Feature",
  "properties": {
    "addr:full":"18 Forest Ave Portland ME 04101",
    "addr:housenumber":"18",
    "addr:postcode":"04101",
    "addr:street":"Forest Ave",
    "iso:country":"US",
    "sg:address":"18 Forest Ave",
    "sg:city":"Portland",
    "sg:classifiers":[
        {
            "category":"Real Estate",
            "subcategory":"Real Estate Operator",
            "type":"Services"
        },
        {
            "category":"Social Services",
            "type":"Services"
        }
    ],
    "sg:phone":"+1 207 771 0295",
    "sg:postcode":"04101",
    "sg:province":"ME",
    "sg:tags":[
        "apartment",
        "center",
        "for",
        "disabled",
        "computer",
        "citizen",
        "senior"
    ],
    "wof:name":"Caleb Adult Center",
    "wof:placetype":"venue"
},
  "geometry": {"coordinates":[-70.276045,43.665692],"type":"Point"}
}