{
  "type": "Feature",
  "properties": {
    "iso:country":"US",
    "sg:address":"55 Lincoln Rd",
    "sg:city":"Saco",
    "sg:classifiers":[
        {
            "category":"Building & Trades",
            "subcategory":"Plumbing",
            "type":"Services"
        }
    ],
    "sg:phone":"+1 207 282 5440",
    "sg:postcode":"04072",
    "sg:province":"ME",
    "sg:tags":[
        "plumbing",
        "contractor"
    ],
    "wof:name":"Prompt Plumbing & Heating",
    "wof:placetype":"venue"
},
  "geometry": {"coordinates":[-70.451658,43.574492],"type":"Point"}
}