{
  "type": "Feature",
  "properties": {
    "addr:full":"18 Pleasant Ridge Rd Dexter ME 04930",
    "addr:housenumber":"18",
    "addr:postcode":"04930",
    "addr:street":"Pleasant Ridge Rd",
    "iso:country":"US",
    "sg:address":"18 Pleasant Ridge Rd",
    "sg:city":"Dexter",
    "sg:classifiers":[
        {
            "category":"Home & Garden",
            "subcategory":"Building Materials",
            "type":"Retail Goods"
        }
    ],
    "sg:phone":"+1 207 924 7809",
    "sg:postcode":"04930",
    "sg:province":"ME",
    "sg:tags":[
        "modular"
    ],
    "wof:name":"Kel Bee Homes",
    "wof:placetype":"venue"
},
  "geometry": {"coordinates":[-69.29153599999999,45.06252],"type":"Point"}
}