{
  "type": "Feature",
  "properties": {
    "addr:full":"16 Vernon St Long Island ME 04072",
    "addr:housenumber":"16",
    "addr:postcode":"04072",
    "addr:street":"Vernon St",
    "iso:country":"US",
    "sg:address":"16 Vernon St",
    "sg:city":"Long Island",
    "sg:classifiers":[
        {
            "category":"Food & Beverages",
            "subcategory":"Meat & Fish",
            "type":"Retail Goods"
        }
    ],
    "sg:phone":"+1 207 766 2115",
    "sg:postcode":"04072",
    "sg:province":"ME",
    "sg:tags":[
        "lobster"
    ],
    "wof:name":"Fern Park Lobster Co",
    "wof:placetype":"venue"
},
  "geometry": {"coordinates":[-70.445583,43.501896],"type":"Point"}
}