{
  "type": "Feature",
  "properties": {
    "addr:full":"11 Glenwood Orono ME 04473",
    "addr:housenumber":"11",
    "addr:postcode":"04473",
    "addr:street":"Glenwood",
    "iso:country":"US",
    "sg:address":"11 Glenwood",
    "sg:city":"Orono",
    "sg:classifiers":[
        {
            "category":"Professional",
            "subcategory":"Testing Lab",
            "type":"Services"
        }
    ],
    "sg:phone":"+1 207 866 7059",
    "sg:postcode":"04473",
    "sg:province":"ME",
    "sg:tags":[
        "laboratory",
        "consulting",
        "management"
    ],
    "wof:name":"Sorg Marcella H PH D PA",
    "wof:placetype":"venue"
},
  "geometry": {"coordinates":[-68.68195299999999,44.875615],"type":"Point"}
}