{
  "type": "Feature",
  "properties": {
    "iso:country":"US",
    "sg:address":"77 Western Ave",
    "sg:city":"Hampden",
    "sg:classifiers":[
        {
            "category":"Shopping",
            "subcategory":"Pharmacy",
            "type":"Retail Goods"
        }
    ],
    "sg:phone":"+1 207 862 5280",
    "sg:postcode":"04444",
    "sg:province":"ME",
    "wof:name":"Hampden Pharmacy",
    "wof:placetype":"venue"
},
  "geometry": {"coordinates":[-68.844451,44.744859],"type":"Point"}
}