{
  "type": "Feature",
  "properties": {
    "iso:country":"US",
    "sg:address":"119 Spurwink Rd",
    "sg:city":"Scarborough",
    "sg:classifiers":[
        {
            "category":"Manufacturing",
            "subcategory":"Apparel",
            "type":"Manufacturing & Wholesale Goods"
        }
    ],
    "sg:phone":"+1 207 767 3977",
    "sg:postcode":"04074",
    "sg:province":"ME",
    "sg:tags":[
        "flag",
        "banner"
    ],
    "sg:website":"www.eugeniascountryflags.com",
    "wof:name":"Eugenia's Country Flags",
    "wof:placetype":"venue"
},
  "geometry": {"coordinates":[-70.27733499999999,43.574574],"type":"Point"}
}