{
  "type": "Feature",
  "properties": {
    "iso:country":"US",
    "sg:address":"24 Broadway St",
    "sg:city":"York",
    "sg:classifiers":[
        {
            "category":"Building & Trades",
            "subcategory":"Construction",
            "type":"Services"
        }
    ],
    "sg:phone":"+1 207 363 7993",
    "sg:postcode":"03909",
    "sg:province":"ME",
    "sg:tags":[
        "wallpaper"
    ],
    "wof:name":"Bob Rivers Painting & Wallppr",
    "wof:placetype":"venue"
},
  "geometry": {"coordinates":[-70.605487,43.172354],"type":"Point"}
}