{
  "type": "Feature",
  "properties": {
    "iso:country":"US",
    "sg:address":"12 Victoria Ln",
    "sg:city":"Falmouth",
    "sg:classifiers":[
        {
            "category":"Professional",
            "type":"Services"
        }
    ],
    "sg:phone":"+1 207 797 9210",
    "sg:postcode":"04105",
    "sg:province":"ME",
    "sg:tags":[
        "establishment"
    ],
    "wof:name":"Mobilecomm",
    "wof:placetype":"venue"
},
  "geometry": {"coordinates":[-70.319893,43.755303],"type":"Point"}
}