{
  "type": "Feature",
  "properties": {
    "iso:country":"US",
    "sg:address":"4 Sunrise Summit",
    "sg:city":"Rockland",
    "sg:classifiers":[
        {
            "category":"Professional",
            "type":"Services"
        }
    ],
    "sg:phone":"+1 207 594 7967",
    "sg:postcode":"04841",
    "sg:province":"ME",
    "wof:name":"Studysmart Inc",
    "wof:placetype":"venue"
},
  "geometry": {"coordinates":[-69.130222,44.145997],"type":"Point"}
}