{
  "type": "Feature",
  "properties": {
    "addr:full":"332 New Portland Rd Gorham ME 04038",
    "addr:housenumber":"332",
    "addr:postcode":"04038",
    "addr:street":"New Portland Rd",
    "iso:country":"US",
    "sg:address":"332 New Portland Rd",
    "sg:city":"Gorham",
    "sg:classifiers":[
        {
            "category":"Manufacturing",
            "subcategory":"Signs",
            "type":"Manufacturing & Wholesale Goods"
        }
    ],
    "sg:phone":"+1 207 854 4999",
    "sg:postcode":"04038",
    "sg:province":"ME",
    "sg:tags":[
        "advertising",
        "specialty"
    ],
    "wof:name":"Sinnett Signs & Graphics",
    "wof:placetype":"venue"
},
  "geometry": {"coordinates":[-70.402507,43.677988],"type":"Point"}
}