{
  "type": "Feature",
  "properties": {
    "iso:country":"US",
    "sg:address":"27 Orchard Rd",
    "sg:city":"Cape Elizabeth",
    "sg:classifiers":[
        {
            "category":"Building & Trades",
            "subcategory":"Landscaping Services",
            "type":"Services"
        }
    ],
    "sg:phone":"+1 207 767 3818",
    "sg:postcode":"04107",
    "sg:province":"ME",
    "sg:tags":[
        "landscape"
    ],
    "wof:name":"McGeachey Tree & Landscaping",
    "wof:placetype":"venue"
},
  "geometry": {"coordinates":[-70.235625,43.595116],"type":"Point"}
}