{
  "type": "Feature",
  "properties": {
    "iso:country":"US",
    "sg:address":"12 Valley Ave",
    "sg:city":"Falmouth",
    "sg:classifiers":[
        {
            "category":"Building & Trades",
            "subcategory":"Construction",
            "type":"Services"
        }
    ],
    "sg:phone":"+1 207 781 8474",
    "sg:postcode":"04105",
    "sg:province":"ME",
    "sg:tags":[
        "excavating",
        "contractor"
    ],
    "wof:name":"Fox General Contracting Co",
    "wof:placetype":"venue"
},
  "geometry": {"coordinates":[-70.217375,43.738243],"type":"Point"}
}