{
  "type": "Feature",
  "properties": {
    "iso:country":"US",
    "sg:address":"16 Emerson St",
    "sg:city":"Portland",
    "sg:classifiers":[
        {
            "category":"Real Estate",
            "subcategory":"Real Estate Operator",
            "type":"Services"
        }
    ],
    "sg:phone":"+1 207 761 8098",
    "sg:postcode":"04101",
    "sg:province":"ME",
    "sg:tags":[
        "property",
        "lessor"
    ],
    "wof:name":"Maine Wood Salvage",
    "wof:placetype":"venue"
},
  "geometry": {"coordinates":[-70.246134,43.668007],"type":"Point"}
}