{
  "type": "Feature",
  "properties": {
    "addr:full":"16 Pinewood Dr Cumberland Ctr ME 04021",
    "addr:housenumber":"16",
    "addr:postcode":"04021",
    "addr:street":"Pinewood Dr",
    "iso:country":"US",
    "sg:address":"16 Pinewood Dr",
    "sg:city":"Cumberland Ctr",
    "sg:classifiers":[
        {
            "category":"Professional",
            "subcategory":"Business Services",
            "type":"Services"
        }
    ],
    "sg:phone":"+1 207 829 4008",
    "sg:postcode":"04021",
    "sg:province":"ME",
    "sg:tags":[
        "convention",
        "meeting",
        "facility"
    ],
    "wof:name":"Tuller Group Intl Speakers Bur",
    "wof:placetype":"venue"
},
  "geometry": {"coordinates":[-70.24818999999999,43.800979],"type":"Point"}
}