{
  "type": "Feature",
  "properties": {
    "addr:full":"187 Washington St Auburn ME 04210",
    "addr:housenumber":"187",
    "addr:postcode":"04210",
    "addr:street":"Washington St",
    "iso:country":"US",
    "sg:address":"187 Washington St",
    "sg:city":"Auburn",
    "sg:classifiers":[
        {
            "category":"Building & Trades",
            "subcategory":"Construction",
            "type":"Services"
        }
    ],
    "sg:phone":"+1 207 777 5739",
    "sg:postcode":"04210",
    "sg:province":"ME",
    "sg:tags":[
        "dry wall",
        "contractor"
    ],
    "wof:name":"LA Pointe Drywall Inc",
    "wof:placetype":"venue"
},
  "geometry": {"coordinates":[-70.233943,44.082521],"type":"Point"}
}