{
  "type": "Feature",
  "properties": {
    "addr:full":"2331 Congress St Portland ME 04102",
    "addr:housenumber":"2331",
    "addr:postcode":"04102",
    "addr:street":"Congress St",
    "iso:country":"US",
    "sg:address":"2331 Congress St",
    "sg:city":"Portland",
    "sg:classifiers":[
        {
            "category":"Insurance",
            "subcategory":"Insurance Agent",
            "type":"Services"
        }
    ],
    "sg:phone":"+1 207 780 1677",
    "sg:postcode":"04102",
    "sg:province":"ME",
    "sg:website":"www.crossagency.com",
    "wof:name":"Cross Insurance",
    "wof:placetype":"venue"
},
  "geometry": {"coordinates":[-70.33413400000001,43.650961],"type":"Point"}
}