{
  "type": "Feature",
  "properties": {
    "iso:country":"US",
    "sg:address":"79 Main St",
    "sg:city":"Newport",
    "sg:classifiers":[
        {
            "category":"Banks & Credit Unions",
            "subcategory":"Bank",
            "type":"Services"
        }
    ],
    "sg:phone":"+1 207 368 4382",
    "sg:postcode":"04953",
    "sg:province":"ME",
    "wof:name":"Bank Of America",
    "wof:placetype":"venue"
},
  "geometry": {"coordinates":[-69.27846,44.83544],"type":"Point"}
}