{
  "type": "Feature",
  "properties": {
    "iso:country":"US",
    "sg:address":"16 Child St",
    "sg:city":"Augusta",
    "sg:classifiers":[
        {
            "category":"Government",
            "subcategory":"Office",
            "type":"Public Place"
        }
    ],
    "sg:phone":"+1 207 624 3100",
    "sg:postcode":"04330",
    "sg:province":"ME",
    "wof:name":"Transportation-Environmental",
    "wof:placetype":"venue"
},
  "geometry": {"coordinates":[-69.77641199999999,44.307465],"type":"Point"}
}