{
  "type": "Feature",
  "properties": {
    "addr:full":"28 Main St Bangor ME 04401",
    "addr:housenumber":"28",
    "addr:postcode":"04401",
    "addr:street":"Main St",
    "iso:country":"US",
    "sg:address":"28 Main St",
    "sg:city":"Bangor",
    "sg:classifiers":[
        {
            "category":"Professional",
            "subcategory":"Lawyer & Legal Services",
            "type":"Services"
        }
    ],
    "sg:phone":"+1 207 941 2395",
    "sg:postcode":"04401",
    "sg:province":"ME",
    "sg:tags":[
        "attorney"
    ],
    "wof:name":"Stephen C Smith Law Offices",
    "wof:placetype":"venue"
},
  "geometry": {"coordinates":[-68.771844,44.800362],"type":"Point"}
}