{
  "type": "Feature",
  "properties": {
    "iso:country":"US",
    "sg:address":"16 Shackford St",
    "sg:city":"Eastport",
    "sg:classifiers":[
        {
            "category":"Organizations",
            "subcategory":"Religious Organization",
            "type":"Services"
        }
    ],
    "sg:phone":"+1 207 853 2326",
    "sg:postcode":"04631",
    "sg:province":"ME",
    "sg:tags":[
        "church"
    ],
    "wof:name":"First Unitarian Society",
    "wof:placetype":"venue"
},
  "geometry": {"coordinates":[-66.987465,44.903015],"type":"Point"}
}