{
  "type": "Feature",
  "properties": {
    "addr:full":"273 Presumpscot St Portland ME 04103",
    "addr:housenumber":"273",
    "addr:postcode":"04103",
    "addr:street":"Presumpscot St",
    "iso:country":"US",
    "sg:address":"273 Presumpscot St",
    "sg:city":"Portland",
    "sg:classifiers":[
        {
            "category":"Wholesale",
            "subcategory":"Home Furnishings",
            "type":"Manufacturing & Wholesale Goods"
        }
    ],
    "sg:phone":"+1 207 780 8387",
    "sg:postcode":"04103",
    "sg:province":"ME",
    "sg:tags":[
        "picture",
        "frame"
    ],
    "wof:name":"Mark Allan Framing",
    "wof:placetype":"venue"
},
  "geometry": {"coordinates":[-70.25948,43.699129],"type":"Point"}
}