{
  "type": "Feature",
  "properties": {
    "addr:full":"91 Auburn St Portland ME 04103",
    "addr:housenumber":"91",
    "addr:postcode":"04103",
    "addr:street":"Auburn St",
    "iso:country":"US",
    "sg:address":"91 Auburn St",
    "sg:city":"Portland",
    "sg:classifiers":[
        {
            "category":"Coffee & Tea",
            "type":"Food & Drink"
        }
    ],
    "sg:menulink":"http://www.allmenus.com/me/portland/113670-starbucks-coffee/menu/",
    "sg:phone":"+1 207 878 6583",
    "sg:postcode":"04103",
    "sg:province":"ME",
    "sg:tags":[
        "american"
    ],
    "wof:name":"Starbucks Coffee",
    "wof:placetype":"venue"
},
  "geometry": {"coordinates":[-70.28948800000001,43.703664],"type":"Point"}
}