{
  "type": "Feature",
  "properties": {
    "iso:country":"US",
    "sg:address":"129 Newfield Rd",
    "sg:city":"Shapleigh",
    "sg:classifiers":[
        {
            "category":"Building & Trades",
            "subcategory":"Construction",
            "type":"Services"
        }
    ],
    "sg:phone":"+1 207 247 4459",
    "sg:postcode":"04076",
    "sg:province":"ME",
    "sg:tags":[
        "contractor"
    ],
    "wof:name":"Norseland Builders",
    "wof:placetype":"venue"
},
  "geometry": {"coordinates":[-70.8103,43.595731],"type":"Point"}
}