{
  "type": "Feature",
  "properties": {
    "addr:full":"105 Middle St Lewiston ME 04240",
    "addr:housenumber":"105",
    "addr:postcode":"04240",
    "addr:street":"Middle St",
    "iso:country":"US",
    "sg:address":"105 Middle St",
    "sg:city":"Lewiston",
    "sg:classifiers":[
        {
            "category":"Social Services",
            "type":"Services"
        }
    ],
    "sg:phone":"+1 207 784 8774",
    "sg:postcode":"04240",
    "sg:province":"ME",
    "sg:tags":[
        "counselor",
        "marriage",
        "family"
    ],
    "wof:name":"Patrick D'Ambroise",
    "wof:placetype":"venue"
},
  "geometry": {"coordinates":[-70.216334,44.098395],"type":"Point"}
}