{
  "type": "Feature",
  "properties": {
    "iso:country":"US",
    "sg:address":"400 Egypt Rd",
    "sg:city":"Damariscotta",
    "sg:classifiers":[
        {
            "category":"Personal",
            "type":"Services"
        }
    ],
    "sg:phone":"+1 207 563 2737",
    "sg:postcode":"04543",
    "sg:province":"ME",
    "sg:tags":[
        "therapist",
        "massage"
    ],
    "wof:name":"Tree Of Life Ctr",
    "wof:placetype":"venue"
},
  "geometry": {"coordinates":[-69.467305,44.058709],"type":"Point"}
}