{
  "type": "Feature",
  "properties": {
    "addr:full":"986 Acadia Hwy East Orland ME 04431",
    "addr:housenumber":"986",
    "addr:postcode":"04431",
    "addr:street":"Acadia Hwy East",
    "iso:country":"US",
    "sg:address":"986 Acadia Hwy",
    "sg:city":"East Orland",
    "sg:classifiers":[
        {
            "category":"Government",
            "subcategory":"Post Office",
            "type":"Public Place"
        }
    ],
    "sg:phone":"+1 207 469 1170",
    "sg:postcode":"04431",
    "sg:province":"ME",
    "wof:name":"US Post Office",
    "wof:placetype":"venue"
},
  "geometry": {"coordinates":[-68.689418,44.564586],"type":"Point"}
}