{
  "type": "Feature",
  "properties": {
    "iso:country":"US",
    "sg:address":"1080 S Main St",
    "sg:city":"Andover",
    "sg:classifiers":[
        {
            "category":"Sports & Exercise",
            "subcategory":"Race Track",
            "type":"Entertainment"
        }
    ],
    "sg:phone":"+1 207 392 4101",
    "sg:postcode":"04216",
    "sg:province":"ME",
    "wof:name":"Race Basics",
    "wof:placetype":"venue"
},
  "geometry": {"coordinates":[-70.736852,44.591058],"type":"Point"}
}