{
  "type": "Feature",
  "properties": {
    "addr:full":"10 Stillwater Ave Orono ME 04473",
    "addr:housenumber":"10",
    "addr:postcode":"04473",
    "addr:street":"Stillwater Ave",
    "iso:country":"US",
    "sg:address":"10 Stillwater Ave",
    "sg:city":"Orono",
    "sg:classifiers":[
        {
            "category":"Restaurant",
            "type":"Food & Drink"
        }
    ],
    "sg:menulink":"http://www.allmenus.com/me/orono/119837-subway/menu/",
    "sg:phone":"+1 207 827 4780",
    "sg:postcode":"04473",
    "sg:province":"ME",
    "sg:tags":[
        "american",
        "sandwich"
    ],
    "wof:name":"Subway",
    "wof:placetype":"venue"
},
  "geometry": {"coordinates":[-68.689491,44.905144],"type":"Point"}
}