{
  "type": "Feature",
  "properties": {
    "addr:full":"10 Washington St Waterville ME 04901",
    "addr:housenumber":"10",
    "addr:postcode":"04901",
    "addr:street":"Washington St",
    "iso:country":"US",
    "sg:address":"10 Washington St",
    "sg:city":"Waterville",
    "sg:classifiers":[
        {
            "category":"Health Services",
            "subcategory":"Doctor",
            "type":"Services"
        }
    ],
    "sg:phone":"+1 207 877 7100",
    "sg:postcode":"04901",
    "sg:province":"ME",
    "sg:tags":[
        "physician",
        "surgeon"
    ],
    "wof:name":"Family Medicine Assoc",
    "wof:placetype":"venue"
},
  "geometry": {"coordinates":[-69.675498,44.545752],"type":"Point"}
}