{
  "type": "Feature",
  "properties": {
    "iso:country":"US",
    "sg:address":"281 Main St",
    "sg:city":"Warren",
    "sg:classifiers":[
        {
            "category":"Retail",
            "subcategory":"Laundry & Dry Cleaning",
            "type":"Services"
        }
    ],
    "sg:phone":"+1 207 273 3204",
    "sg:postcode":"04864",
    "sg:province":"ME",
    "wof:name":"Warren Village Laundry",
    "wof:placetype":"venue"
},
  "geometry": {"coordinates":[-69.241465,44.120524],"type":"Point"}
}