{
  "type": "Feature",
  "properties": {
    "iso:country":"US",
    "sg:address":"119 Forest Ave",
    "sg:city":"Bangor",
    "sg:classifiers":[
        {
            "category":"Retail",
            "subcategory":"Repair Shop",
            "type":"Services"
        }
    ],
    "sg:phone":"+1 207 990 3881",
    "sg:postcode":"04401",
    "sg:province":"ME",
    "sg:tags":[
        "upholsterer"
    ],
    "wof:name":"Babcock's Kustom Upholstery",
    "wof:placetype":"venue"
},
  "geometry": {"coordinates":[-68.764691,44.812448],"type":"Point"}
}