{
  "type": "Feature",
  "properties": {
    "iso:country":"US",
    "sg:address":"844 Long Plains Rd",
    "sg:city":"Buxton",
    "sg:classifiers":[
        {
            "category":"Wholesale",
            "subcategory":"Construction Materials",
            "type":"Manufacturing & Wholesale Goods"
        }
    ],
    "sg:phone":"+1 207 929 8595",
    "sg:postcode":"04093",
    "sg:province":"ME",
    "sg:tags":[
        "lumber"
    ],
    "wof:name":"Buxton Log-Yard",
    "wof:placetype":"venue"
},
  "geometry": {"coordinates":[-70.559311,43.657551],"type":"Point"}
}