{
  "type": "Feature",
  "properties": {
    "addr:full":"844 Long Plains Rd Buxton ME 04093",
    "addr:housenumber":"844",
    "addr:postcode":"04093",
    "addr:street":"Long Plains Rd",
    "iso:country":"US",
    "sg:address":"844 Long Plains Rd",
    "sg:city":"Buxton",
    "sg:classifiers":[
        {
            "category":"Wholesale",
            "subcategory":"Construction Materials",
            "type":"Manufacturing & Wholesale Goods"
        }
    ],
    "sg:phone":"+1 207 929 8595",
    "sg:postcode":"04093",
    "sg:province":"ME",
    "sg:tags":[
        "lumber"
    ],
    "wof:name":"Buxton Log-Yard",
    "wof:placetype":"venue"
},
  "geometry": {"coordinates":[-70.55931099999999,43.657551],"type":"Point"}
}