{
  "type": "Feature",
  "properties": {
    "addr:full":"376 Main St Rockland ME 04841",
    "addr:housenumber":"376",
    "addr:postcode":"04841",
    "addr:street":"Main St",
    "iso:country":"US",
    "sg:address":"376 Main St",
    "sg:city":"Rockland",
    "sg:classifiers":[
        {
            "category":"Shopping",
            "subcategory":"Jewelry",
            "type":"Retail Goods"
        }
    ],
    "sg:phone":"+1 207 594 4552",
    "sg:postcode":"04841",
    "sg:province":"ME",
    "sg:tags":[
        "jeweler"
    ],
    "wof:name":"By George Jewelers",
    "wof:placetype":"venue"
},
  "geometry": {"coordinates":[-69.109184,44.102895],"type":"Point"}
}