{
  "type": "Feature",
  "properties": {
    "iso:country":"US",
    "sg:address":"15 Shop N Save Dr",
    "sg:city":"Scarborough",
    "sg:classifiers":[
        {
            "category":"Personal",
            "subcategory":"Beauty Salon",
            "type":"Services"
        }
    ],
    "sg:phone":"+1 207 885 5931",
    "sg:postcode":"04074",
    "sg:province":"ME",
    "wof:name":"Haircuts Plus",
    "wof:placetype":"venue"
},
  "geometry": {"coordinates":[-70.33270899999999,43.593979],"type":"Point"}
}