{
  "type": "Feature",
  "properties": {
    "addr:full":"18 Common St Waterville ME 04901",
    "addr:housenumber":"18",
    "addr:postcode":"04901",
    "addr:street":"Common St",
    "iso:country":"US",
    "sg:address":"18 Common St",
    "sg:city":"Waterville",
    "sg:classifiers":[
        {
            "category":"Banks & Credit Unions",
            "subcategory":"Investment Brokerage",
            "type":"Services"
        }
    ],
    "sg:phone":"+1 207 873 7302",
    "sg:postcode":"04901",
    "sg:province":"ME",
    "sg:tags":[
        "advisory",
        "financial"
    ],
    "wof:name":"Edward S Riggs Investment Cnsl",
    "wof:placetype":"venue"
},
  "geometry": {"coordinates":[-69.628816,44.549311],"type":"Point"}
}