{
  "type": "Feature",
  "properties": {
    "iso:country":"US",
    "sg:address":"500 Main St",
    "sg:city":"Caribou",
    "sg:classifiers":[
        {
            "category":"Autos & Motor Vehicles",
            "subcategory":"Automobile Sales",
            "type":"Retail Goods"
        }
    ],
    "sg:phone":"+1 207 493 3358",
    "sg:postcode":"04736",
    "sg:province":"ME",
    "sg:tags":[
        "car",
        "dealer"
    ],
    "wof:name":"Gagnon's Auto-Rv Sales Inc",
    "wof:placetype":"venue"
},
  "geometry": {"coordinates":[-68.01078,46.848456],"type":"Point"}
}