{
  "type": "Feature",
  "properties": {
    "iso:country":"US",
    "sg:address":"50 New Portland Rd",
    "sg:city":"Gorham",
    "sg:classifiers":[
        {
            "category":"Health Services",
            "subcategory":"Nursing And Care Facility",
            "type":"Services"
        }
    ],
    "sg:phone":"+1 207 839 5757",
    "sg:postcode":"04038",
    "sg:province":"ME",
    "sg:tags":[
        "home",
        "convalescent"
    ],
    "wof:name":"Gorham House Preschool",
    "wof:placetype":"venue"
},
  "geometry": {"coordinates":[-70.434226,43.68077],"type":"Point"}
}