{
  "type": "Feature",
  "properties": {
    "addr:full":"10 Forest Falls Dr Yarmouth ME 04096",
    "addr:housenumber":"10",
    "addr:postcode":"04096",
    "addr:street":"Forest Falls Dr",
    "iso:country":"US",
    "sg:address":"10 Forest Falls Dr",
    "sg:city":"Yarmouth",
    "sg:classifiers":[
        {
            "category":"Insurance",
            "subcategory":"Insurance Agent",
            "type":"Services"
        }
    ],
    "sg:phone":"+1 207 846 3500",
    "sg:postcode":"04096",
    "sg:province":"ME",
    "wof:name":"Professional Planning Group",
    "wof:placetype":"venue"
},
  "geometry": {"coordinates":[-70.186094,43.805736],"type":"Point"}
}