{
  "type": "Feature",
  "properties": {
    "iso:country":"US",
    "sg:address":"1177 Broadway",
    "sg:city":"South Portland",
    "sg:classifiers":[
        {
            "category":"Home & Garden",
            "subcategory":"Building Materials",
            "type":"Retail Goods"
        }
    ],
    "sg:phone":"+1 207 985 8889",
    "sg:postcode":"04106",
    "sg:province":"ME",
    "sg:tags":[
        "windows"
    ],
    "wof:name":"A-Best Window",
    "wof:placetype":"venue"
},
  "geometry": {"coordinates":[-70.28112,43.628675],"type":"Point"}
}