{
  "type": "Feature",
  "properties": {
    "iso:country":"US",
    "sg:address":"812 Webster St",
    "sg:city":"Lewiston",
    "sg:classifiers":[
        {
            "category":"Building & Trades",
            "subcategory":"Construction",
            "type":"Services"
        }
    ],
    "sg:phone":"+1 207 783 1567",
    "sg:postcode":"04240",
    "sg:province":"ME",
    "sg:tags":[
        "excavating",
        "contractor"
    ],
    "wof:name":"Dube Gravel Co",
    "wof:placetype":"venue"
},
  "geometry": {"coordinates":[-70.163247,44.078604],"type":"Point"}
}