{
  "type": "Feature",
  "properties": {
    "iso:country":"US",
    "sg:address":"5 Park St",
    "sg:city":"Waterville",
    "sg:classifiers":[
        {
            "category":"Retail",
            "subcategory":"Funeral Services",
            "type":"Services"
        }
    ],
    "sg:phone":"+1 207 873 3611",
    "sg:postcode":"04901",
    "sg:province":"ME",
    "sg:tags":[
        "director"
    ],
    "wof:name":"Redington Co Funeral Home",
    "wof:placetype":"venue"
},
  "geometry": {"coordinates":[-69.632509,44.55123],"type":"Point"}
}