{
  "type": "Feature",
  "properties": {
    "addr:full":"352 Finntown Rd Waldoboro ME 04572",
    "addr:housenumber":"352",
    "addr:postcode":"04572",
    "addr:street":"Finntown Rd",
    "iso:country":"US",
    "sg:address":"352 Finntown Rd",
    "sg:city":"Waldoboro",
    "sg:classifiers":[
        {
            "category":"Retail",
            "subcategory":"Repair Shop",
            "type":"Services"
        }
    ],
    "sg:phone":"+1 207 832 7056",
    "sg:postcode":"04572",
    "sg:province":"ME",
    "wof:name":"Robies Septic Tank Cleaning",
    "wof:placetype":"venue"
},
  "geometry": {"coordinates":[-69.31749499999999,44.043434],"type":"Point"}
}