{
  "type": "Feature",
  "properties": {
    "iso:country":"US",
    "sg:address":"48 River St",
    "sg:city":"Fryeburg",
    "sg:classifiers":[
        {
            "category":"Farming",
            "subcategory":"Farm",
            "type":"Manufacturing & Wholesale Goods"
        }
    ],
    "sg:phone":"+1 207 935 2567",
    "sg:postcode":"04037",
    "sg:province":"ME",
    "sg:website":"www.westonsfarm.com",
    "wof:name":"Weston's Farm",
    "wof:placetype":"venue"
},
  "geometry": {"coordinates":[-70.98366,44.014506],"type":"Point"}
}