{
  "type": "Feature",
  "properties": {
    "iso:country":"US",
    "sg:address":"11 Pleasant St",
    "sg:city":"Milo",
    "sg:classifiers":[
        {
            "category":"Organizations",
            "subcategory":"Religious Organization",
            "type":"Services"
        }
    ],
    "sg:phone":"+1 207 943 5500",
    "sg:postcode":"04463",
    "sg:province":"ME",
    "wof:name":"United Bptst Chrch Prsng Study",
    "wof:placetype":"venue"
},
  "geometry": {"coordinates":[-68.984486,45.254606],"type":"Point"}
}