{
  "type": "Feature",
  "properties": {
    "iso:country":"US",
    "sg:address":"61 Main St",
    "sg:city":"Calais",
    "sg:classifiers":[
        {
            "category":"Shopping",
            "subcategory":"Department Store",
            "type":"Retail Goods"
        }
    ],
    "sg:phone":"+1 207 454 1421",
    "sg:postcode":"04619",
    "sg:province":"ME",
    "wof:name":"Marden's Surplus & Salvage",
    "wof:placetype":"venue"
},
  "geometry": {"coordinates":[-67.280994,45.188788],"type":"Point"}
}