{
  "type": "Feature",
  "properties": {
    "iso:country":"US",
    "sg:address":"101 Alewive Rd",
    "sg:city":"Kennebunk",
    "sg:classifiers":[
        {
            "category":"Freight",
            "type":"Transportation"
        }
    ],
    "sg:phone":"+1 207 985 9900",
    "sg:postcode":"04043",
    "sg:province":"ME",
    "sg:tags":[
        "commercial",
        "storage"
    ],
    "wof:name":"Exit 3 Safe Storage",
    "wof:placetype":"venue"
},
  "geometry": {"coordinates":[-70.563115,43.410024],"type":"Point"}
}