{
  "type": "Feature",
  "properties": {
    "iso:country":"US",
    "sg:address":"27 Margison Rd",
    "sg:city":"Caribou",
    "sg:classifiers":[
        {
            "category":"Home & Garden",
            "subcategory":"Hardware",
            "type":"Retail Goods"
        }
    ],
    "sg:phone":"+1 207 896 5716",
    "sg:postcode":"04762",
    "sg:province":"ME",
    "wof:name":"Bellport Hardware",
    "wof:placetype":"venue"
},
  "geometry": {"coordinates":[-68.118916,46.918994],"type":"Point"}
}