{
  "type": "Feature",
  "properties": {
    "addr:full":"75 Main St Belfast ME 04915",
    "addr:housenumber":"75",
    "addr:postcode":"04915",
    "addr:street":"Main St",
    "iso:country":"US",
    "sg:address":"75 Main St",
    "sg:city":"Belfast",
    "sg:classifiers":[
        {
            "category":"Home & Garden",
            "subcategory":"Hardware",
            "type":"Retail Goods"
        }
    ],
    "sg:phone":"+1 207 338 1094",
    "sg:postcode":"04915",
    "sg:province":"ME",
    "wof:name":"Home Supply Ctr",
    "wof:placetype":"venue"
},
  "geometry": {"coordinates":[-69.00648099999999,44.426475],"type":"Point"}
}