{
  "type": "Feature",
  "properties": {
    "iso:country":"US",
    "sg:address":"17 Parsons Rd",
    "sg:city":"Presque Isle",
    "sg:classifiers":[
        {
            "category":"Home & Garden",
            "subcategory":"Building Materials",
            "type":"Retail Goods"
        }
    ],
    "sg:phone":"+1 207 764 4488",
    "sg:postcode":"04769",
    "sg:province":"ME",
    "sg:tags":[
        "plumbing",
        "fixture",
        "supply"
    ],
    "wof:name":"Northeast Kitchen & Bath",
    "wof:placetype":"venue"
},
  "geometry": {"coordinates":[-68.01923600000001,46.684897],"type":"Point"}
}