{
  "type": "Feature",
  "properties": {
    "iso:country":"US",
    "sg:address":"117 Goff St",
    "sg:city":"Auburn",
    "sg:classifiers":[
        {
            "category":"Health Services",
            "subcategory":"Doctor",
            "type":"Services"
        }
    ],
    "sg:phone":"+1 207 784 3000",
    "sg:postcode":"04210",
    "sg:province":"ME",
    "sg:tags":[
        "physician",
        "surgeon"
    ],
    "wof:name":"Kurt M Oswald MD",
    "wof:placetype":"venue"
},
  "geometry": {"coordinates":[-70.233487,44.102514],"type":"Point"}
}