{
  "type": "Feature",
  "properties": {
    "iso:country":"US",
    "sg:address":"51 Main St",
    "sg:city":"Bucksport",
    "sg:classifiers":[
        {
            "category":"Professional",
            "subcategory":"Research",
            "type":"Services"
        }
    ],
    "sg:phone":"+1 207 469 6616",
    "sg:postcode":"04416",
    "sg:province":"ME",
    "sg:tags":[
        "market",
        "analysis"
    ],
    "wof:name":"Bucksport Marine Svc",
    "wof:placetype":"venue"
},
  "geometry": {"coordinates":[-68.77686,44.570142],"type":"Point"}
}