{
  "type": "Feature",
  "properties": {
    "addr:full":"20 Shore Rd Ogunquit ME 03907",
    "addr:housenumber":"20",
    "addr:postcode":"03907",
    "addr:street":"Shore Rd",
    "iso:country":"US",
    "sg:address":"20 Shore Rd",
    "sg:city":"Ogunquit",
    "sg:classifiers":[
        {
            "category":"Travel",
            "subcategory":"Hotels & Motels",
            "type":"Entertainment"
        }
    ],
    "sg:phone":"+1 207 646 1470",
    "sg:postcode":"03907",
    "sg:province":"ME",
    "wof:name":"Village House",
    "wof:placetype":"venue"
},
  "geometry": {"coordinates":[-70.594002,43.238098],"type":"Point"}
}