{
  "type": "Feature",
  "properties": {
    "addr:full":"550 College St Lewiston ME 04240",
    "addr:housenumber":"550",
    "addr:postcode":"04240",
    "addr:street":"College St",
    "iso:country":"US",
    "sg:address":"550 College St",
    "sg:city":"Lewiston",
    "sg:classifiers":[
        {
            "category":"Health Services",
            "subcategory":"Clinic",
            "type":"Services"
        }
    ],
    "sg:phone":"+1 207 783 7375",
    "sg:postcode":"04240",
    "sg:province":"ME",
    "sg:tags":[
        "home"
    ],
    "wof:name":"Assisted Home Care II",
    "wof:placetype":"venue"
},
  "geometry": {"coordinates":[-70.188108,44.124759],"type":"Point"}
}