{
  "type": "Feature",
  "properties": {
    "iso:country":"US",
    "sg:address":"33 Elmwood Ave",
    "sg:city":"Westbrook",
    "sg:classifiers":[
        {
            "category":"Recreation",
            "type":"Entertainment"
        }
    ],
    "sg:phone":"+1 207 797 4248",
    "sg:postcode":"04092",
    "sg:province":"ME",
    "sg:tags":[
        "parlor",
        "billiard"
    ],
    "wof:name":"Prides Corner Billiards",
    "wof:placetype":"venue"
},
  "geometry": {"coordinates":[-70.334728,43.715888],"type":"Point"}
}