{
  "type": "Feature",
  "properties": {
    "addr:full":"925 Main St Sanford ME 04073",
    "addr:housenumber":"925",
    "addr:postcode":"04073",
    "addr:street":"Main St",
    "iso:country":"US",
    "sg:address":"925 Main St",
    "sg:city":"Sanford",
    "sg:classifiers":[
        {
            "category":"Bakery",
            "type":"Food & Drink"
        },
        {
            "category":"Coffee & Tea",
            "type":"Food & Drink"
        },
        {
            "category":"Bagels",
            "type":"Food & Drink"
        },
        {
            "category":"Donuts",
            "type":"Food & Drink"
        }
    ],
    "sg:menulink":"http://www.allmenus.com/me/sanford/149069-dunkin-donuts/menu/",
    "sg:phone":"+1 207 324 8663",
    "sg:postcode":"04073",
    "sg:province":"ME",
    "sg:tags":[
        "wrap",
        "american",
        "sandwich",
        "pastry"
    ],
    "wof:name":"Dunkin' Donuts",
    "wof:placetype":"venue"
},
  "geometry": {"coordinates":[-70.77437399999999,43.437885],"type":"Point"}
}