{
  "type": "Feature",
  "properties": {
    "iso:country":"US",
    "sg:address":"16 Union St",
    "sg:city":"Brunswick",
    "sg:classifiers":[
        {
            "category":"Manufacturing",
            "subcategory":"Jewelry",
            "type":"Manufacturing & Wholesale Goods"
        }
    ],
    "sg:phone":"+1 207 729 3599",
    "sg:postcode":"04011",
    "sg:province":"ME",
    "sg:tags":[
        "casting"
    ],
    "wof:name":"J A Henkel Co Inc",
    "wof:placetype":"venue"
},
  "geometry": {"coordinates":[-69.968611,43.917256],"type":"Point"}
}