{
  "type": "Feature",
  "properties": {
    "addr:full":"15 Main St Blue Hill ME 04609",
    "addr:housenumber":"15",
    "addr:postcode":"04609",
    "addr:street":"Main St",
    "iso:country":"US",
    "sg:address":"15 Main St",
    "sg:city":"Blue Hill",
    "sg:classifiers":[
        {
            "category":"Banks & Credit Unions",
            "subcategory":"Bank",
            "type":"Services"
        }
    ],
    "sg:phone":"+1 207 374 3640",
    "sg:postcode":"04609",
    "sg:province":"ME",
    "sg:tags":[
        "loan",
        "real estate"
    ],
    "wof:name":"Wells Fargo Home Mortgage Inc",
    "wof:placetype":"venue"
},
  "geometry": {"coordinates":[-68.20487199999999,44.390401],"type":"Point"}
}