{
  "type": "Feature",
  "properties": {
    "iso:country":"US",
    "sg:address":"400 Allen Ave",
    "sg:city":"Portland",
    "sg:classifiers":[
        {
            "category":"Home & Garden",
            "subcategory":"Building Materials",
            "type":"Retail Goods"
        }
    ],
    "sg:phone":"+1 207 878 2345",
    "sg:postcode":"04103",
    "sg:province":"ME",
    "sg:tags":[
        "modular"
    ],
    "wof:name":"Southern Maine Real Estate",
    "wof:placetype":"venue"
},
  "geometry": {"coordinates":[-70.287772,43.700233],"type":"Point"}
}