{
  "type": "Feature",
  "properties": {
    "addr:full":"650 Main St Oxford ME 04270",
    "addr:housenumber":"650",
    "addr:postcode":"04270",
    "addr:street":"Main St",
    "iso:country":"US",
    "sg:address":"650 Main St",
    "sg:city":"Oxford",
    "sg:classifiers":[
        {
            "category":"Manufacturing",
            "subcategory":"Watercraft",
            "type":"Manufacturing & Wholesale Goods"
        }
    ],
    "sg:phone":"+1 207 539 8116",
    "sg:postcode":"04270",
    "sg:province":"ME",
    "sg:tags":[
        "rebuilt",
        "part",
        "boat"
    ],
    "wof:name":"Seaway Boats Inc",
    "wof:placetype":"venue"
},
  "geometry": {"coordinates":[-70.47336799999999,44.140483],"type":"Point"}
}