{
  "type": "Feature",
  "properties": {
    "addr:full":"36 W Main St Monroe ME 04951",
    "addr:housenumber":"36",
    "addr:postcode":"04951",
    "addr:street":"W Main St",
    "iso:country":"US",
    "sg:address":"36 W Main St",
    "sg:city":"Monroe",
    "sg:classifiers":[
        {
            "category":"Education",
            "subcategory":"School",
            "type":"Public Place"
        }
    ],
    "sg:phone":"+1 207 525 3504",
    "sg:postcode":"04951",
    "sg:province":"ME",
    "wof:name":"Monroe Elementary School",
    "wof:placetype":"venue"
},
  "geometry": {"coordinates":[-69.035713,44.612258],"type":"Point"}
}