{
  "type": "Feature",
  "properties": {
    "addr:full":"24 Two Lights Rd Cape Elizabeth ME 04107",
    "addr:housenumber":"24",
    "addr:postcode":"04107",
    "addr:street":"Two Lights Rd",
    "iso:country":"US",
    "sg:address":"24 Two Lights Rd",
    "sg:city":"Cape Elizabeth",
    "sg:classifiers":[
        {
            "category":"Professional",
            "subcategory":"Computer Services",
            "type":"Services"
        }
    ],
    "sg:phone":"+1 207 799 1600",
    "sg:postcode":"04107",
    "sg:province":"ME",
    "sg:tags":[
        "repair"
    ],
    "wof:name":"The Tech Guys",
    "wof:placetype":"venue"
},
  "geometry": {"coordinates":[-70.220052,43.571842],"type":"Point"}
}