{
  "type": "Feature",
  "properties": {
    "iso:country":"US",
    "sg:address":"4 Newton St",
    "sg:city":"Portland",
    "sg:classifiers":[
        {
            "category":"Insurance",
            "subcategory":"Insurance Agent",
            "type":"Services"
        }
    ],
    "sg:phone":"+1 207 797 2203",
    "sg:postcode":"04103",
    "sg:province":"ME",
    "wof:name":"Delano Associates",
    "wof:placetype":"venue"
},
  "geometry": {"coordinates":[-70.305841,43.69859],"type":"Point"}
}