{
  "type": "Feature",
  "properties": {
    "iso:country":"US",
    "sg:address":"69 Old Settlers Ln",
    "sg:city":"Cushing",
    "sg:classifiers":[
        {
            "category":"Building & Trades",
            "subcategory":"Construction",
            "type":"Services"
        }
    ],
    "sg:phone":"+1 207 354 9561",
    "sg:postcode":"04563",
    "sg:province":"ME",
    "sg:tags":[
        "general",
        "contractor"
    ],
    "wof:name":"Haskell's Handyman Svc",
    "wof:placetype":"venue"
},
  "geometry": {"coordinates":[-69.214685,44.027998],"type":"Point"}
}