{
  "type": "Feature",
  "properties": {
    "addr:full":"14 Golda Ct Guilford ME 04443",
    "addr:housenumber":"14",
    "addr:postcode":"04443",
    "addr:street":"Golda Ct",
    "iso:country":"US",
    "sg:address":"14 Golda Ct",
    "sg:city":"Guilford",
    "sg:classifiers":[
        {
            "category":"Education",
            "subcategory":"Special Training",
            "type":"Public Place"
        }
    ],
    "sg:phone":"+1 207 876 4445",
    "sg:postcode":"04443",
    "sg:province":"ME",
    "sg:tags":[
        "instruction",
        "driving"
    ],
    "wof:name":"Positive Traction Driving Sch",
    "wof:placetype":"venue"
},
  "geometry": {"coordinates":[-69.385582,45.170272],"type":"Point"}
}