{
  "type": "Feature",
  "properties": {
    "addr:full":"140 Main St Lisbon Falls ME 04252",
    "addr:housenumber":"140",
    "addr:postcode":"04252",
    "addr:street":"Main St",
    "iso:country":"US",
    "sg:address":"140 Main St",
    "sg:city":"Lisbon Falls",
    "sg:classifiers":[
        {
            "category":"Retail",
            "subcategory":"Auto Repair",
            "type":"Services"
        }
    ],
    "sg:phone":"+1 207 353 2329",
    "sg:postcode":"04252",
    "sg:province":"ME",
    "sg:tags":[
        "body",
        "automobile",
        "painting"
    ],
    "sg:website":"www.icarmaine.com",
    "wof:name":"Fern's Body Shop",
    "wof:placetype":"venue"
},
  "geometry": {"coordinates":[-70.054215,44.006271],"type":"Point"}
}