{
  "type": "Feature",
  "properties": {
    "addr:full":"132 Brentwood St Portland ME 04103",
    "addr:housenumber":"132",
    "addr:postcode":"04103",
    "addr:street":"Brentwood St",
    "iso:country":"US",
    "sg:address":"132 Brentwood St",
    "sg:city":"Portland",
    "sg:classifiers":[
        {
            "category":"Professional",
            "subcategory":"Engineering",
            "type":"Services"
        }
    ],
    "sg:phone":"+1 207 773 4880",
    "sg:postcode":"04103",
    "sg:province":"ME",
    "sg:tags":[
        "engineer"
    ],
    "wof:name":"Resurgence Engineering",
    "wof:placetype":"venue"
},
  "geometry": {"coordinates":[-70.299762,43.677548],"type":"Point"}
}