{
  "type": "Feature",
  "properties": {
    "iso:country":"US",
    "sg:address":"34 Gould Rd",
    "sg:city":"Biddeford",
    "sg:classifiers":[
        {
            "category":"Building & Trades",
            "subcategory":"Cleaning & Sanitation",
            "type":"Services"
        }
    ],
    "sg:phone":"+1 207 499 2768",
    "sg:postcode":"04005",
    "sg:province":"ME",
    "sg:tags":[
        "maintenance"
    ],
    "wof:name":"Doyons Property Maintenance",
    "wof:placetype":"venue"
},
  "geometry": {"coordinates":[-70.584893,43.531182],"type":"Point"}
}