{
  "type": "Feature",
  "properties": {
    "addr:full":"529 US Hwy 1 York ME 03909",
    "addr:housenumber":"529",
    "addr:postcode":"03909",
    "addr:street":"Us Hwy 1",
    "iso:country":"US",
    "sg:address":"529 US Hwy 1",
    "sg:city":"York",
    "sg:classifiers":[
        {
            "category":"Shopping",
            "type":"Retail Goods"
        }
    ],
    "sg:phone":"+1 207 363 0295",
    "sg:postcode":"03909",
    "sg:province":"ME",
    "sg:tags":[
        "orthopedic",
        "appliance"
    ],
    "wof:name":"Maine Orthotics & Prosthetics",
    "wof:placetype":"venue"
},
  "geometry": {"coordinates":[-70.659632,43.154049],"type":"Point"}
}