{
  "type": "Feature",
  "properties": {
    "addr:full":"15 Depot St Bridgton ME 04009",
    "addr:housenumber":"15",
    "addr:postcode":"04009",
    "addr:street":"Depot St",
    "iso:country":"US",
    "sg:address":"15 Depot St",
    "sg:city":"Bridgton",
    "sg:classifiers":[
        {
            "category":"Government",
            "subcategory":"Office",
            "type":"Public Place"
        }
    ],
    "sg:phone":"+1 207 647 2071",
    "sg:postcode":"04009",
    "sg:province":"ME",
    "sg:tags":[
        "federal",
        "security"
    ],
    "wof:name":"US Army Reserve Training",
    "wof:placetype":"venue"
},
  "geometry": {"coordinates":[-70.706057,44.052808],"type":"Point"}
}