{
  "type": "Feature",
  "properties": {
    "iso:country":"US",
    "sg:address":"5 Pine Rd",
    "sg:city":"Falmouth",
    "sg:classifiers":[
        {
            "category":"Restaurant",
            "type":"Food & Drink"
        }
    ],
    "sg:phone":"+1 207 774 1227",
    "sg:postcode":"04105",
    "sg:province":"ME",
    "wof:name":"Great Maine Lobster Co",
    "wof:placetype":"venue"
},
  "geometry": {"coordinates":[-70.256602,43.710094],"type":"Point"}
}