{
  "type": "Feature",
  "properties": {
    "addr:full":"138 Main St Madison ME 04950",
    "addr:housenumber":"138",
    "addr:postcode":"04950",
    "addr:street":"Main St",
    "iso:country":"US",
    "sg:address":"138 Main St",
    "sg:city":"Madison",
    "sg:classifiers":[
        {
            "category":"Building & Trades",
            "subcategory":"Equipment Rental",
            "type":"Services"
        }
    ],
    "sg:phone":"+1 207 696 4034",
    "sg:postcode":"04950",
    "sg:province":"ME",
    "sg:tags":[
        "leasing",
        "furniture"
    ],
    "wof:name":"Jeff's Rent To Own",
    "wof:placetype":"venue"
},
  "geometry": {"coordinates":[-69.878884,44.797906],"type":"Point"}
}