{
  "type": "Feature",
  "properties": {
    "iso:country":"US",
    "sg:address":"367 Togus Rd",
    "sg:city":"Augusta",
    "sg:classifiers":[
        {
            "category":"Building & Trades",
            "subcategory":"Construction",
            "type":"Services"
        }
    ],
    "sg:phone":"+1 207 582 0606",
    "sg:postcode":"04330",
    "sg:province":"ME",
    "sg:tags":[
        "contractor"
    ],
    "wof:name":"D&M Drywall",
    "wof:placetype":"venue"
},
  "geometry": {"coordinates":[-69.710629,44.256367],"type":"Point"}
}