{
  "type": "Feature",
  "properties": {
    "addr:full":"893 Main St Palmyra ME 04965",
    "addr:housenumber":"893",
    "addr:postcode":"04965",
    "addr:street":"Main St",
    "iso:country":"US",
    "sg:address":"893 Main St",
    "sg:city":"Palmyra",
    "sg:classifiers":[
        {
            "category":"Professional",
            "type":"Services"
        }
    ],
    "sg:phone":"+1 207 938 3456",
    "sg:postcode":"04965",
    "sg:province":"ME",
    "sg:tags":[
        "establishment"
    ],
    "wof:name":"Mother Nature's Many Faces",
    "wof:placetype":"venue"
},
  "geometry": {"coordinates":[-69.36019899999999,44.846597],"type":"Point"}
}