{
  "type": "Feature",
  "properties": {
    "addr:full":"82 Neck Rd Litchfield ME 04348",
    "addr:housenumber":"82",
    "addr:postcode":"04348",
    "addr:street":"Neck Rd",
    "iso:country":"US",
    "sg:address":"82 Neck Rd",
    "sg:city":"Litchfield",
    "sg:classifiers":[
        {
            "category":"Shopping",
            "subcategory":"Gifts & Souvenirs",
            "type":"Retail Goods"
        }
    ],
    "sg:phone":"+1 207 724 7300",
    "sg:postcode":"04348",
    "sg:province":"ME",
    "sg:tags":[
        "shop"
    ],
    "wof:name":"Grand View Gardens",
    "wof:placetype":"venue"
},
  "geometry": {"coordinates":[-69.50331,44.187207],"type":"Point"}
}