{
  "type": "Feature",
  "properties": {
    "iso:country":"US",
    "sg:address":"135 Military St",
    "sg:city":"Houlton",
    "sg:classifiers":[
        {
            "category":"Food & Beverages",
            "subcategory":"Groceries & Convenience Stores",
            "type":"Retail Goods"
        }
    ],
    "sg:phone":"+1 207 532 6948",
    "sg:postcode":"04730",
    "sg:province":"ME",
    "wof:name":"Graham's Quick Mart",
    "wof:placetype":"venue"
},
  "geometry": {"coordinates":[-67.824202,46.125049],"type":"Point"}
}