{
  "type": "Feature",
  "properties": {
    "addr:full":"2451 E Conway Rd North Conway ME 03813",
    "addr:housenumber":"2451",
    "addr:postcode":"03813",
    "addr:street":"E Conway Rd",
    "iso:country":"US",
    "sg:address":"2451 E Conway Rd",
    "sg:city":"North Conway",
    "sg:classifiers":[
        {
            "category":"Home & Garden",
            "subcategory":"Building Materials",
            "type":"Retail Goods"
        }
    ],
    "sg:phone":"+1 603 356 6689",
    "sg:postcode":"03813",
    "sg:province":"ME",
    "wof:name":"Northern Building Supply",
    "wof:placetype":"venue"
},
  "geometry": {"coordinates":[-71.03616599999999,44.0007],"type":"Point"}
}