{
  "type": "Feature",
  "properties": {
    "addr:full":"6 Cascade Mill Rd Oakland ME 04963",
    "addr:housenumber":"6",
    "addr:postcode":"04963",
    "addr:street":"Cascade Mill Rd",
    "iso:country":"US",
    "sg:address":"6 Cascade Mill Rd",
    "sg:city":"Oakland",
    "sg:classifiers":[
        {
            "category":"Government",
            "subcategory":"Office",
            "type":"Public Place"
        }
    ],
    "sg:phone":"+1 207 465 2750",
    "sg:postcode":"04963",
    "sg:province":"ME",
    "sg:tags":[
        "city",
        "taxation"
    ],
    "wof:name":"Town Assessor",
    "wof:placetype":"venue"
},
  "geometry": {"coordinates":[-69.709951,44.549124],"type":"Point"}
}