{
  "type": "Feature",
  "properties": {
    "iso:country":"US",
    "sg:address":"1036 Pinkham Brook Rd",
    "sg:city":"Durham",
    "sg:classifiers":[
        {
            "category":"Manufacturing",
            "subcategory":"Building Materials",
            "type":"Manufacturing & Wholesale Goods"
        }
    ],
    "sg:phone":"+1 207 353 5915",
    "sg:postcode":"04222",
    "sg:province":"ME",
    "sg:tags":[
        "making",
        "kitchen",
        "sales",
        "cabinet"
    ],
    "wof:name":"Jerry Dugal & Co Inc",
    "wof:placetype":"venue"
},
  "geometry": {"coordinates":[-70.074111,43.94195],"type":"Point"}
}