{
  "type": "Feature",
  "properties": {
    "iso:country":"US",
    "sg:address":"9 Free St",
    "sg:city":"Camden",
    "sg:classifiers":[
        {
            "category":"Real Estate",
            "subcategory":"Surveying",
            "type":"Services"
        }
    ],
    "sg:phone":"+1 207 236 3480",
    "sg:postcode":"04843",
    "sg:province":"ME",
    "sg:tags":[
        "surveyor"
    ],
    "wof:name":"Island Marine Co",
    "wof:placetype":"venue"
},
  "geometry": {"coordinates":[-69.067902,44.208826],"type":"Point"}
}