{
  "type": "Feature",
  "properties": {
    "addr:full":"131 Messalonskee High Dr Oakland ME 04963",
    "addr:housenumber":"131",
    "addr:postcode":"04963",
    "addr:street":"Messalonskee High Dr",
    "iso:country":"US",
    "sg:address":"131 Messalonskee High Dr",
    "sg:city":"Oakland",
    "sg:classifiers":[
        {
            "category":"Arts & Performance",
            "subcategory":"Theater",
            "type":"Entertainment"
        }
    ],
    "sg:phone":"+1 207 465 9135",
    "sg:postcode":"04963",
    "sg:province":"ME",
    "wof:name":"Messalonskee Performing Arts",
    "wof:placetype":"venue"
},
  "geometry": {"coordinates":[-69.71689000000001,44.557344],"type":"Point"}
}