{
  "type": "Feature",
  "properties": {
    "iso:country":"US",
    "sg:address":"305 Main St",
    "sg:city":"Wilton",
    "sg:classifiers":[
        {
            "category":"Social Services",
            "type":"Services"
        }
    ],
    "sg:phone":"+1 207 645 9700",
    "sg:postcode":"04294",
    "sg:province":"ME",
    "sg:tags":[
        "counselor",
        "marriage",
        "family"
    ],
    "wof:name":"Bright Horizons",
    "wof:placetype":"venue"
},
  "geometry": {"coordinates":[-70.229588,44.589711],"type":"Point"}
}