{
  "type": "Feature",
  "properties": {
    "iso:country":"US",
    "sg:address":"378 Gorham Rd",
    "sg:city":"Scarborough",
    "sg:classifiers":[
        {
            "category":"Professional",
            "subcategory":"Advertising",
            "type":"Services"
        }
    ],
    "sg:phone":"+1 207 854 0900",
    "sg:postcode":"04074",
    "sg:province":"ME",
    "sg:tags":[
        "counselor"
    ],
    "wof:name":"Hunt Productions",
    "wof:placetype":"venue"
},
  "geometry": {"coordinates":[-70.376982,43.628918],"type":"Point"}
}