{
  "type": "Feature",
  "properties": {
    "iso:country":"US",
    "sg:address":"35 Holland Ave",
    "sg:city":"Bar Harbor",
    "sg:classifiers":[
        {
            "category":"Travel",
            "subcategory":"Hotels & Motels",
            "type":"Entertainment"
        }
    ],
    "sg:phone":"+1 207 288 2757",
    "sg:postcode":"04609",
    "sg:province":"ME",
    "sg:tags":[
        "operation"
    ],
    "wof:name":"Evin Hulbert",
    "wof:placetype":"venue"
},
  "geometry": {"coordinates":[-68.211753,44.387829],"type":"Point"}
}