{
  "type": "Feature",
  "properties": {
    "addr:full":"606 Old County Rd Rockland ME 04841",
    "addr:housenumber":"606",
    "addr:postcode":"04841",
    "addr:street":"Old County Rd",
    "iso:country":"US",
    "sg:address":"606 Old County Rd",
    "sg:city":"Rockland",
    "sg:classifiers":[
        {
            "category":"Sports & Exercise",
            "subcategory":"Golf",
            "type":"Entertainment"
        }
    ],
    "sg:phone":"+1 207 594 9322",
    "sg:postcode":"04841",
    "sg:province":"ME",
    "sg:tags":[
        "course"
    ],
    "sg:website":"www.rocklandgolf.com",
    "wof:name":"Rockland Golf Club",
    "wof:placetype":"venue"
},
  "geometry": {"coordinates":[-69.11540599999999,44.124955],"type":"Point"}
}