{
  "type": "Feature",
  "properties": {
    "addr:full":"96 Center St Bangor ME 04401",
    "addr:housenumber":"96",
    "addr:postcode":"04401",
    "addr:street":"Center St",
    "iso:country":"US",
    "sg:address":"96 Center St",
    "sg:city":"Bangor",
    "sg:classifiers":[
        {
            "category":"Shopping",
            "subcategory":"Florist",
            "type":"Retail Goods"
        }
    ],
    "sg:phone":"+1 207 947 4569",
    "sg:postcode":"04401",
    "sg:province":"ME",
    "wof:name":"Bangor Floral Co",
    "wof:placetype":"venue"
},
  "geometry": {"coordinates":[-68.771124,44.806256],"type":"Point"}
}