{
  "type": "Feature",
  "properties": {
    "iso:country":"US",
    "sg:address":"203 Penobscot St",
    "sg:city":"Brewer",
    "sg:classifiers":[
        {
            "category":"Manufacturing",
            "subcategory":"Electronics",
            "type":"Manufacturing & Wholesale Goods"
        }
    ],
    "sg:phone":"+1 207 989 6658",
    "sg:postcode":"04412",
    "sg:province":"ME",
    "sg:tags":[
        "sound",
        "equipment",
        "system"
    ],
    "wof:name":"Mark's Music",
    "wof:placetype":"venue"
},
  "geometry": {"coordinates":[-68.762452,44.797762],"type":"Point"}
}