{
  "type": "Feature",
  "properties": {
    "iso:country":"US",
    "sg:address":"315 Main St",
    "sg:city":"Rockland",
    "sg:classifiers":[
        {
            "category":"Restaurant",
            "type":"Food & Drink"
        }
    ],
    "sg:phone":"+1 207 594 0015",
    "sg:postcode":"04841",
    "sg:province":"ME",
    "wof:name":"Market On Main",
    "wof:placetype":"venue"
},
  "geometry": {"coordinates":[-69.109115,44.104695],"type":"Point"}
}