{
  "type": "Feature",
  "properties": {
    "addr:full":"195 S Main St Brewer ME 04412",
    "addr:housenumber":"195",
    "addr:postcode":"04412",
    "addr:street":"S Main St",
    "iso:country":"US",
    "sg:address":"195 S Main St",
    "sg:city":"Brewer",
    "sg:classifiers":[
        {
            "category":"Manufacturing",
            "subcategory":"Metals",
            "type":"Manufacturing & Wholesale Goods"
        }
    ],
    "sg:phone":"+1 207 989 9676",
    "sg:postcode":"04412",
    "sg:province":"ME",
    "sg:tags":[
        "fabrication",
        "structural"
    ],
    "wof:name":"Kustom Steel",
    "wof:placetype":"venue"
},
  "geometry": {"coordinates":[-68.769177,44.790525],"type":"Point"}
}