{
  "type": "Feature",
  "properties": {
    "addr:full":"73 Portland Street Pier South Portland ME 04106",
    "addr:housenumber":"73",
    "addr:postcode":"04106",
    "addr:street":"Portland Street Pier",
    "iso:country":"US",
    "sg:address":"73 Portland Street Pier",
    "sg:city":"South Portland",
    "sg:classifiers":[
        {
            "category":"Building & Trades",
            "subcategory":"Construction",
            "type":"Services"
        }
    ],
    "sg:phone":"+1 207 657 5375",
    "sg:postcode":"04106",
    "sg:province":"ME",
    "sg:tags":[
        "hanging",
        "contractor"
    ],
    "wof:name":"Schools Leland Pntg Carpentry",
    "wof:placetype":"venue"
},
  "geometry": {"coordinates":[-70.242054,43.649719],"type":"Point"}
}