{
  "type": "Feature",
  "properties": {
    "addr:full":"99 Main St Newport ME 04953",
    "addr:housenumber":"99",
    "addr:postcode":"04953",
    "addr:street":"Main St",
    "iso:country":"US",
    "sg:address":"99 Main St",
    "sg:city":"Newport",
    "sg:classifiers":[
        {
            "category":"Banks & Credit Unions",
            "subcategory":"Bank",
            "type":"Services"
        }
    ],
    "sg:phone":"+1 207 368 4363",
    "sg:postcode":"04953",
    "sg:province":"ME",
    "wof:name":"Banknorth",
    "wof:placetype":"venue"
},
  "geometry": {"coordinates":[-69.278937,44.835488],"type":"Point"}
}