{
  "type": "Feature",
  "properties": {
    "iso:country":"US",
    "sg:address":"64 Main St",
    "sg:city":"Richmond",
    "sg:classifiers":[
        {
            "category":"Restaurant",
            "type":"Food & Drink"
        }
    ],
    "sg:phone":"+1 207 737 2277",
    "sg:postcode":"04357",
    "sg:province":"ME",
    "wof:name":"Railway Cafe",
    "wof:placetype":"venue"
},
  "geometry": {"coordinates":[-69.802824,44.08807],"type":"Point"}
}