{
  "type": "Feature",
  "properties": {
    "iso:country":"US",
    "sg:address":"13 Ocean St",
    "sg:city":"South Portland",
    "sg:classifiers":[
        {
            "category":"Real Estate",
            "subcategory":"Real Estate Agent",
            "type":"Services"
        }
    ],
    "sg:phone":"+1 207 767 5678",
    "sg:postcode":"04106",
    "sg:province":"ME",
    "wof:name":"Millet Edward RE Appraisal",
    "wof:placetype":"venue"
},
  "geometry": {"coordinates":[-70.255055,43.64147],"type":"Point"}
}