{
  "type": "Feature",
  "properties": {
    "addr:full":"39 Main St Clinton ME 04927",
    "addr:housenumber":"39",
    "addr:postcode":"04927",
    "addr:street":"Main St",
    "iso:country":"US",
    "sg:address":"39 Main St",
    "sg:city":"Clinton",
    "sg:classifiers":[
        {
            "category":"Personal",
            "subcategory":"Beauty Salon",
            "type":"Services"
        }
    ],
    "sg:phone":"+1 207 426 2661",
    "sg:postcode":"04927",
    "sg:province":"ME",
    "wof:name":"Gerry's Beauty Salon",
    "wof:placetype":"venue"
},
  "geometry": {"coordinates":[-69.50103799999999,44.637386],"type":"Point"}
}