{
  "type": "Feature",
  "properties": {
    "addr:full":"37 State Rte 236 Kittery ME 03904",
    "addr:housenumber":"37",
    "addr:postcode":"03904",
    "addr:street":"State Rte 236",
    "iso:country":"US",
    "sg:address":"37 State Rte 236",
    "sg:city":"Kittery",
    "sg:classifiers":[
        {
            "category":"Farming",
            "subcategory":"Farm",
            "type":"Manufacturing & Wholesale Goods"
        }
    ],
    "sg:phone":"+1 207 439 3186",
    "sg:postcode":"03904",
    "sg:province":"ME",
    "wof:name":"Lewis Farm LLC",
    "wof:placetype":"venue"
},
  "geometry": {"coordinates":[-70.737713,43.094819],"type":"Point"}
}