{
  "type": "Feature",
  "properties": {
    "addr:full":"516 Mount Hope Ave Bangor ME 04401",
    "addr:housenumber":"516",
    "addr:postcode":"04401",
    "addr:street":"Mount Hope Ave",
    "iso:country":"US",
    "sg:address":"516 Mount Hope Ave",
    "sg:city":"Bangor",
    "sg:classifiers":[
        {
            "category":"Health Services",
            "subcategory":"Nursing And Care Facility",
            "type":"Services"
        }
    ],
    "sg:phone":"+1 207 947 6131",
    "sg:postcode":"04401",
    "sg:province":"ME",
    "sg:tags":[
        "home",
        "convalescent"
    ],
    "wof:name":"Eastside Rehabilitation Ctr",
    "wof:placetype":"venue"
},
  "geometry": {"coordinates":[-68.743666,44.821234],"type":"Point"}
}