{
  "type": "Feature",
  "properties": {
    "iso:country":"US",
    "sg:address":"345 Broadway",
    "sg:city":"Rockland",
    "sg:classifiers":[
        {
            "category":"Organizations",
            "subcategory":"Religious Organization",
            "type":"Services"
        }
    ],
    "sg:phone":"+1 207 594 8750",
    "sg:postcode":"04841",
    "sg:province":"ME",
    "sg:tags":[
        "church"
    ],
    "wof:name":"Unitarian Universalist",
    "wof:placetype":"venue"
},
  "geometry": {"coordinates":[-69.114861,44.112029],"type":"Point"}
}