{
  "type": "Feature",
  "properties": {
    "addr:full":"7 Hinks St Bucksport ME 04416",
    "addr:housenumber":"7",
    "addr:postcode":"04416",
    "addr:street":"Hinks St",
    "iso:country":"US",
    "sg:address":"7 Hinks St",
    "sg:city":"Bucksport",
    "sg:classifiers":[
        {
            "category":"Autos & Motor Vehicles",
            "subcategory":"Auto Supplies",
            "type":"Retail Goods"
        }
    ],
    "sg:phone":"+1 207 469 7977",
    "sg:postcode":"04416",
    "sg:province":"ME",
    "sg:tags":[
        "automobile",
        "parts"
    ],
    "wof:name":"Carquest Auto Parts",
    "wof:placetype":"venue"
},
  "geometry": {"coordinates":[-68.78415200000001,44.572957],"type":"Point"}
}