{
  "type": "Feature",
  "properties": {
    "addr:full":"23 Spring St Scarborough ME 04074",
    "addr:housenumber":"23",
    "addr:postcode":"04074",
    "addr:street":"Spring St",
    "iso:country":"US",
    "sg:address":"23 Spring St",
    "sg:city":"Scarborough",
    "sg:classifiers":[
        {
            "category":"Banks & Credit Unions",
            "subcategory":"Investment Brokerage",
            "type":"Services"
        },
        {
            "category":"Professional",
            "type":"Services"
        }
    ],
    "sg:phone":"+1 207 885 8827",
    "sg:postcode":"04074",
    "sg:province":"ME",
    "sg:tags":[
        "establishment",
        "financial",
        "advisory"
    ],
    "wof:name":"Tress Wealth Management",
    "wof:placetype":"venue"
},
  "geometry": {"coordinates":[-70.34519400000001,43.619867],"type":"Point"}
}