{
  "type": "Feature",
  "properties": {
    "addr:full":"164 Clewleyville Rd Eddington ME 04428",
    "addr:housenumber":"164",
    "addr:postcode":"04428",
    "addr:street":"Clewleyville Rd",
    "iso:country":"US",
    "sg:address":"164 Clewleyville Rd",
    "sg:city":"Eddington",
    "sg:classifiers":[
        {
            "category":"Home & Garden",
            "subcategory":"Building Materials",
            "type":"Retail Goods"
        }
    ],
    "sg:phone":"+1 207 989 5684",
    "sg:postcode":"04428",
    "sg:province":"ME",
    "sg:tags":[
        "glass",
        "window",
        "plate"
    ],
    "wof:name":"Robertson Glass Co",
    "wof:placetype":"venue"
},
  "geometry": {"coordinates":[-68.687506,44.811306],"type":"Point"}
}