{
  "type": "Feature",
  "properties": {
    "addr:full":"1326 Forest Ave Portland ME 04103",
    "addr:housenumber":"1326",
    "addr:postcode":"04103",
    "addr:street":"Forest Ave",
    "iso:country":"US",
    "sg:address":"1326 Forest Ave",
    "sg:city":"Portland",
    "sg:classifiers":[
        {
            "category":"Organizations",
            "subcategory":"Community Association",
            "type":"Services"
        }
    ],
    "sg:phone":"+1 207 797 2148",
    "sg:postcode":"04103",
    "sg:province":"ME",
    "wof:name":"Marine Corps League",
    "wof:placetype":"venue"
},
  "geometry": {"coordinates":[-70.29702899999999,43.690069],"type":"Point"}
}