{
  "type": "Feature",
  "properties": {
    "addr:full":"9 Water St Rockland ME 04841",
    "addr:housenumber":"9",
    "addr:postcode":"04841",
    "addr:street":"Water St",
    "iso:country":"US",
    "sg:address":"9 Water St",
    "sg:city":"Rockland",
    "sg:classifiers":[
        {
            "category":"Social Services",
            "subcategory":"Child Care",
            "type":"Services"
        }
    ],
    "sg:phone":"+1 207 701 2267",
    "sg:postcode":"04841",
    "sg:province":"ME",
    "sg:tags":[
        "day"
    ],
    "wof:name":"Bright Horizons Childrens Ctrs",
    "wof:placetype":"venue"
},
  "geometry": {"coordinates":[-69.108976,44.09961],"type":"Point"}
}