{
  "type": "Feature",
  "properties": {
    "addr:full":"60 Sanford Dr Gorham ME 04038",
    "addr:housenumber":"60",
    "addr:postcode":"04038",
    "addr:street":"Sanford Dr",
    "iso:country":"US",
    "sg:address":"60 Sanford Dr",
    "sg:city":"Gorham",
    "sg:classifiers":[
        {
            "category":"Wholesale",
            "subcategory":"Machinery & Supplies",
            "type":"Manufacturing & Wholesale Goods"
        }
    ],
    "sg:phone":"+1 207 772 1500",
    "sg:postcode":"04038",
    "sg:province":"ME",
    "sg:tags":[
        "equipment",
        "industrial"
    ],
    "sg:website":"www.northerntoolsupply.com",
    "wof:name":"Northern Tool Supply",
    "wof:placetype":"venue"
},
  "geometry": {"coordinates":[-70.395078,43.679675],"type":"Point"}
}