{
  "type": "Feature",
  "properties": {
    "addr:full":"146 Turner St Auburn ME 04210",
    "addr:housenumber":"146",
    "addr:postcode":"04210",
    "addr:street":"Turner St",
    "iso:country":"US",
    "sg:address":"146 Turner St",
    "sg:city":"Auburn",
    "sg:classifiers":[
        {
            "category":"Retail",
            "subcategory":"Auto Repair",
            "type":"Services"
        }
    ],
    "sg:phone":"+1 207 782 2091",
    "sg:postcode":"04210",
    "sg:province":"ME",
    "sg:tags":[
        "repairing",
        "automobile"
    ],
    "wof:name":"Cook's Automotive Svc",
    "wof:placetype":"venue"
},
  "geometry": {"coordinates":[-70.22723499999999,44.100398],"type":"Point"}
}