{
  "type": "Feature",
  "properties": {
    "iso:country":"US",
    "sg:address":"12 Henley Ln",
    "sg:city":"Greenwood",
    "sg:classifiers":[
        {
            "category":"Retail",
            "subcategory":"Auto Repair",
            "type":"Services"
        }
    ],
    "sg:phone":"+1 207 875 3870",
    "sg:postcode":"04255",
    "sg:province":"ME",
    "sg:tags":[
        "general"
    ],
    "wof:name":"Arts Auto Repair",
    "wof:placetype":"venue"
},
  "geometry": {"coordinates":[-70.704234,44.385539],"type":"Point"}
}