{
  "type": "Feature",
  "properties": {
    "iso:country":"US",
    "sg:address":"97 Riverton Dr",
    "sg:city":"Portland",
    "sg:classifiers":[
        {
            "category":"Building & Trades",
            "subcategory":"Construction",
            "type":"Services"
        }
    ],
    "sg:phone":"+1 207 878 4112",
    "sg:postcode":"04103",
    "sg:province":"ME",
    "sg:tags":[
        "floor",
        "laying",
        "contractor"
    ],
    "wof:name":"C & P Hardwood Floors",
    "wof:placetype":"venue"
},
  "geometry": {"coordinates":[-70.318487,43.697977],"type":"Point"}
}