{
  "type": "Feature",
  "properties": {
    "iso:country":"US",
    "sg:address":"1021 Turner St",
    "sg:city":"Auburn",
    "sg:classifiers":[
        {
            "category":"Real Estate",
            "subcategory":"Real Estate Operator",
            "type":"Services"
        }
    ],
    "sg:phone":"+1 207 782 1542",
    "sg:postcode":"04210",
    "sg:province":"ME",
    "sg:tags":[
        "building",
        "nonresidential"
    ],
    "wof:name":"Masonic Hall Lewistown",
    "wof:placetype":"venue"
},
  "geometry": {"coordinates":[-70.2291,44.127003],"type":"Point"}
}