{
  "type": "Feature",
  "properties": {
    "addr:full":"25 Birchview Dr Augusta ME 04330",
    "addr:housenumber":"25",
    "addr:postcode":"04330",
    "addr:street":"Birchview Dr",
    "iso:country":"US",
    "sg:address":"25 Birchview Dr",
    "sg:city":"Augusta",
    "sg:classifiers":[
        {
            "category":"Building & Trades",
            "subcategory":"Construction",
            "type":"Services"
        }
    ],
    "sg:phone":"+1 207 622 9453",
    "sg:postcode":"04330",
    "sg:province":"ME",
    "sg:tags":[
        "contractor"
    ],
    "wof:name":"Rodrigue Builders Inc",
    "wof:placetype":"venue"
},
  "geometry": {"coordinates":[-69.772784,44.344082],"type":"Point"}
}