{
  "type": "Feature",
  "properties": {
    "iso:country":"US",
    "sg:address":"460 Main St",
    "sg:city":"Madawaska",
    "sg:classifiers":[
        {
            "category":"Personal",
            "type":"Services"
        }
    ],
    "sg:phone":"+1 207 728 6026",
    "sg:postcode":"04756",
    "sg:province":"ME",
    "sg:tags":[
        "consultant",
        "program",
        "health",
        "fitness"
    ],
    "wof:name":"Acadia Fitness Ctr",
    "wof:placetype":"venue"
},
  "geometry": {"coordinates":[-68.323776,47.35547],"type":"Point"}
}