{
  "type": "Feature",
  "properties": {
    "addr:full":"58 Rumford Ave Rumford ME 04276",
    "addr:housenumber":"58",
    "addr:postcode":"04276",
    "addr:street":"Rumford Ave",
    "iso:country":"US",
    "sg:address":"58 Rumford Ave",
    "sg:city":"Rumford",
    "sg:classifiers":[
        {
            "category":"Education",
            "subcategory":"Library",
            "type":"Public Place"
        }
    ],
    "sg:phone":"+1 207 364 3661",
    "sg:postcode":"04276",
    "sg:province":"ME",
    "wof:name":"Rumford Public Library",
    "wof:placetype":"venue"
},
  "geometry": {"coordinates":[-70.549345,44.546656],"type":"Point"}
}