{
  "type": "Feature",
  "properties": {
    "iso:country":"US",
    "sg:address":"62 Main St",
    "sg:city":"Mechanic Falls",
    "sg:classifiers":[
        {
            "category":"Shopping",
            "subcategory":"Used Merchandise",
            "type":"Retail Goods"
        }
    ],
    "sg:phone":"+1 207 345 9100",
    "sg:postcode":"04256",
    "sg:province":"ME",
    "sg:tags":[
        "antique"
    ],
    "wof:name":"Something For Everyone",
    "wof:placetype":"venue"
},
  "geometry": {"coordinates":[-70.392048,44.111366],"type":"Point"}
}