{
  "type": "Feature",
  "properties": {
    "addr:full":"275 Water St Gardiner ME 04345",
    "addr:housenumber":"275",
    "addr:postcode":"04345",
    "addr:street":"Water St",
    "iso:country":"US",
    "sg:address":"275 Water St",
    "sg:city":"Gardiner",
    "sg:classifiers":[
        {
            "category":"Manufacturing",
            "subcategory":"Printing",
            "type":"Manufacturing & Wholesale Goods"
        }
    ],
    "sg:phone":"+1 207 582 5508",
    "sg:postcode":"04345",
    "sg:province":"ME",
    "sg:tags":[
        "printer"
    ],
    "wof:name":"New England Graphics",
    "wof:placetype":"venue"
},
  "geometry": {"coordinates":[-69.773297,44.229613],"type":"Point"}
}