{
  "type": "Feature",
  "properties": {
    "iso:country":"US",
    "sg:address":"88 Hall Hill Rd",
    "sg:city":"Rumford",
    "sg:classifiers":[
        {
            "category":"Retail",
            "subcategory":"Animal Services",
            "type":"Services"
        }
    ],
    "sg:phone":"+1 207 364 7176",
    "sg:postcode":"04276",
    "sg:province":"ME",
    "sg:tags":[
        "pet",
        "boarding",
        "sitting"
    ],
    "wof:name":"Mc Kennel's Animal Adoption",
    "wof:placetype":"venue"
},
  "geometry": {"coordinates":[-70.55122,44.509811],"type":"Point"}
}