{
  "type": "Feature",
  "properties": {
    "iso:country":"US",
    "sg:address":"361 Waldoboro Rd",
    "sg:city":"Friendship",
    "sg:classifiers":[
        {
            "category":"Personal",
            "type":"Services"
        }
    ],
    "sg:phone":"+1 207 832 2233",
    "sg:postcode":"04547",
    "sg:province":"ME",
    "wof:name":"Your Grandmothers Trunk",
    "wof:placetype":"venue"
},
  "geometry": {"coordinates":[-69.334745,43.984124],"type":"Point"}
}