{
  "type": "Feature",
  "properties": {
    "addr:full":"423 Main St Caribou ME 04736",
    "addr:housenumber":"423",
    "addr:postcode":"04736",
    "addr:street":"Main St",
    "iso:country":"US",
    "sg:address":"423 Main St",
    "sg:city":"Caribou",
    "sg:classifiers":[
        {
            "category":"Personal",
            "subcategory":"Beauty Salon",
            "type":"Services"
        }
    ],
    "sg:phone":"+1 207 492 0079",
    "sg:postcode":"04736",
    "sg:province":"ME",
    "wof:name":"A Cut Above Hair Graphics",
    "wof:placetype":"venue"
},
  "geometry": {"coordinates":[-68.010437,46.858656],"type":"Point"}
}