{
  "type": "Feature",
  "properties": {
    "addr:full":"674 Main St Lewiston ME 04240",
    "addr:housenumber":"674",
    "addr:postcode":"04240",
    "addr:street":"Main St",
    "iso:country":"US",
    "sg:address":"674 Main St",
    "sg:city":"Lewiston",
    "sg:classifiers":[
        {
            "category":"Food & Beverages",
            "subcategory":"Groceries & Convenience Stores",
            "type":"Retail Goods"
        }
    ],
    "sg:phone":"+1 207 795 0604",
    "sg:postcode":"04240",
    "sg:province":"ME",
    "wof:name":"Lewiston Irving Mainway",
    "wof:placetype":"venue"
},
  "geometry": {"coordinates":[-70.201988,44.122675],"type":"Point"}
}