{
  "type": "Feature",
  "properties": {
    "iso:country":"US",
    "sg:address":"13 2nd St",
    "sg:city":"Lincoln",
    "sg:classifiers":[
        {
            "category":"Education",
            "subcategory":"School",
            "type":"Public Place"
        }
    ],
    "sg:phone":"+1 207 794 6199",
    "sg:postcode":"04457",
    "sg:province":"ME",
    "wof:name":"Lincoln Montessori",
    "wof:placetype":"venue"
},
  "geometry": {"coordinates":[-68.50932,45.361623],"type":"Point"}
}