{
  "type": "Feature",
  "properties": {
    "addr:full":"1236 Carrabassett Dr Carrabassett Vly ME 04947",
    "addr:housenumber":"1236",
    "addr:postcode":"04947",
    "addr:street":"Carrabassett Dr",
    "iso:country":"US",
    "sg:address":"1236 Carrabassett Dr",
    "sg:city":"Carrabassett Vly",
    "sg:classifiers":[
        {
            "category":"Real Estate",
            "subcategory":"Real Estate Agent",
            "type":"Services"
        }
    ],
    "sg:phone":"+1 207 235 2090",
    "sg:postcode":"04947",
    "sg:province":"ME",
    "wof:name":"Sugarloaf Area Real Estate",
    "wof:placetype":"venue"
},
  "geometry": {"coordinates":[-70.27185799999999,45.089864],"type":"Point"}
}