{
  "type": "Feature",
  "properties": {
    "iso:country":"US",
    "sg:address":"45 Whitten Hills Rd",
    "sg:city":"Kennebunkport",
    "sg:classifiers":[
        {
            "category":"Organizations",
            "subcategory":"Religious Organization",
            "type":"Services"
        }
    ],
    "sg:phone":"+1 207 967 2271",
    "sg:postcode":"04046",
    "sg:province":"ME",
    "wof:name":"International Students",
    "wof:placetype":"venue"
},
  "geometry": {"coordinates":[-70.447766,43.419134],"type":"Point"}
}