{
  "type": "Feature",
  "properties": {
    "iso:country":"US",
    "sg:address":"36 Main St",
    "sg:city":"Clinton",
    "sg:classifiers":[
        {
            "category":"Cinema",
            "subcategory":"Movie Rental",
            "type":"Entertainment"
        }
    ],
    "sg:phone":"+1 207 426 8880",
    "sg:postcode":"04927",
    "sg:province":"ME",
    "sg:tags":[
        "leasing",
        "video",
        "disc",
        "tape"
    ],
    "wof:name":"Video Escape",
    "wof:placetype":"venue"
},
  "geometry": {"coordinates":[-69.501726,44.637114],"type":"Point"}
}