{
  "type": "Feature",
  "properties": {
    "iso:country":"US",
    "sg:address":"241 Main St",
    "sg:city":"Norway",
    "sg:classifiers":[
        {
            "category":"Wholesale",
            "subcategory":"Scrap",
            "type":"Manufacturing & Wholesale Goods"
        }
    ],
    "sg:phone":"+1 207 743 8311",
    "sg:postcode":"04268",
    "sg:province":"ME",
    "sg:tags":[
        "recycling",
        "center"
    ],
    "wof:name":"John's Redemption Ctr",
    "wof:placetype":"venue"
},
  "geometry": {"coordinates":[-70.543615,44.213886],"type":"Point"}
}