{
  "type": "Feature",
  "properties": {
    "addr:full":"30 Fair St Norway ME 04268",
    "addr:housenumber":"30",
    "addr:postcode":"04268",
    "addr:street":"Fair St",
    "iso:country":"US",
    "sg:address":"30 Fair St",
    "sg:city":"Norway",
    "sg:classifiers":[
        {
            "category":"Restaurant",
            "type":"Food & Drink"
        }
    ],
    "sg:phone":"+1 207 743 6194",
    "sg:postcode":"04268",
    "sg:province":"ME",
    "sg:tags":[
        "pizza"
    ],
    "sg:website":"www.amatos.com",
    "wof:name":"Amato's Italian Sandwich",
    "wof:placetype":"venue"
},
  "geometry": {"coordinates":[-70.530539,44.209236],"type":"Point"}
}