{
  "type": "Feature",
  "properties": {
    "iso:country":"US",
    "sg:address":"132 Pleasant St",
    "sg:city":"Portland",
    "sg:classifiers":[
        {
            "category":"Health Services",
            "subcategory":"Health Practitioner",
            "type":"Services"
        }
    ],
    "sg:phone":"+1 207 774 2211",
    "sg:postcode":"04101",
    "sg:province":"ME",
    "sg:tags":[
        "psychologist"
    ],
    "wof:name":"R De Viller Seymour",
    "wof:placetype":"venue"
},
  "geometry": {"coordinates":[-70.26177800000001,43.652343],"type":"Point"}
}