{
  "type": "Feature",
  "properties": {
    "addr:full":"460 Commercial St Portland ME 04101",
    "addr:housenumber":"460",
    "addr:postcode":"04101",
    "addr:street":"Commercial St",
    "iso:country":"US",
    "sg:address":"460 Commercial St",
    "sg:city":"Portland",
    "sg:classifiers":[
        {
            "category":"Professional",
            "subcategory":"Business Services",
            "type":"Services"
        }
    ],
    "sg:phone":"+1 207 772 0113",
    "sg:postcode":"04101",
    "sg:province":"ME",
    "wof:name":"P & O Ports New England Inc",
    "wof:placetype":"venue"
},
  "geometry": {"coordinates":[-70.258245,43.649595],"type":"Point"}
}