{
  "type": "Feature",
  "properties": {
    "iso:country":"US",
    "sg:address":"26 Main St",
    "sg:city":"Newport",
    "sg:classifiers":[
        {
            "category":"Shopping",
            "subcategory":"Gifts & Souvenirs",
            "type":"Retail Goods"
        }
    ],
    "sg:phone":"+1 207 368 9051",
    "sg:postcode":"04953",
    "sg:province":"ME",
    "sg:tags":[
        "christmas",
        "stocking"
    ],
    "wof:name":"Dollar Queen",
    "wof:placetype":"venue"
},
  "geometry": {"coordinates":[-69.274415,44.835144],"type":"Point"}
}