{
  "type": "Feature",
  "properties": {
    "addr:full":"1630 Forest Ave Portland ME 04103",
    "addr:housenumber":"1630",
    "addr:postcode":"04103",
    "addr:street":"Forest Ave",
    "iso:country":"US",
    "sg:address":"1630 Forest Ave",
    "sg:city":"Portland",
    "sg:classifiers":[
        {
            "category":"Building & Trades",
            "subcategory":"Plumbing",
            "type":"Services"
        }
    ],
    "sg:phone":"+1 207 878 2212",
    "sg:postcode":"04103",
    "sg:province":"ME",
    "sg:tags":[
        "plumbing",
        "contractor"
    ],
    "wof:name":"Lewis W C Jr Plumbing & Htg",
    "wof:placetype":"venue"
},
  "geometry": {"coordinates":[-70.307917,43.697304],"type":"Point"}
}