{
  "type": "Feature",
  "properties": {
    "addr:full":"6 E River Rd Whitefield ME 04353",
    "addr:housenumber":"6",
    "addr:postcode":"04353",
    "addr:street":"E River Rd",
    "iso:country":"US",
    "sg:address":"6 E River Rd",
    "sg:city":"Whitefield",
    "sg:phone":"+1 207 633 6272",
    "sg:postcode":"04353",
    "sg:province":"ME",
    "sg:tags":[
        "fuel",
        "diesel"
    ],
    "wof:name":"Midnight Oil",
    "wof:placetype":"venue"
},
  "geometry": {"coordinates":[-69.587153,44.220405],"type":"Point"}
}