{
  "type": "Feature",
  "properties": {
    "addr:full":"938 Forest Ave Portland ME 04103",
    "addr:housenumber":"938",
    "addr:postcode":"04103",
    "addr:street":"Forest Ave",
    "iso:country":"US",
    "sg:address":"938 Forest Ave",
    "sg:city":"Portland",
    "sg:classifiers":[
        {
            "category":"Banks & Credit Unions",
            "subcategory":"Investment Brokerage",
            "type":"Services"
        }
    ],
    "sg:phone":"+1 207 797 2090",
    "sg:postcode":"04103",
    "sg:province":"ME",
    "sg:tags":[
        "consultant",
        "planning",
        "financial"
    ],
    "wof:name":"W R Rice Financial Svc Inc",
    "wof:placetype":"venue"
},
  "geometry": {"coordinates":[-70.288785,43.679019],"type":"Point"}
}