{
  "type": "Feature",
  "properties": {
    "iso:country":"US",
    "sg:address":"6 Airport Rd",
    "sg:city":"N New Portland",
    "sg:classifiers":[
        {
            "category":"Professional",
            "subcategory":"Computer Services",
            "type":"Services"
        }
    ],
    "sg:phone":"+1 207 628 2842",
    "sg:postcode":"04957",
    "sg:province":"ME",
    "sg:tags":[
        "consultant",
        "designer"
    ],
    "wof:name":"CDI Inc",
    "wof:placetype":"venue"
},
  "geometry": {"coordinates":[-69.813,44.70875],"type":"Point"}
}