{
  "type": "Feature",
  "properties": {
    "addr:full":"39 Lincoln St Lewiston ME 04240",
    "addr:housenumber":"39",
    "addr:postcode":"04240",
    "addr:street":"Lincoln St",
    "iso:country":"US",
    "sg:address":"39 Lincoln St",
    "sg:city":"Lewiston",
    "sg:classifiers":[
        {
            "category":"Organizations",
            "subcategory":"Religious Organization",
            "type":"Services"
        }
    ],
    "sg:phone":"+1 207 784 0401",
    "sg:postcode":"04240",
    "sg:province":"ME",
    "sg:tags":[
        "baptist",
        "church"
    ],
    "wof:name":"Lighthouse Baptist Church",
    "wof:placetype":"venue"
},
  "geometry": {"coordinates":[-70.220947,44.096465],"type":"Point"}
}