{
  "type": "Feature",
  "properties": {
    "addr:full":"131 Maine Ave Farmingdale ME 04344",
    "addr:housenumber":"131",
    "addr:postcode":"04344",
    "addr:street":"Maine Ave",
    "iso:country":"US",
    "sg:address":"131 Maine Ave",
    "sg:city":"Farmingdale",
    "sg:classifiers":[
        {
            "category":"Autos & Motor Vehicles",
            "subcategory":"Boat Sales",
            "type":"Retail Goods"
        }
    ],
    "sg:phone":"+1 207 582 0075",
    "sg:postcode":"04344",
    "sg:province":"ME",
    "wof:name":"Foggy Bottom Rv Campground",
    "wof:placetype":"venue"
},
  "geometry": {"coordinates":[-69.77168899999999,44.237189],"type":"Point"}
}