{
  "type": "Feature",
  "properties": {
    "addr:full":"30 Lord Rd Wiscasset ME 04578",
    "addr:housenumber":"30",
    "addr:postcode":"04578",
    "addr:street":"Lord Rd",
    "iso:country":"US",
    "sg:address":"30 Lord Rd",
    "sg:city":"Wiscasset",
    "sg:classifiers":[
        {
            "category":"Professional",
            "subcategory":"Management & Consulting",
            "type":"Services"
        }
    ],
    "sg:phone":"+1 207 882 8110",
    "sg:postcode":"04578",
    "sg:province":"ME",
    "wof:name":"Consultant To Management Inc",
    "wof:placetype":"venue"
},
  "geometry": {"coordinates":[-69.670192,43.974547],"type":"Point"}
}