{
  "type": "Feature",
  "properties": {
    "addr:full":"119 Main St Bridgton ME 04009",
    "addr:housenumber":"119",
    "addr:postcode":"04009",
    "addr:street":"Main St",
    "iso:country":"US",
    "sg:address":"119 Main St",
    "sg:city":"Bridgton",
    "sg:classifiers":[
        {
            "category":"Food & Beverages",
            "subcategory":"Groceries & Convenience Stores",
            "type":"Retail Goods"
        }
    ],
    "sg:phone":"+1 207 647 2766",
    "sg:postcode":"04009",
    "sg:province":"ME",
    "sg:tags":[
        "grocer"
    ],
    "wof:name":"Food City",
    "wof:placetype":"venue"
},
  "geometry": {"coordinates":[-70.69904099999999,44.054472],"type":"Point"}
}