{
  "type": "Feature",
  "properties": {
    "iso:country":"US",
    "sg:address":"566 Moose Hill Rd",
    "sg:city":"Livermore Falls",
    "sg:classifiers":[
        {
            "category":"Building & Trades",
            "subcategory":"Construction",
            "type":"Services"
        }
    ],
    "sg:phone":"+1 207 897 4379",
    "sg:postcode":"04254",
    "sg:province":"ME",
    "sg:tags":[
        "house"
    ],
    "wof:name":"Moosehill Builders",
    "wof:placetype":"venue"
},
  "geometry": {"coordinates":[-70.13690699999999,44.472663],"type":"Point"}
}