{
  "type": "Feature",
  "properties": {
    "addr:full":"649 Broadway Bangor ME 04401",
    "addr:housenumber":"649",
    "addr:postcode":"04401",
    "addr:street":"Broadway",
    "iso:country":"US",
    "sg:address":"649 Broadway",
    "sg:city":"Bangor",
    "sg:classifiers":[
        {
            "category":"Real Estate",
            "subcategory":"Real Estate Operator",
            "type":"Services"
        }
    ],
    "sg:phone":"+1 207 947 8713",
    "sg:postcode":"04401",
    "sg:province":"ME",
    "sg:tags":[
        "mall",
        "shopping",
        "center"
    ],
    "wof:name":"Broadway Shopping Ctr",
    "wof:placetype":"venue"
},
  "geometry": {"coordinates":[-68.778621,44.822607],"type":"Point"}
}