{
  "type": "Feature",
  "properties": {
    "iso:country":"US",
    "sg:address":"215 N River Rd",
    "sg:city":"Auburn",
    "sg:classifiers":[
        {
            "category":"Wholesale",
            "subcategory":"Fruits & Vegetables",
            "type":"Manufacturing & Wholesale Goods"
        }
    ],
    "sg:phone":"+1 207 782 0922",
    "sg:postcode":"04210",
    "sg:province":"ME",
    "sg:tags":[
        "tomato"
    ],
    "wof:name":"Crusader Tomato Co",
    "wof:placetype":"venue"
},
  "geometry": {"coordinates":[-70.220004,44.110215],"type":"Point"}
}