{
  "type": "Feature",
  "properties": {
    "addr:full":"28 Fairfield St Oakland ME 04963",
    "addr:housenumber":"28",
    "addr:postcode":"04963",
    "addr:street":"Fairfield St",
    "iso:country":"US",
    "sg:address":"28 Fairfield St",
    "sg:city":"Oakland",
    "sg:classifiers":[
        {
            "category":"Building & Trades",
            "subcategory":"Construction",
            "type":"Services"
        }
    ],
    "sg:phone":"+1 207 465 2408",
    "sg:postcode":"04963",
    "sg:province":"ME",
    "sg:tags":[
        "marking",
        "maintenance",
        "parking"
    ],
    "wof:name":"Public Works",
    "wof:placetype":"venue"
},
  "geometry": {"coordinates":[-69.712217,44.548462],"type":"Point"}
}