{
  "type": "Feature",
  "properties": {
    "iso:country":"US",
    "sg:address":"28 Mill St",
    "sg:city":"Orono",
    "sg:classifiers":[
        {
            "category":"Restaurant",
            "type":"Food & Drink"
        }
    ],
    "sg:phone":"+1 207 866 4200",
    "sg:postcode":"04473",
    "sg:province":"ME",
    "wof:name":"Thai Orchid",
    "wof:placetype":"venue"
},
  "geometry": {"coordinates":[-68.67183,44.883574],"type":"Point"}
}