{
  "type": "Feature",
  "properties": {
    "addr:full":"449 Lewiston Rd New Gloucester ME 04260",
    "addr:housenumber":"449",
    "addr:postcode":"04260",
    "addr:street":"Lewiston Rd",
    "iso:country":"US",
    "sg:address":"449 Lewiston Rd",
    "sg:city":"New Gloucester",
    "sg:classifiers":[
        {
            "category":"Social Services",
            "subcategory":"Child Care",
            "type":"Services"
        }
    ],
    "sg:phone":"+1 207 926 4432",
    "sg:postcode":"04260",
    "sg:province":"ME",
    "sg:tags":[
        "day"
    ],
    "wof:name":"Rioux Raymounde Day Care",
    "wof:placetype":"venue"
},
  "geometry": {"coordinates":[-70.300175,43.966255],"type":"Point"}
}