{
  "type": "Feature",
  "properties": {
    "addr:full":"16 Old County Rd Winterport ME 04496",
    "addr:housenumber":"16",
    "addr:postcode":"04496",
    "addr:street":"Old County Rd",
    "iso:country":"US",
    "sg:address":"16 Old County Rd",
    "sg:city":"Winterport",
    "sg:classifiers":[
        {
            "category":"Wholesale",
            "subcategory":"Durable Goods & Equipment",
            "type":"Manufacturing & Wholesale Goods"
        }
    ],
    "sg:phone":"+1 207 223 5788",
    "sg:postcode":"04496",
    "sg:province":"ME",
    "wof:name":"Country Bargains",
    "wof:placetype":"venue"
},
  "geometry": {"coordinates":[-68.846351,44.688229],"type":"Point"}
}