{
  "type": "Feature",
  "properties": {
    "addr:full":"1355 Congress St Portland ME 04102",
    "addr:housenumber":"1355",
    "addr:postcode":"04102",
    "addr:street":"Congress St",
    "iso:country":"US",
    "sg:address":"1355 Congress St",
    "sg:city":"Portland",
    "sg:classifiers":[
        {
            "category":"Government",
            "subcategory":"Police Station",
            "type":"Public Place"
        }
    ],
    "sg:phone":"+1 207 780 3331",
    "sg:postcode":"04102",
    "sg:province":"ME",
    "sg:tags":[
        "federal"
    ],
    "wof:name":"US Drug Enforcement Adm",
    "wof:placetype":"venue"
},
  "geometry": {"coordinates":[-70.29561699999999,43.658918],"type":"Point"}
}