{
  "type": "Feature",
  "properties": {
    "addr:full":"52 Washington Ave Portland ME 04101",
    "addr:housenumber":"52",
    "addr:postcode":"04101",
    "addr:street":"Washington Ave",
    "iso:country":"US",
    "sg:address":"52 Washington Ave",
    "sg:city":"Portland",
    "sg:classifiers":[
        {
            "category":"Food & Beverages",
            "subcategory":"Fruits & Vegetables",
            "type":"Retail Goods"
        }
    ],
    "sg:phone":"+1 207 347 4517",
    "sg:postcode":"04101",
    "sg:province":"ME",
    "sg:tags":[
        "juice"
    ],
    "wof:name":"Wicked Pulp",
    "wof:placetype":"venue"
},
  "geometry": {"coordinates":[-70.251777,43.664231],"type":"Point"}
}