{
  "type": "Feature",
  "properties": {
    "addr:full":"428 Shaker Rd Gray ME 04039",
    "addr:housenumber":"428",
    "addr:postcode":"04039",
    "addr:street":"Shaker Rd",
    "iso:country":"US",
    "sg:address":"428 Shaker Rd",
    "sg:city":"Gray",
    "sg:classifiers":[
        {
            "category":"Building & Trades",
            "subcategory":"Landscaping Services",
            "type":"Services"
        }
    ],
    "sg:phone":"+1 207 657 2525",
    "sg:postcode":"04039",
    "sg:province":"ME",
    "sg:tags":[
        "landscape",
        "contractor"
    ],
    "wof:name":"Hadlock's Hardscaping Inc",
    "wof:placetype":"venue"
},
  "geometry": {"coordinates":[-70.35136,43.936703],"type":"Point"}
}