{
  "type": "Feature",
  "properties": {
    "addr:full":"785 High St Bath ME 04530",
    "addr:housenumber":"785",
    "addr:postcode":"04530",
    "addr:street":"High St",
    "iso:country":"US",
    "sg:address":"785 High St",
    "sg:city":"Bath",
    "sg:classifiers":[
        {
            "category":"Social Services",
            "subcategory":"Child Care",
            "type":"Services"
        }
    ],
    "sg:phone":"+1 207 442 9447",
    "sg:postcode":"04530",
    "sg:province":"ME",
    "sg:tags":[
        "kindergarten",
        "academic",
        "school"
    ],
    "wof:name":"Midcoast Montessori School",
    "wof:placetype":"venue"
},
  "geometry": {"coordinates":[-69.819833,43.911762],"type":"Point"}
}