{
  "type": "Feature",
  "properties": {
    "iso:country":"US",
    "sg:address":"225 Buxton Rd",
    "sg:city":"Saco",
    "sg:classifiers":[
        {
            "category":"Professional",
            "type":"Services"
        }
    ],
    "sg:phone":"+1 207 283 1809",
    "sg:postcode":"04072",
    "sg:province":"ME",
    "wof:name":"Earthwork Services Inc",
    "wof:placetype":"venue"
},
  "geometry": {"coordinates":[-70.496189,43.554998],"type":"Point"}
}