{
  "type": "Feature",
  "properties": {
    "addr:full":"56 Sewall St Augusta ME 04330",
    "addr:housenumber":"56",
    "addr:postcode":"04330",
    "addr:street":"Sewall St",
    "iso:country":"US",
    "sg:address":"56 Sewall St",
    "sg:city":"Augusta",
    "sg:classifiers":[
        {
            "category":"Education",
            "subcategory":"School",
            "type":"Public Place"
        }
    ],
    "sg:phone":"+1 207 623 3491",
    "sg:postcode":"04330",
    "sg:province":"ME",
    "sg:website":"www.stmarysmaine.org",
    "wof:name":"St Mary's School",
    "wof:placetype":"venue"
},
  "geometry": {"coordinates":[-69.782833,44.311741],"type":"Point"}
}