{
  "type": "Feature",
  "properties": {
    "iso:country":"US",
    "sg:address":"52 Martin Hts",
    "sg:city":"Raymond",
    "sg:classifiers":[
        {
            "category":"Professional",
            "subcategory":"Computer Services",
            "type":"Services"
        }
    ],
    "sg:phone":"+1 207 761 9321",
    "sg:postcode":"04071",
    "sg:province":"ME",
    "sg:tags":[
        "website",
        "design"
    ],
    "wof:name":"Creative Interactive Solutions",
    "wof:placetype":"venue"
},
  "geometry": {"coordinates":[-70.46019200000001,43.938771],"type":"Point"}
}