{
  "type": "Feature",
  "properties": {
    "iso:country":"US",
    "sg:address":"2 Industry Rd",
    "sg:city":"Brunswick",
    "sg:classifiers":[
        {
            "category":"Manufacturing",
            "subcategory":"Tools & Machinery",
            "type":"Manufacturing & Wholesale Goods"
        }
    ],
    "sg:phone":"+1 207 729 0191",
    "sg:postcode":"04011",
    "sg:province":"ME",
    "sg:tags":[
        "machine",
        "shop"
    ],
    "wof:name":"Aeromarine Corp",
    "wof:placetype":"venue"
},
  "geometry": {"coordinates":[-69.960317,43.921064],"type":"Point"}
}