{
  "type": "Feature",
  "properties": {
    "iso:country":"US",
    "sg:address":"8 Smith St",
    "sg:city":"Van Buren",
    "sg:classifiers":[
        {
            "category":"Retail",
            "subcategory":"Repair Shop",
            "type":"Services"
        }
    ],
    "sg:phone":"+1 207 868 2221",
    "sg:postcode":"04785",
    "sg:province":"ME",
    "wof:name":"Alphy Upholstery",
    "wof:placetype":"venue"
},
  "geometry": {"coordinates":[-67.927887,47.149007],"type":"Point"}
}