{
  "type": "Feature",
  "properties": {
    "iso:country":"US",
    "sg:address":"23 Railroad St",
    "sg:city":"Newport",
    "sg:classifiers":[
        {
            "category":"Building & Trades",
            "subcategory":"Construction",
            "type":"Services"
        }
    ],
    "sg:phone":"+1 207 426 2500",
    "sg:postcode":"04953",
    "sg:province":"ME",
    "sg:tags":[
        "insulation",
        "heat",
        "contractor"
    ],
    "wof:name":"Advanced Spray Foam Insulation",
    "wof:placetype":"venue"
},
  "geometry": {"coordinates":[-69.275307,44.834341],"type":"Point"}
}