{
  "type": "Feature",
  "properties": {
    "addr:full":"40 Blanchette Ln Fort Kent ME 04743",
    "addr:housenumber":"40",
    "addr:postcode":"04743",
    "addr:street":"Blanchette Ln",
    "iso:country":"US",
    "sg:address":"40 Blanchette Ln",
    "sg:city":"Fort Kent",
    "sg:classifiers":[
        {
            "category":"Freight",
            "type":"Transportation"
        }
    ],
    "sg:phone":"+1 207 834 2129",
    "sg:postcode":"04743",
    "sg:province":"ME",
    "sg:tags":[
        "operator",
        "local",
        "trucking"
    ],
    "wof:name":"Blanchette Trucking",
    "wof:placetype":"venue"
},
  "geometry": {"coordinates":[-68.553078,47.193915],"type":"Point"}
}