{
  "type": "Feature",
  "properties": {
    "iso:country":"US",
    "sg:address":"8 Norton St",
    "sg:city":"South Berwick",
    "sg:classifiers":[
        {
            "category":"Banks & Credit Unions",
            "subcategory":"Bank",
            "type":"Services"
        }
    ],
    "sg:phone":"+1 207 384 5005",
    "sg:postcode":"03908",
    "sg:province":"ME",
    "wof:name":"Ocean National Bank",
    "wof:placetype":"venue"
},
  "geometry": {"coordinates":[-70.808982,43.236395],"type":"Point"}
}