{
  "type": "Feature",
  "properties": {
    "iso:country":"US",
    "sg:address":"206 Water St",
    "sg:city":"Skowhegan",
    "sg:classifiers":[
        {
            "category":"Professional",
            "subcategory":"Lawyer & Legal Services",
            "type":"Services"
        }
    ],
    "sg:phone":"+1 207 474 2383",
    "sg:postcode":"04976",
    "sg:province":"ME",
    "sg:tags":[
        "attorney"
    ],
    "wof:name":"Bloom & Bloom",
    "wof:placetype":"venue"
},
  "geometry": {"coordinates":[-69.71666500000001,44.766209],"type":"Point"}
}