{
  "type": "Feature",
  "properties": {
    "addr:full":"27 Oakwood Dr Brunswick ME 04093",
    "addr:housenumber":"27",
    "addr:postcode":"04093",
    "addr:street":"Oakwood Dr",
    "iso:country":"US",
    "sg:address":"27 Oakwood Dr",
    "sg:city":"Brunswick",
    "sg:classifiers":[
        {
            "category":"Building & Trades",
            "subcategory":"Construction",
            "type":"Services"
        }
    ],
    "sg:phone":"+1 207 725 0702",
    "sg:postcode":"04093",
    "sg:province":"ME",
    "sg:tags":[
        "hanging",
        "contractor"
    ],
    "wof:name":"Dans Painting",
    "wof:placetype":"venue"
},
  "geometry": {"coordinates":[-70.64973500000001,43.653436],"type":"Point"}
}