{
  "type": "Feature",
  "properties": {
    "iso:country":"US",
    "sg:address":"27 Oakwood Dr",
    "sg:city":"Brunswick",
    "sg:classifiers":[
        {
            "category":"Building & Trades",
            "subcategory":"Construction",
            "type":"Services"
        }
    ],
    "sg:phone":"+1 207 725 0702",
    "sg:postcode":"04093",
    "sg:province":"ME",
    "sg:tags":[
        "hanging",
        "contractor"
    ],
    "wof:name":"Dans Painting",
    "wof:placetype":"venue"
},
  "geometry": {"coordinates":[-70.649735,43.653436],"type":"Point"}
}