{
  "type": "Feature",
  "properties": {
    "addr:full":"101 Jennifer Dr Auburn ME 04210",
    "addr:housenumber":"101",
    "addr:postcode":"04210",
    "addr:street":"Jennifer Dr",
    "iso:country":"US",
    "sg:address":"101 Jennifer Dr",
    "sg:city":"Auburn",
    "sg:classifiers":[
        {
            "category":"Wholesale",
            "subcategory":"Stationery",
            "type":"Manufacturing & Wholesale Goods"
        }
    ],
    "sg:phone":"+1 207 783 0400",
    "sg:postcode":"04210",
    "sg:province":"ME",
    "sg:tags":[
        "business",
        "form",
        "system"
    ],
    "wof:name":"Holtan Business Forms",
    "wof:placetype":"venue"
},
  "geometry": {"coordinates":[-70.262845,44.046123],"type":"Point"}
}