{
  "type": "Feature",
  "properties": {
    "addr:full":"517 S Main St Brewer ME 04412",
    "addr:housenumber":"517",
    "addr:postcode":"04412",
    "addr:street":"S Main St",
    "iso:country":"US",
    "sg:address":"517 S Main St",
    "sg:city":"Brewer",
    "sg:classifiers":[
        {
            "category":"Manufacturing",
            "subcategory":"Paper Products",
            "type":"Manufacturing & Wholesale Goods"
        }
    ],
    "sg:phone":"+1 207 989 7070",
    "sg:postcode":"04412",
    "sg:province":"ME",
    "wof:name":"Eastern Fine Paper Inc",
    "wof:placetype":"venue"
},
  "geometry": {"coordinates":[-68.78014,44.77278],"type":"Point"}
}