{
  "type": "Feature",
  "properties": {
    "iso:country":"US",
    "sg:address":"472 Ocean St",
    "sg:city":"South Portland",
    "sg:classifiers":[
        {
            "category":"Shopping",
            "subcategory":"Hobbies, Toys, & Games",
            "type":"Retail Goods"
        }
    ],
    "sg:phone":"+1 207 799 6009",
    "sg:postcode":"04106",
    "sg:province":"ME",
    "sg:tags":[
        "doll"
    ],
    "wof:name":"Dollfanatics",
    "wof:placetype":"venue"
},
  "geometry": {"coordinates":[-70.250475,43.626573],"type":"Point"}
}