{
  "type": "Feature",
  "properties": {
    "iso:country":"US",
    "sg:address":"595 Brighton Ave",
    "sg:city":"Portland",
    "sg:classifiers":[
        {
            "category":"Health Services",
            "subcategory":"Doctor",
            "type":"Services"
        }
    ],
    "sg:phone":"+1 207 774 1471",
    "sg:postcode":"04102",
    "sg:province":"ME",
    "sg:tags":[
        "dentist"
    ],
    "wof:name":"Donald L Theriault DDS",
    "wof:placetype":"venue"
},
  "geometry": {"coordinates":[-70.30226399999999,43.668999],"type":"Point"}
}