{
  "type": "Feature",
  "properties": {
    "iso:country":"US",
    "sg:address":"122 Mill St",
    "sg:city":"Lagrange",
    "sg:classifiers":[
        {
            "category":"Shopping",
            "subcategory":"Gifts & Souvenirs",
            "type":"Retail Goods"
        }
    ],
    "sg:phone":"+1 207 943 2975",
    "sg:postcode":"04473",
    "sg:province":"ME",
    "wof:name":"Rabbits Cats & More",
    "wof:placetype":"venue"
},
  "geometry": {"coordinates":[-68.66655,44.882807],"type":"Point"}
}