{
  "type": "Feature",
  "properties": {
    "addr:full":"25 Middle St Portland ME 04101",
    "addr:housenumber":"25",
    "addr:postcode":"04101",
    "addr:street":"Middle St",
    "iso:country":"US",
    "sg:address":"25 Middle St",
    "sg:city":"Portland",
    "sg:classifiers":[
        {
            "category":"Social Services",
            "type":"Services"
        }
    ],
    "sg:phone":"+1 207 775 2732",
    "sg:postcode":"04101",
    "sg:province":"ME",
    "sg:tags":[
        "counselor",
        "marriage",
        "family"
    ],
    "wof:name":"Elizabeth Goodie",
    "wof:placetype":"venue"
},
  "geometry": {"coordinates":[-70.249323,43.660867],"type":"Point"}
}