{
  "type": "Feature",
  "properties": {
    "iso:country":"US",
    "sg:address":"63 School St",
    "sg:city":"Stockholm",
    "sg:classifiers":[
        {
            "category":"Education",
            "subcategory":"School",
            "type":"Public Place"
        }
    ],
    "sg:phone":"+1 207 896 3092",
    "sg:postcode":"04783",
    "sg:province":"ME",
    "wof:name":"Stockholm Elementary School",
    "wof:placetype":"venue"
},
  "geometry": {"coordinates":[-68.134927,47.041125],"type":"Point"}
}