{
  "type": "Feature",
  "properties": {
    "iso:country":"US",
    "sg:address":"150 Husson Ave",
    "sg:city":"Bangor",
    "sg:classifiers":[
        {
            "category":"Building & Trades",
            "subcategory":"Construction",
            "type":"Services"
        }
    ],
    "sg:phone":"+1 207 942 2169",
    "sg:postcode":"04401",
    "sg:province":"ME",
    "sg:tags":[
        "general",
        "contractor"
    ],
    "wof:name":"S E Mac Millan Co",
    "wof:placetype":"venue"
},
  "geometry": {"coordinates":[-68.789371,44.823855],"type":"Point"}
}