{
  "type": "Feature",
  "properties": {
    "addr:full":"182 Metcalf Rd Winthrop ME 04364",
    "addr:housenumber":"182",
    "addr:postcode":"04364",
    "addr:street":"Metcalf Rd",
    "iso:country":"US",
    "sg:address":"182 Metcalf Rd",
    "sg:city":"Winthrop",
    "sg:classifiers":[
        {
            "category":"Professional",
            "subcategory":"Art Services",
            "type":"Services"
        }
    ],
    "sg:phone":"+1 207 395 4300",
    "sg:postcode":"04364",
    "sg:province":"ME",
    "sg:tags":[
        "graphic",
        "designer"
    ],
    "wof:name":"Cal-Art Productions",
    "wof:placetype":"venue"
},
  "geometry": {"coordinates":[-69.957285,44.310907],"type":"Point"}
}