{
  "type": "Feature",
  "properties": {
    "addr:full":"63 Bridgton Rd Westbrook ME 04092",
    "addr:housenumber":"63",
    "addr:postcode":"04092",
    "addr:street":"Bridgton Rd",
    "iso:country":"US",
    "sg:address":"63 Bridgton Rd",
    "sg:city":"Westbrook",
    "sg:classifiers":[
        {
            "category":"Shopping",
            "subcategory":"Used Merchandise",
            "type":"Retail Goods"
        }
    ],
    "sg:phone":"+1 207 878 1776",
    "sg:postcode":"04092",
    "sg:province":"ME",
    "sg:tags":[
        "security"
    ],
    "wof:name":"Diabetes Endocrine & Ntrtn Ctr",
    "wof:placetype":"venue"
},
  "geometry": {"coordinates":[-70.326538,43.705561],"type":"Point"}
}