{
  "type": "Feature",
  "properties": {
    "addr:full":"45 Center Dr Orrington ME 04474",
    "addr:housenumber":"45",
    "addr:postcode":"04474",
    "addr:street":"Center Dr",
    "iso:country":"US",
    "sg:address":"45 Center Dr",
    "sg:city":"Orrington",
    "sg:classifiers":[
        {
            "category":"Retail",
            "subcategory":"Repair Shop",
            "type":"Services"
        }
    ],
    "sg:phone":"+1 207 825 8898",
    "sg:postcode":"04474",
    "sg:province":"ME",
    "sg:tags":[
        "clocks",
        "parts"
    ],
    "wof:name":"Family Time Clock Shoppe",
    "wof:placetype":"venue"
},
  "geometry": {"coordinates":[-68.82504,44.730433],"type":"Point"}
}