{
  "type": "Feature",
  "properties": {
    "addr:full":"1 Industrial Way Portland ME 04103",
    "addr:housenumber":"1",
    "addr:postcode":"04103",
    "addr:street":"Industrial Way",
    "iso:country":"US",
    "sg:address":"1 Industrial Way",
    "sg:city":"Portland",
    "sg:classifiers":[
        {
            "category":"Retail",
            "subcategory":"Laundry & Dry Cleaning",
            "type":"Services"
        }
    ],
    "sg:phone":"+1 207 878 0559",
    "sg:postcode":"04103",
    "sg:province":"ME",
    "sg:tags":[
        "cleaners",
        "rug",
        "carpet"
    ],
    "wof:name":"Stanley Steemer Carpet Cleaner",
    "wof:placetype":"venue"
},
  "geometry": {"coordinates":[-70.31354399999999,43.70719],"type":"Point"}
}