{
  "type": "Feature",
  "properties": {
    "iso:country":"US",
    "sg:address":"64 Heath Ln",
    "sg:city":"Bath",
    "sg:classifiers":[
        {
            "category":"Building & Trades",
            "subcategory":"Construction",
            "type":"Services"
        }
    ],
    "sg:phone":"+1 207 443 9015",
    "sg:postcode":"04530",
    "sg:province":"ME",
    "sg:tags":[
        "painter"
    ],
    "wof:name":"Mark & Kevin's Painting",
    "wof:placetype":"venue"
},
  "geometry": {"coordinates":[-69.824014,43.929462],"type":"Point"}
}