{
  "type": "Feature",
  "properties": {
    "iso:country":"US",
    "sg:address":"9 Pleasant St",
    "sg:city":"Brunswick",
    "sg:classifiers":[
        {
            "category":"Health Services",
            "subcategory":"Chiropractor",
            "type":"Services"
        }
    ],
    "sg:phone":"+1 207 725 7177",
    "sg:postcode":"04011",
    "sg:province":"ME",
    "wof:name":"Augat Chiropractic Ctr",
    "wof:placetype":"venue"
},
  "geometry": {"coordinates":[-69.96591600000001,43.914306],"type":"Point"}
}