{
  "type": "Feature",
  "properties": {
    "addr:full":"149 Front St Bath ME 04530",
    "addr:housenumber":"149",
    "addr:postcode":"04530",
    "addr:street":"Front St",
    "iso:country":"US",
    "sg:address":"149 Front St",
    "sg:city":"Bath",
    "sg:classifiers":[
        {
            "category":"Health Services",
            "subcategory":"Health Practitioner",
            "type":"Services"
        }
    ],
    "sg:phone":"+1 207 443 3341",
    "sg:postcode":"04530",
    "sg:province":"ME",
    "sg:tags":[
        "audiologists"
    ],
    "sg:website":"www.pinetreesociety.org",
    "wof:name":"Pine Tree Society",
    "wof:placetype":"venue"
},
  "geometry": {"coordinates":[-69.814204,43.914231],"type":"Point"}
}