{
  "type": "Feature",
  "properties": {
    "iso:country":"US",
    "sg:address":"45 State St",
    "sg:city":"Augusta",
    "sg:classifiers":[
        {
            "category":"Government",
            "subcategory":"Office",
            "type":"Public Place"
        }
    ],
    "sg:phone":"+1 207 624 6460",
    "sg:postcode":"04330",
    "sg:province":"ME",
    "sg:tags":[
        "state",
        "safety",
        "order"
    ],
    "wof:name":"Safety Division",
    "wof:placetype":"venue"
},
  "geometry": {"coordinates":[-69.776086,44.318192],"type":"Point"}
}