{
  "type": "Feature",
  "properties": {
    "addr:full":"810 Banton Rd Palermo ME 04354",
    "addr:housenumber":"810",
    "addr:postcode":"04354",
    "addr:street":"Banton Rd",
    "iso:country":"US",
    "sg:address":"810 Banton Rd",
    "sg:city":"Palermo",
    "sg:classifiers":[
        {
            "category":"Manufacturing",
            "subcategory":"Tools & Machinery",
            "type":"Manufacturing & Wholesale Goods"
        }
    ],
    "sg:phone":"+1 207 993 2944",
    "sg:postcode":"04354",
    "sg:province":"ME",
    "sg:tags":[
        "equipment",
        "hydraulic"
    ],
    "wof:name":"Hydrepair Inc",
    "wof:placetype":"venue"
},
  "geometry": {"coordinates":[-69.40087200000001,44.353566],"type":"Point"}
}