{
  "type": "Feature",
  "properties": {
    "addr:full":"166 Main St South Paris ME 04281",
    "addr:housenumber":"166",
    "addr:postcode":"04281",
    "addr:street":"Main St South",
    "iso:country":"US",
    "sg:address":"166 Main St",
    "sg:city":"South Paris",
    "sg:classifiers":[
        {
            "category":"Home & Garden",
            "subcategory":"Building Materials",
            "type":"Retail Goods"
        }
    ],
    "sg:phone":"+1 207 784 6974",
    "sg:postcode":"04281",
    "sg:province":"ME",
    "sg:tags":[
        "paint"
    ],
    "wof:name":"Painter's Supply",
    "wof:placetype":"venue"
},
  "geometry": {"coordinates":[-70.51763200000001,44.216532],"type":"Point"}
}