{
  "type": "Feature",
  "properties": {
    "addr:full":"2324 Portland Rd Arundel ME 04046",
    "addr:housenumber":"2324",
    "addr:postcode":"04046",
    "addr:street":"Portland Rd",
    "iso:country":"US",
    "sg:address":"2324 Portland Rd",
    "sg:city":"Arundel",
    "sg:classifiers":[
        {
            "category":"Banks & Credit Unions",
            "subcategory":"Bank",
            "type":"Services"
        }
    ],
    "sg:phone":"+1 207 985 9411",
    "sg:postcode":"04046",
    "sg:province":"ME",
    "sg:tags":[
        "loan",
        "real estate"
    ],
    "wof:name":"Freedom Financial",
    "wof:placetype":"venue"
},
  "geometry": {"coordinates":[-70.49544899999999,43.453891],"type":"Point"}
}