{
  "type": "Feature",
  "properties": {
    "addr:full":"105 Congress St Rumford ME 04276",
    "addr:housenumber":"105",
    "addr:postcode":"04276",
    "addr:street":"Congress St",
    "iso:country":"US",
    "sg:address":"105 Congress St",
    "sg:city":"Rumford",
    "sg:classifiers":[
        {
            "category":"Restaurant",
            "type":"Food & Drink"
        }
    ],
    "sg:phone":"+1 207 364 2878",
    "sg:postcode":"04276",
    "sg:province":"ME",
    "wof:name":"Fortune Island Restaurant",
    "wof:placetype":"venue"
},
  "geometry": {"coordinates":[-70.54576,44.545188],"type":"Point"}
}