{
  "type": "Feature",
  "properties": {
    "addr:full":"553 Congress St Portland ME 04101",
    "addr:housenumber":"553",
    "addr:postcode":"04101",
    "addr:street":"Congress St",
    "iso:country":"US",
    "sg:address":"553 Congress St",
    "sg:city":"Portland",
    "sg:classifiers":[
        {
            "category":"Shopping",
            "subcategory":"Gifts & Souvenirs",
            "type":"Retail Goods"
        }
    ],
    "sg:phone":"+1 207 775 4860",
    "sg:postcode":"04101",
    "sg:province":"ME",
    "sg:tags":[
        "shop"
    ],
    "wof:name":"Just Maine Made",
    "wof:placetype":"venue"
},
  "geometry": {"coordinates":[-70.262417,43.654836],"type":"Point"}
}