{
  "type": "Feature",
  "properties": {
    "iso:country":"US",
    "sg:address":"7 Dennison Ave",
    "sg:city":"Freeport",
    "sg:classifiers":[
        {
            "category":"Professional",
            "subcategory":"Business Services",
            "type":"Services"
        }
    ],
    "sg:phone":"+1 207 865 6512",
    "sg:postcode":"04032",
    "sg:province":"ME",
    "wof:name":"John T Brogan",
    "wof:placetype":"venue"
},
  "geometry": {"coordinates":[-70.099622,43.853902],"type":"Point"}
}