{
  "type": "Feature",
  "properties": {
    "iso:country":"US",
    "sg:address":"470 Fore St",
    "sg:city":"Portland",
    "sg:classifiers":[
        {
            "category":"Personal",
            "subcategory":"Beauty Salon",
            "type":"Services"
        }
    ],
    "sg:phone":"+1 207 772 9060",
    "sg:postcode":"04101",
    "sg:province":"ME",
    "sg:website":"www.akarihairspa.com",
    "wof:name":"Akari Hair Care & Day Spa",
    "wof:placetype":"venue"
},
  "geometry": {"coordinates":[-70.255318,43.655589],"type":"Point"}
}