{
  "type": "Feature",
  "properties": {
    "addr:full":"83 Pine Ridge Rd North Yarmouth ME 04097",
    "addr:housenumber":"83",
    "addr:postcode":"04097",
    "addr:street":"Pine Ridge Rd",
    "iso:country":"US",
    "sg:address":"83 Pine Ridge Rd",
    "sg:city":"North Yarmouth",
    "sg:classifiers":[
        {
            "category":"Professional",
            "subcategory":"Management & Consulting",
            "type":"Services"
        }
    ],
    "sg:phone":"+1 207 846 6512",
    "sg:postcode":"04097",
    "sg:province":"ME",
    "sg:tags":[
        "consultant",
        "training"
    ],
    "wof:name":"Yarmouth Etiquette School",
    "wof:placetype":"venue"
},
  "geometry": {"coordinates":[-70.203745,43.835603],"type":"Point"}
}