{
  "type": "Feature",
  "properties": {
    "iso:country":"US",
    "sg:address":"425 Gorham Rd",
    "sg:city":"South Portland",
    "sg:classifiers":[
        {
            "category":"Retail",
            "subcategory":"Car Wash",
            "type":"Services"
        }
    ],
    "sg:phone":"+1 207 772 1838",
    "sg:postcode":"04106",
    "sg:province":"ME",
    "sg:tags":[
        "polishing",
        "washing"
    ],
    "wof:name":"Fill-It-Up-Please",
    "wof:placetype":"venue"
},
  "geometry": {"coordinates":[-70.330873,43.636332],"type":"Point"}
}