{
  "type": "Feature",
  "properties": {
    "iso:country":"US",
    "sg:address":"1 Coffin St",
    "sg:city":"Howland",
    "sg:classifiers":[
        {
            "category":"Wholesale",
            "subcategory":"Scrap",
            "type":"Manufacturing & Wholesale Goods"
        }
    ],
    "sg:phone":"+1 207 732 5613",
    "sg:postcode":"04448",
    "sg:province":"ME",
    "sg:tags":[
        "recycling",
        "center"
    ],
    "wof:name":"Riverside Redemption & Variety",
    "wof:placetype":"venue"
},
  "geometry": {"coordinates":[-68.659734,45.239347],"type":"Point"}
}