{
  "type": "Feature",
  "properties": {
    "iso:country":"US",
    "sg:address":"1321 Washington Ave",
    "sg:city":"Portland",
    "sg:classifiers":[
        {
            "category":"Professional",
            "subcategory":"Advertising",
            "type":"Services"
        }
    ],
    "sg:phone":"+1 207 878 2490",
    "sg:postcode":"04103",
    "sg:province":"ME",
    "sg:tags":[
        "medium",
        "buying"
    ],
    "wof:name":"Jvi Media",
    "wof:placetype":"venue"
},
  "geometry": {"coordinates":[-70.28782099999999,43.699503],"type":"Point"}
}