{
  "type": "Feature",
  "properties": {
    "iso:country":"US",
    "sg:address":"169 Portland Ave",
    "sg:city":"Old Orchard Beach",
    "sg:classifiers":[
        {
            "category":"Shopping",
            "subcategory":"Hobbies, Toys, & Games",
            "type":"Retail Goods"
        },
        {
            "category":"Shopping",
            "subcategory":"Florist",
            "type":"Retail Goods"
        }
    ],
    "sg:phone":"+1 207 934 3729",
    "sg:postcode":"04064",
    "sg:province":"ME",
    "wof:name":"Everlastings and More",
    "wof:placetype":"venue"
},
  "geometry": {"coordinates":[-70.38510599999999,43.537516],"type":"Point"}
}