{
  "type": "Feature",
  "properties": {
    "addr:full":"2 Spring Pl Waterville ME 04901",
    "addr:housenumber":"2",
    "addr:postcode":"04901",
    "addr:street":"Spring Pl",
    "iso:country":"US",
    "sg:address":"2 Spring Pl",
    "sg:city":"Waterville",
    "sg:classifiers":[
        {
            "category":"Real Estate",
            "subcategory":"Real Estate Operator",
            "type":"Services"
        }
    ],
    "sg:phone":"+1 207 872 0396",
    "sg:postcode":"04901",
    "sg:province":"ME",
    "sg:tags":[
        "apartment"
    ],
    "wof:name":"Thibodeau Apartment Management",
    "wof:placetype":"venue"
},
  "geometry": {"coordinates":[-69.632987,44.548612],"type":"Point"}
}