{
  "type": "Feature",
  "properties": {
    "addr:full":"1328 Main St East Wilton ME 04240",
    "addr:housenumber":"1328",
    "addr:postcode":"04240",
    "addr:street":"Main St East",
    "iso:country":"US",
    "sg:address":"1328 Main St",
    "sg:city":"East Wilton",
    "sg:classifiers":[
        {
            "category":"Government",
            "subcategory":"Post Office",
            "type":"Public Place"
        }
    ],
    "sg:phone":"+1 207 645 4542",
    "sg:postcode":"04240",
    "sg:province":"ME",
    "wof:name":"US Post Office",
    "wof:placetype":"venue"
},
  "geometry": {"coordinates":[-70.19213999999999,44.144026],"type":"Point"}
}