{
  "type": "Feature",
  "properties": {
    "addr:full":"373 Walnut Hill Rd North Yarmouth ME 04097",
    "addr:housenumber":"373",
    "addr:postcode":"04097",
    "addr:street":"Walnut Hill Rd",
    "iso:country":"US",
    "sg:address":"373 Walnut Hill Rd",
    "sg:city":"North Yarmouth",
    "sg:classifiers":[
        {
            "category":"Home & Garden",
            "subcategory":"Carpets & Floor Coverings",
            "type":"Retail Goods"
        }
    ],
    "sg:phone":"+1 207 829 3386",
    "sg:postcode":"04097",
    "sg:province":"ME",
    "sg:tags":[
        "material"
    ],
    "sg:website":"www.fatandys.com",
    "wof:name":"Fat Andy's Inc",
    "wof:placetype":"venue"
},
  "geometry": {"coordinates":[-70.246533,43.823795],"type":"Point"}
}