{
  "type": "Feature",
  "properties": {
    "iso:country":"US",
    "sg:address":"9 Harding Ave",
    "sg:city":"Island Falls",
    "sg:classifiers":[
        {
            "category":"Retail",
            "subcategory":"Veterinary Services",
            "type":"Services"
        }
    ],
    "sg:phone":"+1 207 463 2204",
    "sg:postcode":"04742",
    "sg:province":"ME",
    "sg:tags":[
        "veterinarian"
    ],
    "wof:name":"Island Falls Vet Clinic",
    "wof:placetype":"venue"
},
  "geometry": {"coordinates":[-67.826947,46.762931],"type":"Point"}
}