{
  "type": "Feature",
  "properties": {
    "iso:country":"US",
    "sg:address":"9 Alfred St",
    "sg:city":"Biddeford",
    "sg:classifiers":[
        {
            "category":"Professional",
            "subcategory":"Lawyer & Legal Services",
            "type":"Services"
        }
    ],
    "sg:phone":"+1 207 282 5194",
    "sg:postcode":"04005",
    "sg:province":"ME",
    "sg:tags":[
        "attorney"
    ],
    "wof:name":"Herschel M Lerman",
    "wof:placetype":"venue"
},
  "geometry": {"coordinates":[-70.453383,43.492342],"type":"Point"}
}