{
  "type": "Feature",
  "properties": {
    "addr:full":"23 Washington Ave Scarborough ME 04074",
    "addr:housenumber":"23",
    "addr:postcode":"04074",
    "addr:street":"Washington Ave",
    "iso:country":"US",
    "sg:address":"23 Washington Ave",
    "sg:city":"Scarborough",
    "sg:classifiers":[
        {
            "category":"Sports & Exercise",
            "subcategory":"Race Track",
            "type":"Entertainment"
        }
    ],
    "sg:phone":"+1 207 885 0058",
    "sg:postcode":"04074",
    "sg:province":"ME",
    "wof:name":"Maine Indoor Karting",
    "wof:placetype":"venue"
},
  "geometry": {"coordinates":[-70.357602,43.578018],"type":"Point"}
}