{
  "type": "Feature",
  "properties": {
    "iso:country":"US",
    "sg:address":"640 Dead River Rd",
    "sg:city":"Bowdoin",
    "sg:classifiers":[
        {
            "category":"Building & Trades",
            "subcategory":"Plumbing",
            "type":"Services"
        }
    ],
    "sg:phone":"+1 207 666 3310",
    "sg:postcode":"04287",
    "sg:province":"ME",
    "sg:tags":[
        "plumbing",
        "contractor"
    ],
    "wof:name":"Mark E Turcotte Plumbing & Htg",
    "wof:placetype":"venue"
},
  "geometry": {"coordinates":[-69.932584,44.112109],"type":"Point"}
}