{
  "type": "Feature",
  "properties": {
    "iso:country":"US",
    "sg:address":"56 Chamberlain St",
    "sg:city":"Brewer",
    "sg:classifiers":[
        {
            "category":"Shopping",
            "subcategory":"Computers & Home Electronics",
            "type":"Retail Goods"
        },
        {
            "category":"Professional",
            "subcategory":"Computer Services",
            "type":"Services"
        }
    ],
    "sg:phone":"+1 207 989 1443",
    "sg:postcode":"04412",
    "sg:province":"ME",
    "sg:tags":[
        "equipment",
        "dealer"
    ],
    "wof:name":"Traveling Technicians",
    "wof:placetype":"venue"
},
  "geometry": {"coordinates":[-68.75858599999999,44.797863],"type":"Point"}
}