{
  "type": "Feature",
  "properties": {
    "iso:country":"US",
    "sg:address":"135 Washington Ave",
    "sg:city":"Portland",
    "sg:classifiers":[
        {
            "category":"Organizations",
            "subcategory":"Community Association",
            "type":"Services"
        }
    ],
    "sg:phone":"+1 207 772 9215",
    "sg:postcode":"04101",
    "sg:province":"ME",
    "sg:tags":[
        "club"
    ],
    "sg:website":"www.sahara.com",
    "wof:name":"Sahara Club",
    "wof:placetype":"venue"
},
  "geometry": {"coordinates":[-70.252774,43.666627],"type":"Point"}
}