{
  "type": "Feature",
  "properties": {
    "iso:country":"US",
    "sg:address":"85 Washington St",
    "sg:city":"Eastport",
    "sg:classifiers":[
        {
            "category":"Food & Beverages",
            "subcategory":"Groceries & Convenience Stores",
            "type":"Retail Goods"
        }
    ],
    "sg:phone":"+1 207 853 2376",
    "sg:postcode":"04631",
    "sg:province":"ME",
    "wof:name":"Eastport Rte 1 Irving",
    "wof:placetype":"venue"
},
  "geometry": {"coordinates":[-66.99291,44.906243],"type":"Point"}
}