{
  "type": "Feature",
  "properties": {
    "iso:country":"US",
    "sg:address":"220 River Rd",
    "sg:city":"Detroit",
    "sg:classifiers":[
        {
            "category":"Retail",
            "subcategory":"Repair Shop",
            "type":"Services"
        }
    ],
    "sg:phone":"+1 207 487 5271",
    "sg:postcode":"04929",
    "sg:province":"ME",
    "wof:name":"Rons TV",
    "wof:placetype":"venue"
},
  "geometry": {"coordinates":[-69.338326,44.775972],"type":"Point"}
}