{
  "type": "Feature",
  "properties": {
    "iso:country":"US",
    "sg:address":"23 Pierce Ave",
    "sg:city":"Portland",
    "sg:classifiers":[
        {
            "category":"Building & Trades",
            "subcategory":"Construction",
            "type":"Services"
        }
    ],
    "sg:phone":"+1 207 774 7373",
    "sg:postcode":"04102",
    "sg:province":"ME",
    "sg:tags":[
        "well",
        "drilling"
    ],
    "wof:name":"Downeast Drilling",
    "wof:placetype":"venue"
},
  "geometry": {"coordinates":[-70.32610699999999,43.661854],"type":"Point"}
}