{
  "type": "Feature",
  "properties": {
    "iso:country":"US",
    "sg:address":"115 Maine St",
    "sg:city":"Brunswick",
    "sg:classifiers":[
        {
            "category":"Restaurant",
            "type":"Food & Drink"
        }
    ],
    "sg:phone":"+1 207 729 9673",
    "sg:postcode":"04011",
    "sg:province":"ME",
    "wof:name":"Richard's",
    "wof:placetype":"venue"
},
  "geometry": {"coordinates":[-69.96543,43.915752],"type":"Point"}
}