{
  "type": "Feature",
  "properties": {
    "iso:country":"US",
    "sg:address":"295 Harpswell Neck Rd",
    "sg:city":"South Harpswell",
    "sg:classifiers":[
        {
            "category":"Wholesale",
            "subcategory":"Seafood",
            "type":"Manufacturing & Wholesale Goods"
        }
    ],
    "sg:phone":"+1 207 833 7348",
    "sg:postcode":"04079",
    "sg:province":"ME",
    "wof:name":"Ferns Bugs",
    "wof:placetype":"venue"
},
  "geometry": {"coordinates":[-69.958074,43.834922],"type":"Point"}
}