{
  "type": "Feature",
  "properties": {
    "iso:country":"US",
    "sg:address":"4 Commercial St",
    "sg:city":"Boothbay Harbor",
    "sg:classifiers":[
        {
            "category":"Shopping",
            "subcategory":"Clothing, Apparel, & Fashions",
            "type":"Retail Goods"
        }
    ],
    "sg:phone":"+1 207 633 3262",
    "sg:postcode":"04538",
    "sg:province":"ME",
    "wof:name":"Paine's Clothing Store",
    "wof:placetype":"venue"
},
  "geometry": {"coordinates":[-69.62781099999999,43.851295],"type":"Point"}
}