{
  "type": "Feature",
  "properties": {
    "addr:full":"299 Union St Bangor ME 04401",
    "addr:housenumber":"299",
    "addr:postcode":"04401",
    "addr:street":"Union St",
    "iso:country":"US",
    "sg:address":"299 Union St",
    "sg:city":"Bangor",
    "sg:classifiers":[
        {
            "category":"Retail",
            "subcategory":"Funeral Services",
            "type":"Services"
        }
    ],
    "sg:phone":"+1 207 942 0392",
    "sg:postcode":"04401",
    "sg:province":"ME",
    "sg:tags":[
        "director"
    ],
    "wof:name":"Foley Funeral Svc",
    "wof:placetype":"venue"
},
  "geometry": {"coordinates":[-68.781189,44.803017],"type":"Point"}
}