{
  "type": "Feature",
  "properties": {
    "addr:full":"29 Ferry Rd Deer Isle ME 04685",
    "addr:housenumber":"29",
    "addr:postcode":"04685",
    "addr:street":"Ferry Rd;Isle",
    "iso:country":"US",
    "sg:address":"29 Ferry Rd",
    "sg:city":"Deer Isle",
    "sg:classifiers":[
        {
            "category":"Retail",
            "subcategory":"Repair Shop",
            "type":"Services"
        }
    ],
    "sg:phone":"+1 207 348 9922",
    "sg:postcode":"04685",
    "sg:province":"ME",
    "sg:tags":[
        "blacksmith"
    ],
    "wof:name":"Old Ferry Road Forge",
    "wof:placetype":"venue"
},
  "geometry": {"coordinates":[-68.42016099999999,44.177323],"type":"Point"}
}