{
  "type": "Feature",
  "properties": {
    "iso:country":"US",
    "sg:address":"53 Main St",
    "sg:city":"Raymond",
    "sg:classifiers":[
        {
            "category":"Shopping",
            "subcategory":"Gifts & Souvenirs",
            "type":"Retail Goods"
        }
    ],
    "sg:phone":"+1 207 655 8802",
    "sg:postcode":"04071",
    "sg:province":"ME",
    "wof:name":"Cottage Industries Of Raymond",
    "wof:placetype":"venue"
},
  "geometry": {"coordinates":[-70.47187099999999,43.902519],"type":"Point"}
}