{
  "type": "Feature",
  "properties": {
    "iso:country":"US",
    "sg:address":"5 Moulton St",
    "sg:city":"Portland",
    "sg:classifiers":[
        {
            "category":"Government",
            "subcategory":"Office",
            "type":"Public Place"
        }
    ],
    "sg:phone":"+1 207 879 6111",
    "sg:postcode":"04101",
    "sg:province":"ME",
    "sg:tags":[
        "village"
    ],
    "wof:name":"Affordable Housing Prsrvtn",
    "wof:placetype":"venue"
},
  "geometry": {"coordinates":[-70.252725,43.656191],"type":"Point"}
}