{
  "type": "Feature",
  "properties": {
    "iso:country":"US",
    "sg:address":"15 Main St",
    "sg:city":"Dexter",
    "sg:classifiers":[
        {
            "category":"Real Estate",
            "subcategory":"Real Estate Agent",
            "type":"Services"
        }
    ],
    "sg:phone":"+1 207 924 3491",
    "sg:postcode":"04930",
    "sg:province":"ME",
    "wof:name":"Assist 2 Sell",
    "wof:placetype":"venue"
},
  "geometry": {"coordinates":[-69.289553,45.024095],"type":"Point"}
}