{
  "type": "Feature",
  "properties": {
    "iso:country":"US",
    "sg:address":"39 Jordan Ave",
    "sg:city":"Brunswick",
    "sg:classifiers":[
        {
            "category":"Retail",
            "subcategory":"Auto Repair",
            "type":"Services"
        }
    ],
    "sg:phone":"+1 207 725 7908",
    "sg:postcode":"04011",
    "sg:province":"ME",
    "sg:tags":[
        "body",
        "automobile",
        "painting"
    ],
    "wof:name":"Brunswick Auto Body & Custom",
    "wof:placetype":"venue"
},
  "geometry": {"coordinates":[-69.957188,43.914877],"type":"Point"}
}