{
  "type": "Feature",
  "properties": {
    "addr:full":"4 Wallingford Sq Kittery ME 03904",
    "addr:housenumber":"4",
    "addr:postcode":"03904",
    "addr:street":"Wallingford Sq",
    "iso:country":"US",
    "sg:address":"4 Wallingford Sq",
    "sg:city":"Kittery",
    "sg:classifiers":[
        {
            "category":"Bars & Pubs",
            "type":"Food & Drink"
        }
    ],
    "sg:phone":"+1 207 439 8822",
    "sg:postcode":"03904",
    "sg:province":"ME",
    "wof:name":"Corner Pub",
    "wof:placetype":"venue"
},
  "geometry": {"coordinates":[-70.743255,43.08584],"type":"Point"}
}