{
  "type": "Feature",
  "properties": {
    "addr:full":"438 Newfield Rd Shapleigh ME 04076",
    "addr:housenumber":"438",
    "addr:postcode":"04076",
    "addr:street":"Newfield Rd",
    "iso:country":"US",
    "sg:address":"438 Newfield Rd",
    "sg:city":"Shapleigh",
    "sg:classifiers":[
        {
            "category":"Building & Trades",
            "subcategory":"Construction",
            "type":"Services"
        }
    ],
    "sg:phone":"+1 207 432 4499",
    "sg:postcode":"04076",
    "sg:province":"ME",
    "sg:tags":[
        "roofing",
        "contractor"
    ],
    "wof:name":"P R Construction",
    "wof:placetype":"venue"
},
  "geometry": {"coordinates":[-70.824372,43.611072],"type":"Point"}
}