{
  "type": "Feature",
  "properties": {
    "addr:full":"36 Rocky Hill Rd Saco ME 04072",
    "addr:housenumber":"36",
    "addr:postcode":"04072",
    "addr:street":"Rocky Hill Rd",
    "iso:country":"US",
    "sg:address":"36 Rocky Hill Rd",
    "sg:city":"Saco",
    "sg:classifiers":[
        {
            "category":"Professional",
            "subcategory":"Management & Consulting",
            "type":"Services"
        }
    ],
    "sg:phone":"+1 207 282 5598",
    "sg:postcode":"04072",
    "sg:province":"ME",
    "wof:name":"Carl Lakari Inc",
    "wof:placetype":"venue"
},
  "geometry": {"coordinates":[-70.49696299999999,43.56401],"type":"Point"}
}