{
  "type": "Feature",
  "properties": {
    "iso:country":"US",
    "sg:address":"936 Brighton Ave",
    "sg:city":"Portland",
    "sg:classifiers":[
        {
            "category":"Shopping",
            "subcategory":"Pharmacy",
            "type":"Retail Goods"
        }
    ],
    "sg:phone":"+1 207 842 9202",
    "sg:postcode":"04102",
    "sg:province":"ME",
    "wof:name":"Rite Aid Pharmacy",
    "wof:placetype":"venue"
},
  "geometry": {"coordinates":[-70.31706,43.673638],"type":"Point"}
}