{
  "type": "Feature",
  "properties": {
    "iso:country":"US",
    "sg:address":"60 Industrial St",
    "sg:city":"Waterville",
    "sg:classifiers":[
        {
            "category":"Government",
            "subcategory":"Office",
            "type":"Public Place"
        }
    ],
    "sg:phone":"+1 207 877 0522",
    "sg:postcode":"04901",
    "sg:province":"ME",
    "sg:tags":[
        "village"
    ],
    "wof:name":"Recycling Center",
    "wof:placetype":"venue"
},
  "geometry": {"coordinates":[-69.633294,44.571922],"type":"Point"}
}