{
  "type": "Feature",
  "properties": {
    "addr:full":"725 Main St Presque Isle ME 04769",
    "addr:housenumber":"725",
    "addr:postcode":"04769",
    "addr:street":"Main St",
    "iso:country":"US",
    "sg:address":"725 Main St",
    "sg:city":"Presque Isle",
    "sg:classifiers":[
        {
            "category":"Restaurant",
            "type":"Food & Drink"
        }
    ],
    "sg:phone":"+1 207 764 3601",
    "sg:postcode":"04769",
    "sg:province":"ME",
    "wof:name":"Bonanza Steakhouse",
    "wof:placetype":"venue"
},
  "geometry": {"coordinates":[-68.012258,46.694798],"type":"Point"}
}