{
  "type": "Feature",
  "properties": {
    "iso:country":"US",
    "sg:address":"30 Milk St",
    "sg:city":"Portland",
    "sg:classifiers":[
        {
            "category":"Professional",
            "subcategory":"Computer Services",
            "type":"Services"
        }
    ],
    "sg:phone":"+1 207 761 0996",
    "sg:postcode":"04101",
    "sg:province":"ME",
    "sg:tags":[
        "design",
        "system"
    ],
    "wof:name":"Electronic Data Systems Corp",
    "wof:placetype":"venue"
},
  "geometry": {"coordinates":[-70.253844,43.656951],"type":"Point"}
}