{
  "type": "Feature",
  "properties": {
    "addr:full":"15 Nelson Ridge Rd N Washington ME 04574",
    "addr:housenumber":"15",
    "addr:postcode":"me 04574",
    "addr:street":"Nelson Ridge Rd N",
    "iso:country":"US",
    "sg:address":"15 Nelson Ridge Rd N",
    "sg:city":"Washington",
    "sg:classifiers":[
        {
            "category":"Building & Trades",
            "subcategory":"Construction",
            "type":"Services"
        }
    ],
    "sg:phone":"+1 207 845 2440",
    "sg:postcode":"04574",
    "sg:province":"ME",
    "sg:tags":[
        "plumbing",
        "masonry",
        "contractor"
    ],
    "wof:name":"Brick Stove Works",
    "wof:placetype":"venue"
},
  "geometry": {"coordinates":[-69.39406700000001,44.271558],"type":"Point"}
}