{
  "type": "Feature",
  "properties": {
    "iso:country":"US",
    "sg:address":"149 US Hwy 201",
    "sg:city":"Fairfield",
    "sg:classifiers":[
        {
            "category":"Health Services",
            "subcategory":"Nursing And Care Facility",
            "type":"Services"
        }
    ],
    "sg:phone":"+1 207 453 2112",
    "sg:postcode":"04937",
    "sg:province":"ME",
    "sg:tags":[
        "home",
        "convalescent"
    ],
    "sg:website":"www.northcountryassociates.com",
    "wof:name":"Klearview Manor Nursing Home",
    "wof:placetype":"venue"
},
  "geometry": {"coordinates":[-69.59689899999999,44.608246],"type":"Point"}
}