{
  "type": "Feature",
  "properties": {
    "addr:full":"15 Church St Shawmut ME 04975",
    "addr:housenumber":"15",
    "addr:postcode":"04975",
    "addr:street":"Church St",
    "iso:country":"US",
    "sg:address":"15 Church St",
    "sg:city":"Shawmut",
    "sg:classifiers":[
        {
            "category":"Home & Garden",
            "subcategory":"Garden Supply",
            "type":"Retail Goods"
        }
    ],
    "sg:phone":"+1 207 453 7800",
    "sg:postcode":"04975",
    "sg:province":"ME",
    "sg:tags":[
        "lawn",
        "mower"
    ],
    "wof:name":"Tom Hayes",
    "wof:placetype":"venue"
},
  "geometry": {"coordinates":[-69.58560799999999,44.623118],"type":"Point"}
}