{
  "type": "Feature",
  "properties": {
    "iso:country":"US",
    "sg:address":"120 Bedford St",
    "sg:city":"Portland",
    "sg:classifiers":[
        {
            "category":"Education",
            "subcategory":"College",
            "type":"Public Place"
        }
    ],
    "sg:phone":"+1 207 780 5926",
    "sg:postcode":"04102",
    "sg:province":"ME",
    "sg:tags":[
        "academic",
        "school"
    ],
    "wof:name":"University Of Southern Maine",
    "wof:placetype":"venue"
},
  "geometry": {"coordinates":[-70.277147,43.660928],"type":"Point"}
}