{
  "type": "Feature",
  "properties": {
    "addr:full":"2 Central St Rockport ME 04856",
    "addr:housenumber":"2",
    "addr:postcode":"04856",
    "addr:street":"Central St",
    "iso:country":"US",
    "sg:address":"2 Central St",
    "sg:city":"Rockport",
    "sg:classifiers":[
        {
            "category":"Education",
            "subcategory":"College",
            "type":"Public Place"
        }
    ],
    "sg:phone":"+1 207 236 8581",
    "sg:postcode":"04856",
    "sg:province":"ME",
    "sg:tags":[
        "academic",
        "school"
    ],
    "sg:website":"www.photographicworkshops.com",
    "wof:name":"Maine Photographic Workshops",
    "wof:placetype":"venue"
},
  "geometry": {"coordinates":[-69.070914,44.187924],"type":"Point"}
}