{
  "type": "Feature",
  "properties": {
    "addr:full":"840 Sabattus Rd Sabattus ME 04280",
    "addr:housenumber":"840",
    "addr:postcode":"04280",
    "addr:street":"Sabattus Rd",
    "iso:country":"US",
    "sg:address":"840 Sabattus Rd",
    "sg:city":"Sabattus",
    "sg:classifiers":[
        {
            "category":"Farming",
            "subcategory":"Farm",
            "type":"Manufacturing & Wholesale Goods"
        }
    ],
    "sg:phone":"+1 207 375 9939",
    "sg:postcode":"04280",
    "sg:province":"ME",
    "wof:name":"Waterman Farms",
    "wof:placetype":"venue"
},
  "geometry": {"coordinates":[-70.072512,44.126837],"type":"Point"}
}