{
  "type": "Feature",
  "properties": {
    "iso:country":"US",
    "sg:address":"31 Bromo Rd",
    "sg:city":"Berwick",
    "sg:classifiers":[
        {
            "category":"Building & Trades",
            "subcategory":"Construction",
            "type":"Services"
        }
    ],
    "sg:phone":"+1 207 676 4009",
    "sg:postcode":"03901",
    "sg:province":"ME",
    "sg:tags":[
        "excavating",
        "contractor"
    ],
    "wof:name":"Morrill Excavating",
    "wof:placetype":"venue"
},
  "geometry": {"coordinates":[-70.862212,43.279821],"type":"Point"}
}