{
  "type": "Feature",
  "properties": {
    "iso:country":"US",
    "sg:address":"40 Curtis Dr",
    "sg:city":"Augusta",
    "sg:classifiers":[
        {
            "category":"Manufacturing",
            "subcategory":"Building Materials",
            "type":"Manufacturing & Wholesale Goods"
        }
    ],
    "sg:phone":"+1 207 547 3844",
    "sg:postcode":"04330",
    "sg:province":"ME",
    "sg:tags":[
        "mfg",
        "wood",
        "kitchen",
        "cabinet"
    ],
    "wof:name":"Kitchens Unlimited",
    "wof:placetype":"venue"
},
  "geometry": {"coordinates":[-69.79902300000001,44.399937],"type":"Point"}
}