{
  "type": "Feature",
  "properties": {
    "iso:country":"US",
    "sg:address":"34 Roak St",
    "sg:city":"Auburn",
    "sg:classifiers":[
        {
            "category":"Building & Trades",
            "subcategory":"Construction",
            "type":"Services"
        }
    ],
    "sg:phone":"+1 207 783 4362",
    "sg:postcode":"04210",
    "sg:province":"ME",
    "sg:tags":[
        "contractor"
    ],
    "wof:name":"Chucks Masonry Restoration",
    "wof:placetype":"venue"
},
  "geometry": {"coordinates":[-70.221103,44.084176],"type":"Point"}
}