{
  "type": "Feature",
  "properties": {
    "addr:full":"13 Western Ave Kennebunk ME 04046",
    "addr:housenumber":"13",
    "addr:postcode":"04046",
    "addr:street":"Western Ave",
    "iso:country":"US",
    "sg:address":"13 Western Ave",
    "sg:city":"Kennebunk",
    "sg:classifiers":[
        {
            "category":"Shopping",
            "subcategory":"Optical Goods",
            "type":"Retail Goods"
        }
    ],
    "sg:phone":"+1 207 967 3555",
    "sg:postcode":"04046",
    "sg:province":"ME",
    "sg:tags":[
        "optician"
    ],
    "wof:name":"Bayberry Optical",
    "wof:placetype":"venue"
},
  "geometry": {"coordinates":[-70.480857,43.35984],"type":"Point"}
}