{
  "type": "Feature",
  "properties": {
    "addr:full":"117 Broadway Bangor ME 04401",
    "addr:housenumber":"117",
    "addr:postcode":"04401",
    "addr:street":"Broadway",
    "iso:country":"US",
    "sg:address":"117 Broadway",
    "sg:city":"Bangor",
    "sg:classifiers":[
        {
            "category":"Professional",
            "subcategory":"Management & Consulting",
            "type":"Services"
        }
    ],
    "sg:phone":"+1 207 945 9432",
    "sg:postcode":"04401",
    "sg:province":"ME",
    "sg:tags":[
        "consultant",
        "training"
    ],
    "wof:name":"Job Training Program",
    "wof:placetype":"venue"
},
  "geometry": {"coordinates":[-68.76861700000001,44.807127],"type":"Point"}
}