{
  "type": "Feature",
  "properties": {
    "iso:country":"US",
    "sg:address":"8 Cromwell St",
    "sg:city":"Kittery",
    "sg:classifiers":[
        {
            "category":"Professional",
            "type":"Services"
        }
    ],
    "sg:phone":"+1 207 439 5144",
    "sg:postcode":"03904",
    "sg:province":"ME",
    "wof:name":"BP Games",
    "wof:placetype":"venue"
},
  "geometry": {"coordinates":[-70.733117,43.091654],"type":"Point"}
}