{
  "type": "Feature",
  "properties": {
    "addr:full":"11 Floral St Bath ME 04530",
    "addr:housenumber":"11",
    "addr:postcode":"04530",
    "addr:street":"Floral St",
    "iso:country":"US",
    "sg:address":"11 Floral St",
    "sg:city":"Bath",
    "sg:classifiers":[
        {
            "category":"Wholesale",
            "subcategory":"Groceries",
            "type":"Manufacturing & Wholesale Goods"
        }
    ],
    "sg:phone":"+1 207 443 8500",
    "sg:postcode":"04530",
    "sg:province":"ME",
    "sg:tags":[
        "baker"
    ],
    "wof:name":"Seaflour",
    "wof:placetype":"venue"
},
  "geometry": {"coordinates":[-69.82657500000001,43.911208],"type":"Point"}
}