{
  "type": "Feature",
  "properties": {
    "addr:full":"423 Church Hill Rd Augusta ME 04330",
    "addr:housenumber":"423",
    "addr:postcode":"04330",
    "addr:street":"Church Hill Rd",
    "iso:country":"US",
    "sg:address":"423 Church Hill Rd",
    "sg:city":"Augusta",
    "sg:classifiers":[
        {
            "category":"Building & Trades",
            "subcategory":"Electrical",
            "type":"Services"
        }
    ],
    "sg:phone":"+1 207 623 4341",
    "sg:postcode":"04330",
    "sg:province":"ME",
    "sg:tags":[
        "electric",
        "contractor"
    ],
    "wof:name":"Dick Lerette Electrical",
    "wof:placetype":"venue"
},
  "geometry": {"coordinates":[-69.72018300000001,44.348824],"type":"Point"}
}