{
  "type": "Feature",
  "properties": {
    "addr:full":"10 Water St Bangor ME 04401",
    "addr:housenumber":"10",
    "addr:postcode":"04401",
    "addr:street":"Water St",
    "iso:country":"US",
    "sg:address":"10 Water St",
    "sg:city":"Bangor",
    "sg:classifiers":[
        {
            "category":"Social Services",
            "subcategory":"Adult Care",
            "type":"Services"
        }
    ],
    "sg:phone":"+1 207 942 2426",
    "sg:postcode":"04401",
    "sg:province":"ME",
    "sg:tags":[
        "home",
        "residential"
    ],
    "wof:name":"Freese's Assisted Living",
    "wof:placetype":"venue"
},
  "geometry": {"coordinates":[-68.77196499999999,44.799741],"type":"Point"}
}