{
  "type": "Feature",
  "properties": {
    "iso:country":"US",
    "sg:address":"28 Main St",
    "sg:city":"Sumner",
    "sg:classifiers":[
        {
            "category":"Retail",
            "subcategory":"Repair Shop",
            "type":"Services"
        }
    ],
    "sg:phone":"+1 207 388 3177",
    "sg:postcode":"04292",
    "sg:province":"ME",
    "sg:tags":[
        "upholsterer"
    ],
    "wof:name":"Osborn Alan Fine Furniture",
    "wof:placetype":"venue"
},
  "geometry": {"coordinates":[-70.38039499999999,44.357141],"type":"Point"}
}