{
  "type": "Feature",
  "properties": {
    "iso:country":"US",
    "sg:address":"261 Main St",
    "sg:city":"Yarmouth",
    "sg:classifiers":[
        {
            "category":"Sports & Exercise",
            "subcategory":"Gym",
            "type":"Entertainment"
        }
    ],
    "sg:phone":"+1 207 846 9053",
    "sg:postcode":"04096",
    "sg:province":"ME",
    "sg:tags":[
        "fitness",
        "physical",
        "facility"
    ],
    "wof:name":"Weighty Issues",
    "wof:placetype":"venue"
},
  "geometry": {"coordinates":[-70.189807,43.801904],"type":"Point"}
}