{
  "type": "Feature",
  "properties": {
    "addr:full":"49 Alton Rd Winthrop ME 04330",
    "addr:housenumber":"49",
    "addr:postcode":"04330",
    "addr:street":"Alton Rd",
    "iso:country":"US",
    "sg:address":"49 Alton Rd",
    "sg:city":"Winthrop",
    "sg:classifiers":[
        {
            "category":"Retail",
            "subcategory":"Auto Repair",
            "type":"Services"
        }
    ],
    "sg:phone":"+1 207 377 2401",
    "sg:postcode":"04330",
    "sg:province":"ME",
    "sg:tags":[
        "repairing",
        "automobile"
    ],
    "wof:name":"Ron's Mechanic Svc",
    "wof:placetype":"venue"
},
  "geometry": {"coordinates":[-69.792703,44.309222],"type":"Point"}
}