{
  "type": "Feature",
  "properties": {
    "iso:country":"US",
    "sg:address":"18 Abigail Way",
    "sg:city":"Scarborough",
    "sg:classifiers":[
        {
            "category":"Professional",
            "subcategory":"Computer Services",
            "type":"Services"
        }
    ],
    "sg:phone":"+1 207 883 3220",
    "sg:postcode":"04074",
    "sg:province":"ME",
    "sg:tags":[
        "datum"
    ],
    "wof:name":"Paul Stubbs",
    "wof:placetype":"venue"
},
  "geometry": {"coordinates":[-70.33393700000001,43.604244],"type":"Point"}
}