{
  "type": "Feature",
  "properties": {
    "iso:country":"US",
    "sg:address":"12 Stephen King Dr",
    "sg:city":"Augusta",
    "sg:classifiers":[
        {
            "category":"Shopping",
            "subcategory":"Department Store",
            "type":"Retail Goods"
        }
    ],
    "sg:phone":"+1 207 623 0964",
    "sg:postcode":"04330",
    "sg:province":"ME",
    "sg:tags":[
        "shop"
    ],
    "sg:website":"www.pier1.com",
    "wof:name":"Pier 1 Imports",
    "wof:placetype":"venue"
},
  "geometry": {"coordinates":[-69.785633,44.343592],"type":"Point"}
}