{
  "type": "Feature",
  "properties": {
    "addr:full":"401 Johnson Mill Rd Orrington ME 04474",
    "addr:housenumber":"401",
    "addr:postcode":"04474",
    "addr:street":"Johnson Mill Rd",
    "iso:country":"US",
    "sg:address":"401 Johnson Mill Rd",
    "sg:city":"Orrington",
    "sg:classifiers":[
        {
            "category":"Home & Garden",
            "subcategory":"Household Appliances",
            "type":"Retail Goods"
        }
    ],
    "sg:phone":"+1 207 989 2825",
    "sg:postcode":"04474",
    "sg:province":"ME",
    "sg:tags":[
        "repair",
        "electrical"
    ],
    "wof:name":"Kens Vac & Sew Shop",
    "wof:placetype":"venue"
},
  "geometry": {"coordinates":[-68.791195,44.731345],"type":"Point"}
}