{
  "type": "Feature",
  "properties": {
    "addr:full":"338 Elm St Biddeford ME 04005",
    "addr:housenumber":"338",
    "addr:postcode":"04005",
    "addr:street":"Elm St",
    "iso:country":"US",
    "sg:address":"338 Elm St",
    "sg:city":"Biddeford",
    "sg:classifiers":[
        {
            "category":"Banks & Credit Unions",
            "subcategory":"Investment Brokerage",
            "type":"Services"
        }
    ],
    "sg:phone":"+1 207 282 5672",
    "sg:postcode":"04005",
    "sg:province":"ME",
    "sg:tags":[
        "retirement",
        "planning"
    ],
    "wof:name":"Daigneault & Assoc",
    "wof:placetype":"venue"
},
  "geometry": {"coordinates":[-70.468217,43.486201],"type":"Point"}
}