{
  "type": "Feature",
  "properties": {
    "addr:full":"968 Back Cove Rd Waldoboro ME 04572",
    "addr:housenumber":"968",
    "addr:postcode":"04572",
    "addr:street":"Back Cove Rd",
    "iso:country":"US",
    "sg:address":"968 Back Cove Rd",
    "sg:city":"Waldoboro",
    "sg:classifiers":[
        {
            "category":"Professional",
            "subcategory":"Art Services",
            "type":"Services"
        }
    ],
    "sg:phone":"+1 207 832 6806",
    "sg:postcode":"04572",
    "sg:province":"ME",
    "sg:tags":[
        "commercial",
        "design"
    ],
    "wof:name":"Audrey Bechler",
    "wof:placetype":"venue"
},
  "geometry": {"coordinates":[-69.355605,44.022959],"type":"Point"}
}