{
  "type": "Feature",
  "properties": {
    "iso:country":"US",
    "sg:address":"160 College Ave",
    "sg:city":"Waterville",
    "sg:classifiers":[
        {
            "category":"Insurance",
            "subcategory":"Insurance Agent",
            "type":"Services"
        }
    ],
    "sg:phone":"+1 207 877 7861",
    "sg:postcode":"04901",
    "sg:province":"ME",
    "sg:tags":[
        "investment",
        "closed"
    ],
    "wof:name":"Poulin & Bolduc",
    "wof:placetype":"venue"
},
  "geometry": {"coordinates":[-69.622574,44.568101],"type":"Point"}
}