{
  "type": "Feature",
  "properties": {
    "iso:country":"US",
    "sg:address":"431 Main St",
    "sg:city":"Biddeford",
    "sg:classifiers":[
        {
            "category":"Freight",
            "type":"Transportation"
        }
    ],
    "sg:phone":"+1 207 284 4526",
    "sg:postcode":"04005",
    "sg:province":"ME",
    "sg:tags":[
        "commercial",
        "storage"
    ],
    "wof:name":"Main Street Storage Co",
    "wof:placetype":"venue"
},
  "geometry": {"coordinates":[-70.464516,43.497294],"type":"Point"}
}