{
  "type": "Feature",
  "properties": {
    "addr:full":"108 Lewiston St Mechanic Falls ME 04256",
    "addr:housenumber":"108",
    "addr:postcode":"04256",
    "addr:street":"Lewiston St",
    "iso:country":"US",
    "sg:address":"108 Lewiston St",
    "sg:city":"Mechanic Falls",
    "sg:classifiers":[
        {
            "category":"Education",
            "subcategory":"School",
            "type":"Public Place"
        }
    ],
    "sg:phone":"+1 207 345 3217",
    "sg:postcode":"04256",
    "sg:province":"ME",
    "wof:name":"Adult Education",
    "wof:placetype":"venue"
},
  "geometry": {"coordinates":[-70.365649,44.103838],"type":"Point"}
}