{
  "type": "Feature",
  "properties": {
    "addr:full":"75 Pearl St Portland ME 04101",
    "addr:housenumber":"75",
    "addr:postcode":"04101",
    "addr:street":"Pearl St",
    "iso:country":"US",
    "sg:address":"75 Pearl St",
    "sg:city":"Portland",
    "sg:classifiers":[
        {
            "category":"Real Estate",
            "subcategory":"Real Estate Agent",
            "type":"Services"
        },
        {
            "category":"Professional",
            "subcategory":"Business Services",
            "type":"Services"
        }
    ],
    "sg:phone":"+1 207 774 0811",
    "sg:postcode":"04101",
    "sg:province":"ME",
    "sg:tags":[
        "arbitration"
    ],
    "wof:name":"Dana A Cleaves Associates",
    "wof:placetype":"venue"
},
  "geometry": {"coordinates":[-70.25421,43.658853],"type":"Point"}
}