{
  "type": "Feature",
  "properties": {
    "iso:country":"US",
    "sg:address":"581 Main St",
    "sg:city":"South Portland",
    "sg:classifiers":[
        {
            "category":"Shopping",
            "subcategory":"Used Merchandise",
            "type":"Retail Goods"
        }
    ],
    "sg:phone":"+1 207 773 8823",
    "sg:postcode":"04106",
    "sg:province":"ME",
    "sg:tags":[
        "shop",
        "consignment"
    ],
    "wof:name":"Bishop & Co",
    "wof:placetype":"venue"
},
  "geometry": {"coordinates":[-70.301701,43.622795],"type":"Point"}
}