{
  "type": "Feature",
  "properties": {
    "iso:country":"US",
    "sg:address":"119 Vaill Point Rd",
    "sg:city":"Yarmouth",
    "sg:classifiers":[
        {
            "category":"Social Services",
            "subcategory":"Child Care",
            "type":"Services"
        }
    ],
    "sg:phone":"+1 207 846 6606",
    "sg:postcode":"04096",
    "sg:province":"ME",
    "sg:tags":[
        "day"
    ],
    "wof:name":"Blueberry Ledge Nursery School",
    "wof:placetype":"venue"
},
  "geometry": {"coordinates":[-70.156723,43.784442],"type":"Point"}
}