{
  "type": "Feature",
  "properties": {
    "addr:full":"99 Fort St Presque Isle ME 04769",
    "addr:housenumber":"99",
    "addr:postcode":"04769",
    "addr:street":"Fort St;Isle",
    "iso:country":"US",
    "sg:address":"99 Fort St",
    "sg:city":"Presque Isle",
    "sg:classifiers":[
        {
            "category":"Government",
            "subcategory":"Office",
            "type":"Public Place"
        }
    ],
    "sg:phone":"+1 207 764 4151",
    "sg:postcode":"04769",
    "sg:province":"ME",
    "sg:tags":[
        "federal"
    ],
    "wof:name":"US Consolidated Farm Svc Agcy",
    "wof:placetype":"venue"
},
  "geometry": {"coordinates":[-68.00316599999999,46.688234],"type":"Point"}
}