{
  "type": "Feature",
  "properties": {
    "iso:country":"US",
    "sg:address":"1570 Broadway",
    "sg:city":"Bangor",
    "sg:classifiers":[
        {
            "category":"Health Services",
            "subcategory":"Chiropractor",
            "type":"Services"
        }
    ],
    "sg:phone":"+1 207 947 3333",
    "sg:postcode":"04401",
    "sg:province":"ME",
    "wof:name":"Myerowitz Chiropractic Ctr",
    "wof:placetype":"venue"
},
  "geometry": {"coordinates":[-68.797331,44.842023],"type":"Point"}
}