{
  "type": "Feature",
  "properties": {
    "addr:full":"630 County Rd Westbrook ME 04092",
    "addr:housenumber":"630",
    "addr:postcode":"04092",
    "addr:street":"County Rd",
    "iso:country":"US",
    "sg:address":"630 County Rd",
    "sg:city":"Westbrook",
    "sg:classifiers":[
        {
            "category":"Professional",
            "type":"Services"
        }
    ],
    "sg:phone":"+1 207 773 7377",
    "sg:postcode":"04092",
    "sg:province":"ME",
    "sg:tags":[
        "animal"
    ],
    "wof:name":"Marine Animal Lifeline",
    "wof:placetype":"venue"
},
  "geometry": {"coordinates":[-70.36879999999999,43.649128],"type":"Point"}
}