{
  "type": "Feature",
  "properties": {
    "iso:country":"US",
    "sg:address":"1 Park St",
    "sg:city":"Pittsfield",
    "sg:classifiers":[
        {
            "category":"Restaurant",
            "type":"Food & Drink"
        }
    ],
    "sg:phone":"+1 207 487 2707",
    "sg:postcode":"04967",
    "sg:province":"ME",
    "sg:tags":[
        "delicatessen"
    ],
    "wof:name":"Hole In The Wall Deli",
    "wof:placetype":"venue"
},
  "geometry": {"coordinates":[-69.383877,44.784729],"type":"Point"}
}