{
  "type": "Feature",
  "properties": {
    "iso:country":"US",
    "sg:address":"10 Library Dr",
    "sg:city":"Freeport",
    "sg:classifiers":[
        {
            "category":"Education",
            "subcategory":"Library",
            "type":"Public Place"
        }
    ],
    "sg:phone":"+1 207 865 3307",
    "sg:postcode":"04032",
    "sg:province":"ME",
    "sg:website":"www.freeportlibrary.com",
    "wof:name":"Freeport Community Library",
    "wof:placetype":"venue"
},
  "geometry": {"coordinates":[-70.101364,43.862581],"type":"Point"}
}