{
  "type": "Feature",
  "properties": {
    "addr:full":"386 Fore St Portland ME 04101",
    "addr:housenumber":"386",
    "addr:postcode":"04101",
    "addr:street":"Fore St",
    "iso:country":"US",
    "sg:address":"386 Fore St",
    "sg:city":"Portland",
    "sg:classifiers":[
        {
            "category":"Professional",
            "subcategory":"Advertising",
            "type":"Services"
        }
    ],
    "sg:phone":"+1 207 772 4141",
    "sg:postcode":"04101",
    "sg:province":"ME",
    "sg:tags":[
        "counselor"
    ],
    "wof:name":"Cameron Gale",
    "wof:placetype":"venue"
},
  "geometry": {"coordinates":[-70.25308699999999,43.656538],"type":"Point"}
}