{
  "type": "Feature",
  "properties": {
    "iso:country":"US",
    "sg:address":"166 Ossipee Trl",
    "sg:city":"Limington",
    "sg:classifiers":[
        {
            "category":"Personal",
            "subcategory":"Beauty Salon",
            "type":"Services"
        }
    ],
    "sg:phone":"+1 207 637 2682",
    "sg:postcode":"04068",
    "sg:province":"ME",
    "wof:name":"Mainely Hair",
    "wof:placetype":"venue"
},
  "geometry": {"coordinates":[-70.898389,43.804331],"type":"Point"}
}