{
  "type": "Feature",
  "properties": {
    "iso:country":"US",
    "sg:address":"318 Willey Point Rd",
    "sg:city":"Oakland",
    "sg:classifiers":[
        {
            "category":"Building & Trades",
            "subcategory":"Construction",
            "type":"Services"
        }
    ],
    "sg:phone":"+1 207 465 3663",
    "sg:postcode":"04963",
    "sg:province":"ME",
    "sg:tags":[
        "general",
        "contractor"
    ],
    "wof:name":"William Mushero Inc",
    "wof:placetype":"venue"
},
  "geometry": {"coordinates":[-69.734252,44.535213],"type":"Point"}
}