{
  "type": "Feature",
  "properties": {
    "iso:country":"US",
    "sg:address":"32 Sherwood Dr",
    "sg:city":"Auburn",
    "sg:classifiers":[
        {
            "category":"Education",
            "subcategory":"School",
            "type":"Public Place"
        }
    ],
    "sg:phone":"+1 207 783 8526",
    "sg:postcode":"04210",
    "sg:province":"ME",
    "sg:website":"www.auburnschl.edu",
    "wof:name":"Sherwood Heights Elem School",
    "wof:placetype":"venue"
},
  "geometry": {"coordinates":[-70.22753,44.077326],"type":"Point"}
}