{
  "type": "Feature",
  "properties": {
    "iso:country":"US",
    "sg:address":"69 Augusta Rd",
    "sg:city":"Whitefield",
    "sg:classifiers":[
        {
            "category":"Education",
            "subcategory":"School",
            "type":"Public Place"
        }
    ],
    "sg:phone":"+1 207 549 3261",
    "sg:postcode":"04353",
    "sg:province":"ME",
    "wof:name":"Superintendent Of Schools",
    "wof:placetype":"venue"
},
  "geometry": {"coordinates":[-69.647142,44.274972],"type":"Point"}
}