{
  "type": "Feature",
  "properties": {
    "addr:full":"360 Main St Southwest Harbor ME 04679",
    "addr:housenumber":"360",
    "addr:postcode":"04679",
    "addr:street":"Main St",
    "iso:country":"US",
    "sg:address":"360 Main St",
    "sg:city":"Southwest Harbor",
    "sg:classifiers":[
        {
            "category":"Shopping",
            "subcategory":"Books",
            "type":"Retail Goods"
        }
    ],
    "sg:phone":"+1 207 244 5542",
    "sg:postcode":"04679",
    "sg:province":"ME",
    "sg:tags":[
        "dealer"
    ],
    "wof:name":"Rue Cottage Books",
    "wof:placetype":"venue"
},
  "geometry": {"coordinates":[-68.326032,44.271191],"type":"Point"}
}