{
  "type": "Feature",
  "properties": {
    "iso:country":"US",
    "sg:address":"947 Waterford Rd",
    "sg:city":"Waterford",
    "sg:classifiers":[
        {
            "category":"Manufacturing",
            "subcategory":"Buildings",
            "type":"Manufacturing & Wholesale Goods"
        }
    ],
    "sg:phone":"+1 207 583 4100",
    "sg:postcode":"04088",
    "sg:province":"ME",
    "sg:tags":[
        "mobile",
        "home"
    ],
    "wof:name":"Waterford Homes Inc",
    "wof:placetype":"venue"
},
  "geometry": {"coordinates":[-70.70251399999999,44.191172],"type":"Point"}
}