{
  "type": "Feature",
  "properties": {
    "iso:country":"US",
    "sg:address":"12 Detullio Ln",
    "sg:city":"Wells",
    "sg:classifiers":[
        {
            "category":"Professional",
            "subcategory":"Business Services",
            "type":"Services"
        }
    ],
    "sg:phone":"+1 207 646 7539",
    "sg:postcode":"04090",
    "sg:province":"ME",
    "wof:name":"Smart Home Solutions Inc",
    "wof:placetype":"venue"
},
  "geometry": {"coordinates":[-70.573285,43.289127],"type":"Point"}
}