{
  "type": "Feature",
  "properties": {
    "iso:country":"US",
    "sg:address":"115 Old Pine Hill Rd",
    "sg:city":"Berwick",
    "sg:classifiers":[
        {
            "category":"Shopping",
            "type":"Retail Goods"
        }
    ],
    "sg:phone":"+1 207 698 1751",
    "sg:postcode":"03901",
    "sg:province":"ME",
    "sg:tags":[
        "repair",
        "saddlery",
        "tack",
        "grain",
        "riding"
    ],
    "wof:name":"D D s Leather Shop & Feeds",
    "wof:placetype":"venue"
},
  "geometry": {"coordinates":[-70.863475,43.280786],"type":"Point"}
}