{
  "type": "Feature",
  "properties": {
    "iso:country":"US",
    "sg:address":"8 Western Ave",
    "sg:city":"Kennebunk",
    "sg:classifiers":[
        {
            "category":"Manufacturing",
            "subcategory":"Food",
            "type":"Manufacturing & Wholesale Goods"
        }
    ],
    "sg:phone":"+1 207 967 4311",
    "sg:postcode":"04043",
    "sg:province":"ME",
    "sg:tags":[
        "brewer"
    ],
    "wof:name":"Kennebunkport Brewing Co",
    "wof:placetype":"venue"
},
  "geometry": {"coordinates":[-70.479439,43.360436],"type":"Point"}
}