{
  "type": "Feature",
  "properties": {
    "addr:full":"28 Portland Rd Kennebunk ME 04043",
    "addr:housenumber":"28",
    "addr:postcode":"04043",
    "addr:street":"Portland Rd",
    "iso:country":"US",
    "sg:address":"28 Portland Rd",
    "sg:city":"Kennebunk",
    "sg:classifiers":[
        {
            "category":"Shopping",
            "subcategory":"Florist",
            "type":"Retail Goods"
        }
    ],
    "sg:phone":"+1 207 985 2949",
    "sg:postcode":"04043",
    "sg:province":"ME",
    "sg:website":"www.bloomsandheirlooms.com",
    "wof:name":"Blooms & Heirlooms",
    "wof:placetype":"venue"
},
  "geometry": {"coordinates":[-70.53679700000001,43.388199],"type":"Point"}
}