{
  "type": "Feature",
  "properties": {
    "iso:country":"US",
    "sg:address":"374 Tate Rd",
    "sg:city":"East Corinth",
    "sg:classifiers":[
        {
            "category":"Farming",
            "subcategory":"Livestock Farm",
            "type":"Manufacturing & Wholesale Goods"
        }
    ],
    "sg:phone":"+1 207 285 7980",
    "sg:postcode":"04427",
    "sg:province":"ME",
    "sg:tags":[
        "beef",
        "feedlot",
        "cattle"
    ],
    "wof:name":"Mike Hatch",
    "wof:placetype":"venue"
},
  "geometry": {"coordinates":[-68.966397,45.000801],"type":"Point"}
}