{
  "type": "Feature",
  "properties": {
    "addr:full":"449 Main St Rockland ME 04841",
    "addr:housenumber":"449",
    "addr:postcode":"04841",
    "addr:street":"Main St",
    "iso:country":"US",
    "sg:address":"449 Main St",
    "sg:city":"Rockland",
    "sg:classifiers":[
        {
            "category":"Professional",
            "subcategory":"Lawyer & Legal Services",
            "type":"Services"
        }
    ],
    "sg:phone":"+1 207 594 4491",
    "sg:postcode":"04841",
    "sg:province":"ME",
    "sg:tags":[
        "attorney"
    ],
    "wof:name":"Grossman-Faber Law Firm",
    "wof:placetype":"venue"
},
  "geometry": {"coordinates":[-69.10928199999999,44.105326],"type":"Point"}
}