{
  "type": "Feature",
  "properties": {
    "iso:country":"US",
    "sg:address":"1248 Roosevelt Trl",
    "sg:city":"Raymond",
    "sg:classifiers":[
        {
            "category":"Professional",
            "type":"Services"
        }
    ],
    "sg:phone":"+1 207 655 2770",
    "sg:postcode":"04071",
    "sg:province":"ME",
    "sg:tags":[
        "establishment"
    ],
    "wof:name":"Harold Jones Enterprises",
    "wof:placetype":"venue"
},
  "geometry": {"coordinates":[-70.465468,43.882351],"type":"Point"}
}