{
  "type": "Feature",
  "properties": {
    "iso:country":"US",
    "sg:address":"7 C St",
    "sg:city":"Portland",
    "sg:classifiers":[
        {
            "category":"Building & Trades",
            "subcategory":"Electrical",
            "type":"Services"
        }
    ],
    "sg:phone":"+1 207 761 2446",
    "sg:postcode":"04102",
    "sg:province":"ME",
    "sg:tags":[
        "electric",
        "contractor"
    ],
    "sg:website":"www.laplanteelectric.com",
    "wof:name":"LA Plante Electronics",
    "wof:placetype":"venue"
},
  "geometry": {"coordinates":[-70.278639,43.651264],"type":"Point"}
}