{
  "type": "Feature",
  "properties": {
    "iso:country":"US",
    "sg:address":"111 Washington Ave",
    "sg:city":"Portland",
    "sg:classifiers":[
        {
            "category":"Professional",
            "type":"Services"
        }
    ],
    "sg:phone":"+1 207 791 5000",
    "sg:postcode":"04101",
    "sg:province":"ME",
    "wof:name":"Splitrock Prodigy Svc",
    "wof:placetype":"venue"
},
  "geometry": {"coordinates":[-70.253054,43.667262],"type":"Point"}
}