{
  "type": "Feature",
  "properties": {
    "addr:full":"235 Eastern Ave Springfield ME 01109",
    "addr:housenumber":"235",
    "addr:postcode":"01109",
    "addr:street":"Eastern Ave",
    "iso:country":"US",
    "sg:address":"235 Eastern Ave",
    "sg:city":"Springfield",
    "sg:classifiers":[
        {
            "category":"Organizations",
            "subcategory":"Religious Organization",
            "type":"Services"
        }
    ],
    "sg:phone":"+1 413 788 9790",
    "sg:postcode":"01109",
    "sg:province":"ME",
    "sg:tags":[
        "church"
    ],
    "wof:name":"Black Catholic Apostolate",
    "wof:placetype":"venue"
},
  "geometry": {"coordinates":[-72.56285699999999,42.10541],"type":"Point"}
}