{
  "type": "Feature",
  "properties": {
    "iso:country":"US",
    "sg:address":"103 Pleasant St",
    "sg:city":"Brunswick",
    "sg:classifiers":[
        {
            "category":"Wholesale",
            "subcategory":"Machinery & Supplies",
            "type":"Manufacturing & Wholesale Goods"
        }
    ],
    "sg:phone":"+1 207 729 3811",
    "sg:postcode":"04011",
    "sg:province":"ME",
    "sg:tags":[
        "vacuum",
        "system",
        "cleaning"
    ],
    "wof:name":"Electrolux Corp",
    "wof:placetype":"venue"
},
  "geometry": {"coordinates":[-69.978438,43.912762],"type":"Point"}
}