{
  "type": "Feature",
  "properties": {
    "iso:country":"US",
    "sg:address":"25 Pleasant St",
    "sg:city":"Dover Foxcroft",
    "sg:classifiers":[
        {
            "category":"Education",
            "subcategory":"Special Training",
            "type":"Public Place"
        }
    ],
    "sg:phone":"+1 207 564 5168",
    "sg:postcode":"04426",
    "sg:province":"ME",
    "sg:tags":[
        "instruction",
        "music"
    ],
    "wof:name":"Buie School Of Music",
    "wof:placetype":"venue"
},
  "geometry": {"coordinates":[-69.226499,45.182869],"type":"Point"}
}