{
  "type": "Feature",
  "properties": {
    "addr:full":"14 Yarmouth Junction Yarmouth ME 04096",
    "addr:housenumber":"14",
    "addr:postcode":"04096",
    "iso:country":"US",
    "sg:address":"14 Yarmouth Junction",
    "sg:city":"Yarmouth",
    "sg:classifiers":[
        {
            "category":"Wholesale",
            "subcategory":"Medical Equipment & Supplies",
            "type":"Manufacturing & Wholesale Goods"
        }
    ],
    "sg:phone":"+1 207 846 8543",
    "sg:postcode":"04096",
    "sg:province":"ME",
    "sg:tags":[
        "hospital"
    ],
    "sg:website":"www.apria.com",
    "wof:name":"Apria Healthcare",
    "wof:placetype":"venue"
},
  "geometry": {"coordinates":[-70.19105,43.813657],"type":"Point"}
}