{
  "type": "Feature",
  "properties": {
    "iso:country":"US",
    "sg:address":"9 Rainbow Ln",
    "sg:city":"Gorham",
    "sg:classifiers":[
        {
            "category":"Professional",
            "subcategory":"Computer Services",
            "type":"Services"
        }
    ],
    "sg:phone":"+1 207 892 5148",
    "sg:postcode":"04038",
    "sg:province":"ME",
    "sg:tags":[
        "prepackaged",
        "software"
    ],
    "wof:name":"Sebago Software Inc",
    "wof:placetype":"venue"
},
  "geometry": {"coordinates":[-70.456038,43.801831],"type":"Point"}
}