{
  "type": "Feature",
  "properties": {
    "addr:full":"150 Broadway Rockland ME 04841",
    "addr:housenumber":"150",
    "addr:postcode":"04841",
    "addr:street":"Broadway",
    "iso:country":"US",
    "sg:address":"150 Broadway",
    "sg:city":"Rockland",
    "sg:classifiers":[
        {
            "category":"Organizations",
            "subcategory":"Religious Organization",
            "type":"Services"
        }
    ],
    "sg:phone":"+1 207 594 4322",
    "sg:postcode":"04841",
    "sg:province":"ME",
    "sg:tags":[
        "church"
    ],
    "wof:name":"St Bernard's Church",
    "wof:placetype":"venue"
},
  "geometry": {"coordinates":[-69.118061,44.102132],"type":"Point"}
}