{
  "type": "Feature",
  "properties": {
    "iso:country":"US",
    "sg:address":"270 Main St",
    "sg:city":"Saco",
    "sg:classifiers":[
        {
            "category":"Banks & Credit Unions",
            "subcategory":"Bank",
            "type":"Services"
        }
    ],
    "sg:phone":"+1 207 282 9210",
    "sg:postcode":"04072",
    "sg:province":"ME",
    "sg:tags":[
        "state",
        "commercial",
        "mortgage"
    ],
    "wof:name":"Pepperell Bank & Trust",
    "wof:placetype":"venue"
},
  "geometry": {"coordinates":[-70.438,43.506018],"type":"Point"}
}