{
  "type": "Feature",
  "properties": {
    "iso:country":"US",
    "sg:address":"598 Elm St",
    "sg:city":"Biddeford",
    "sg:classifiers":[
        {
            "category":"Wholesale",
            "subcategory":"Construction Materials",
            "type":"Manufacturing & Wholesale Goods"
        }
    ],
    "sg:phone":"+1 207 283 8988",
    "sg:postcode":"04005",
    "sg:province":"ME",
    "sg:tags":[
        "fence"
    ],
    "sg:website":"www.bensflooring.com",
    "wof:name":"Ben Beaulieu & Son Inc",
    "wof:placetype":"venue"
},
  "geometry": {"coordinates":[-70.488757,43.465553],"type":"Point"}
}