{
  "type": "Feature",
  "properties": {
    "addr:full":"1 Game Farm Rd Gray ME 04039",
    "addr:housenumber":"1",
    "addr:postcode":"04039",
    "addr:street":"Game Farm Rd",
    "iso:country":"US",
    "sg:address":"1 Game Farm Rd",
    "sg:city":"Gray",
    "sg:classifiers":[
        {
            "category":"Government",
            "subcategory":"Police Station",
            "type":"Public Place"
        }
    ],
    "sg:phone":"+1 207 657 5710",
    "sg:postcode":"04039",
    "sg:province":"ME",
    "sg:tags":[
        "polygraph",
        "unit"
    ],
    "wof:name":"Public Safety Maine Department",
    "wof:placetype":"venue"
},
  "geometry": {"coordinates":[-70.351677,43.926466],"type":"Point"}
}