{
  "type": "Feature",
  "properties": {
    "iso:country":"US",
    "sg:address":"17 Sequoia Dr",
    "sg:city":"Freeport",
    "sg:classifiers":[
        {
            "category":"Professional",
            "subcategory":"Business Services",
            "type":"Services"
        }
    ],
    "sg:phone":"+1 207 865 2187",
    "sg:postcode":"04032",
    "sg:province":"ME",
    "sg:tags":[
        "transcribing",
        "disc"
    ],
    "wof:name":"Casco Bay Transcription",
    "wof:placetype":"venue"
},
  "geometry": {"coordinates":[-70.16072200000001,43.834275],"type":"Point"}
}