{
  "type": "Feature",
  "properties": {
    "iso:country":"US",
    "sg:address":"27 Adams Dr",
    "sg:city":"Kittery",
    "sg:classifiers":[
        {
            "category":"Building & Trades",
            "subcategory":"Cleaning & Sanitation",
            "type":"Services"
        }
    ],
    "sg:phone":"+1 207 439 5567",
    "sg:postcode":"03904",
    "sg:province":"ME",
    "sg:tags":[
        "maintenance"
    ],
    "wof:name":"ABC Cleaning Co",
    "wof:placetype":"venue"
},
  "geometry": {"coordinates":[-70.738578,43.108239],"type":"Point"}
}