{
  "type": "Feature",
  "properties": {
    "addr:full":"67 Elm St Somersworth ME 03878",
    "addr:housenumber":"67",
    "addr:postcode":"03878",
    "addr:street":"Elm St",
    "iso:country":"US",
    "sg:address":"67 Elm St",
    "sg:city":"Somersworth",
    "sg:classifiers":[
        {
            "category":"Travel",
            "subcategory":"Hotels & Motels",
            "type":"Entertainment"
        }
    ],
    "sg:phone":"+1 603 692 4374",
    "sg:postcode":"03878",
    "sg:province":"ME",
    "sg:tags":[
        "operation"
    ],
    "wof:name":"Somersworth Hotel",
    "wof:placetype":"venue"
},
  "geometry": {"coordinates":[-70.863488,43.260435],"type":"Point"}
}