{
  "type": "Feature",
  "properties": {
    "addr:full":"2 China Rd Winslow ME 04901",
    "addr:housenumber":"2",
    "addr:postcode":"04901",
    "addr:street":"China Rd",
    "iso:country":"US",
    "sg:address":"2 China Rd",
    "sg:city":"Winslow",
    "sg:classifiers":[
        {
            "category":"Professional",
            "subcategory":"Computer Services",
            "type":"Services"
        }
    ],
    "sg:phone":"+1 207 861 5611",
    "sg:postcode":"04901",
    "sg:province":"ME",
    "sg:tags":[
        "internet"
    ],
    "wof:name":"Maine Internetworks Inc",
    "wof:placetype":"venue"
},
  "geometry": {"coordinates":[-69.62640399999999,44.53723],"type":"Point"}
}