{
  "type": "Feature",
  "properties": {
    "iso:country":"US",
    "sg:address":"455 US Hwy 1",
    "sg:city":"Steuben",
    "sg:classifiers":[
        {
            "category":"Restaurant",
            "type":"Food & Drink"
        }
    ],
    "sg:phone":"+1 207 546 3422",
    "sg:postcode":"04680",
    "sg:province":"ME",
    "wof:name":"Mathews Country Store",
    "wof:placetype":"venue"
},
  "geometry": {"coordinates":[-67.944609,44.508882],"type":"Point"}
}