{
  "type": "Feature",
  "properties": {
    "addr:full":"151 Howe Rd Whitefield ME 04353",
    "addr:housenumber":"151",
    "addr:postcode":"04353",
    "addr:street":"Howe Rd",
    "iso:country":"US",
    "sg:address":"151 Howe Rd",
    "sg:city":"Whitefield",
    "sg:classifiers":[
        {
            "category":"Professional",
            "subcategory":"Engineering",
            "type":"Services"
        }
    ],
    "sg:phone":"+1 207 549 7000",
    "sg:postcode":"04353",
    "sg:province":"ME",
    "sg:tags":[
        "engineer"
    ],
    "wof:name":"Dirigo Environmental Consultan",
    "wof:placetype":"venue"
},
  "geometry": {"coordinates":[-69.582005,44.246767],"type":"Point"}
}