{
  "type": "Feature",
  "properties": {
    "addr:full":"222 Highland Ave Millinocket ME 04462",
    "addr:housenumber":"222",
    "addr:postcode":"04462",
    "addr:street":"Highland Ave",
    "iso:country":"US",
    "sg:address":"222 Highland Ave",
    "sg:city":"Millinocket",
    "sg:phone":"+1 207 723 4297",
    "sg:postcode":"04462",
    "sg:province":"ME",
    "sg:tags":[
        "oil"
    ],
    "wof:name":"Bragdon Energy Svc",
    "wof:placetype":"venue"
},
  "geometry": {"coordinates":[-68.711331,45.663644],"type":"Point"}
}