{
  "type": "Feature",
  "properties": {
    "addr:full":"13 N Main St Pittsfield ME 04967",
    "addr:housenumber":"13",
    "addr:postcode":"04967",
    "addr:street":"N Main St",
    "iso:country":"US",
    "sg:address":"13 N Main St",
    "sg:city":"Pittsfield",
    "sg:classifiers":[
        {
            "category":"Food & Beverages",
            "subcategory":"Groceries & Convenience Stores",
            "type":"Retail Goods"
        }
    ],
    "sg:phone":"+1 207 487 5980",
    "sg:postcode":"04967",
    "sg:province":"ME",
    "sg:tags":[
        "grocer"
    ],
    "wof:name":"Corner Cupboard",
    "wof:placetype":"venue"
},
  "geometry": {"coordinates":[-69.37996699999999,44.789159],"type":"Point"}
}