{
  "type": "Feature",
  "properties": {
    "iso:country":"US",
    "sg:address":"81 Main St",
    "sg:city":"Gorham",
    "sg:classifiers":[
        {
            "category":"Personal",
            "subcategory":"Beauty Salon",
            "type":"Services"
        }
    ],
    "sg:phone":"+1 207 839 2100",
    "sg:postcode":"04038",
    "sg:province":"ME",
    "wof:name":"Village Hair",
    "wof:placetype":"venue"
},
  "geometry": {"coordinates":[-70.441991,43.680114],"type":"Point"}
}