{
  "type": "Feature",
  "properties": {
    "iso:country":"US",
    "sg:address":"886 Dover Rd",
    "sg:city":"Charleston",
    "sg:classifiers":[
        {
            "category":"Shopping",
            "subcategory":"Florist",
            "type":"Retail Goods"
        }
    ],
    "sg:phone":"+1 207 285 7022",
    "sg:postcode":"04422",
    "sg:province":"ME",
    "wof:name":"Touch Of Whimsy",
    "wof:placetype":"venue"
},
  "geometry": {"coordinates":[-69.067989,45.066731],"type":"Point"}
}