{
  "type": "Feature",
  "properties": {
    "addr:full":"14 Crystal Ln Windham ME 04062",
    "addr:housenumber":"14",
    "addr:postcode":"04062",
    "addr:street":"Crystal Ln",
    "iso:country":"US",
    "sg:address":"14 Crystal Ln",
    "sg:city":"Windham",
    "sg:classifiers":[
        {
            "category":"Personal",
            "subcategory":"Beauty Salon",
            "type":"Services"
        }
    ],
    "sg:phone":"+1 207 892 8886",
    "sg:postcode":"04062",
    "sg:province":"ME",
    "wof:name":"Advance Innovations Hair Salon",
    "wof:placetype":"venue"
},
  "geometry": {"coordinates":[-70.397772,43.768872],"type":"Point"}
}