{
  "type": "Feature",
  "properties": {
    "iso:country":"US",
    "sg:address":"9 Miller Ave",
    "sg:city":"Parsonsfield",
    "sg:classifiers":[
        {
            "category":"Manufacturing",
            "subcategory":"Textiles",
            "type":"Manufacturing & Wholesale Goods"
        }
    ],
    "sg:phone":"+1 207 625 3267",
    "sg:postcode":"04005",
    "sg:province":"ME",
    "sg:tags":[
        "woolen",
        "mills"
    ],
    "wof:name":"Kezar Falls Woolen Co",
    "wof:placetype":"venue"
},
  "geometry": {"coordinates":[-70.444606,43.489223],"type":"Point"}
}