{
  "type": "Feature",
  "properties": {
    "addr:full":"293 Wilson St Brewer ME 04412",
    "addr:housenumber":"293",
    "addr:postcode":"04412",
    "addr:street":"Wilson St",
    "iso:country":"US",
    "sg:address":"293 Wilson St",
    "sg:city":"Brewer",
    "sg:classifiers":[
        {
            "category":"Social Services",
            "subcategory":"Child Care",
            "type":"Services"
        }
    ],
    "sg:phone":"+1 207 989 4348",
    "sg:postcode":"04412",
    "sg:province":"ME",
    "wof:name":"ABC Preschool & Child Care",
    "wof:placetype":"venue"
},
  "geometry": {"coordinates":[-68.758194,44.789104],"type":"Point"}
}