{
  "type": "Feature",
  "properties": {
    "addr:full":"50 Mona Rd Portland ME 04103",
    "addr:housenumber":"50",
    "addr:postcode":"04103",
    "addr:street":"Mona Rd",
    "iso:country":"US",
    "sg:address":"50 Mona Rd",
    "sg:city":"Portland",
    "sg:classifiers":[
        {
            "category":"Retail",
            "subcategory":"Repair Shop",
            "type":"Services"
        }
    ],
    "sg:phone":"+1 207 797 7281",
    "sg:postcode":"04103",
    "sg:province":"ME",
    "wof:name":"S & L Upholstery Inc",
    "wof:placetype":"venue"
},
  "geometry": {"coordinates":[-70.287567,43.695871],"type":"Point"}
}