{
  "type": "Feature",
  "properties": {
    "addr:full":"70 High St Limestone ME 04750",
    "addr:housenumber":"70",
    "addr:postcode":"04750",
    "addr:street":"High St",
    "iso:country":"US",
    "sg:address":"70 High St",
    "sg:city":"Limestone",
    "sg:classifiers":[
        {
            "category":"Organizations",
            "subcategory":"Religious Organization",
            "type":"Services"
        }
    ],
    "sg:phone":"+1 207 325 4436",
    "sg:postcode":"04750",
    "sg:province":"ME",
    "sg:tags":[
        "church"
    ],
    "wof:name":"Conservative Baptist Church",
    "wof:placetype":"venue"
},
  "geometry": {"coordinates":[-67.82772799999999,46.907668],"type":"Point"}
}