{
  "type": "Feature",
  "properties": {
    "addr:full":"28 Perkins Rd Mechanic Falls ME 04256",
    "addr:housenumber":"28",
    "addr:postcode":"04256",
    "addr:street":"Perkins Rd",
    "iso:country":"US",
    "sg:address":"28 Perkins Rd",
    "sg:city":"Mechanic Falls",
    "sg:classifiers":[
        {
            "category":"Professional",
            "subcategory":"Accounting & Tax Preparation",
            "type":"Services"
        }
    ],
    "sg:phone":"+1 207 345 3789",
    "sg:postcode":"04256",
    "sg:province":"ME",
    "wof:name":"At Your Service Bookkeeping",
    "wof:placetype":"venue"
},
  "geometry": {"coordinates":[-70.41099800000001,44.101457],"type":"Point"}
}