{
  "type": "Feature",
  "properties": {
    "iso:country":"US",
    "sg:address":"156 State St",
    "sg:city":"Bangor",
    "sg:classifiers":[
        {
            "category":"Wholesale",
            "subcategory":"Electrical",
            "type":"Manufacturing & Wholesale Goods"
        }
    ],
    "sg:phone":"+1 207 942 0171",
    "sg:postcode":"04401",
    "sg:province":"ME",
    "sg:tags":[
        "control",
        "security",
        "system"
    ],
    "wof:name":"Northeast Burglar & Fire Alarm",
    "wof:placetype":"venue"
},
  "geometry": {"coordinates":[-68.76409200000001,44.804444],"type":"Point"}
}