{
  "type": "Feature",
  "properties": {
    "addr:full":"2115 Union St Bangor ME 04401",
    "addr:housenumber":"2115",
    "addr:postcode":"04401",
    "addr:street":"Union St",
    "iso:country":"US",
    "sg:address":"2115 Union St",
    "sg:city":"Bangor",
    "sg:classifiers":[
        {
            "category":"Manufacturing",
            "subcategory":"Pottery",
            "type":"Manufacturing & Wholesale Goods"
        }
    ],
    "sg:phone":"+1 207 942 9013",
    "sg:postcode":"04401",
    "sg:province":"ME",
    "sg:tags":[
        "product",
        "mfg"
    ],
    "wof:name":"Hendersons Redware",
    "wof:placetype":"venue"
},
  "geometry": {"coordinates":[-68.84930799999999,44.836151],"type":"Point"}
}