{
  "type": "Feature",
  "properties": {
    "addr:full":"33 Davis St Presque Isle ME 04769",
    "addr:housenumber":"33",
    "addr:postcode":"04769",
    "addr:street":"Davis St;Isle",
    "iso:country":"US",
    "sg:address":"33 Davis St",
    "sg:city":"Presque Isle",
    "sg:classifiers":[
        {
            "category":"Professional",
            "subcategory":"Lawyer & Legal Services",
            "type":"Services"
        }
    ],
    "sg:phone":"+1 207 764 4883",
    "sg:postcode":"04769",
    "sg:province":"ME",
    "sg:website":"www.mainelse.org",
    "wof:name":"Legal Services For The Elderly",
    "wof:placetype":"venue"
},
  "geometry": {"coordinates":[-68.008933,46.690774],"type":"Point"}
}