{
  "type": "Feature",
  "properties": {
    "iso:country":"US",
    "sg:address":"1437 Poland Springs Rd",
    "sg:city":"Casco",
    "sg:classifiers":[
        {
            "category":"Education",
            "subcategory":"School",
            "type":"Public Place"
        }
    ],
    "sg:phone":"+1 207 627 4291",
    "sg:postcode":"04015",
    "sg:province":"ME",
    "wof:name":"Crooked River Elementary Schl",
    "wof:placetype":"venue"
},
  "geometry": {"coordinates":[-70.563054,43.979575],"type":"Point"}
}