{
  "type": "Feature",
  "properties": {
    "addr:full":"127 Bennett Dr Caribou ME 04736",
    "addr:housenumber":"127",
    "addr:postcode":"04736",
    "addr:street":"Bennett Dr",
    "iso:country":"US",
    "sg:address":"127 Bennett Dr",
    "sg:city":"Caribou",
    "sg:classifiers":[
        {
            "category":"Restaurant",
            "type":"Food & Drink"
        }
    ],
    "sg:menulink":"http://www.allmenus.com/me/caribou/215779-mcdonalds/menu/",
    "sg:postcode":"04736",
    "sg:province":"ME",
    "sg:tags":[
        "burger",
        "american"
    ],
    "wof:name":"McDonald's",
    "wof:placetype":"venue"
},
  "geometry": {"coordinates":[-68.00396600000001,46.869272],"type":"Point"}
}