{
  "type": "Feature",
  "properties": {
    "addr:full":"432 Winthrop Rd Winthrop ME 04355",
    "addr:housenumber":"432",
    "addr:postcode":"04355",
    "addr:street":"Winthrop Rd",
    "iso:country":"US",
    "sg:address":"432 Winthrop Rd",
    "sg:city":"Winthrop",
    "sg:classifiers":[
        {
            "category":"Retail",
            "subcategory":"Repair Shop",
            "type":"Services"
        }
    ],
    "sg:phone":"+1 207 395 2180",
    "sg:postcode":"04355",
    "sg:province":"ME",
    "wof:name":"Neills Outboard",
    "wof:placetype":"venue"
},
  "geometry": {"coordinates":[-69.970849,44.360533],"type":"Point"}
}