{
  "type": "Feature",
  "properties": {
    "iso:country":"US",
    "sg:address":"82 Birch St",
    "sg:city":"Biddeford",
    "sg:classifiers":[
        {
            "category":"Shopping",
            "subcategory":"Discount & Variety Stores",
            "type":"Retail Goods"
        }
    ],
    "sg:phone":"+1 207 283 1197",
    "sg:postcode":"04005",
    "sg:province":"ME",
    "wof:name":"Dave's Variety & Sandwich Shop",
    "wof:placetype":"venue"
},
  "geometry": {"coordinates":[-70.455244,43.488172],"type":"Point"}
}