{
  "type": "Feature",
  "properties": {
    "iso:country":"US",
    "sg:address":"280 Riverside Dr",
    "sg:city":"Augusta",
    "sg:classifiers":[
        {
            "category":"Personal",
            "subcategory":"Beauty Salon",
            "type":"Services"
        }
    ],
    "sg:phone":"+1 207 623 1846",
    "sg:postcode":"04330",
    "sg:province":"ME",
    "wof:name":"Mary's Golden Shears Salon",
    "wof:placetype":"venue"
},
  "geometry": {"coordinates":[-69.759313,44.335391],"type":"Point"}
}