{
  "type": "Feature",
  "properties": {
    "iso:country":"US",
    "sg:address":"2243 Camden Rd",
    "sg:city":"Warren",
    "sg:classifiers":[
        {
            "category":"Autos & Motor Vehicles",
            "subcategory":"Recreational Vehicle Sales",
            "type":"Retail Goods"
        }
    ],
    "sg:phone":"+1 207 273 3780",
    "sg:postcode":"04864",
    "sg:province":"ME",
    "sg:tags":[
        "parts",
        "trailer"
    ],
    "sg:website":"www.on-the-road.net",
    "wof:name":"On The Road Inc",
    "wof:placetype":"venue"
},
  "geometry": {"coordinates":[-69.199542,44.145361],"type":"Point"}
}