{
  "type": "Feature",
  "properties": {
    "iso:country":"US",
    "sg:address":"715 Benton Ave",
    "sg:city":"Winslow",
    "sg:classifiers":[
        {
            "category":"Food & Beverages",
            "subcategory":"Meat & Fish",
            "type":"Retail Goods"
        }
    ],
    "sg:phone":"+1 207 873 3671",
    "sg:postcode":"04901",
    "sg:province":"ME",
    "wof:name":"Boucher's Meat",
    "wof:placetype":"venue"
},
  "geometry": {"coordinates":[-69.597893,44.574666],"type":"Point"}
}