{
  "type": "Feature",
  "properties": {
    "iso:country":"US",
    "sg:address":"550 Center St",
    "sg:city":"Auburn",
    "sg:classifiers":[
        {
            "category":"Health Services",
            "subcategory":"Optometrist",
            "type":"Services"
        }
    ],
    "sg:phone":"+1 207 782 5030",
    "sg:postcode":"04210",
    "sg:province":"ME",
    "sg:website":"www.auburnmall.com",
    "wof:name":"Auburn Mall Eye Care",
    "wof:placetype":"venue"
},
  "geometry": {"coordinates":[-70.225247,44.121472],"type":"Point"}
}