{
  "type": "Feature",
  "properties": {
    "iso:country":"US",
    "sg:address":"137 Valley Rd",
    "sg:city":"Raymond",
    "sg:classifiers":[
        {
            "category":"Building & Trades",
            "subcategory":"Landscaping Services",
            "type":"Services"
        }
    ],
    "sg:phone":"+1 207 655 2578",
    "sg:postcode":"04071",
    "sg:province":"ME",
    "sg:tags":[
        "landscape",
        "contractor"
    ],
    "wof:name":"Dwayne Buzzell Excavation",
    "wof:placetype":"venue"
},
  "geometry": {"coordinates":[-70.419282,43.957635],"type":"Point"}
}