{
  "type": "Feature",
  "properties": {
    "iso:country":"US",
    "sg:address":"107 Maine Ave",
    "sg:city":"Bangor",
    "sg:classifiers":[
        {
            "category":"Education",
            "subcategory":"College",
            "type":"Public Place"
        }
    ],
    "sg:phone":"+1 207 973 3200",
    "sg:postcode":"04401",
    "sg:province":"ME",
    "sg:tags":[
        "academic",
        "school"
    ],
    "wof:name":"University Of Maine Systems",
    "wof:placetype":"venue"
},
  "geometry": {"coordinates":[-68.8192,44.81704],"type":"Point"}
}