{
  "type": "Feature",
  "properties": {
    "addr:full":"256 Main St Bingham ME 04901",
    "addr:housenumber":"256",
    "addr:postcode":"04901",
    "addr:street":"Main St",
    "iso:country":"US",
    "sg:address":"256 Main St",
    "sg:city":"Bingham",
    "sg:classifiers":[
        {
            "category":"Wholesale",
            "subcategory":"Scrap",
            "type":"Manufacturing & Wholesale Goods"
        }
    ],
    "sg:phone":"+1 207 672 4963",
    "sg:postcode":"04901",
    "sg:province":"ME",
    "sg:tags":[
        "recycling",
        "center"
    ],
    "wof:name":"Valley Redemption",
    "wof:placetype":"venue"
},
  "geometry": {"coordinates":[-69.633511,44.559371],"type":"Point"}
}