{
  "type": "Feature",
  "properties": {
    "addr:full":"146 Fern St Bangor ME 04401",
    "addr:housenumber":"146",
    "addr:postcode":"04401",
    "addr:street":"Fern St",
    "iso:country":"US",
    "sg:address":"146 Fern St",
    "sg:city":"Bangor",
    "sg:classifiers":[
        {
            "category":"Building & Trades",
            "subcategory":"Electrical",
            "type":"Services"
        }
    ],
    "sg:phone":"+1 207 942 8393",
    "sg:postcode":"04401",
    "sg:province":"ME",
    "sg:tags":[
        "electric",
        "contractor"
    ],
    "wof:name":"Vance's Electric Svc",
    "wof:placetype":"venue"
},
  "geometry": {"coordinates":[-68.75919500000001,44.812501],"type":"Point"}
}