{
  "type": "Feature",
  "properties": {
    "addr:full":"3 Maple St Camden ME 04843",
    "addr:housenumber":"3",
    "addr:postcode":"04843",
    "addr:street":"Maple St",
    "iso:country":"US",
    "sg:address":"3 Maple St",
    "sg:city":"Camden",
    "sg:classifiers":[
        {
            "category":"Personal",
            "subcategory":"Beauty Salon",
            "type":"Services"
        }
    ],
    "sg:phone":"+1 207 236 3876",
    "sg:postcode":"04843",
    "sg:province":"ME",
    "sg:tags":[
        "shop"
    ],
    "wof:name":"Silver Scissors",
    "wof:placetype":"venue"
},
  "geometry": {"coordinates":[-69.073087,44.208316],"type":"Point"}
}