{
  "type": "Feature",
  "properties": {
    "iso:country":"US",
    "sg:address":"262 Brewer Lake Rd",
    "sg:city":"Orrington",
    "sg:classifiers":[
        {
            "category":"Building & Trades",
            "subcategory":"Construction",
            "type":"Services"
        }
    ],
    "sg:phone":"+1 207 989 7820",
    "sg:postcode":"04474",
    "sg:province":"ME",
    "sg:tags":[
        "boring",
        "drilling",
        "contractor"
    ],
    "sg:website":"www.maintest.com",
    "wof:name":"Maine Test Borings Inc",
    "wof:placetype":"venue"
},
  "geometry": {"coordinates":[-68.767007,44.748065],"type":"Point"}
}