{
  "type": "Feature",
  "properties": {
    "iso:country":"US",
    "sg:address":"394 Lakewood Rd",
    "sg:city":"Madison",
    "sg:classifiers":[
        {
            "category":"Shopping",
            "subcategory":"Computers & Home Electronics",
            "type":"Retail Goods"
        }
    ],
    "sg:phone":"+1 207 858 4321",
    "sg:postcode":"04979",
    "sg:province":"ME",
    "wof:name":"Kirbys Karaoke Shop",
    "wof:placetype":"venue"
},
  "geometry": {"coordinates":[-69.834785,44.930621],"type":"Point"}
}