{
  "type": "Feature",
  "properties": {
    "addr:full":"335 Water St Augusta ME 04330",
    "addr:housenumber":"335",
    "addr:postcode":"04330",
    "addr:street":"Water St",
    "iso:country":"US",
    "sg:address":"335 Water St",
    "sg:city":"Augusta",
    "sg:classifiers":[
        {
            "category":"Organizations",
            "subcategory":"Non-profit Organization",
            "type":"Services"
        }
    ],
    "sg:phone":"+1 207 621 6388",
    "sg:postcode":"04330",
    "sg:province":"ME",
    "wof:name":"Capital Kids/Augusta Community",
    "wof:placetype":"venue"
},
  "geometry": {"coordinates":[-69.774647,44.313807],"type":"Point"}
}