{
  "type": "Feature",
  "properties": {
    "addr:full":"181 High St Portland ME 04101",
    "addr:housenumber":"181",
    "addr:postcode":"04101",
    "addr:street":"High St",
    "iso:country":"US",
    "sg:address":"181 High St",
    "sg:city":"Portland",
    "sg:classifiers":[
        {
            "category":"Real Estate",
            "subcategory":"Real Estate Agent",
            "type":"Services"
        }
    ],
    "sg:phone":"+1 207 761 1568",
    "sg:postcode":"04101",
    "sg:province":"ME",
    "wof:name":"Gateway Parking Garage",
    "wof:placetype":"venue"
},
  "geometry": {"coordinates":[-70.264977,43.655233],"type":"Point"}
}