{
  "type": "Feature",
  "properties": {
    "addr:full":"19 Elliot St Thomaston ME 04861",
    "addr:housenumber":"19",
    "addr:postcode":"04861",
    "addr:street":"Elliot St",
    "iso:country":"US",
    "sg:address":"19 Elliot St",
    "sg:city":"Thomaston",
    "sg:classifiers":[
        {
            "category":"Manufacturing",
            "subcategory":"Metals",
            "type":"Manufacturing & Wholesale Goods"
        }
    ],
    "sg:phone":"+1 207 594 7655",
    "sg:postcode":"04861",
    "sg:province":"ME",
    "wof:name":"Lyman-Morse Fabrication",
    "wof:placetype":"venue"
},
  "geometry": {"coordinates":[-69.183671,44.073964],"type":"Point"}
}