{
  "type": "Feature",
  "properties": {
    "iso:country":"US",
    "sg:address":"1 Bucknam Rd",
    "sg:city":"Falmouth",
    "sg:classifiers":[
        {
            "category":"Health Services",
            "subcategory":"Doctor",
            "type":"Services"
        }
    ],
    "sg:phone":"+1 207 781 1775",
    "sg:postcode":"04105",
    "sg:province":"ME",
    "sg:tags":[
        "physician",
        "surgeon"
    ],
    "wof:name":"Greater Portland Pediatrics",
    "wof:placetype":"venue"
},
  "geometry": {"coordinates":[-70.23125,43.725876],"type":"Point"}
}