{
  "type": "Feature",
  "properties": {
    "iso:country":"US",
    "sg:address":"320 Ferry Rd",
    "sg:city":"Saco",
    "sg:classifiers":[
        {
            "category":"Restaurant",
            "type":"Food & Drink"
        }
    ],
    "sg:phone":"+1 207 283 0045",
    "sg:postcode":"04072",
    "sg:province":"ME",
    "sg:tags":[
        "parlor",
        "ice",
        "cream"
    ],
    "wof:name":"Garside's Ice Cream Inc",
    "wof:placetype":"venue"
},
  "geometry": {"coordinates":[-70.405728,43.481566],"type":"Point"}
}