{
  "type": "Feature",
  "properties": {
    "addr:full":"667 Sawyer St South Portland ME 04106",
    "addr:housenumber":"667",
    "addr:postcode":"04106",
    "addr:street":"Sawyer St",
    "iso:country":"US",
    "sg:address":"667 Sawyer St",
    "sg:city":"South Portland",
    "sg:classifiers":[
        {
            "category":"Social Services",
            "subcategory":"Child Care",
            "type":"Services"
        }
    ],
    "sg:phone":"+1 207 767 1075",
    "sg:postcode":"04106",
    "sg:province":"ME",
    "sg:tags":[
        "day"
    ],
    "wof:name":"Cottage Road Neighborhood School",
    "wof:placetype":"venue"
},
  "geometry": {"coordinates":[-70.24285999999999,43.628205],"type":"Point"}
}