{
  "type": "Feature",
  "properties": {
    "addr:full":"36 Pleasant St Bangor ME 04401",
    "addr:housenumber":"36",
    "addr:postcode":"04401",
    "addr:street":"Pleasant St",
    "iso:country":"US",
    "sg:address":"36 Pleasant St",
    "sg:city":"Bangor",
    "sg:classifiers":[
        {
            "category":"Professional",
            "subcategory":"Accounting & Tax Preparation",
            "type":"Services"
        }
    ],
    "sg:phone":"+1 207 942 1600",
    "sg:postcode":"04401",
    "sg:province":"ME",
    "sg:tags":[
        "accountant"
    ],
    "wof:name":"Berry Dunn Mc Neil & Parker",
    "wof:placetype":"venue"
},
  "geometry": {"coordinates":[-68.77162800000001,44.796069],"type":"Point"}
}