{
  "type": "Feature",
  "properties": {
    "iso:country":"US",
    "sg:address":"288 Maine St",
    "sg:city":"Brunswick",
    "sg:classifiers":[
        {
            "category":"Organizations",
            "subcategory":"Religious Organization",
            "type":"Services"
        }
    ],
    "sg:phone":"+1 207 729 1045",
    "sg:postcode":"04011",
    "sg:province":"ME",
    "wof:name":"First Church Christ Scientist",
    "wof:placetype":"venue"
},
  "geometry": {"coordinates":[-69.966785,43.902757],"type":"Point"}
}