{
  "type": "Feature",
  "properties": {
    "iso:country":"US",
    "sg:address":"957 Union St",
    "sg:city":"Bangor",
    "sg:classifiers":[
        {
            "category":"Restaurant",
            "type":"Food & Drink"
        }
    ],
    "sg:phone":"+1 207 942 3430",
    "sg:postcode":"04401",
    "sg:province":"ME",
    "wof:name":"Nicky's Cruisin Diner",
    "wof:placetype":"venue"
},
  "geometry": {"coordinates":[-68.814714,44.819141],"type":"Point"}
}