{
  "type": "Feature",
  "properties": {
    "addr:full":"2435 Milton Mills Rd Acton ME 04001",
    "addr:housenumber":"2435",
    "addr:postcode":"04001",
    "addr:street":"Milton Mills Rd",
    "iso:country":"US",
    "sg:address":"2435 Milton Mills Rd",
    "sg:city":"Acton",
    "sg:classifiers":[
        {
            "category":"Education",
            "subcategory":"School",
            "type":"Public Place"
        }
    ],
    "sg:phone":"+1 207 477 2829",
    "sg:postcode":"04001",
    "sg:province":"ME",
    "wof:name":"Maplestone Farm",
    "wof:placetype":"venue"
},
  "geometry": {"coordinates":[-70.924328,43.493313],"type":"Point"}
}