{
  "type": "Feature",
  "properties": {
    "addr:full":"92 Oak St Bath ME 04530",
    "addr:housenumber":"92",
    "addr:postcode":"04530",
    "addr:street":"Oak St",
    "iso:country":"US",
    "sg:address":"92 Oak St",
    "sg:city":"Bath",
    "sg:classifiers":[
        {
            "category":"Education",
            "subcategory":"Dance Studio",
            "type":"Public Place"
        }
    ],
    "sg:phone":"+1 207 443 2956",
    "sg:postcode":"04530",
    "sg:province":"ME",
    "sg:tags":[
        "instruction",
        "dancing"
    ],
    "wof:name":"Fay Pye's Dance Studio",
    "wof:placetype":"venue"
},
  "geometry": {"coordinates":[-69.81869,43.916857],"type":"Point"}
}