{
  "type": "Feature",
  "properties": {
    "addr:full":"128 State St Augusta ME 04330",
    "addr:housenumber":"128",
    "addr:postcode":"04330",
    "addr:street":"State St",
    "iso:country":"US",
    "sg:address":"128 State St",
    "sg:city":"Augusta",
    "sg:classifiers":[
        {
            "category":"Professional",
            "subcategory":"Lawyer & Legal Services",
            "type":"Services"
        }
    ],
    "sg:phone":"+1 207 622 1918",
    "sg:postcode":"04330",
    "sg:province":"ME",
    "sg:tags":[
        "attorney"
    ],
    "wof:name":"P J Perrino Jr Law Offices",
    "wof:placetype":"venue"
},
  "geometry": {"coordinates":[-69.77843,44.313213],"type":"Point"}
}