{
  "type": "Feature",
  "properties": {
    "iso:country":"US",
    "sg:address":"119 S Main St",
    "sg:city":"Auburn",
    "sg:classifiers":[
        {
            "category":"Social Services",
            "subcategory":"Child Care",
            "type":"Services"
        }
    ],
    "sg:phone":"+1 207 784 5359",
    "sg:postcode":"04210",
    "sg:province":"ME",
    "sg:tags":[
        "day"
    ],
    "wof:name":"Paula's Daycare",
    "wof:placetype":"venue"
},
  "geometry": {"coordinates":[-70.223644,44.08162],"type":"Point"}
}