{
  "type": "Feature",
  "properties": {
    "iso:country":"US",
    "sg:address":"9 Church St",
    "sg:city":"Hope",
    "sg:classifiers":[
        {
            "category":"Organizations",
            "subcategory":"Religious Organization",
            "type":"Services"
        }
    ],
    "sg:phone":"+1 207 763 4567",
    "sg:postcode":"04847",
    "sg:province":"ME",
    "wof:name":"Hope Community Bible Church",
    "wof:placetype":"venue"
},
  "geometry": {"coordinates":[-69.154384,44.268224],"type":"Point"}
}