{
  "type": "Feature",
  "properties": {
    "iso:country":"US",
    "sg:address":"35 Farwell Dr",
    "sg:city":"Rockland",
    "sg:classifiers":[
        {
            "category":"Freight",
            "type":"Transportation"
        }
    ],
    "sg:phone":"+1 207 596 6401",
    "sg:postcode":"04864",
    "sg:province":"ME",
    "sg:tags":[
        "commercial",
        "storage"
    ],
    "wof:name":"Swift Storage & Trailers",
    "wof:placetype":"venue"
},
  "geometry": {"coordinates":[-69.162383,44.16666],"type":"Point"}
}