{
  "type": "Feature",
  "properties": {
    "addr:full":"119 Main St Lincoln ME 04457",
    "addr:housenumber":"119",
    "addr:postcode":"04457",
    "addr:street":"Main St",
    "iso:country":"US",
    "sg:address":"119 Main St",
    "sg:city":"Lincoln",
    "sg:phone":"+1 207 794 8300",
    "sg:postcode":"04457",
    "sg:province":"ME",
    "sg:tags":[
        "oil"
    ],
    "wof:name":"Whitney Energy Inc",
    "wof:placetype":"venue"
},
  "geometry": {"coordinates":[-68.503123,45.365894],"type":"Point"}
}