{
  "type": "Feature",
  "properties": {
    "addr:full":"1451 Main St Oxford ME 04270",
    "addr:housenumber":"1451",
    "addr:postcode":"04270",
    "addr:street":"Main St",
    "iso:country":"US",
    "sg:address":"1451 Main St",
    "sg:city":"Oxford",
    "sg:classifiers":[
        {
            "category":"Shopping",
            "subcategory":"Used Merchandise",
            "type":"Retail Goods"
        }
    ],
    "sg:phone":"+1 207 743 9788",
    "sg:postcode":"04270",
    "sg:province":"ME",
    "sg:tags":[
        "antique"
    ],
    "wof:name":"KALL Us Antiques",
    "wof:placetype":"venue"
},
  "geometry": {"coordinates":[-70.51827,44.185624],"type":"Point"}
}