{
  "type": "Feature",
  "properties": {
    "addr:full":"1106 Van Buren Rd Caribou ME 04736",
    "addr:housenumber":"1106",
    "addr:postcode":"04736",
    "addr:street":"Van Buren Rd",
    "iso:country":"US",
    "sg:address":"1106 Van Buren Rd",
    "sg:city":"Caribou",
    "sg:classifiers":[
        {
            "category":"Retail",
            "subcategory":"Auto Repair",
            "type":"Services"
        }
    ],
    "sg:phone":"+1 207 498 6047",
    "sg:postcode":"04736",
    "sg:province":"ME",
    "sg:tags":[
        "exchanging",
        "engine",
        "general"
    ],
    "wof:name":"Caron & Son Engine Machine Shp",
    "wof:placetype":"venue"
},
  "geometry": {"coordinates":[-68.026951,46.953772],"type":"Point"}
}