{
  "type": "Feature",
  "properties": {
    "iso:country":"US",
    "sg:address":"37 Labbe Ave",
    "sg:city":"Lewiston",
    "sg:classifiers":[
        {
            "category":"Organizations",
            "subcategory":"Membership Organization",
            "type":"Services"
        }
    ],
    "sg:phone":"+1 207 783 0706",
    "sg:postcode":"04240",
    "sg:province":"ME",
    "wof:name":"Isadore Shapiro Scholarship",
    "wof:placetype":"venue"
},
  "geometry": {"coordinates":[-70.190274,44.08994],"type":"Point"}
}