{
  "type": "Feature",
  "properties": {
    "iso:country":"US",
    "sg:address":"298 Main St",
    "sg:city":"Jonesport",
    "sg:classifiers":[
        {
            "category":"Health Services",
            "subcategory":"Doctor",
            "type":"Services"
        }
    ],
    "sg:phone":"+1 207 497 3144",
    "sg:postcode":"04694",
    "sg:province":"ME",
    "sg:tags":[
        "physician",
        "surgeon"
    ],
    "wof:name":"Jonesport-Beals Family Clinic",
    "wof:placetype":"venue"
},
  "geometry": {"coordinates":[-67.316541,45.136065],"type":"Point"}
}