{
  "type": "Feature",
  "properties": {
    "addr:full":"180 Larrabee Rd Westbrook ME 04092",
    "addr:housenumber":"180",
    "addr:postcode":"04092",
    "addr:street":"Larrabee Rd",
    "iso:country":"US",
    "sg:address":"180 Larrabee Rd",
    "sg:city":"Westbrook",
    "sg:classifiers":[
        {
            "category":"Autos & Motor Vehicles",
            "subcategory":"Auto Supplies",
            "type":"Retail Goods"
        }
    ],
    "sg:phone":"+1 207 854 1141",
    "sg:postcode":"04092",
    "sg:province":"ME",
    "sg:tags":[
        "automobile",
        "parts"
    ],
    "wof:name":"Genuine Parts Co",
    "wof:placetype":"venue"
},
  "geometry": {"coordinates":[-70.33398099999999,43.678439],"type":"Point"}
}