{
  "type": "Feature",
  "properties": {
    "addr:full":"2 Delorme Dr Yarmouth ME 04096",
    "addr:housenumber":"2",
    "addr:postcode":"04096",
    "addr:street":"Delorme Dr",
    "iso:country":"US",
    "sg:address":"2 Delorme Dr",
    "sg:city":"Yarmouth",
    "sg:classifiers":[
        {
            "category":"Wholesale",
            "subcategory":"Stationery",
            "type":"Manufacturing & Wholesale Goods"
        }
    ],
    "sg:phone":"+1 207 846 7000",
    "sg:postcode":"04096",
    "sg:province":"ME",
    "sg:tags":[
        "map"
    ],
    "sg:website":"www.delormemapping.com",
    "wof:name":"Delorme Publishing Co",
    "wof:placetype":"venue"
},
  "geometry": {"coordinates":[-70.16151000000001,43.808285],"type":"Point"}
}