{
  "type": "Feature",
  "properties": {
    "addr:full":"486 Turner Center Rd Turner ME 04282",
    "addr:housenumber":"486",
    "addr:postcode":"04282",
    "addr:street":"Turner Center Rd",
    "iso:country":"US",
    "sg:address":"486 Turner Center Rd",
    "sg:city":"Turner",
    "sg:classifiers":[
        {
            "category":"Social Services",
            "subcategory":"Child Care",
            "type":"Services"
        }
    ],
    "sg:phone":"+1 207 225 3750",
    "sg:postcode":"04282",
    "sg:province":"ME",
    "wof:name":"Turner Primary Daycare",
    "wof:placetype":"venue"
},
  "geometry": {"coordinates":[-70.219675,44.271523],"type":"Point"}
}