{
  "type": "Feature",
  "properties": {
    "addr:full":"155 Dover Rd Charleston ME 04422",
    "addr:housenumber":"155",
    "addr:postcode":"04422",
    "addr:street":"Dover Rd",
    "iso:country":"US",
    "sg:address":"155 Dover Rd",
    "sg:city":"Charleston",
    "sg:classifiers":[
        {
            "category":"Social Services",
            "subcategory":"Child Care",
            "type":"Services"
        },
        {
            "category":"Education",
            "subcategory":"Special Training",
            "type":"Public Place"
        }
    ],
    "sg:phone":"+1 207 285 7982",
    "sg:postcode":"04422",
    "sg:province":"ME",
    "sg:tags":[
        "kindergarten",
        "academic",
        "school",
        "day"
    ],
    "wof:name":"Little House Daycare Center",
    "wof:placetype":"venue"
},
  "geometry": {"coordinates":[-69.05515699999999,45.050049],"type":"Point"}
}