{
  "type": "Feature",
  "properties": {
    "addr:full":"17 Ludlow Rd Houlton ME 04730",
    "addr:housenumber":"17",
    "addr:postcode":"04730",
    "addr:street":"Ludlow Rd",
    "iso:country":"US",
    "sg:address":"17 Ludlow Rd",
    "sg:city":"Houlton",
    "sg:classifiers":[
        {
            "category":"Utilities",
            "subcategory":"Mobile Phone",
            "type":"Services"
        }
    ],
    "sg:phone":"+1 207 521 0182",
    "sg:postcode":"04730",
    "sg:province":"ME",
    "sg:tags":[
        "telephone",
        "cellular"
    ],
    "wof:name":"US Cellular",
    "wof:placetype":"venue"
},
  "geometry": {"coordinates":[-67.840902,46.141703],"type":"Point"}
}