{
  "type": "Feature",
  "properties": {
    "addr:full":"120 Kenney Rd Leeds ME 04263",
    "addr:housenumber":"120",
    "addr:postcode":"04263",
    "addr:street":"Kenney Rd",
    "iso:country":"US",
    "sg:address":"120 Kenney Rd",
    "sg:city":"Leeds",
    "sg:classifiers":[
        {
            "category":"Insurance",
            "subcategory":"Hazard Insurance",
            "type":"Services"
        }
    ],
    "sg:phone":"+1 207 524 2176",
    "sg:postcode":"04263",
    "sg:province":"ME",
    "sg:tags":[
        "carrier",
        "surety"
    ],
    "wof:name":"Mortons Services",
    "wof:placetype":"venue"
},
  "geometry": {"coordinates":[-70.10556800000001,44.240278],"type":"Point"}
}