{
  "type": "Feature",
  "properties": {
    "iso:country":"US",
    "sg:address":"120 Kenney Rd",
    "sg:city":"Leeds",
    "sg:classifiers":[
        {
            "category":"Insurance",
            "subcategory":"Hazard Insurance",
            "type":"Services"
        }
    ],
    "sg:phone":"+1 207 524 2176",
    "sg:postcode":"04263",
    "sg:province":"ME",
    "sg:tags":[
        "carrier",
        "surety"
    ],
    "wof:name":"Mortons Services",
    "wof:placetype":"venue"
},
  "geometry": {"coordinates":[-70.105568,44.240278],"type":"Point"}
}