{
  "type": "Feature",
  "properties": {
    "iso:country":"US",
    "sg:address":"167 Black Point Rd",
    "sg:city":"Scarborough",
    "sg:classifiers":[
        {
            "category":"Organizations",
            "subcategory":"Religious Organization",
            "type":"Services"
        }
    ],
    "sg:phone":"+1 207 883 2342",
    "sg:postcode":"04074",
    "sg:province":"ME",
    "sg:tags":[
        "church"
    ],
    "sg:website":"www.fccscarborough.com",
    "wof:name":"First Congregational Church",
    "wof:placetype":"venue"
},
  "geometry": {"coordinates":[-70.320916,43.576282],"type":"Point"}
}