{
  "type": "Feature",
  "properties": {
    "addr:full":"316 E Main St Denmark ME 04096",
    "addr:housenumber":"316",
    "addr:postcode":"04096",
    "addr:street":"E Main St",
    "iso:country":"US",
    "sg:address":"316 E Main St",
    "sg:city":"Denmark",
    "sg:classifiers":[
        {
            "category":"Professional",
            "subcategory":"Secretarial Services",
            "type":"Services"
        }
    ],
    "sg:phone":"+1 207 452 2781",
    "sg:postcode":"04096",
    "sg:province":"ME",
    "sg:tags":[
        "reporting"
    ],
    "wof:name":"Denmark Small Business Service",
    "wof:placetype":"venue"
},
  "geometry": {"coordinates":[-70.17280700000001,43.808586],"type":"Point"}
}