{
  "type": "Feature",
  "properties": {
    "addr:full":"25 Main St Mexico ME 04257",
    "addr:housenumber":"25",
    "addr:postcode":"04257",
    "addr:street":"Main St",
    "iso:country":"US",
    "sg:address":"25 Main St",
    "sg:city":"Mexico",
    "sg:classifiers":[
        {
            "category":"Restaurant",
            "type":"Food & Drink"
        }
    ],
    "sg:phone":"+1 207 369 9448",
    "sg:postcode":"04257",
    "sg:province":"ME",
    "wof:name":"Covered Wagon Restaurant",
    "wof:placetype":"venue"
},
  "geometry": {"coordinates":[-70.545794,44.55591],"type":"Point"}
}