{
  "type": "Feature",
  "properties": {
    "iso:country":"US",
    "sg:address":"16 York St",
    "sg:city":"Portland",
    "sg:classifiers":[
        {
            "category":"Manufacturing",
            "subcategory":"Printing",
            "type":"Manufacturing & Wholesale Goods"
        }
    ],
    "sg:phone":"+1 207 773 8900",
    "sg:postcode":"04101",
    "sg:province":"ME",
    "sg:tags":[
        "newspaper"
    ],
    "wof:name":"Portland Phoenix",
    "wof:placetype":"venue"
},
  "geometry": {"coordinates":[-70.25722,43.653979],"type":"Point"}
}