{
  "type": "Feature",
  "properties": {
    "addr:full":"15 Pleasant Valley Rd Cumberland Center ME 04021",
    "addr:housenumber":"15",
    "addr:postcode":"04021",
    "addr:street":"Pleasant Valley Rd",
    "iso:country":"US",
    "sg:address":"15 Pleasant Valley Rd",
    "sg:city":"Cumberland Center",
    "sg:classifiers":[
        {
            "category":"Recreation",
            "type":"Entertainment"
        }
    ],
    "sg:phone":"+1 207 232 5377",
    "sg:postcode":"04021",
    "sg:province":"ME",
    "wof:name":"Endurance Sports Training",
    "wof:placetype":"venue"
},
  "geometry": {"coordinates":[-70.276172,43.820604],"type":"Point"}
}