{
  "type": "Feature",
  "properties": {
    "addr:full":"499 Stevens Ave Portland ME 04103",
    "addr:housenumber":"499",
    "addr:postcode":"04103",
    "addr:street":"Stevens Ave",
    "iso:country":"US",
    "sg:address":"499 Stevens Ave",
    "sg:city":"Portland",
    "sg:classifiers":[
        {
            "category":"Health Services",
            "subcategory":"Doctor",
            "type":"Services"
        }
    ],
    "sg:phone":"+1 207 774 1222",
    "sg:postcode":"04103",
    "sg:province":"ME",
    "sg:tags":[
        "physician",
        "surgeon"
    ],
    "wof:name":"Ciampi Family Practice",
    "wof:placetype":"venue"
},
  "geometry": {"coordinates":[-70.295034,43.675],"type":"Point"}
}