{
  "type": "Feature",
  "properties": {
    "iso:country":"US",
    "sg:address":"97 Oak St",
    "sg:city":"Bangor",
    "sg:classifiers":[
        {
            "category":"Autos & Motor Vehicles",
            "subcategory":"Automobile Sales",
            "type":"Retail Goods"
        }
    ],
    "sg:phone":"+1 207 262 3289",
    "sg:postcode":"04401",
    "sg:province":"ME",
    "sg:tags":[
        "car",
        "dealer"
    ],
    "wof:name":"Bangor Car Care",
    "wof:placetype":"venue"
},
  "geometry": {"coordinates":[-68.766637,44.801273],"type":"Point"}
}