{
  "type": "Feature",
  "properties": {
    "addr:full":"45 Portland Rd Ste 1 Kennebunk ME 04043",
    "addr:housenumber":"45",
    "addr:postcode":"04043",
    "addr:street":"Portland Rd Ste 1",
    "iso:country":"US",
    "sg:address":"45 Portland Rd Ste 1",
    "sg:city":"Kennebunk",
    "sg:classifiers":[
        {
            "category":"Health Services",
            "subcategory":"Optometrist",
            "type":"Services"
        }
    ],
    "sg:phone":"+1 207 324 8888",
    "sg:postcode":"04043",
    "sg:province":"ME",
    "sg:website":"www.associatedeyecare.net",
    "wof:name":"Associated Eye Care",
    "wof:placetype":"venue"
},
  "geometry": {"coordinates":[-70.530901,43.396017],"type":"Point"}
}