{
  "type": "Feature",
  "properties": {
    "iso:country":"US",
    "sg:address":"246 State St",
    "sg:city":"Bangor",
    "sg:classifiers":[
        {
            "category":"Shopping",
            "subcategory":"Clothing, Apparel, & Fashions",
            "type":"Retail Goods"
        }
    ],
    "sg:phone":"+1 207 945 9778",
    "sg:postcode":"04401",
    "sg:province":"ME",
    "sg:tags":[
        "tailor"
    ],
    "wof:name":"Linda's Alterations & Leather",
    "wof:placetype":"venue"
},
  "geometry": {"coordinates":[-68.76000999999999,44.805939],"type":"Point"}
}