{
  "type": "Feature",
  "properties": {
    "addr:full":"60 Dow Hwy Eliot ME 03903",
    "addr:housenumber":"60",
    "addr:postcode":"03903",
    "addr:street":"Dow Hwy",
    "iso:country":"US",
    "sg:address":"60 Dow Hwy",
    "sg:city":"Eliot",
    "sg:classifiers":[
        {
            "category":"Organizations",
            "subcategory":"Religious Organization",
            "type":"Services"
        }
    ],
    "sg:phone":"+1 207 439 6593",
    "sg:postcode":"03903",
    "sg:province":"ME",
    "sg:tags":[
        "church"
    ],
    "wof:name":"Eliot United Methodist Church",
    "wof:placetype":"venue"
},
  "geometry": {"coordinates":[-70.78176999999999,43.13888],"type":"Point"}
}