{
  "type": "Feature",
  "properties": {
    "addr:full":"Arundel Rd Kennebunkport ME 04046",
    "addr:postcode":"04046",
    "addr:street":"Arundel Rd",
    "iso:country":"US",
    "sg:address":"Arundel Rd",
    "sg:city":"Kennebunkport",
    "sg:classifiers":[
        {
            "category":"Building & Trades",
            "subcategory":"Locksmith",
            "type":"Services"
        }
    ],
    "sg:phone":"+1 207 967 3086",
    "sg:postcode":"04046",
    "sg:province":"ME",
    "sg:tags":[
        "key"
    ],
    "wof:name":"Drown Wilfred M",
    "wof:placetype":"venue"
},
  "geometry": {"coordinates":[-70.489502,43.406799],"type":"Point"}
}