{
  "type": "Feature",
  "properties": {
    "iso:country":"US",
    "sg:address":"150 Main St",
    "sg:city":"Sanford",
    "sg:classifiers":[
        {
            "category":"Professional",
            "type":"Services"
        }
    ],
    "sg:phone":"+1 207 490 6000",
    "sg:postcode":"04073",
    "sg:province":"ME",
    "sg:tags":[
        "establishment"
    ],
    "wof:name":"Lamere Camera",
    "wof:placetype":"venue"
},
  "geometry": {"coordinates":[-70.780642,43.442699],"type":"Point"}
}