{
  "type": "Feature",
  "properties": {
    "addr:full":"301 Littlefield Rd Newburgh ME 04444",
    "addr:housenumber":"301",
    "addr:postcode":"04444",
    "addr:street":"Littlefield Rd",
    "iso:country":"US",
    "sg:address":"301 Littlefield Rd",
    "sg:city":"Newburgh",
    "sg:classifiers":[
        {
            "category":"Building & Trades",
            "subcategory":"Construction",
            "type":"Services"
        }
    ],
    "sg:phone":"+1 207 234 2454",
    "sg:postcode":"04444",
    "sg:province":"ME",
    "sg:tags":[
        "pavement",
        "marking"
    ],
    "wof:name":"Superior Lines",
    "wof:placetype":"venue"
},
  "geometry": {"coordinates":[-68.991506,44.678504],"type":"Point"}
}