{
  "type": "Feature",
  "properties": {
    "addr:full":"27 Wards Hill Rd Gorham ME 04038",
    "addr:housenumber":"27",
    "addr:postcode":"04038",
    "addr:street":"Wards Hill Rd",
    "iso:country":"US",
    "sg:address":"27 Wards Hill Rd",
    "sg:city":"Gorham",
    "sg:classifiers":[
        {
            "category":"Building & Trades",
            "subcategory":"Construction",
            "type":"Services"
        }
    ],
    "sg:phone":"+1 207 892 2744",
    "sg:postcode":"04038",
    "sg:province":"ME",
    "sg:tags":[
        "contractor"
    ],
    "wof:name":"Great Falls Builders Inc",
    "wof:placetype":"venue"
},
  "geometry": {"coordinates":[-70.449079,43.73519],"type":"Point"}
}