{
  "type": "Feature",
  "properties": {
    "addr:full":"233 Parker Farm Rd Buxton ME 04093",
    "addr:housenumber":"233",
    "addr:postcode":"04093",
    "addr:street":"Parker Farm Rd",
    "iso:country":"US",
    "sg:address":"233 Parker Farm Rd",
    "sg:city":"Buxton",
    "sg:classifiers":[
        {
            "category":"Shopping",
            "subcategory":"Florist",
            "type":"Retail Goods"
        }
    ],
    "sg:phone":"+1 207 727 5897",
    "sg:postcode":"04093",
    "sg:province":"ME",
    "wof:name":"Patty's Flower Bouquet",
    "wof:placetype":"venue"
},
  "geometry": {"coordinates":[-70.594785,43.674318],"type":"Point"}
}