{
  "type": "Feature",
  "properties": {
    "iso:country":"US",
    "sg:address":"409 Main St",
    "sg:city":"Presque Isle",
    "sg:classifiers":[
        {
            "category":"Professional",
            "subcategory":"Engineering",
            "type":"Services"
        }
    ],
    "sg:phone":"+1 207 764 2622",
    "sg:postcode":"04769",
    "sg:province":"ME",
    "wof:name":"Buck Engineering",
    "wof:placetype":"venue"
},
  "geometry": {"coordinates":[-68.015545,46.681049],"type":"Point"}
}