{
  "type": "Feature",
  "properties": {
    "addr:full":"149 Main St Northeast Harbor ME 04662",
    "addr:housenumber":"149",
    "addr:postcode":"04662",
    "addr:street":"Main St Northeast",
    "iso:country":"US",
    "sg:address":"149 Main St",
    "sg:city":"Northeast Harbor",
    "sg:classifiers":[
        {
            "category":"Real Estate",
            "subcategory":"Real Estate Agent",
            "type":"Services"
        }
    ],
    "sg:phone":"+1 207 276 3050",
    "sg:postcode":"04662",
    "sg:province":"ME",
    "sg:website":"www.blackndillon.com",
    "wof:name":"Black & Dillon Real Estate",
    "wof:placetype":"venue"
},
  "geometry": {"coordinates":[-68.288855,44.293103],"type":"Point"}
}