{
  "type": "Feature",
  "properties": {
    "addr:full":"161 Park St Orono ME 04473",
    "addr:housenumber":"161",
    "addr:postcode":"04473",
    "addr:street":"Park St",
    "iso:country":"US",
    "sg:address":"161 Park St",
    "sg:city":"Orono",
    "sg:classifiers":[
        {
            "category":"Freight",
            "type":"Transportation"
        }
    ],
    "sg:phone":"+1 207 866 7867",
    "sg:postcode":"04473",
    "sg:province":"ME",
    "sg:tags":[
        "commercial",
        "storage"
    ],
    "wof:name":"Orono Old Town Self Storage",
    "wof:placetype":"venue"
},
  "geometry": {"coordinates":[-68.65528399999999,44.897631],"type":"Point"}
}