{
  "type": "Feature",
  "properties": {
    "iso:country":"US",
    "sg:address":"109 Waterville Rd",
    "sg:city":"Skowhegan",
    "sg:classifiers":[
        {
            "category":"Building & Trades",
            "subcategory":"Plumbing",
            "type":"Services"
        }
    ],
    "sg:phone":"+1 207 474 7216",
    "sg:postcode":"04976",
    "sg:province":"ME",
    "sg:tags":[
        "septic"
    ],
    "wof:name":"Central Maine Septic",
    "wof:placetype":"venue"
},
  "geometry": {"coordinates":[-69.709964,44.763194],"type":"Point"}
}