{
  "type": "Feature",
  "properties": {
    "iso:country":"US",
    "sg:address":"3 Dexter Rd",
    "sg:city":"Corinna",
    "sg:classifiers":[
        {
            "category":"Autos & Motor Vehicles",
            "subcategory":"Fuel & Gas Station",
            "type":"Retail Goods"
        }
    ],
    "sg:phone":"+1 207 278 2132",
    "sg:postcode":"04923",
    "sg:province":"ME",
    "sg:tags":[
        "oil"
    ],
    "wof:name":"Corinna Fuel & Svc Ctr",
    "wof:placetype":"venue"
},
  "geometry": {"coordinates":[-69.470772,45.025447],"type":"Point"}
}