{
  "type": "Feature",
  "properties": {
    "addr:full":"1707 Woodland Center Rd Perham ME 04766",
    "addr:housenumber":"1707",
    "addr:postcode":"04766",
    "addr:street":"Woodland Center Rd",
    "iso:country":"US",
    "sg:address":"1707 Woodland Center Rd",
    "sg:city":"Perham",
    "sg:classifiers":[
        {
            "category":"Building & Trades",
            "subcategory":"Construction",
            "type":"Services"
        }
    ],
    "sg:phone":"+1 207 496 4191",
    "sg:postcode":"04766",
    "sg:province":"ME",
    "sg:tags":[
        "carpentry",
        "business",
        "contractor"
    ],
    "wof:name":"Ouellette Detlef",
    "wof:placetype":"venue"
},
  "geometry": {"coordinates":[-68.21360300000001,46.87871],"type":"Point"}
}