{
  "type": "Feature",
  "properties": {
    "addr:full":"60 Wilson Rd Kittery ME 03904",
    "addr:housenumber":"60",
    "addr:postcode":"03904",
    "addr:street":"Wilson Rd",
    "iso:country":"US",
    "sg:address":"60 Wilson Rd",
    "sg:city":"Kittery",
    "sg:classifiers":[
        {
            "category":"Insurance",
            "subcategory":"Insurance Agent",
            "type":"Services"
        }
    ],
    "sg:phone":"+1 207 439 7000",
    "sg:postcode":"03904",
    "sg:province":"ME",
    "wof:name":"Gail B Burns",
    "wof:placetype":"venue"
},
  "geometry": {"coordinates":[-70.744512,43.135971],"type":"Point"}
}