{
  "type": "Feature",
  "properties": {
    "addr:full":"72 High St Eastport ME 04631",
    "addr:housenumber":"72",
    "addr:postcode":"04631",
    "addr:street":"High St",
    "iso:country":"US",
    "sg:address":"72 High St",
    "sg:city":"Eastport",
    "sg:classifiers":[
        {
            "category":"Retail",
            "subcategory":"Funeral Services",
            "type":"Services"
        }
    ],
    "sg:phone":"+1 207 853 4240",
    "sg:postcode":"04631",
    "sg:province":"ME",
    "sg:tags":[
        "director"
    ],
    "wof:name":"Flagg Funeral Home",
    "wof:placetype":"venue"
},
  "geometry": {"coordinates":[-66.98976999999999,44.904813],"type":"Point"}
}