{
  "type": "Feature",
  "properties": {
    "addr:full":"220 Water St Hallowell ME 04347",
    "addr:housenumber":"220",
    "addr:postcode":"04347",
    "addr:street":"Water St",
    "iso:country":"US",
    "sg:address":"220 Water St",
    "sg:city":"Hallowell",
    "sg:classifiers":[
        {
            "category":"Organizations",
            "subcategory":"Community Association",
            "type":"Services"
        }
    ],
    "sg:phone":"+1 207 622 9766",
    "sg:postcode":"04347",
    "sg:province":"ME",
    "sg:tags":[
        "environmental",
        "org"
    ],
    "wof:name":"Maine Environmental Policy",
    "wof:placetype":"venue"
},
  "geometry": {"coordinates":[-69.791115,44.2832],"type":"Point"}
}