{
  "type": "Feature",
  "properties": {
    "iso:country":"US",
    "sg:address":"160 Cottage St",
    "sg:city":"Sanford",
    "sg:classifiers":[
        {
            "category":"Health Services",
            "subcategory":"Doctor",
            "type":"Services"
        }
    ],
    "sg:phone":"+1 207 459 7902",
    "sg:postcode":"04073",
    "sg:province":"ME",
    "sg:tags":[
        "physician",
        "surgeon"
    ],
    "wof:name":"Mousam Valley Orthopedics",
    "wof:placetype":"venue"
},
  "geometry": {"coordinates":[-70.769817,43.44835],"type":"Point"}
}