{
  "type": "Feature",
  "properties": {
    "addr:full":"328 US Hwy 1 York ME 03909",
    "addr:housenumber":"328",
    "addr:postcode":"03909",
    "addr:street":"Us Hwy 1",
    "iso:country":"US",
    "sg:address":"328 US Hwy 1",
    "sg:city":"York",
    "sg:classifiers":[
        {
            "category":"Freight",
            "type":"Transportation"
        }
    ],
    "sg:phone":"+1 207 363 3311",
    "sg:postcode":"03909",
    "sg:province":"ME",
    "sg:tags":[
        "commercial",
        "storage"
    ],
    "wof:name":"Atlantic Self Storage",
    "wof:placetype":"venue"
},
  "geometry": {"coordinates":[-70.690296,43.141935],"type":"Point"}
}