{
  "type": "Feature",
  "properties": {
    "iso:country":"US",
    "sg:address":"671 Main St",
    "sg:city":"Lewiston",
    "sg:classifiers":[
        {
            "category":"Professional",
            "subcategory":"Employment Agencies",
            "type":"Services"
        }
    ],
    "sg:phone":"+1 207 777 5294",
    "sg:postcode":"04240",
    "sg:province":"ME",
    "sg:tags":[
        "home",
        "health",
        "care"
    ],
    "wof:name":"Helping Hands",
    "wof:placetype":"venue"
},
  "geometry": {"coordinates":[-70.204354,44.118155],"type":"Point"}
}