{
  "type": "Feature",
  "properties": {
    "addr:full":"236 Main Rd S Hampden ME 04444",
    "addr:housenumber":"236",
    "addr:postcode":"04444",
    "addr:street":"Main Rd",
    "iso:country":"US",
    "sg:address":"236 Main Rd S",
    "sg:city":"Hampden",
    "sg:classifiers":[
        {
            "category":"Travel",
            "subcategory":"Hotels & Motels",
            "type":"Entertainment"
        }
    ],
    "sg:phone":"+1 207 862 5500",
    "sg:postcode":"04444",
    "sg:province":"ME",
    "wof:name":"Park-Rest Motel",
    "wof:placetype":"venue"
},
  "geometry": {"coordinates":[-68.84493500000001,44.72412],"type":"Point"}
}