{
  "type": "Feature",
  "properties": {
    "iso:country":"US",
    "sg:address":"2 Military St",
    "sg:city":"Blaine",
    "sg:classifiers":[
        {
            "category":"Wholesale",
            "subcategory":"Fruits & Vegetables",
            "type":"Manufacturing & Wholesale Goods"
        }
    ],
    "sg:phone":"+1 207 425 3941",
    "sg:postcode":"04730",
    "sg:province":"ME",
    "sg:tags":[
        "potato"
    ],
    "wof:name":"County Produce Inc",
    "wof:placetype":"venue"
},
  "geometry": {"coordinates":[-67.844748,46.123343],"type":"Point"}
}