{
  "type": "Feature",
  "properties": {
    "addr:full":"49 Elm St Camden ME 04843",
    "addr:housenumber":"49",
    "addr:postcode":"04843",
    "addr:street":"Elm St",
    "iso:country":"US",
    "sg:address":"49 Elm St",
    "sg:city":"Camden",
    "sg:classifiers":[
        {
            "category":"Health Services",
            "subcategory":"Chiropractor",
            "type":"Services"
        }
    ],
    "sg:phone":"+1 207 236 3416",
    "sg:postcode":"04843",
    "sg:province":"ME",
    "wof:name":"Johnstone Chiropractic Ctr",
    "wof:placetype":"venue"
},
  "geometry": {"coordinates":[-69.067143,44.208093],"type":"Point"}
}