{
  "type": "Feature",
  "properties": {
    "addr:full":"1 Maverick St Rockland ME 04841",
    "addr:housenumber":"1",
    "addr:postcode":"04841",
    "addr:street":"Maverick St",
    "iso:country":"US",
    "sg:address":"1 Maverick St",
    "sg:city":"Rockland",
    "sg:classifiers":[
        {
            "category":"Restaurant",
            "type":"Food & Drink"
        }
    ],
    "sg:menulink":"http://www.allmenus.com/me/rockland/119848-subway/menu/",
    "sg:phone":"+1 207 594 7579",
    "sg:postcode":"04841",
    "sg:province":"ME",
    "sg:tags":[
        "american",
        "sandwich"
    ],
    "wof:name":"Subway",
    "wof:placetype":"venue"
},
  "geometry": {"coordinates":[-69.102626,44.114644],"type":"Point"}
}