{
  "type": "Feature",
  "properties": {
    "addr:full":"104 Main St Lincoln ME 04457",
    "addr:housenumber":"104",
    "addr:postcode":"04457",
    "addr:street":"Main St",
    "iso:country":"US",
    "sg:address":"104 Main St",
    "sg:city":"Lincoln",
    "sg:classifiers":[
        {
            "category":"Personal",
            "subcategory":"Tanning Parlor",
            "type":"Services"
        }
    ],
    "sg:phone":"+1 207 794 0909",
    "sg:postcode":"04457",
    "sg:province":"ME",
    "sg:tags":[
        "salon"
    ],
    "wof:name":"She Gi's",
    "wof:placetype":"venue"
},
  "geometry": {"coordinates":[-68.503241,45.365445],"type":"Point"}
}