{
  "type": "Feature",
  "properties": {
    "addr:full":"1490 Lisbon St Lewiston ME 04240",
    "addr:housenumber":"1490",
    "addr:postcode":"04240",
    "addr:street":"Lisbon St",
    "iso:country":"US",
    "sg:address":"1490 Lisbon St",
    "sg:city":"Lewiston",
    "sg:classifiers":[
        {
            "category":"Retail",
            "subcategory":"Auto Repair",
            "type":"Services"
        }
    ],
    "sg:phone":"+1 207 786 0013",
    "sg:postcode":"04240",
    "sg:province":"ME",
    "sg:tags":[
        "repairing",
        "automobile"
    ],
    "wof:name":"Paul's Garage",
    "wof:placetype":"venue"
},
  "geometry": {"coordinates":[-70.17591,44.073078],"type":"Point"}
}