{
  "type": "Feature",
  "properties": {
    "addr:full":"51 Franklin St Ellsworth ME 04605",
    "addr:housenumber":"51",
    "addr:postcode":"04605",
    "addr:street":"Franklin St",
    "iso:country":"US",
    "sg:address":"51 Franklin St",
    "sg:city":"Ellsworth",
    "sg:classifiers":[
        {
            "category":"Professional",
            "subcategory":"Accounting & Tax Preparation",
            "type":"Services"
        }
    ],
    "sg:phone":"+1 207 667 3320",
    "sg:postcode":"04605",
    "sg:province":"ME",
    "sg:tags":[
        "return"
    ],
    "wof:name":"Lounder Business Service",
    "wof:placetype":"venue"
},
  "geometry": {"coordinates":[-68.423602,44.541596],"type":"Point"}
}