{
  "type": "Feature",
  "properties": {
    "addr:full":"213 Aroostook Ave Millinocket ME 04462",
    "addr:housenumber":"213",
    "addr:postcode":"04462",
    "addr:street":"Aroostook Ave",
    "iso:country":"US",
    "sg:address":"213 Aroostook Ave",
    "sg:city":"Millinocket",
    "sg:classifiers":[
        {
            "category":"Organizations",
            "subcategory":"Community Association",
            "type":"Services"
        }
    ],
    "sg:phone":"+1 207 723 4207",
    "sg:postcode":"04462",
    "sg:province":"ME",
    "sg:tags":[
        "fraternal"
    ],
    "wof:name":"Elks Lodge",
    "wof:placetype":"venue"
},
  "geometry": {"coordinates":[-68.707994,45.65398],"type":"Point"}
}