{
  "type": "Feature",
  "properties": {
    "iso:country":"US",
    "sg:address":"115 Main St",
    "sg:city":"Lincoln",
    "sg:classifiers":[
        {
            "category":"Social Services",
            "type":"Services"
        }
    ],
    "sg:phone":"+1 207 794 3093",
    "sg:postcode":"04457",
    "sg:province":"ME",
    "sg:tags":[
        "organization",
        "welfare"
    ],
    "wof:name":"Penquis Community Action Progr",
    "wof:placetype":"venue"
},
  "geometry": {"coordinates":[-68.50327299999999,45.365283],"type":"Point"}
}