{
  "type": "Feature",
  "properties": {
    "iso:country":"US",
    "sg:address":"425 Waterville Rd",
    "sg:city":"Norridgewock",
    "sg:classifiers":[
        {
            "category":"Professional",
            "subcategory":"Management & Consulting",
            "type":"Services"
        }
    ],
    "sg:phone":"+1 207 634 3469",
    "sg:postcode":"04957",
    "sg:province":"ME",
    "sg:tags":[
        "independent",
        "retailing",
        "cosmetic",
        "beauty",
        "consultant"
    ],
    "wof:name":"Yvonnes Consulting Service",
    "wof:placetype":"venue"
},
  "geometry": {"coordinates":[-69.757389,44.698742],"type":"Point"}
}