{
  "type": "Feature",
  "properties": {
    "iso:country":"US",
    "sg:address":"380 Elm St",
    "sg:city":"Biddeford",
    "sg:classifiers":[
        {
            "category":"Autos & Motor Vehicles",
            "subcategory":"Auto Supplies",
            "type":"Retail Goods"
        }
    ],
    "sg:phone":"+1 207 286 2388",
    "sg:postcode":"04005",
    "sg:province":"ME",
    "sg:tags":[
        "automobile",
        "parts"
    ],
    "sg:website":"www.advanceautoparts.com",
    "wof:name":"Advance Auto Parts",
    "wof:placetype":"venue"
},
  "geometry": {"coordinates":[-70.470668,43.483773],"type":"Point"}
}