{
  "type": "Feature",
  "properties": {
    "addr:full":"162 Sam Allen Rd Sanford ME 04073",
    "addr:housenumber":"162",
    "addr:postcode":"04073",
    "addr:street":"Sam Allen Rd",
    "iso:country":"US",
    "sg:address":"162 Sam Allen Rd",
    "sg:city":"Sanford",
    "sg:classifiers":[
        {
            "category":"Building & Trades",
            "subcategory":"Landscaping Services",
            "type":"Services"
        }
    ],
    "sg:phone":"+1 207 324 1744",
    "sg:postcode":"04073",
    "sg:province":"ME",
    "wof:name":"Woltersdorfs Acres",
    "wof:placetype":"venue"
},
  "geometry": {"coordinates":[-70.70843600000001,43.373117],"type":"Point"}
}