{
  "type": "Feature",
  "properties": {
    "addr:full":"1236 Congress St Portland ME 04102",
    "addr:housenumber":"1236",
    "addr:postcode":"04102",
    "addr:street":"Congress St",
    "iso:country":"US",
    "sg:address":"1236 Congress St",
    "sg:city":"Portland",
    "sg:classifiers":[
        {
            "category":"Retail",
            "subcategory":"Repair Shop",
            "type":"Services"
        }
    ],
    "sg:phone":"+1 207 773 3400",
    "sg:postcode":"04102",
    "sg:province":"ME",
    "sg:tags":[
        "repairing",
        "lamp"
    ],
    "wof:name":"Lotfey Lamp Repair",
    "wof:placetype":"venue"
},
  "geometry": {"coordinates":[-70.29043799999999,43.657371],"type":"Point"}
}