{
  "type": "Feature",
  "properties": {
    "iso:country":"US",
    "sg:address":"99 Harpswell Neck Rd",
    "sg:city":"South Harpswell",
    "sg:classifiers":[
        {
            "category":"Retail",
            "subcategory":"Repair Shop",
            "type":"Services"
        }
    ],
    "sg:phone":"+1 207 721 1133",
    "sg:postcode":"04079",
    "sg:province":"ME",
    "wof:name":"Rainbow Upholstery",
    "wof:placetype":"venue"
},
  "geometry": {"coordinates":[-69.954438,43.844063],"type":"Point"}
}