{
  "type": "Feature",
  "properties": {
    "addr:full":"84 Organug Rd York ME 03909",
    "addr:housenumber":"84",
    "addr:postcode":"03909",
    "addr:street":"Organug Rd",
    "iso:country":"US",
    "sg:address":"84 Organug Rd",
    "sg:city":"York",
    "sg:classifiers":[
        {
            "category":"Education",
            "subcategory":"School",
            "type":"Public Place"
        }
    ],
    "sg:phone":"+1 207 363 4214",
    "sg:postcode":"03909",
    "sg:province":"ME",
    "sg:tags":[
        "high",
        "middle",
        "elementary"
    ],
    "sg:website":"parksandrec.yorkmaine.org",
    "wof:name":"York Town of",
    "wof:placetype":"venue"
},
  "geometry": {"coordinates":[-70.66012000000001,43.137779],"type":"Point"}
}