{
  "type": "Feature",
  "properties": {
    "iso:country":"US",
    "sg:address":"1278 Sawyer Rd",
    "sg:city":"Cape Elizabeth",
    "sg:classifiers":[
        {
            "category":"Real Estate",
            "subcategory":"Real Estate Agent",
            "type":"Services"
        }
    ],
    "sg:phone":"+1 207 741 2887",
    "sg:postcode":"04107",
    "sg:province":"ME",
    "wof:name":"Pillsbury Wnslow S RE Apprisal",
    "wof:placetype":"venue"
},
  "geometry": {"coordinates":[-70.263263,43.587973],"type":"Point"}
}