{
  "type": "Feature",
  "properties": {
    "iso:country":"US",
    "sg:address":"32 Kyle Ln",
    "sg:city":"Auburn",
    "sg:classifiers":[
        {
            "category":"Manufacturing",
            "subcategory":"Printing",
            "type":"Manufacturing & Wholesale Goods"
        }
    ],
    "sg:phone":"+1 207 783 2329",
    "sg:postcode":"04210",
    "sg:province":"ME",
    "sg:tags":[
        "commercial"
    ],
    "wof:name":"Inkworks Screenprinting",
    "wof:placetype":"venue"
},
  "geometry": {"coordinates":[-70.228117,44.047288],"type":"Point"}
}