{
  "type": "Feature",
  "properties": {
    "iso:country":"US",
    "sg:address":"190 E Main St",
    "sg:city":"Searsport",
    "sg:classifiers":[
        {
            "category":"Personal",
            "subcategory":"Beauty Salon",
            "type":"Services"
        }
    ],
    "sg:phone":"+1 207 548 6699",
    "sg:postcode":"04974",
    "sg:province":"ME",
    "sg:tags":[
        "shop"
    ],
    "wof:name":"Beauty By Marianna",
    "wof:placetype":"venue"
},
  "geometry": {"coordinates":[-68.905281,44.463174],"type":"Point"}
}