{
  "type": "Feature",
  "properties": {
    "iso:country":"US",
    "sg:address":"9 Main St",
    "sg:city":"Norridgewock",
    "sg:classifiers":[
        {
            "category":"Banks & Credit Unions",
            "subcategory":"Bank",
            "type":"Services"
        }
    ],
    "sg:phone":"+1 207 634 3501",
    "sg:postcode":"04957",
    "sg:province":"ME",
    "wof:name":"Skowhegan Savings Bank",
    "wof:placetype":"venue"
},
  "geometry": {"coordinates":[-69.79053,44.712931],"type":"Point"}
}