{
  "type": "Feature",
  "properties": {
    "addr:full":"82 Princes Point Rd Yarmouth ME 04096",
    "addr:housenumber":"82",
    "addr:postcode":"04096",
    "addr:street":"Princes Point Rd",
    "iso:country":"US",
    "sg:address":"82 Princes Point Rd",
    "sg:city":"Yarmouth",
    "sg:classifiers":[
        {
            "category":"Utilities",
            "subcategory":"Sewage",
            "type":"Services"
        }
    ],
    "sg:phone":"+1 207 846 2415",
    "sg:postcode":"04096",
    "sg:province":"ME",
    "sg:tags":[
        "disposal",
        "system"
    ],
    "wof:name":"Waste Water Treatment Plant",
    "wof:placetype":"venue"
},
  "geometry": {"coordinates":[-70.16986900000001,43.786076],"type":"Point"}
}