{
  "type": "Feature",
  "properties": {
    "iso:country":"US",
    "sg:address":"158 Beachwood Ave",
    "sg:city":"Kennebunkport",
    "sg:classifiers":[
        {
            "category":"Wholesale",
            "subcategory":"Electrical",
            "type":"Manufacturing & Wholesale Goods"
        }
    ],
    "sg:phone":"+1 207 967 0010",
    "sg:postcode":"04046",
    "sg:province":"ME",
    "sg:tags":[
        "alarm",
        "burglar",
        "system"
    ],
    "wof:name":"Eastern New England Security",
    "wof:placetype":"venue"
},
  "geometry": {"coordinates":[-70.451878,43.395672],"type":"Point"}
}