{
  "type": "Feature",
  "properties": {
    "iso:country":"US",
    "sg:address":"127 Allen Ave",
    "sg:city":"Auburn",
    "sg:classifiers":[
        {
            "category":"Professional",
            "subcategory":"Business Services",
            "type":"Services"
        }
    ],
    "sg:phone":"+1 207 782 0954",
    "sg:postcode":"04210",
    "sg:province":"ME",
    "wof:name":"International Assoc of Ad",
    "wof:placetype":"venue"
},
  "geometry": {"coordinates":[-70.254819,44.093046],"type":"Point"}
}