{
  "type": "Feature",
  "properties": {
    "addr:full":"46 Concourse E Belfast ME 04901",
    "addr:housenumber":"46",
    "addr:postcode":"04901",
    "addr:street":"Concourse E",
    "iso:country":"US",
    "sg:address":"46 Concourse E",
    "sg:city":"Belfast",
    "sg:classifiers":[
        {
            "category":"Social Services",
            "subcategory":"Child Care",
            "type":"Services"
        }
    ],
    "sg:phone":"+1 207 338 5046",
    "sg:postcode":"04901",
    "sg:province":"ME",
    "sg:tags":[
        "kindergarten",
        "academic",
        "school"
    ],
    "wof:name":"Woodland Management",
    "wof:placetype":"venue"
},
  "geometry": {"coordinates":[-69.631203,44.549839],"type":"Point"}
}