{
  "type": "Feature",
  "properties": {
    "addr:full":"59 Main St Dexter ME 04930",
    "addr:housenumber":"59",
    "addr:postcode":"04930",
    "addr:street":"Main St",
    "iso:country":"US",
    "sg:address":"59 Main St",
    "sg:city":"Dexter",
    "sg:classifiers":[
        {
            "category":"Organizations",
            "subcategory":"Religious Organization",
            "type":"Services"
        }
    ],
    "sg:phone":"+1 207 924 8843",
    "sg:postcode":"04930",
    "sg:province":"ME",
    "sg:tags":[
        "church"
    ],
    "wof:name":"Dexter United Methodist Church",
    "wof:placetype":"venue"
},
  "geometry": {"coordinates":[-69.29348,45.020678],"type":"Point"}
}