{
  "type": "Feature",
  "properties": {
    "addr:full":"6 Gibson Rd Scarborough ME 04074",
    "addr:housenumber":"6",
    "addr:postcode":"04074",
    "addr:street":"Gibson Rd",
    "iso:country":"US",
    "sg:address":"6 Gibson Rd",
    "sg:city":"Scarborough",
    "sg:classifiers":[
        {
            "category":"Retail",
            "subcategory":"Auto Rental",
            "type":"Services"
        }
    ],
    "sg:phone":"+1 207 885 0101",
    "sg:postcode":"04074",
    "sg:province":"ME",
    "sg:tags":[
        "car"
    ],
    "sg:website":"www.hertzequip.com",
    "wof:name":"Hertz Equipment Rental Corporation",
    "wof:placetype":"venue"
},
  "geometry": {"coordinates":[-70.302696,43.608299],"type":"Point"}
}