{
  "type": "Feature",
  "properties": {
    "iso:country":"US",
    "sg:address":"30 Elm St",
    "sg:city":"Mechanic Falls",
    "sg:classifiers":[
        {
            "category":"Utilities",
            "subcategory":"Refuse",
            "type":"Services"
        }
    ],
    "sg:phone":"+1 207 346 3917",
    "sg:postcode":"04256",
    "sg:province":"ME",
    "sg:tags":[
        "disposal",
        "waste"
    ],
    "sg:website":"www.casella.com",
    "wof:name":"Pinetree Waste",
    "wof:placetype":"venue"
},
  "geometry": {"coordinates":[-70.390356,44.110546],"type":"Point"}
}