{
  "type": "Feature",
  "properties": {
    "iso:country":"US",
    "sg:address":"366 Main St",
    "sg:city":"Southwest Harbor",
    "sg:classifiers":[
        {
            "category":"Shopping",
            "subcategory":"Clothing, Apparel, & Fashions",
            "type":"Retail Goods"
        }
    ],
    "sg:phone":"+1 207 244 3121",
    "sg:postcode":"04679",
    "sg:province":"ME",
    "wof:name":"MDI Sportswear",
    "wof:placetype":"venue"
},
  "geometry": {"coordinates":[-68.326093,44.271131],"type":"Point"}
}