{
  "type": "Feature",
  "properties": {
    "iso:country":"US",
    "sg:address":"443 Whites Bridge Rd",
    "sg:city":"Standish",
    "sg:classifiers":[
        {
            "category":"Building & Trades",
            "subcategory":"Landscaping Services",
            "type":"Services"
        }
    ],
    "sg:phone":"+1 207 892 7426",
    "sg:postcode":"04084",
    "sg:province":"ME",
    "sg:tags":[
        "tree"
    ],
    "wof:name":"Expert Tree Svc",
    "wof:placetype":"venue"
},
  "geometry": {"coordinates":[-70.466261,43.845454],"type":"Point"}
}