{
  "type": "Feature",
  "properties": {
    "addr:full":"339 Main St Calais ME 04619",
    "addr:housenumber":"339",
    "addr:postcode":"04619",
    "addr:street":"Main St",
    "iso:country":"US",
    "sg:address":"339 Main St",
    "sg:city":"Calais",
    "sg:classifiers":[
        {
            "category":"Organizations",
            "subcategory":"Religious Organization",
            "type":"Services"
        }
    ],
    "sg:phone":"+1 207 454 7226",
    "sg:postcode":"04619",
    "sg:province":"ME",
    "sg:tags":[
        "church"
    ],
    "wof:name":"Methodist Church Study",
    "wof:placetype":"venue"
},
  "geometry": {"coordinates":[-67.256277,45.179648],"type":"Point"}
}