{
  "type": "Feature",
  "properties": {
    "addr:full":"8 Thurston Rd Scarborough ME 04010",
    "addr:housenumber":"8",
    "addr:postcode":"04010",
    "addr:street":"Thurston Rd",
    "iso:country":"US",
    "sg:address":"8 Thurston Rd",
    "sg:city":"Scarborough",
    "sg:classifiers":[
        {
            "category":"Professional",
            "subcategory":"Advertising",
            "type":"Services"
        }
    ],
    "sg:phone":"+1 207 883 5230",
    "sg:postcode":"04010",
    "sg:province":"ME",
    "wof:name":"Media Place",
    "wof:placetype":"venue"
},
  "geometry": {"coordinates":[-70.979384,43.91621],"type":"Point"}
}