{
  "type": "Feature",
  "properties": {
    "addr:full":"5 Pier Rd Kennebunkport ME 04046",
    "addr:housenumber":"5",
    "addr:postcode":"04046",
    "addr:street":"Pier Rd",
    "iso:country":"US",
    "sg:address":"5 Pier Rd",
    "sg:city":"Kennebunkport",
    "sg:classifiers":[
        {
            "category":"Arts & Performance",
            "subcategory":"Art Gallery",
            "type":"Entertainment"
        }
    ],
    "sg:phone":"+1 207 967 5053",
    "sg:postcode":"04046",
    "sg:province":"ME",
    "wof:name":"Wright Gallery the",
    "wof:placetype":"venue"
},
  "geometry": {"coordinates":[-70.43409699999999,43.370499],"type":"Point"}
}