{
  "type": "Feature",
  "properties": {
    "iso:country":"US",
    "sg:address":"517 Summit St",
    "sg:city":"Portland",
    "sg:classifiers":[
        {
            "category":"Organizations",
            "subcategory":"Membership Organization",
            "type":"Services"
        }
    ],
    "sg:phone":"+1 207 797 8508",
    "sg:postcode":"04103",
    "sg:province":"ME",
    "wof:name":"National Organization-Women",
    "wof:placetype":"venue"
},
  "geometry": {"coordinates":[-70.297439,43.718964],"type":"Point"}
}