{
  "type": "Feature",
  "properties": {
    "iso:country":"US",
    "sg:address":"1339 Main St",
    "sg:city":"East Wilton",
    "sg:classifiers":[
        {
            "category":"Food & Beverages",
            "subcategory":"Groceries & Convenience Stores",
            "type":"Retail Goods"
        }
    ],
    "sg:phone":"+1 207 645 2323",
    "sg:postcode":"04240",
    "sg:province":"ME",
    "sg:tags":[
        "grocer"
    ],
    "wof:name":"Your Hometown Market",
    "wof:placetype":"venue"
},
  "geometry": {"coordinates":[-70.191085,44.148719],"type":"Point"}
}