{
  "type": "Feature",
  "properties": {
    "addr:full":"355 Main St Old Town ME 04468",
    "addr:housenumber":"355",
    "addr:postcode":"04468",
    "addr:street":"Main St",
    "iso:country":"US",
    "sg:address":"355 Main St",
    "sg:city":"Old Town",
    "sg:classifiers":[
        {
            "category":"Social Services",
            "subcategory":"Child Care",
            "type":"Services"
        }
    ],
    "sg:phone":"+1 207 827 5800",
    "sg:postcode":"04468",
    "sg:province":"ME",
    "wof:name":"Happy Place Child Care Ctr",
    "wof:placetype":"venue"
},
  "geometry": {"coordinates":[-68.644192,44.9282],"type":"Point"}
}