{
  "type": "Feature",
  "properties": {
    "addr:full":"226 McCrillis Corner Rd Wilton ME 04294",
    "addr:housenumber":"226",
    "addr:postcode":"04294",
    "addr:street":"Mccrillis Corner Rd",
    "iso:country":"US",
    "sg:address":"226 McCrillis Corner Rd",
    "sg:city":"Wilton",
    "sg:classifiers":[
        {
            "category":"Personal",
            "subcategory":"Beauty Salon",
            "type":"Services"
        }
    ],
    "sg:phone":"+1 207 779 1144",
    "sg:postcode":"04294",
    "sg:province":"ME",
    "wof:name":"Snippers",
    "wof:placetype":"venue"
},
  "geometry": {"coordinates":[-70.164385,44.6061],"type":"Point"}
}