{
  "type": "Feature",
  "properties": {
    "iso:country":"US",
    "sg:address":"94 Cross Point Rd",
    "sg:city":"Edgecomb",
    "sg:classifiers":[
        {
            "category":"Real Estate",
            "subcategory":"Architect",
            "type":"Services"
        }
    ],
    "sg:phone":"+1 207 882 8155",
    "sg:postcode":"04556",
    "sg:province":"ME",
    "sg:tags":[
        "architectural"
    ],
    "wof:name":"Suzanne O Carlson",
    "wof:placetype":"venue"
},
  "geometry": {"coordinates":[-69.648818,43.978154],"type":"Point"}
}