{
  "type": "Feature",
  "properties": {
    "iso:country":"US",
    "sg:address":"324 Fore St",
    "sg:city":"Portland",
    "sg:classifiers":[
        {
            "category":"Shopping",
            "subcategory":"Used Merchandise",
            "type":"Retail Goods"
        }
    ],
    "sg:phone":"+1 207 773 0081",
    "sg:postcode":"04101",
    "sg:province":"ME",
    "sg:tags":[
        "antique"
    ],
    "wof:name":"China Sea Marine Trading Co",
    "wof:placetype":"venue"
},
  "geometry": {"coordinates":[-70.251992,43.656949],"type":"Point"}
}