{
  "type": "Feature",
  "properties": {
    "addr:full":"647 Houlton Rd Baileyville ME 04694",
    "addr:housenumber":"647",
    "addr:postcode":"04694",
    "addr:street":"Houlton Rd",
    "iso:country":"US",
    "sg:address":"647 Houlton Rd",
    "sg:city":"Baileyville",
    "sg:classifiers":[
        {
            "category":"Shopping",
            "subcategory":"Stationery & Office Supplies",
            "type":"Retail Goods"
        }
    ],
    "sg:phone":"+1 207 427 4200",
    "sg:postcode":"04694",
    "sg:province":"ME",
    "wof:name":"Netherland Office Products",
    "wof:placetype":"venue"
},
  "geometry": {"coordinates":[-67.40046700000001,45.148735],"type":"Point"}
}