{
  "type": "Feature",
  "properties": {
    "addr:full":"40 Glenridge Dr Augusta ME 04330",
    "addr:housenumber":"40",
    "addr:postcode":"04330",
    "addr:street":"Glenridge Dr",
    "iso:country":"US",
    "sg:address":"40 Glenridge Dr",
    "sg:city":"Augusta",
    "sg:classifiers":[
        {
            "category":"Organizations",
            "subcategory":"Non-profit Organization",
            "type":"Services"
        },
        {
            "category":"Health Services",
            "subcategory":"Nursing And Care Facility",
            "type":"Services"
        }
    ],
    "sg:phone":"+1 207 626 2600",
    "sg:postcode":"04330",
    "sg:province":"ME",
    "sg:tags":[
        "home",
        "convalescent"
    ],
    "wof:name":"Me General Rehabilitation",
    "wof:placetype":"venue"
},
  "geometry": {"coordinates":[-69.764566,44.303525],"type":"Point"}
}