{
  "type": "Feature",
  "properties": {
    "iso:country":"US",
    "sg:address":"2 Pleasant St",
    "sg:city":"Blue Hill",
    "sg:classifiers":[
        {
            "category":"Shopping",
            "subcategory":"Books",
            "type":"Retail Goods"
        }
    ],
    "sg:phone":"+1 207 374 5632",
    "sg:postcode":"04614",
    "sg:province":"ME",
    "sg:tags":[
        "dealer"
    ],
    "sg:website":"www.bluehillbooks.com",
    "wof:name":"Blue Hill Books",
    "wof:placetype":"venue"
},
  "geometry": {"coordinates":[-68.594141,44.421493],"type":"Point"}
}