{
  "type": "Feature",
  "properties": {
    "iso:country":"US",
    "sg:address":"68 Water St",
    "sg:city":"Machias",
    "sg:classifiers":[
        {
            "category":"Government",
            "subcategory":"Office",
            "type":"Public Place"
        }
    ],
    "sg:phone":"+1 207 255 4715",
    "sg:postcode":"04654",
    "sg:province":"ME",
    "sg:tags":[
        "state"
    ],
    "wof:name":"Wildlife Div",
    "wof:placetype":"venue"
},
  "geometry": {"coordinates":[-67.466494,44.71032],"type":"Point"}
}