{
  "type": "Feature",
  "properties": {
    "iso:country":"US",
    "sg:address":"259 Main St",
    "sg:city":"Yarmouth",
    "sg:classifiers":[
        {
            "category":"Health Services",
            "subcategory":"Medical Lab",
            "type":"Services"
        }
    ],
    "sg:phone":"+1 207 846 5728",
    "sg:postcode":"04096",
    "sg:province":"ME",
    "sg:tags":[
        "x"
    ],
    "wof:name":"Yarmouth X-Ray",
    "wof:placetype":"venue"
},
  "geometry": {"coordinates":[-70.18976000000001,43.801876],"type":"Point"}
}