{
  "type": "Feature",
  "properties": {
    "iso:country":"US",
    "sg:address":"8 Baker Ln",
    "sg:city":"Bradley",
    "sg:classifiers":[
        {
            "category":"Building & Trades",
            "subcategory":"Construction",
            "type":"Services"
        }
    ],
    "sg:phone":"+1 207 827 8700",
    "sg:postcode":"04411",
    "sg:province":"ME",
    "sg:tags":[
        "general",
        "contractor"
    ],
    "wof:name":"Power Lines Construction Inc",
    "wof:placetype":"venue"
},
  "geometry": {"coordinates":[-68.601698,44.912898],"type":"Point"}
}