{
  "type": "Feature",
  "properties": {
    "addr:full":"28 Dock Sq Kennebunkport ME 04046",
    "addr:housenumber":"28",
    "addr:postcode":"04046",
    "addr:street":"Dock Sq",
    "iso:country":"US",
    "sg:address":"28 Dock Sq",
    "sg:city":"Kennebunkport",
    "sg:classifiers":[
        {
            "category":"Shopping",
            "type":"Retail Goods"
        }
    ],
    "sg:phone":"+1 207 967 0493",
    "sg:postcode":"04046",
    "sg:province":"ME",
    "sg:website":"www.beachgrassshop.com/",
    "wof:name":"Beach Grass",
    "wof:placetype":"venue"
},
  "geometry": {"coordinates":[-70.47717900000001,43.361602],"type":"Point"}
}