{
  "type": "Feature",
  "properties": {
    "addr:full":"238 Ocean Ave Portland ME 04103",
    "addr:housenumber":"238",
    "addr:postcode":"04103",
    "addr:street":"Ocean Ave",
    "iso:country":"US",
    "sg:address":"238 Ocean Ave",
    "sg:city":"Portland",
    "sg:classifiers":[
        {
            "category":"Personal",
            "subcategory":"Beauty Salon",
            "type":"Services"
        }
    ],
    "sg:phone":"+1 207 774 3763",
    "sg:postcode":"04103",
    "sg:province":"ME",
    "sg:tags":[
        "shop"
    ],
    "wof:name":"Salon 238",
    "wof:placetype":"venue"
},
  "geometry": {"coordinates":[-70.279196,43.679108],"type":"Point"}
}