{
  "type": "Feature",
  "properties": {
    "addr:full":"160 Broadway Bangor ME 04401",
    "addr:housenumber":"160",
    "addr:postcode":"04401",
    "addr:street":"Broadway",
    "iso:country":"US",
    "sg:address":"160 Broadway",
    "sg:city":"Bangor",
    "sg:classifiers":[
        {
            "category":"Real Estate",
            "subcategory":"Real Estate Agent",
            "type":"Services"
        }
    ],
    "sg:phone":"+1 207 942 1585",
    "sg:postcode":"04401",
    "sg:province":"ME",
    "sg:tags":[
        "appraiser"
    ],
    "wof:name":"Singleton Appraisal Co",
    "wof:placetype":"venue"
},
  "geometry": {"coordinates":[-68.769041,44.808351],"type":"Point"}
}