{
  "type": "Feature",
  "properties": {
    "addr:full":"195 Riverside St Portland ME 04103",
    "addr:housenumber":"195",
    "addr:postcode":"04103",
    "addr:street":"Riverside St",
    "iso:country":"US",
    "sg:address":"195 Riverside St",
    "sg:city":"Portland",
    "sg:classifiers":[
        {
            "category":"Communications",
            "type":"Services"
        }
    ],
    "sg:phone":"+1 207 828 0018",
    "sg:postcode":"04103",
    "sg:province":"ME",
    "wof:name":"G4 Communications",
    "wof:placetype":"venue"
},
  "geometry": {"coordinates":[-70.32874099999999,43.677572],"type":"Point"}
}