{
  "type": "Feature",
  "properties": {
    "addr:full":"618 Overlock Hill Rd Union ME 04862",
    "addr:housenumber":"618",
    "addr:postcode":"04862",
    "addr:street":"Overlock Hill Rd",
    "iso:country":"US",
    "sg:address":"618 Overlock Hill Rd",
    "sg:city":"Union",
    "sg:classifiers":[
        {
            "category":"Building & Trades",
            "subcategory":"Construction",
            "type":"Services"
        }
    ],
    "sg:phone":"+1 207 785 4268",
    "sg:postcode":"04862",
    "sg:province":"ME",
    "sg:tags":[
        "general",
        "contractor"
    ],
    "wof:name":"J & L Construction",
    "wof:placetype":"venue"
},
  "geometry": {"coordinates":[-69.312652,44.227697],"type":"Point"}
}