{
  "type": "Feature",
  "properties": {
    "iso:country":"US",
    "sg:address":"299 N Hill Rd",
    "sg:city":"Weld",
    "sg:classifiers":[
        {
            "category":"Recreation",
            "type":"Entertainment"
        }
    ],
    "sg:phone":"+1 207 585 2261",
    "sg:postcode":"04220",
    "sg:province":"ME",
    "sg:tags":[
        "parks"
    ],
    "sg:website":"www.campwithme.com",
    "wof:name":"Mt Blue State Park",
    "wof:placetype":"venue"
},
  "geometry": {"coordinates":[-70.352413,44.269448],"type":"Point"}
}