{
  "type": "Feature",
  "properties": {
    "addr:full":"250 Main St Lewiston ME 04240",
    "addr:housenumber":"250",
    "addr:postcode":"04240",
    "addr:street":"Main St",
    "iso:country":"US",
    "sg:address":"250 Main St",
    "sg:city":"Lewiston",
    "sg:classifiers":[
        {
            "category":"Organizations",
            "subcategory":"Religious Organization",
            "type":"Services"
        }
    ],
    "sg:phone":"+1 207 782 0821",
    "sg:postcode":"04240",
    "sg:province":"ME",
    "sg:tags":[
        "church"
    ],
    "wof:name":"United Baptist Church",
    "wof:placetype":"venue"
},
  "geometry": {"coordinates":[-70.215901,44.100167],"type":"Point"}
}