{
  "type": "Feature",
  "properties": {
    "addr:full":"17 Old County Rd Milbridge ME 04658",
    "addr:housenumber":"17",
    "addr:postcode":"04658",
    "addr:street":"Old County Rd",
    "iso:country":"US",
    "sg:address":"17 Old County Rd",
    "sg:city":"Milbridge",
    "sg:classifiers":[
        {
            "category":"Manufacturing",
            "subcategory":"Tools & Machinery",
            "type":"Manufacturing & Wholesale Goods"
        }
    ],
    "sg:phone":"+1 207 546 2798",
    "sg:postcode":"04658",
    "sg:province":"ME",
    "sg:tags":[
        "equipment",
        "mfg"
    ],
    "wof:name":"Atlantic Aeromarine",
    "wof:placetype":"venue"
},
  "geometry": {"coordinates":[-67.876479,44.599131],"type":"Point"}
}