{
  "type": "Feature",
  "properties": {
    "addr:full":"86 Pleasant Hill Rd Scarborough ME 04074",
    "addr:housenumber":"86",
    "addr:postcode":"04074",
    "addr:street":"Pleasant Hill Rd",
    "iso:country":"US",
    "sg:address":"86 Pleasant Hill Rd",
    "sg:city":"Scarborough",
    "sg:classifiers":[
        {
            "category":"Building & Trades",
            "subcategory":"Construction",
            "type":"Services"
        }
    ],
    "sg:phone":"+1 207 883 3544",
    "sg:postcode":"04074",
    "sg:province":"ME",
    "sg:tags":[
        "dry wall",
        "contractor"
    ],
    "wof:name":"Wagner Drywall Inc",
    "wof:placetype":"venue"
},
  "geometry": {"coordinates":[-70.3022,43.602901],"type":"Point"}
}