{
  "type": "Feature",
  "properties": {
    "addr:full":"55 Beechwood Ln Durham ME 04222",
    "addr:housenumber":"55",
    "addr:postcode":"04222",
    "addr:street":"Beechwood Ln",
    "iso:country":"US",
    "sg:address":"55 Beechwood Ln",
    "sg:city":"Durham",
    "sg:classifiers":[
        {
            "category":"Building & Trades",
            "subcategory":"Construction",
            "type":"Services"
        }
    ],
    "sg:phone":"+1 207 688 4116",
    "sg:postcode":"04222",
    "sg:province":"ME",
    "sg:tags":[
        "stonework",
        "masonry",
        "other"
    ],
    "wof:name":"Yankee Tradesmen",
    "wof:placetype":"venue"
},
  "geometry": {"coordinates":[-70.148934,43.924223],"type":"Point"}
}