{
  "type": "Feature",
  "properties": {
    "iso:country":"US",
    "sg:address":"162 Elm St",
    "sg:city":"Newport",
    "sg:classifiers":[
        {
            "category":"Home & Garden",
            "subcategory":"Building Materials",
            "type":"Retail Goods"
        }
    ],
    "sg:phone":"+1 207 368 5698",
    "sg:postcode":"04953",
    "sg:province":"ME",
    "sg:tags":[
        "glass",
        "window",
        "plate"
    ],
    "wof:name":"Newport Glass",
    "wof:placetype":"venue"
},
  "geometry": {"coordinates":[-69.241626,44.824215],"type":"Point"}
}