{
  "type": "Feature",
  "properties": {
    "addr:full":"945 Center St Auburn ME 04210",
    "addr:housenumber":"945",
    "addr:postcode":"04210",
    "addr:street":"Center St",
    "iso:country":"US",
    "sg:address":"945 Center St",
    "sg:city":"Auburn",
    "sg:classifiers":[
        {
            "category":"Autos & Motor Vehicles",
            "subcategory":"Auto Supplies",
            "type":"Retail Goods"
        }
    ],
    "sg:phone":"+1 207 786 0400",
    "sg:postcode":"04210",
    "sg:province":"ME",
    "sg:tags":[
        "automobile",
        "parts"
    ],
    "wof:name":"Foreign Autopart",
    "wof:placetype":"venue"
},
  "geometry": {"coordinates":[-70.224909,44.130956],"type":"Point"}
}