{
  "type": "Feature",
  "properties": {
    "addr:city":"Kennebunkport",
    "addr:full":"195 Log Cabin Road Kennebunkport, Me 04046-1690",
    "addr:house_number":"195",
    "addr:housenumber":"195",
    "addr:phone":"+1 207-967-2800",
    "addr:postcode":"04046-1690",
    "addr:road":"Log Cabin Road",
    "addr:state":"ME",
    "addr:street":"Log Cabin Rd",
    "iso:country":"US",
    "sg:address":"195 Log Cabin Rd",
    "sg:city":"Kennebunkport",
    "sg:classifiers":[
        {
            "category":"Museum",
            "type":"Entertainment"
        }
    ],
    "sg:phone":"+1 207 967 2712",
    "sg:postcode":"04046",
    "sg:province":"ME",
    "sg:website":"www.trolleymuseum.org/",
    "wof:airports":[
        102527407
    ],
    "wof:name":"Seashore Trolley Museum",
    "wof:placetype":"venue"
},
  "geometry": {"coordinates":[-70.48942,43.4071],"type":"Point"}
}