{
  "type": "Feature",
  "properties": {
    "addr:full":"195 Log Cabin Rd Kennebunkport ME 04046",
    "addr:housenumber":"195",
    "addr:postcode":"04046",
    "addr:street":"Log Cabin Rd",
    "iso:country":"US",
    "sg:address":"195 Log Cabin Rd",
    "sg:city":"Kennebunkport",
    "sg:classifiers":[
        {
            "category":"Museum",
            "type":"Entertainment"
        }
    ],
    "sg:phone":"+1 207 967 2712",
    "sg:postcode":"04046",
    "sg:province":"ME",
    "sg:website":"www.trolleymuseum.org/",
    "wof:name":"Seashore Trolley Museum",
    "wof:placetype":"venue"
},
  "geometry": {"coordinates":[-70.492699,43.408401],"type":"Point"}
}