{
  "type": "Feature",
  "properties": {
    "addr:full":"9 S Hunts Meadow Rd Whitefield ME 04353",
    "addr:housenumber":"9",
    "addr:postcode":"04353",
    "addr:street":"S Hunts Meadow Rd",
    "iso:country":"US",
    "sg:address":"9 S Hunts Meadow Rd",
    "sg:city":"Whitefield",
    "sg:classifiers":[
        {
            "category":"Professional",
            "subcategory":"Computer Services",
            "type":"Services"
        }
    ],
    "sg:phone":"+1 207 588 0979",
    "sg:postcode":"04353",
    "sg:province":"ME",
    "sg:tags":[
        "datum"
    ],
    "wof:name":"Cec Systems",
    "wof:placetype":"venue"
},
  "geometry": {"coordinates":[-69.65858799999999,44.21953],"type":"Point"}
}