{
  "type": "Feature",
  "properties": {
    "iso:country":"US",
    "sg:address":"30 Sunset Dr",
    "sg:city":"Old Town",
    "sg:classifiers":[
        {
            "category":"Professional",
            "subcategory":"Business Services",
            "type":"Services"
        }
    ],
    "sg:phone":"+1 207 827 2998",
    "sg:postcode":"04468",
    "sg:province":"ME",
    "wof:name":"Levitsky Design",
    "wof:placetype":"venue"
},
  "geometry": {"coordinates":[-68.657781,44.938782],"type":"Point"}
}