{
  "type": "Feature",
  "properties": {
    "addr:full":"85 Lincoln Ave Rumford ME 04276",
    "addr:housenumber":"85",
    "addr:postcode":"04276",
    "addr:street":"Lincoln Ave",
    "iso:country":"US",
    "sg:address":"85 Lincoln Ave",
    "sg:city":"Rumford",
    "sg:classifiers":[
        {
            "category":"Government",
            "subcategory":"Office",
            "type":"Public Place"
        }
    ],
    "sg:phone":"+1 207 364 3010",
    "sg:postcode":"04276",
    "sg:province":"ME",
    "sg:tags":[
        "federal",
        "program",
        "adm"
    ],
    "wof:name":"US Census Bureau",
    "wof:placetype":"venue"
},
  "geometry": {"coordinates":[-70.55067200000001,44.55397],"type":"Point"}
}