{
  "type": "Feature",
  "properties": {
    "addr:full":"40 School St Porter ME 04068",
    "addr:housenumber":"40",
    "addr:postcode":"04068",
    "addr:street":"School St",
    "iso:country":"US",
    "sg:address":"40 School St",
    "sg:city":"Porter",
    "sg:classifiers":[
        {
            "category":"Home & Garden",
            "subcategory":"Furniture",
            "type":"Retail Goods"
        }
    ],
    "sg:phone":"+1 207 625 7800",
    "sg:postcode":"04068",
    "sg:province":"ME",
    "sg:tags":[
        "equipment",
        "kitchen",
        "cabinet"
    ],
    "wof:name":"Homestyle Kitchens",
    "wof:placetype":"venue"
},
  "geometry": {"coordinates":[-70.89097599999999,43.809066],"type":"Point"}
}