{
  "type": "Feature",
  "properties": {
    "addr:full":"156 E Main St Dover Foxcroft ME 04426",
    "addr:housenumber":"156",
    "addr:postcode":"04426",
    "addr:street":"E Main St",
    "iso:country":"US",
    "sg:address":"156 E Main St",
    "sg:city":"Dover Foxcroft",
    "sg:classifiers":[
        {
            "category":"Government",
            "subcategory":"Office",
            "type":"Public Place"
        }
    ],
    "sg:phone":"+1 207 564 7083",
    "sg:postcode":"04426",
    "sg:province":"ME",
    "sg:tags":[
        "state",
        "program"
    ],
    "wof:name":"Motor Vehicle Div",
    "wof:placetype":"venue"
},
  "geometry": {"coordinates":[-69.21762,45.179792],"type":"Point"}
}