{
  "type": "Feature",
  "properties": {
    "iso:country":"US",
    "sg:address":"628 Main Rd",
    "sg:city":"Holden",
    "sg:classifiers":[
        {
            "category":"Building & Trades",
            "subcategory":"Equipment Rental",
            "type":"Services"
        }
    ],
    "sg:phone":"+1 207 843 6630",
    "sg:postcode":"04429",
    "sg:province":"ME",
    "sg:tags":[
        "yard"
    ],
    "wof:name":"Granville Rental Station",
    "wof:placetype":"venue"
},
  "geometry": {"coordinates":[-68.712636,44.76752],"type":"Point"}
}