{
  "type": "Feature",
  "properties": {
    "iso:country":"US",
    "sg:address":"799 Main Rd N",
    "sg:city":"Hampden",
    "sg:classifiers":[
        {
            "category":"Building & Trades",
            "subcategory":"Electrical",
            "type":"Services"
        }
    ],
    "sg:phone":"+1 207 945 9899",
    "sg:postcode":"04444",
    "sg:province":"ME",
    "sg:tags":[
        "electric",
        "contractor"
    ],
    "wof:name":"United Electrical Sys",
    "wof:placetype":"venue"
},
  "geometry": {"coordinates":[-68.7852,44.77817],"type":"Point"}
}