{
  "type": "Feature",
  "properties": {
    "iso:country":"US",
    "sg:address":"72 Winthrop St",
    "sg:city":"Augusta",
    "sg:classifiers":[
        {
            "category":"Social Services",
            "type":"Services"
        }
    ],
    "sg:phone":"+1 207 620 7130",
    "sg:postcode":"04330",
    "sg:province":"ME",
    "sg:tags":[
        "organization",
        "welfare"
    ],
    "wof:name":"Living Innovations",
    "wof:placetype":"venue"
},
  "geometry": {"coordinates":[-69.779296,44.315467],"type":"Point"}
}