{
  "type": "Feature",
  "properties": {
    "addr:full":"190 Birch St Lewiston ME 04240",
    "addr:housenumber":"190",
    "addr:postcode":"04240",
    "addr:street":"Birch St",
    "iso:country":"US",
    "sg:address":"190 Birch St",
    "sg:city":"Lewiston",
    "sg:classifiers":[
        {
            "category":"Professional",
            "subcategory":"Management & Consulting",
            "type":"Services"
        }
    ],
    "sg:phone":"+1 207 782 4238",
    "sg:postcode":"04240",
    "sg:province":"ME",
    "sg:tags":[
        "construction"
    ],
    "wof:name":"Richard Theriault",
    "wof:placetype":"venue"
},
  "geometry": {"coordinates":[-70.205765,44.094841],"type":"Point"}
}