{
  "type": "Feature",
  "properties": {
    "addr:full":"36 Garfield St Calais ME 04619",
    "addr:housenumber":"36",
    "addr:postcode":"04619",
    "addr:street":"Garfield St",
    "iso:country":"US",
    "sg:address":"36 Garfield St",
    "sg:city":"Calais",
    "sg:classifiers":[
        {
            "category":"Retail",
            "subcategory":"Auto Repair",
            "type":"Services"
        }
    ],
    "sg:phone":"+1 207 454 8419",
    "sg:postcode":"04619",
    "sg:province":"ME",
    "sg:tags":[
        "general"
    ],
    "wof:name":"Ingersoll Deisel Service Inc",
    "wof:placetype":"venue"
},
  "geometry": {"coordinates":[-67.28459599999999,45.181211],"type":"Point"}
}