{
  "type": "Feature",
  "properties": {
    "addr:full":"722 Congress St Portland ME 04102",
    "addr:housenumber":"722",
    "addr:postcode":"04102",
    "addr:street":"Congress St",
    "iso:country":"US",
    "sg:address":"722 Congress St",
    "sg:city":"Portland",
    "sg:classifiers":[
        {
            "category":"Manufacturing",
            "subcategory":"Printing",
            "type":"Manufacturing & Wholesale Goods"
        }
    ],
    "sg:phone":"+1 207 775 4339",
    "sg:postcode":"04102",
    "sg:province":"ME",
    "sg:tags":[
        "publisher"
    ],
    "sg:website":"www.portlandmagazine.net",
    "wof:name":"Portland Magazine",
    "wof:placetype":"venue"
},
  "geometry": {"coordinates":[-70.269046,43.652948],"type":"Point"}
}