{
  "type": "Feature",
  "properties": {
    "addr:full":"246 Old Greene Rd Lewiston ME 04240",
    "addr:housenumber":"246",
    "addr:postcode":"04240",
    "addr:street":"Old Greene Rd",
    "iso:country":"US",
    "sg:address":"246 Old Greene Rd",
    "sg:city":"Lewiston",
    "sg:classifiers":[
        {
            "category":"Arts & Performance",
            "subcategory":"Theater",
            "type":"Entertainment"
        }
    ],
    "sg:phone":"+1 207 786 0735",
    "sg:postcode":"04240",
    "sg:province":"ME",
    "sg:tags":[
        "live",
        "music"
    ],
    "wof:name":"Martin Entertainment",
    "wof:placetype":"venue"
},
  "geometry": {"coordinates":[-70.161373,44.110112],"type":"Point"}
}