{
  "type": "Feature",
  "properties": {
    "iso:country":"US",
    "sg:address":"64 Eastern Promenade",
    "sg:city":"Portland",
    "sg:classifiers":[
        {
            "category":"Personal",
            "type":"Services"
        }
    ],
    "sg:phone":"+1 207 773 7540",
    "sg:postcode":"04101",
    "sg:province":"ME",
    "sg:tags":[
        "therapist",
        "massage"
    ],
    "wof:name":"Jane Kressy",
    "wof:placetype":"venue"
},
  "geometry": {"coordinates":[-70.241316,43.665745],"type":"Point"}
}