{
  "type": "Feature",
  "properties": {
    "iso:country":"US",
    "sg:address":"386 Blaine Ave",
    "sg:city":"Guilford",
    "sg:classifiers":[
        {
            "category":"Building & Trades",
            "subcategory":"Construction",
            "type":"Services"
        }
    ],
    "sg:phone":"+1 207 876 2276",
    "sg:postcode":"04443",
    "sg:province":"ME",
    "sg:tags":[
        "foundation"
    ],
    "wof:name":"French Construction",
    "wof:placetype":"venue"
},
  "geometry": {"coordinates":[-69.390244,45.211188],"type":"Point"}
}