{
  "type": "Feature",
  "properties": {
    "addr:full":"25 Preble St Portland ME 04101",
    "addr:housenumber":"25",
    "addr:postcode":"04101",
    "addr:street":"Preble St",
    "iso:country":"US",
    "sg:address":"25 Preble St",
    "sg:city":"Portland",
    "sg:classifiers":[
        {
            "category":"Food & Beverages",
            "subcategory":"Bakery",
            "type":"Retail Goods"
        }
    ],
    "sg:phone":"+1 207 228 2058",
    "sg:postcode":"04101",
    "sg:province":"ME",
    "sg:tags":[
        "baker"
    ],
    "wof:name":"Downhome Cookin'",
    "wof:placetype":"venue"
},
  "geometry": {"coordinates":[-70.259815,43.65746],"type":"Point"}
}