{
  "type": "Feature",
  "properties": {
    "addr:full":"175 W Main St Searsport ME 04974",
    "addr:housenumber":"175",
    "addr:postcode":"04974",
    "addr:street":"W Main St",
    "iso:country":"US",
    "sg:address":"175 W Main St",
    "sg:city":"Searsport",
    "sg:classifiers":[
        {
            "category":"Real Estate",
            "subcategory":"Real Estate Agent",
            "type":"Services"
        }
    ],
    "sg:phone":"+1 207 548 0100",
    "sg:postcode":"04974",
    "sg:province":"ME",
    "wof:name":"Remarkable Realty",
    "wof:placetype":"venue"
},
  "geometry": {"coordinates":[-68.934218,44.447331],"type":"Point"}
}