{
  "type": "Feature",
  "properties": {
    "addr:full":"17 Graham Rd Westbrook ME 04092",
    "addr:housenumber":"17",
    "addr:postcode":"04092",
    "addr:street":"Graham Rd",
    "iso:country":"US",
    "sg:address":"17 Graham Rd",
    "sg:city":"Westbrook",
    "sg:classifiers":[
        {
            "category":"Professional",
            "subcategory":"Computer Services",
            "type":"Services"
        }
    ],
    "sg:phone":"+1 207 854 0357",
    "sg:postcode":"04092",
    "sg:province":"ME",
    "sg:tags":[
        "repair"
    ],
    "wof:name":"Hard Drive Computing",
    "wof:placetype":"venue"
},
  "geometry": {"coordinates":[-70.356405,43.690264],"type":"Point"}
}