{
  "type": "Feature",
  "properties": {
    "addr:full":"72 Winthrop St Augusta ME 04330",
    "addr:housenumber":"72",
    "addr:postcode":"04330",
    "addr:street":"Winthrop St",
    "iso:country":"US",
    "sg:address":"72 Winthrop St",
    "sg:city":"Augusta",
    "sg:classifiers":[
        {
            "category":"Personal",
            "type":"Services"
        }
    ],
    "sg:phone":"+1 207 622 4062",
    "sg:postcode":"04330",
    "sg:province":"ME",
    "sg:tags":[
        "therapist",
        "massage"
    ],
    "wof:name":"Ida Gammon-Wilson",
    "wof:placetype":"venue"
},
  "geometry": {"coordinates":[-69.779296,44.315467],"type":"Point"}
}