{
  "type": "Feature",
  "properties": {
    "iso:country":"US",
    "sg:address":"41 Davis Dr",
    "sg:city":"Hermon",
    "sg:classifiers":[
        {
            "category":"Manufacturing",
            "subcategory":"Signs",
            "type":"Manufacturing & Wholesale Goods"
        }
    ],
    "sg:phone":"+1 207 848 7889",
    "sg:postcode":"04401",
    "sg:province":"ME",
    "wof:name":"Caron Sign Co Inc",
    "wof:placetype":"venue"
},
  "geometry": {"coordinates":[-68.716324,44.835269],"type":"Point"}
}