{
  "type": "Feature",
  "properties": {
    "iso:country":"US",
    "sg:address":"265 Pleasant Ave",
    "sg:city":"Peaks Island",
    "sg:classifiers":[
        {
            "category":"Professional",
            "subcategory":"Art Services",
            "type":"Services"
        }
    ],
    "sg:phone":"+1 207 766 9726",
    "sg:postcode":"04108",
    "sg:province":"ME",
    "sg:tags":[
        "commercial",
        "design"
    ],
    "wof:name":"Marty Braun Illustrator",
    "wof:placetype":"venue"
},
  "geometry": {"coordinates":[-70.189707,43.66851],"type":"Point"}
}