{
  "type": "Feature",
  "properties": {
    "iso:country":"US",
    "sg:address":"51 US Hwy 1",
    "sg:city":"Scarborough",
    "sg:classifiers":[
        {
            "category":"Professional",
            "subcategory":"Management & Consulting",
            "type":"Services"
        }
    ],
    "sg:phone":"+1 207 774 0500",
    "sg:postcode":"04074",
    "sg:province":"ME",
    "sg:tags":[
        "consultant",
        "business"
    ],
    "wof:name":"Human Resource Partners LLC",
    "wof:placetype":"venue"
},
  "geometry": {"coordinates":[-70.396084,43.564077],"type":"Point"}
}