{
  "type": "Feature",
  "properties": {
    "addr:full":"1148 Main St Jay ME 04239",
    "addr:housenumber":"1148",
    "addr:postcode":"04239",
    "addr:street":"Main St",
    "iso:country":"US",
    "sg:address":"1148 Main St",
    "sg:city":"Jay",
    "sg:classifiers":[
        {
            "category":"Manufacturing",
            "subcategory":"Metals",
            "type":"Manufacturing & Wholesale Goods"
        }
    ],
    "sg:phone":"+1 207 645 2581",
    "sg:postcode":"04239",
    "sg:province":"ME",
    "sg:tags":[
        "steel"
    ],
    "wof:name":"Howie's Welding",
    "wof:placetype":"venue"
},
  "geometry": {"coordinates":[-70.235021,44.559239],"type":"Point"}
}