{
  "type": "Feature",
  "properties": {
    "addr:full":"38 Memory Ln West Gardiner ME 04345",
    "addr:housenumber":"38",
    "addr:postcode":"04345",
    "addr:street":"Memory Ln West",
    "iso:country":"US",
    "sg:address":"38 Memory Ln",
    "sg:city":"West Gardiner",
    "sg:classifiers":[
        {
            "category":"Social Services",
            "subcategory":"Child Care",
            "type":"Services"
        }
    ],
    "sg:phone":"+1 207 582 1434",
    "sg:postcode":"04345",
    "sg:province":"ME",
    "wof:name":"Kimmie's Kids Daycare",
    "wof:placetype":"venue"
},
  "geometry": {"coordinates":[-69.875637,44.213216],"type":"Point"}
}