{
  "type": "Feature",
  "properties": {
    "iso:country":"US",
    "sg:address":"10 Forest Ln",
    "sg:city":"Cumberland Ctr",
    "sg:classifiers":[
        {
            "category":"Building & Trades",
            "subcategory":"Electrical",
            "type":"Services"
        }
    ],
    "sg:phone":"+1 207 829 4179",
    "sg:postcode":"04021",
    "sg:province":"ME",
    "sg:tags":[
        "electric",
        "contractor"
    ],
    "wof:name":"Brian's Plumbing & Electric",
    "wof:placetype":"venue"
},
  "geometry": {"coordinates":[-70.320303,43.814769],"type":"Point"}
}