{
  "type": "Feature",
  "properties": {
    "iso:country":"US",
    "sg:address":"913 Post Rd",
    "sg:city":"Wells",
    "sg:classifiers":[
        {
            "category":"Sports & Exercise",
            "subcategory":"Gym",
            "type":"Entertainment"
        }
    ],
    "sg:phone":"+1 207 641 8610",
    "sg:postcode":"04090",
    "sg:province":"ME",
    "sg:tags":[
        "club",
        "health",
        "studio",
        "gymnasium"
    ],
    "wof:name":"Curves For Women",
    "wof:placetype":"venue"
},
  "geometry": {"coordinates":[-70.584783,43.30996],"type":"Point"}
}