{
  "type": "Feature",
  "properties": {
    "addr:full":"78 Eben Hill Rd Yarmouth ME 04096",
    "addr:housenumber":"78",
    "addr:postcode":"04096",
    "addr:street":"Eben Hill Rd",
    "iso:country":"US",
    "sg:address":"78 Eben Hill Rd",
    "sg:city":"Yarmouth",
    "sg:classifiers":[
        {
            "category":"Health Services",
            "subcategory":"Health Practitioner",
            "type":"Services"
        }
    ],
    "sg:phone":"+1 207 846 3262",
    "sg:postcode":"04096",
    "sg:province":"ME",
    "wof:name":"Salter Margery PH D",
    "wof:placetype":"venue"
},
  "geometry": {"coordinates":[-70.135852,43.765367],"type":"Point"}
}