{
  "type": "Feature",
  "properties": {
    "addr:full":"71 Main St Newcastle ME 04553",
    "addr:housenumber":"71",
    "addr:postcode":"04553",
    "addr:street":"Main St",
    "iso:country":"US",
    "sg:address":"71 Main St",
    "sg:city":"Newcastle",
    "sg:classifiers":[
        {
            "category":"Health Services",
            "subcategory":"Doctor",
            "type":"Services"
        }
    ],
    "sg:phone":"+1 207 563 3782",
    "sg:postcode":"04553",
    "sg:province":"ME",
    "sg:tags":[
        "physician",
        "surgeon"
    ],
    "wof:name":"Roy E Seibel Jr MD",
    "wof:placetype":"venue"
},
  "geometry": {"coordinates":[-69.536586,44.034811],"type":"Point"}
}