{
  "type": "Feature",
  "properties": {
    "addr:full":"58 Park St Milo ME 04463",
    "addr:housenumber":"58",
    "addr:postcode":"04463",
    "addr:street":"Park St",
    "iso:country":"US",
    "sg:address":"58 Park St",
    "sg:city":"Milo",
    "sg:classifiers":[
        {
            "category":"Shopping",
            "subcategory":"Used Merchandise",
            "type":"Retail Goods"
        }
    ],
    "sg:phone":"+1 207 943 5671",
    "sg:postcode":"04463",
    "sg:province":"ME",
    "wof:name":"Joyce Antiques",
    "wof:placetype":"venue"
},
  "geometry": {"coordinates":[-68.987548,45.258053],"type":"Point"}
}