{
  "type": "Feature",
  "properties": {
    "iso:country":"US",
    "sg:address":"544 S Main St",
    "sg:city":"Solon",
    "sg:classifiers":[
        {
            "category":"Manufacturing",
            "subcategory":"Lumber",
            "type":"Manufacturing & Wholesale Goods"
        }
    ],
    "sg:phone":"+1 207 643 2301",
    "sg:postcode":"04979",
    "sg:province":"ME",
    "sg:tags":[
        "logging"
    ],
    "wof:name":"Paul Ollivier",
    "wof:placetype":"venue"
},
  "geometry": {"coordinates":[-69.826743,44.921887],"type":"Point"}
}