{
  "type": "Feature",
  "properties": {
    "addr:full":"52 Stanley St Norway ME 04210",
    "addr:housenumber":"52",
    "addr:postcode":"04210",
    "addr:street":"Stanley St",
    "iso:country":"US",
    "sg:address":"52 Stanley St",
    "sg:city":"Norway",
    "sg:classifiers":[
        {
            "category":"Professional",
            "subcategory":"Engineering",
            "type":"Services"
        }
    ],
    "sg:phone":"+1 207 743 6585",
    "sg:postcode":"04210",
    "sg:province":"ME",
    "sg:tags":[
        "engineer"
    ],
    "wof:name":"Ped",
    "wof:placetype":"venue"
},
  "geometry": {"coordinates":[-70.227283,44.108048],"type":"Point"}
}