{
  "type": "Feature",
  "properties": {
    "addr:full":"175 Bucksport Rd Ellsworth ME 04605",
    "addr:housenumber":"175",
    "addr:postcode":"04605",
    "addr:street":"Bucksport Rd",
    "iso:country":"US",
    "sg:address":"175 Bucksport Rd",
    "sg:city":"Ellsworth",
    "sg:classifiers":[
        {
            "category":"Shopping",
            "subcategory":"Crafts & Fabrics",
            "type":"Retail Goods"
        }
    ],
    "sg:phone":"+1 207 664 0750",
    "sg:postcode":"04605",
    "sg:province":"ME",
    "sg:tags":[
        "shop"
    ],
    "wof:name":"Silks & Tapestries Inc",
    "wof:placetype":"venue"
},
  "geometry": {"coordinates":[-68.43179000000001,44.539045],"type":"Point"}
}