{
  "type": "Feature",
  "properties": {
    "addr:full":"1 Schooner Ridge Rd Bath ME 04530",
    "addr:housenumber":"1",
    "addr:postcode":"04530",
    "addr:street":"Schooner Ridge Rd",
    "iso:country":"US",
    "sg:address":"1 Schooner Ridge Rd",
    "sg:city":"Bath",
    "sg:classifiers":[
        {
            "category":"Real Estate",
            "subcategory":"Real Estate Operator",
            "type":"Services"
        }
    ],
    "sg:phone":"+1 207 442 7245",
    "sg:postcode":"04530",
    "sg:province":"ME",
    "sg:tags":[
        "condominium"
    ],
    "wof:name":"Schooner Ridge Condo",
    "wof:placetype":"venue"
},
  "geometry": {"coordinates":[-69.819597,43.892293],"type":"Point"}
}