{
  "type": "Feature",
  "properties": {
    "iso:country":"US",
    "sg:address":"251 Water St",
    "sg:city":"Gardiner",
    "sg:classifiers":[
        {
            "category":"Professional",
            "subcategory":"Lawyer & Legal Services",
            "type":"Services"
        }
    ],
    "sg:phone":"+1 207 582 3650",
    "sg:postcode":"04345",
    "sg:province":"ME",
    "sg:tags":[
        "attorney"
    ],
    "wof:name":"Farris Law",
    "wof:placetype":"venue"
},
  "geometry": {"coordinates":[-69.773768,44.229854],"type":"Point"}
}