{
  "type": "Feature",
  "properties": {
    "addr:full":"203 Birch Point Rd Wiscasset ME 04578",
    "addr:housenumber":"203",
    "addr:postcode":"04578",
    "addr:street":"Birch Point Rd",
    "iso:country":"US",
    "sg:address":"203 Birch Point Rd",
    "sg:city":"Wiscasset",
    "sg:classifiers":[
        {
            "category":"Wholesale",
            "subcategory":"Computers",
            "type":"Manufacturing & Wholesale Goods"
        }
    ],
    "sg:phone":"+1 207 882 7202",
    "sg:postcode":"04578",
    "sg:province":"ME",
    "wof:name":"Harvey John",
    "wof:placetype":"venue"
},
  "geometry": {"coordinates":[-69.68733,43.979742],"type":"Point"}
}