{
  "type": "Feature",
  "properties": {
    "addr:full":"862 Heald Hwy Union ME 04862",
    "addr:housenumber":"862",
    "addr:postcode":"04862",
    "addr:street":"Heald Hwy Union",
    "iso:country":"US",
    "sg:address":"862 Heald Hwy",
    "sg:city":"Union",
    "sg:classifiers":[
        {
            "category":"Personal",
            "subcategory":"Beauty Salon",
            "type":"Services"
        }
    ],
    "sg:phone":"+1 207 785 6500",
    "sg:postcode":"04862",
    "sg:province":"ME",
    "wof:name":"Kathy's Full Svc Salon",
    "wof:placetype":"venue"
},
  "geometry": {"coordinates":[-69.246376,44.213493],"type":"Point"}
}