{
  "type": "Feature",
  "properties": {
    "iso:country":"US",
    "sg:address":"1200 Ohio St",
    "sg:city":"Bangor",
    "sg:classifiers":[
        {
            "category":"Social Services",
            "type":"Services"
        }
    ],
    "sg:phone":"+1 207 945 5021",
    "sg:postcode":"04401",
    "sg:province":"ME",
    "sg:tags":[
        "organization",
        "welfare"
    ],
    "wof:name":"St Andre Home-Bangor Group Hme",
    "wof:placetype":"venue"
},
  "geometry": {"coordinates":[-68.81709600000001,44.830538],"type":"Point"}
}