{
  "type": "Feature",
  "properties": {
    "addr:full":"51 W Gray Rd Gray ME 04039",
    "addr:housenumber":"51",
    "addr:postcode":"04039",
    "addr:street":"W Gray Rd",
    "iso:country":"US",
    "sg:address":"51 W Gray Rd",
    "sg:city":"Gray",
    "sg:classifiers":[
        {
            "category":"Education",
            "subcategory":"School",
            "type":"Public Place"
        }
    ],
    "sg:phone":"+1 207 657 6994",
    "sg:postcode":"04039",
    "sg:province":"ME",
    "wof:name":"Northern New England Institute",
    "wof:placetype":"venue"
},
  "geometry": {"coordinates":[-70.340659,43.882718],"type":"Point"}
}