{
  "type": "Feature",
  "properties": {
    "iso:country":"US",
    "sg:address":"420 Chopps Point Rd",
    "sg:city":"Woolwich",
    "sg:classifiers":[
        {
            "category":"Travel",
            "subcategory":"Campground",
            "type":"Entertainment"
        }
    ],
    "sg:phone":"+1 207 443 5860",
    "sg:postcode":"04579",
    "sg:province":"ME",
    "sg:tags":[
        "camp"
    ],
    "sg:website":"www.choppoint.com",
    "wof:name":"Chop Point Camp",
    "wof:placetype":"venue"
},
  "geometry": {"coordinates":[-69.808926,44.00379],"type":"Point"}
}