{
  "type": "Feature",
  "properties": {
    "addr:full":"50 Oarweed Rd Ogunquit ME 03907",
    "addr:housenumber":"50",
    "addr:postcode":"03907",
    "addr:street":"Oarweed Rd",
    "iso:country":"US",
    "sg:address":"50 Oarweed Rd",
    "sg:city":"Ogunquit",
    "sg:classifiers":[
        {
            "category":"Home & Garden",
            "subcategory":"Home Furnishings",
            "type":"Retail Goods"
        }
    ],
    "sg:phone":"+1 207 646 7619",
    "sg:postcode":"03907",
    "sg:province":"ME",
    "sg:tags":[
        "pottery"
    ],
    "wof:name":"Pottery Shop In Perkins Cove",
    "wof:placetype":"venue"
},
  "geometry": {"coordinates":[-70.592046,43.237889],"type":"Point"}
}