{
  "type": "Feature",
  "properties": {
    "iso:country":"US",
    "sg:address":"155 Saco Ave",
    "sg:city":"Old Orchard Bch",
    "sg:classifiers":[
        {
            "category":"Health Services",
            "subcategory":"Chiropractor",
            "type":"Services"
        }
    ],
    "sg:phone":"+1 207 934 4600",
    "sg:postcode":"04064",
    "sg:province":"ME",
    "wof:name":"Old Orchard Beach Chiropractic",
    "wof:placetype":"venue"
},
  "geometry": {"coordinates":[-70.390559,43.513242],"type":"Point"}
}