{
  "type": "Feature",
  "properties": {
    "iso:country":"US",
    "sg:address":"326 Main St",
    "sg:city":"Bingham",
    "sg:classifiers":[
        {
            "category":"Food & Beverages",
            "subcategory":"Groceries & Convenience Stores",
            "type":"Retail Goods"
        }
    ],
    "sg:phone":"+1 207 672 3322",
    "sg:postcode":"04901",
    "sg:province":"ME",
    "sg:tags":[
        "grocer"
    ],
    "wof:name":"Valley View Market",
    "wof:placetype":"venue"
},
  "geometry": {"coordinates":[-69.637053,44.564828],"type":"Point"}
}