{
  "type": "Feature",
  "properties": {
    "addr:full":"234 Penobscot Ave Millinocket ME 04462",
    "addr:housenumber":"234",
    "addr:postcode":"04462",
    "addr:street":"Penobscot Ave",
    "iso:country":"US",
    "sg:address":"234 Penobscot Ave",
    "sg:city":"Millinocket",
    "sg:classifiers":[
        {
            "category":"Personal",
            "subcategory":"Beauty Salon",
            "type":"Services"
        }
    ],
    "sg:phone":"+1 207 723 5115",
    "sg:postcode":"04462",
    "sg:province":"ME",
    "wof:name":"Hair Razor",
    "wof:placetype":"venue"
},
  "geometry": {"coordinates":[-68.70916,45.656348],"type":"Point"}
}