{
  "type": "Feature",
  "properties": {
    "iso:country":"US",
    "sg:address":"9 Burnham Rd",
    "sg:city":"Gorham",
    "sg:classifiers":[
        {
            "category":"Utilities",
            "subcategory":"Fuel Oil & Lpg",
            "type":"Services"
        }
    ],
    "sg:phone":"+1 207 839 4342",
    "sg:postcode":"04038",
    "sg:province":"ME",
    "sg:tags":[
        "firewood"
    ],
    "wof:name":"Southern Maine Firewood",
    "wof:placetype":"venue"
},
  "geometry": {"coordinates":[-70.420675,43.63624],"type":"Point"}
}