{
  "type": "Feature",
  "properties": {
    "addr:full":"968 Memorial Dr Winthrop ME 04364",
    "addr:housenumber":"968",
    "addr:postcode":"04364",
    "addr:street":"Memorial Dr",
    "iso:country":"US",
    "sg:address":"968 Memorial Dr",
    "sg:city":"Winthrop",
    "sg:classifiers":[
        {
            "category":"Professional",
            "type":"Services"
        }
    ],
    "sg:phone":"+1 207 377 4805",
    "sg:postcode":"04364",
    "sg:province":"ME",
    "sg:tags":[
        "writer"
    ],
    "wof:name":"ETW Inc Technical Writing",
    "wof:placetype":"venue"
},
  "geometry": {"coordinates":[-69.94522600000001,44.33752],"type":"Point"}
}