{
  "type": "Feature",
  "properties": {
    "iso:country":"US",
    "sg:address":"134 Front St",
    "sg:city":"Bath",
    "sg:classifiers":[
        {
            "category":"Organizations",
            "subcategory":"Religious Organization",
            "type":"Services"
        }
    ],
    "sg:phone":"+1 207 443 4994",
    "sg:postcode":"04530",
    "sg:province":"ME",
    "sg:tags":[
        "church"
    ],
    "wof:name":"Christian Science Society",
    "wof:placetype":"venue"
},
  "geometry": {"coordinates":[-69.81435500000001,43.914253],"type":"Point"}
}