{
  "type": "Feature",
  "properties": {
    "addr:full":"1787 Main St Sanford ME 04073",
    "addr:housenumber":"1787",
    "addr:postcode":"04073",
    "addr:street":"Main St",
    "iso:country":"US",
    "sg:address":"1787 Main St",
    "sg:city":"Sanford",
    "sg:classifiers":[
        {
            "category":"Wholesale",
            "subcategory":"Machinery & Supplies",
            "type":"Manufacturing & Wholesale Goods"
        }
    ],
    "sg:phone":"+1 207 324 1518",
    "sg:postcode":"04073",
    "sg:province":"ME",
    "sg:tags":[
        "equipment",
        "welding"
    ],
    "wof:name":"Advantage Gases & Tools",
    "wof:placetype":"venue"
},
  "geometry": {"coordinates":[-70.711955,43.402621],"type":"Point"}
}