{
  "type": "Feature",
  "properties": {
    "addr:full":"8 Lindsey St Rockland ME 04841",
    "addr:housenumber":"8",
    "addr:postcode":"04841",
    "addr:street":"Lindsey St",
    "iso:country":"US",
    "sg:address":"8 Lindsey St",
    "sg:city":"Rockland",
    "sg:classifiers":[
        {
            "category":"Food & Beverages",
            "subcategory":"Groceries & Convenience Stores",
            "type":"Retail Goods"
        }
    ],
    "sg:phone":"+1 207 594 7233",
    "sg:postcode":"04841",
    "sg:province":"ME",
    "sg:tags":[
        "product"
    ],
    "wof:name":"Penobscot Bay Soup Co",
    "wof:placetype":"venue"
},
  "geometry": {"coordinates":[-69.11084099999999,44.105989],"type":"Point"}
}