{
  "type": "Feature",
  "properties": {
    "iso:country":"US",
    "sg:address":"98 Eden St",
    "sg:city":"Bar Harbor",
    "sg:classifiers":[
        {
            "category":"Travel",
            "subcategory":"Hotels & Motels",
            "type":"Entertainment"
        }
    ],
    "sg:phone":"+1 207 288 3500",
    "sg:postcode":"04609",
    "sg:province":"ME",
    "sg:website":"www.acadiainn.com",
    "wof:name":"Acadia Inn",
    "wof:placetype":"venue"
},
  "geometry": {"coordinates":[-68.222186,44.394095],"type":"Point"}
}