{
  "type": "Feature",
  "properties": {
    "iso:country":"US",
    "sg:address":"250 Vernon St",
    "sg:city":"Bethel",
    "sg:classifiers":[
        {
            "category":"Building & Trades",
            "subcategory":"Construction",
            "type":"Services"
        }
    ],
    "sg:phone":"+1 207 824 2258",
    "sg:postcode":"04217",
    "sg:province":"ME",
    "sg:tags":[
        "general",
        "contractor"
    ],
    "wof:name":"Jack Cross Excavating",
    "wof:placetype":"venue"
},
  "geometry": {"coordinates":[-70.785856,44.408151],"type":"Point"}
}