{
  "type": "Feature",
  "properties": {
    "iso:country":"US",
    "sg:address":"717 Narragansett Trl",
    "sg:city":"Buxton",
    "sg:classifiers":[
        {
            "category":"Personal",
            "subcategory":"Beauty Salon",
            "type":"Services"
        }
    ],
    "sg:phone":"+1 207 929 3003",
    "sg:postcode":"04093",
    "sg:province":"ME",
    "wof:name":"Classic Cuts Plus",
    "wof:placetype":"venue"
},
  "geometry": {"coordinates":[-70.506072,43.631604],"type":"Point"}
}