{
  "type": "Feature",
  "properties": {
    "addr:full":"169 S Levant Rd Levant ME 04456",
    "addr:housenumber":"169",
    "addr:postcode":"04456",
    "addr:street":"S Levant Rd",
    "iso:country":"US",
    "sg:address":"169 S Levant Rd",
    "sg:city":"Levant",
    "sg:classifiers":[
        {
            "category":"Education",
            "subcategory":"School",
            "type":"Public Place"
        }
    ],
    "sg:phone":"+1 207 884 7444",
    "sg:postcode":"04456",
    "sg:province":"ME",
    "sg:tags":[
        "high",
        "middle",
        "elementary"
    ],
    "sg:website":"sad23.k12.me.us",
    "wof:name":"Levant Town of",
    "wof:placetype":"venue"
},
  "geometry": {"coordinates":[-68.988899,44.861],"type":"Point"}
}