{
  "type": "Feature",
  "properties": {
    "addr:full":"125 High St Farmington ME 04938",
    "addr:housenumber":"125",
    "addr:postcode":"04938",
    "addr:street":"High St",
    "iso:country":"US",
    "sg:address":"125 High St",
    "sg:city":"Farmington",
    "sg:classifiers":[
        {
            "category":"Professional",
            "type":"Services"
        }
    ],
    "sg:phone":"+1 207 778 9508",
    "sg:postcode":"04938",
    "sg:province":"ME",
    "sg:tags":[
        "establishment"
    ],
    "wof:name":"Skane LTD",
    "wof:placetype":"venue"
},
  "geometry": {"coordinates":[-70.132268,44.653995],"type":"Point"}
}