{
  "type": "Feature",
  "properties": {
    "iso:country":"US",
    "sg:address":"1135 Waterford Rd",
    "sg:city":"Waterford",
    "sg:classifiers":[
        {
            "category":"Building & Trades",
            "subcategory":"Construction",
            "type":"Services"
        }
    ],
    "sg:phone":"+1 207 583 4242",
    "sg:postcode":"04088",
    "sg:province":"ME",
    "sg:tags":[
        "carpentry",
        "contractor"
    ],
    "wof:name":"R & S Building",
    "wof:placetype":"venue"
},
  "geometry": {"coordinates":[-70.69108799999999,44.202516],"type":"Point"}
}