{
  "type": "Feature",
  "properties": {
    "iso:country":"US",
    "sg:address":"88 Washington St",
    "sg:city":"Camden",
    "sg:classifiers":[
        {
            "category":"Wholesale",
            "subcategory":"Toys & Hobbies",
            "type":"Manufacturing & Wholesale Goods"
        }
    ],
    "sg:phone":"+1 207 236 0137",
    "sg:postcode":"04843",
    "sg:province":"ME",
    "wof:name":"Meredith Messer",
    "wof:placetype":"venue"
},
  "geometry": {"coordinates":[-69.075603,44.215057],"type":"Point"}
}