{
  "type": "Feature",
  "properties": {
    "addr:full":"1175 US Route 1 York ME 03909",
    "addr:housenumber":"1175",
    "addr:postcode":"03909",
    "addr:street":"Us Route 1",
    "iso:country":"US",
    "sg:address":"1175 US Route 1",
    "sg:city":"York",
    "sg:classifiers":[
        {
            "category":"Shopping",
            "subcategory":"Antiques",
            "type":"Retail Goods"
        }
    ],
    "sg:phone":"+1 207 363 5797",
    "sg:postcode":"03909",
    "sg:province":"ME",
    "wof:name":"Essence of Time",
    "wof:placetype":"venue"
},
  "geometry": {"coordinates":[-70.622162,43.186201],"type":"Point"}
}