{
  "type": "Feature",
  "properties": {
    "addr:full":"64 Blueberry Rd Portland ME 04102",
    "addr:housenumber":"64",
    "addr:postcode":"04102",
    "addr:street":"Blueberry Rd",
    "iso:country":"US",
    "sg:address":"64 Blueberry Rd",
    "sg:city":"Portland",
    "sg:classifiers":[
        {
            "category":"Organizations",
            "subcategory":"Non-profit Organization",
            "type":"Services"
        }
    ],
    "sg:phone":"+1 207 773 1738",
    "sg:postcode":"04102",
    "sg:province":"ME",
    "sg:website":"www.regionalwaste.com",
    "wof:name":"Regional Waste Systems",
    "wof:placetype":"venue"
},
  "geometry": {"coordinates":[-70.333195,43.652319],"type":"Point"}
}