{
  "type": "Feature",
  "properties": {
    "iso:country":"US",
    "sg:address":"143 Portland Rd",
    "sg:city":"Gray",
    "sg:classifiers":[
        {
            "category":"Retail",
            "subcategory":"Auto Repair",
            "type":"Services"
        }
    ],
    "sg:phone":"+1 207 657 6000",
    "sg:postcode":"04039",
    "sg:province":"ME",
    "sg:tags":[
        "body",
        "automobile",
        "painting"
    ],
    "wof:name":"Collision Center #1",
    "wof:placetype":"venue"
},
  "geometry": {"coordinates":[-70.324637,43.86752],"type":"Point"}
}