{
  "type": "Feature",
  "properties": {
    "iso:country":"US",
    "sg:address":"30 Washington Ave",
    "sg:city":"Portland",
    "sg:classifiers":[
        {
            "category":"Food & Beverages",
            "subcategory":"Groceries & Convenience Stores",
            "type":"Retail Goods"
        }
    ],
    "sg:phone":"+1 207 774 6882",
    "sg:postcode":"04101",
    "sg:province":"ME",
    "sg:tags":[
        "grocer"
    ],
    "wof:name":"Discount Grocery",
    "wof:placetype":"venue"
},
  "geometry": {"coordinates":[-70.252025,43.664903],"type":"Point"}
}