{
  "type": "Feature",
  "properties": {
    "addr:full":"342 Fore St Portland ME 04101",
    "addr:housenumber":"342",
    "addr:postcode":"04101",
    "addr:street":"Fore St",
    "iso:country":"US",
    "sg:address":"342 Fore St",
    "sg:city":"Portland",
    "sg:classifiers":[
        {
            "category":"Personal",
            "subcategory":"Barber",
            "type":"Services"
        }
    ],
    "sg:phone":"+1 207 774 2872",
    "sg:postcode":"04101",
    "sg:province":"ME",
    "sg:tags":[
        "shop"
    ],
    "wof:name":"Bob's Barber Shop",
    "wof:placetype":"venue"
},
  "geometry": {"coordinates":[-70.25162899999999,43.657236],"type":"Point"}
}