{
  "type": "Feature",
  "properties": {
    "iso:country":"US",
    "sg:address":"37 Huston Rd",
    "sg:city":"Gorham",
    "sg:classifiers":[
        {
            "category":"Building & Trades",
            "subcategory":"Landscaping Services",
            "type":"Services"
        }
    ],
    "sg:phone":"+1 207 839 5450",
    "sg:postcode":"04038",
    "sg:province":"ME",
    "sg:tags":[
        "landscape",
        "contractor"
    ],
    "wof:name":"Bayside Property Maintenance",
    "wof:placetype":"venue"
},
  "geometry": {"coordinates":[-70.460613,43.718464],"type":"Point"}
}