{
  "type": "Feature",
  "properties": {
    "addr:full":"75 Townsend Ave Boothbay Harbor ME 04538",
    "addr:housenumber":"75",
    "addr:postcode":"04538",
    "addr:street":"Townsend Ave",
    "iso:country":"US",
    "sg:address":"75 Townsend Ave",
    "sg:city":"Boothbay Harbor",
    "sg:classifiers":[
        {
            "category":"Travel",
            "subcategory":"Hotels & Motels",
            "type":"Entertainment"
        }
    ],
    "sg:phone":"+1 207 633 4640",
    "sg:postcode":"04538",
    "sg:province":"ME",
    "sg:tags":[
        "operation"
    ],
    "wof:name":"Harborage Inn",
    "wof:placetype":"venue"
},
  "geometry": {"coordinates":[-69.626846,43.853158],"type":"Point"}
}