{
  "type": "Feature",
  "properties": {
    "iso:country":"US",
    "sg:address":"640 Brighton Ave",
    "sg:city":"Portland",
    "sg:classifiers":[
        {
            "category":"Professional",
            "subcategory":"Employment Agencies",
            "type":"Services"
        }
    ],
    "sg:phone":"+1 207 774 4123",
    "sg:postcode":"04102",
    "sg:province":"ME",
    "sg:tags":[
        "opportunity"
    ],
    "wof:name":"Gouzie Associates",
    "wof:placetype":"venue"
},
  "geometry": {"coordinates":[-70.305286,43.669985],"type":"Point"}
}