{
  "type": "Feature",
  "properties": {
    "iso:country":"US",
    "sg:address":"50 Fairmount St",
    "sg:city":"Lewiston",
    "sg:classifiers":[
        {
            "category":"Wholesale",
            "subcategory":"Electrical",
            "type":"Manufacturing & Wholesale Goods"
        }
    ],
    "sg:phone":"+1 207 786 2910",
    "sg:postcode":"04240",
    "sg:province":"ME",
    "sg:tags":[
        "control",
        "security",
        "system"
    ],
    "wof:name":"C & M Security",
    "wof:placetype":"venue"
},
  "geometry": {"coordinates":[-70.188632,44.084441],"type":"Point"}
}