{
  "type": "Feature",
  "properties": {
    "iso:country":"US",
    "sg:address":"112 Madison Ave",
    "sg:city":"Skowhegan",
    "sg:classifiers":[
        {
            "category":"Social Services",
            "type":"Services"
        }
    ],
    "sg:phone":"+1 207 858 4860",
    "sg:postcode":"04976",
    "sg:province":"ME",
    "sg:tags":[
        "organization",
        "welfare"
    ],
    "wof:name":"Community Health & Counseling",
    "wof:placetype":"venue"
},
  "geometry": {"coordinates":[-69.72099799999999,44.7684],"type":"Point"}
}