{
  "type": "Feature",
  "properties": {
    "addr:full":"316 Beech Ridge Rd Scarborough ME 04074",
    "addr:housenumber":"316",
    "addr:postcode":"04074",
    "addr:street":"Beech Ridge Rd",
    "iso:country":"US",
    "sg:address":"316 Beech Ridge Rd",
    "sg:city":"Scarborough",
    "sg:classifiers":[
        {
            "category":"Professional",
            "subcategory":"Management & Consulting",
            "type":"Services"
        }
    ],
    "sg:phone":"+1 207 839 3382",
    "sg:postcode":"04074",
    "sg:province":"ME",
    "sg:tags":[
        "marketing",
        "program"
    ],
    "wof:name":"Devito Inc",
    "wof:placetype":"venue"
},
  "geometry": {"coordinates":[-70.40115400000001,43.638055],"type":"Point"}
}