{
  "type": "Feature",
  "properties": {
    "iso:country":"US",
    "sg:address":"148 Main St",
    "sg:city":"South Paris",
    "sg:classifiers":[
        {
            "category":"Cinema",
            "subcategory":"Movie Rental",
            "type":"Entertainment"
        }
    ],
    "sg:phone":"+1 207 743 7080",
    "sg:postcode":"04281",
    "sg:province":"ME",
    "sg:tags":[
        "leasing",
        "video",
        "disc",
        "tape"
    ],
    "wof:name":"Movie Gallery",
    "wof:placetype":"venue"
},
  "geometry": {"coordinates":[-70.517257,44.217399],"type":"Point"}
}