{
  "type": "Feature",
  "properties": {
    "iso:country":"US",
    "sg:address":"171 State St",
    "sg:city":"Augusta",
    "sg:classifiers":[
        {
            "category":"Autos & Motor Vehicles",
            "subcategory":"Auto Supplies",
            "type":"Retail Goods"
        }
    ],
    "sg:phone":"+1 207 623 1971",
    "sg:postcode":"04330",
    "sg:province":"ME",
    "sg:tags":[
        "automobile",
        "parts"
    ],
    "wof:name":"Motor Supply Co",
    "wof:placetype":"venue"
},
  "geometry": {"coordinates":[-69.779964,44.309667],"type":"Point"}
}