{
  "type": "Feature",
  "properties": {
    "iso:country":"US",
    "sg:address":"77 Bates St",
    "sg:city":"Lewiston",
    "sg:classifiers":[
        {
            "category":"Health Services",
            "subcategory":"Health Practitioner",
            "type":"Services"
        }
    ],
    "sg:phone":"+1 207 753 3080",
    "sg:postcode":"04240",
    "sg:province":"ME",
    "sg:tags":[
        "occupational",
        "safety"
    ],
    "wof:name":"Work Med",
    "wof:placetype":"venue"
},
  "geometry": {"coordinates":[-70.215568,44.098948],"type":"Point"}
}