{
  "type": "Feature",
  "properties": {
    "iso:country":"US",
    "sg:address":"43 Acme Rd",
    "sg:city":"Brewer",
    "sg:classifiers":[
        {
            "category":"Professional",
            "subcategory":"Employment Agencies",
            "type":"Services"
        }
    ],
    "sg:phone":"+1 207 989 0824",
    "sg:postcode":"04412",
    "sg:province":"ME",
    "sg:tags":[
        "opportunity"
    ],
    "wof:name":"Atwork Personnel Svc",
    "wof:placetype":"venue"
},
  "geometry": {"coordinates":[-68.75626200000001,44.786673],"type":"Point"}
}