{
  "type": "Feature",
  "properties": {
    "addr:full":"404 S High St Bridgton ME 04009",
    "addr:housenumber":"404",
    "addr:postcode":"04009",
    "addr:street":"S High St",
    "iso:country":"US",
    "sg:address":"404 S High St",
    "sg:city":"Bridgton",
    "sg:classifiers":[
        {
            "category":"Retail",
            "subcategory":"Auto Repair",
            "type":"Services"
        }
    ],
    "sg:phone":"+1 207 647 2056",
    "sg:postcode":"04009",
    "sg:province":"ME",
    "sg:tags":[
        "exhaust",
        "general"
    ],
    "wof:name":"Triple J Small Engine Repair",
    "wof:placetype":"venue"
},
  "geometry": {"coordinates":[-70.708122,44.034007],"type":"Point"}
}