{
  "type": "Feature",
  "properties": {
    "addr:full":"4 Day Rd Gorham ME 04038",
    "addr:housenumber":"4",
    "addr:postcode":"04038",
    "addr:street":"Day Rd",
    "iso:country":"US",
    "sg:address":"4 Day Rd",
    "sg:city":"Gorham",
    "sg:classifiers":[
        {
            "category":"Building & Trades",
            "subcategory":"Landscaping Services",
            "type":"Services"
        }
    ],
    "sg:phone":"+1 207 807 2821",
    "sg:postcode":"04038",
    "sg:province":"ME",
    "sg:tags":[
        "landscape",
        "contractor"
    ],
    "wof:name":"Green Thumb Property Mntnc",
    "wof:placetype":"venue"
},
  "geometry": {"coordinates":[-70.43153700000001,43.663384],"type":"Point"}
}