{
  "type": "Feature",
  "properties": {
    "addr:full":"24 Somerset St Bangor ME 04401",
    "addr:housenumber":"24",
    "addr:postcode":"04401",
    "addr:street":"Somerset St",
    "iso:country":"US",
    "sg:address":"24 Somerset St",
    "sg:city":"Bangor",
    "sg:classifiers":[
        {
            "category":"Health Services",
            "subcategory":"Doctor",
            "type":"Services"
        }
    ],
    "sg:phone":"+1 207 942 3293",
    "sg:postcode":"04401",
    "sg:province":"ME",
    "sg:tags":[
        "physician",
        "surgeon"
    ],
    "wof:name":"James R Curtis MD",
    "wof:placetype":"venue"
},
  "geometry": {"coordinates":[-68.770141,44.805687],"type":"Point"}
}