{
  "type": "Feature",
  "properties": {
    "addr:full":"73 Main St East Millinocket ME 04430",
    "addr:housenumber":"73",
    "addr:postcode":"04430",
    "addr:street":"Main St",
    "iso:country":"US",
    "sg:address":"73 Main St",
    "sg:city":"East Millinocket",
    "sg:classifiers":[
        {
            "category":"Insurance",
            "subcategory":"Insurance Agent",
            "type":"Services"
        }
    ],
    "sg:phone":"+1 207 746 9838",
    "sg:postcode":"04430",
    "sg:province":"ME",
    "wof:name":"Employee Benefits Design Inc",
    "wof:placetype":"venue"
},
  "geometry": {"coordinates":[-68.576111,45.625753],"type":"Point"}
}