{
  "type": "Feature",
  "properties": {
    "iso:country":"US",
    "sg:address":"410 New Sweden Rd",
    "sg:city":"New Sweden",
    "sg:classifiers":[
        {
            "category":"Health Services",
            "subcategory":"Health Practitioner",
            "type":"Services"
        }
    ],
    "sg:phone":"+1 207 896 3408",
    "sg:postcode":"04762",
    "sg:province":"ME",
    "wof:name":"County Physical Therapy",
    "wof:placetype":"venue"
},
  "geometry": {"coordinates":[-68.133853,46.942933],"type":"Point"}
}