{
  "type": "Feature",
  "properties": {
    "addr:full":"1 Seavey St Waterville ME 04901",
    "addr:housenumber":"1",
    "addr:postcode":"04901",
    "addr:street":"Seavey St",
    "iso:country":"US",
    "sg:address":"1 Seavey St",
    "sg:city":"Waterville",
    "sg:classifiers":[
        {
            "category":"Sports & Exercise",
            "subcategory":"Gym",
            "type":"Entertainment"
        }
    ],
    "sg:phone":"+1 207 872 7140",
    "sg:postcode":"04901",
    "sg:province":"ME",
    "sg:tags":[
        "club",
        "health",
        "studio",
        "gymnasium"
    ],
    "wof:name":"Gilly's Gym",
    "wof:placetype":"venue"
},
  "geometry": {"coordinates":[-69.62189600000001,44.565968],"type":"Point"}
}