{
  "type": "Feature",
  "properties": {
    "iso:country":"US",
    "sg:address":"1 Stanley Ave",
    "sg:city":"Kingfield",
    "sg:classifiers":[
        {
            "category":"Restaurant",
            "type":"Food & Drink"
        }
    ],
    "sg:phone":"+1 207 265 5541",
    "sg:postcode":"04938",
    "sg:province":"ME",
    "wof:name":"One Stanley Avenue Restaurant",
    "wof:placetype":"venue"
},
  "geometry": {"coordinates":[-70.141041,44.662369],"type":"Point"}
}