{
  "type": "Feature",
  "properties": {
    "addr:full":"289 Lisbon St Lewiston ME 04240",
    "addr:housenumber":"289",
    "addr:postcode":"04240",
    "addr:street":"Lisbon St",
    "iso:country":"US",
    "sg:address":"289 Lisbon St",
    "sg:city":"Lewiston",
    "sg:classifiers":[
        {
            "category":"Restaurant",
            "type":"Food & Drink"
        }
    ],
    "sg:phone":"+1 207 782 7200",
    "sg:postcode":"04240",
    "sg:province":"ME",
    "wof:name":"LA Pizza & Restaurant",
    "wof:placetype":"venue"
},
  "geometry": {"coordinates":[-70.215349,44.093419],"type":"Point"}
}