{
  "type": "Feature",
  "properties": {
    "addr:full":"11 N Bath Rd West Bath ME 04530",
    "addr:housenumber":"11",
    "addr:postcode":"04530",
    "addr:street":"N Bath Rd",
    "iso:country":"US",
    "sg:address":"11 N Bath Rd",
    "sg:city":"West Bath",
    "sg:classifiers":[
        {
            "category":"Retail",
            "subcategory":"Repair Shop",
            "type":"Services"
        }
    ],
    "sg:phone":"+1 207 443 6828",
    "sg:postcode":"04530",
    "sg:province":"ME",
    "sg:tags":[
        "instrument",
        "musical"
    ],
    "wof:name":"Jonathan Waldo Instr Maker",
    "wof:placetype":"venue"
},
  "geometry": {"coordinates":[-69.838362,43.941847],"type":"Point"}
}