{
  "type": "Feature",
  "properties": {
    "addr:full":"82 Charles St Lewiston ME 04240",
    "addr:housenumber":"82",
    "addr:postcode":"04240",
    "addr:street":"Charles St",
    "iso:country":"US",
    "sg:address":"82 Charles St",
    "sg:city":"Lewiston",
    "sg:classifiers":[
        {
            "category":"Manufacturing",
            "subcategory":"Musical Instruments",
            "type":"Manufacturing & Wholesale Goods"
        }
    ],
    "sg:phone":"+1 207 783 3277",
    "sg:postcode":"04240",
    "sg:province":"ME",
    "sg:tags":[
        "mfg"
    ],
    "wof:name":"Mattys Music",
    "wof:placetype":"venue"
},
  "geometry": {"coordinates":[-70.188338,44.096998],"type":"Point"}
}