{
  "type": "Feature",
  "properties": {
    "iso:country":"US",
    "sg:address":"754 Roosevelt Trl",
    "sg:city":"Windham",
    "sg:classifiers":[
        {
            "category":"Restaurant",
            "type":"Food & Drink"
        }
    ],
    "sg:phone":"+1 207 892 8595",
    "sg:postcode":"04062",
    "sg:province":"ME",
    "sg:website":"www.charliebeiggs.us",
    "wof:name":"Charlie Beigg's Restaurant",
    "wof:placetype":"venue"
},
  "geometry": {"coordinates":[-70.449168,43.849468],"type":"Point"}
}