{
  "type": "Feature",
  "properties": {
    "addr:full":"336 Bath Rd Brunswick ME 04011",
    "addr:housenumber":"336",
    "addr:postcode":"04011",
    "addr:street":"Bath Rd",
    "iso:country":"US",
    "sg:address":"336 Bath Rd",
    "sg:city":"Brunswick",
    "sg:classifiers":[
        {
            "category":"Professional",
            "subcategory":"Computer Services",
            "type":"Services"
        }
    ],
    "sg:phone":"+1 207 721 9896",
    "sg:postcode":"04011",
    "sg:province":"ME",
    "sg:tags":[
        "internet"
    ],
    "wof:name":"Blazenet Me",
    "wof:placetype":"venue"
},
  "geometry": {"coordinates":[-69.895196,43.912247],"type":"Point"}
}