{
  "type": "Feature",
  "properties": {
    "iso:country":"US",
    "sg:address":"73 Main St",
    "sg:city":"Kennebunk",
    "sg:classifiers":[
        {
            "category":"Real Estate",
            "subcategory":"Real Estate Agent",
            "type":"Services"
        }
    ],
    "sg:phone":"+1 207 985 3328",
    "sg:postcode":"04043",
    "sg:province":"ME",
    "sg:website":"www.downingagency.com",
    "wof:name":"Downing Agency",
    "wof:placetype":"venue"
},
  "geometry": {"coordinates":[-70.537905,43.387264],"type":"Point"}
}