{
  "type": "Feature",
  "properties": {
    "addr:full":"120 Seabury Rd York ME 03909",
    "addr:housenumber":"120",
    "addr:postcode":"03909",
    "addr:street":"Seabury Rd",
    "iso:country":"US",
    "sg:address":"120 Seabury Rd",
    "sg:city":"York",
    "sg:classifiers":[
        {
            "category":"Travel",
            "subcategory":"Bed & Breakfast",
            "type":"Entertainment"
        }
    ],
    "sg:phone":"+1 207 363 2062",
    "sg:postcode":"03909",
    "sg:province":"ME",
    "sg:website":"www.morninggloryinnmaine.com",
    "wof:name":"Morning Glory Inn",
    "wof:placetype":"venue"
},
  "geometry": {"coordinates":[-70.65543599999999,43.129915],"type":"Point"}
}