{
  "type": "Feature",
  "properties": {
    "iso:country":"US",
    "sg:address":"1250 Roosevelt Trl",
    "sg:city":"Raymond",
    "sg:classifiers":[
        {
            "category":"Utilities",
            "subcategory":"Mobile Phone",
            "type":"Services"
        }
    ],
    "sg:phone":"+1 207 655 8001",
    "sg:postcode":"04071",
    "sg:province":"ME",
    "sg:tags":[
        "telephone",
        "cellular"
    ],
    "wof:name":"Affordable Wireless",
    "wof:placetype":"venue"
},
  "geometry": {"coordinates":[-70.465518,43.881955],"type":"Point"}
}