{
  "type": "Feature",
  "properties": {
    "addr:full":"851 Lawrence Rd Pownal ME 04069",
    "addr:housenumber":"851",
    "addr:postcode":"04069",
    "addr:street":"Lawrence Rd",
    "iso:country":"US",
    "sg:address":"851 Lawrence Rd",
    "sg:city":"Pownal",
    "sg:classifiers":[
        {
            "category":"Organizations",
            "subcategory":"Religious Organization",
            "type":"Services"
        }
    ],
    "sg:phone":"+1 207 688 4938",
    "sg:postcode":"04069",
    "sg:province":"ME",
    "sg:tags":[
        "church"
    ],
    "wof:name":"N Pownal United Methodist Ch",
    "wof:placetype":"venue"
},
  "geometry": {"coordinates":[-70.19229900000001,43.93484],"type":"Point"}
}