{
  "type": "Feature",
  "properties": {
    "iso:country":"US",
    "sg:address":"195 Middle St",
    "sg:city":"Portland",
    "sg:classifiers":[
        {
            "category":"Shopping",
            "type":"Retail Goods"
        }
    ],
    "sg:phone":"+1 207 772 9072",
    "sg:postcode":"04101",
    "sg:province":"ME",
    "sg:tags":[
        "art",
        "gallery",
        "dealer"
    ],
    "sg:website":"www.steinglass.com",
    "wof:name":"Stein Glass Gallery",
    "wof:placetype":"venue"
},
  "geometry": {"coordinates":[-70.254673,43.657695],"type":"Point"}
}