{
  "type": "Feature",
  "properties": {
    "addr:full":"712 Main St Caribou ME 04736",
    "addr:housenumber":"712",
    "addr:postcode":"04736",
    "addr:street":"Main St",
    "iso:country":"US",
    "sg:address":"712 Main St",
    "sg:city":"Caribou",
    "sg:classifiers":[
        {
            "category":"Health Services",
            "subcategory":"Nursing And Care Facility",
            "type":"Services"
        }
    ],
    "sg:phone":"+1 207 498 3097",
    "sg:postcode":"04736",
    "sg:province":"ME",
    "sg:tags":[
        "home",
        "retirement",
        "community"
    ],
    "wof:name":"Townview Estates",
    "wof:placetype":"venue"
},
  "geometry": {"coordinates":[-68.011691,46.861576],"type":"Point"}
}