{
  "type": "Feature",
  "properties": {
    "addr:full":"337 Main St Waterville ME 04901",
    "addr:housenumber":"337",
    "addr:postcode":"04901",
    "addr:street":"Main St",
    "iso:country":"US",
    "sg:address":"337 Main St",
    "sg:city":"Waterville",
    "sg:classifiers":[
        {
            "category":"Shopping",
            "subcategory":"Hobbies, Toys, & Games",
            "type":"Retail Goods"
        }
    ],
    "sg:phone":"+1 207 872 7653",
    "sg:postcode":"04901",
    "sg:province":"ME",
    "sg:tags":[
        "supply"
    ],
    "wof:name":"Game Zone",
    "wof:placetype":"venue"
},
  "geometry": {"coordinates":[-69.642138,44.573723],"type":"Point"}
}