{
  "type": "Feature",
  "properties": {
    "iso:country":"US",
    "sg:address":"133 S Waterboro Rd",
    "sg:city":"North Waterboro",
    "sg:classifiers":[
        {
            "category":"Manufacturing",
            "subcategory":"Pottery",
            "type":"Manufacturing & Wholesale Goods"
        }
    ],
    "sg:phone":"+1 207 793 2150",
    "sg:postcode":"04002",
    "sg:province":"ME",
    "sg:tags":[
        "product",
        "mfg"
    ],
    "wof:name":"Happy Valley Pot Work",
    "wof:placetype":"venue"
},
  "geometry": {"coordinates":[-70.590762,43.506388],"type":"Point"}
}