{
  "type": "Feature",
  "properties": {
    "addr:full":"240 Bartlett St Lewiston ME 04240",
    "addr:housenumber":"240",
    "addr:postcode":"04240",
    "addr:street":"Bartlett St",
    "iso:country":"US",
    "sg:address":"240 Bartlett St",
    "sg:city":"Lewiston",
    "sg:classifiers":[
        {
            "category":"Wholesale",
            "subcategory":"Toys & Hobbies",
            "type":"Manufacturing & Wholesale Goods"
        }
    ],
    "sg:phone":"+1 207 786 3737",
    "sg:postcode":"04240",
    "sg:province":"ME",
    "sg:tags":[
        "game",
        "supply"
    ],
    "wof:name":"Sparta Vending",
    "wof:placetype":"venue"
},
  "geometry": {"coordinates":[-70.20844200000001,44.092971],"type":"Point"}
}