{
  "type": "Feature",
  "properties": {
    "iso:country":"US",
    "sg:address":"23 Portland Street Pier",
    "sg:city":"South Portland",
    "sg:classifiers":[
        {
            "category":"Professional",
            "subcategory":"Management & Consulting",
            "type":"Services"
        }
    ],
    "sg:phone":"+1 207 799 4022",
    "sg:postcode":"04106",
    "sg:province":"ME",
    "sg:tags":[
        "engineering"
    ],
    "wof:name":"Design Solutions",
    "wof:placetype":"venue"
},
  "geometry": {"coordinates":[-70.242369,43.650183],"type":"Point"}
}