{
  "type": "Feature",
  "properties": {
    "addr:full":"1 Old Orchard St Old Orchard Bch ME 04064",
    "addr:housenumber":"1",
    "addr:postcode":"04064",
    "addr:street":"Old Orchard St",
    "iso:country":"US",
    "sg:address":"1 Old Orchard St",
    "sg:city":"Old Orchard Bch",
    "sg:classifiers":[
        {
            "category":"Recreation",
            "subcategory":"Amusement Park",
            "type":"Entertainment"
        }
    ],
    "sg:phone":"+1 207 934 2001",
    "sg:postcode":"04064",
    "sg:province":"ME",
    "sg:website":"www.palaceplayland.com",
    "wof:name":"Palace Playland",
    "wof:placetype":"venue"
},
  "geometry": {"coordinates":[-70.377599,43.517497],"type":"Point"}
}