{
  "type": "Feature",
  "properties": {
    "addr:full":"831 Middle St Bath ME 04530",
    "addr:housenumber":"831",
    "addr:postcode":"04530",
    "addr:street":"Middle St",
    "iso:country":"US",
    "sg:address":"831 Middle St",
    "sg:city":"Bath",
    "sg:classifiers":[
        {
            "category":"Banks & Credit Unions",
            "subcategory":"Bank",
            "type":"Services"
        }
    ],
    "sg:phone":"+1 207 443 5531",
    "sg:postcode":"04530",
    "sg:province":"ME",
    "sg:website":"www.midcoastfcu.net",
    "wof:name":"Midcoast Federal Credit Union",
    "wof:placetype":"venue"
},
  "geometry": {"coordinates":[-69.81777599999999,43.914352],"type":"Point"}
}