{
  "type": "Feature",
  "properties": {
    "iso:country":"US",
    "sg:address":"2980 Hotel Rd",
    "sg:city":"Auburn",
    "sg:classifiers":[
        {
            "category":"Building & Trades",
            "subcategory":"Equipment Rental",
            "type":"Services"
        }
    ],
    "sg:phone":"+1 207 783 0561",
    "sg:postcode":"04210",
    "sg:province":"ME",
    "sg:tags":[
        "crane"
    ],
    "sg:website":"www.cotecrane.com",
    "wof:name":"Cote Crane & Rigging",
    "wof:placetype":"venue"
},
  "geometry": {"coordinates":[-70.280609,44.03871],"type":"Point"}
}