{
  "type": "Feature",
  "properties": {
    "iso:country":"US",
    "sg:address":"488 US Hwy 2",
    "sg:city":"Macwahoc Plt",
    "sg:classifiers":[
        {
            "category":"Manufacturing",
            "subcategory":"Lumber",
            "type":"Manufacturing & Wholesale Goods"
        }
    ],
    "sg:phone":"+1 207 765 2681",
    "sg:postcode":"04473",
    "sg:province":"ME",
    "sg:tags":[
        "company",
        "logging"
    ],
    "wof:name":"Hanington Brothers Inc",
    "wof:placetype":"venue"
},
  "geometry": {"coordinates":[-68.690317,44.858636],"type":"Point"}
}