{
  "type": "Feature",
  "properties": {
    "addr:full":"18 Spring St Belfast ME 04915",
    "addr:housenumber":"18",
    "addr:postcode":"04915",
    "addr:street":"Spring St",
    "iso:country":"US",
    "sg:address":"18 Spring St",
    "sg:city":"Belfast",
    "sg:classifiers":[
        {
            "category":"Home & Garden",
            "subcategory":"Building Materials",
            "type":"Retail Goods"
        }
    ],
    "sg:phone":"+1 207 338 3359",
    "sg:postcode":"04915",
    "sg:province":"ME",
    "sg:tags":[
        "windows"
    ],
    "sg:website":"www.mathewsbrothers.com",
    "wof:name":"Mathews Brothers Co",
    "wof:placetype":"venue"
},
  "geometry": {"coordinates":[-69.005112,44.425859],"type":"Point"}
}