{
  "type": "Feature",
  "properties": {
    "addr:full":"358 Skip Rd Buxton ME 04093",
    "addr:housenumber":"358",
    "addr:postcode":"04093",
    "addr:street":"Skip Rd",
    "iso:country":"US",
    "sg:address":"358 Skip Rd",
    "sg:city":"Buxton",
    "sg:classifiers":[
        {
            "category":"Building & Trades",
            "subcategory":"Electrical",
            "type":"Services"
        }
    ],
    "sg:phone":"+1 207 727 5707",
    "sg:postcode":"04093",
    "sg:province":"ME",
    "sg:tags":[
        "electric",
        "contractor"
    ],
    "wof:name":"D & R Electric",
    "wof:placetype":"venue"
},
  "geometry": {"coordinates":[-70.570583,43.674],"type":"Point"}
}