{
  "type": "Feature",
  "properties": {
    "addr:full":"1040 Broadway South Portland ME 04106",
    "addr:housenumber":"1040",
    "addr:postcode":"04106",
    "addr:street":"Broadway",
    "iso:country":"US",
    "sg:address":"1040 Broadway",
    "sg:city":"South Portland",
    "sg:classifiers":[
        {
            "category":"Health Services",
            "subcategory":"Clinic",
            "type":"Services"
        }
    ],
    "sg:phone":"+1 207 767 7135",
    "sg:postcode":"04106",
    "sg:province":"ME",
    "sg:tags":[
        "counseling",
        "mental"
    ],
    "wof:name":"Sanford David E Dr Counslr",
    "wof:placetype":"venue"
},
  "geometry": {"coordinates":[-70.274597,43.629101],"type":"Point"}
}