{
  "type": "Feature",
  "properties": {
    "iso:country":"US",
    "sg:address":"239 Center St",
    "sg:city":"Old Town",
    "sg:classifiers":[
        {
            "category":"Personal",
            "subcategory":"Beauty Salon",
            "type":"Services"
        }
    ],
    "sg:phone":"+1 207 827 3485",
    "sg:postcode":"04468",
    "sg:province":"ME",
    "sg:tags":[
        "shop"
    ],
    "wof:name":"Marilyn's Beauty Salon",
    "wof:placetype":"venue"
},
  "geometry": {"coordinates":[-68.649143,44.93362],"type":"Point"}
}