{
  "type": "Feature",
  "properties": {
    "addr:full":"130 Wescott Rd South Portland ME 04106",
    "addr:housenumber":"130",
    "addr:postcode":"04106",
    "addr:street":"Wescott Rd",
    "iso:country":"US",
    "sg:address":"130 Wescott Rd",
    "sg:city":"South Portland",
    "sg:classifiers":[
        {
            "category":"Education",
            "subcategory":"School",
            "type":"Public Place"
        }
    ],
    "sg:phone":"+1 207 871 0555",
    "sg:postcode":"04106",
    "sg:province":"ME",
    "wof:name":"South Portland School Supt",
    "wof:placetype":"venue"
},
  "geometry": {"coordinates":[-70.30468,43.626997],"type":"Point"}
}