{
  "type": "Feature",
  "properties": {
    "iso:country":"US",
    "sg:address":"11 Hills Beach Rd",
    "sg:city":"Biddeford",
    "sg:classifiers":[
        {
            "category":"Education",
            "subcategory":"College",
            "type":"Public Place"
        }
    ],
    "sg:phone":"+1 207 830 0170",
    "sg:postcode":"04005",
    "sg:province":"ME",
    "sg:tags":[
        "university"
    ],
    "wof:name":"University of New England",
    "wof:placetype":"venue"
},
  "geometry": {"coordinates":[-70.385025,43.45775],"type":"Point"}
}