{
  "type": "Feature",
  "properties": {
    "iso:country":"US",
    "sg:address":"39 Mechanic St",
    "sg:city":"Camden",
    "sg:classifiers":[
        {
            "category":"Professional",
            "subcategory":"Computer Services",
            "type":"Services"
        }
    ],
    "sg:phone":"+1 207 236 4237",
    "sg:postcode":"04843",
    "sg:province":"ME",
    "sg:tags":[
        "consultant",
        "designer"
    ],
    "sg:website":"www.knowtechnology.net",
    "wof:name":"Know Technology Group",
    "wof:placetype":"venue"
},
  "geometry": {"coordinates":[-69.068411,44.209555],"type":"Point"}
}