{
  "type": "Feature",
  "properties": {
    "iso:country":"US",
    "sg:address":"215 Main St",
    "sg:city":"Ellsworth",
    "sg:classifiers":[
        {
            "category":"Retail",
            "subcategory":"Funeral Services",
            "type":"Services"
        }
    ],
    "sg:phone":"+1 207 667 8325",
    "sg:postcode":"04605",
    "sg:province":"ME",
    "sg:tags":[
        "director"
    ],
    "wof:name":"Bragdon-Kelley Monuments",
    "wof:placetype":"venue"
},
  "geometry": {"coordinates":[-68.422336,44.542142],"type":"Point"}
}