{
  "type": "Feature",
  "properties": {
    "addr:full":"106 Western Ave Hampden ME 04444",
    "addr:housenumber":"106",
    "addr:postcode":"04444",
    "addr:street":"Western Ave",
    "iso:country":"US",
    "sg:address":"106 Western Ave",
    "sg:city":"Hampden",
    "sg:classifiers":[
        {
            "category":"Recreation",
            "type":"Entertainment"
        }
    ],
    "sg:phone":"+1 207 862 4305",
    "sg:postcode":"04444",
    "sg:province":"ME",
    "sg:tags":[
        "pool",
        "swimming"
    ],
    "sg:website":"www.hampdenmaine.com",
    "wof:name":"Lura E Hoit Pool",
    "wof:placetype":"venue"
},
  "geometry": {"coordinates":[-68.847578,44.745077],"type":"Point"}
}