{
  "type": "Feature",
  "properties": {
    "addr:full":"154 Clark St Portland ME 04102",
    "addr:housenumber":"154",
    "addr:postcode":"04102",
    "addr:street":"Clark St",
    "iso:country":"US",
    "sg:address":"154 Clark St",
    "sg:city":"Portland",
    "sg:classifiers":[
        {
            "category":"Professional",
            "type":"Services"
        }
    ],
    "sg:phone":"+1 207 874 1092",
    "sg:postcode":"04102",
    "sg:province":"ME",
    "sg:tags":[
        "establishment"
    ],
    "wof:name":"Shalom House Inc",
    "wof:placetype":"venue"
},
  "geometry": {"coordinates":[-70.26735499999999,43.64971],"type":"Point"}
}