{
  "type": "Feature",
  "properties": {
    "iso:country":"US",
    "sg:address":"460 Eastern Ave",
    "sg:city":"Augusta",
    "sg:classifiers":[
        {
            "category":"Shopping",
            "subcategory":"Used Merchandise",
            "type":"Retail Goods"
        }
    ],
    "sg:phone":"+1 207 623 4036",
    "sg:postcode":"04330",
    "sg:province":"ME",
    "wof:name":"Marshalls Antiques",
    "wof:placetype":"venue"
},
  "geometry": {"coordinates":[-69.732675,44.299128],"type":"Point"}
}