{
  "type": "Feature",
  "properties": {
    "addr:full":"96 Searsport Ave Belfast ME 04974",
    "addr:housenumber":"96",
    "addr:postcode":"04974",
    "addr:street":"Searsport Ave",
    "iso:country":"US",
    "sg:address":"96 Searsport Ave",
    "sg:city":"Belfast",
    "sg:classifiers":[
        {
            "category":"Home & Garden",
            "subcategory":"Hardware",
            "type":"Retail Goods"
        }
    ],
    "sg:phone":"+1 207 338 0409",
    "sg:postcode":"04974",
    "sg:province":"ME",
    "wof:name":"Jerry's True Value",
    "wof:placetype":"venue"
},
  "geometry": {"coordinates":[-68.974825,44.429538],"type":"Point"}
}