{
  "type": "Feature",
  "properties": {
    "addr:full":"78 Auburn Rd Turner ME 04282",
    "addr:housenumber":"78",
    "addr:postcode":"04282",
    "addr:street":"Auburn Rd",
    "iso:country":"US",
    "sg:address":"78 Auburn Rd",
    "sg:city":"Turner",
    "sg:classifiers":[
        {
            "category":"Food & Beverages",
            "subcategory":"Groceries & Convenience Stores",
            "type":"Retail Goods"
        }
    ],
    "sg:phone":"+1 207 225 3752",
    "sg:postcode":"04282",
    "sg:province":"ME",
    "sg:website":"www.cnbrown.com",
    "wof:name":"Big Apple",
    "wof:placetype":"venue"
},
  "geometry": {"coordinates":[-70.237686,44.189033],"type":"Point"}
}