{
  "type": "Feature",
  "properties": {
    "addr:full":"106 North St Houlton ME 04730",
    "addr:housenumber":"106",
    "addr:postcode":"04730",
    "addr:street":"North St",
    "iso:country":"US",
    "sg:address":"106 North St",
    "sg:city":"Houlton",
    "sg:classifiers":[
        {
            "category":"Home & Garden",
            "subcategory":"Garden Supply",
            "type":"Retail Goods"
        }
    ],
    "sg:phone":"+1 207 532 6518",
    "sg:postcode":"04730",
    "sg:province":"ME",
    "sg:tags":[
        "lawn",
        "mower"
    ],
    "wof:name":"Peabody Lawn & Leisure Co",
    "wof:placetype":"venue"
},
  "geometry": {"coordinates":[-67.83955899999999,46.13452],"type":"Point"}
}