{
  "type": "Feature",
  "properties": {
    "iso:country":"US",
    "sg:address":"4 Franks Pl",
    "sg:city":"West Gardiner",
    "sg:classifiers":[
        {
            "category":"Utilities",
            "subcategory":"Mobile Phone",
            "type":"Services"
        }
    ],
    "sg:phone":"+1 207 582 1545",
    "sg:postcode":"04345",
    "sg:province":"ME",
    "sg:tags":[
        "telephone",
        "cellular"
    ],
    "wof:name":"Verizon Wireless",
    "wof:placetype":"venue"
},
  "geometry": {"coordinates":[-69.82596100000001,44.208637],"type":"Point"}
}