{
  "type": "Feature",
  "properties": {
    "iso:country":"US",
    "sg:address":"166 S Main St",
    "sg:city":"Rockland",
    "sg:classifiers":[
        {
            "category":"Building & Trades",
            "subcategory":"Landscaping Services",
            "type":"Services"
        }
    ],
    "sg:phone":"+1 207 594 2299",
    "sg:postcode":"04841",
    "sg:province":"ME",
    "sg:tags":[
        "planning",
        "land"
    ],
    "wof:name":"Mid-Coast Regional Planning",
    "wof:placetype":"venue"
},
  "geometry": {"coordinates":[-69.109814,44.099513],"type":"Point"}
}