{
  "type": "Feature",
  "properties": {
    "addr:full":"26 Heather Ln Wales ME 04280",
    "addr:housenumber":"26",
    "addr:postcode":"me 04280",
    "addr:street":"Heather Ln",
    "iso:country":"US",
    "sg:address":"26 Heather Ln",
    "sg:city":"Wales",
    "sg:classifiers":[
        {
            "category":"Building & Trades",
            "subcategory":"Construction",
            "type":"Services"
        }
    ],
    "sg:phone":"+1 207 375 4567",
    "sg:postcode":"04280",
    "sg:province":"ME",
    "sg:tags":[
        "concrete",
        "contractor"
    ],
    "wof:name":"J & N Foundations Co Inc",
    "wof:placetype":"venue"
},
  "geometry": {"coordinates":[-70.09665,44.147685],"type":"Point"}
}