{
  "type": "Feature",
  "properties": {
    "iso:country":"US",
    "sg:address":"178 Washington Ave",
    "sg:city":"Portland",
    "sg:classifiers":[
        {
            "category":"Shopping",
            "type":"Retail Goods"
        }
    ],
    "sg:phone":"+1 207 874 0095",
    "sg:postcode":"04101",
    "sg:province":"ME",
    "sg:tags":[
        "picture",
        "frame"
    ],
    "wof:name":"T W Green Co",
    "wof:placetype":"venue"
},
  "geometry": {"coordinates":[-70.25415099999999,43.668693],"type":"Point"}
}