{
  "type": "Feature",
  "properties": {
    "addr:full":"1456 US Hwy 1 Freeport ME 04032",
    "addr:housenumber":"1456",
    "addr:postcode":"04032",
    "addr:street":"Us Hwy 1",
    "iso:country":"US",
    "sg:address":"1456 US Hwy 1",
    "sg:city":"Freeport",
    "sg:classifiers":[
        {
            "category":"Communications",
            "subcategory":"Radio Station",
            "type":"Services"
        }
    ],
    "sg:phone":"+1 207 865 3448",
    "sg:postcode":"04032",
    "sg:province":"ME",
    "sg:tags":[
        "company",
        "broadcasting"
    ],
    "wof:name":"WMSJ",
    "wof:placetype":"venue"
},
  "geometry": {"coordinates":[-70.081903,43.880257],"type":"Point"}
}