{
  "type": "Feature",
  "properties": {
    "addr:full":"32 Pines Rd Benton ME 04901",
    "addr:housenumber":"32",
    "addr:postcode":"04901",
    "addr:street":"Pines Rd",
    "iso:country":"US",
    "sg:address":"32 Pines Rd",
    "sg:city":"Benton",
    "sg:classifiers":[
        {
            "category":"Building & Trades",
            "subcategory":"Landscaping Services",
            "type":"Services"
        }
    ],
    "sg:phone":"+1 207 453 0070",
    "sg:postcode":"04901",
    "sg:province":"ME",
    "sg:tags":[
        "landscape",
        "contractor"
    ],
    "wof:name":"Goodwin's Unlimited",
    "wof:placetype":"venue"
},
  "geometry": {"coordinates":[-69.551035,44.576889],"type":"Point"}
}