{
  "type": "Feature",
  "properties": {
    "iso:country":"US",
    "sg:address":"50 Houlton Rd",
    "sg:city":"Island Falls",
    "sg:classifiers":[
        {
            "category":"Food & Beverages",
            "subcategory":"Groceries & Convenience Stores",
            "type":"Retail Goods"
        }
    ],
    "sg:phone":"+1 207 463 2828",
    "sg:postcode":"04769",
    "sg:province":"ME",
    "sg:tags":[
        "grocer"
    ],
    "wof:name":"Jerry's Thriftway",
    "wof:placetype":"venue"
},
  "geometry": {"coordinates":[-68.006074,46.656461],"type":"Point"}
}