{
  "type": "Feature",
  "properties": {
    "iso:country":"US",
    "sg:address":"333 Cony Rd",
    "sg:city":"Augusta",
    "sg:classifiers":[
        {
            "category":"Government",
            "subcategory":"Office",
            "type":"Public Place"
        }
    ],
    "sg:phone":"+1 207 287 3621",
    "sg:postcode":"04330",
    "sg:province":"ME",
    "wof:name":"Dairy Council & Promotion Brd",
    "wof:placetype":"venue"
},
  "geometry": {"coordinates":[-69.744661,44.298787],"type":"Point"}
}