{
  "type": "Feature",
  "properties": {
    "addr:full":"333 Cony Rd Augusta ME 04330",
    "addr:housenumber":"333",
    "addr:postcode":"04330",
    "addr:street":"Cony Rd",
    "iso:country":"US",
    "sg:address":"333 Cony Rd",
    "sg:city":"Augusta",
    "sg:classifiers":[
        {
            "category":"Government",
            "subcategory":"Office",
            "type":"Public Place"
        }
    ],
    "sg:phone":"+1 207 287 3621",
    "sg:postcode":"04330",
    "sg:province":"ME",
    "wof:name":"Dairy Council & Promotion Brd",
    "wof:placetype":"venue"
},
  "geometry": {"coordinates":[-69.74466099999999,44.298787],"type":"Point"}
}