{
  "type": "Feature",
  "properties": {
    "addr:full":"53 E Grand Ave Old Orchard Bch ME 04064",
    "addr:housenumber":"53",
    "addr:postcode":"04064",
    "addr:street":"E Grand Ave",
    "iso:country":"US",
    "sg:address":"53 E Grand Ave",
    "sg:city":"Old Orchard Bch",
    "sg:classifiers":[
        {
            "category":"Restaurant",
            "type":"Food & Drink"
        }
    ],
    "sg:phone":"+1 207 934 2733",
    "sg:postcode":"04064",
    "sg:province":"ME",
    "wof:name":"Christopher's Lobster Pound",
    "wof:placetype":"venue"
},
  "geometry": {"coordinates":[-70.37075900000001,43.520029],"type":"Point"}
}