{
  "type": "Feature",
  "properties": {
    "addr:full":"650 Brighton Ave Portland ME 04102",
    "addr:housenumber":"650",
    "addr:postcode":"04102",
    "addr:street":"Brighton Ave",
    "iso:country":"US",
    "sg:address":"650 Brighton Ave",
    "sg:city":"Portland",
    "sg:classifiers":[
        {
            "category":"Health Services",
            "subcategory":"Health Practitioner",
            "type":"Services"
        }
    ],
    "sg:phone":"+1 207 828 4299",
    "sg:postcode":"04102",
    "sg:province":"ME",
    "sg:tags":[
        "physician"
    ],
    "wof:name":"Center-Advanced Natural Med",
    "wof:placetype":"venue"
},
  "geometry": {"coordinates":[-70.306237,43.670356],"type":"Point"}
}