{
  "type": "Feature",
  "properties": {
    "iso:country":"US",
    "sg:address":"489 State St",
    "sg:city":"Bangor",
    "sg:classifiers":[
        {
            "category":"Health Services",
            "subcategory":"Doctor",
            "type":"Services"
        }
    ],
    "sg:phone":"+1 207 973 8000",
    "sg:postcode":"04401",
    "sg:province":"ME",
    "sg:tags":[
        "physician",
        "surgeon"
    ],
    "wof:name":"Jacques Larochelle MD",
    "wof:placetype":"venue"
},
  "geometry": {"coordinates":[-68.74995199999999,44.809739],"type":"Point"}
}