{
  "type": "Feature",
  "properties": {
    "addr:full":"20 Day St South Portland ME 04106",
    "addr:housenumber":"20",
    "addr:postcode":"04106",
    "addr:street":"Day St",
    "iso:country":"US",
    "sg:address":"20 Day St",
    "sg:city":"South Portland",
    "sg:classifiers":[
        {
            "category":"Professional",
            "type":"Services"
        }
    ],
    "sg:phone":"+1 207 741 2908",
    "sg:postcode":"04106",
    "sg:province":"ME",
    "sg:tags":[
        "establishment"
    ],
    "wof:name":"M P Assoc",
    "wof:placetype":"venue"
},
  "geometry": {"coordinates":[-70.23155800000001,43.640192],"type":"Point"}
}