{
  "type": "Feature",
  "properties": {
    "addr:full":"5 Main St Gray ME 04039",
    "addr:housenumber":"5",
    "addr:postcode":"04039",
    "addr:street":"Main St",
    "iso:country":"US",
    "sg:address":"5 Main St",
    "sg:city":"Gray",
    "sg:classifiers":[
        {
            "category":"Retail",
            "subcategory":"Repair Shop",
            "type":"Services"
        }
    ],
    "sg:phone":"+1 207 657 2777",
    "sg:postcode":"04039",
    "sg:province":"ME",
    "sg:tags":[
        "lock",
        "locksmith"
    ],
    "wof:name":"Al Martin & Son Locksmith",
    "wof:placetype":"venue"
},
  "geometry": {"coordinates":[-70.330591,43.885709],"type":"Point"}
}