{
  "type": "Feature",
  "properties": {
    "iso:country":"US",
    "sg:address":"8 Fleming St",
    "sg:city":"Lincoln",
    "sg:classifiers":[
        {
            "category":"Organizations",
            "subcategory":"Non-profit Organization",
            "type":"Services"
        }
    ],
    "sg:phone":"+1 207 794 3283",
    "sg:postcode":"04457",
    "sg:province":"ME",
    "wof:name":"Lincoln Community Transition",
    "wof:placetype":"venue"
},
  "geometry": {"coordinates":[-68.504761,45.365678],"type":"Point"}
}