{
  "type": "Feature",
  "properties": {
    "addr:full":"21 McKeen St Brunswick ME 04011",
    "addr:housenumber":"21",
    "addr:postcode":"04011",
    "addr:street":"Mckeen St",
    "iso:country":"US",
    "sg:address":"21 McKeen St",
    "sg:city":"Brunswick",
    "sg:classifiers":[
        {
            "category":"Professional",
            "subcategory":"Business Services",
            "type":"Services"
        }
    ],
    "sg:phone":"+1 207 725 2888",
    "sg:postcode":"04011",
    "sg:province":"ME",
    "sg:tags":[
        "textile",
        "good",
        "mfg"
    ],
    "wof:name":"Textile Enhancements Intl",
    "wof:placetype":"venue"
},
  "geometry": {"coordinates":[-69.968773,43.907827],"type":"Point"}
}