{
  "type": "Feature",
  "properties": {
    "addr:full":"970 Baxter Blvd Portland ME 04103",
    "addr:housenumber":"970",
    "addr:postcode":"04103",
    "addr:street":"Baxter Blvd",
    "iso:country":"US",
    "sg:address":"970 Baxter Blvd",
    "sg:city":"Portland",
    "sg:classifiers":[
        {
            "category":"Real Estate",
            "subcategory":"Real Estate Agent",
            "type":"Services"
        }
    ],
    "sg:phone":"+1 207 773 8987",
    "sg:postcode":"04103",
    "sg:province":"ME",
    "wof:name":"Elizabeth McFadden RE Appraisr",
    "wof:placetype":"venue"
},
  "geometry": {"coordinates":[-70.258574,43.678916],"type":"Point"}
}