{
  "type": "Feature",
  "properties": {
    "iso:country":"US",
    "sg:address":"433 US Hwy 1",
    "sg:city":"York",
    "sg:classifiers":[
        {
            "category":"Insurance",
            "subcategory":"Insurance Agent",
            "type":"Services"
        }
    ],
    "sg:phone":"+1 207 363 8556",
    "sg:postcode":"03909",
    "sg:province":"ME",
    "wof:name":"Anthony A Mont",
    "wof:placetype":"venue"
},
  "geometry": {"coordinates":[-70.665832,43.150666],"type":"Point"}
}