{
  "type": "Feature",
  "properties": {
    "addr:full":"65 Columbia Ave Brunswick ME 04011",
    "addr:housenumber":"65",
    "addr:postcode":"04011",
    "addr:street":"Columbia Ave",
    "iso:country":"US",
    "sg:address":"65 Columbia Ave",
    "sg:city":"Brunswick",
    "sg:classifiers":[
        {
            "category":"Education",
            "subcategory":"School",
            "type":"Public Place"
        }
    ],
    "sg:phone":"+1 207 729 1669",
    "sg:postcode":"04011",
    "sg:province":"ME",
    "wof:name":"Brunswick Junior High School",
    "wof:placetype":"venue"
},
  "geometry": {"coordinates":[-69.978494,43.90284],"type":"Point"}
}