{
  "type": "Feature",
  "properties": {
    "addr:full":"61 Old Calais Rd Hodgdon ME 04730",
    "addr:housenumber":"61",
    "addr:postcode":"04730",
    "addr:street":"Old Calais Rd",
    "iso:country":"US",
    "sg:address":"61 Old Calais Rd",
    "sg:city":"Hodgdon",
    "sg:classifiers":[
        {
            "category":"Sports & Exercise",
            "subcategory":"Bowling",
            "type":"Entertainment"
        }
    ],
    "sg:phone":"+1 207 532 6791",
    "sg:postcode":"04730",
    "sg:province":"ME",
    "sg:tags":[
        "center"
    ],
    "wof:name":"Hill-Top Lanes",
    "wof:placetype":"venue"
},
  "geometry": {"coordinates":[-67.840571,46.111748],"type":"Point"}
}