{
  "type": "Feature",
  "properties": {
    "addr:full":"75 Bishop St Portland ME 04103",
    "addr:housenumber":"75",
    "addr:postcode":"04103",
    "addr:street":"Bishop St",
    "iso:country":"US",
    "sg:address":"75 Bishop St",
    "sg:city":"Portland",
    "sg:classifiers":[
        {
            "category":"Insurance",
            "subcategory":"Insurance Agent",
            "type":"Services"
        }
    ],
    "sg:phone":"+1 207 775 1133",
    "sg:postcode":"04103",
    "sg:province":"ME",
    "wof:name":"American Income Life Ins Co",
    "wof:placetype":"venue"
},
  "geometry": {"coordinates":[-70.29879,43.687252],"type":"Point"}
}