{
  "type": "Feature",
  "properties": {
    "addr:full":"319 Grant Rd St Albans ME 04971",
    "addr:housenumber":"319",
    "addr:postcode":"04971",
    "addr:street":"Grant Rd",
    "iso:country":"US",
    "sg:address":"319 Grant Rd",
    "sg:city":"St Albans",
    "sg:classifiers":[
        {
            "category":"Professional",
            "subcategory":"Computer Services",
            "type":"Services"
        }
    ],
    "sg:phone":"+1 207 938 3450",
    "sg:postcode":"04971",
    "sg:province":"ME",
    "sg:tags":[
        "repair"
    ],
    "wof:name":"Ashton Computers",
    "wof:placetype":"venue"
},
  "geometry": {"coordinates":[-69.40421000000001,44.942691],"type":"Point"}
}