{
  "type": "Feature",
  "properties": {
    "iso:country":"US",
    "sg:address":"55 Front St",
    "sg:city":"Bath",
    "sg:classifiers":[
        {
            "category":"Government",
            "subcategory":"Office",
            "type":"Public Place"
        }
    ],
    "sg:phone":"+1 207 443 8336",
    "sg:postcode":"04530",
    "sg:province":"ME",
    "sg:tags":[
        "city",
        "taxation"
    ],
    "wof:name":"City Of Bath Assessors Office",
    "wof:placetype":"venue"
},
  "geometry": {"coordinates":[-69.814207,43.913443],"type":"Point"}
}