{
  "type": "Feature",
  "properties": {
    "addr:full":"12 Crystal Ln Cumberland Ctr ME 04021",
    "addr:housenumber":"12",
    "addr:postcode":"04021",
    "addr:street":"Crystal Ln",
    "iso:country":"US",
    "sg:address":"12 Crystal Ln",
    "sg:city":"Cumberland Ctr",
    "sg:classifiers":[
        {
            "category":"Real Estate",
            "subcategory":"Real Estate Agent",
            "type":"Services"
        }
    ],
    "sg:phone":"+1 207 829 9304",
    "sg:postcode":"04021",
    "sg:province":"ME",
    "sg:tags":[
        "appraiser"
    ],
    "wof:name":"Craig C Milne",
    "wof:placetype":"venue"
},
  "geometry": {"coordinates":[-70.25567100000001,43.807237],"type":"Point"}
}