{
  "type": "Feature",
  "properties": {
    "addr:full":"224 Bath Rd Brunswick ME 04011",
    "addr:housenumber":"224",
    "addr:postcode":"04011",
    "addr:street":"Bath Rd",
    "iso:country":"US",
    "sg:address":"224 Bath Rd",
    "sg:city":"Brunswick",
    "sg:classifiers":[
        {
            "category":"Travel",
            "subcategory":"Hotels & Motels",
            "type":"Entertainment"
        }
    ],
    "sg:phone":"+1 207 725 8883",
    "sg:postcode":"04011",
    "sg:province":"ME",
    "wof:name":"Super 8 Motel",
    "wof:placetype":"venue"
},
  "geometry": {"coordinates":[-69.913011,43.908374],"type":"Point"}
}