{
  "type": "Feature",
  "properties": {
    "addr:full":"54 Pine St Lewiston ME 04240",
    "addr:housenumber":"54",
    "addr:postcode":"04240",
    "addr:street":"Pine St",
    "iso:country":"US",
    "sg:address":"54 Pine St",
    "sg:city":"Lewiston",
    "sg:classifiers":[
        {
            "category":"Professional",
            "subcategory":"Lawyer & Legal Services",
            "type":"Services"
        }
    ],
    "sg:phone":"+1 207 784 2931",
    "sg:postcode":"04240",
    "sg:province":"ME",
    "sg:tags":[
        "attorney"
    ],
    "wof:name":"Cote Cote Hamann & Fournier",
    "wof:placetype":"venue"
},
  "geometry": {"coordinates":[-70.21388,44.096069],"type":"Point"}
}