{
  "type": "Feature",
  "properties": {
    "addr:full":"252 Main St Warren ME 04864",
    "addr:housenumber":"252",
    "addr:postcode":"04864",
    "addr:street":"Main St",
    "iso:country":"US",
    "sg:address":"252 Main St",
    "sg:city":"Warren",
    "sg:classifiers":[
        {
            "category":"Organizations",
            "subcategory":"Religious Organization",
            "type":"Services"
        }
    ],
    "sg:phone":"+1 207 273 2338",
    "sg:postcode":"04864",
    "sg:province":"ME",
    "sg:tags":[
        "church"
    ],
    "wof:name":"Second Congregational Church",
    "wof:placetype":"venue"
},
  "geometry": {"coordinates":[-69.24138499999999,44.120547],"type":"Point"}
}