{
  "type": "Feature",
  "properties": {
    "iso:country":"US",
    "sg:address":"758 W Minot Rd",
    "sg:city":"West Minot",
    "sg:classifiers":[
        {
            "category":"Government",
            "subcategory":"Post Office",
            "type":"Public Place"
        }
    ],
    "sg:phone":"+1 207 966 2602",
    "sg:postcode":"04258",
    "sg:province":"ME",
    "wof:name":"US Post Office",
    "wof:placetype":"venue"
},
  "geometry": {"coordinates":[-70.367041,44.170937],"type":"Point"}
}