{
  "type": "Feature",
  "properties": {
    "iso:country":"US",
    "sg:address":"71 Poplar St",
    "sg:city":"Bangor",
    "sg:classifiers":[
        {
            "category":"Professional",
            "subcategory":"Business Services",
            "type":"Services"
        }
    ],
    "sg:phone":"+1 207 942 2880",
    "sg:postcode":"04401",
    "sg:province":"ME",
    "wof:name":"Chas E Heinonen Site Evaluator",
    "wof:placetype":"venue"
},
  "geometry": {"coordinates":[-68.777001,44.81713],"type":"Point"}
}