{
  "type": "Feature",
  "properties": {
    "iso:country":"US",
    "sg:address":"28 Neck Rd",
    "sg:city":"Litchfield",
    "sg:classifiers":[
        {
            "category":"Professional",
            "subcategory":"Secretarial Services",
            "type":"Services"
        }
    ],
    "sg:phone":"+1 207 268 4496",
    "sg:postcode":"04348",
    "sg:province":"ME",
    "sg:tags":[
        "convention",
        "court",
        "reporter"
    ],
    "wof:name":"Bickford & Melton Reporting",
    "wof:placetype":"venue"
},
  "geometry": {"coordinates":[-69.498337,44.188087],"type":"Point"}
}