{
  "type": "Feature",
  "properties": {
    "iso:country":"US",
    "sg:address":"2 Profenno Way",
    "sg:city":"Freeport",
    "sg:classifiers":[
        {
            "category":"Freight",
            "type":"Transportation"
        }
    ],
    "sg:phone":"+1 207 865 3920",
    "sg:postcode":"04032",
    "sg:province":"ME",
    "sg:tags":[
        "commercial",
        "storage",
        "special"
    ],
    "wof:name":"Freeport Self Storage",
    "wof:placetype":"venue"
},
  "geometry": {"coordinates":[-70.07025899999999,43.886514],"type":"Point"}
}