{
  "type": "Feature",
  "properties": {
    "iso:country":"US",
    "sg:address":"1 Depot St",
    "sg:city":"Livermore Falls",
    "sg:classifiers":[
        {
            "category":"Personal",
            "subcategory":"Beauty Salon",
            "type":"Services"
        }
    ],
    "sg:phone":"+1 207 897 7007",
    "sg:postcode":"04254",
    "sg:province":"ME",
    "sg:tags":[
        "manicuring"
    ],
    "wof:name":"Nothin' But Nails II",
    "wof:placetype":"venue"
},
  "geometry": {"coordinates":[-70.186734,44.472763],"type":"Point"}
}