{
  "type": "Feature",
  "properties": {
    "iso:country":"US",
    "sg:address":"465 Main St",
    "sg:city":"Lewiston",
    "sg:classifiers":[
        {
            "category":"Social Services",
            "type":"Services"
        }
    ],
    "sg:phone":"+1 207 795 4970",
    "sg:postcode":"04240",
    "sg:province":"ME",
    "sg:tags":[
        "counselor",
        "marriage",
        "family"
    ],
    "wof:name":"Ralph Sprague",
    "wof:placetype":"venue"
},
  "geometry": {"coordinates":[-70.21054,44.106813],"type":"Point"}
}