{
  "type": "Feature",
  "properties": {
    "addr:full":"256 Northport Ave Belfast ME 04915",
    "addr:housenumber":"256",
    "addr:postcode":"04915",
    "addr:street":"Northport Ave",
    "iso:country":"US",
    "sg:address":"256 Northport Ave",
    "sg:city":"Belfast",
    "sg:classifiers":[
        {
            "category":"Retail",
            "subcategory":"Animal Services",
            "type":"Services"
        }
    ],
    "sg:phone":"+1 207 338 2423",
    "sg:postcode":"04915",
    "sg:province":"ME",
    "sg:tags":[
        "pet"
    ],
    "wof:name":"Black Paw & Co",
    "wof:placetype":"venue"
},
  "geometry": {"coordinates":[-68.98723,44.398765],"type":"Point"}
}