{
  "type": "Feature",
  "properties": {
    "addr:full":"8 Dover Rd Anson ME 04939",
    "addr:housenumber":"8",
    "addr:postcode":"04939",
    "addr:street":"Dover Rd",
    "iso:country":"US",
    "sg:address":"8 Dover Rd",
    "sg:city":"Anson",
    "sg:classifiers":[
        {
            "category":"Freight",
            "type":"Transportation"
        }
    ],
    "sg:phone":"+1 207 696 3655",
    "sg:postcode":"04939",
    "sg:province":"ME",
    "sg:tags":[
        "trucking"
    ],
    "wof:name":"Evans Delivery Svc",
    "wof:placetype":"venue"
},
  "geometry": {"coordinates":[-69.10976599999999,45.107029],"type":"Point"}
}