{
  "type": "Feature",
  "properties": {
    "addr:full":"26 Portland Street Pier South Portland ME 04106",
    "addr:housenumber":"26",
    "addr:postcode":"04106",
    "addr:street":"Portland Street Pier",
    "iso:country":"US",
    "sg:address":"26 Portland Street Pier",
    "sg:city":"South Portland",
    "sg:classifiers":[
        {
            "category":"Insurance",
            "subcategory":"Insurance Agent",
            "type":"Services"
        }
    ],
    "sg:phone":"+1 207 772 1997",
    "sg:postcode":"04106",
    "sg:province":"ME",
    "wof:name":"Allstate Insurance",
    "wof:placetype":"venue"
},
  "geometry": {"coordinates":[-70.242484,43.650083],"type":"Point"}
}