{
  "type": "Feature",
  "properties": {
    "addr:full":"23 High St Fort Fairfield ME 04742",
    "addr:housenumber":"23",
    "addr:postcode":"04742",
    "addr:street":"High St",
    "iso:country":"US",
    "sg:address":"23 High St",
    "sg:city":"Fort Fairfield",
    "sg:classifiers":[
        {
            "category":"Health Services",
            "subcategory":"Hospital",
            "type":"Services"
        }
    ],
    "sg:phone":"+1 207 768 4731",
    "sg:postcode":"04742",
    "sg:province":"ME",
    "sg:tags":[
        "mental"
    ],
    "sg:website":"www.aroostook.org",
    "wof:name":"Tamc Psychiatric Svc",
    "wof:placetype":"venue"
},
  "geometry": {"coordinates":[-67.83724100000001,46.773418],"type":"Point"}
}