{
  "type": "Feature",
  "properties": {
    "addr:full":"12 Westfield St Portland ME 04102",
    "addr:housenumber":"12",
    "addr:postcode":"04102",
    "addr:street":"Westfield St",
    "iso:country":"US",
    "sg:address":"12 Westfield St",
    "sg:city":"Portland",
    "sg:classifiers":[
        {
            "category":"Wholesale",
            "subcategory":"Construction Materials",
            "type":"Manufacturing & Wholesale Goods"
        }
    ],
    "sg:phone":"+1 207 772 1955",
    "sg:postcode":"04102",
    "sg:province":"ME",
    "sg:tags":[
        "tile"
    ],
    "wof:name":"Albert F Fitzgerald Inc",
    "wof:placetype":"venue"
},
  "geometry": {"coordinates":[-70.28278299999999,43.653112],"type":"Point"}
}