{
  "type": "Feature",
  "properties": {
    "iso:country":"US",
    "sg:address":"28 Water St",
    "sg:city":"Biddeford",
    "sg:classifiers":[
        {
            "category":"Personal",
            "type":"Services"
        }
    ],
    "sg:phone":"+1 207 283 9101",
    "sg:postcode":"04005",
    "sg:province":"ME",
    "wof:name":"Ink Factory Inc",
    "wof:placetype":"venue"
},
  "geometry": {"coordinates":[-70.449827,43.492318],"type":"Point"}
}