{
  "type": "Feature",
  "properties": {
    "iso:country":"US",
    "sg:address":"1 Church St",
    "sg:city":"Jay",
    "sg:classifiers":[
        {
            "category":"Education",
            "subcategory":"School",
            "type":"Public Place"
        }
    ],
    "sg:phone":"+1 207 897 3940",
    "sg:postcode":"04239",
    "sg:province":"ME",
    "wof:name":"St Rose's School",
    "wof:placetype":"venue"
},
  "geometry": {"coordinates":[-70.19158299999999,44.479855],"type":"Point"}
}