{
  "type": "Feature",
  "properties": {
    "iso:country":"US",
    "sg:address":"60 Portland Pier",
    "sg:city":"Portland",
    "sg:classifiers":[
        {
            "category":"Wholesale",
            "subcategory":"Seafood",
            "type":"Manufacturing & Wholesale Goods"
        }
    ],
    "sg:phone":"+1 207 775 1612",
    "sg:postcode":"04101",
    "sg:province":"ME",
    "sg:website":"www.newmeadowslobster.com",
    "wof:name":"Newmeadows Lobster Inc",
    "wof:placetype":"venue"
},
  "geometry": {"coordinates":[-70.251294,43.656307],"type":"Point"}
}