{
  "type": "Feature",
  "properties": {
    "addr:full":"1729 Congress St Portland ME 04102",
    "addr:housenumber":"1729",
    "addr:postcode":"04102",
    "addr:street":"Congress St",
    "iso:country":"US",
    "sg:address":"1729 Congress St",
    "sg:city":"Portland",
    "sg:classifiers":[
        {
            "category":"Organizations",
            "subcategory":"Religious Organization",
            "type":"Services"
        }
    ],
    "sg:phone":"+1 207 773 2211",
    "sg:postcode":"04102",
    "sg:province":"ME",
    "sg:tags":[
        "church"
    ],
    "wof:name":"Stroudwater Baptist Church",
    "wof:placetype":"venue"
},
  "geometry": {"coordinates":[-70.311509,43.658721],"type":"Point"}
}