{
  "type": "Feature",
  "properties": {
    "addr:full":"901 Roosevelt Trl Windham ME 04062",
    "addr:housenumber":"901",
    "addr:postcode":"04062",
    "addr:street":"Roosevelt Trl",
    "iso:country":"US",
    "sg:address":"901 Roosevelt Trl",
    "sg:city":"Windham",
    "sg:classifiers":[
        {
            "category":"Food & Beverages",
            "subcategory":"Meat & Fish",
            "type":"Retail Goods"
        }
    ],
    "sg:phone":"+1 207 893 2882",
    "sg:postcode":"04062",
    "sg:province":"ME",
    "sg:tags":[
        "seafood"
    ],
    "wof:name":"Bob's Seafood",
    "wof:placetype":"venue"
},
  "geometry": {"coordinates":[-70.450248,43.8509],"type":"Point"}
}