{
  "type": "Feature",
  "properties": {
    "iso:country":"US",
    "sg:address":"4 Park St",
    "sg:city":"Lewiston",
    "sg:classifiers":[
        {
            "category":"Social Services",
            "type":"Services"
        }
    ],
    "sg:phone":"+1 207 784 0922",
    "sg:postcode":"04240",
    "sg:province":"ME",
    "sg:tags":[
        "counselor",
        "marriage",
        "family"
    ],
    "wof:name":"Facing Change",
    "wof:placetype":"venue"
},
  "geometry": {"coordinates":[-70.217159,44.099034],"type":"Point"}
}