{
  "type": "Feature",
  "properties": {
    "addr:full":"4 Union St Bangor ME 04401",
    "addr:housenumber":"4",
    "addr:postcode":"04401",
    "addr:street":"Union St",
    "iso:country":"US",
    "sg:address":"4 Union St",
    "sg:city":"Bangor",
    "sg:classifiers":[
        {
            "category":"Building & Trades",
            "subcategory":"Cleaning & Sanitation",
            "type":"Services"
        }
    ],
    "sg:phone":"+1 207 941 9444",
    "sg:postcode":"04401",
    "sg:province":"ME",
    "sg:tags":[
        "janitor"
    ],
    "wof:name":"CMC & Maintenance",
    "wof:placetype":"venue"
},
  "geometry": {"coordinates":[-68.771219,44.79808],"type":"Point"}
}