{
  "type": "Feature",
  "properties": {
    "iso:country":"US",
    "sg:address":"884 Portland Rd",
    "sg:city":"Saco",
    "sg:classifiers":[
        {
            "category":"Autos & Motor Vehicles",
            "subcategory":"Automobile Sales",
            "type":"Retail Goods"
        }
    ],
    "sg:phone":"+1 207 284 5986",
    "sg:postcode":"04072",
    "sg:province":"ME",
    "sg:tags":[
        "car",
        "dealer"
    ],
    "sg:website":"www.frankgalos.com",
    "wof:name":"Frank Galos Chvrlet Cdillc Inc",
    "wof:placetype":"venue"
},
  "geometry": {"coordinates":[-70.423175,43.535048],"type":"Point"}
}