{
  "type": "Feature",
  "properties": {
    "iso:country":"US",
    "sg:address":"10 Gibson Rd",
    "sg:city":"Scarborough",
    "sg:classifiers":[
        {
            "category":"Manufacturing",
            "subcategory":"Tools & Machinery",
            "type":"Manufacturing & Wholesale Goods"
        }
    ],
    "sg:phone":"+1 207 883 8155",
    "sg:postcode":"04074",
    "sg:province":"ME",
    "sg:tags":[
        "engine",
        "internal",
        "combustion",
        "mfg"
    ],
    "wof:name":"Cummins Inc",
    "wof:placetype":"venue"
},
  "geometry": {"coordinates":[-70.303428,43.607836],"type":"Point"}
}