{
  "type": "Feature",
  "properties": {
    "addr:full":"945 Coastal Rd Brooksville ME 04617",
    "addr:housenumber":"945",
    "addr:postcode":"04617",
    "addr:street":"Coastal Rd",
    "iso:country":"US",
    "sg:address":"945 Coastal Rd",
    "sg:city":"Brooksville",
    "sg:classifiers":[
        {
            "category":"Government",
            "subcategory":"Post Office",
            "type":"Public Place"
        }
    ],
    "sg:phone":"+1 207 326 4873",
    "sg:postcode":"04617",
    "sg:province":"ME",
    "wof:name":"US Post Office",
    "wof:placetype":"venue"
},
  "geometry": {"coordinates":[-68.749713,44.360124],"type":"Point"}
}