{
  "type": "Feature",
  "properties": {
    "addr:full":"125 Dube Dr Sabattus ME 04280",
    "addr:housenumber":"125",
    "addr:postcode":"04280",
    "addr:street":"Dube Dr",
    "iso:country":"US",
    "sg:address":"125 Dube Dr",
    "sg:city":"Sabattus",
    "sg:classifiers":[
        {
            "category":"Professional",
            "subcategory":"Business Services",
            "type":"Services"
        }
    ],
    "sg:phone":"+1 207 375 8657",
    "sg:postcode":"04280",
    "sg:province":"ME",
    "sg:tags":[
        "notary"
    ],
    "wof:name":"Carmella Rose Murphy",
    "wof:placetype":"venue"
},
  "geometry": {"coordinates":[-70.09464199999999,44.065234],"type":"Point"}
}