{
  "type": "Feature",
  "properties": {
    "addr:full":"40 Carver St Bangor ME 04401",
    "addr:housenumber":"40",
    "addr:postcode":"04401",
    "addr:street":"Carver St",
    "iso:country":"US",
    "sg:address":"40 Carver St",
    "sg:city":"Bangor",
    "sg:classifiers":[
        {
            "category":"Personal",
            "subcategory":"Beauty Salon",
            "type":"Services"
        }
    ],
    "sg:phone":"+1 207 942 4345",
    "sg:postcode":"04401",
    "sg:province":"ME",
    "sg:tags":[
        "shop"
    ],
    "wof:name":"Image",
    "wof:placetype":"venue"
},
  "geometry": {"coordinates":[-68.78764099999999,44.793997],"type":"Point"}
}