{
  "type": "Feature",
  "properties": {
    "iso:country":"US",
    "sg:address":"168 Ridge Rd",
    "sg:city":"Bowdoinham",
    "sg:classifiers":[
        {
            "category":"Professional",
            "subcategory":"Computer Services",
            "type":"Services"
        }
    ],
    "sg:phone":"+1 207 666 5750",
    "sg:postcode":"04008",
    "sg:province":"ME",
    "sg:tags":[
        "house",
        "custom",
        "programing",
        "mail"
    ],
    "wof:name":"Project Pluto",
    "wof:placetype":"venue"
},
  "geometry": {"coordinates":[-69.888705,44.019387],"type":"Point"}
}