{
  "type": "Feature",
  "properties": {
    "addr:full":"7 Canal St Lisbon Falls ME 04294",
    "addr:housenumber":"7",
    "addr:postcode":"04294",
    "addr:street":"Canal St",
    "iso:country":"US",
    "sg:address":"7 Canal St",
    "sg:city":"Lisbon Falls",
    "sg:classifiers":[
        {
            "category":"Manufacturing",
            "subcategory":"Textiles",
            "type":"Manufacturing & Wholesale Goods"
        }
    ],
    "sg:phone":"+1 207 353 4371",
    "sg:postcode":"04294",
    "sg:province":"ME",
    "sg:tags":[
        "mills"
    ],
    "sg:website":"www.mjblankets.com",
    "wof:name":"Miller Industries",
    "wof:placetype":"venue"
},
  "geometry": {"coordinates":[-70.23291399999999,44.586563],"type":"Point"}
}