{
  "type": "Feature",
  "properties": {
    "iso:country":"US",
    "sg:address":"2 Fore St",
    "sg:city":"Portland",
    "sg:classifiers":[
        {
            "category":"Professional",
            "subcategory":"Lawyer & Legal Services",
            "type":"Services"
        }
    ],
    "sg:phone":"+1 207 772 2800",
    "sg:postcode":"04101",
    "sg:province":"ME",
    "sg:tags":[
        "attorney"
    ],
    "sg:website":"www.leblancyoung.com",
    "wof:name":"Le Blanc & Young",
    "wof:placetype":"venue"
},
  "geometry": {"coordinates":[-70.243738,43.663677],"type":"Point"}
}