{
  "type": "Feature",
  "properties": {
    "addr:full":"135 Dennett Rd Biddeford ME 04005",
    "addr:housenumber":"135",
    "addr:postcode":"04005",
    "addr:street":"Dennett Rd",
    "iso:country":"US",
    "sg:address":"135 Dennett Rd",
    "sg:city":"Biddeford",
    "sg:classifiers":[
        {
            "category":"Building & Trades",
            "subcategory":"Construction",
            "type":"Services"
        }
    ],
    "sg:phone":"+1 207 499 0072",
    "sg:postcode":"04005",
    "sg:province":"ME",
    "sg:tags":[
        "hanging",
        "contractor"
    ],
    "wof:name":"American Heritage Painting",
    "wof:placetype":"venue"
},
  "geometry": {"coordinates":[-70.56226700000001,43.498097],"type":"Point"}
}