{
  "type": "Feature",
  "properties": {
    "addr:full":"1401 Happytown Rd Ellsworth ME 04605",
    "addr:housenumber":"1401",
    "addr:postcode":"04605",
    "addr:street":"Happytown Rd",
    "iso:country":"US",
    "sg:address":"1401 Happytown Rd",
    "sg:city":"Ellsworth",
    "sg:classifiers":[
        {
            "category":"Building & Trades",
            "subcategory":"Construction",
            "type":"Services"
        }
    ],
    "sg:phone":"+1 207 667 5554",
    "sg:postcode":"04605",
    "sg:province":"ME",
    "sg:tags":[
        "house"
    ],
    "wof:name":"Lord Builders",
    "wof:placetype":"venue"
},
  "geometry": {"coordinates":[-68.62902,44.627176],"type":"Point"}
}