{
  "type": "Feature",
  "properties": {
    "addr:full":"34 Main St Camden ME 04843",
    "addr:housenumber":"34",
    "addr:postcode":"04843",
    "addr:street":"Main St",
    "iso:country":"US",
    "sg:address":"34 Main St",
    "sg:city":"Camden",
    "sg:classifiers":[
        {
            "category":"Shopping",
            "subcategory":"Luggage & Leather Goods",
            "type":"Retail Goods"
        }
    ],
    "sg:phone":"+1 207 236 4688",
    "sg:postcode":"04843",
    "sg:province":"ME",
    "sg:website":"www.leatherbench.com",
    "wof:name":"Leather Bench",
    "wof:placetype":"venue"
},
  "geometry": {"coordinates":[-69.06488899999999,44.21091],"type":"Point"}
}