{
  "type": "Feature",
  "properties": {
    "iso:country":"US",
    "sg:address":"397 Minot Ave",
    "sg:city":"Auburn",
    "sg:classifiers":[
        {
            "category":"Education",
            "subcategory":"School",
            "type":"Public Place"
        }
    ],
    "sg:phone":"+1 207 784 3559",
    "sg:postcode":"04210",
    "sg:province":"ME",
    "wof:name":"Fairview School",
    "wof:placetype":"venue"
},
  "geometry": {"coordinates":[-70.240936,44.085083],"type":"Point"}
}