{
  "type": "Feature",
  "properties": {
    "iso:country":"US",
    "sg:address":"379 Hudson Rd",
    "sg:city":"Glenburn",
    "sg:classifiers":[
        {
            "category":"Retail",
            "subcategory":"Repair Shop",
            "type":"Services"
        }
    ],
    "sg:phone":"+1 207 990 1773",
    "sg:postcode":"04401",
    "sg:province":"ME",
    "sg:tags":[
        "oil",
        "burner"
    ],
    "wof:name":"Heaten Oil Co",
    "wof:placetype":"venue"
},
  "geometry": {"coordinates":[-68.83831499999999,44.874549],"type":"Point"}
}