{
  "type": "Feature",
  "properties": {
    "addr:full":"120 Exchange St Portland ME 04101",
    "addr:housenumber":"120",
    "addr:postcode":"04101",
    "addr:street":"Exchange St",
    "iso:country":"US",
    "sg:address":"120 Exchange St",
    "sg:city":"Portland",
    "sg:classifiers":[
        {
            "category":"Professional",
            "subcategory":"Lawyer & Legal Services",
            "type":"Services"
        }
    ],
    "sg:phone":"+1 207 774 2266",
    "sg:postcode":"04101",
    "sg:province":"ME",
    "sg:tags":[
        "attorney"
    ],
    "wof:name":"Maxine P Pouravelis",
    "wof:placetype":"venue"
},
  "geometry": {"coordinates":[-70.25678499999999,43.659],"type":"Point"}
}