{
  "type": "Feature",
  "properties": {
    "iso:country":"US",
    "sg:address":"125 Valley Rd",
    "sg:city":"Plymouth",
    "sg:classifiers":[
        {
            "category":"Wholesale",
            "subcategory":"Farm Supplies",
            "type":"Manufacturing & Wholesale Goods"
        }
    ],
    "sg:phone":"+1 207 257 3430",
    "sg:postcode":"04921",
    "sg:province":"ME",
    "sg:tags":[
        "fertilizer"
    ],
    "wof:name":"Soil Preperation Inc",
    "wof:placetype":"venue"
},
  "geometry": {"coordinates":[-69.144206,44.550468],"type":"Point"}
}