{
  "type": "Feature",
  "properties": {
    "addr:full":"352 Main St Fort Fairfield ME 04742",
    "addr:housenumber":"352",
    "addr:postcode":"04742",
    "addr:street":"Main St",
    "iso:country":"US",
    "sg:address":"352 Main St",
    "sg:city":"Fort Fairfield",
    "sg:classifiers":[
        {
            "category":"Food & Beverages",
            "subcategory":"Groceries & Convenience Stores",
            "type":"Retail Goods"
        }
    ],
    "sg:phone":"+1 207 472 1333",
    "sg:postcode":"04742",
    "sg:province":"ME",
    "wof:name":"Harvest Market",
    "wof:placetype":"venue"
},
  "geometry": {"coordinates":[-67.834501,46.772634],"type":"Point"}
}