{
  "type": "Feature",
  "properties": {
    "addr:full":"18 Main Rd Holden ME 04429",
    "addr:housenumber":"18",
    "addr:postcode":"04429",
    "addr:street":"Main Rd",
    "iso:country":"US",
    "sg:address":"18 Main Rd",
    "sg:city":"Holden",
    "sg:classifiers":[
        {
            "category":"Travel",
            "subcategory":"Hotels & Motels",
            "type":"Entertainment"
        }
    ],
    "sg:phone":"+1 207 989 3060",
    "sg:postcode":"04429",
    "sg:province":"ME",
    "wof:name":"Town'n Country Motel",
    "wof:placetype":"venue"
},
  "geometry": {"coordinates":[-68.71101899999999,44.76686],"type":"Point"}
}