{
  "type": "Feature",
  "properties": {
    "iso:country":"US",
    "sg:address":"1221 Broadway",
    "sg:city":"Bangor",
    "sg:classifiers":[
        {
            "category":"Home & Garden",
            "subcategory":"Furniture",
            "type":"Retail Goods"
        }
    ],
    "sg:phone":"+1 207 947 8631",
    "sg:postcode":"04401",
    "sg:province":"ME",
    "wof:name":"Broadway Wholesale Furniture",
    "wof:placetype":"venue"
},
  "geometry": {"coordinates":[-68.793978,44.838764],"type":"Point"}
}