{
  "type": "Feature",
  "properties": {
    "addr:full":"83 College Ave Orono ME 04473",
    "addr:housenumber":"83",
    "addr:postcode":"04473",
    "addr:street":"College Ave",
    "iso:country":"US",
    "sg:address":"83 College Ave",
    "sg:city":"Orono",
    "sg:classifiers":[
        {
            "category":"Organizations",
            "subcategory":"Religious Organization",
            "type":"Services"
        }
    ],
    "sg:phone":"+1 207 866 2155",
    "sg:postcode":"04473",
    "sg:province":"ME",
    "sg:tags":[
        "church"
    ],
    "wof:name":"Newman Center",
    "wof:placetype":"venue"
},
  "geometry": {"coordinates":[-68.673436,44.89461],"type":"Point"}
}