{
  "type": "Feature",
  "properties": {
    "iso:country":"US",
    "sg:address":"1 Portland Ave",
    "sg:city":"Old Orchard Bch",
    "sg:classifiers":[
        {
            "category":"Government",
            "subcategory":"Office",
            "type":"Public Place"
        }
    ],
    "sg:phone":"+1 207 934 5714",
    "sg:postcode":"04064",
    "sg:province":"ME",
    "sg:tags":[
        "city",
        "village"
    ],
    "wof:name":"Old Orchard Beach Town Office",
    "wof:placetype":"venue"
},
  "geometry": {"coordinates":[-70.378148,43.519417],"type":"Point"}
}