{
  "type": "Feature",
  "properties": {
    "iso:country":"US",
    "sg:address":"796 Main St",
    "sg:city":"Vassalboro",
    "sg:classifiers":[
        {
            "category":"Restaurant",
            "type":"Food & Drink"
        }
    ],
    "sg:phone":"+1 207 872 9090",
    "sg:postcode":"04965",
    "sg:province":"ME",
    "wof:name":"Sunrise Lunch",
    "wof:placetype":"venue"
},
  "geometry": {"coordinates":[-69.364366,44.847214],"type":"Point"}
}