{
  "type": "Feature",
  "properties": {
    "iso:country":"US",
    "sg:address":"76 Main St",
    "sg:city":"Waterville",
    "sg:classifiers":[
        {
            "category":"Health Services",
            "subcategory":"Health Practitioner",
            "type":"Services"
        }
    ],
    "sg:phone":"+1 207 872 7831",
    "sg:postcode":"04901",
    "sg:province":"ME",
    "sg:tags":[
        "psychologist"
    ],
    "wof:name":"Willard E Millis Jr",
    "wof:placetype":"venue"
},
  "geometry": {"coordinates":[-69.632165,44.556889],"type":"Point"}
}