{
  "type": "Feature",
  "properties": {
    "iso:country":"US",
    "sg:address":"216 North Rd",
    "sg:city":"Dixmont",
    "sg:classifiers":[
        {
            "category":"Health Services",
            "subcategory":"Health Practitioner",
            "type":"Services"
        }
    ],
    "sg:phone":"+1 207 257 3178",
    "sg:postcode":"04942",
    "sg:province":"ME",
    "sg:tags":[
        "therapist",
        "physical"
    ],
    "wof:name":"Exub Living Physical Therapy",
    "wof:placetype":"venue"
},
  "geometry": {"coordinates":[-69.582955,44.985706],"type":"Point"}
}