{
  "type": "Feature",
  "properties": {
    "addr:full":"98 Chestnut St Portland ME 04101",
    "addr:housenumber":"98",
    "addr:postcode":"04101",
    "addr:street":"Chestnut St",
    "iso:country":"US",
    "sg:address":"98 Chestnut St",
    "sg:city":"Portland",
    "sg:classifiers":[
        {
            "category":"Manufacturing",
            "subcategory":"Printing",
            "type":"Manufacturing & Wholesale Goods"
        }
    ],
    "sg:phone":"+1 207 772 8900",
    "sg:postcode":"04101",
    "sg:province":"ME",
    "sg:tags":[
        "publisher"
    ],
    "wof:name":"Provincial Press",
    "wof:placetype":"venue"
},
  "geometry": {"coordinates":[-70.258633,43.659737],"type":"Point"}
}