{
  "type": "Feature",
  "properties": {
    "addr:full":"338 Carl Bailey Rd Bristol ME 04539",
    "addr:housenumber":"338",
    "addr:postcode":"04539",
    "addr:street":"Carl Bailey Rd",
    "iso:country":"US",
    "sg:address":"338 Carl Bailey Rd",
    "sg:city":"Bristol",
    "sg:classifiers":[
        {
            "category":"Professional",
            "subcategory":"Testing Lab",
            "type":"Services"
        }
    ],
    "sg:phone":"+1 207 677 2700",
    "sg:postcode":"04539",
    "sg:province":"ME",
    "sg:tags":[
        "soil"
    ],
    "wof:name":"Ken Cotton Site Evaluator",
    "wof:placetype":"venue"
},
  "geometry": {"coordinates":[-69.52608600000001,43.936334],"type":"Point"}
}