{
  "type": "Feature",
  "properties": {
    "addr:full":"105 Saint James St Portland ME 04102",
    "addr:housenumber":"105",
    "addr:postcode":"04102",
    "addr:street":"Saint James St",
    "iso:country":"US",
    "sg:address":"105 Saint James St",
    "sg:city":"Portland",
    "sg:classifiers":[
        {
            "category":"Wholesale",
            "subcategory":"Electrical",
            "type":"Manufacturing & Wholesale Goods"
        }
    ],
    "sg:phone":"+1 207 774 4444",
    "sg:postcode":"04102",
    "sg:province":"ME",
    "sg:tags":[
        "appliance"
    ],
    "wof:name":"Twin City Supply Co",
    "wof:placetype":"venue"
},
  "geometry": {"coordinates":[-70.28352099999999,43.657097],"type":"Point"}
}