{
  "type": "Feature",
  "properties": {
    "iso:country":"US",
    "sg:address":"9 Market St",
    "sg:city":"South Portland",
    "sg:classifiers":[
        {
            "category":"Banks & Credit Unions",
            "subcategory":"Bank",
            "type":"Services"
        }
    ],
    "sg:phone":"+1 207 767 5573",
    "sg:postcode":"04106",
    "sg:province":"ME",
    "sg:website":"www.peoplesheritagebank.com",
    "wof:name":"Banknorth",
    "wof:placetype":"venue"
},
  "geometry": {"coordinates":[-70.253732,43.635975],"type":"Point"}
}