{
  "type": "Feature",
  "properties": {
    "iso:country":"US",
    "sg:address":"1 Valley Ln",
    "sg:city":"Old Orchard Bch",
    "sg:classifiers":[
        {
            "category":"Building & Trades",
            "subcategory":"Plumbing",
            "type":"Services"
        }
    ],
    "sg:phone":"+1 207 934 2525",
    "sg:postcode":"04064",
    "sg:province":"ME",
    "sg:tags":[
        "septic"
    ],
    "wof:name":"Blow Brothers",
    "wof:placetype":"venue"
},
  "geometry": {"coordinates":[-70.407316,43.519259],"type":"Point"}
}