{
  "type": "Feature",
  "properties": {
    "iso:country":"US",
    "sg:address":"36 Dibiase St",
    "sg:city":"Portland",
    "sg:classifiers":[
        {
            "category":"Building & Trades",
            "subcategory":"Plumbing",
            "type":"Services"
        }
    ],
    "sg:phone":"+1 207 797 2685",
    "sg:postcode":"04103",
    "sg:province":"ME",
    "sg:tags":[
        "contractor"
    ],
    "wof:name":"Peter Maietta Plumbing & Htg",
    "wof:placetype":"venue"
},
  "geometry": {"coordinates":[-70.305058,43.691651],"type":"Point"}
}