{
  "type": "Feature",
  "properties": {
    "addr:full":"50 Shore Rd Ogunquit ME 03907",
    "addr:housenumber":"50",
    "addr:postcode":"03907",
    "addr:street":"Shore Rd",
    "iso:country":"US",
    "sg:address":"50 Shore Rd",
    "sg:city":"Ogunquit",
    "sg:classifiers":[
        {
            "category":"Restaurant",
            "type":"Food & Drink"
        }
    ],
    "sg:phone":"+1 207 646 5001",
    "sg:postcode":"03907",
    "sg:province":"ME",
    "wof:name":"Five-O",
    "wof:placetype":"venue"
},
  "geometry": {"coordinates":[-70.59429900000001,43.2393],"type":"Point"}
}