{
  "type": "Feature",
  "properties": {
    "iso:country":"US",
    "sg:address":"1 Somerset Ave",
    "sg:city":"Pittsfield",
    "sg:classifiers":[
        {
            "category":"Food & Beverages",
            "subcategory":"Groceries & Convenience Stores",
            "type":"Retail Goods"
        }
    ],
    "sg:phone":"+1 207 487 5161",
    "sg:postcode":"04967",
    "sg:province":"ME",
    "sg:tags":[
        "grocer"
    ],
    "wof:name":"Bud's Shop & Save",
    "wof:placetype":"venue"
},
  "geometry": {"coordinates":[-69.388526,44.785135],"type":"Point"}
}