{
  "type": "Feature",
  "properties": {
    "iso:country":"US",
    "sg:address":"736 Lower St",
    "sg:city":"Turner",
    "sg:classifiers":[
        {
            "category":"Building & Trades",
            "subcategory":"Construction",
            "type":"Services"
        }
    ],
    "sg:phone":"+1 207 225 3879",
    "sg:postcode":"04282",
    "sg:province":"ME",
    "sg:tags":[
        "masonry",
        "contractor"
    ],
    "wof:name":"Randall Wells",
    "wof:placetype":"venue"
},
  "geometry": {"coordinates":[-70.22902499999999,44.267293],"type":"Point"}
}