{
  "type": "Feature",
  "properties": {
    "iso:country":"US",
    "sg:address":"372 Fore St",
    "sg:city":"Portland",
    "sg:classifiers":[
        {
            "category":"Museum",
            "type":"Entertainment"
        }
    ],
    "sg:phone":"+1 207 874 8084",
    "sg:postcode":"04101",
    "sg:province":"ME",
    "sg:tags":[
        "gallery"
    ],
    "wof:name":"Fore St Museum",
    "wof:placetype":"venue"
},
  "geometry": {"coordinates":[-70.25285700000001,43.656549],"type":"Point"}
}