{
  "type": "Feature",
  "properties": {
    "addr:full":"765 Five Islands Rd Georgetown ME 04548",
    "addr:housenumber":"765",
    "addr:postcode":"04548",
    "addr:street":"Five Islands Rd",
    "iso:country":"US",
    "sg:address":"765 Five Islands Rd",
    "sg:city":"Georgetown",
    "sg:classifiers":[
        {
            "category":"Government",
            "subcategory":"Post Office",
            "type":"Public Place"
        }
    ],
    "sg:phone":"+1 207 371 2000",
    "sg:postcode":"04548",
    "sg:province":"ME",
    "sg:tags":[
        "postal",
        "us"
    ],
    "wof:name":"US Post Office",
    "wof:placetype":"venue"
},
  "geometry": {"coordinates":[-69.756452,43.806149],"type":"Point"}
}