{
  "type": "Feature",
  "properties": {
    "addr:full":"788 Forest Ave Portland ME 04103",
    "addr:housenumber":"788",
    "addr:postcode":"04103",
    "addr:street":"Forest Ave",
    "iso:country":"US",
    "sg:address":"788 Forest Ave",
    "sg:city":"Portland",
    "sg:classifiers":[
        {
            "category":"Retail",
            "subcategory":"Auto Repair",
            "type":"Services"
        }
    ],
    "sg:phone":"+1 207 780 8863",
    "sg:postcode":"04103",
    "sg:province":"ME",
    "sg:tags":[
        "repairing",
        "automobile"
    ],
    "wof:name":"Precision Tune Auto Care",
    "wof:placetype":"venue"
},
  "geometry": {"coordinates":[-70.28623,43.674386],"type":"Point"}
}