{
  "type": "Feature",
  "properties": {
    "iso:country":"US",
    "sg:address":"7 N Chestnut St",
    "sg:city":"Augusta",
    "sg:classifiers":[
        {
            "category":"Banks & Credit Unions",
            "subcategory":"Investment Brokerage",
            "type":"Services"
        }
    ],
    "sg:phone":"+1 207 622 9009",
    "sg:postcode":"04330",
    "sg:province":"ME",
    "sg:tags":[
        "advisory",
        "financial"
    ],
    "wof:name":"Joel D Davis & Assoc",
    "wof:placetype":"venue"
},
  "geometry": {"coordinates":[-69.782313,44.317736],"type":"Point"}
}