{
  "type": "Feature",
  "properties": {
    "addr:full":"69 Lee Rd Lincoln ME 04457",
    "addr:housenumber":"69",
    "addr:postcode":"04457",
    "addr:street":"Lee Rd",
    "iso:country":"US",
    "sg:address":"69 Lee Rd",
    "sg:city":"Lincoln",
    "sg:classifiers":[
        {
            "category":"Health Services",
            "subcategory":"Doctor",
            "type":"Services"
        }
    ],
    "sg:phone":"+1 207 794 6896",
    "sg:postcode":"04457",
    "sg:province":"ME",
    "sg:tags":[
        "dentist"
    ],
    "wof:name":"H Joseph Thibodeau DDS",
    "wof:placetype":"venue"
},
  "geometry": {"coordinates":[-68.497124,45.369686],"type":"Point"}
}