{
  "type": "Feature",
  "properties": {
    "addr:full":"82 Falmouth Rd Windham ME 04062",
    "addr:housenumber":"82",
    "addr:postcode":"04062",
    "addr:street":"Falmouth Rd",
    "iso:country":"US",
    "sg:address":"82 Falmouth Rd",
    "sg:city":"Windham",
    "sg:classifiers":[
        {
            "category":"Building & Trades",
            "subcategory":"Plumbing",
            "type":"Services"
        }
    ],
    "sg:phone":"+1 207 892 4746",
    "sg:postcode":"04062",
    "sg:province":"ME",
    "sg:tags":[
        "plumbing",
        "contractor"
    ],
    "wof:name":"Le Clair's Plumbing & Heating",
    "wof:placetype":"venue"
},
  "geometry": {"coordinates":[-70.362005,43.795008],"type":"Point"}
}