{
  "type": "Feature",
  "properties": {
    "iso:country":"US",
    "sg:address":"625 Broadway",
    "sg:city":"Bangor",
    "sg:classifiers":[
        {
            "category":"Home & Garden",
            "subcategory":"Building Materials",
            "type":"Retail Goods"
        }
    ],
    "sg:phone":"+1 207 942 8119",
    "sg:postcode":"04401",
    "sg:province":"ME",
    "sg:tags":[
        "paint"
    ],
    "wof:name":"Sherwin-Williams Paints",
    "wof:placetype":"venue"
},
  "geometry": {"coordinates":[-68.77907999999999,44.823282],"type":"Point"}
}