{
  "type": "Feature",
  "properties": {
    "iso:country":"US",
    "sg:address":"19 Ole Ironside Ln",
    "sg:city":"Scarborough",
    "sg:classifiers":[
        {
            "category":"Building & Trades",
            "subcategory":"Construction",
            "type":"Services"
        }
    ],
    "sg:phone":"+1 207 883 0388",
    "sg:postcode":"04074",
    "sg:province":"ME",
    "sg:tags":[
        "painter"
    ],
    "wof:name":"Steve Hilton Painting",
    "wof:placetype":"venue"
},
  "geometry": {"coordinates":[-70.295686,43.586462],"type":"Point"}
}