{
  "type": "Feature",
  "properties": {
    "addr:full":"9 Place Ln Unity ME 04952",
    "addr:housenumber":"9",
    "addr:postcode":"04952",
    "addr:street":"Place Ln",
    "iso:country":"US",
    "sg:address":"9 Place Ln",
    "sg:city":"Unity",
    "sg:classifiers":[
        {
            "category":"Restaurant",
            "type":"Food & Drink"
        }
    ],
    "sg:phone":"+1 207 948 3363",
    "sg:postcode":"04952",
    "sg:province":"ME",
    "wof:name":"China Jade",
    "wof:placetype":"venue"
},
  "geometry": {"coordinates":[-69.205628,44.442643],"type":"Point"}
}