{
  "type": "Feature",
  "properties": {
    "addr:full":"517 Congress St Portland ME 04101",
    "addr:housenumber":"517",
    "addr:postcode":"04101",
    "addr:street":"Congress St",
    "iso:country":"US",
    "sg:address":"517 Congress St",
    "sg:city":"Portland",
    "sg:classifiers":[
        {
            "category":"Retail",
            "subcategory":"Photofinishing",
            "type":"Services"
        }
    ],
    "sg:phone":"+1 207 773 6461",
    "sg:postcode":"04101",
    "sg:province":"ME",
    "sg:tags":[
        "photo",
        "finishing"
    ],
    "wof:name":"Fotoshops",
    "wof:placetype":"venue"
},
  "geometry": {"coordinates":[-70.26076399999999,43.656423],"type":"Point"}
}