{
  "type": "Feature",
  "properties": {
    "iso:country":"US",
    "sg:address":"118 Griffin Rd",
    "sg:city":"Bangor",
    "sg:classifiers":[
        {
            "category":"Retail",
            "subcategory":"Auto Repair",
            "type":"Services"
        }
    ],
    "sg:phone":"+1 207 942 3202",
    "sg:postcode":"04401",
    "sg:province":"ME",
    "sg:tags":[
        "repairing",
        "automobile"
    ],
    "wof:name":"Smith's Fuel Injection",
    "wof:placetype":"venue"
},
  "geometry": {"coordinates":[-68.807025,44.825642],"type":"Point"}
}