{
  "type": "Feature",
  "properties": {
    "addr:full":"560 North St Houlton ME 04730",
    "addr:housenumber":"560",
    "addr:postcode":"04730",
    "addr:street":"North St",
    "iso:country":"US",
    "sg:address":"560 North St",
    "sg:city":"Houlton",
    "sg:classifiers":[
        {
            "category":"Professional",
            "subcategory":"Lawyer & Legal Services",
            "type":"Services"
        }
    ],
    "sg:phone":"+1 207 532 2232",
    "sg:postcode":"04730",
    "sg:province":"ME",
    "sg:tags":[
        "attorney"
    ],
    "wof:name":"Carpenter Law Office",
    "wof:placetype":"venue"
},
  "geometry": {"coordinates":[-67.840687,46.164253],"type":"Point"}
}