{
  "type": "Feature",
  "properties": {
    "addr:full":"9 Little River Rd Lebanon ME 04027",
    "addr:housenumber":"9",
    "addr:postcode":"04027",
    "addr:street":"Little River Rd",
    "iso:country":"US",
    "sg:address":"9 Little River Rd",
    "sg:city":"Lebanon",
    "sg:classifiers":[
        {
            "category":"Government",
            "subcategory":"Office",
            "type":"Public Place"
        }
    ],
    "sg:phone":"+1 207 457 1171",
    "sg:postcode":"04027",
    "sg:province":"ME",
    "sg:tags":[
        "village"
    ],
    "wof:name":"Lebanon Selectmen",
    "wof:placetype":"venue"
},
  "geometry": {"coordinates":[-70.868376,43.412391],"type":"Point"}
}