{
  "type": "Feature",
  "properties": {
    "iso:country":"US",
    "sg:address":"15 Morin St",
    "sg:city":"Biddeford",
    "sg:classifiers":[
        {
            "category":"Freight",
            "type":"Transportation"
        }
    ],
    "sg:phone":"+1 207 284 0344",
    "sg:postcode":"04005",
    "sg:province":"ME",
    "sg:tags":[
        "delivery"
    ],
    "wof:name":"On Time Delivery Svc",
    "wof:placetype":"venue"
},
  "geometry": {"coordinates":[-70.492645,43.46674],"type":"Point"}
}