{
  "type": "Feature",
  "properties": {
    "iso:country":"US",
    "sg:address":"49 E Grand Ave",
    "sg:city":"Old Orchard Bch",
    "sg:classifiers":[
        {
            "category":"Organizations",
            "subcategory":"Religious Organization",
            "type":"Services"
        }
    ],
    "sg:phone":"+1 207 934 2973",
    "sg:postcode":"04064",
    "sg:province":"ME",
    "sg:tags":[
        "synagogue"
    ],
    "wof:name":"Congregation Beth Israel",
    "wof:placetype":"venue"
},
  "geometry": {"coordinates":[-70.37093900000001,43.519895],"type":"Point"}
}