{
  "type": "Feature",
  "properties": {
    "addr:full":"150 Pepperrell Rd Kittery Point ME 03905",
    "addr:housenumber":"150",
    "addr:postcode":"03905",
    "addr:street":"Pepperrell Rd",
    "iso:country":"US",
    "sg:address":"150 Pepperrell Rd",
    "sg:city":"Kittery Point",
    "sg:classifiers":[
        {
            "category":"Autos & Motor Vehicles",
            "subcategory":"Fuel & Gas Station",
            "type":"Retail Goods"
        }
    ],
    "sg:phone":"+1 207 439 9898",
    "sg:postcode":"03905",
    "sg:province":"ME",
    "sg:tags":[
        "oil"
    ],
    "wof:name":"Kittery Point Citgo",
    "wof:placetype":"venue"
},
  "geometry": {"coordinates":[-70.69962099999999,43.083649],"type":"Point"}
}