{
  "type": "Feature",
  "properties": {
    "iso:country":"US",
    "sg:address":"452 Square Rd",
    "sg:city":"St Albans",
    "sg:classifiers":[
        {
            "category":"Education",
            "subcategory":"School",
            "type":"Public Place"
        }
    ],
    "sg:phone":"+1 207 938 2046",
    "sg:postcode":"04971",
    "sg:province":"ME",
    "sg:tags":[
        "academic",
        "special"
    ],
    "wof:name":"Square Road Group Home",
    "wof:placetype":"venue"
},
  "geometry": {"coordinates":[-69.32643299999999,44.909271],"type":"Point"}
}