{
  "type": "Feature",
  "properties": {
    "iso:country":"US",
    "sg:address":"6 Brookview Ave",
    "sg:city":"Fort Fairfield",
    "sg:classifiers":[
        {
            "category":"Insurance",
            "subcategory":"Hazard Insurance",
            "type":"Services"
        }
    ],
    "sg:phone":"+1 207 473 7052",
    "sg:postcode":"04742",
    "sg:province":"ME",
    "sg:tags":[
        "carrier"
    ],
    "wof:name":"Maine Employers Mutl Insur Co",
    "wof:placetype":"venue"
},
  "geometry": {"coordinates":[-67.83186600000001,46.768793],"type":"Point"}
}