{
  "type": "Feature",
  "properties": {
    "addr:full":"87 Carroll St Portland ME 04102",
    "addr:housenumber":"87",
    "addr:postcode":"04102",
    "addr:street":"Carroll St",
    "iso:country":"US",
    "sg:address":"87 Carroll St",
    "sg:city":"Portland",
    "sg:classifiers":[
        {
            "category":"Professional",
            "subcategory":"Business Services",
            "type":"Services"
        }
    ],
    "sg:phone":"+1 207 772 5011",
    "sg:postcode":"04102",
    "sg:province":"ME",
    "sg:tags":[
        "auctioneer"
    ],
    "sg:website":"www.barridoff.com",
    "wof:name":"Barridoff Galleries",
    "wof:placetype":"venue"
},
  "geometry": {"coordinates":[-70.274855,43.64837],"type":"Point"}
}