{
  "type": "Feature",
  "properties": {
    "addr:full":"14 Williams St Boothbay Harbor ME 04538",
    "addr:housenumber":"14",
    "addr:postcode":"04538",
    "addr:street":"Williams St",
    "iso:country":"US",
    "sg:address":"14 Williams St",
    "sg:city":"Boothbay Harbor",
    "sg:classifiers":[
        {
            "category":"Building & Trades",
            "subcategory":"Construction",
            "type":"Services"
        }
    ],
    "sg:phone":"+1 207 633 6445",
    "sg:postcode":"04538",
    "sg:province":"ME",
    "sg:tags":[
        "heavy",
        "cargo",
        "handler",
        "marine"
    ],
    "wof:name":"Boothbay Mariner Inc",
    "wof:placetype":"venue"
},
  "geometry": {"coordinates":[-69.63809500000001,43.853873],"type":"Point"}
}