{
  "type": "Feature",
  "properties": {
    "iso:country":"US",
    "sg:address":"125 John Roberts Rd",
    "sg:city":"South Portland",
    "sg:classifiers":[
        {
            "category":"Professional",
            "subcategory":"Testing Lab",
            "type":"Services"
        }
    ],
    "sg:phone":"+1 207 772 3333",
    "sg:postcode":"04106",
    "sg:province":"ME",
    "sg:tags":[
        "measuring",
        "air",
        "pollution"
    ],
    "wof:name":"TRC Environmental Corp",
    "wof:placetype":"venue"
},
  "geometry": {"coordinates":[-70.329374,43.629944],"type":"Point"}
}