{
  "type": "Feature",
  "properties": {
    "addr:full":"701 Forest Ave Portland ME 04103",
    "addr:housenumber":"701",
    "addr:postcode":"04103",
    "addr:street":"Forest Ave",
    "iso:country":"US",
    "sg:address":"701 Forest Ave",
    "sg:city":"Portland",
    "sg:classifiers":[
        {
            "category":"Shopping",
            "subcategory":"Pharmacy",
            "type":"Retail Goods"
        }
    ],
    "sg:phone":"+1 207 780 8144",
    "sg:postcode":"04103",
    "sg:province":"ME",
    "wof:name":"Rite Aid Pharmacy",
    "wof:placetype":"venue"
},
  "geometry": {"coordinates":[-70.28513,43.672672],"type":"Point"}
}