{
  "type": "Feature",
  "properties": {
    "addr:full":"162 School St Unity ME 04988",
    "addr:housenumber":"162",
    "addr:postcode":"04988",
    "addr:street":"School St",
    "iso:country":"US",
    "sg:address":"162 School St",
    "sg:city":"Unity",
    "sg:classifiers":[
        {
            "category":"Food & Beverages",
            "subcategory":"Groceries & Convenience Stores",
            "type":"Retail Goods"
        }
    ],
    "sg:phone":"+1 207 948 2731",
    "sg:postcode":"04988",
    "sg:province":"ME",
    "sg:tags":[
        "grocer"
    ],
    "wof:name":"Mc Cormicks Thriftyway Store",
    "wof:placetype":"venue"
},
  "geometry": {"coordinates":[-69.354619,44.613195],"type":"Point"}
}