{
  "type": "Feature",
  "properties": {
    "iso:country":"US",
    "sg:address":"980 Pinkham Brook Rd",
    "sg:city":"Durham",
    "sg:classifiers":[
        {
            "category":"Building & Trades",
            "subcategory":"Landscaping Services",
            "type":"Services"
        }
    ],
    "sg:phone":"+1 207 353 4783",
    "sg:postcode":"04222",
    "sg:province":"ME",
    "wof:name":"Balfour Landscape",
    "wof:placetype":"venue"
},
  "geometry": {"coordinates":[-70.074332,43.941638],"type":"Point"}
}