{
  "type": "Feature",
  "properties": {
    "iso:country":"US",
    "sg:address":"19 Pine Hill Dr",
    "sg:city":"Bangor",
    "sg:classifiers":[
        {
            "category":"Building & Trades",
            "subcategory":"Landscaping Services",
            "type":"Services"
        }
    ],
    "sg:phone":"+1 207 947 2378",
    "sg:postcode":"04401",
    "sg:province":"ME",
    "sg:tags":[
        "landscape",
        "contractor"
    ],
    "wof:name":"Best Care Landscaping & Design",
    "wof:placetype":"venue"
},
  "geometry": {"coordinates":[-68.813914,44.904131],"type":"Point"}
}