{
  "type": "Feature",
  "properties": {
    "addr:full":"33 Birch Ln Island Falls ME 04730",
    "addr:housenumber":"33",
    "addr:postcode":"04730",
    "addr:street":"Birch Ln",
    "iso:country":"US",
    "sg:address":"33 Birch Ln",
    "sg:city":"Island Falls",
    "sg:classifiers":[
        {
            "category":"Travel",
            "subcategory":"Campground",
            "type":"Entertainment"
        }
    ],
    "sg:phone":"+1 207 463 2515",
    "sg:postcode":"04730",
    "sg:province":"ME",
    "wof:name":"Birch Point Lodge Campgrounds",
    "wof:placetype":"venue"
},
  "geometry": {"coordinates":[-67.921927,46.102799],"type":"Point"}
}