{
  "type": "Feature",
  "properties": {
    "iso:country":"US",
    "sg:address":"994 Crockett Ridge Rd",
    "sg:city":"Norway",
    "sg:classifiers":[
        {
            "category":"Building & Trades",
            "subcategory":"Construction",
            "type":"Services"
        }
    ],
    "sg:phone":"+1 207 743 2114",
    "sg:postcode":"04268",
    "sg:province":"ME",
    "sg:tags":[
        "hanging",
        "contractor"
    ],
    "wof:name":"Dan Noble Contracting Inc",
    "wof:placetype":"venue"
},
  "geometry": {"coordinates":[-70.574382,44.264948],"type":"Point"}
}