{
  "type": "Feature",
  "properties": {
    "iso:country":"US",
    "sg:address":"16 Vannah Ave",
    "sg:city":"Portland",
    "sg:classifiers":[
        {
            "category":"Social Services",
            "subcategory":"Child Care",
            "type":"Services"
        }
    ],
    "sg:phone":"+1 207 774 7322",
    "sg:postcode":"04103",
    "sg:province":"ME",
    "wof:name":"Childrens Enrichment Ctr",
    "wof:placetype":"venue"
},
  "geometry": {"coordinates":[-70.283835,43.671859],"type":"Point"}
}