{
  "type": "Feature",
  "properties": {
    "addr:full":"158 Capisic St Portland ME 04102",
    "addr:housenumber":"158",
    "addr:postcode":"04102",
    "addr:street":"Capisic St",
    "iso:country":"US",
    "sg:address":"158 Capisic St",
    "sg:city":"Portland",
    "sg:classifiers":[
        {
            "category":"Recreation",
            "type":"Entertainment"
        }
    ],
    "sg:phone":"+1 207 761 0975",
    "sg:postcode":"04102",
    "sg:province":"ME",
    "sg:tags":[
        "boxing",
        "instruction"
    ],
    "wof:name":"Portland Boxing Club",
    "wof:placetype":"venue"
},
  "geometry": {"coordinates":[-70.30458900000001,43.663219],"type":"Point"}
}