{
  "type": "Feature",
  "properties": {
    "iso:country":"US",
    "sg:address":"127 E Main St",
    "sg:city":"Searsport",
    "sg:classifiers":[
        {
            "category":"Travel",
            "subcategory":"Hotels & Motels",
            "type":"Entertainment"
        }
    ],
    "sg:phone":"+1 207 548 0055",
    "sg:postcode":"04974",
    "sg:province":"ME",
    "wof:name":"Captain AV Nickels Inn",
    "wof:placetype":"venue"
},
  "geometry": {"coordinates":[-68.911333,44.460114],"type":"Point"}
}