{
  "type": "Feature",
  "properties": {
    "iso:country":"US",
    "sg:address":"38 Sterling St",
    "sg:city":"Waterville",
    "sg:classifiers":[
        {
            "category":"Social Services",
            "subcategory":"Child Care",
            "type":"Services"
        }
    ],
    "sg:phone":"+1 207 877 7769",
    "sg:postcode":"04901",
    "sg:province":"ME",
    "sg:tags":[
        "day"
    ],
    "wof:name":"Dufours Terri Day Care",
    "wof:placetype":"venue"
},
  "geometry": {"coordinates":[-69.655485,44.540289],"type":"Point"}
}