{
  "type": "Feature",
  "properties": {
    "addr:full":"19 Summer St Brunswick ME 04011",
    "addr:housenumber":"19",
    "addr:postcode":"04011",
    "addr:street":"Summer St",
    "iso:country":"US",
    "sg:address":"19 Summer St",
    "sg:city":"Brunswick",
    "sg:phone":"+1 207 729 3337",
    "sg:postcode":"04011",
    "sg:province":"ME",
    "sg:tags":[
        "oil"
    ],
    "wof:name":"Thibeault Energy",
    "wof:placetype":"venue"
},
  "geometry": {"coordinates":[-69.977465,43.911096],"type":"Point"}
}