{
  "type": "Feature",
  "properties": {
    "addr:full":"1 Bangor St Houlton ME 04730",
    "addr:housenumber":"1",
    "addr:postcode":"04730",
    "addr:street":"Bangor St",
    "iso:country":"US",
    "sg:address":"1 Bangor St",
    "sg:city":"Houlton",
    "sg:classifiers":[
        {
            "category":"Home & Garden",
            "subcategory":"Home Furnishings",
            "type":"Retail Goods"
        }
    ],
    "sg:phone":"+1 207 532 2302",
    "sg:postcode":"04730",
    "sg:province":"ME",
    "sg:tags":[
        "lighting",
        "fixture"
    ],
    "sg:website":"www.morethanlights.com",
    "wof:name":"Light House",
    "wof:placetype":"venue"
},
  "geometry": {"coordinates":[-67.84169799999999,46.125287],"type":"Point"}
}