{
  "type": "Feature",
  "properties": {
    "addr:full":"2 Leighton St Waterville ME 04901",
    "addr:housenumber":"2",
    "addr:postcode":"04901",
    "addr:street":"Leighton St",
    "iso:country":"US",
    "sg:address":"2 Leighton St",
    "sg:city":"Waterville",
    "sg:classifiers":[
        {
            "category":"Building & Trades",
            "subcategory":"Landscaping Services",
            "type":"Services"
        }
    ],
    "sg:phone":"+1 207 859 8989",
    "sg:postcode":"04901",
    "sg:province":"ME",
    "sg:tags":[
        "landscape",
        "contractor"
    ],
    "wof:name":"Karter's Landscaping",
    "wof:placetype":"venue"
},
  "geometry": {"coordinates":[-69.629594,44.55231],"type":"Point"}
}