{
  "type": "Feature",
  "properties": {
    "iso:country":"US",
    "sg:address":"8 Arbor Woods Rd",
    "sg:city":"Raymond",
    "sg:classifiers":[
        {
            "category":"Manufacturing",
            "subcategory":"Electronics",
            "type":"Manufacturing & Wholesale Goods"
        }
    ],
    "sg:phone":"+1 207 655 4870",
    "sg:postcode":"04071",
    "sg:province":"ME",
    "sg:tags":[
        "filtration"
    ],
    "wof:name":"Midwesco Inc",
    "wof:placetype":"venue"
},
  "geometry": {"coordinates":[-70.496255,43.898158],"type":"Point"}
}