{
  "type": "Feature",
  "properties": {
    "addr:full":"1685 Congress St Portland ME 04102",
    "addr:housenumber":"1685",
    "addr:postcode":"04102",
    "addr:street":"Congress St",
    "iso:country":"US",
    "sg:address":"1685 Congress St",
    "sg:city":"Portland",
    "sg:classifiers":[
        {
            "category":"Professional",
            "type":"Services"
        }
    ],
    "sg:phone":"+1 207 775 7774",
    "sg:postcode":"04102",
    "sg:province":"ME",
    "sg:tags":[
        "establishment"
    ],
    "wof:name":"AARP",
    "wof:placetype":"venue"
},
  "geometry": {"coordinates":[-70.30852899999999,43.659807],"type":"Point"}
}