{
  "type": "Feature",
  "properties": {
    "addr:full":"966 Access Hwy Caribou ME 04736",
    "addr:housenumber":"966",
    "addr:postcode":"04736",
    "addr:street":"Access Hwy",
    "iso:country":"US",
    "sg:address":"966 Access Hwy",
    "sg:city":"Caribou",
    "sg:classifiers":[
        {
            "category":"Retail",
            "subcategory":"Repair Shop",
            "type":"Services"
        }
    ],
    "sg:phone":"+1 207 498 2770",
    "sg:postcode":"04736",
    "sg:province":"ME",
    "sg:tags":[
        "equipment"
    ],
    "wof:name":"Petersons Septic Services",
    "wof:placetype":"venue"
},
  "geometry": {"coordinates":[-67.94677799999999,46.895614],"type":"Point"}
}