{
  "type": "Feature",
  "properties": {
    "iso:country":"US",
    "sg:address":"72 Bear Hill Rd",
    "sg:city":"Dover Foxcroft",
    "sg:classifiers":[
        {
            "category":"Building & Trades",
            "subcategory":"Plumbing",
            "type":"Services"
        }
    ],
    "sg:phone":"+1 207 564 2705",
    "sg:postcode":"04426",
    "sg:province":"ME",
    "sg:tags":[
        "contractor"
    ],
    "wof:name":"Advantage Plumbing & Heating",
    "wof:placetype":"venue"
},
  "geometry": {"coordinates":[-69.206414,45.160334],"type":"Point"}
}