{
  "type": "Feature",
  "properties": {
    "addr:full":"20 Smith St Portland ME 04101",
    "addr:housenumber":"20",
    "addr:postcode":"04101",
    "addr:street":"Smith St",
    "iso:country":"US",
    "sg:address":"20 Smith St",
    "sg:city":"Portland",
    "sg:classifiers":[
        {
            "category":"Building & Trades",
            "subcategory":"Construction",
            "type":"Services"
        }
    ],
    "sg:phone":"+1 207 774 2951",
    "sg:postcode":"04101",
    "sg:province":"ME",
    "sg:tags":[
        "handyman"
    ],
    "wof:name":"Back Bay Construction",
    "wof:placetype":"venue"
},
  "geometry": {"coordinates":[-70.25271100000001,43.66266],"type":"Point"}
}