{
  "type": "Feature",
  "properties": {
    "addr:full":"1103 Main St Lewiston ME 04240",
    "addr:housenumber":"1103",
    "addr:postcode":"04240",
    "addr:street":"Main St",
    "iso:country":"US",
    "sg:address":"1103 Main St",
    "sg:city":"Lewiston",
    "sg:classifiers":[
        {
            "category":"Autos & Motor Vehicles",
            "subcategory":"Automobile Sales",
            "type":"Retail Goods"
        }
    ],
    "sg:phone":"+1 207 786 3039",
    "sg:postcode":"04240",
    "sg:province":"ME",
    "sg:tags":[
        "car",
        "dealer"
    ],
    "wof:name":"Empire Auto Sales",
    "wof:placetype":"venue"
},
  "geometry": {"coordinates":[-70.19259099999999,44.14064],"type":"Point"}
}