{
  "type": "Feature",
  "properties": {
    "iso:country":"US",
    "sg:address":"13 Sesame St",
    "sg:city":"Skowhegan",
    "sg:classifiers":[
        {
            "category":"Retail",
            "subcategory":"Auto Repair",
            "type":"Services"
        }
    ],
    "sg:phone":"+1 207 474 2233",
    "sg:postcode":"04976",
    "sg:province":"ME",
    "sg:tags":[
        "repairing",
        "automobile"
    ],
    "wof:name":"Reid Car & Truck Inc",
    "wof:placetype":"venue"
},
  "geometry": {"coordinates":[-69.72224,44.754277],"type":"Point"}
}