{
  "type": "Feature",
  "properties": {
    "iso:country":"US",
    "sg:address":"85 India St",
    "sg:city":"Portland",
    "sg:classifiers":[
        {
            "category":"Professional",
            "subcategory":"Lawyer & Legal Services",
            "type":"Services"
        }
    ],
    "sg:phone":"+1 207 872 6467",
    "sg:postcode":"04101",
    "sg:province":"ME",
    "sg:tags":[
        "attorney"
    ],
    "sg:website":"www.employment-law.org",
    "wof:name":"Jackson & Mac Nichol",
    "wof:placetype":"venue"
},
  "geometry": {"coordinates":[-70.250878,43.660941],"type":"Point"}
}