{
  "type": "Feature",
  "properties": {
    "addr:full":"86 Lincolnville Ave Belfast ME 04915",
    "addr:housenumber":"86",
    "addr:postcode":"04915",
    "addr:street":"Lincolnville Ave",
    "iso:country":"US",
    "sg:address":"86 Lincolnville Ave",
    "sg:city":"Belfast",
    "sg:classifiers":[
        {
            "category":"Health Services",
            "subcategory":"Doctor",
            "type":"Services"
        }
    ],
    "sg:phone":"+1 207 338 0540",
    "sg:postcode":"04915",
    "sg:province":"ME",
    "sg:tags":[
        "dentist"
    ],
    "wof:name":"Edward R Zanca DDS",
    "wof:placetype":"venue"
},
  "geometry": {"coordinates":[-69.01660099999999,44.420467],"type":"Point"}
}