{
  "type": "Feature",
  "properties": {
    "iso:country":"US",
    "sg:address":"40 Union St",
    "sg:city":"Blue Hill",
    "sg:classifiers":[
        {
            "category":"Restaurant",
            "type":"Food & Drink"
        }
    ],
    "sg:phone":"+1 207 374 9922",
    "sg:postcode":"04605",
    "sg:province":"ME",
    "sg:tags":[
        "caterer"
    ],
    "wof:name":"Bianco's Catering",
    "wof:placetype":"venue"
},
  "geometry": {"coordinates":[-68.414811,44.548068],"type":"Point"}
}