{
  "type": "Feature",
  "properties": {
    "iso:country":"US",
    "sg:address":"68 Fort Hill St",
    "sg:city":"Fort Fairfield",
    "sg:classifiers":[
        {
            "category":"Professional",
            "type":"Services"
        }
    ],
    "sg:phone":"+1 207 473 7171",
    "sg:postcode":"04742",
    "sg:province":"ME",
    "sg:tags":[
        "establishment"
    ],
    "wof:name":"Langley & Langley",
    "wof:placetype":"venue"
},
  "geometry": {"coordinates":[-67.82406,46.767864],"type":"Point"}
}