{
  "type": "Feature",
  "properties": {
    "iso:country":"US",
    "sg:address":"4 Ridgewood Cir",
    "sg:city":"Kennebunk",
    "sg:classifiers":[
        {
            "category":"Professional",
            "subcategory":"Business Services",
            "type":"Services"
        }
    ],
    "sg:phone":"+1 207 985 2807",
    "sg:postcode":"04043",
    "sg:province":"ME",
    "sg:tags":[
        "telemarketing"
    ],
    "wof:name":"Blu-Jack",
    "wof:placetype":"venue"
},
  "geometry": {"coordinates":[-70.52341699999999,43.370379],"type":"Point"}
}