{
  "type": "Feature",
  "properties": {
    "iso:country":"US",
    "sg:address":"351 Main St",
    "sg:city":"Wilton",
    "sg:classifiers":[
        {
            "category":"Shopping",
            "subcategory":"Clothing, Apparel, & Fashions",
            "type":"Retail Goods"
        }
    ],
    "sg:phone":"+1 207 645 4123",
    "sg:postcode":"04294",
    "sg:province":"ME",
    "sg:tags":[
        "t"
    ],
    "wof:name":"Shirt Tales",
    "wof:placetype":"venue"
},
  "geometry": {"coordinates":[-70.22958800000001,44.589711],"type":"Point"}
}