{
  "type": "Feature",
  "properties": {
    "addr:full":"65 Sherman St Portland ME 04101",
    "addr:housenumber":"65",
    "addr:postcode":"04101",
    "addr:street":"Sherman St",
    "iso:country":"US",
    "sg:address":"65 Sherman St",
    "sg:city":"Portland",
    "sg:classifiers":[
        {
            "category":"Real Estate",
            "subcategory":"Real Estate Agent",
            "type":"Services"
        }
    ],
    "sg:phone":"+1 207 541 3604",
    "sg:postcode":"04101",
    "sg:province":"ME",
    "wof:name":"HCR Properties",
    "wof:placetype":"venue"
},
  "geometry": {"coordinates":[-70.26901700000001,43.655812],"type":"Point"}
}