{
  "type": "Feature",
  "properties": {
    "iso:country":"US",
    "sg:address":"99 Elm St",
    "sg:city":"Camden",
    "sg:classifiers":[
        {
            "category":"Retail",
            "subcategory":"Auto Repair",
            "type":"Services"
        }
    ],
    "sg:phone":"+1 207 230 0011",
    "sg:postcode":"04843",
    "sg:province":"ME",
    "sg:tags":[
        "repairing",
        "automobile"
    ],
    "wof:name":"Discount Tire & Alignment",
    "wof:placetype":"venue"
},
  "geometry": {"coordinates":[-69.072915,44.203776],"type":"Point"}
}