{
  "type": "Feature",
  "properties": {
    "iso:country":"US",
    "sg:address":"56 Western Ave",
    "sg:city":"Augusta",
    "sg:classifiers":[
        {
            "category":"Government",
            "subcategory":"Office",
            "type":"Public Place"
        }
    ],
    "sg:phone":"+1 207 622 4910",
    "sg:postcode":"04330",
    "sg:province":"ME",
    "sg:tags":[
        "armed",
        "force",
        "recruiting"
    ],
    "wof:name":"US Army Recruiting",
    "wof:placetype":"venue"
},
  "geometry": {"coordinates":[-69.786467,44.311652],"type":"Point"}
}