{
  "type": "Feature",
  "properties": {
    "addr:full":"131 Washington Ave Portland ME 04101",
    "addr:housenumber":"131",
    "addr:postcode":"04101",
    "addr:street":"Washington Ave",
    "iso:country":"US",
    "sg:address":"131 Washington Ave",
    "sg:city":"Portland",
    "sg:classifiers":[
        {
            "category":"Manufacturing",
            "subcategory":"Printing",
            "type":"Manufacturing & Wholesale Goods"
        }
    ],
    "sg:phone":"+1 207 879 7940",
    "sg:postcode":"04101",
    "sg:province":"ME",
    "sg:tags":[
        "screen"
    ],
    "wof:name":"Bowers Ink",
    "wof:placetype":"venue"
},
  "geometry": {"coordinates":[-70.252813,43.666732],"type":"Point"}
}