{
  "type": "Feature",
  "properties": {
    "iso:country":"US",
    "sg:address":"51 Nequasset Rd",
    "sg:city":"Woolwich",
    "sg:classifiers":[
        {
            "category":"Building & Trades",
            "subcategory":"Electrical",
            "type":"Services"
        }
    ],
    "sg:phone":"+1 207 443 5805",
    "sg:postcode":"04579",
    "sg:province":"ME",
    "sg:tags":[
        "electric",
        "contractor"
    ],
    "wof:name":"D J Electric",
    "wof:placetype":"venue"
},
  "geometry": {"coordinates":[-69.780072,43.937486],"type":"Point"}
}