{
  "type": "Feature",
  "properties": {
    "addr:full":"3 Downing Pl Presque Isle ME 04769",
    "addr:housenumber":"3",
    "addr:postcode":"04769",
    "addr:street":"Downing Pl",
    "iso:country":"US",
    "sg:address":"3 Downing Pl",
    "sg:city":"Presque Isle",
    "sg:classifiers":[
        {
            "category":"Wholesale",
            "subcategory":"Machinery & Supplies",
            "type":"Manufacturing & Wholesale Goods"
        }
    ],
    "sg:phone":"+1 207 764 0595",
    "sg:postcode":"04769",
    "sg:province":"ME",
    "sg:tags":[
        "truck"
    ],
    "wof:name":"Thomas Manufacturing",
    "wof:placetype":"venue"
},
  "geometry": {"coordinates":[-68.01638699999999,46.690273],"type":"Point"}
}