{
  "type": "Feature",
  "properties": {
    "iso:country":"US",
    "sg:address":"174 W Minot Rd",
    "sg:city":"Minot",
    "sg:classifiers":[
        {
            "category":"Building & Trades",
            "subcategory":"Construction",
            "type":"Services"
        }
    ],
    "sg:phone":"+1 207 346 3002",
    "sg:postcode":"04258",
    "sg:province":"ME",
    "sg:tags":[
        "resurfacing",
        "laying",
        "refinishing",
        "floor"
    ],
    "wof:name":"Floortek",
    "wof:placetype":"venue"
},
  "geometry": {"coordinates":[-70.385651,44.127352],"type":"Point"}
}