{
  "type": "Feature",
  "properties": {
    "iso:country":"US",
    "sg:address":"10 Washington St",
    "sg:city":"Auburn",
    "sg:classifiers":[
        {
            "category":"Freight",
            "type":"Transportation"
        }
    ],
    "sg:phone":"+1 207 782 2917",
    "sg:postcode":"04210",
    "sg:province":"ME",
    "wof:name":"Liley Transportation Gates",
    "wof:placetype":"venue"
},
  "geometry": {"coordinates":[-70.23107,44.089514],"type":"Point"}
}