{
  "type": "Feature",
  "properties": {
    "iso:country":"US",
    "sg:address":"29 Ocean Ave",
    "sg:city":"Portland",
    "sg:classifiers":[
        {
            "category":"Shopping",
            "subcategory":"Used Merchandise",
            "type":"Retail Goods"
        }
    ],
    "sg:phone":"+1 207 842 2929",
    "sg:postcode":"04103",
    "sg:province":"ME",
    "sg:tags":[
        "shop",
        "consignment"
    ],
    "wof:name":"29 Ocean",
    "wof:placetype":"venue"
},
  "geometry": {"coordinates":[-70.28436499999999,43.672467],"type":"Point"}
}