{
  "type": "Feature",
  "properties": {
    "iso:country":"US",
    "sg:address":"142 Presumpscot St",
    "sg:city":"Portland",
    "sg:classifiers":[
        {
            "category":"Wholesale",
            "subcategory":"Home Furnishings",
            "type":"Manufacturing & Wholesale Goods"
        }
    ],
    "sg:phone":"+1 207 775 1100",
    "sg:postcode":"04103",
    "sg:province":"ME",
    "sg:tags":[
        "mat",
        "matting"
    ],
    "sg:website":"www.coastalequipment.com",
    "wof:name":"Coastal Equipment Corp",
    "wof:placetype":"venue"
},
  "geometry": {"coordinates":[-70.260033,43.686478],"type":"Point"}
}