{
  "type": "Feature",
  "properties": {
    "iso:country":"US",
    "sg:address":"2 Old Orchard St",
    "sg:city":"Old Orchard Bch",
    "sg:classifiers":[
        {
            "category":"Restaurant",
            "type":"Food & Drink"
        }
    ],
    "sg:phone":"+1 207 934 7642",
    "sg:postcode":"04064",
    "sg:province":"ME",
    "sg:tags":[
        "out"
    ],
    "wof:name":"Krazy Klam",
    "wof:placetype":"venue"
},
  "geometry": {"coordinates":[-70.37743399999999,43.517434],"type":"Point"}
}