{
  "type": "Feature",
  "properties": {
    "iso:country":"US",
    "sg:address":"511 S Main St",
    "sg:city":"Brewer",
    "sg:classifiers":[
        {
            "category":"Shopping",
            "subcategory":"Optical Goods",
            "type":"Retail Goods"
        }
    ],
    "sg:phone":"+1 207 989 0406",
    "sg:postcode":"04412",
    "sg:province":"ME",
    "sg:tags":[
        "optician"
    ],
    "wof:name":"Brewer Optical",
    "wof:placetype":"venue"
},
  "geometry": {"coordinates":[-68.780179,44.772705],"type":"Point"}
}