{
  "type": "Feature",
  "properties": {
    "iso:country":"US",
    "sg:address":"244 Main St",
    "sg:city":"Saco",
    "sg:classifiers":[
        {
            "category":"Shopping",
            "subcategory":"Pharmacy",
            "type":"Retail Goods"
        }
    ],
    "sg:phone":"+1 207 283 0709",
    "sg:postcode":"04072",
    "sg:province":"ME",
    "sg:website":"www.communityrx.com",
    "wof:name":"Community Pharmacy Of Saco",
    "wof:placetype":"venue"
},
  "geometry": {"coordinates":[-70.440103,43.503842],"type":"Point"}
}