{
  "type": "Feature",
  "properties": {
    "iso:country":"US",
    "sg:address":"142 Farm Rd",
    "sg:city":"Bangor",
    "sg:classifiers":[
        {
            "category":"Wholesale",
            "subcategory":"Scrap",
            "type":"Manufacturing & Wholesale Goods"
        }
    ],
    "sg:phone":"+1 207 942 6772",
    "sg:postcode":"04401",
    "sg:province":"ME",
    "sg:tags":[
        "recycling",
        "center"
    ],
    "wof:name":"Maine Resource Recovery Assoc",
    "wof:placetype":"venue"
},
  "geometry": {"coordinates":[-68.784088,44.785698],"type":"Point"}
}