{
  "type": "Feature",
  "properties": {
    "addr:full":"163 Pleasant St Brunswick ME 04011",
    "addr:housenumber":"163",
    "addr:postcode":"04011",
    "addr:street":"Pleasant St",
    "iso:country":"US",
    "sg:address":"163 Pleasant St",
    "sg:city":"Brunswick",
    "sg:classifiers":[
        {
            "category":"Bakery",
            "type":"Food & Drink"
        },
        {
            "category":"Coffee & Tea",
            "type":"Food & Drink"
        },
        {
            "category":"Bagels",
            "type":"Food & Drink"
        },
        {
            "category":"Donuts",
            "type":"Food & Drink"
        }
    ],
    "sg:menulink":"http://www.allmenus.com/me/brunswick/149040-dunkin-donuts/menu/",
    "sg:phone":"+1 207 725 5602",
    "sg:postcode":"04011",
    "sg:province":"ME",
    "sg:tags":[
        "wrap",
        "american",
        "sandwich",
        "pastry"
    ],
    "wof:name":"Dunkin' Donuts",
    "wof:placetype":"venue"
},
  "geometry": {"coordinates":[-69.987988,43.9123],"type":"Point"}
}