{
  "type": "Feature",
  "properties": {
    "iso:country":"US",
    "sg:address":"449 Forest Ave",
    "sg:city":"Portland",
    "sg:classifiers":[
        {
            "category":"Banks & Credit Unions",
            "subcategory":"Bank",
            "type":"Services"
        }
    ],
    "sg:phone":"+1 207 774 1733",
    "sg:postcode":"04101",
    "sg:province":"ME",
    "sg:website":"www.peoplesheritage.com",
    "wof:name":"Banknorth",
    "wof:placetype":"venue"
},
  "geometry": {"coordinates":[-70.27672699999999,43.666053],"type":"Point"}
}