{
  "type": "Feature",
  "properties": {
    "addr:full":"42 Spring St Dexter ME 04930",
    "addr:housenumber":"42",
    "addr:postcode":"04930",
    "addr:street":"Spring St",
    "iso:country":"US",
    "sg:address":"42 Spring St",
    "sg:city":"Dexter",
    "sg:classifiers":[
        {
            "category":"Autos & Motor Vehicles",
            "subcategory":"Automobile Sales",
            "type":"Retail Goods"
        }
    ],
    "sg:phone":"+1 207 924 7171",
    "sg:postcode":"04930",
    "sg:province":"ME",
    "sg:tags":[
        "car",
        "dealer"
    ],
    "wof:name":"Bailey Motors Inc",
    "wof:placetype":"venue"
},
  "geometry": {"coordinates":[-69.290255,45.020663],"type":"Point"}
}