{
  "type": "Feature",
  "properties": {
    "iso:country":"US",
    "sg:address":"41 Union Wharf",
    "sg:city":"Portland",
    "sg:classifiers":[
        {
            "category":"Food & Beverages",
            "subcategory":"Meat & Fish",
            "type":"Retail Goods"
        }
    ],
    "sg:phone":"+1 207 775 2917",
    "sg:postcode":"04101",
    "sg:province":"ME",
    "sg:tags":[
        "lobster"
    ],
    "wof:name":"CBS Lobster Inc",
    "wof:placetype":"venue"
},
  "geometry": {"coordinates":[-70.253441,43.654143],"type":"Point"}
}