{
  "type": "Feature",
  "properties": {
    "addr:full":"918 Walkers Mill Rd Bethel ME 04217",
    "addr:housenumber":"918",
    "addr:postcode":"04217",
    "addr:street":"Walkers Mill Rd",
    "iso:country":"US",
    "sg:address":"918 Walkers Mill Rd",
    "sg:city":"Bethel",
    "sg:classifiers":[
        {
            "category":"Real Estate",
            "subcategory":"Real Estate Agent",
            "type":"Services"
        }
    ],
    "sg:phone":"+1 207 875 2414",
    "sg:postcode":"04217",
    "sg:province":"ME",
    "sg:website":"www.fourseasonsrealtyme.com",
    "wof:name":"Four Seasons Realty",
    "wof:placetype":"venue"
},
  "geometry": {"coordinates":[-70.73165899999999,44.41242],"type":"Point"}
}