{
  "type": "Feature",
  "properties": {
    "addr:full":"141 Main St South Portland ME 04106",
    "addr:housenumber":"141",
    "addr:postcode":"04106",
    "addr:street":"Main St",
    "iso:country":"US",
    "sg:address":"141 Main St",
    "sg:city":"South Portland",
    "sg:phone":"+1 207 799 8518",
    "sg:postcode":"04106",
    "sg:province":"ME",
    "sg:tags":[
        "oil",
        "gasoline"
    ],
    "wof:name":"Getty Petroleum Corp",
    "wof:placetype":"venue"
},
  "geometry": {"coordinates":[-70.288554,43.633901],"type":"Point"}
}