{
  "type": "Feature",
  "properties": {
    "iso:country":"US",
    "sg:address":"194 State Rte 108",
    "sg:city":"Rumford",
    "sg:classifiers":[
        {
            "category":"Shopping",
            "subcategory":"Hobbies, Toys, & Games",
            "type":"Retail Goods"
        }
    ],
    "sg:phone":"+1 207 364 2544",
    "sg:postcode":"04276",
    "sg:province":"ME",
    "sg:tags":[
        "product",
        "ceramic"
    ],
    "wof:name":"Studio One Ceramics",
    "wof:placetype":"venue"
},
  "geometry": {"coordinates":[-70.517076,44.534558],"type":"Point"}
}