{
  "type": "Feature",
  "properties": {
    "addr:full":"420 Wiscasset Rd Whitefield ME 04353",
    "addr:housenumber":"420",
    "addr:postcode":"04353",
    "addr:street":"Wiscasset Rd",
    "iso:country":"US",
    "sg:address":"420 Wiscasset Rd",
    "sg:city":"Whitefield",
    "sg:classifiers":[
        {
            "category":"Professional",
            "subcategory":"Computer Services",
            "type":"Services"
        }
    ],
    "sg:phone":"+1 207 549 3192",
    "sg:postcode":"04353",
    "sg:province":"ME",
    "sg:tags":[
        "related"
    ],
    "wof:name":"Downeast Solutions",
    "wof:placetype":"venue"
},
  "geometry": {"coordinates":[-69.634945,44.13817],"type":"Point"}
}