{
  "type": "Feature",
  "properties": {
    "iso:country":"US",
    "sg:address":"12 Pendleton St",
    "sg:city":"Belfast",
    "sg:classifiers":[
        {
            "category":"Organizations",
            "subcategory":"Membership Organization",
            "type":"Services"
        }
    ],
    "sg:phone":"+1 207 338 2858",
    "sg:postcode":"04915",
    "sg:province":"ME",
    "sg:tags":[
        "wear"
    ],
    "wof:name":"Ntwh Gallery",
    "wof:placetype":"venue"
},
  "geometry": {"coordinates":[-69.005754,44.42645],"type":"Point"}
}