{
  "type": "Feature",
  "properties": {
    "addr:full":"101 Hospital St Augusta ME 04330",
    "addr:housenumber":"101",
    "addr:postcode":"04330",
    "addr:street":"Hospital St",
    "iso:country":"US",
    "sg:address":"101 Hospital St",
    "sg:city":"Augusta",
    "sg:classifiers":[
        {
            "category":"Restaurant",
            "type":"Food & Drink"
        }
    ],
    "sg:phone":"+1 207 629 9175",
    "sg:postcode":"04330",
    "sg:province":"ME",
    "sg:tags":[
        "cafe"
    ],
    "wof:name":"Tim's Cafe",
    "wof:placetype":"venue"
},
  "geometry": {"coordinates":[-69.765919,44.302816],"type":"Point"}
}