{
  "type": "Feature",
  "properties": {
    "iso:country":"US",
    "sg:address":"1 One Pie Rd",
    "sg:city":"Waldoboro",
    "sg:classifiers":[
        {
            "category":"Retail",
            "subcategory":"Repair Shop",
            "type":"Services"
        }
    ],
    "sg:phone":"+1 207 832 2185",
    "sg:postcode":"04572",
    "sg:province":"ME",
    "wof:name":"Bar Harbor Interiors",
    "wof:placetype":"venue"
},
  "geometry": {"coordinates":[-69.414244,44.121767],"type":"Point"}
}