{
  "type": "Feature",
  "properties": {
    "iso:country":"US",
    "sg:address":"30 Weld St",
    "sg:city":"Dixfield",
    "sg:classifiers":[
        {
            "category":"Retail",
            "subcategory":"Funeral Services",
            "type":"Services"
        }
    ],
    "sg:phone":"+1 207 562 7211",
    "sg:postcode":"04224",
    "sg:province":"ME",
    "sg:tags":[
        "director"
    ],
    "wof:name":"Wiles Funeral Homes & Memorial",
    "wof:placetype":"venue"
},
  "geometry": {"coordinates":[-70.456209,44.533193],"type":"Point"}
}