{
  "type": "Feature",
  "properties": {
    "addr:full":"53 Sheridan St Portland ME 04101",
    "addr:housenumber":"53",
    "addr:postcode":"04101",
    "addr:street":"Sheridan St",
    "iso:country":"US",
    "sg:address":"53 Sheridan St",
    "sg:city":"Portland",
    "sg:classifiers":[
        {
            "category":"Building & Trades",
            "subcategory":"Landscaping Services",
            "type":"Services"
        }
    ],
    "sg:phone":"+1 207 294 3222",
    "sg:postcode":"04101",
    "sg:province":"ME",
    "sg:tags":[
        "lawn",
        "maintenance",
        "grounds"
    ],
    "wof:name":"Earthmama Organic Gardening",
    "wof:placetype":"venue"
},
  "geometry": {"coordinates":[-70.248891,43.664421],"type":"Point"}
}