{
  "type": "Feature",
  "properties": {
    "iso:country":"US",
    "sg:address":"7 Pumpkin Hill Ln",
    "sg:city":"Gray",
    "sg:classifiers":[
        {
            "category":"Social Services",
            "subcategory":"Child Care",
            "type":"Services"
        }
    ],
    "sg:phone":"+1 207 657 2126",
    "sg:postcode":"04039",
    "sg:province":"ME",
    "wof:name":"Puddleducks Country Child Care",
    "wof:placetype":"venue"
},
  "geometry": {"coordinates":[-70.374079,43.934139],"type":"Point"}
}