{
  "type": "Feature",
  "properties": {
    "iso:country":"US",
    "sg:address":"45 River Rd",
    "sg:city":"Newcastle",
    "sg:classifiers":[
        {
            "category":"Travel",
            "subcategory":"Hotels & Motels",
            "type":"Entertainment"
        }
    ],
    "sg:phone":"+1 207 563 2484",
    "sg:postcode":"04553",
    "sg:province":"ME",
    "sg:tags":[
        "breakfast",
        "accommodation",
        "bed"
    ],
    "sg:website":"www.theflyingcloud.com",
    "wof:name":"Flying Cloud Bed & Breakfast",
    "wof:placetype":"venue"
},
  "geometry": {"coordinates":[-69.537181,44.034839],"type":"Point"}
}