{
  "type": "Feature",
  "properties": {
    "iso:country":"US",
    "sg:address":"44 Commercial St",
    "sg:city":"Boothbay Harbor",
    "sg:classifiers":[
        {
            "category":"Shopping",
            "subcategory":"Gifts & Souvenirs",
            "type":"Retail Goods"
        }
    ],
    "sg:phone":"+1 207 633 3522",
    "sg:postcode":"04538",
    "sg:province":"ME",
    "sg:tags":[
        "shop"
    ],
    "wof:name":"Angels Unawares",
    "wof:placetype":"venue"
},
  "geometry": {"coordinates":[-69.628218,43.85066],"type":"Point"}
}