{
  "type": "Feature",
  "properties": {
    "iso:country":"US",
    "sg:address":"465 Congress St",
    "sg:city":"Portland",
    "sg:classifiers":[
        {
            "category":"Professional",
            "subcategory":"Lawyer & Legal Services",
            "type":"Services"
        }
    ],
    "sg:phone":"+1 207 775 1515",
    "sg:postcode":"04101",
    "sg:province":"ME",
    "sg:tags":[
        "attorney"
    ],
    "wof:name":"Cloutier Barrett Cloutier",
    "wof:placetype":"venue"
},
  "geometry": {"coordinates":[-70.259287,43.657435],"type":"Point"}
}