{
  "type": "Feature",
  "properties": {
    "iso:country":"US",
    "sg:address":"269 N Shore Dr",
    "sg:city":"Owls Head",
    "sg:classifiers":[
        {
            "category":"Shopping",
            "subcategory":"Gifts & Souvenirs",
            "type":"Retail Goods"
        },
        {
            "category":"Farming",
            "subcategory":"Nursery",
            "type":"Manufacturing & Wholesale Goods"
        }
    ],
    "sg:phone":"+1 207 594 9301",
    "sg:postcode":"04854",
    "sg:province":"ME",
    "sg:tags":[
        "shop",
        "ornamental"
    ],
    "wof:name":"Golden Owl",
    "wof:placetype":"venue"
},
  "geometry": {"coordinates":[-69.087275,44.082561],"type":"Point"}
}