{
  "type": "Feature",
  "properties": {
    "iso:country":"US",
    "sg:address":"726 Johnson Mill Rd",
    "sg:city":"Orrington",
    "sg:classifiers":[
        {
            "category":"Retail",
            "subcategory":"Auto Repair",
            "type":"Services"
        }
    ],
    "sg:phone":"+1 207 825 4010",
    "sg:postcode":"04474",
    "sg:province":"ME",
    "sg:tags":[
        "repairing",
        "automobile"
    ],
    "wof:name":"Higgins Pumps",
    "wof:placetype":"venue"
},
  "geometry": {"coordinates":[-68.804346,44.71711],"type":"Point"}
}