{
  "type": "Feature",
  "properties": {
    "addr:full":"384 Ridge Rd Marshfield ME 04671",
    "addr:housenumber":"384",
    "addr:postcode":"04671",
    "addr:street":"Ridge Rd",
    "iso:country":"US",
    "sg:address":"384 Ridge Rd",
    "sg:city":"Marshfield",
    "sg:classifiers":[
        {
            "category":"Building & Trades",
            "subcategory":"Construction",
            "type":"Services"
        }
    ],
    "sg:phone":"+1 207 255 8067",
    "sg:postcode":"04671",
    "sg:province":"ME",
    "sg:tags":[
        "general",
        "contractor"
    ],
    "wof:name":"Hanscom Construction Inc",
    "wof:placetype":"venue"
},
  "geometry": {"coordinates":[-67.135215,45.051479],"type":"Point"}
}