{
  "type": "Feature",
  "properties": {
    "addr:full":"934 Center Dr Orrington ME 04474",
    "addr:housenumber":"934",
    "addr:postcode":"04474",
    "addr:street":"Center Dr",
    "iso:country":"US",
    "sg:address":"934 Center Dr",
    "sg:city":"Orrington",
    "sg:classifiers":[
        {
            "category":"Autos & Motor Vehicles",
            "subcategory":"Motorcycle Sales",
            "type":"Retail Goods"
        }
    ],
    "sg:phone":"+1 207 825 8747",
    "sg:postcode":"04474",
    "sg:province":"ME",
    "wof:name":"Once Upon A Triumph",
    "wof:placetype":"venue"
},
  "geometry": {"coordinates":[-68.75447800000001,44.708258],"type":"Point"}
}