{
  "type": "Feature",
  "properties": {
    "iso:country":"US",
    "sg:address":"11 Straw Rd",
    "sg:city":"Gorham",
    "sg:classifiers":[
        {
            "category":"Wholesale",
            "subcategory":"Stationery",
            "type":"Manufacturing & Wholesale Goods"
        }
    ],
    "sg:phone":"+1 207 839 2811",
    "sg:postcode":"04038",
    "sg:province":"ME",
    "sg:tags":[
        "container",
        "plastic"
    ],
    "wof:name":"Tupperware",
    "wof:placetype":"venue"
},
  "geometry": {"coordinates":[-70.42815,43.64791],"type":"Point"}
}