{
  "type": "Feature",
  "properties": {
    "iso:country":"US",
    "sg:address":"18 Temple St",
    "sg:city":"Waterville",
    "sg:classifiers":[
        {
            "category":"Personal",
            "subcategory":"Beauty Salon",
            "type":"Services"
        }
    ],
    "sg:phone":"+1 207 873 5939",
    "sg:postcode":"04901",
    "sg:province":"ME",
    "sg:website":"www.peoplessalon.com",
    "wof:name":"People's Salon & Spa",
    "wof:placetype":"venue"
},
  "geometry": {"coordinates":[-69.628818,44.550591],"type":"Point"}
}