{
  "type": "Feature",
  "properties": {
    "addr:full":"1901 US Hwy 1 Cape Neddick ME 03902",
    "addr:housenumber":"1901",
    "addr:postcode":"03902",
    "addr:street":"Us Hwy 1",
    "iso:country":"US",
    "sg:address":"1901 US Hwy 1",
    "sg:city":"Cape Neddick",
    "sg:classifiers":[
        {
            "category":"Home & Garden",
            "subcategory":"Home Furnishings",
            "type":"Retail Goods"
        }
    ],
    "sg:phone":"+1 207 361 2500",
    "sg:postcode":"03902",
    "sg:province":"ME",
    "sg:tags":[
        "quilting"
    ],
    "sg:website":"www.mainequiltshop.com",
    "wof:name":"Knight's Country Store Quilt",
    "wof:placetype":"venue"
},
  "geometry": {"coordinates":[-70.616794,43.207136],"type":"Point"}
}