{
  "type": "Feature",
  "properties": {
    "iso:country":"US",
    "sg:address":"1 E Main St",
    "sg:city":"Searsport",
    "sg:classifiers":[
        {
            "category":"Restaurant",
            "type":"Food & Drink"
        }
    ],
    "sg:phone":"+1 207 548 2555",
    "sg:postcode":"04974",
    "sg:province":"ME",
    "wof:name":"Chocolate Grill",
    "wof:placetype":"venue"
},
  "geometry": {"coordinates":[-68.927242,44.457322],"type":"Point"}
}