{
  "type": "Feature",
  "properties": {
    "addr:full":"91 Spring St Dexter ME 04930",
    "addr:housenumber":"91",
    "addr:postcode":"04930",
    "addr:street":"Spring St",
    "iso:country":"US",
    "sg:address":"91 Spring St",
    "sg:city":"Dexter",
    "sg:classifiers":[
        {
            "category":"Food & Beverages",
            "subcategory":"Groceries & Convenience Stores",
            "type":"Retail Goods"
        }
    ],
    "sg:phone":"+1 207 924 7060",
    "sg:postcode":"04930",
    "sg:province":"ME",
    "sg:tags":[
        "market"
    ],
    "wof:name":"Toots Deli",
    "wof:placetype":"venue"
},
  "geometry": {"coordinates":[-69.290359,45.018749],"type":"Point"}
}