{
  "type": "Feature",
  "properties": {
    "iso:country":"US",
    "sg:address":"474 Howe Rd",
    "sg:city":"Whitefield",
    "sg:classifiers":[
        {
            "category":"Building & Trades",
            "subcategory":"Construction",
            "type":"Services"
        }
    ],
    "sg:phone":"+1 207 549 4596",
    "sg:postcode":"04353",
    "sg:province":"ME",
    "sg:tags":[
        "residential"
    ],
    "wof:name":"Toulouse Enterprises",
    "wof:placetype":"venue"
},
  "geometry": {"coordinates":[-69.559372,44.258431],"type":"Point"}
}