{
  "type": "Feature",
  "properties": {
    "addr:full":"200 Birch St Bangor ME 04401",
    "addr:housenumber":"200",
    "addr:postcode":"04401",
    "addr:street":"Birch St",
    "iso:country":"US",
    "sg:address":"200 Birch St",
    "sg:city":"Bangor",
    "sg:classifiers":[
        {
            "category":"Retail",
            "subcategory":"Auto Repair",
            "type":"Services"
        }
    ],
    "sg:phone":"+1 207 942 5021",
    "sg:postcode":"04401",
    "sg:province":"ME",
    "sg:tags":[
        "automobile",
        "top",
        "upholstery"
    ],
    "wof:name":"Bangor Seat Cover Shop",
    "wof:placetype":"venue"
},
  "geometry": {"coordinates":[-68.760426,44.812177],"type":"Point"}
}