{
  "type": "Feature",
  "properties": {
    "iso:country":"US",
    "sg:address":"304 Hancock St",
    "sg:city":"Bangor",
    "sg:classifiers":[
        {
            "category":"Health Services",
            "subcategory":"Hospital",
            "type":"Services"
        }
    ],
    "sg:phone":"+1 207 941 1113",
    "sg:postcode":"04401",
    "sg:province":"ME",
    "sg:tags":[
        "mental"
    ],
    "wof:name":"Phoenix Mental Health Svc",
    "wof:placetype":"venue"
},
  "geometry": {"coordinates":[-68.760145,44.802959],"type":"Point"}
}