{
  "type": "Feature",
  "properties": {
    "addr:full":"16 Union St Ellsworth ME 04605",
    "addr:housenumber":"16",
    "addr:postcode":"04605",
    "addr:street":"Union St",
    "iso:country":"US",
    "sg:address":"16 Union St",
    "sg:city":"Ellsworth",
    "sg:classifiers":[
        {
            "category":"Retail",
            "subcategory":"Auto Rental",
            "type":"Services"
        }
    ],
    "sg:phone":"+1 207 667 6600",
    "sg:postcode":"04605",
    "sg:province":"ME",
    "sg:tags":[
        "passenger",
        "car"
    ],
    "wof:name":"RPM Rentals",
    "wof:placetype":"venue"
},
  "geometry": {"coordinates":[-68.417317,44.544658],"type":"Point"}
}