{
  "type": "Feature",
  "properties": {
    "addr:full":"42 Atlantic St Portland ME 04101",
    "addr:housenumber":"42",
    "addr:postcode":"04101",
    "addr:street":"Atlantic St",
    "iso:country":"US",
    "sg:address":"42 Atlantic St",
    "sg:city":"Portland",
    "sg:classifiers":[
        {
            "category":"Organizations",
            "subcategory":"Community Association",
            "type":"Services"
        }
    ],
    "sg:phone":"+1 207 772 9314",
    "sg:postcode":"04101",
    "sg:province":"ME",
    "sg:tags":[
        "club"
    ],
    "wof:name":"American Legion",
    "wof:placetype":"venue"
},
  "geometry": {"coordinates":[-70.243853,43.664577],"type":"Point"}
}