{
  "type": "Feature",
  "properties": {
    "iso:country":"US",
    "sg:address":"212 Canco Rd",
    "sg:city":"Portland",
    "sg:classifiers":[
        {
            "category":"Professional",
            "subcategory":"Business Services",
            "type":"Services"
        }
    ],
    "sg:phone":"+1 207 771 0206",
    "sg:postcode":"04103",
    "sg:province":"ME",
    "wof:name":"Coler & Colantonio",
    "wof:placetype":"venue"
},
  "geometry": {"coordinates":[-70.284533,43.682493],"type":"Point"}
}