{
  "type": "Feature",
  "properties": {
    "addr:full":"1144 Main St Mt Desert ME 04660",
    "addr:housenumber":"1144",
    "addr:postcode":"04660",
    "addr:street":"Main St",
    "iso:country":"US",
    "sg:address":"1144 Main St",
    "sg:city":"Mt Desert",
    "sg:classifiers":[
        {
            "category":"Health Services",
            "subcategory":"Doctor",
            "type":"Services"
        }
    ],
    "sg:phone":"+1 207 244 3776",
    "sg:postcode":"04660",
    "sg:province":"ME",
    "sg:tags":[
        "dentist"
    ],
    "wof:name":"Robert L Massucco DDS",
    "wof:placetype":"venue"
},
  "geometry": {"coordinates":[-68.336235,44.360231],"type":"Point"}
}