{
  "type": "Feature",
  "properties": {
    "addr:full":"197 State St Presque Isle ME 04769",
    "addr:housenumber":"197",
    "addr:postcode":"04769",
    "addr:street":"State St",
    "iso:country":"US",
    "sg:address":"197 State St",
    "sg:city":"Presque Isle",
    "sg:classifiers":[
        {
            "category":"Travel",
            "subcategory":"Travel Agent",
            "type":"Entertainment"
        }
    ],
    "sg:phone":"+1 207 764 1994",
    "sg:postcode":"04769",
    "sg:province":"ME",
    "sg:tags":[
        "agency",
        "bureau"
    ],
    "wof:name":"Crown Travel",
    "wof:placetype":"venue"
},
  "geometry": {"coordinates":[-68.014743,46.681258],"type":"Point"}
}