{
  "type": "Feature",
  "properties": {
    "addr:full":"120 Thadeus St South Portland ME 04106",
    "addr:housenumber":"120",
    "addr:postcode":"04106",
    "addr:street":"Thadeus St",
    "iso:country":"US",
    "sg:address":"120 Thadeus St",
    "sg:city":"South Portland",
    "sg:classifiers":[
        {
            "category":"Retail",
            "subcategory":"Auto Repair",
            "type":"Services"
        }
    ],
    "sg:phone":"+1 207 767 3773",
    "sg:postcode":"04106",
    "sg:province":"ME",
    "sg:tags":[
        "body",
        "automobile",
        "painting"
    ],
    "wof:name":"Rigby Auto",
    "wof:placetype":"venue"
},
  "geometry": {"coordinates":[-70.286736,43.625769],"type":"Point"}
}