{
  "type": "Feature",
  "properties": {
    "iso:country":"US",
    "sg:address":"36 Fording Rd",
    "sg:city":"Norridgewock",
    "sg:classifiers":[
        {
            "category":"Manufacturing",
            "subcategory":"Tools & Machinery",
            "type":"Manufacturing & Wholesale Goods"
        }
    ],
    "sg:phone":"+1 207 634 3829",
    "sg:postcode":"04957",
    "sg:province":"ME",
    "sg:tags":[
        "machine",
        "shop"
    ],
    "wof:name":"Accu Machining & Mechanical Sv",
    "wof:placetype":"venue"
},
  "geometry": {"coordinates":[-69.894279,44.739648],"type":"Point"}
}