{
  "type": "Feature",
  "properties": {
    "addr:full":"75 Somerset St Bangor ME 04401",
    "addr:housenumber":"75",
    "addr:postcode":"04401",
    "addr:street":"Somerset St",
    "iso:country":"US",
    "sg:address":"75 Somerset St",
    "sg:city":"Bangor",
    "sg:classifiers":[
        {
            "category":"Professional",
            "type":"Services"
        }
    ],
    "sg:phone":"+1 207 947 3886",
    "sg:postcode":"04401",
    "sg:province":"ME",
    "sg:tags":[
        "establishment"
    ],
    "wof:name":"Ego Technologies",
    "wof:placetype":"venue"
},
  "geometry": {"coordinates":[-68.766946,44.806022],"type":"Point"}
}