{
  "type": "Feature",
  "properties": {
    "addr:full":"106 Gilman St Portland ME 04102",
    "addr:housenumber":"106",
    "addr:postcode":"04102",
    "addr:street":"Gilman St",
    "iso:country":"US",
    "sg:address":"106 Gilman St",
    "sg:city":"Portland",
    "sg:classifiers":[
        {
            "category":"Social Services",
            "type":"Services"
        }
    ],
    "sg:phone":"+1 207 874 1080",
    "sg:postcode":"04102",
    "sg:province":"ME",
    "sg:tags":[
        "organization",
        "welfare"
    ],
    "sg:website":"www.shalomhouseinc.org",
    "wof:name":"Shalom House",
    "wof:placetype":"venue"
},
  "geometry": {"coordinates":[-70.278801,43.655054],"type":"Point"}
}