{
  "type": "Feature",
  "properties": {
    "addr:full":"83 Maine St Brunswick ME 04011",
    "addr:housenumber":"83",
    "addr:postcode":"04011",
    "addr:street":"Maine St",
    "iso:country":"US",
    "sg:address":"83 Maine St",
    "sg:city":"Brunswick",
    "sg:classifiers":[
        {
            "category":"Banks & Credit Unions",
            "subcategory":"Bank",
            "type":"Services"
        }
    ],
    "sg:phone":"+1 207 725 5591",
    "sg:postcode":"04011",
    "sg:province":"ME",
    "wof:name":"Norway Savings Bank",
    "wof:placetype":"venue"
},
  "geometry": {"coordinates":[-69.965917,43.916754],"type":"Point"}
}