{
  "type": "Feature",
  "properties": {
    "addr:full":"295 Mechanic Falls Rd Poland ME 04274",
    "addr:housenumber":"295",
    "addr:postcode":"04274",
    "addr:street":"Mechanic Falls Rd",
    "iso:country":"US",
    "sg:address":"295 Mechanic Falls Rd",
    "sg:city":"Poland",
    "sg:classifiers":[
        {
            "category":"Autos & Motor Vehicles",
            "subcategory":"Automobile Sales",
            "type":"Retail Goods"
        }
    ],
    "sg:phone":"+1 207 345 9708",
    "sg:postcode":"04274",
    "sg:province":"ME",
    "sg:tags":[
        "car",
        "used",
        "dealer"
    ],
    "wof:name":"Evergreen Auto Sales Inc",
    "wof:placetype":"venue"
},
  "geometry": {"coordinates":[-70.358712,44.097238],"type":"Point"}
}