{
  "type": "Feature",
  "properties": {
    "iso:country":"US",
    "sg:address":"121 Montrose Ave",
    "sg:city":"Portland",
    "sg:classifiers":[
        {
            "category":"Personal",
            "subcategory":"Beauty Salon",
            "type":"Services"
        }
    ],
    "sg:phone":"+1 207 874 4043",
    "sg:postcode":"04103",
    "sg:province":"ME",
    "wof:name":"Cady & Co Hair & Bodyworx",
    "wof:placetype":"venue"
},
  "geometry": {"coordinates":[-70.299963,43.668632],"type":"Point"}
}