{
  "type": "Feature",
  "properties": {
    "addr:full":"12 Veranda St Portland ME 04103",
    "addr:housenumber":"12",
    "addr:postcode":"04103",
    "addr:street":"Veranda St",
    "iso:country":"US",
    "sg:address":"12 Veranda St",
    "sg:city":"Portland",
    "sg:classifiers":[
        {
            "category":"Personal",
            "subcategory":"Beauty Salon",
            "type":"Services"
        }
    ],
    "sg:phone":"+1 207 874 2909",
    "sg:postcode":"04103",
    "sg:province":"ME",
    "wof:name":"Davanti",
    "wof:placetype":"venue"
},
  "geometry": {"coordinates":[-70.25753400000001,43.680462],"type":"Point"}
}