{
  "type": "Feature",
  "properties": {
    "iso:country":"US",
    "sg:address":"88 York St",
    "sg:city":"Kennebunk",
    "sg:classifiers":[
        {
            "category":"Home & Garden",
            "subcategory":"Home Furnishings",
            "type":"Retail Goods"
        }
    ],
    "sg:phone":"+1 207 985 3501",
    "sg:postcode":"04043",
    "sg:province":"ME",
    "sg:tags":[
        "lighting",
        "fixture"
    ],
    "wof:name":"Lighthouse",
    "wof:placetype":"venue"
},
  "geometry": {"coordinates":[-70.550709,43.375733],"type":"Point"}
}