{
  "type": "Feature",
  "properties": {
    "addr:full":"71 Main St Topsham ME 04086",
    "addr:housenumber":"71",
    "addr:postcode":"04086",
    "addr:street":"Main St",
    "iso:country":"US",
    "sg:address":"71 Main St",
    "sg:city":"Topsham",
    "sg:classifiers":[
        {
            "category":"Personal",
            "subcategory":"Beauty Salon",
            "type":"Services"
        }
    ],
    "sg:phone":"+1 207 725 4845",
    "sg:postcode":"04086",
    "sg:province":"ME",
    "wof:name":"Everlasting Electrology",
    "wof:placetype":"venue"
},
  "geometry": {"coordinates":[-69.964135,43.929183],"type":"Point"}
}