{
  "type": "Feature",
  "properties": {
    "addr:full":"185 Front St Bath ME 04530",
    "addr:housenumber":"185",
    "addr:postcode":"04530",
    "addr:street":"Front St",
    "iso:country":"US",
    "sg:address":"185 Front St",
    "sg:city":"Bath",
    "sg:classifiers":[
        {
            "category":"Food & Beverages",
            "subcategory":"Groceries & Convenience Stores",
            "type":"Retail Goods"
        }
    ],
    "sg:phone":"+1 207 443 2012",
    "sg:postcode":"04530",
    "sg:province":"ME",
    "sg:tags":[
        "grocer"
    ],
    "sg:website":"www.brackettsmarket.com",
    "wof:name":"Bracketts Market",
    "wof:placetype":"venue"
},
  "geometry": {"coordinates":[-69.814397,43.915352],"type":"Point"}
}