{
  "type": "Feature",
  "properties": {
    "iso:country":"US",
    "sg:address":"186 Round-The-Pond Rd",
    "sg:city":"Norway",
    "sg:classifiers":[
        {
            "category":"Organizations",
            "subcategory":"Religious Organization",
            "type":"Services"
        }
    ],
    "sg:phone":"+1 207 743 5857",
    "sg:postcode":"04268",
    "sg:province":"ME",
    "wof:name":"LDS Missionaries",
    "wof:placetype":"venue"
},
  "geometry": {"coordinates":[-70.594069,44.25186],"type":"Point"}
}