{
  "type": "Feature",
  "properties": {
    "iso:country":"US",
    "sg:address":"279 Main St",
    "sg:city":"Rockland",
    "sg:classifiers":[
        {
            "category":"Restaurant",
            "type":"Food & Drink"
        }
    ],
    "sg:phone":"+1 207 594 4944",
    "sg:postcode":"04841",
    "sg:province":"ME",
    "wof:name":"Park Street Grille",
    "wof:placetype":"venue"
},
  "geometry": {"coordinates":[-69.109221,44.100496],"type":"Point"}
}