{
  "type": "Feature",
  "properties": {
    "iso:country":"US",
    "sg:address":"262 Spring Rd",
    "sg:city":"Pittsfield",
    "sg:classifiers":[
        {
            "category":"Autos & Motor Vehicles",
            "subcategory":"Auto Supplies",
            "type":"Retail Goods"
        }
    ],
    "sg:phone":"+1 207 487 3626",
    "sg:postcode":"04967",
    "sg:province":"ME",
    "sg:tags":[
        "automobile",
        "parts"
    ],
    "wof:name":"Automotive Truck Ind Supply",
    "wof:placetype":"venue"
},
  "geometry": {"coordinates":[-69.409409,44.786358],"type":"Point"}
}