{
  "type": "Feature",
  "properties": {
    "addr:full":"8 Highland Ave Caribou ME 04736",
    "addr:housenumber":"8",
    "addr:postcode":"04736",
    "addr:street":"Highland Ave",
    "iso:country":"US",
    "sg:address":"8 Highland Ave",
    "sg:city":"Caribou",
    "sg:classifiers":[
        {
            "category":"Retail",
            "subcategory":"Auto Repair",
            "type":"Services"
        }
    ],
    "sg:phone":"+1 207 492 6721",
    "sg:postcode":"04736",
    "sg:province":"ME",
    "sg:tags":[
        "body",
        "automobile",
        "painting"
    ],
    "wof:name":"Bell's Body & Paint Shop",
    "wof:placetype":"venue"
},
  "geometry": {"coordinates":[-68.009772,46.840972],"type":"Point"}
}