{
  "type": "Feature",
  "properties": {
    "addr:full":"8 Highwood St Waterville ME 04901",
    "addr:housenumber":"8",
    "addr:postcode":"04901",
    "addr:street":"Highwood St",
    "iso:country":"US",
    "sg:address":"8 Highwood St",
    "sg:city":"Waterville",
    "sg:classifiers":[
        {
            "category":"Health Services",
            "subcategory":"Clinic",
            "type":"Services"
        }
    ],
    "sg:phone":"+1 207 873 1127",
    "sg:postcode":"04901",
    "sg:province":"ME",
    "wof:name":"Health Reach Network",
    "wof:placetype":"venue"
},
  "geometry": {"coordinates":[-69.62278499999999,44.569471],"type":"Point"}
}