{
  "type": "Feature",
  "properties": {
    "addr:full":"39 Exchange St Rumford ME 04276",
    "addr:housenumber":"39",
    "addr:postcode":"04276",
    "addr:street":"Exchange St",
    "iso:country":"US",
    "sg:address":"39 Exchange St",
    "sg:city":"Rumford",
    "sg:classifiers":[
        {
            "category":"Restaurant",
            "type":"Food & Drink"
        }
    ],
    "sg:phone":"+1 207 369 0810",
    "sg:postcode":"04276",
    "sg:province":"ME",
    "wof:name":"River Valley Grill",
    "wof:placetype":"venue"
},
  "geometry": {"coordinates":[-70.544982,44.544967],"type":"Point"}
}