{
  "type": "Feature",
  "properties": {
    "addr:full":"411 Stevens Ave Portland ME 04103",
    "addr:housenumber":"411",
    "addr:postcode":"04103",
    "addr:street":"Stevens Ave",
    "iso:country":"US",
    "sg:address":"411 Stevens Ave",
    "sg:city":"Portland",
    "sg:classifiers":[
        {
            "category":"Professional",
            "subcategory":"Art Services",
            "type":"Services"
        }
    ],
    "sg:phone":"+1 207 828 6338",
    "sg:postcode":"04103",
    "sg:province":"ME",
    "sg:tags":[
        "photographer"
    ],
    "wof:name":"Barry Lewis Photography Inc",
    "wof:placetype":"venue"
},
  "geometry": {"coordinates":[-70.295147,43.672948],"type":"Point"}
}