{
  "type": "Feature",
  "properties": {
    "iso:country":"US",
    "sg:address":"683 Hollis Rd",
    "sg:city":"Hollis Center",
    "sg:classifiers":[
        {
            "category":"Retail",
            "subcategory":"Animal Services",
            "type":"Services"
        }
    ],
    "sg:phone":"+1 207 929 6376",
    "sg:postcode":"04042",
    "sg:province":"ME",
    "sg:tags":[
        "pet",
        "grooming",
        "washing"
    ],
    "wof:name":"Falco Farms Grooming",
    "wof:placetype":"venue"
},
  "geometry": {"coordinates":[-70.616381,43.593855],"type":"Point"}
}