{
  "type": "Feature",
  "properties": {
    "iso:country":"US",
    "sg:address":"565 Congress St",
    "sg:city":"Portland",
    "sg:classifiers":[
        {
            "category":"Real Estate",
            "subcategory":"Surveying",
            "type":"Services"
        },
        {
            "category":"Building & Trades",
            "subcategory":"Landscaping Services",
            "type":"Services"
        }
    ],
    "sg:phone":"+1 207 874 4774",
    "sg:postcode":"04101",
    "sg:province":"ME",
    "sg:tags":[
        "designer",
        "landscape"
    ],
    "wof:name":"Monro Associates",
    "wof:placetype":"venue"
},
  "geometry": {"coordinates":[-70.26218299999999,43.65513],"type":"Point"}
}