{
  "type": "Feature",
  "properties": {
    "iso:country":"US",
    "sg:address":"471 Hartland Rd",
    "sg:city":"St Albans",
    "sg:classifiers":[
        {
            "category":"Social Services",
            "type":"Services"
        }
    ],
    "sg:phone":"+1 207 938 2699",
    "sg:postcode":"04971",
    "sg:province":"ME",
    "sg:tags":[
        "organization",
        "welfare"
    ],
    "wof:name":"Lawrence Acres",
    "wof:placetype":"venue"
},
  "geometry": {"coordinates":[-69.431262,44.891736],"type":"Point"}
}