{
  "type": "Feature",
  "properties": {
    "iso:country":"US",
    "sg:address":"10 Wilson St",
    "sg:city":"Augusta",
    "sg:classifiers":[
        {
            "category":"Education",
            "subcategory":"School",
            "type":"Public Place"
        }
    ],
    "sg:phone":"+1 207 622 1721",
    "sg:postcode":"04330",
    "sg:province":"ME",
    "wof:name":"Dirigere Christian Academy",
    "wof:placetype":"venue"
},
  "geometry": {"coordinates":[-69.793746,44.371777],"type":"Point"}
}