{
  "type": "Feature",
  "properties": {
    "iso:country":"US",
    "sg:address":"149 Maine St",
    "sg:city":"Brunswick",
    "sg:classifiers":[
        {
            "category":"Utilities",
            "subcategory":"Mobile Phone",
            "type":"Services"
        }
    ],
    "sg:phone":"+1 207 729 8300",
    "sg:postcode":"04011",
    "sg:province":"ME",
    "sg:tags":[
        "telephone",
        "cellular"
    ],
    "wof:name":"New England Wireless",
    "wof:placetype":"venue"
},
  "geometry": {"coordinates":[-69.964961,43.914922],"type":"Point"}
}