{
  "type": "Feature",
  "properties": {
    "addr:full":"220 Camden Rd Appleton ME 04862",
    "addr:housenumber":"220",
    "addr:postcode":"04862",
    "addr:street":"Camden Rd",
    "iso:country":"US",
    "sg:address":"220 Camden Rd",
    "sg:city":"Appleton",
    "sg:classifiers":[
        {
            "category":"Building & Trades",
            "subcategory":"Construction",
            "type":"Services"
        }
    ],
    "sg:phone":"+1 207 785 2895",
    "sg:postcode":"04862",
    "sg:province":"ME",
    "sg:tags":[
        "contractor"
    ],
    "wof:name":"Cardinal Builders Inc",
    "wof:placetype":"venue"
},
  "geometry": {"coordinates":[-69.215363,44.307705],"type":"Point"}
}