{
  "type": "Feature",
  "properties": {
    "addr:full":"25 Terrence St Springfield ME 01109",
    "addr:housenumber":"25",
    "addr:postcode":"01109",
    "addr:street":"Terrence St",
    "iso:country":"US",
    "sg:address":"25 Terrence St",
    "sg:city":"Springfield",
    "sg:classifiers":[
        {
            "category":"Organizations",
            "subcategory":"Religious Organization",
            "type":"Services"
        }
    ],
    "sg:phone":"+1 413 788 9302",
    "sg:postcode":"01109",
    "sg:province":"ME",
    "sg:tags":[
        "church"
    ],
    "wof:name":"Eglesia Koinonia Sambleas De",
    "wof:placetype":"venue"
},
  "geometry": {"coordinates":[-72.56955000000001,42.108456],"type":"Point"}
}