{
  "type": "Feature",
  "properties": {
    "iso:country":"US",
    "sg:address":"934 Center Dr",
    "sg:city":"Orrington",
    "sg:classifiers":[
        {
            "category":"Shopping",
            "subcategory":"Hobbies, Toys, & Games",
            "type":"Retail Goods"
        }
    ],
    "sg:phone":"+1 207 825 5593",
    "sg:postcode":"04474",
    "sg:province":"ME",
    "sg:tags":[
        "model",
        "supply"
    ],
    "wof:name":"King Mountain RC",
    "wof:placetype":"venue"
},
  "geometry": {"coordinates":[-68.75447800000001,44.708258],"type":"Point"}
}