{
  "type": "Feature",
  "properties": {
    "addr:full":"756 Roosevelt Trl Windham ME 04062",
    "addr:housenumber":"756",
    "addr:postcode":"04062",
    "addr:street":"Roosevelt Trl",
    "iso:country":"US",
    "sg:address":"756 Roosevelt Trl",
    "sg:city":"Windham",
    "sg:classifiers":[
        {
            "category":"Banks & Credit Unions",
            "subcategory":"Bank",
            "type":"Services"
        }
    ],
    "sg:phone":"+1 207 892 6500",
    "sg:postcode":"04062",
    "sg:province":"ME",
    "sg:website":"www.peoplesheritage.com",
    "wof:name":"Peoples Heritage Bank",
    "wof:placetype":"venue"
},
  "geometry": {"coordinates":[-70.44927199999999,43.849506],"type":"Point"}
}