{
  "type": "Feature",
  "properties": {
    "addr:full":"145 Commercial St Portland ME 04101",
    "addr:housenumber":"145",
    "addr:postcode":"04101",
    "addr:street":"Commercial St",
    "iso:country":"US",
    "sg:address":"145 Commercial St",
    "sg:city":"Portland",
    "sg:classifiers":[
        {
            "category":"Insurance",
            "subcategory":"Insurance Agent",
            "type":"Services"
        }
    ],
    "sg:phone":"+1 207 756 8550",
    "sg:postcode":"04101",
    "sg:province":"ME",
    "sg:website":"www.dcgre.com",
    "wof:name":"Disability Consulting Group",
    "wof:placetype":"venue"
},
  "geometry": {"coordinates":[-70.251773,43.656367],"type":"Point"}
}