{
  "type": "Feature",
  "properties": {
    "addr:full":"835 Main St Westbrook ME 04092",
    "addr:housenumber":"835",
    "addr:postcode":"04092",
    "addr:street":"Main St",
    "iso:country":"US",
    "sg:address":"835 Main St",
    "sg:city":"Westbrook",
    "sg:classifiers":[
        {
            "category":"Banks & Credit Unions",
            "subcategory":"Bank",
            "type":"Services"
        }
    ],
    "sg:phone":"+1 207 854 9141",
    "sg:postcode":"04092",
    "sg:province":"ME",
    "wof:name":"Banknorth",
    "wof:placetype":"venue"
},
  "geometry": {"coordinates":[-70.366715,43.676802],"type":"Point"}
}