{
  "type": "Feature",
  "properties": {
    "addr:full":"127 Howe St Lewiston ME 04240",
    "addr:housenumber":"127",
    "addr:postcode":"04240",
    "addr:street":"Howe St",
    "iso:country":"US",
    "sg:address":"127 Howe St",
    "sg:city":"Lewiston",
    "sg:classifiers":[
        {
            "category":"Building & Trades",
            "subcategory":"Construction",
            "type":"Services"
        }
    ],
    "sg:phone":"+1 207 784 0460",
    "sg:postcode":"04240",
    "sg:province":"ME",
    "wof:name":"Stans Roofing & Siding",
    "wof:placetype":"venue"
},
  "geometry": {"coordinates":[-70.207786,44.094823],"type":"Point"}
}