{
  "type": "Feature",
  "properties": {
    "iso:country":"US",
    "sg:address":"67 Snow Hill Rd",
    "sg:city":"New Gloucester",
    "sg:classifiers":[
        {
            "category":"Building & Trades",
            "subcategory":"Construction",
            "type":"Services"
        }
    ],
    "sg:phone":"+1 207 926 3531",
    "sg:postcode":"04260",
    "sg:province":"ME",
    "sg:tags":[
        "concrete",
        "contractor"
    ],
    "wof:name":"Quality Concrete Floors Inc",
    "wof:placetype":"venue"
},
  "geometry": {"coordinates":[-70.30887,43.98569],"type":"Point"}
}