{
  "type": "Feature",
  "properties": {
    "iso:country":"US",
    "sg:address":"665 Saco St",
    "sg:city":"Westbrook",
    "sg:classifiers":[
        {
            "category":"Freight",
            "type":"Transportation"
        }
    ],
    "sg:phone":"+1 207 856 9934",
    "sg:postcode":"04092",
    "sg:province":"ME",
    "sg:tags":[
        "operator",
        "trucking"
    ],
    "wof:name":"Roy W McPherson",
    "wof:placetype":"venue"
},
  "geometry": {"coordinates":[-70.378375,43.663249],"type":"Point"}
}