{
  "type": "Feature",
  "properties": {
    "iso:country":"US",
    "sg:address":"41 Farmer Rd",
    "sg:city":"Eliot",
    "sg:classifiers":[
        {
            "category":"Food & Beverages",
            "subcategory":"Groceries & Convenience Stores",
            "type":"Retail Goods"
        }
    ],
    "sg:phone":"+1 207 439 2983",
    "sg:postcode":"03903",
    "sg:province":"ME",
    "sg:tags":[
        "market"
    ],
    "wof:name":"Eliot Meat Market",
    "wof:placetype":"venue"
},
  "geometry": {"coordinates":[-70.792563,43.118381],"type":"Point"}
}