{
  "type": "Feature",
  "properties": {
    "iso:country":"US",
    "sg:address":"757 Coastal Rd",
    "sg:city":"Brooksville",
    "sg:classifiers":[
        {
            "category":"Real Estate",
            "subcategory":"Real Estate Agent",
            "type":"Services"
        }
    ],
    "sg:phone":"+1 207 326 4618",
    "sg:postcode":"04617",
    "sg:province":"ME",
    "wof:name":"Bucks Harbor Realty",
    "wof:placetype":"venue"
},
  "geometry": {"coordinates":[-68.750032,44.361486],"type":"Point"}
}