{
  "type": "Feature",
  "properties": {
    "iso:country":"US",
    "sg:address":"23 Market Sq",
    "sg:city":"Houlton",
    "sg:classifiers":[
        {
            "category":"Shopping",
            "subcategory":"Books",
            "type":"Retail Goods"
        }
    ],
    "sg:phone":"+1 800 850 0833",
    "sg:postcode":"04730",
    "sg:province":"ME",
    "wof:name":"Ernies Books & Comics",
    "wof:placetype":"venue"
},
  "geometry": {"coordinates":[-67.841089,46.125588],"type":"Point"}
}