{
  "type": "Feature",
  "properties": {
    "iso:country":"US",
    "sg:address":"59 Thatcher St",
    "sg:city":"Bangor",
    "sg:classifiers":[
        {
            "category":"Building & Trades",
            "subcategory":"Electrical",
            "type":"Services"
        }
    ],
    "sg:phone":"+1 207 989 4700",
    "sg:postcode":"04401",
    "sg:province":"ME",
    "sg:tags":[
        "electric",
        "contractor"
    ],
    "wof:name":"Scott's Electric",
    "wof:placetype":"venue"
},
  "geometry": {"coordinates":[-68.783411,44.783568],"type":"Point"}
}