{
  "type": "Feature",
  "properties": {
    "iso:country":"US",
    "sg:address":"28 Mercer Rd",
    "sg:city":"New Sharon",
    "sg:classifiers":[
        {
            "category":"Wholesale",
            "subcategory":"Farm Supplies",
            "type":"Manufacturing & Wholesale Goods"
        }
    ],
    "sg:phone":"+1 207 778 4748",
    "sg:postcode":"04955",
    "sg:province":"ME",
    "sg:tags":[
        "grain"
    ],
    "wof:name":"Whitewater Farm",
    "wof:placetype":"venue"
},
  "geometry": {"coordinates":[-70.013965,44.637746],"type":"Point"}
}