{
  "type": "Feature",
  "properties": {
    "addr:full":"7 Gilman St Waterville ME 04901",
    "addr:housenumber":"7",
    "addr:postcode":"04901",
    "addr:street":"Gilman St",
    "iso:country":"US",
    "sg:address":"7 Gilman St",
    "sg:city":"Waterville",
    "sg:classifiers":[
        {
            "category":"Organizations",
            "subcategory":"Religious Organization",
            "type":"Services"
        }
    ],
    "sg:phone":"+1 207 314 3811",
    "sg:postcode":"04901",
    "sg:province":"ME",
    "sg:tags":[
        "monastery",
        "convent"
    ],
    "wof:name":"Sisters Of St Joseph",
    "wof:placetype":"venue"
},
  "geometry": {"coordinates":[-69.634359,44.55316],"type":"Point"}
}