{
  "type": "Feature",
  "properties": {
    "addr:full":"325 Main St Waterville ME 04901",
    "addr:housenumber":"325",
    "addr:postcode":"04901",
    "addr:street":"Main St",
    "iso:country":"US",
    "sg:address":"325 Main St",
    "sg:city":"Waterville",
    "sg:classifiers":[
        {
            "category":"Building & Trades",
            "subcategory":"Equipment Rental",
            "type":"Services"
        }
    ],
    "sg:phone":"+1 207 861 8039",
    "sg:postcode":"04901",
    "sg:province":"ME",
    "sg:tags":[
        "yard"
    ],
    "wof:name":"Color Tyme",
    "wof:placetype":"venue"
},
  "geometry": {"coordinates":[-69.642708,44.574633],"type":"Point"}
}