{
  "type": "Feature",
  "properties": {
    "addr:full":"31 E Jay Rd Jay ME 04239",
    "addr:housenumber":"31",
    "addr:postcode":"04239",
    "addr:street":"E Jay Rd",
    "iso:country":"US",
    "sg:address":"31 E Jay Rd",
    "sg:city":"Jay",
    "sg:classifiers":[
        {
            "category":"Retail",
            "subcategory":"Self-service Laundry",
            "type":"Services"
        }
    ],
    "sg:phone":"+1 207 897 4960",
    "sg:postcode":"04239",
    "sg:province":"ME",
    "wof:name":"Garden Island Laundry",
    "wof:placetype":"venue"
},
  "geometry": {"coordinates":[-70.17768599999999,44.50267],"type":"Point"}
}