{
  "type": "Feature",
  "properties": {
    "iso:country":"US",
    "sg:address":"82 Best St",
    "sg:city":"Portland",
    "sg:classifiers":[
        {
            "category":"Banks & Credit Unions",
            "subcategory":"Investment Brokerage",
            "type":"Services"
        }
    ],
    "sg:phone":"+1 207 615 0035",
    "sg:postcode":"04103",
    "sg:province":"ME",
    "sg:tags":[
        "consultant",
        "financing"
    ],
    "wof:name":"Blackstone Consulting",
    "wof:placetype":"venue"
},
  "geometry": {"coordinates":[-70.298502,43.678247],"type":"Point"}
}