{
  "type": "Feature",
  "properties": {
    "iso:country":"US",
    "sg:address":"56 Elm St",
    "sg:city":"Camden",
    "sg:classifiers":[
        {
            "category":"Manufacturing",
            "subcategory":"Printing",
            "type":"Manufacturing & Wholesale Goods"
        }
    ],
    "sg:phone":"+1 207 236 8511",
    "sg:postcode":"04843",
    "sg:province":"ME",
    "sg:tags":[
        "newspaper"
    ],
    "wof:name":"Camden Herald",
    "wof:placetype":"venue"
},
  "geometry": {"coordinates":[-69.06719,44.207979],"type":"Point"}
}