{
  "type": "Feature",
  "properties": {
    "iso:country":"US",
    "sg:address":"5 Mc Lellan St",
    "sg:city":"Brunswick",
    "sg:classifiers":[
        {
            "category":"Building & Trades",
            "subcategory":"Electrical",
            "type":"Services"
        }
    ],
    "sg:phone":"+1 207 729 6345",
    "sg:postcode":"04011",
    "sg:province":"ME",
    "sg:tags":[
        "electric",
        "contractor"
    ],
    "wof:name":"Dwelley Electric",
    "wof:placetype":"venue"
},
  "geometry": {"coordinates":[-69.95713499999999,43.906317],"type":"Point"}
}