{
  "type": "Feature",
  "properties": {
    "iso:country":"US",
    "sg:address":"175 Lewiston Rd",
    "sg:city":"Gray",
    "sg:classifiers":[
        {
            "category":"Retail",
            "subcategory":"Repair Shop",
            "type":"Services"
        }
    ],
    "sg:phone":"+1 207 657 6400",
    "sg:postcode":"04039",
    "sg:province":"ME",
    "sg:tags":[
        "equipment"
    ],
    "wof:name":"Pine Tree Food Equipment",
    "wof:placetype":"venue"
},
  "geometry": {"coordinates":[-70.321294,43.914044],"type":"Point"}
}