{
  "type": "Feature",
  "properties": {
    "addr:full":"59 Main St Orono ME 04473",
    "addr:housenumber":"59",
    "addr:postcode":"04473",
    "addr:street":"Main St",
    "iso:country":"US",
    "sg:address":"59 Main St",
    "sg:city":"Orono",
    "sg:classifiers":[
        {
            "category":"Government",
            "subcategory":"Office",
            "type":"Public Place"
        }
    ],
    "sg:phone":"+1 207 866 5051",
    "sg:postcode":"04473",
    "sg:province":"ME",
    "sg:tags":[
        "village"
    ],
    "wof:name":"Code Enforcement",
    "wof:placetype":"venue"
},
  "geometry": {"coordinates":[-68.672724,44.882778],"type":"Point"}
}