{
  "type": "Feature",
  "properties": {
    "addr:full":"2 Footbridge Rd Belfast ME 04915",
    "addr:housenumber":"2",
    "addr:postcode":"04915",
    "addr:street":"Footbridge Rd",
    "iso:country":"US",
    "sg:address":"2 Footbridge Rd",
    "sg:city":"Belfast",
    "sg:classifiers":[
        {
            "category":"Social Services",
            "subcategory":"Job Training",
            "type":"Services"
        }
    ],
    "sg:phone":"+1 207 338 0246",
    "sg:postcode":"04915",
    "sg:province":"ME",
    "sg:tags":[
        "rehabilitation"
    ],
    "wof:name":"Rehabworks",
    "wof:placetype":"venue"
},
  "geometry": {"coordinates":[-69.005685,44.43342],"type":"Point"}
}