{
  "type": "Feature",
  "properties": {
    "addr:full":"3 China Rd Waterville ME 04901",
    "addr:housenumber":"3",
    "addr:postcode":"04901",
    "addr:street":"China Rd",
    "iso:country":"US",
    "sg:address":"3 China Rd",
    "sg:city":"Waterville",
    "sg:classifiers":[
        {
            "category":"Building & Trades",
            "subcategory":"Electrical",
            "type":"Services"
        }
    ],
    "sg:phone":"+1 207 872 5031",
    "sg:postcode":"04901",
    "sg:province":"ME",
    "sg:tags":[
        "electrical",
        "contractor"
    ],
    "wof:name":"Veilleux & Company",
    "wof:placetype":"venue"
},
  "geometry": {"coordinates":[-69.626065,44.536991],"type":"Point"}
}