{
  "type": "Feature",
  "properties": {
    "addr:full":"416 Commercial St Portland ME 04101",
    "addr:housenumber":"416",
    "addr:postcode":"04101",
    "addr:street":"Commercial St",
    "iso:country":"US",
    "sg:address":"416 Commercial St",
    "sg:city":"Portland",
    "sg:classifiers":[
        {
            "category":"Manufacturing",
            "subcategory":"Food",
            "type":"Manufacturing & Wholesale Goods"
        }
    ],
    "sg:phone":"+1 207 253 5012",
    "sg:postcode":"04101",
    "sg:province":"ME",
    "sg:tags":[
        "packer",
        "fish"
    ],
    "wof:name":"Kme",
    "wof:placetype":"venue"
},
  "geometry": {"coordinates":[-70.25765699999999,43.65033],"type":"Point"}
}