{
  "type": "Feature",
  "properties": {
    "iso:country":"US",
    "sg:address":"1750 Lisbon St",
    "sg:city":"Lewiston",
    "sg:classifiers":[
        {
            "category":"Shopping",
            "subcategory":"Department Store",
            "type":"Retail Goods"
        }
    ],
    "sg:phone":"+1 207 786 8996",
    "sg:postcode":"04240",
    "sg:province":"ME",
    "sg:tags":[
        "shop"
    ],
    "wof:name":"Bob's Discount",
    "wof:placetype":"venue"
},
  "geometry": {"coordinates":[-70.169611,44.070041],"type":"Point"}
}