{
  "type": "Feature",
  "properties": {
    "addr:full":"571 Sabattus St Lewiston ME 04240",
    "addr:housenumber":"571",
    "addr:postcode":"04240",
    "addr:street":"Sabattus St",
    "iso:country":"US",
    "sg:address":"571 Sabattus St",
    "sg:city":"Lewiston",
    "sg:classifiers":[
        {
            "category":"Professional",
            "subcategory":"Detective & Security Services",
            "type":"Services"
        }
    ],
    "sg:phone":"+1 207 782 3113",
    "sg:postcode":"04240",
    "sg:province":"ME",
    "sg:tags":[
        "investigator"
    ],
    "wof:name":"Pinnacle Services",
    "wof:placetype":"venue"
},
  "geometry": {"coordinates":[-70.18514999999999,44.101963],"type":"Point"}
}