{
  "type": "Feature",
  "properties": {
    "iso:country":"US",
    "sg:address":"76 Nickerson Rd",
    "sg:city":"Brooks",
    "sg:classifiers":[
        {
            "category":"Farming",
            "subcategory":"Dairy Farm",
            "type":"Manufacturing & Wholesale Goods"
        }
    ],
    "sg:phone":"+1 207 722 3675",
    "sg:postcode":"04921",
    "sg:province":"ME",
    "wof:name":"Paul Nickerson",
    "wof:placetype":"venue"
},
  "geometry": {"coordinates":[-69.125033,44.53468],"type":"Point"}
}