{
  "type": "Feature",
  "properties": {
    "iso:country":"US",
    "sg:address":"2 Grant St",
    "sg:city":"Ellsworth",
    "sg:classifiers":[
        {
            "category":"Retail",
            "subcategory":"Animal Services",
            "type":"Services"
        }
    ],
    "sg:phone":"+1 207 664 0333",
    "sg:postcode":"04605",
    "sg:province":"ME",
    "sg:tags":[
        "pet",
        "grooming",
        "washing"
    ],
    "wof:name":"Pampered Pooch",
    "wof:placetype":"venue"
},
  "geometry": {"coordinates":[-68.42718000000001,44.541312],"type":"Point"}
}