{
  "type": "Feature",
  "properties": {
    "iso:country":"US",
    "sg:address":"111 Elm St",
    "sg:city":"Mechanic Falls",
    "sg:classifiers":[
        {
            "category":"Organizations",
            "subcategory":"Religious Organization",
            "type":"Services"
        }
    ],
    "sg:phone":"+1 207 345 3505",
    "sg:postcode":"04256",
    "sg:province":"ME",
    "sg:tags":[
        "church"
    ],
    "wof:name":"Our Lady Of Ransom Church",
    "wof:placetype":"venue"
},
  "geometry": {"coordinates":[-70.385362,44.105678],"type":"Point"}
}