{
  "type": "Feature",
  "properties": {
    "iso:country":"US",
    "sg:address":"289 Water St",
    "sg:city":"Skowhegan",
    "sg:classifiers":[
        {
            "category":"Health Services",
            "subcategory":"Chiropractor",
            "type":"Services"
        }
    ],
    "sg:phone":"+1 207 858 0510",
    "sg:postcode":"04976",
    "sg:province":"ME",
    "wof:name":"Merrill & Merrill Family",
    "wof:placetype":"venue"
},
  "geometry": {"coordinates":[-69.713338,44.769135],"type":"Point"}
}