{
  "type": "Feature",
  "properties": {
    "addr:full":"124 River Rd Arundel ME 04046",
    "addr:housenumber":"124",
    "addr:postcode":"04046",
    "addr:street":"River Rd",
    "iso:country":"US",
    "sg:address":"124 River Rd",
    "sg:city":"Arundel",
    "sg:classifiers":[
        {
            "category":"Professional",
            "type":"Services"
        }
    ],
    "sg:phone":"+1 207 967 0778",
    "sg:postcode":"04046",
    "sg:province":"ME",
    "sg:tags":[
        "establishment"
    ],
    "wof:name":"Demadu LTD",
    "wof:placetype":"venue"
},
  "geometry": {"coordinates":[-70.48969700000001,43.377981],"type":"Point"}
}