{
  "type": "Feature",
  "properties": {
    "iso:country":"US",
    "sg:address":"243 Indiana Rd",
    "sg:city":"West Gardiner",
    "sg:classifiers":[
        {
            "category":"Building & Trades",
            "subcategory":"Construction",
            "type":"Services"
        }
    ],
    "sg:phone":"+1 207 582 8995",
    "sg:postcode":"04345",
    "sg:province":"ME",
    "sg:tags":[
        "excavating",
        "contractor"
    ],
    "wof:name":"Kevin B Peckham Excavation",
    "wof:placetype":"venue"
},
  "geometry": {"coordinates":[-69.87611,44.190112],"type":"Point"}
}