{
  "type": "Feature",
  "properties": {
    "iso:country":"US",
    "sg:address":"6 Haskell St",
    "sg:city":"Auburn",
    "sg:classifiers":[
        {
            "category":"Real Estate",
            "subcategory":"Real Estate Agent",
            "type":"Services"
        }
    ],
    "sg:phone":"+1 207 783 6010",
    "sg:postcode":"04210",
    "sg:province":"ME",
    "wof:name":"Dunkin Donuts",
    "wof:placetype":"venue"
},
  "geometry": {"coordinates":[-70.236655,44.098641],"type":"Point"}
}