{
  "type": "Feature",
  "properties": {
    "iso:country":"US",
    "sg:address":"1606 Hammond St",
    "sg:city":"Hermon",
    "sg:classifiers":[
        {
            "category":"Recreation",
            "type":"Entertainment"
        }
    ],
    "sg:phone":"+1 207 947 0400",
    "sg:postcode":"04401",
    "sg:province":"ME",
    "sg:tags":[
        "boxing",
        "instruction"
    ],
    "wof:name":"Mc Auliffe Boxing Club",
    "wof:placetype":"venue"
},
  "geometry": {"coordinates":[-68.83789299999999,44.794523],"type":"Point"}
}