{
  "type": "Feature",
  "properties": {
    "iso:country":"US",
    "sg:address":"37 Harrison St",
    "sg:city":"Calais",
    "sg:classifiers":[
        {
            "category":"Organizations",
            "subcategory":"Religious Organization",
            "type":"Services"
        }
    ],
    "sg:phone":"+1 207 454 8160",
    "sg:postcode":"04619",
    "sg:province":"ME",
    "wof:name":"Saint Croix Vly Assembly God",
    "wof:placetype":"venue"
},
  "geometry": {"coordinates":[-67.284843,45.17101],"type":"Point"}
}