{
  "type": "Feature",
  "properties": {
    "addr:full":"150 Main Rd Islesboro ME 04848",
    "addr:housenumber":"150",
    "addr:postcode":"04848",
    "addr:street":"Main Rd",
    "iso:country":"US",
    "sg:address":"150 Main Rd",
    "sg:city":"Islesboro",
    "sg:classifiers":[
        {
            "category":"Government",
            "subcategory":"Office",
            "type":"Public Place"
        }
    ],
    "sg:phone":"+1 207 734 6787",
    "sg:postcode":"04848",
    "sg:province":"ME",
    "sg:tags":[
        "village"
    ],
    "wof:name":"Safety Building Dept",
    "wof:placetype":"venue"
},
  "geometry": {"coordinates":[-68.903097,44.307782],"type":"Point"}
}