{
  "type": "Feature",
  "properties": {
    "addr:full":"243 Long Beach Ave York ME 03909",
    "addr:housenumber":"243",
    "addr:postcode":"03909",
    "addr:street":"Long Beach Ave",
    "iso:country":"US",
    "sg:address":"243 Long Beach Ave",
    "sg:city":"York",
    "sg:classifiers":[
        {
            "category":"Restaurant",
            "type":"Food & Drink"
        }
    ],
    "sg:phone":"+1 207 363 3807",
    "sg:postcode":"03909",
    "sg:province":"ME",
    "sg:tags":[
        "italian"
    ],
    "wof:name":"Mimmo's Fine Italian Continental Cuisine",
    "wof:placetype":"venue"
},
  "geometry": {"coordinates":[-70.62097900000001,43.160641],"type":"Point"}
}