{
  "type": "Feature",
  "properties": {
    "iso:country":"US",
    "sg:address":"231 Main St",
    "sg:city":"Ellsworth",
    "sg:classifiers":[
        {
            "category":"Organizations",
            "subcategory":"Religious Organization",
            "type":"Services"
        }
    ],
    "sg:phone":"+1 207 667 2342",
    "sg:postcode":"04605",
    "sg:province":"ME",
    "sg:tags":[
        "church"
    ],
    "wof:name":"St Joseph Catholic Church",
    "wof:placetype":"venue"
},
  "geometry": {"coordinates":[-68.41984600000001,44.542988],"type":"Point"}
}