{
  "type": "Feature",
  "properties": {
    "addr:full":"155 Saco Ave Old Orchard Bch ME 04064",
    "addr:housenumber":"155",
    "addr:postcode":"04064",
    "addr:street":"Saco Ave",
    "iso:country":"US",
    "sg:address":"155 Saco Ave",
    "sg:city":"Old Orchard Bch",
    "sg:classifiers":[
        {
            "category":"Professional",
            "subcategory":"Management & Consulting",
            "type":"Services"
        }
    ],
    "sg:phone":"+1 207 934 0252",
    "sg:postcode":"04064",
    "sg:province":"ME",
    "sg:tags":[
        "marketing",
        "consultant"
    ],
    "wof:name":"National Automotive Support",
    "wof:placetype":"venue"
},
  "geometry": {"coordinates":[-70.390559,43.513242],"type":"Point"}
}