{
  "type": "Feature",
  "properties": {
    "addr:full":"740 Main Rd N Hampden ME 04444",
    "addr:housenumber":"740",
    "addr:postcode":"04444",
    "addr:street":"Main Rd N",
    "iso:country":"US",
    "sg:address":"740 Main Rd N",
    "sg:city":"Hampden",
    "sg:phone":"+1 207 945 9378",
    "sg:postcode":"04444",
    "sg:province":"ME",
    "sg:tags":[
        "oil"
    ],
    "wof:name":"Huntley Oil Co",
    "wof:placetype":"venue"
},
  "geometry": {"coordinates":[-68.789423,44.774943],"type":"Point"}
}