{
  "type": "Feature",
  "properties": {
    "addr:full":"121 Sawyer St South Portland ME 04106",
    "addr:housenumber":"121",
    "addr:postcode":"04106",
    "addr:street":"Sawyer St",
    "iso:country":"US",
    "sg:address":"121 Sawyer St",
    "sg:city":"South Portland",
    "sg:classifiers":[
        {
            "category":"Bars & Pubs",
            "type":"Food & Drink"
        }
    ],
    "sg:phone":"+1 207 799 8505",
    "sg:postcode":"04106",
    "sg:province":"ME",
    "wof:name":"Evelyn's Tavern",
    "wof:placetype":"venue"
},
  "geometry": {"coordinates":[-70.240438,43.646107],"type":"Point"}
}