{
  "type": "Feature",
  "properties": {
    "addr:full":"1 Cumberland St Bangor ME 04401",
    "addr:housenumber":"1",
    "addr:postcode":"04401",
    "addr:street":"Cumberland St",
    "iso:country":"US",
    "sg:address":"1 Cumberland St",
    "sg:city":"Bangor",
    "sg:classifiers":[
        {
            "category":"Government",
            "subcategory":"Office",
            "type":"Public Place"
        }
    ],
    "sg:phone":"+1 207 945 0432",
    "sg:postcode":"04401",
    "sg:province":"ME",
    "wof:name":"Senator Olympia J Snowe",
    "wof:placetype":"venue"
},
  "geometry": {"coordinates":[-68.772481,44.806414],"type":"Point"}
}