{
  "type": "Feature",
  "properties": {
    "iso:country":"US",
    "sg:address":"75 Main St",
    "sg:city":"Belgrade Lakes",
    "sg:classifiers":[
        {
            "category":"Home & Garden",
            "subcategory":"Furniture",
            "type":"Retail Goods"
        }
    ],
    "sg:phone":"+1 207 495 2954",
    "sg:postcode":"04950",
    "sg:province":"ME",
    "sg:tags":[
        "builder",
        "custom"
    ],
    "wof:name":"Once Upon A Tree",
    "wof:placetype":"venue"
},
  "geometry": {"coordinates":[-69.883105,44.797881],"type":"Point"}
}