{
  "type": "Feature",
  "properties": {
    "addr:full":"459 Millett Rd Minot ME 04258",
    "addr:housenumber":"459",
    "addr:postcode":"04258",
    "addr:street":"Millett Rd",
    "iso:country":"US",
    "sg:address":"459 Millett Rd",
    "sg:city":"Minot",
    "sg:classifiers":[
        {
            "category":"Building & Trades",
            "subcategory":"Construction",
            "type":"Services"
        }
    ],
    "sg:phone":"+1 207 345 5731",
    "sg:postcode":"04258",
    "sg:province":"ME",
    "sg:tags":[
        "house"
    ],
    "wof:name":"M L Brown Construction",
    "wof:placetype":"venue"
},
  "geometry": {"coordinates":[-70.386956,44.137793],"type":"Point"}
}