{
  "type": "Feature",
  "properties": {
    "iso:country":"US",
    "sg:address":"1042 Chadbourne Rd",
    "sg:city":"Standish",
    "sg:classifiers":[
        {
            "category":"Building & Trades",
            "subcategory":"Construction",
            "type":"Services"
        }
    ],
    "sg:phone":"+1 207 892 3636",
    "sg:postcode":"04084",
    "sg:province":"ME",
    "sg:tags":[
        "shed",
        "utility"
    ],
    "sg:website":"www.shedhappens.com",
    "wof:name":"Shed Happens",
    "wof:placetype":"venue"
},
  "geometry": {"coordinates":[-70.463414,43.815079],"type":"Point"}
}