{
  "type": "Feature",
  "properties": {
    "addr:full":"70 Springer Dr Bangor ME 04401",
    "addr:housenumber":"70",
    "addr:postcode":"04401",
    "addr:street":"Springer Dr",
    "iso:country":"US",
    "sg:address":"70 Springer Dr",
    "sg:city":"Bangor",
    "sg:classifiers":[
        {
            "category":"Shopping",
            "subcategory":"Department Store",
            "type":"Retail Goods"
        }
    ],
    "sg:phone":"+1 207 947 5254",
    "sg:postcode":"04401",
    "sg:province":"ME",
    "wof:name":"Wal-Mart",
    "wof:placetype":"venue"
},
  "geometry": {"coordinates":[-68.73967500000001,44.836219],"type":"Point"}
}