{
  "type": "Feature",
  "properties": {
    "addr:full":"327 Water St Gardiner ME 04346",
    "addr:housenumber":"327",
    "addr:postcode":"04346",
    "addr:street":"Water St",
    "iso:country":"US",
    "sg:address":"327 Water St",
    "sg:city":"Gardiner",
    "sg:classifiers":[
        {
            "category":"Insurance",
            "subcategory":"Insurance Agent",
            "type":"Services"
        }
    ],
    "sg:phone":"+1 207 582 7100",
    "sg:postcode":"04346",
    "sg:province":"ME",
    "wof:name":"Janet Slade Insurance Inc",
    "wof:placetype":"venue"
},
  "geometry": {"coordinates":[-69.759913,44.224508],"type":"Point"}
}