{
  "type": "Feature",
  "properties": {
    "iso:country":"US",
    "sg:address":"73 Harlow St",
    "sg:city":"Bangor",
    "sg:classifiers":[
        {
            "category":"Real Estate",
            "subcategory":"Real Estate Agent",
            "type":"Services"
        }
    ],
    "sg:phone":"+1 207 947 4842",
    "sg:postcode":"04401",
    "sg:province":"ME",
    "wof:name":"Ban Air Corp",
    "wof:placetype":"venue"
},
  "geometry": {"coordinates":[-68.769381,44.802541],"type":"Point"}
}