{
  "type": "Feature",
  "properties": {
    "iso:country":"US",
    "sg:address":"682 Main St",
    "sg:city":"Vassalboro",
    "sg:classifiers":[
        {
            "category":"Government",
            "subcategory":"Office",
            "type":"Public Place"
        }
    ],
    "sg:phone":"+1 207 872 2826",
    "sg:postcode":"04965",
    "sg:province":"ME",
    "sg:tags":[
        "village"
    ],
    "wof:name":"Vassalboro Town Office",
    "wof:placetype":"venue"
},
  "geometry": {"coordinates":[-69.402518,44.835801],"type":"Point"}
}