{
  "type": "Feature",
  "properties": {
    "iso:country":"US",
    "sg:address":"30 Danforth St",
    "sg:city":"Portland",
    "sg:classifiers":[
        {
            "category":"Professional",
            "type":"Services"
        }
    ],
    "sg:phone":"+1 207 761 2700",
    "sg:postcode":"04101",
    "sg:province":"ME",
    "sg:tags":[
        "establishment"
    ],
    "wof:name":"Eastern League",
    "wof:placetype":"venue"
},
  "geometry": {"coordinates":[-70.257445,43.654053],"type":"Point"}
}