{
  "type": "Feature",
  "properties": {
    "addr:full":"233 Needham Street Newton ME 02464",
    "addr:housenumber":"233",
    "addr:postcode":"02464",
    "addr:street":"Needham Street",
    "iso:country":"US",
    "sg:address":"233 Needham Street",
    "sg:city":"Newton",
    "sg:classifiers":[
        {
            "category":"Professional",
            "subcategory":"Research",
            "type":"Services"
        }
    ],
    "sg:phone":"+1 617 454 1008",
    "sg:postcode":"02464",
    "sg:province":"ME",
    "sg:website":"http://www.nktrx.com/",
    "wof:name":"NKT Therapeutics",
    "wof:placetype":"venue"
},
  "geometry": {"coordinates":[-71.214811,42.309572],"type":"Point"}
}