{
  "type": "Feature",
  "properties": {
    "addr:full":"7 E Presque Isle Rd Caribou ME 04736",
    "addr:housenumber":"7",
    "addr:postcode":"04736",
    "addr:street":"E Presque Isle Rd",
    "iso:country":"US",
    "sg:address":"7 E Presque Isle Rd",
    "sg:city":"Caribou",
    "sg:classifiers":[
        {
            "category":"Retail",
            "subcategory":"Portrait Studio",
            "type":"Services"
        }
    ],
    "sg:phone":"+1 207 496 7101",
    "sg:postcode":"04736",
    "sg:province":"ME",
    "sg:tags":[
        "photography"
    ],
    "wof:name":"Photography By Duane",
    "wof:placetype":"venue"
},
  "geometry": {"coordinates":[-67.999641,46.853618],"type":"Point"}
}