{
  "type": "Feature",
  "properties": {
    "iso:country":"US",
    "sg:address":"38 Elm St",
    "sg:city":"Hartland",
    "sg:classifiers":[
        {
            "category":"Shopping",
            "subcategory":"Florist",
            "type":"Retail Goods"
        },
        {
            "category":"Shopping",
            "subcategory":"Gifts & Souvenirs",
            "type":"Retail Goods"
        }
    ],
    "sg:phone":"+1 207 938 3055",
    "sg:postcode":"04943",
    "sg:province":"ME",
    "wof:name":"Jacquie's Floral & Gift",
    "wof:placetype":"venue"
},
  "geometry": {"coordinates":[-69.447677,44.883148],"type":"Point"}
}