{
  "type": "Feature",
  "properties": {
    "iso:country":"US",
    "sg:address":"4 Crystalvale Rd",
    "sg:city":"Rome",
    "sg:classifiers":[
        {
            "category":"Professional",
            "subcategory":"Business Services",
            "type":"Services"
        }
    ],
    "sg:phone":"+1 207 397 2381",
    "sg:postcode":"04955",
    "sg:province":"ME",
    "sg:tags":[
        "auctioneer"
    ],
    "wof:name":"Rome Auction Hall",
    "wof:placetype":"venue"
},
  "geometry": {"coordinates":[-70.071004,44.69399],"type":"Point"}
}