{
  "type": "Feature",
  "properties": {
    "iso:country":"US",
    "sg:address":"15 Cedar Grove Rd",
    "sg:city":"Litchfield",
    "sg:classifiers":[
        {
            "category":"Building & Trades",
            "subcategory":"Construction",
            "type":"Services"
        }
    ],
    "sg:phone":"+1 207 268 9130",
    "sg:postcode":"04342",
    "sg:province":"ME",
    "sg:tags":[
        "dry wall",
        "contractor"
    ],
    "wof:name":"J P General Constr & Drywall",
    "wof:placetype":"venue"
},
  "geometry": {"coordinates":[-69.73962299999999,44.127055],"type":"Point"}
}