{
  "type": "Feature",
  "properties": {
    "iso:country":"US",
    "sg:address":"175 Main St",
    "sg:city":"Jonesport",
    "sg:classifiers":[
        {
            "category":"Banks & Credit Unions",
            "subcategory":"Bank",
            "type":"Services"
        }
    ],
    "sg:phone":"+1 207 497 2320",
    "sg:postcode":"04693",
    "sg:province":"ME",
    "wof:name":"Bangor Savings Bank",
    "wof:placetype":"venue"
},
  "geometry": {"coordinates":[-68.083046,44.395184],"type":"Point"}
}