{
  "type": "Feature",
  "properties": {
    "addr:full":"1650 Stillwater Ave Bangor ME 04401",
    "addr:housenumber":"1650",
    "addr:postcode":"04401",
    "addr:street":"Stillwater Ave",
    "iso:country":"US",
    "sg:address":"1650 Stillwater Ave",
    "sg:city":"Bangor",
    "sg:classifiers":[
        {
            "category":"Building & Trades",
            "subcategory":"Landscaping Services",
            "type":"Services"
        }
    ],
    "sg:phone":"+1 207 990 2037",
    "sg:postcode":"04401",
    "sg:province":"ME",
    "sg:tags":[
        "landscape",
        "contractor"
    ],
    "wof:name":"Family Tree Landscaping",
    "wof:placetype":"venue"
},
  "geometry": {"coordinates":[-68.723365,44.861478],"type":"Point"}
}