{
  "type": "Feature",
  "properties": {
    "addr:full":"30 Mayflower Rd Hallowell ME 04347",
    "addr:housenumber":"30",
    "addr:postcode":"04347",
    "addr:street":"Mayflower Rd",
    "iso:country":"US",
    "sg:address":"30 Mayflower Rd",
    "sg:city":"Hallowell",
    "sg:classifiers":[
        {
            "category":"Social Services",
            "type":"Services"
        }
    ],
    "sg:phone":"+1 207 621 1023",
    "sg:postcode":"04347",
    "sg:province":"ME",
    "sg:tags":[
        "organization",
        "welfare"
    ],
    "wof:name":"Families Matter Inc",
    "wof:placetype":"venue"
},
  "geometry": {"coordinates":[-69.80312000000001,44.286574],"type":"Point"}
}