{
  "type": "Feature",
  "properties": {
    "iso:country":"US",
    "sg:address":"19 Montgomery St",
    "sg:city":"Bangor",
    "sg:classifiers":[
        {
            "category":"Professional",
            "subcategory":"Business Services",
            "type":"Services"
        }
    ],
    "sg:phone":"+1 207 942 0997",
    "sg:postcode":"04401",
    "sg:province":"ME",
    "wof:name":"Bradford Marlo Interiors",
    "wof:placetype":"venue"
},
  "geometry": {"coordinates":[-68.777793,44.812719],"type":"Point"}
}