{
  "type": "Feature",
  "properties": {
    "addr:full":"407 Main St Presque Isle ME 04769",
    "addr:housenumber":"407",
    "addr:postcode":"04769",
    "addr:street":"Main St",
    "iso:country":"US",
    "sg:address":"407 Main St",
    "sg:city":"Presque Isle",
    "sg:classifiers":[
        {
            "category":"Shopping",
            "subcategory":"Jewelry",
            "type":"Retail Goods"
        }
    ],
    "sg:phone":"+1 207 764 0309",
    "sg:postcode":"04769",
    "sg:province":"ME",
    "sg:tags":[
        "diamond"
    ],
    "wof:name":"Wilder's Jewelry Store",
    "wof:placetype":"venue"
},
  "geometry": {"coordinates":[-68.015541,46.681093],"type":"Point"}
}