{
  "type": "Feature",
  "properties": {
    "iso:country":"US",
    "sg:address":"13 Cottage St",
    "sg:city":"Bangor",
    "sg:classifiers":[
        {
            "category":"Building & Trades",
            "subcategory":"Construction",
            "type":"Services"
        }
    ],
    "sg:phone":"+1 207 864 9930",
    "sg:postcode":"04401",
    "sg:province":"ME",
    "sg:tags":[
        "contractor"
    ],
    "wof:name":"H&I Contractors",
    "wof:placetype":"venue"
},
  "geometry": {"coordinates":[-68.78524,44.807331],"type":"Point"}
}