{
  "type": "Feature",
  "properties": {
    "iso:country":"US",
    "sg:address":"20 East Ave",
    "sg:city":"Lewiston",
    "sg:classifiers":[
        {
            "category":"Building & Trades",
            "subcategory":"Equipment Rental",
            "type":"Services"
        }
    ],
    "sg:phone":"+1 207 783 7808",
    "sg:postcode":"04240",
    "sg:province":"ME",
    "sg:tags":[
        "yard"
    ],
    "wof:name":"Rent-A-Center",
    "wof:placetype":"venue"
},
  "geometry": {"coordinates":[-70.201066,44.08663],"type":"Point"}
}