{
  "type": "Feature",
  "properties": {
    "iso:country":"US",
    "sg:address":"10 Pierce St",
    "sg:city":"South Portland",
    "sg:classifiers":[
        {
            "category":"Retail",
            "subcategory":"Auto Repair",
            "type":"Services"
        }
    ],
    "sg:phone":"+1 207 767 1911",
    "sg:postcode":"04106",
    "sg:province":"ME",
    "sg:tags":[
        "repairing",
        "automobile"
    ],
    "wof:name":"Vance & Sons Garage",
    "wof:placetype":"venue"
},
  "geometry": {"coordinates":[-70.24203,43.644968],"type":"Point"}
}