{
  "type": "Feature",
  "properties": {
    "addr:full":"695 Roosevelt Trl Windham ME 04062",
    "addr:housenumber":"695",
    "addr:postcode":"04062",
    "addr:street":"Roosevelt Trl",
    "iso:country":"US",
    "sg:address":"695 Roosevelt Trl",
    "sg:city":"Windham",
    "sg:classifiers":[
        {
            "category":"Retail",
            "subcategory":"Auto Repair",
            "type":"Services"
        }
    ],
    "sg:phone":"+1 207 892 2833",
    "sg:postcode":"04062",
    "sg:province":"ME",
    "sg:tags":[
        "repairing",
        "automobile"
    ],
    "wof:name":"Lifetime Muffler & Brake",
    "wof:placetype":"venue"
},
  "geometry": {"coordinates":[-70.44770699999999,43.8474],"type":"Point"}
}