{
  "type": "Feature",
  "properties": {
    "iso:country":"US",
    "sg:address":"411 Congress St",
    "sg:city":"Portland",
    "sg:classifiers":[
        {
            "category":"Banks & Credit Unions",
            "subcategory":"Bank",
            "type":"Services"
        }
    ],
    "sg:phone":"+1 207 775 2620",
    "sg:postcode":"04101",
    "sg:province":"ME",
    "sg:tags":[
        "loan",
        "real estate"
    ],
    "wof:name":"Barton Mortgage Corp",
    "wof:placetype":"venue"
},
  "geometry": {"coordinates":[-70.25734799999999,43.65875],"type":"Point"}
}