{
  "type": "Feature",
  "properties": {
    "iso:country":"US",
    "sg:address":"1035 Lisbon St",
    "sg:city":"Lewiston",
    "sg:classifiers":[
        {
            "category":"Shopping",
            "subcategory":"Used Merchandise",
            "type":"Retail Goods"
        }
    ],
    "sg:phone":"+1 207 782 3050",
    "sg:postcode":"04240",
    "sg:province":"ME",
    "sg:tags":[
        "shop",
        "thrift"
    ],
    "sg:website":"www.ginne.org",
    "wof:name":"Goodwill Industries",
    "wof:placetype":"venue"
},
  "geometry": {"coordinates":[-70.19729599999999,44.08146],"type":"Point"}
}