{
  "type": "Feature",
  "properties": {
    "iso:country":"US",
    "sg:address":"22 Walnut St",
    "sg:city":"Millinocket",
    "sg:classifiers":[
        {
            "category":"Health Services",
            "subcategory":"Nursing And Care Facility",
            "type":"Services"
        }
    ],
    "sg:phone":"+1 207 723 4711",
    "sg:postcode":"04462",
    "sg:province":"ME",
    "sg:tags":[
        "home",
        "convalescent"
    ],
    "wof:name":"Katahdin Nursing Home",
    "wof:placetype":"venue"
},
  "geometry": {"coordinates":[-68.69316999999999,45.656848],"type":"Point"}
}