{
  "type": "Feature",
  "properties": {
    "iso:country":"US",
    "sg:address":"131 Orchard Dr",
    "sg:city":"Wilton",
    "sg:classifiers":[
        {
            "category":"Wholesale",
            "subcategory":"Durable Goods & Equipment",
            "type":"Manufacturing & Wholesale Goods"
        }
    ],
    "sg:phone":"+1 207 645 2238",
    "sg:postcode":"04294",
    "sg:province":"ME",
    "wof:name":"Pochepan Assoc Shaklee Pdts",
    "wof:placetype":"venue"
},
  "geometry": {"coordinates":[-70.227997,44.606003],"type":"Point"}
}