{
  "type": "Feature",
  "properties": {
    "iso:country":"US",
    "sg:address":"110 Mount Auburn Ave",
    "sg:city":"Auburn",
    "sg:classifiers":[
        {
            "category":"Shopping",
            "subcategory":"Department Store",
            "type":"Retail Goods"
        }
    ],
    "sg:phone":"+1 207 753 1300",
    "sg:postcode":"04210",
    "sg:province":"ME",
    "sg:tags":[
        "club",
        "wholesale"
    ],
    "wof:name":"Bj's Wholesale Club",
    "wof:placetype":"venue"
},
  "geometry": {"coordinates":[-70.241919,44.12246],"type":"Point"}
}