{
  "type": "Feature",
  "properties": {
    "addr:full":"613 Main St Jackman ME 04965",
    "addr:housenumber":"613",
    "addr:postcode":"04965",
    "addr:street":"Main St",
    "iso:country":"US",
    "sg:address":"613 Main St",
    "sg:city":"Jackman",
    "sg:classifiers":[
        {
            "category":"Banks & Credit Unions",
            "subcategory":"Bank",
            "type":"Services"
        }
    ],
    "sg:phone":"+1 207 668 2251",
    "sg:postcode":"04965",
    "sg:province":"ME",
    "wof:name":"Border Trust Co",
    "wof:placetype":"venue"
},
  "geometry": {"coordinates":[-69.39929100000001,44.837863],"type":"Point"}
}