{
  "type": "Feature",
  "properties": {
    "iso:country":"US",
    "sg:address":"16 Grammar Rd",
    "sg:city":"Sanford",
    "sg:classifiers":[
        {
            "category":"Organizations",
            "subcategory":"Religious Organization",
            "type":"Services"
        }
    ],
    "sg:phone":"+1 207 324 4750",
    "sg:postcode":"04073",
    "sg:province":"ME",
    "sg:tags":[
        "church"
    ],
    "wof:name":"Crossroads United Methodist",
    "wof:placetype":"venue"
},
  "geometry": {"coordinates":[-70.760977,43.458868],"type":"Point"}
}