{
  "type": "Feature",
  "properties": {
    "iso:country":"US",
    "sg:address":"917 Main St",
    "sg:city":"Monmouth",
    "sg:classifiers":[
        {
            "category":"Building & Trades",
            "subcategory":"Landscaping Services",
            "type":"Services"
        }
    ],
    "sg:phone":"+1 207 933 3450",
    "sg:postcode":"04259",
    "sg:province":"ME",
    "sg:tags":[
        "landscape",
        "contractor"
    ],
    "wof:name":"Yard Guards",
    "wof:placetype":"venue"
},
  "geometry": {"coordinates":[-70.031899,44.249756],"type":"Point"}
}