{
  "type": "Feature",
  "properties": {
    "addr:full":"1975 N Lisbon Rd Lewiston ME 04240",
    "addr:housenumber":"1975",
    "addr:postcode":"04240",
    "addr:street":"N Lisbon Rd",
    "iso:country":"US",
    "sg:address":"1975 N Lisbon Rd",
    "sg:city":"Lewiston",
    "sg:classifiers":[
        {
            "category":"Building & Trades",
            "subcategory":"Construction",
            "type":"Services"
        }
    ],
    "sg:phone":"+1 207 784 1735",
    "sg:postcode":"04240",
    "sg:province":"ME",
    "sg:tags":[
        "coping",
        "plastering",
        "tiling",
        "pool",
        "swimming"
    ],
    "wof:name":"Aqua Tech Pool & Spa",
    "wof:placetype":"venue"
},
  "geometry": {"coordinates":[-70.15773,44.064355],"type":"Point"}
}