{
  "type": "Feature",
  "properties": {
    "addr:full":"23 Main St Bethel ME 04217",
    "addr:housenumber":"23",
    "addr:postcode":"04217",
    "addr:street":"Main St",
    "iso:country":"US",
    "sg:address":"23 Main St",
    "sg:city":"Bethel",
    "sg:classifiers":[
        {
            "category":"Manufacturing",
            "subcategory":"Wood Products",
            "type":"Manufacturing & Wholesale Goods"
        }
    ],
    "sg:phone":"+1 207 824 2522",
    "sg:postcode":"04217",
    "sg:province":"ME",
    "wof:name":"Maine Line Products",
    "wof:placetype":"venue"
},
  "geometry": {"coordinates":[-70.790459,44.40484],"type":"Point"}
}