{
  "type": "Feature",
  "properties": {
    "iso:country":"US",
    "sg:address":"9 Timberline Rd",
    "sg:city":"Newry",
    "sg:classifiers":[
        {
            "category":"Restaurant",
            "type":"Food & Drink"
        }
    ],
    "sg:phone":"+1 207 824 2222",
    "sg:postcode":"04261",
    "sg:province":"ME",
    "sg:website":"www.phoenixhouseandwell.com",
    "wof:name":"Phoenix House & Well",
    "wof:placetype":"venue"
},
  "geometry": {"coordinates":[-70.852237,44.47341],"type":"Point"}
}