{
  "type": "Feature",
  "properties": {
    "iso:country":"US",
    "sg:address":"206 Maine St",
    "sg:city":"Brunswick",
    "sg:classifiers":[
        {
            "category":"Local Transit",
            "type":"Transportation"
        }
    ],
    "sg:phone":"+1 207 729 5301",
    "sg:postcode":"04011",
    "sg:province":"ME",
    "sg:tags":[
        "bus",
        "line"
    ],
    "wof:name":"Vermont Transit Co Inc",
    "wof:placetype":"venue"
},
  "geometry": {"coordinates":[-69.96343,43.91175],"type":"Point"}
}