{
  "type": "Feature",
  "properties": {
    "addr:full":"27 School St Houlton ME 04730",
    "addr:housenumber":"27",
    "addr:postcode":"04730",
    "addr:street":"School St",
    "iso:country":"US",
    "sg:address":"27 School St",
    "sg:city":"Houlton",
    "sg:classifiers":[
        {
            "category":"Education",
            "subcategory":"School",
            "type":"Public Place"
        }
    ],
    "sg:phone":"+1 207 532 0736",
    "sg:postcode":"04730",
    "sg:province":"ME",
    "sg:website":"www.ghca.com",
    "wof:name":"Greater Houlton Christian Acad",
    "wof:placetype":"venue"
},
  "geometry": {"coordinates":[-67.83822000000001,46.12372],"type":"Point"}
}