{
  "type": "Feature",
  "properties": {
    "iso:country":"US",
    "sg:address":"11 Corey Rd",
    "sg:city":"Cumberland Ctr",
    "sg:classifiers":[
        {
            "category":"Building & Trades",
            "subcategory":"Construction",
            "type":"Services"
        }
    ],
    "sg:phone":"+1 207 772 7663",
    "sg:postcode":"04021",
    "sg:province":"ME",
    "sg:tags":[
        "roofing",
        "contractor"
    ],
    "wof:name":"Portland Roofing Co",
    "wof:placetype":"venue"
},
  "geometry": {"coordinates":[-70.252698,43.775895],"type":"Point"}
}