{
  "type": "Feature",
  "properties": {
    "iso:country":"US",
    "sg:address":"228 Emerald Dr",
    "sg:city":"South Portland",
    "sg:classifiers":[
        {
            "category":"Professional",
            "subcategory":"Management & Consulting",
            "type":"Services"
        }
    ],
    "sg:phone":"+1 207 885 0653",
    "sg:postcode":"04106",
    "sg:province":"ME",
    "sg:tags":[
        "cosmetic",
        "selling",
        "clothing",
        "jewelry",
        "direct"
    ],
    "wof:name":"Avon",
    "wof:placetype":"venue"
},
  "geometry": {"coordinates":[-70.31721,43.612299],"type":"Point"}
}