{
  "type": "Feature",
  "properties": {
    "iso:country":"US",
    "sg:address":"8 South St",
    "sg:city":"Ellsworth",
    "sg:classifiers":[
        {
            "category":"Restaurant",
            "type":"Food & Drink"
        }
    ],
    "sg:phone":"+1 207 667 5077",
    "sg:postcode":"04605",
    "sg:province":"ME",
    "sg:website":"www.lobsterpot.com",
    "wof:name":"Union River Lobster Pot",
    "wof:placetype":"venue"
},
  "geometry": {"coordinates":[-68.427311,44.536568],"type":"Point"}
}