{
  "type": "Feature",
  "properties": {
    "iso:country":"US",
    "sg:address":"159 State St",
    "sg:city":"Portland",
    "sg:classifiers":[
        {
            "category":"Organizations",
            "subcategory":"Religious Organization",
            "type":"Services"
        }
    ],
    "sg:phone":"+1 207 774 6396",
    "sg:postcode":"04101",
    "sg:province":"ME",
    "sg:tags":[
        "church"
    ],
    "sg:website":"www.statestreetchurch.org",
    "wof:name":"State Street Church UCC",
    "wof:placetype":"venue"
},
  "geometry": {"coordinates":[-70.265219,43.652105],"type":"Point"}
}