{
  "type": "Feature",
  "properties": {
    "addr:full":"55 Front St Bath ME 04530",
    "addr:housenumber":"55",
    "addr:postcode":"04530",
    "addr:street":"Front St",
    "iso:country":"US",
    "sg:address":"55 Front St",
    "sg:city":"Bath",
    "sg:classifiers":[
        {
            "category":"Government",
            "subcategory":"Office",
            "type":"Public Place"
        }
    ],
    "sg:phone":"+1 207 443 8333",
    "sg:postcode":"04530",
    "sg:province":"ME",
    "sg:tags":[
        "village"
    ],
    "wof:name":"City Of Bath Voters Rgstrtn",
    "wof:placetype":"venue"
},
  "geometry": {"coordinates":[-69.814207,43.913443],"type":"Point"}
}