{
  "type": "Feature",
  "properties": {
    "iso:country":"US",
    "sg:address":"496 Wottons Mill Rd",
    "sg:city":"Union",
    "sg:classifiers":[
        {
            "category":"Building & Trades",
            "subcategory":"Construction",
            "type":"Services"
        }
    ],
    "sg:phone":"+1 207 785 2522",
    "sg:postcode":"04862",
    "sg:province":"ME",
    "sg:tags":[
        "house"
    ],
    "wof:name":"Maine Builder",
    "wof:placetype":"venue"
},
  "geometry": {"coordinates":[-69.224004,44.193971],"type":"Point"}
}