{
  "type": "Feature",
  "properties": {
    "iso:country":"US",
    "sg:address":"1 Government St",
    "sg:city":"Kittery",
    "sg:classifiers":[
        {
            "category":"Personal",
            "subcategory":"Beauty Salon",
            "type":"Services"
        }
    ],
    "sg:phone":"+1 207 451 9200",
    "sg:postcode":"03904",
    "sg:province":"ME",
    "sg:tags":[
        "treatment",
        "skin"
    ],
    "wof:name":"Cire Skin Care",
    "wof:placetype":"venue"
},
  "geometry": {"coordinates":[-70.74443599999999,43.085625],"type":"Point"}
}