{
  "type": "Feature",
  "properties": {
    "addr:full":"22 Snow Rd Scarborough ME 04074",
    "addr:housenumber":"22",
    "addr:postcode":"04074",
    "addr:street":"Snow Rd",
    "iso:country":"US",
    "sg:address":"22 Snow Rd",
    "sg:city":"Scarborough",
    "sg:classifiers":[
        {
            "category":"Building & Trades",
            "subcategory":"Electrical",
            "type":"Services"
        }
    ],
    "sg:phone":"+1 207 885 0030",
    "sg:postcode":"04074",
    "sg:province":"ME",
    "sg:tags":[
        "electric",
        "contractor"
    ],
    "wof:name":"Dube Electric",
    "wof:placetype":"venue"
},
  "geometry": {"coordinates":[-70.356469,43.545179],"type":"Point"}
}