{
  "type": "Feature",
  "properties": {
    "addr:full":"158 Pleasant Ave Portland ME 04103",
    "addr:housenumber":"158",
    "addr:postcode":"04103",
    "addr:street":"Pleasant Ave",
    "iso:country":"US",
    "sg:address":"158 Pleasant Ave",
    "sg:city":"Portland",
    "sg:classifiers":[
        {
            "category":"Professional",
            "subcategory":"Lawyer & Legal Services",
            "type":"Services"
        }
    ],
    "sg:phone":"+1 207 879 0708",
    "sg:postcode":"04103",
    "sg:province":"ME",
    "wof:name":"David Crocker",
    "wof:placetype":"venue"
},
  "geometry": {"coordinates":[-70.29309499999999,43.673829],"type":"Point"}
}