{
  "type": "Feature",
  "properties": {
    "addr:full":"165 Read St Portland ME 04103",
    "addr:housenumber":"165",
    "addr:postcode":"04103",
    "addr:street":"Read St",
    "iso:country":"US",
    "sg:address":"165 Read St",
    "sg:city":"Portland",
    "sg:classifiers":[
        {
            "category":"Freight",
            "type":"Transportation"
        }
    ],
    "sg:phone":"+1 207 773 7258",
    "sg:postcode":"04103",
    "sg:province":"ME",
    "sg:tags":[
        "warehouse",
        "storage"
    ],
    "wof:name":"Ameri Cold Logistics",
    "wof:placetype":"venue"
},
  "geometry": {"coordinates":[-70.28689199999999,43.683259],"type":"Point"}
}