{
  "type": "Feature",
  "properties": {
    "addr:full":"21 Park St Dover Foxcroft ME 04426",
    "addr:housenumber":"21",
    "addr:postcode":"04426",
    "addr:street":"Park St",
    "iso:country":"US",
    "sg:address":"21 Park St",
    "sg:city":"Dover Foxcroft",
    "sg:classifiers":[
        {
            "category":"Personal",
            "subcategory":"Beauty Salon",
            "type":"Services"
        }
    ],
    "sg:phone":"+1 207 564 8125",
    "sg:postcode":"04426",
    "sg:province":"ME",
    "sg:tags":[
        "shop"
    ],
    "wof:name":"Michael's Boutique",
    "wof:placetype":"venue"
},
  "geometry": {"coordinates":[-69.232912,45.190403],"type":"Point"}
}