{
  "type": "Feature",
  "properties": {
    "iso:country":"US",
    "sg:address":"348 S Hiram Rd",
    "sg:city":"Hiram",
    "sg:classifiers":[
        {
            "category":"Organizations",
            "subcategory":"Religious Organization",
            "type":"Services"
        }
    ],
    "sg:phone":"+1 207 625 4352",
    "sg:postcode":"04041",
    "sg:province":"ME",
    "sg:tags":[
        "church"
    ],
    "wof:name":"Calvary Bible Church",
    "wof:placetype":"venue"
},
  "geometry": {"coordinates":[-70.849287,43.80891],"type":"Point"}
}