{
  "type": "Feature",
  "properties": {
    "iso:country":"US",
    "sg:address":"2367 Congress St",
    "sg:city":"Portland",
    "sg:classifiers":[
        {
            "category":"Banks & Credit Unions",
            "subcategory":"Investment Brokerage",
            "type":"Services"
        }
    ],
    "sg:phone":"+1 207 773 3990",
    "sg:postcode":"04102",
    "sg:province":"ME",
    "sg:tags":[
        "advisory",
        "financial"
    ],
    "wof:name":"Cumberland Advisors Inc",
    "wof:placetype":"venue"
},
  "geometry": {"coordinates":[-70.340828,43.650731],"type":"Point"}
}