{
  "type": "Feature",
  "properties": {
    "addr:full":"79 Harlow St Brewer ME 04412",
    "addr:housenumber":"79",
    "addr:postcode":"04412",
    "addr:street":"Harlow St",
    "iso:country":"US",
    "sg:address":"79 Harlow St",
    "sg:city":"Brewer",
    "sg:classifiers":[
        {
            "category":"Arts & Performance",
            "subcategory":"Theater",
            "type":"Entertainment"
        }
    ],
    "sg:phone":"+1 207 989 2911",
    "sg:postcode":"04412",
    "sg:province":"ME",
    "sg:tags":[
        "group"
    ],
    "wof:name":"Beat Msters Prof Adio Entertai",
    "wof:placetype":"venue"
},
  "geometry": {"coordinates":[-68.755475,44.795173],"type":"Point"}
}