{
  "type": "Feature",
  "properties": {
    "addr:full":"183 Main St Lewiston ME 04240",
    "addr:housenumber":"183",
    "addr:postcode":"04240",
    "addr:street":"Main St",
    "iso:country":"US",
    "sg:address":"183 Main St",
    "sg:city":"Lewiston",
    "sg:classifiers":[
        {
            "category":"Health Services",
            "subcategory":"Clinic",
            "type":"Services"
        }
    ],
    "sg:phone":"+1 207 233 2333",
    "sg:postcode":"04240",
    "sg:province":"ME",
    "sg:tags":[
        "hypnotherapy"
    ],
    "wof:name":"Central Maine Hypnotherapy",
    "wof:placetype":"venue"
},
  "geometry": {"coordinates":[-70.21749199999999,44.099096],"type":"Point"}
}