{
  "type": "Feature",
  "properties": {
    "addr:full":"56 Mount Pleasant Ave Skowhegan ME 04976",
    "addr:housenumber":"56",
    "addr:postcode":"04976",
    "addr:street":"Mount Pleasant Ave",
    "iso:country":"US",
    "sg:address":"56 Mount Pleasant Ave",
    "sg:city":"Skowhegan",
    "sg:classifiers":[
        {
            "category":"Retail",
            "subcategory":"Repair Shop",
            "type":"Services"
        }
    ],
    "sg:phone":"+1 207 474 0410",
    "sg:postcode":"04976",
    "sg:province":"ME",
    "sg:tags":[
        "small",
        "engine"
    ],
    "wof:name":"Jims Quality Small Eng Repr",
    "wof:placetype":"venue"
},
  "geometry": {"coordinates":[-69.712183,44.766217],"type":"Point"}
}