{
  "type": "Feature",
  "properties": {
    "iso:country":"US",
    "sg:address":"59 H Rd",
    "sg:city":"Acton",
    "sg:classifiers":[
        {
            "category":"Organizations",
            "subcategory":"Religious Organization",
            "type":"Services"
        }
    ],
    "sg:phone":"+1 207 636 3430",
    "sg:postcode":"04001",
    "sg:province":"ME",
    "sg:tags":[
        "church"
    ],
    "wof:name":"Congregational United Church",
    "wof:placetype":"venue"
},
  "geometry": {"coordinates":[-70.909272,43.532664],"type":"Point"}
}