{
  "type": "Feature",
  "properties": {
    "iso:country":"US",
    "sg:address":"690 Minot Ave",
    "sg:city":"Auburn",
    "sg:classifiers":[
        {
            "category":"Health Services",
            "subcategory":"Health Practitioner",
            "type":"Services"
        }
    ],
    "sg:phone":"+1 207 783 3450",
    "sg:postcode":"04210",
    "sg:province":"ME",
    "sg:tags":[
        "therapist",
        "physical"
    ],
    "sg:website":"www.healthsouth.com",
    "wof:name":"Healthsouth Sports Medicine",
    "wof:placetype":"venue"
},
  "geometry": {"coordinates":[-70.255131,44.082015],"type":"Point"}
}