{
  "type": "Feature",
  "properties": {
    "addr:full":"2 Depot St Freeport ME 04032",
    "addr:housenumber":"2",
    "addr:postcode":"04032",
    "addr:street":"Depot St",
    "iso:country":"US",
    "sg:address":"2 Depot St",
    "sg:city":"Freeport",
    "sg:classifiers":[
        {
            "category":"Shopping",
            "subcategory":"Clothing, Apparel, & Fashions",
            "type":"Retail Goods"
        }
    ],
    "sg:phone":"+1 207 865 6740",
    "sg:postcode":"04032",
    "sg:province":"ME",
    "sg:tags":[
        "furnishing"
    ],
    "wof:name":"S&K Famous Brand Menswear",
    "wof:placetype":"venue"
},
  "geometry": {"coordinates":[-70.10129499999999,43.85666],"type":"Point"}
}