{
  "type": "Feature",
  "properties": {
    "addr:full":"386 Fore St Portland ME 04101",
    "addr:housenumber":"386",
    "addr:postcode":"04101",
    "addr:street":"Fore St",
    "iso:country":"US",
    "sg:address":"386 Fore St",
    "sg:city":"Portland",
    "sg:classifiers":[
        {
            "category":"Wholesale",
            "subcategory":"Drugs",
            "type":"Manufacturing & Wholesale Goods"
        }
    ],
    "sg:phone":"+1 207 772 5659",
    "sg:postcode":"04101",
    "sg:province":"ME",
    "sg:tags":[
        "aid",
        "product",
        "health",
        "beauty"
    ],
    "wof:name":"Milburn Marketing",
    "wof:placetype":"venue"
},
  "geometry": {"coordinates":[-70.25308699999999,43.656538],"type":"Point"}
}