{
  "type": "Feature",
  "properties": {
    "iso:country":"US",
    "sg:address":"409 Maine St",
    "sg:city":"Stoneham",
    "sg:classifiers":[
        {
            "category":"Food & Beverages",
            "subcategory":"Groceries & Convenience Stores",
            "type":"Retail Goods"
        }
    ],
    "sg:phone":"+1 207 928 2454",
    "sg:postcode":"04231",
    "sg:province":"ME",
    "wof:name":"A J's Everything",
    "wof:placetype":"venue"
},
  "geometry": {"coordinates":[-70.810264,44.249688],"type":"Point"}
}