{
  "type": "Feature",
  "properties": {
    "iso:country":"US",
    "sg:address":"47 Frederick St",
    "sg:city":"Portland",
    "sg:classifiers":[
        {
            "category":"Social Services",
            "subcategory":"Child Care",
            "type":"Services"
        }
    ],
    "sg:phone":"+1 207 773 0557",
    "sg:postcode":"04102",
    "sg:province":"ME",
    "sg:tags":[
        "day"
    ],
    "wof:name":"Kids Korner Child Care",
    "wof:placetype":"venue"
},
  "geometry": {"coordinates":[-70.285087,43.652601],"type":"Point"}
}