{
  "type": "Feature",
  "properties": {
    "iso:country":"US",
    "sg:address":"295 Carl Bailey Rd",
    "sg:city":"Bristol",
    "sg:classifiers":[
        {
            "category":"Building & Trades",
            "subcategory":"Construction",
            "type":"Services"
        }
    ],
    "sg:phone":"+1 207 677 3591",
    "sg:postcode":"04539",
    "sg:province":"ME",
    "sg:tags":[
        "house"
    ],
    "wof:name":"Dallas Emery",
    "wof:placetype":"venue"
},
  "geometry": {"coordinates":[-69.5262,43.936107],"type":"Point"}
}