{
  "type": "Feature",
  "properties": {
    "addr:full":"4 Fundy Rd Falmouth ME 04105",
    "addr:housenumber":"4",
    "addr:postcode":"04105",
    "addr:street":"Fundy Rd",
    "iso:country":"US",
    "sg:address":"4 Fundy Rd",
    "sg:city":"Falmouth",
    "sg:classifiers":[
        {
            "category":"Wholesale",
            "subcategory":"Chemicals & Plastics",
            "type":"Manufacturing & Wholesale Goods"
        }
    ],
    "sg:phone":"+1 207 781 5551",
    "sg:postcode":"04105",
    "sg:province":"ME",
    "sg:tags":[
        "oxygen"
    ],
    "wof:name":"Lincare",
    "wof:placetype":"venue"
},
  "geometry": {"coordinates":[-70.230289,43.718374],"type":"Point"}
}