{
  "type": "Feature",
  "properties": {
    "iso:country":"US",
    "sg:address":"33 Rigby Rd",
    "sg:city":"South Portland",
    "sg:classifiers":[
        {
            "category":"Utilities",
            "subcategory":"Refuse",
            "type":"Services"
        }
    ],
    "sg:phone":"+1 207 773 1122",
    "sg:postcode":"04106",
    "sg:province":"ME",
    "sg:tags":[
        "garbage",
        "collection"
    ],
    "sg:website":"www.pinetreewaste.com",
    "wof:name":"Pine Tree Waste",
    "wof:placetype":"venue"
},
  "geometry": {"coordinates":[-70.295801,43.626003],"type":"Point"}
}