{
  "type": "Feature",
  "properties": {
    "iso:country":"US",
    "sg:address":"113 Cottage St",
    "sg:city":"Bar Harbor",
    "sg:classifiers":[
        {
            "category":"Real Estate",
            "subcategory":"Real Estate Agent",
            "type":"Services"
        }
    ],
    "sg:phone":"+1 207 288 4656",
    "sg:postcode":"04609",
    "sg:province":"ME",
    "sg:tags":[
        "investment"
    ],
    "wof:name":"Mc Farland Realty Inc",
    "wof:placetype":"venue"
},
  "geometry": {"coordinates":[-68.212125,44.388812],"type":"Point"}
}