{
  "type": "Feature",
  "properties": {
    "iso:country":"US",
    "sg:address":"11 Pleasant Ridge Rd",
    "sg:city":"Camden",
    "sg:classifiers":[
        {
            "category":"Professional",
            "type":"Services"
        }
    ],
    "sg:phone":"+1 207 236 6070",
    "sg:postcode":"04843",
    "sg:province":"ME",
    "wof:name":"Tess Gerritsen Co",
    "wof:placetype":"venue"
},
  "geometry": {"coordinates":[-69.087877,44.221511],"type":"Point"}
}