{
  "type": "Feature",
  "properties": {
    "addr:full":"117 Bridge St Augusta ME 04330",
    "addr:housenumber":"117",
    "addr:postcode":"04330",
    "addr:street":"Bridge St",
    "iso:country":"US",
    "sg:address":"117 Bridge St",
    "sg:city":"Augusta",
    "sg:classifiers":[
        {
            "category":"Building & Trades",
            "subcategory":"Construction",
            "type":"Services"
        }
    ],
    "sg:phone":"+1 207 629 9496",
    "sg:postcode":"04330",
    "sg:province":"ME",
    "sg:tags":[
        "painter"
    ],
    "wof:name":"Gary's Painting",
    "wof:placetype":"venue"
},
  "geometry": {"coordinates":[-69.782735,44.318198],"type":"Point"}
}