{
  "type": "Feature",
  "properties": {
    "addr:full":"28 Federal St Brunswick ME 04011",
    "addr:housenumber":"28",
    "addr:postcode":"04011",
    "addr:street":"Federal St",
    "iso:country":"US",
    "sg:address":"28 Federal St",
    "sg:city":"Brunswick",
    "sg:classifiers":[
        {
            "category":"Government",
            "subcategory":"Office",
            "type":"Public Place"
        }
    ],
    "sg:phone":"+1 207 725 6639",
    "sg:postcode":"04011",
    "sg:province":"ME",
    "sg:tags":[
        "village"
    ],
    "wof:name":"Brunswick Natural Resources",
    "wof:placetype":"venue"
},
  "geometry": {"coordinates":[-69.96335999999999,43.916061],"type":"Point"}
}