{
  "type": "Feature",
  "properties": {
    "addr:full":"24 Ventura St Lewiston ME 04240",
    "addr:housenumber":"24",
    "addr:postcode":"04240",
    "addr:street":"Ventura St",
    "iso:country":"US",
    "sg:address":"24 Ventura St",
    "sg:city":"Lewiston",
    "sg:classifiers":[
        {
            "category":"Professional",
            "subcategory":"Accounting & Tax Preparation",
            "type":"Services"
        }
    ],
    "sg:phone":"+1 207 784 6884",
    "sg:postcode":"04240",
    "sg:province":"ME",
    "sg:tags":[
        "accountant"
    ],
    "wof:name":"Martin F Morgan Jr CPA",
    "wof:placetype":"venue"
},
  "geometry": {"coordinates":[-70.19202,44.116412],"type":"Point"}
}