{
  "type": "Feature",
  "properties": {
    "addr:full":"481 Alfred St Biddeford ME 04005",
    "addr:housenumber":"481",
    "addr:postcode":"04005",
    "addr:street":"Alfred St",
    "iso:country":"US",
    "sg:address":"481 Alfred St",
    "sg:city":"Biddeford",
    "sg:classifiers":[
        {
            "category":"Health Services",
            "subcategory":"Doctor",
            "type":"Services"
        }
    ],
    "sg:phone":"+1 207 283 4395",
    "sg:postcode":"04005",
    "sg:province":"ME",
    "sg:tags":[
        "physician",
        "surgeon"
    ],
    "wof:name":"George Abboud MD",
    "wof:placetype":"venue"
},
  "geometry": {"coordinates":[-70.490393,43.479071],"type":"Point"}
}