{
  "type": "Feature",
  "properties": {
    "iso:country":"US",
    "sg:address":"495 Roosevelt Trl",
    "sg:city":"Windham",
    "sg:classifiers":[
        {
            "category":"Home & Garden",
            "subcategory":"Household Appliances",
            "type":"Retail Goods"
        }
    ],
    "sg:phone":"+1 207 892 4501",
    "sg:postcode":"04062",
    "sg:province":"ME",
    "wof:name":"Atlantic Appliance Svc",
    "wof:placetype":"venue"
},
  "geometry": {"coordinates":[-70.432601,43.818086],"type":"Point"}
}