{
  "type": "Feature",
  "properties": {
    "iso:country":"US",
    "sg:address":"52 N High St",
    "sg:city":"Bridgton",
    "sg:classifiers":[
        {
            "category":"Organizations",
            "subcategory":"Non-profit Organization",
            "type":"Services"
        }
    ],
    "sg:phone":"+1 207 647 8396",
    "sg:postcode":"04009",
    "sg:province":"ME",
    "wof:name":"Landmark Human Resources",
    "wof:placetype":"venue"
},
  "geometry": {"coordinates":[-70.715163,44.054331],"type":"Point"}
}