{
  "type": "Feature",
  "properties": {
    "addr:full":"284 North Rd Detroit ME 04929",
    "addr:housenumber":"284",
    "addr:postcode":"04929",
    "addr:street":"North Rd",
    "iso:country":"US",
    "sg:address":"284 North Rd",
    "sg:city":"Detroit",
    "sg:classifiers":[
        {
            "category":"Autos & Motor Vehicles",
            "subcategory":"Automobile Sales",
            "type":"Retail Goods"
        }
    ],
    "sg:phone":"+1 207 487 3338",
    "sg:postcode":"04929",
    "sg:province":"ME",
    "sg:tags":[
        "snowmobile"
    ],
    "sg:website":"www.huffforestproducts.com",
    "wof:name":"Huff Forest Products",
    "wof:placetype":"venue"
},
  "geometry": {"coordinates":[-69.33751599999999,44.794708],"type":"Point"}
}