{
  "type": "Feature",
  "properties": {
    "addr:full":"45 Main St Beals ME 04694",
    "addr:housenumber":"45",
    "addr:postcode":"04694",
    "addr:street":"Main St",
    "iso:country":"US",
    "sg:address":"45 Main St",
    "sg:city":"Beals",
    "sg:phone":"+1 207 497 5477",
    "sg:postcode":"04694",
    "sg:province":"ME",
    "sg:tags":[
        "oil"
    ],
    "wof:name":"Carver Energy Fuels",
    "wof:placetype":"venue"
},
  "geometry": {"coordinates":[-67.40494,45.154657],"type":"Point"}
}