{
  "type": "Feature",
  "properties": {
    "addr:full":"89 County Rd Scarborough ME 04074",
    "addr:housenumber":"89",
    "addr:postcode":"04074",
    "addr:street":"County Rd",
    "iso:country":"US",
    "sg:address":"89 County Rd",
    "sg:city":"Scarborough",
    "sg:classifiers":[
        {
            "category":"Restaurant",
            "type":"Food & Drink"
        }
    ],
    "sg:phone":"+1 207 839 3040",
    "sg:postcode":"04074",
    "sg:province":"ME",
    "wof:name":"Pad Thai Restaurant",
    "wof:placetype":"venue"
},
  "geometry": {"coordinates":[-70.397711,43.642128],"type":"Point"}
}