{
  "type": "Feature",
  "properties": {
    "addr:full":"19 Pleasant St Freeport ME 04092",
    "addr:housenumber":"19",
    "addr:postcode":"04092",
    "addr:street":"Pleasant St",
    "iso:country":"US",
    "sg:address":"19 Pleasant St",
    "sg:city":"Freeport",
    "sg:classifiers":[
        {
            "category":"Education",
            "subcategory":"School",
            "type":"Public Place"
        }
    ],
    "sg:phone":"+1 207 865 6051",
    "sg:postcode":"04092",
    "sg:province":"ME",
    "sg:website":"www.freeportpublicschools.org",
    "wof:name":"Freeport Middle School",
    "wof:placetype":"venue"
},
  "geometry": {"coordinates":[-70.362222,43.676674],"type":"Point"}
}