{
  "type": "Feature",
  "properties": {
    "addr:full":"51 S Alpine St Oakland ME 04963",
    "addr:housenumber":"51",
    "addr:postcode":"04963",
    "addr:street":"S Alpine St",
    "iso:country":"US",
    "sg:address":"51 S Alpine St",
    "sg:city":"Oakland",
    "sg:classifiers":[
        {
            "category":"Building & Trades",
            "subcategory":"Construction",
            "type":"Services"
        }
    ],
    "sg:phone":"+1 207 465 8398",
    "sg:postcode":"04963",
    "sg:province":"ME",
    "sg:tags":[
        "painter"
    ],
    "wof:name":"Professional Fishing Systems",
    "wof:placetype":"venue"
},
  "geometry": {"coordinates":[-69.710953,44.543396],"type":"Point"}
}