{
  "type": "Feature",
  "properties": {
    "addr:full":"301 Capitol St Exd Augusta ME 04330",
    "addr:housenumber":"301",
    "addr:postcode":"04330",
    "addr:street":"Capitol St Exd",
    "iso:country":"US",
    "sg:address":"301 Capitol St Exd",
    "sg:city":"Augusta",
    "sg:classifiers":[
        {
            "category":"Real Estate",
            "subcategory":"Real Estate Operator",
            "type":"Services"
        }
    ],
    "sg:phone":"+1 207 626 0726",
    "sg:postcode":"04330",
    "sg:province":"ME",
    "sg:tags":[
        "apartment"
    ],
    "wof:name":"Pine View Estates",
    "wof:placetype":"venue"
},
  "geometry": {"coordinates":[-69.80404299999999,44.309242],"type":"Point"}
}