{
  "type": "Feature",
  "properties": {
    "addr:full":"250 Main St Westbrook ME 04092",
    "addr:housenumber":"250",
    "addr:postcode":"04092",
    "addr:street":"Main St",
    "iso:country":"US",
    "sg:address":"250 Main St",
    "sg:city":"Westbrook",
    "sg:classifiers":[
        {
            "category":"Freight",
            "type":"Transportation"
        }
    ],
    "sg:phone":"+1 207 712 0814",
    "sg:postcode":"04092",
    "sg:province":"ME",
    "sg:tags":[
        "operator",
        "trucking"
    ],
    "wof:name":"Oma Trucking",
    "wof:placetype":"venue"
},
  "geometry": {"coordinates":[-70.341105,43.679208],"type":"Point"}
}