{
  "type": "Feature",
  "properties": {
    "iso:country":"US",
    "sg:address":"61 Middle St",
    "sg:city":"Hallowell",
    "sg:classifiers":[
        {
            "category":"Professional",
            "subcategory":"Management & Consulting",
            "type":"Services"
        }
    ],
    "sg:phone":"+1 207 622 4036",
    "sg:postcode":"04347",
    "sg:province":"ME",
    "sg:tags":[
        "lobbying",
        "environmental"
    ],
    "wof:name":"John Bastey Envmtl Conslt",
    "wof:placetype":"venue"
},
  "geometry": {"coordinates":[-69.79475600000001,44.282886],"type":"Point"}
}