{
  "type": "Feature",
  "properties": {
    "addr:full":"26 North St Presque Isle ME 04769",
    "addr:housenumber":"26",
    "addr:postcode":"04769",
    "addr:street":"North St;Isle",
    "iso:country":"US",
    "sg:address":"26 North St",
    "sg:city":"Presque Isle",
    "sg:classifiers":[
        {
            "category":"Shopping",
            "subcategory":"Gifts & Souvenirs",
            "type":"Retail Goods"
        }
    ],
    "sg:phone":"+1 207 764 3625",
    "sg:postcode":"04769",
    "sg:province":"ME",
    "sg:tags":[
        "party",
        "supply"
    ],
    "wof:name":"D & D Decorating",
    "wof:placetype":"venue"
},
  "geometry": {"coordinates":[-68.005675,46.688234],"type":"Point"}
}