{
  "type": "Feature",
  "properties": {
    "addr:full":"195 Congress St Portland ME 04101",
    "addr:housenumber":"195",
    "addr:postcode":"04101",
    "addr:street":"Congress St",
    "iso:country":"US",
    "sg:address":"195 Congress St",
    "sg:city":"Portland",
    "sg:classifiers":[
        {
            "category":"Health Services",
            "subcategory":"Health Practitioner",
            "type":"Services"
        }
    ],
    "sg:phone":"+1 207 773 5778",
    "sg:postcode":"04101",
    "sg:province":"ME",
    "sg:tags":[
        "acupuncture"
    ],
    "wof:name":"Jade Trade",
    "wof:placetype":"venue"
},
  "geometry": {"coordinates":[-70.25100999999999,43.663435],"type":"Point"}
}