{
  "type": "Feature",
  "properties": {
    "iso:country":"US",
    "sg:address":"67 Turbatts Creek Rd",
    "sg:city":"Kennebunkport",
    "sg:classifiers":[
        {
            "category":"Home & Garden",
            "subcategory":"Home Furnishings",
            "type":"Retail Goods"
        }
    ],
    "sg:phone":"+1 207 967 4727",
    "sg:postcode":"04046",
    "sg:province":"ME",
    "sg:tags":[
        "stove",
        "wood",
        "burning"
    ],
    "wof:name":"Boucher Propane Svc",
    "wof:placetype":"venue"
},
  "geometry": {"coordinates":[-70.447985,43.356679],"type":"Point"}
}