{
  "type": "Feature",
  "properties": {
    "addr:full":"1216 Hammond St Bangor ME 04401",
    "addr:housenumber":"1216",
    "addr:postcode":"04401",
    "addr:street":"Hammond St",
    "iso:country":"US",
    "sg:address":"1216 Hammond St",
    "sg:city":"Bangor",
    "sg:classifiers":[
        {
            "category":"Wholesale",
            "subcategory":"Machinery & Supplies",
            "type":"Manufacturing & Wholesale Goods"
        }
    ],
    "sg:phone":"+1 207 945 5635",
    "sg:postcode":"04401",
    "sg:province":"ME",
    "sg:tags":[
        "contractor"
    ],
    "wof:name":"Nations Rent",
    "wof:placetype":"venue"
},
  "geometry": {"coordinates":[-68.826216,44.79192],"type":"Point"}
}