{
  "type": "Feature",
  "properties": {
    "iso:country":"US",
    "sg:address":"3225 Broadway",
    "sg:city":"Glenburn",
    "sg:classifiers":[
        {
            "category":"Restaurant",
            "type":"Food & Drink"
        }
    ],
    "sg:phone":"+1 207 942 4522",
    "sg:postcode":"04401",
    "sg:province":"ME",
    "wof:name":"Village Variety",
    "wof:placetype":"venue"
},
  "geometry": {"coordinates":[-68.877285,44.8922],"type":"Point"}
}