{
  "type": "Feature",
  "properties": {
    "iso:country":"US",
    "sg:address":"257 Harlow St",
    "sg:city":"Bangor",
    "sg:classifiers":[
        {
            "category":"Professional",
            "subcategory":"Computer Services",
            "type":"Services"
        }
    ],
    "sg:phone":"+1 207 942 2222",
    "sg:postcode":"04401",
    "sg:province":"ME",
    "sg:tags":[
        "consultant",
        "designer"
    ],
    "sg:website":"www.sunburysoftware.com",
    "wof:name":"Sunbury Group",
    "wof:placetype":"venue"
},
  "geometry": {"coordinates":[-68.773928,44.805372],"type":"Point"}
}