{
  "type": "Feature",
  "properties": {
    "addr:full":"389 E Main St Searsport ME 04974",
    "addr:housenumber":"389",
    "addr:postcode":"04974",
    "addr:street":"E Main St",
    "iso:country":"US",
    "sg:address":"389 E Main St",
    "sg:city":"Searsport",
    "sg:classifiers":[
        {
            "category":"Autos & Motor Vehicles",
            "subcategory":"Automobile Sales",
            "type":"Retail Goods"
        }
    ],
    "sg:phone":"+1 207 548 6199",
    "sg:postcode":"04974",
    "sg:province":"ME",
    "sg:tags":[
        "car",
        "dealer"
    ],
    "wof:name":"Greg's Auto Sales",
    "wof:placetype":"venue"
},
  "geometry": {"coordinates":[-68.886509,44.474024],"type":"Point"}
}