{
  "type": "Feature",
  "properties": {
    "addr:full":"8 Western Ave Kennebunk ME 04043",
    "addr:housenumber":"8",
    "addr:postcode":"04043",
    "addr:street":"Western Ave",
    "iso:country":"US",
    "sg:address":"8 Western Ave",
    "sg:city":"Kennebunk",
    "sg:classifiers":[
        {
            "category":"Shopping",
            "subcategory":"Jewelry",
            "type":"Retail Goods"
        }
    ],
    "sg:phone":"+1 207 967 6185",
    "sg:postcode":"04043",
    "sg:province":"ME",
    "wof:name":"Deep Blue Inc the",
    "wof:placetype":"venue"
},
  "geometry": {"coordinates":[-70.478438,43.360836],"type":"Point"}
}