{
  "type": "Feature",
  "properties": {
    "iso:country":"US",
    "sg:address":"145 Auburn St",
    "sg:city":"Portland",
    "sg:classifiers":[
        {
            "category":"Professional",
            "subcategory":"Accounting & Tax Preparation",
            "type":"Services"
        }
    ],
    "sg:phone":"+1 207 773 1040",
    "sg:postcode":"04103",
    "sg:province":"ME",
    "sg:tags":[
        "consultant"
    ],
    "wof:name":"Lewis Mc Donald Assoc",
    "wof:placetype":"venue"
},
  "geometry": {"coordinates":[-70.288961,43.701727],"type":"Point"}
}