{
  "type": "Feature",
  "properties": {
    "iso:country":"US",
    "sg:address":"77 Exchange St",
    "sg:city":"Bangor",
    "sg:classifiers":[
        {
            "category":"Banks & Credit Unions",
            "subcategory":"Investment Brokerage",
            "type":"Services"
        }
    ],
    "sg:phone":"+1 207 974 2200",
    "sg:postcode":"04401",
    "sg:province":"ME",
    "sg:tags":[
        "advisory",
        "financial"
    ],
    "wof:name":"Peoples Heritage Bank",
    "wof:placetype":"venue"
},
  "geometry": {"coordinates":[-68.767973,44.799733],"type":"Point"}
}