{
  "type": "Feature",
  "properties": {
    "iso:country":"US",
    "sg:address":"919 Upper St",
    "sg:city":"Turner",
    "sg:classifiers":[
        {
            "category":"Organizations",
            "subcategory":"Religious Organization",
            "type":"Services"
        }
    ],
    "sg:phone":"+1 207 369 0416",
    "sg:postcode":"04282",
    "sg:province":"ME",
    "wof:name":"LDS Missionaries",
    "wof:placetype":"venue"
},
  "geometry": {"coordinates":[-70.21627100000001,44.262691],"type":"Point"}
}