{
  "type": "Feature",
  "properties": {
    "iso:country":"US",
    "sg:address":"95 Alewive Rd",
    "sg:city":"Kennebunk",
    "sg:classifiers":[
        {
            "category":"Travel",
            "subcategory":"Hotels & Motels",
            "type":"Entertainment"
        }
    ],
    "sg:phone":"+1 207 985 9010",
    "sg:postcode":"04043",
    "sg:province":"ME",
    "wof:name":"Lodge Of Kennebunk",
    "wof:placetype":"venue"
},
  "geometry": {"coordinates":[-70.56309,43.407824],"type":"Point"}
}