{
  "type": "Feature",
  "properties": {
    "iso:country":"US",
    "sg:address":"30 Highland Ave",
    "sg:city":"Scarborough",
    "sg:classifiers":[
        {
            "category":"Manufacturing",
            "subcategory":"Metals",
            "type":"Manufacturing & Wholesale Goods"
        }
    ],
    "sg:phone":"+1 207 883 3368",
    "sg:postcode":"04074",
    "sg:province":"ME",
    "sg:tags":[
        "steel"
    ],
    "wof:name":"M & M Engineering",
    "wof:placetype":"venue"
},
  "geometry": {"coordinates":[-70.31746800000001,43.580223],"type":"Point"}
}