{
  "type": "Feature",
  "properties": {
    "addr:full":"35 Woodhaven Dr Kennebunk ME 04043",
    "addr:housenumber":"35",
    "addr:postcode":"04043",
    "addr:street":"Woodhaven Dr",
    "iso:country":"US",
    "sg:address":"35 Woodhaven Dr",
    "sg:city":"Kennebunk",
    "sg:classifiers":[
        {
            "category":"Utilities",
            "subcategory":"Telephone",
            "type":"Services"
        }
    ],
    "sg:phone":"+1 207 985 9997",
    "sg:postcode":"04043",
    "sg:province":"ME",
    "sg:tags":[
        "communications"
    ],
    "wof:name":"Webhanet Web Works",
    "wof:placetype":"venue"
},
  "geometry": {"coordinates":[-70.547111,43.396455],"type":"Point"}
}