{
  "type": "Feature",
  "properties": {
    "iso:country":"US",
    "sg:address":"78 Park St",
    "sg:city":"Dover Foxcroft",
    "sg:classifiers":[
        {
            "category":"Organizations",
            "subcategory":"Community Association",
            "type":"Services"
        }
    ],
    "sg:phone":"+1 207 564 8550",
    "sg:postcode":"04426",
    "sg:province":"ME",
    "sg:tags":[
        "military"
    ],
    "wof:name":"American Legion",
    "wof:placetype":"venue"
},
  "geometry": {"coordinates":[-69.254412,45.19752],"type":"Point"}
}