{
  "type": "Feature",
  "properties": {
    "iso:country":"US",
    "sg:address":"97 Center Conway Rd",
    "sg:city":"Brownfield",
    "sg:classifiers":[
        {
            "category":"Recreation",
            "type":"Entertainment"
        }
    ],
    "sg:phone":"+1 207 935 2008",
    "sg:postcode":"04010",
    "sg:province":"ME",
    "wof:name":"New England Guide",
    "wof:placetype":"venue"
},
  "geometry": {"coordinates":[-70.961513,43.936381],"type":"Point"}
}