{
  "type": "Feature",
  "properties": {
    "iso:country":"US",
    "sg:address":"156 Brentwood St",
    "sg:city":"Portland",
    "sg:classifiers":[
        {
            "category":"Retail",
            "subcategory":"Repair Shop",
            "type":"Services"
        }
    ],
    "sg:phone":"+1 207 774 2702",
    "sg:postcode":"04103",
    "sg:province":"ME",
    "sg:tags":[
        "repairing",
        "organs"
    ],
    "wof:name":"Nick Orso Organ Svc",
    "wof:placetype":"venue"
},
  "geometry": {"coordinates":[-70.30026700000001,43.677915],"type":"Point"}
}