{
  "type": "Feature",
  "properties": {
    "iso:country":"US",
    "sg:address":"98 Pleasant St",
    "sg:city":"Oxford",
    "sg:classifiers":[
        {
            "category":"Government",
            "subcategory":"Post Office",
            "type":"Public Place"
        }
    ],
    "sg:phone":"+1 207 539 4484",
    "sg:postcode":"04270",
    "sg:province":"ME",
    "wof:name":"US Post Office",
    "wof:placetype":"venue"
},
  "geometry": {"coordinates":[-70.495154,44.132185],"type":"Point"}
}