{
  "type": "Feature",
  "properties": {
    "iso:country":"US",
    "sg:address":"43 W Main St",
    "sg:city":"Dover Foxcroft",
    "sg:classifiers":[
        {
            "category":"Shopping",
            "subcategory":"Florist",
            "type":"Retail Goods"
        }
    ],
    "sg:phone":"+1 207 564 2701",
    "sg:postcode":"04426",
    "sg:province":"ME",
    "wof:name":"Bragdon's Flower Shop",
    "wof:placetype":"venue"
},
  "geometry": {"coordinates":[-69.235,45.185802],"type":"Point"}
}