{
  "type": "Feature",
  "properties": {
    "iso:country":"US",
    "sg:address":"12 Grindle Hill Rd",
    "sg:city":"Swans Island",
    "sg:classifiers":[
        {
            "category":"Wholesale",
            "subcategory":"Seafood",
            "type":"Manufacturing & Wholesale Goods"
        }
    ],
    "sg:phone":"+1 207 526 4251",
    "sg:postcode":"04685",
    "sg:province":"ME",
    "wof:name":"Carlton Joyce Inc",
    "wof:placetype":"venue"
},
  "geometry": {"coordinates":[-68.452973,44.155705],"type":"Point"}
}