{
  "type": "Feature",
  "properties": {
    "iso:country":"US",
    "sg:address":"19 Main St",
    "sg:city":"Livermore Falls",
    "sg:classifiers":[
        {
            "category":"Education",
            "subcategory":"School",
            "type":"Public Place"
        }
    ],
    "sg:phone":"+1 207 897 6384",
    "sg:postcode":"04254",
    "sg:province":"ME",
    "wof:name":"Livermore Falls Adult Ed",
    "wof:placetype":"venue"
},
  "geometry": {"coordinates":[-70.189769,44.472717],"type":"Point"}
}