{
  "type": "Feature",
  "properties": {
    "addr:full":"9 Sawyer Rd Hampden ME 04444",
    "addr:housenumber":"9",
    "addr:postcode":"04444",
    "addr:street":"Sawyer Rd",
    "iso:country":"US",
    "sg:address":"9 Sawyer Rd",
    "sg:city":"Hampden",
    "sg:classifiers":[
        {
            "category":"Shopping",
            "subcategory":"Florist",
            "type":"Retail Goods"
        }
    ],
    "sg:phone":"+1 207 862 3980",
    "sg:postcode":"04444",
    "sg:province":"ME",
    "wof:name":"Country Flowers & Accents",
    "wof:placetype":"venue"
},
  "geometry": {"coordinates":[-68.941402,44.743171],"type":"Point"}
}