{
  "type": "Feature",
  "properties": {
    "iso:country":"US",
    "sg:address":"5 School St",
    "sg:city":"Ellsworth",
    "sg:classifiers":[
        {
            "category":"Professional",
            "subcategory":"Lawyer & Legal Services",
            "type":"Services"
        }
    ],
    "sg:phone":"+1 207 667 0076",
    "sg:postcode":"04605",
    "sg:province":"ME",
    "sg:tags":[
        "attorney"
    ],
    "wof:name":"Ferinand A Slater",
    "wof:placetype":"venue"
},
  "geometry": {"coordinates":[-68.422386,44.542326],"type":"Point"}
}