{
  "type": "Feature",
  "properties": {
    "iso:country":"US",
    "sg:address":"741 Houlton Rd",
    "sg:city":"Baileyville",
    "sg:classifiers":[
        {
            "category":"Personal",
            "subcategory":"Beauty Salon",
            "type":"Services"
        }
    ],
    "sg:phone":"+1 207 427 3990",
    "sg:postcode":"04694",
    "sg:province":"ME",
    "wof:name":"Lad's & Lassies",
    "wof:placetype":"venue"
},
  "geometry": {"coordinates":[-67.405344,45.150453],"type":"Point"}
}