{
  "type": "Feature",
  "properties": {
    "iso:country":"US",
    "sg:address":"27 Ocean Ave",
    "sg:city":"Kennebunkport",
    "sg:classifiers":[
        {
            "category":"Shopping",
            "subcategory":"Gifts & Souvenirs",
            "type":"Retail Goods"
        }
    ],
    "sg:phone":"+1 207 967 2889",
    "sg:postcode":"04046",
    "sg:province":"ME",
    "sg:tags":[
        "shop"
    ],
    "wof:name":"Old Goose Gifts & Antiques",
    "wof:placetype":"venue"
},
  "geometry": {"coordinates":[-70.476747,43.361359],"type":"Point"}
}