{
  "type": "Feature",
  "properties": {
    "addr:full":"65 Canal St Rumford ME 04276",
    "addr:housenumber":"65",
    "addr:postcode":"04276",
    "addr:street":"Canal St",
    "iso:country":"US",
    "sg:address":"65 Canal St",
    "sg:city":"Rumford",
    "sg:classifiers":[
        {
            "category":"Travel",
            "subcategory":"Hotels & Motels",
            "type":"Entertainment"
        }
    ],
    "sg:phone":"+1 207 364 3621",
    "sg:postcode":"04276",
    "sg:province":"ME",
    "wof:name":"Hotel Rumford",
    "wof:placetype":"venue"
},
  "geometry": {"coordinates":[-70.544967,44.545822],"type":"Point"}
}