{
  "type": "Feature",
  "properties": {
    "addr:full":"8 Longview Ter Kennebunk ME 04043",
    "addr:housenumber":"8",
    "addr:postcode":"04043",
    "addr:street":"Longview Ter",
    "iso:country":"US",
    "sg:address":"8 Longview Ter",
    "sg:city":"Kennebunk",
    "sg:classifiers":[
        {
            "category":"Banks & Credit Unions",
            "subcategory":"Financial Services",
            "type":"Services"
        }
    ],
    "sg:phone":"+1 207 985 2895",
    "sg:postcode":"04043",
    "sg:province":"ME",
    "sg:tags":[
        "broker",
        "mortgage"
    ],
    "wof:name":"Integrity Mortgage Services",
    "wof:placetype":"venue"
},
  "geometry": {"coordinates":[-70.535698,43.391499],"type":"Point"}
}