{
  "type": "Feature",
  "properties": {
    "addr:full":"62 Portland Rd, Ste 8 Kennebunk ME 04043",
    "addr:housenumber":"62",
    "addr:postcode":"04043",
    "addr:street":"Portland Rd Ste 8",
    "iso:country":"US",
    "sg:address":"62 Portland Rd, Ste 8",
    "sg:city":"Kennebunk",
    "sg:classifiers":[
        {
            "category":"Banks & Credit Unions",
            "subcategory":"Investment Brokerage",
            "type":"Services"
        },
        {
            "category":"Banks & Credit Unions",
            "subcategory":"Financial Services",
            "type":"Services"
        }
    ],
    "sg:phone":"+1 207 985 6543",
    "sg:postcode":"04043",
    "sg:province":"ME",
    "sg:tags":[
        "investing",
        "advising"
    ],
    "sg:website":"www.ameripriseadvisors.com/jeffr...",
    "wof:name":"Jeffrey Bonney - Ameriprise Financial Advisor",
    "wof:placetype":"venue"
},
  "geometry": {"coordinates":[-70.531265,43.395579],"type":"Point"}
}