{
  "type": "Feature",
  "properties": {
    "iso:country":"US",
    "sg:address":"500 Congress St",
    "sg:city":"Portland",
    "sg:classifiers":[
        {
            "category":"Building & Trades",
            "subcategory":"Construction",
            "type":"Services"
        }
    ],
    "sg:phone":"+1 207 775 3652",
    "sg:postcode":"04101",
    "sg:province":"ME",
    "sg:tags":[
        "restoration",
        "preservation"
    ],
    "wof:name":"Maine Preservation",
    "wof:placetype":"venue"
},
  "geometry": {"coordinates":[-70.259692,43.657016],"type":"Point"}
}