{
  "type": "Feature",
  "properties": {
    "addr:full":"79 State St Augusta ME 04330",
    "addr:housenumber":"79",
    "addr:postcode":"04330",
    "addr:street":"State St",
    "iso:country":"US",
    "sg:address":"79 State St",
    "sg:city":"Augusta",
    "sg:classifiers":[
        {
            "category":"Government",
            "subcategory":"Office",
            "type":"Public Place"
        }
    ],
    "sg:phone":"+1 207 287 4447",
    "sg:postcode":"04330",
    "sg:province":"ME",
    "sg:tags":[
        "state",
        "inspection"
    ],
    "wof:name":"Employee Relations Bureau",
    "wof:placetype":"venue"
},
  "geometry": {"coordinates":[-69.77752,44.315094],"type":"Point"}
}