{
  "type": "Feature",
  "properties": {
    "iso:country":"US",
    "sg:address":"376 Maine Mall Rd",
    "sg:city":"South Portland",
    "sg:classifiers":[
        {
            "category":"Shopping",
            "subcategory":"Optical Goods",
            "type":"Retail Goods"
        }
    ],
    "sg:phone":"+1 207 773 3361",
    "sg:postcode":"04106",
    "sg:province":"ME",
    "wof:name":"Pro Vision Ctr",
    "wof:placetype":"venue"
},
  "geometry": {"coordinates":[-70.241918,43.649447],"type":"Point"}
}