{
  "type": "Feature",
  "properties": {
    "addr:full":"193 Pond Rd York ME 03908",
    "addr:housenumber":"193",
    "addr:postcode":"03908",
    "addr:street":"Pond Rd",
    "iso:country":"US",
    "sg:address":"193 Pond Rd",
    "sg:city":"York",
    "sg:classifiers":[
        {
            "category":"Building & Trades",
            "subcategory":"Construction",
            "type":"Services"
        }
    ],
    "sg:phone":"+1 207 351 3184",
    "sg:postcode":"03908",
    "sg:province":"ME",
    "sg:tags":[
        "contractor"
    ],
    "wof:name":"Fogg Bros Drywall",
    "wof:placetype":"venue"
},
  "geometry": {"coordinates":[-70.780435,43.254401],"type":"Point"}
}