{
  "type": "Feature",
  "properties": {
    "iso:country":"US",
    "sg:address":"46 Betton St",
    "sg:city":"Brewer",
    "sg:classifiers":[
        {
            "category":"Health Services",
            "subcategory":"Clinic",
            "type":"Services"
        }
    ],
    "sg:phone":"+1 207 989 5155",
    "sg:postcode":"04412",
    "sg:province":"ME",
    "sg:tags":[
        "home"
    ],
    "wof:name":"Arcadia Health Svc",
    "wof:placetype":"venue"
},
  "geometry": {"coordinates":[-68.763151,44.796579],"type":"Point"}
}