{
  "type": "Feature",
  "properties": {
    "addr:full":"263 Town Farm Rd New Gloucester ME 04260",
    "addr:housenumber":"263",
    "addr:postcode":"04260",
    "addr:street":"Town Farm Rd",
    "iso:country":"US",
    "sg:address":"263 Town Farm Rd",
    "sg:city":"New Gloucester",
    "sg:classifiers":[
        {
            "category":"Building & Trades",
            "subcategory":"Electrical",
            "type":"Services"
        }
    ],
    "sg:phone":"+1 207 926 5200",
    "sg:postcode":"04260",
    "sg:province":"ME",
    "sg:tags":[
        "electric",
        "contractor"
    ],
    "wof:name":"Scott Arnold",
    "wof:placetype":"venue"
},
  "geometry": {"coordinates":[-70.305313,43.935876],"type":"Point"}
}