{
  "type": "Feature",
  "properties": {
    "addr:full":"100 Main St Northeast Harbor ME 04662",
    "addr:housenumber":"100",
    "addr:postcode":"04662",
    "addr:street":"Main St Northeast",
    "iso:country":"US",
    "sg:address":"100 Main St",
    "sg:city":"Northeast Harbor",
    "sg:classifiers":[
        {
            "category":"Shopping",
            "subcategory":"Jewelry",
            "type":"Retail Goods"
        }
    ],
    "sg:phone":"+1 207 276 5000",
    "sg:postcode":"04662",
    "sg:province":"ME",
    "sg:tags":[
        "jeweler"
    ],
    "wof:name":"Samuel A Shaw Fine Jewelry",
    "wof:placetype":"venue"
},
  "geometry": {"coordinates":[-68.28896899999999,44.293448],"type":"Point"}
}