{
  "type": "Feature",
  "properties": {
    "iso:country":"US",
    "sg:address":"16 Whitten Rd",
    "sg:city":"Augusta",
    "sg:classifiers":[
        {
            "category":"Shopping",
            "subcategory":"Music",
            "type":"Retail Goods"
        }
    ],
    "sg:phone":"+1 207 623 0461",
    "sg:postcode":"04330",
    "sg:province":"ME",
    "sg:tags":[
        "compact",
        "record",
        "disc",
        "tape"
    ],
    "wof:name":"Sam Goody",
    "wof:placetype":"venue"
},
  "geometry": {"coordinates":[-69.812496,44.315693],"type":"Point"}
}