{
  "type": "Feature",
  "properties": {
    "iso:country":"US",
    "sg:address":"33 Stone St",
    "sg:city":"Augusta",
    "sg:classifiers":[
        {
            "category":"Government",
            "subcategory":"Office",
            "type":"Public Place"
        }
    ],
    "sg:phone":"+1 207 623 0724",
    "sg:postcode":"04330",
    "sg:province":"ME",
    "sg:tags":[
        "federal",
        "taxation"
    ],
    "wof:name":"US Internal Revenue Svc",
    "wof:placetype":"venue"
},
  "geometry": {"coordinates":[-69.765824,44.314254],"type":"Point"}
}