{
  "type": "Feature",
  "properties": {
    "iso:country":"US",
    "sg:address":"40 Pierce St",
    "sg:city":"Augusta",
    "sg:classifiers":[
        {
            "category":"Education",
            "subcategory":"Junior College",
            "type":"Public Place"
        }
    ],
    "sg:phone":"+1 207 626 2475",
    "sg:postcode":"04345",
    "sg:province":"ME",
    "sg:tags":[
        "technical",
        "institute"
    ],
    "sg:website":"www.augustaschools.com",
    "wof:name":"Capital Area Tech Ctr",
    "wof:placetype":"venue"
},
  "geometry": {"coordinates":[-69.77872,44.216469],"type":"Point"}
}