{
  "type": "Feature",
  "properties": {
    "iso:country":"US",
    "sg:address":"91 Mill St",
    "sg:city":"Orono",
    "sg:classifiers":[
        {
            "category":"Professional",
            "subcategory":"Research",
            "type":"Services"
        }
    ],
    "sg:phone":"+1 207 866 7892",
    "sg:postcode":"04473",
    "sg:province":"ME",
    "sg:tags":[
        "market",
        "analysis"
    ],
    "sg:website":"www.stillwaterresearch.com",
    "wof:name":"Stillwater Research",
    "wof:placetype":"venue"
},
  "geometry": {"coordinates":[-68.668819,44.882948],"type":"Point"}
}