{
  "type": "Feature",
  "properties": {
    "iso:country":"US",
    "sg:address":"1217 Stillwater Ave",
    "sg:city":"Bangor",
    "sg:classifiers":[
        {
            "category":"Building & Trades",
            "subcategory":"Construction",
            "type":"Services"
        }
    ],
    "sg:phone":"+1 207 942 7553",
    "sg:postcode":"04401",
    "sg:province":"ME",
    "sg:tags":[
        "general",
        "contractor"
    ],
    "wof:name":"S H Bridges Construction",
    "wof:placetype":"venue"
},
  "geometry": {"coordinates":[-68.740534,44.845232],"type":"Point"}
}