{
  "type": "Feature",
  "properties": {
    "iso:country":"US",
    "sg:address":"44 York St",
    "sg:city":"Caribou",
    "sg:classifiers":[
        {
            "category":"Building & Trades",
            "subcategory":"Electrical",
            "type":"Services"
        }
    ],
    "sg:phone":"+1 207 496 0192",
    "sg:postcode":"04736",
    "sg:province":"ME",
    "sg:tags":[
        "electric",
        "contractor"
    ],
    "wof:name":"Nichols Electric",
    "wof:placetype":"venue"
},
  "geometry": {"coordinates":[-68.022846,46.848765],"type":"Point"}
}