{
  "type": "Feature",
  "properties": {
    "addr:full":"5 Colcord Ave Camden ME 04843",
    "addr:housenumber":"5",
    "addr:postcode":"04843",
    "addr:street":"Colcord Ave",
    "iso:country":"US",
    "sg:address":"5 Colcord Ave",
    "sg:city":"Camden",
    "sg:classifiers":[
        {
            "category":"Manufacturing",
            "subcategory":"Electronics",
            "type":"Manufacturing & Wholesale Goods"
        }
    ],
    "sg:phone":"+1 207 236 3301",
    "sg:postcode":"04843",
    "sg:province":"ME",
    "sg:tags":[
        "coil",
        "transformer",
        "electronic"
    ],
    "sg:website":"www.tibbettsinc.com",
    "wof:name":"Tibbetts Industries Inc",
    "wof:placetype":"venue"
},
  "geometry": {"coordinates":[-69.067459,44.202373],"type":"Point"}
}