{
  "type": "Feature",
  "properties": {
    "addr:full":"22 Main St Topsham ME 04086",
    "addr:housenumber":"22",
    "addr:postcode":"04086",
    "addr:street":"Main St",
    "iso:country":"US",
    "sg:address":"22 Main St",
    "sg:city":"Topsham",
    "sg:classifiers":[
        {
            "category":"Home & Garden",
            "subcategory":"Home Furnishings",
            "type":"Retail Goods"
        }
    ],
    "sg:phone":"+1 207 729 5780",
    "sg:postcode":"04086",
    "sg:province":"ME",
    "sg:tags":[
        "curtain",
        "made",
        "drapery"
    ],
    "wof:name":"Window Dresser",
    "wof:placetype":"venue"
},
  "geometry": {"coordinates":[-69.96366500000001,43.924497],"type":"Point"}
}