{
  "type": "Feature",
  "properties": {
    "addr:full":"123 Rodman Rd Auburn ME 04210",
    "addr:housenumber":"123",
    "addr:postcode":"04210",
    "addr:street":"Rodman Rd",
    "iso:country":"US",
    "sg:address":"123 Rodman Rd",
    "sg:city":"Auburn",
    "sg:classifiers":[
        {
            "category":"Shopping",
            "type":"Retail Goods"
        }
    ],
    "sg:phone":"+1 207 786 0428",
    "sg:postcode":"04210",
    "sg:province":"ME",
    "sg:tags":[
        "chemical"
    ],
    "wof:name":"Itochu Chemicals America Inc",
    "wof:placetype":"venue"
},
  "geometry": {"coordinates":[-70.251936,44.071142],"type":"Point"}
}