{
  "type": "Feature",
  "properties": {
    "addr:full":"89 Hillside Ave Bangor ME 04401",
    "addr:housenumber":"89",
    "addr:postcode":"04401",
    "addr:street":"Hillside Ave",
    "iso:country":"US",
    "sg:address":"89 Hillside Ave",
    "sg:city":"Bangor",
    "sg:classifiers":[
        {
            "category":"Social Services",
            "subcategory":"Child Care",
            "type":"Services"
        }
    ],
    "sg:phone":"+1 207 947 4965",
    "sg:postcode":"04401",
    "sg:province":"ME",
    "sg:tags":[
        "day"
    ],
    "wof:name":"All Children's Day Care",
    "wof:placetype":"venue"
},
  "geometry": {"coordinates":[-68.779169,44.825476],"type":"Point"}
}