{
  "type": "Feature",
  "properties": {
    "iso:country":"US",
    "sg:address":"54 Central Ave",
    "sg:city":"Limerick",
    "sg:classifiers":[
        {
            "category":"Food & Beverages",
            "subcategory":"Groceries & Convenience Stores",
            "type":"Retail Goods"
        }
    ],
    "sg:phone":"+1 207 793 4335",
    "sg:postcode":"04048",
    "sg:province":"ME",
    "sg:tags":[
        "grocer"
    ],
    "wof:name":"Limerick Supermarket",
    "wof:placetype":"venue"
},
  "geometry": {"coordinates":[-70.783607,43.698845],"type":"Point"}
}