{
  "type": "Feature",
  "properties": {
    "addr:full":"20 Hartford St Houlton ME 04730",
    "addr:housenumber":"20",
    "addr:postcode":"04730",
    "addr:street":"Hartford St",
    "iso:country":"US",
    "sg:address":"20 Hartford St",
    "sg:city":"Houlton",
    "sg:classifiers":[
        {
            "category":"Health Services",
            "subcategory":"Doctor",
            "type":"Services"
        }
    ],
    "sg:phone":"+1 207 532 7936",
    "sg:postcode":"04730",
    "sg:province":"ME",
    "sg:tags":[
        "physician",
        "surgeon"
    ],
    "wof:name":"Aroostook County Surgical",
    "wof:placetype":"venue"
},
  "geometry": {"coordinates":[-67.842146,46.133875],"type":"Point"}
}