{
  "type": "Feature",
  "properties": {
    "addr:full":"45 Ox Bow Rd Palmyra ME 04965",
    "addr:housenumber":"45",
    "addr:postcode":"04965",
    "addr:street":"Ox Bow Rd",
    "iso:country":"US",
    "sg:address":"45 Ox Bow Rd",
    "sg:city":"Palmyra",
    "sg:classifiers":[
        {
            "category":"Retail",
            "subcategory":"Auto Repair",
            "type":"Services"
        }
    ],
    "sg:phone":"+1 207 368 4691",
    "sg:postcode":"04965",
    "sg:province":"ME",
    "sg:tags":[
        "repairing",
        "automobile"
    ],
    "wof:name":"Irish Auto Svc",
    "wof:placetype":"venue"
},
  "geometry": {"coordinates":[-69.310593,44.805677],"type":"Point"}
}