{
  "type": "Feature",
  "properties": {
    "iso:country":"US",
    "sg:address":"823 Commercial St",
    "sg:city":"Rockport",
    "sg:classifiers":[
        {
            "category":"Health Services",
            "subcategory":"Doctor",
            "type":"Services"
        }
    ],
    "sg:phone":"+1 207 596 6599",
    "sg:postcode":"04856",
    "sg:province":"ME",
    "sg:tags":[
        "physician",
        "surgeon"
    ],
    "wof:name":"Neil D Smith MD",
    "wof:placetype":"venue"
},
  "geometry": {"coordinates":[-69.088819,44.144145],"type":"Point"}
}