{
  "type": "Feature",
  "properties": {
    "addr:full":"26 Searsport Ave Belfast ME 04974",
    "addr:housenumber":"26",
    "addr:postcode":"04974",
    "addr:street":"Searsport Ave",
    "iso:country":"US",
    "sg:address":"26 Searsport Ave",
    "sg:city":"Belfast",
    "sg:classifiers":[
        {
            "category":"Shopping",
            "subcategory":"Gifts & Souvenirs",
            "type":"Retail Goods"
        }
    ],
    "sg:phone":"+1 207 338 0031",
    "sg:postcode":"04974",
    "sg:province":"ME",
    "sg:tags":[
        "shop"
    ],
    "wof:name":"Sea Witch",
    "wof:placetype":"venue"
},
  "geometry": {"coordinates":[-68.973738,44.429668],"type":"Point"}
}