{
  "type": "Feature",
  "properties": {
    "addr:full":"12 Atlantic Ave Bar Harbor ME 04609",
    "addr:housenumber":"12",
    "addr:postcode":"04609",
    "addr:street":"Atlantic Ave",
    "iso:country":"US",
    "sg:address":"12 Atlantic Ave",
    "sg:city":"Bar Harbor",
    "sg:classifiers":[
        {
            "category":"Travel",
            "subcategory":"Hotels & Motels",
            "type":"Entertainment"
        }
    ],
    "sg:phone":"+1 207 288 5548",
    "sg:postcode":"04609",
    "sg:province":"ME",
    "wof:name":"Town Motel & Moseley Cottage",
    "wof:placetype":"venue"
},
  "geometry": {"coordinates":[-68.20212600000001,44.38679],"type":"Point"}
}