{
  "type": "Feature",
  "properties": {
    "iso:country":"US",
    "sg:address":"12 Atlantic Ave",
    "sg:city":"Bar Harbor",
    "sg:classifiers":[
        {
            "category":"Travel",
            "subcategory":"Hotels & Motels",
            "type":"Entertainment"
        }
    ],
    "sg:phone":"+1 207 288 5548",
    "sg:postcode":"04609",
    "sg:province":"ME",
    "wof:name":"Town Motel & Moseley Cottage",
    "wof:placetype":"venue"
},
  "geometry": {"coordinates":[-68.202126,44.38679],"type":"Point"}
}