{
  "type": "Feature",
  "properties": {
    "iso:country":"US",
    "sg:address":"11 Portland Street Pier",
    "sg:city":"South Portland",
    "sg:classifiers":[
        {
            "category":"Travel",
            "subcategory":"Travel Agent",
            "type":"Entertainment"
        }
    ],
    "sg:phone":"+1 207 799 2266",
    "sg:postcode":"04106",
    "sg:province":"ME",
    "sg:tags":[
        "agency",
        "bureau"
    ],
    "wof:name":"Soule Travel & Cruise Ctr",
    "wof:placetype":"venue"
},
  "geometry": {"coordinates":[-70.242521,43.650308],"type":"Point"}
}