{
  "type": "Feature",
  "properties": {
    "addr:full":"27 Job Rd Standish ME 04084",
    "addr:housenumber":"27",
    "addr:postcode":"04084",
    "addr:street":"Job Rd",
    "iso:country":"US",
    "sg:address":"27 Job Rd",
    "sg:city":"Standish",
    "sg:classifiers":[
        {
            "category":"Building & Trades",
            "subcategory":"Construction",
            "type":"Services"
        }
    ],
    "sg:phone":"+1 207 671 6557",
    "sg:postcode":"04084",
    "sg:province":"ME",
    "sg:tags":[
        "siding",
        "contractor"
    ],
    "wof:name":"Knudsen Knudsen Construction",
    "wof:placetype":"venue"
},
  "geometry": {"coordinates":[-70.570447,43.743568],"type":"Point"}
}