{
  "type": "Feature",
  "properties": {
    "iso:country":"US",
    "sg:address":"93 Raydon Rd Exd",
    "sg:city":"York",
    "sg:classifiers":[
        {
            "category":"Freight",
            "type":"Transportation"
        }
    ],
    "sg:phone":"+1 207 363 0020",
    "sg:postcode":"03909",
    "sg:province":"ME",
    "sg:tags":[
        "special"
    ],
    "wof:name":"Heritage Storage Center",
    "wof:placetype":"venue"
},
  "geometry": {"coordinates":[-70.65833000000001,43.151596],"type":"Point"}
}