{
  "type": "Feature",
  "properties": {
    "addr:full":"491 Main St Rockland ME 04841",
    "addr:housenumber":"491",
    "addr:postcode":"04841",
    "addr:street":"Main St",
    "iso:country":"US",
    "sg:address":"491 Main St",
    "sg:city":"Rockland",
    "sg:classifiers":[
        {
            "category":"Retail",
            "subcategory":"Photofinishing",
            "type":"Services"
        }
    ],
    "sg:phone":"+1 207 594 5010",
    "sg:postcode":"04841",
    "sg:province":"ME",
    "sg:tags":[
        "photo",
        "finishing"
    ],
    "wof:name":"PDQ Prints Done Quickly",
    "wof:placetype":"venue"
},
  "geometry": {"coordinates":[-69.10945,44.106989],"type":"Point"}
}