{
  "type": "Feature",
  "properties": {
    "addr:full":"6 Boynton St Eastport ME 04631",
    "addr:housenumber":"6",
    "addr:postcode":"04631",
    "addr:street":"Boynton St",
    "iso:country":"US",
    "sg:address":"6 Boynton St",
    "sg:city":"Eastport",
    "sg:classifiers":[
        {
            "category":"Real Estate",
            "subcategory":"Real Estate Agent",
            "type":"Services"
        }
    ],
    "sg:phone":"+1 207 853 2777",
    "sg:postcode":"04631",
    "sg:province":"ME",
    "wof:name":"Spinnaker Realty",
    "wof:placetype":"venue"
},
  "geometry": {"coordinates":[-66.985911,44.905047],"type":"Point"}
}