{
  "type": "Feature",
  "properties": {
    "addr:full":"17 Laffin Dr Westbrook ME 04092",
    "addr:housenumber":"17",
    "addr:postcode":"04092",
    "addr:street":"Laffin Dr",
    "iso:country":"US",
    "sg:address":"17 Laffin Dr",
    "sg:city":"Westbrook",
    "sg:classifiers":[
        {
            "category":"Social Services",
            "subcategory":"Child Care",
            "type":"Services"
        }
    ],
    "sg:phone":"+1 207 854 2678",
    "sg:postcode":"04092",
    "sg:province":"ME",
    "sg:tags":[
        "day"
    ],
    "wof:name":"Aunt Dis Day Care",
    "wof:placetype":"venue"
},
  "geometry": {"coordinates":[-70.35023700000001,43.667405],"type":"Point"}
}