{
  "type": "Feature",
  "properties": {
    "iso:country":"US",
    "sg:address":"1810 Post Rd",
    "sg:city":"Wells",
    "sg:classifiers":[
        {
            "category":"Shopping",
            "subcategory":"Used Merchandise",
            "type":"Retail Goods"
        }
    ],
    "sg:phone":"+1 207 641 8696",
    "sg:postcode":"04090",
    "sg:province":"ME",
    "sg:tags":[
        "antique"
    ],
    "wof:name":"Anderson & Kelley Antiques",
    "wof:placetype":"venue"
},
  "geometry": {"coordinates":[-70.571994,43.331907],"type":"Point"}
}