{
  "type": "Feature",
  "properties": {
    "iso:country":"US",
    "sg:address":"945 Congress St",
    "sg:city":"Portland",
    "sg:classifiers":[
        {
            "category":"Shopping",
            "subcategory":"Discount & Variety Stores",
            "type":"Retail Goods"
        }
    ],
    "sg:phone":"+1 207 772 8688",
    "sg:postcode":"04102",
    "sg:province":"ME",
    "sg:tags":[
        "post",
        "trading"
    ],
    "wof:name":"Asian Trading Co",
    "wof:placetype":"venue"
},
  "geometry": {"coordinates":[-70.279228,43.653665],"type":"Point"}
}