{
  "type": "Feature",
  "properties": {
    "iso:country":"US",
    "sg:address":"2804 Middle Rd",
    "sg:city":"Augusta",
    "sg:classifiers":[
        {
            "category":"Professional",
            "subcategory":"Secretarial Services",
            "type":"Services"
        }
    ],
    "sg:phone":"+1 207 547 3528",
    "sg:postcode":"04330",
    "sg:province":"ME",
    "sg:tags":[
        "court",
        "reporter"
    ],
    "wof:name":"Constance Warren",
    "wof:placetype":"venue"
},
  "geometry": {"coordinates":[-69.75315,44.427872],"type":"Point"}
}