{
  "type": "Feature",
  "properties": {
    "iso:country":"US",
    "sg:address":"140 Academy St",
    "sg:city":"Presque Isle",
    "sg:classifiers":[
        {
            "category":"Health Services",
            "subcategory":"Doctor",
            "type":"Services"
        }
    ],
    "sg:phone":"+1 207 768 4335",
    "sg:postcode":"04769",
    "sg:province":"ME",
    "sg:tags":[
        "physician",
        "surgeon"
    ],
    "sg:website":"www.tamc.org",
    "wof:name":"Horizons Health Svc",
    "wof:placetype":"venue"
},
  "geometry": {"coordinates":[-67.998941,46.676684],"type":"Point"}
}