{
  "type": "Feature",
  "properties": {
    "iso:country":"US",
    "sg:address":"585 Walnut Hill Rd",
    "sg:city":"North Yarmouth",
    "sg:classifiers":[
        {
            "category":"Building & Trades",
            "subcategory":"Construction",
            "type":"Services"
        }
    ],
    "sg:phone":"+1 207 829 3455",
    "sg:postcode":"04097",
    "sg:province":"ME",
    "sg:tags":[
        "paving",
        "contractor"
    ],
    "wof:name":"Casco Bay Paving & Constr Inc",
    "wof:placetype":"venue"
},
  "geometry": {"coordinates":[-70.255109,43.835833],"type":"Point"}
}