{
  "type": "Feature",
  "properties": {
    "addr:full":"167 Stream Rd Winterport ME 04496",
    "addr:housenumber":"167",
    "addr:postcode":"04496",
    "addr:street":"Stream Rd",
    "iso:country":"US",
    "sg:address":"167 Stream Rd",
    "sg:city":"Winterport",
    "sg:classifiers":[
        {
            "category":"Home & Garden",
            "subcategory":"Building Materials",
            "type":"Retail Goods"
        }
    ],
    "sg:phone":"+1 207 223 2556",
    "sg:postcode":"04496",
    "sg:province":"ME",
    "sg:tags":[
        "glass",
        "leaded"
    ],
    "wof:name":"Borestone Studio",
    "wof:placetype":"venue"
},
  "geometry": {"coordinates":[-68.90400699999999,44.644718],"type":"Point"}
}