{
  "type": "Feature",
  "properties": {
    "iso:country":"US",
    "sg:address":"1120 Center St",
    "sg:city":"Auburn",
    "sg:classifiers":[
        {
            "category":"Insurance",
            "subcategory":"Insurance Agent",
            "type":"Services"
        }
    ],
    "sg:phone":"+1 207 784 1535",
    "sg:postcode":"04210",
    "sg:province":"ME",
    "sg:website":"www.healeyassociates.com",
    "wof:name":"Healey & Assoc Inc",
    "wof:placetype":"venue"
},
  "geometry": {"coordinates":[-70.22633399999999,44.139806],"type":"Point"}
}