{
  "type": "Feature",
  "properties": {
    "iso:country":"US",
    "sg:address":"127 Oxford St",
    "sg:city":"Portland",
    "sg:classifiers":[
        {
            "category":"Freight",
            "type":"Transportation"
        }
    ],
    "sg:phone":"+1 207 775 5876",
    "sg:postcode":"04101",
    "sg:province":"ME",
    "sg:tags":[
        "mover"
    ],
    "sg:website":"www.noyesmoving.com",
    "wof:name":"Earle W Noyes & Sons",
    "wof:placetype":"venue"
},
  "geometry": {"coordinates":[-70.258046,43.661474],"type":"Point"}
}