{
  "type": "Feature",
  "properties": {
    "iso:country":"US",
    "sg:address":"41 Maplewood St",
    "sg:city":"Portland",
    "sg:classifiers":[
        {
            "category":"Professional",
            "subcategory":"Management & Consulting",
            "type":"Services"
        }
    ],
    "sg:phone":"+1 207 878 5374",
    "sg:postcode":"04103",
    "sg:province":"ME",
    "sg:tags":[
        "business"
    ],
    "wof:name":"Bridges Consulting",
    "wof:placetype":"venue"
},
  "geometry": {"coordinates":[-70.288614,43.697768],"type":"Point"}
}