{
  "type": "Feature",
  "properties": {
    "addr:full":"1 Bates St Guilford ME 04443",
    "addr:housenumber":"1",
    "addr:postcode":"04443",
    "addr:street":"Bates St",
    "iso:country":"US",
    "sg:address":"1 Bates St",
    "sg:city":"Guilford",
    "sg:classifiers":[
        {
            "category":"Restaurant",
            "type":"Food & Drink"
        }
    ],
    "sg:phone":"+1 207 876 1111",
    "sg:postcode":"04443",
    "sg:province":"ME",
    "wof:name":"Subway Sandwiches & Salads",
    "wof:placetype":"venue"
},
  "geometry": {"coordinates":[-69.387874,45.16717],"type":"Point"}
}