{
  "type": "Feature",
  "properties": {
    "iso:country":"US",
    "sg:address":"326 Main St",
    "sg:city":"Cumberland Ctr",
    "sg:classifiers":[
        {
            "category":"Health Services",
            "subcategory":"Doctor",
            "type":"Services"
        }
    ],
    "sg:phone":"+1 207 829 5937",
    "sg:postcode":"04021",
    "sg:province":"ME",
    "sg:tags":[
        "dentist"
    ],
    "wof:name":"Cumberland Dental Arts",
    "wof:placetype":"venue"
},
  "geometry": {"coordinates":[-70.25542299999999,43.800425],"type":"Point"}
}