{
  "type": "Feature",
  "properties": {
    "addr:full":"136 Commercial St Portland ME 04101",
    "addr:housenumber":"136",
    "addr:postcode":"04101",
    "addr:street":"Commercial St",
    "iso:country":"US",
    "sg:address":"136 Commercial St",
    "sg:city":"Portland",
    "sg:classifiers":[
        {
            "category":"Health Services",
            "subcategory":"Health Practitioner",
            "type":"Services"
        }
    ],
    "sg:phone":"+1 207 772 3800",
    "sg:postcode":"04101",
    "sg:province":"ME",
    "wof:name":"Health Alternative Physcl Svcs",
    "wof:placetype":"venue"
},
  "geometry": {"coordinates":[-70.252042,43.656147],"type":"Point"}
}