{
  "type": "Feature",
  "properties": {
    "addr:full":"187 Sawyer St South Portland ME 04106",
    "addr:housenumber":"187",
    "addr:postcode":"04106",
    "addr:street":"Sawyer St",
    "iso:country":"US",
    "sg:address":"187 Sawyer St",
    "sg:city":"South Portland",
    "sg:classifiers":[
        {
            "category":"Building & Trades",
            "subcategory":"Equipment Rental",
            "type":"Services"
        }
    ],
    "sg:phone":"+1 207 799 1541",
    "sg:postcode":"04106",
    "sg:province":"ME",
    "sg:tags":[
        "crane"
    ],
    "wof:name":"Fred I Merrill Inc",
    "wof:placetype":"venue"
},
  "geometry": {"coordinates":[-70.24010699999999,43.64419],"type":"Point"}
}