{
  "type": "Feature",
  "properties": {
    "addr:full":"27 Louise St Auburn ME 04210",
    "addr:housenumber":"27",
    "addr:postcode":"04210",
    "addr:street":"Louise St",
    "iso:country":"US",
    "sg:address":"27 Louise St",
    "sg:city":"Auburn",
    "sg:classifiers":[
        {
            "category":"Insurance",
            "subcategory":"Insurance Agent",
            "type":"Services"
        }
    ],
    "sg:phone":"+1 207 786 3307",
    "sg:postcode":"04210",
    "sg:province":"ME",
    "wof:name":"Us Allianz Securities",
    "wof:placetype":"venue"
},
  "geometry": {"coordinates":[-70.22168600000001,44.073668],"type":"Point"}
}