{
  "type": "Feature",
  "properties": {
    "iso:country":"US",
    "sg:address":"660 Brighton Ave",
    "sg:city":"Portland",
    "sg:classifiers":[
        {
            "category":"Health Services",
            "subcategory":"Doctor",
            "type":"Services"
        }
    ],
    "sg:phone":"+1 207 773 6448",
    "sg:postcode":"04102",
    "sg:province":"ME",
    "sg:tags":[
        "dentist"
    ],
    "wof:name":"C Leighton Philbrick DDS",
    "wof:placetype":"venue"
},
  "geometry": {"coordinates":[-70.30543299999999,43.670148],"type":"Point"}
}