{
  "type": "Feature",
  "properties": {
    "addr:full":"136 Academy St Presque Isle ME 04769",
    "addr:housenumber":"136",
    "addr:postcode":"04769",
    "addr:street":"Academy St",
    "iso:country":"US",
    "sg:address":"136 Academy St",
    "sg:city":"Presque Isle",
    "sg:classifiers":[
        {
            "category":"Health Services",
            "subcategory":"Doctor",
            "type":"Services"
        }
    ],
    "sg:phone":"+1 207 764 3917",
    "sg:postcode":"04769",
    "sg:province":"ME",
    "sg:tags":[
        "physician",
        "surgeon"
    ],
    "wof:name":"Stephen Wood MD",
    "wof:placetype":"venue"
},
  "geometry": {"coordinates":[-67.99987900000001,46.676732],"type":"Point"}
}