{
  "type": "Feature",
  "properties": {
    "iso:country":"US",
    "sg:address":"1043 N Main St",
    "sg:city":"Brewer",
    "sg:classifiers":[
        {
            "category":"Travel",
            "subcategory":"Hotels & Motels",
            "type":"Entertainment"
        }
    ],
    "sg:phone":"+1 207 989 2620",
    "sg:postcode":"04412",
    "sg:province":"ME",
    "wof:name":"Air-Line Motor Inn",
    "wof:placetype":"venue"
},
  "geometry": {"coordinates":[-68.716328,44.819432],"type":"Point"}
}