{
  "type": "Feature",
  "properties": {
    "addr:full":"8 Stewart Dr Corinna ME 04983",
    "addr:housenumber":"8",
    "addr:postcode":"04983",
    "addr:street":"Stewart Dr",
    "iso:country":"US",
    "sg:address":"8 Stewart Dr",
    "sg:city":"Corinna",
    "sg:classifiers":[
        {
            "category":"Education",
            "subcategory":"Library",
            "type":"Public Place"
        }
    ],
    "sg:phone":"+1 207 278 2454",
    "sg:postcode":"04983",
    "sg:province":"ME",
    "wof:name":"Stewart Free Library",
    "wof:placetype":"venue"
},
  "geometry": {"coordinates":[-70.21941,44.808568],"type":"Point"}
}