{
  "type": "Feature",
  "properties": {
    "iso:country":"US",
    "sg:address":"331 Warren Ave",
    "sg:city":"Portland",
    "sg:classifiers":[
        {
            "category":"Recreation",
            "type":"Entertainment"
        }
    ],
    "sg:phone":"+1 207 797 8207",
    "sg:postcode":"04103",
    "sg:province":"ME",
    "sg:tags":[
        "skating",
        "rink"
    ],
    "wof:name":"Happy Wheels Skate Ctr",
    "wof:placetype":"venue"
},
  "geometry": {"coordinates":[-70.312009,43.687555],"type":"Point"}
}