{
  "type": "Feature",
  "properties": {
    "iso:country":"US",
    "sg:address":"60 Lloyds Ln",
    "sg:city":"Windham",
    "sg:classifiers":[
        {
            "category":"Home & Garden",
            "subcategory":"Building Materials",
            "type":"Retail Goods"
        }
    ],
    "sg:phone":"+1 207 893 0181",
    "sg:postcode":"04071",
    "sg:province":"ME",
    "wof:name":"Beveled Edge",
    "wof:placetype":"venue"
},
  "geometry": {"coordinates":[-70.457972,43.937639],"type":"Point"}
}