{
  "type": "Feature",
  "properties": {
    "addr:full":"86 Emery Mills Rd Shapleigh ME 04076",
    "addr:housenumber":"86",
    "addr:postcode":"04076",
    "addr:street":"Emery Mills Rd",
    "iso:country":"US",
    "sg:address":"86 Emery Mills Rd",
    "sg:city":"Shapleigh",
    "sg:classifiers":[
        {
            "category":"Autos & Motor Vehicles",
            "subcategory":"Boat Sales",
            "type":"Retail Goods"
        }
    ],
    "sg:phone":"+1 207 636 2722",
    "sg:postcode":"04076",
    "sg:province":"ME",
    "sg:tags":[
        "dealer",
        "sales"
    ],
    "wof:name":"Parker's Boathouse",
    "wof:placetype":"venue"
},
  "geometry": {"coordinates":[-70.854772,43.498526],"type":"Point"}
}