{
  "type": "Feature",
  "properties": {
    "iso:country":"US",
    "sg:address":"341 Albion Rd",
    "sg:city":"Unity",
    "sg:classifiers":[
        {
            "category":"Shopping",
            "type":"Retail Goods"
        }
    ],
    "sg:phone":"+1 207 948 5473",
    "sg:postcode":"04901",
    "sg:province":"ME",
    "sg:tags":[
        "merchandise"
    ],
    "wof:name":"Harbor Frame Shop Gallery",
    "wof:placetype":"venue"
},
  "geometry": {"coordinates":[-69.51987200000001,44.577322],"type":"Point"}
}