{
  "type": "Feature",
  "properties": {
    "iso:country":"US",
    "sg:address":"209 Pleasant St",
    "sg:city":"Brunswick",
    "sg:classifiers":[
        {
            "category":"Autos & Motor Vehicles",
            "subcategory":"Automobile Sales",
            "type":"Retail Goods"
        }
    ],
    "sg:phone":"+1 207 725 2599",
    "sg:postcode":"04011",
    "sg:province":"ME",
    "sg:tags":[
        "car",
        "dealer"
    ],
    "wof:name":"Atlantic Coast Used Cars",
    "wof:placetype":"venue"
},
  "geometry": {"coordinates":[-69.996046,43.91203],"type":"Point"}
}