{
  "type": "Feature",
  "properties": {
    "iso:country":"US",
    "sg:address":"40 Concourse E",
    "sg:city":"Waterville",
    "sg:classifiers":[
        {
            "category":"Restaurant",
            "type":"Food & Drink"
        }
    ],
    "sg:phone":"+1 207 872 6231",
    "sg:postcode":"04901",
    "sg:province":"ME",
    "wof:name":"Villager Family Restaurant",
    "wof:placetype":"venue"
},
  "geometry": {"coordinates":[-69.631223,44.549883],"type":"Point"}
}