{
  "type": "Feature",
  "properties": {
    "iso:country":"US",
    "sg:address":"484 Richville Rd",
    "sg:city":"Standish",
    "sg:classifiers":[
        {
            "category":"Retail",
            "subcategory":"Auto Repair",
            "type":"Services"
        }
    ],
    "sg:phone":"+1 207 642 3537",
    "sg:postcode":"04084",
    "sg:province":"ME",
    "sg:tags":[
        "repairing",
        "automobile"
    ],
    "wof:name":"Walker's Used Cars",
    "wof:placetype":"venue"
},
  "geometry": {"coordinates":[-70.565018,43.785011],"type":"Point"}
}