{
  "type": "Feature",
  "properties": {
    "addr:full":"76 Smyrna St Houlton ME 04730",
    "addr:housenumber":"76",
    "addr:postcode":"04730",
    "addr:street":"Smyrna St",
    "iso:country":"US",
    "sg:address":"76 Smyrna St",
    "sg:city":"Houlton",
    "sg:classifiers":[
        {
            "category":"Autos & Motor Vehicles",
            "subcategory":"Auto Supplies",
            "type":"Retail Goods"
        }
    ],
    "sg:phone":"+1 207 532 6571",
    "sg:postcode":"04730",
    "sg:province":"ME",
    "sg:tags":[
        "tire"
    ],
    "wof:name":"Houlton Tire",
    "wof:placetype":"venue"
},
  "geometry": {"coordinates":[-67.852513,46.131184],"type":"Point"}
}