{
  "type": "Feature",
  "properties": {
    "addr:full":"47 Bay View St Camden ME 04843",
    "addr:housenumber":"47",
    "addr:postcode":"04843",
    "addr:street":"Bay View St",
    "iso:country":"US",
    "sg:address":"47 Bay View St",
    "sg:city":"Camden",
    "sg:classifiers":[
        {
            "category":"Shopping",
            "subcategory":"Used Merchandise",
            "type":"Retail Goods"
        }
    ],
    "sg:phone":"+1 207 236 8868",
    "sg:postcode":"04843",
    "sg:province":"ME",
    "sg:tags":[
        "antique"
    ],
    "wof:name":"Suffolk Gallery",
    "wof:placetype":"venue"
},
  "geometry": {"coordinates":[-69.063166,44.208059],"type":"Point"}
}