{
  "type": "Feature",
  "properties": {
    "iso:country":"US",
    "sg:address":"723 Maine St",
    "sg:city":"Poland",
    "sg:classifiers":[
        {
            "category":"Restaurant",
            "type":"Food & Drink"
        }
    ],
    "sg:phone":"+1 207 998 4626",
    "sg:postcode":"04274",
    "sg:province":"ME",
    "wof:name":"Flying Lobster",
    "wof:placetype":"venue"
},
  "geometry": {"coordinates":[-70.374594,44.038428],"type":"Point"}
}