{
  "type": "Feature",
  "properties": {
    "addr:full":"7 Pond St Rangeley ME 04970",
    "addr:housenumber":"7",
    "addr:postcode":"04970",
    "addr:street":"Pond St",
    "iso:country":"US",
    "sg:address":"7 Pond St",
    "sg:city":"Rangeley",
    "sg:classifiers":[
        {
            "category":"Shopping",
            "subcategory":"Gifts & Souvenirs",
            "type":"Retail Goods"
        }
    ],
    "sg:phone":"+1 207 864 2771",
    "sg:postcode":"04970",
    "sg:province":"ME",
    "sg:tags":[
        "shop"
    ],
    "wof:name":"Ecopelagicon Nature Store",
    "wof:placetype":"venue"
},
  "geometry": {"coordinates":[-70.642166,44.964591],"type":"Point"}
}