{
  "type": "Feature",
  "properties": {
    "addr:full":"290 Beech Ridge Rd Scarborough ME 04074",
    "addr:housenumber":"290",
    "addr:postcode":"04074",
    "addr:street":"Beech Ridge Rd",
    "iso:country":"US",
    "sg:address":"290 Beech Ridge Rd",
    "sg:city":"Scarborough",
    "sg:classifiers":[
        {
            "category":"Professional",
            "subcategory":"Detective & Security Services",
            "type":"Services"
        }
    ],
    "sg:phone":"+1 207 839 2006",
    "sg:postcode":"04074",
    "sg:province":"ME",
    "sg:tags":[
        "system"
    ],
    "wof:name":"Mak Protection Services",
    "wof:placetype":"venue"
},
  "geometry": {"coordinates":[-70.404696,43.634743],"type":"Point"}
}