{
  "type": "Feature",
  "properties": {
    "addr:full":"387 Clover Mill Rd Farmington ME 04938",
    "addr:housenumber":"387",
    "addr:postcode":"04938",
    "addr:street":"Clover Mill Rd",
    "iso:country":"US",
    "sg:address":"387 Clover Mill Rd",
    "sg:city":"Farmington",
    "sg:classifiers":[
        {
            "category":"Building & Trades",
            "subcategory":"Electrical",
            "type":"Services"
        }
    ],
    "sg:phone":"+1 207 778 6818",
    "sg:postcode":"04938",
    "sg:province":"ME",
    "sg:tags":[
        "electric",
        "contractor"
    ],
    "wof:name":"R S Electric",
    "wof:placetype":"venue"
},
  "geometry": {"coordinates":[-70.210157,44.680301],"type":"Point"}
}