{
  "type": "Feature",
  "properties": {
    "iso:country":"US",
    "sg:address":"113 Booth Boy Rd",
    "sg:city":"East Boothbay",
    "sg:classifiers":[
        {
            "category":"Travel",
            "subcategory":"Hotels & Motels",
            "type":"Entertainment"
        }
    ],
    "sg:phone":"+1 207 633 4551",
    "sg:postcode":"04556",
    "sg:province":"ME",
    "sg:tags":[
        "breakfast",
        "accommodation",
        "bed"
    ],
    "wof:name":"Five Gables Inn",
    "wof:placetype":"venue"
},
  "geometry": {"coordinates":[-69.632263,43.999804],"type":"Point"}
}