{
  "type": "Feature",
  "properties": {
    "addr:full":"1142 State St Springfield ME 01109",
    "addr:housenumber":"1142",
    "addr:postcode":"01109",
    "addr:street":"State St",
    "iso:country":"US",
    "sg:address":"1142 State St",
    "sg:city":"Springfield",
    "sg:classifiers":[
        {
            "category":"Personal",
            "subcategory":"Beauty Salon",
            "type":"Services"
        }
    ],
    "sg:phone":"+1 413 731 6717",
    "sg:postcode":"01109",
    "sg:province":"ME",
    "wof:name":"Hair Connection",
    "wof:placetype":"venue"
},
  "geometry": {"coordinates":[-72.553737,42.114833],"type":"Point"}
}