{
  "type": "Feature",
  "properties": {
    "iso:country":"US",
    "sg:address":"2 Folcutt Rd",
    "sg:city":"Kittery Point",
    "sg:classifiers":[
        {
            "category":"Retail",
            "subcategory":"Repair Shop",
            "type":"Services"
        }
    ],
    "sg:phone":"+1 207 439 0969",
    "sg:postcode":"03905",
    "sg:province":"ME",
    "wof:name":"Spruce Creek TV",
    "wof:placetype":"venue"
},
  "geometry": {"coordinates":[-70.71402500000001,43.087801],"type":"Point"}
}