{
  "type": "Feature",
  "properties": {
    "iso:country":"US",
    "sg:address":"49 Redington St",
    "sg:city":"Rangeley",
    "sg:classifiers":[
        {
            "category":"Utilities",
            "subcategory":"Water",
            "type":"Services"
        }
    ],
    "sg:phone":"+1 207 864 5680",
    "sg:postcode":"04901",
    "sg:province":"ME",
    "sg:tags":[
        "company",
        "sewage"
    ],
    "wof:name":"Rangeley Water District",
    "wof:placetype":"venue"
},
  "geometry": {"coordinates":[-69.635768,44.544439],"type":"Point"}
}