{
  "type": "Feature",
  "properties": {
    "addr:full":"36 Emery Rd Standish ME 04084",
    "addr:housenumber":"36",
    "addr:postcode":"04084",
    "addr:street":"Emery Rd",
    "iso:country":"US",
    "sg:address":"36 Emery Rd",
    "sg:city":"Standish",
    "sg:classifiers":[
        {
            "category":"Building & Trades",
            "subcategory":"Construction",
            "type":"Services"
        }
    ],
    "sg:phone":"+1 207 839 6781",
    "sg:postcode":"04084",
    "sg:province":"ME",
    "sg:tags":[
        "fence",
        "contractor"
    ],
    "wof:name":"Gorham Fence Co",
    "wof:placetype":"venue"
},
  "geometry": {"coordinates":[-70.535878,43.729151],"type":"Point"}
}