{
  "type": "Feature",
  "properties": {
    "iso:country":"US",
    "sg:address":"339 Water St",
    "sg:city":"Gardiner",
    "sg:classifiers":[
        {
            "category":"Food & Beverages",
            "subcategory":"Bakery",
            "type":"Retail Goods"
        }
    ],
    "sg:phone":"+1 207 582 5450",
    "sg:postcode":"04346",
    "sg:province":"ME",
    "sg:tags":[
        "baker"
    ],
    "wof:name":"Mac Donald's Bakery",
    "wof:placetype":"venue"
},
  "geometry": {"coordinates":[-69.759515,44.22434],"type":"Point"}
}