{
  "type": "Feature",
  "properties": {
    "addr:full":"129 Precourt St Biddeford ME 04005",
    "addr:housenumber":"129",
    "addr:postcode":"04005",
    "addr:street":"Precourt St",
    "iso:country":"US",
    "sg:address":"129 Precourt St",
    "sg:city":"Biddeford",
    "sg:classifiers":[
        {
            "category":"Manufacturing",
            "subcategory":"Metals",
            "type":"Manufacturing & Wholesale Goods"
        }
    ],
    "sg:phone":"+1 207 282 6740",
    "sg:postcode":"04005",
    "sg:province":"ME",
    "sg:tags":[
        "fabricator",
        "sheet"
    ],
    "sg:website":"www.donssheetmetal.com",
    "wof:name":"Don's Sheet Metal Shop",
    "wof:placetype":"venue"
},
  "geometry": {"coordinates":[-70.48151,43.466152],"type":"Point"}
}