{
  "type": "Feature",
  "properties": {
    "iso:country":"US",
    "sg:address":"209 Main St",
    "sg:city":"Biddeford",
    "sg:classifiers":[
        {
            "category":"Professional",
            "subcategory":"Lawyer & Legal Services",
            "type":"Services"
        }
    ],
    "sg:phone":"+1 207 283 3777",
    "sg:postcode":"04005",
    "sg:province":"ME",
    "sg:tags":[
        "attorney"
    ],
    "sg:website":"www.molleurlaw.com",
    "wof:name":"James F Molleur",
    "wof:placetype":"venue"
},
  "geometry": {"coordinates":[-70.457521,43.493871],"type":"Point"}
}