{
  "type": "Feature",
  "properties": {
    "iso:country":"US",
    "sg:address":"116 Bangor Rd",
    "sg:city":"Unity",
    "sg:classifiers":[
        {
            "category":"Organizations",
            "subcategory":"Religious Organization",
            "type":"Services"
        }
    ],
    "sg:phone":"+1 207 948 5347",
    "sg:postcode":"04901",
    "sg:province":"ME",
    "sg:tags":[
        "church"
    ],
    "wof:name":"Church Of The Apostolic Way",
    "wof:placetype":"venue"
},
  "geometry": {"coordinates":[-69.54593,44.592999],"type":"Point"}
}