{
  "type": "Feature",
  "properties": {
    "addr:full":"884 Broadway South Portland ME 04106",
    "addr:housenumber":"884",
    "addr:postcode":"04106",
    "addr:street":"Broadway",
    "iso:country":"US",
    "sg:address":"884 Broadway",
    "sg:city":"South Portland",
    "sg:classifiers":[
        {
            "category":"Social Services",
            "type":"Services"
        }
    ],
    "sg:phone":"+1 207 799 9600",
    "sg:postcode":"04106",
    "sg:province":"ME",
    "sg:tags":[
        "counselor",
        "marriage",
        "family"
    ],
    "wof:name":"Jill D Mc Collum",
    "wof:placetype":"venue"
},
  "geometry": {"coordinates":[-70.267602,43.631083],"type":"Point"}
}