{
  "type": "Feature",
  "properties": {
    "addr:full":"6 Old Town Rd Orrs Island ME 04066",
    "addr:housenumber":"6",
    "addr:postcode":"04066",
    "addr:street":"Old Town Rd",
    "iso:country":"US",
    "sg:address":"6 Old Town Rd",
    "sg:city":"Orrs Island",
    "sg:classifiers":[
        {
            "category":"Home & Garden",
            "subcategory":"Furniture",
            "type":"Retail Goods"
        }
    ],
    "sg:phone":"+1 207 833 6934",
    "sg:postcode":"04066",
    "sg:province":"ME",
    "sg:tags":[
        "equipment",
        "kitchen",
        "cabinet"
    ],
    "wof:name":"Brumark Solid Surfaces",
    "wof:placetype":"venue"
},
  "geometry": {"coordinates":[-69.956126,43.778345],"type":"Point"}
}