{
  "type": "Feature",
  "properties": {
    "iso:country":"US",
    "sg:address":"154 Hildreth St N",
    "sg:city":"Bangor",
    "sg:classifiers":[
        {
            "category":"Building & Trades",
            "subcategory":"Cleaning & Sanitation",
            "type":"Services"
        }
    ],
    "sg:phone":"+1 207 989 3211",
    "sg:postcode":"04401",
    "sg:province":"ME",
    "wof:name":"Industrial Services Inc",
    "wof:placetype":"venue"
},
  "geometry": {"coordinates":[-68.838512,44.799953],"type":"Point"}
}