{
  "type": "Feature",
  "properties": {
    "iso:country":"US",
    "sg:address":"1252 Washington St",
    "sg:city":"Bath",
    "sg:classifiers":[
        {
            "category":"Health Services",
            "subcategory":"Health Practitioner",
            "type":"Services"
        }
    ],
    "sg:phone":"+1 207 443 2324",
    "sg:postcode":"04530",
    "sg:province":"ME",
    "wof:name":"Alice J Woodman Rn",
    "wof:placetype":"venue"
},
  "geometry": {"coordinates":[-69.813818,43.928295],"type":"Point"}
}