{
  "type": "Feature",
  "properties": {
    "addr:full":"7 River Rd Indian Island ME 04468",
    "addr:housenumber":"7",
    "addr:postcode":"04468",
    "addr:street":"River Rd",
    "iso:country":"US",
    "sg:address":"7 River Rd",
    "sg:city":"Indian Island",
    "sg:classifiers":[
        {
            "category":"Recreation",
            "type":"Entertainment"
        }
    ],
    "sg:phone":"+1 207 827 7750",
    "sg:postcode":"04468",
    "sg:province":"ME",
    "sg:tags":[
        "bingo",
        "game"
    ],
    "wof:name":"Penobscot Indian Reservation",
    "wof:placetype":"venue"
},
  "geometry": {"coordinates":[-68.648076,44.948389],"type":"Point"}
}