{
  "type": "Feature",
  "properties": {
    "iso:country":"US",
    "sg:address":"110 Main St",
    "sg:city":"Saco",
    "sg:classifiers":[
        {
            "category":"Professional",
            "subcategory":"Accounting & Tax Preparation",
            "type":"Services"
        }
    ],
    "sg:phone":"+1 207 286 1668",
    "sg:postcode":"04072",
    "sg:province":"ME",
    "sg:tags":[
        "accountant"
    ],
    "sg:website":"www.casella.com",
    "wof:name":"Casella Waste Systems Inc",
    "wof:placetype":"venue"
},
  "geometry": {"coordinates":[-70.443469,43.500206],"type":"Point"}
}