{
  "type": "Feature",
  "properties": {
    "addr:full":"14 Strawberry Ave Turner ME 04282",
    "addr:housenumber":"14",
    "addr:postcode":"04282",
    "addr:street":"Strawberry Ave",
    "iso:country":"US",
    "sg:address":"14 Strawberry Ave",
    "sg:city":"Turner",
    "sg:classifiers":[
        {
            "category":"Building & Trades",
            "subcategory":"Construction",
            "type":"Services"
        }
    ],
    "sg:phone":"+1 207 966 1039",
    "sg:postcode":"04282",
    "sg:province":"ME",
    "sg:tags":[
        "builder",
        "stair"
    ],
    "wof:name":"Pandemonium Box Inc",
    "wof:placetype":"venue"
},
  "geometry": {"coordinates":[-70.29997899999999,44.209615],"type":"Point"}
}