{
  "type": "Feature",
  "properties": {
    "iso:country":"US",
    "sg:address":"1039 N Mountain Rd",
    "sg:city":"Jefferson",
    "sg:classifiers":[
        {
            "category":"Freight",
            "type":"Transportation"
        }
    ],
    "sg:phone":"+1 207 799 7226",
    "sg:postcode":"04348",
    "sg:province":"ME",
    "sg:tags":[
        "trucking"
    ],
    "wof:name":"B & J Electronic",
    "wof:placetype":"venue"
},
  "geometry": {"coordinates":[-69.499925,44.218116],"type":"Point"}
}