{
  "type": "Feature",
  "properties": {
    "iso:country":"US",
    "sg:address":"82 Western Ave",
    "sg:city":"Augusta",
    "sg:classifiers":[
        {
            "category":"Personal",
            "subcategory":"Beauty Salon",
            "type":"Services"
        }
    ],
    "sg:phone":"+1 207 622 6177",
    "sg:postcode":"04330",
    "sg:province":"ME",
    "sg:tags":[
        "manicuring"
    ],
    "wof:name":"Top Nails",
    "wof:placetype":"venue"
},
  "geometry": {"coordinates":[-69.788156,44.311906],"type":"Point"}
}