{
  "type": "Feature",
  "properties": {
    "iso:country":"US",
    "sg:address":"60 Main Rd N",
    "sg:city":"Hampden",
    "sg:classifiers":[
        {
            "category":"Professional",
            "subcategory":"Computer Services",
            "type":"Services"
        }
    ],
    "sg:phone":"+1 207 862 5135",
    "sg:postcode":"04444",
    "sg:province":"ME",
    "sg:tags":[
        "repair"
    ],
    "wof:name":"Cyber Mall Inc",
    "wof:placetype":"venue"
},
  "geometry": {"coordinates":[-68.838064,44.743187],"type":"Point"}
}