{
  "type": "Feature",
  "properties": {
    "addr:full":"194 Merrow Rd Auburn ME 04210",
    "addr:housenumber":"194",
    "addr:postcode":"04210",
    "addr:street":"Merrow Rd",
    "iso:country":"US",
    "sg:address":"194 Merrow Rd",
    "sg:city":"Auburn",
    "sg:classifiers":[
        {
            "category":"Building & Trades",
            "subcategory":"Plumbing",
            "type":"Services"
        }
    ],
    "sg:phone":"+1 207 782 0727",
    "sg:postcode":"04210",
    "sg:province":"ME",
    "sg:tags":[
        "conditioning",
        "air",
        "system",
        "contractor"
    ],
    "sg:website":"www.henason.com",
    "wof:name":"Nason Mechanical Systems",
    "wof:placetype":"venue"
},
  "geometry": {"coordinates":[-70.27753300000001,44.069557],"type":"Point"}
}