{
  "type": "Feature",
  "properties": {
    "addr:full":"12 6th Ave Augusta ME 04330",
    "addr:housenumber":"12",
    "addr:postcode":"04330",
    "addr:street":"6Th Ave",
    "iso:country":"US",
    "sg:address":"12 6th Ave",
    "sg:city":"Augusta",
    "sg:classifiers":[
        {
            "category":"Travel",
            "subcategory":"Travel Agent",
            "type":"Entertainment"
        }
    ],
    "sg:phone":"+1 207 622 2221",
    "sg:postcode":"04330",
    "sg:province":"ME",
    "sg:tags":[
        "agency",
        "bureau"
    ],
    "wof:name":"AAA Travel Agency",
    "wof:placetype":"venue"
},
  "geometry": {"coordinates":[-69.763915,44.305229],"type":"Point"}
}