{
  "type": "Feature",
  "properties": {
    "addr:full":"654 Main St Presque Isle ME 04769",
    "addr:housenumber":"654",
    "addr:postcode":"04769",
    "addr:street":"Main St",
    "iso:country":"US",
    "sg:address":"654 Main St",
    "sg:city":"Presque Isle",
    "sg:classifiers":[
        {
            "category":"Retail",
            "subcategory":"Laundry & Dry Cleaning",
            "type":"Services"
        }
    ],
    "sg:phone":"+1 207 764 0995",
    "sg:postcode":"04769",
    "sg:province":"ME",
    "wof:name":"Kelley's Fabric Care Ctr",
    "wof:placetype":"venue"
},
  "geometry": {"coordinates":[-68.013841,46.685885],"type":"Point"}
}