{
  "type": "Feature",
  "properties": {
    "iso:country":"US",
    "sg:address":"32 Main St",
    "sg:city":"Livermore Falls",
    "sg:classifiers":[
        {
            "category":"Health Services",
            "subcategory":"Doctor",
            "type":"Services"
        }
    ],
    "sg:phone":"+1 207 897 6331",
    "sg:postcode":"04254",
    "sg:province":"ME",
    "sg:tags":[
        "physician",
        "surgeon"
    ],
    "wof:name":"David Hurst Billing Office",
    "wof:placetype":"venue"
},
  "geometry": {"coordinates":[-70.18988899999999,44.473044],"type":"Point"}
}