{
  "type": "Feature",
  "properties": {
    "addr:full":"1218 Waterford Rd Waterford ME 04088",
    "addr:housenumber":"1218",
    "addr:postcode":"04088",
    "addr:street":"Waterford Rd",
    "iso:country":"US",
    "sg:address":"1218 Waterford Rd",
    "sg:city":"Waterford",
    "sg:classifiers":[
        {
            "category":"Restaurant",
            "type":"Food & Drink"
        }
    ],
    "sg:phone":"+1 207 583 2051",
    "sg:postcode":"04088",
    "sg:province":"ME",
    "sg:tags":[
        "out"
    ],
    "wof:name":"Springers General Store",
    "wof:placetype":"venue"
},
  "geometry": {"coordinates":[-70.68145699999999,44.209807],"type":"Point"}
}