{
  "type": "Feature",
  "properties": {
    "iso:country":"US",
    "sg:address":"151 Congress St",
    "sg:city":"Rumford",
    "sg:classifiers":[
        {
            "category":"Government",
            "subcategory":"Fire Station",
            "type":"Public Place"
        }
    ],
    "sg:phone":"+1 207 364 2901",
    "sg:postcode":"04276",
    "sg:province":"ME",
    "sg:tags":[
        "department"
    ],
    "wof:name":"Rumford Town Fire Dept",
    "wof:placetype":"venue"
},
  "geometry": {"coordinates":[-70.545805,44.546209],"type":"Point"}
}