{
  "type": "Feature",
  "properties": {
    "iso:country":"US",
    "sg:address":"151 Main St",
    "sg:city":"Westbrook",
    "sg:classifiers":[
        {
            "category":"Shopping",
            "subcategory":"Optical Goods",
            "type":"Retail Goods"
        }
    ],
    "sg:phone":"+1 207 854 1801",
    "sg:postcode":"04092",
    "sg:province":"ME",
    "wof:name":"Eye Care & Eye Wear Ctr Of Me",
    "wof:placetype":"venue"
},
  "geometry": {"coordinates":[-70.334924,43.677976],"type":"Point"}
}