{
  "type": "Feature",
  "properties": {
    "iso:country":"US",
    "sg:address":"64 Park St",
    "sg:city":"Dexter",
    "sg:classifiers":[
        {
            "category":"Health Services",
            "subcategory":"Nursing And Care Facility",
            "type":"Services"
        }
    ],
    "sg:phone":"+1 207 924 5516",
    "sg:postcode":"04930",
    "sg:province":"ME",
    "sg:tags":[
        "home",
        "convalescent"
    ],
    "wof:name":"Dexter Health Care",
    "wof:placetype":"venue"
},
  "geometry": {"coordinates":[-69.283985,45.027046],"type":"Point"}
}