{
  "type": "Feature",
  "properties": {
    "addr:full":"2 Spring St Kennebunkport ME 04046",
    "addr:housenumber":"2",
    "addr:postcode":"04046",
    "addr:street":"Spring St",
    "iso:country":"US",
    "sg:address":"2 Spring St",
    "sg:city":"Kennebunkport",
    "sg:classifiers":[
        {
            "category":"Shopping",
            "subcategory":"Gifts & Souvenirs",
            "type":"Retail Goods"
        }
    ],
    "sg:phone":"+1 207 967 3690",
    "sg:postcode":"04046",
    "sg:province":"ME",
    "sg:tags":[
        "shop"
    ],
    "wof:name":"Kennebunkport Arts",
    "wof:placetype":"venue"
},
  "geometry": {"coordinates":[-70.47583899999999,43.362739],"type":"Point"}
}