{
  "type": "Feature",
  "properties": {
    "iso:country":"US",
    "sg:address":"462 Hammond St",
    "sg:city":"Bangor",
    "sg:classifiers":[
        {
            "category":"Autos & Motor Vehicles",
            "subcategory":"Fuel & Gas Station",
            "type":"Retail Goods"
        }
    ],
    "sg:phone":"+1 207 942 9754",
    "sg:postcode":"04401",
    "sg:province":"ME",
    "sg:tags":[
        "oil"
    ],
    "wof:name":"T & W American Serv Sta",
    "wof:placetype":"venue"
},
  "geometry": {"coordinates":[-68.784816,44.800474],"type":"Point"}
}