{
  "type": "Feature",
  "properties": {
    "iso:country":"US",
    "sg:address":"7 Portland Street Pier",
    "sg:city":"South Portland",
    "sg:classifiers":[
        {
            "category":"Food & Beverages",
            "subcategory":"Groceries & Convenience Stores",
            "type":"Retail Goods"
        }
    ],
    "sg:phone":"+1 207 854 4631",
    "sg:postcode":"04106",
    "sg:province":"ME",
    "sg:tags":[
        "grocer"
    ],
    "wof:name":"Hannaford Supermarkets",
    "wof:placetype":"venue"
},
  "geometry": {"coordinates":[-70.242562,43.650315],"type":"Point"}
}