{
  "type": "Feature",
  "properties": {
    "iso:country":"US",
    "sg:address":"49 Mountain Ave",
    "sg:city":"Fairfield",
    "sg:classifiers":[
        {
            "category":"Wholesale",
            "subcategory":"Construction Materials",
            "type":"Manufacturing & Wholesale Goods"
        }
    ],
    "sg:phone":"+1 207 453 2527",
    "sg:postcode":"04937",
    "sg:province":"ME",
    "sg:tags":[
        "timberland",
        "company",
        "timber"
    ],
    "wof:name":"Plum Creek Timber Co",
    "wof:placetype":"venue"
},
  "geometry": {"coordinates":[-69.600454,44.606285],"type":"Point"}
}