{
  "type": "Feature",
  "properties": {
    "iso:country":"US",
    "sg:address":"16 Caton Rd",
    "sg:city":"Raymond",
    "sg:classifiers":[
        {
            "category":"Personal",
            "subcategory":"Beauty Salon",
            "type":"Services"
        }
    ],
    "sg:phone":"+1 207 655 2593",
    "sg:postcode":"04071",
    "sg:province":"ME",
    "sg:tags":[
        "shop"
    ],
    "wof:name":"Reflections Hair & Tan Salon",
    "wof:placetype":"venue"
},
  "geometry": {"coordinates":[-70.469148,43.887885],"type":"Point"}
}