{
  "type": "Feature",
  "properties": {
    "addr:full":"16 Hartland Ave Pittsfield ME 04967",
    "addr:housenumber":"16",
    "addr:postcode":"04967",
    "addr:street":"Hartland Ave",
    "iso:country":"US",
    "sg:address":"16 Hartland Ave",
    "sg:city":"Pittsfield",
    "sg:classifiers":[
        {
            "category":"Shopping",
            "subcategory":"Optical Goods",
            "type":"Retail Goods"
        }
    ],
    "sg:phone":"+1 207 487 2200",
    "sg:postcode":"04967",
    "sg:province":"ME",
    "sg:tags":[
        "contact",
        "lense"
    ],
    "wof:name":"Central Me Eye Care",
    "wof:placetype":"venue"
},
  "geometry": {"coordinates":[-69.386225,44.786972],"type":"Point"}
}