{
  "type": "Feature",
  "properties": {
    "addr:full":"9 Laurel Ln Berwick ME 03903",
    "addr:housenumber":"9",
    "addr:postcode":"03903",
    "addr:street":"Laurel Ln",
    "iso:country":"US",
    "sg:address":"9 Laurel Ln",
    "sg:city":"Berwick",
    "sg:classifiers":[
        {
            "category":"Wholesale",
            "subcategory":"Jewelry",
            "type":"Manufacturing & Wholesale Goods"
        }
    ],
    "sg:phone":"+1 207 698 1488",
    "sg:postcode":"03903",
    "sg:province":"ME",
    "sg:tags":[
        "ribbon"
    ],
    "wof:name":"Claudette's Crafts Supply",
    "wof:placetype":"venue"
},
  "geometry": {"coordinates":[-70.81063899999999,43.123388],"type":"Point"}
}