{
  "type": "Feature",
  "properties": {
    "iso:country":"US",
    "sg:address":"21 Old Orchard St",
    "sg:city":"Old Orchard Bch",
    "sg:classifiers":[
        {
            "category":"Professional",
            "type":"Services"
        }
    ],
    "sg:phone":"+1 207 934 2858",
    "sg:postcode":"04064",
    "sg:province":"ME",
    "sg:tags":[
        "establishment"
    ],
    "wof:name":"New Edition",
    "wof:placetype":"venue"
},
  "geometry": {"coordinates":[-70.37752500000001,43.517373],"type":"Point"}
}