{
  "type": "Feature",
  "properties": {
    "iso:country":"US",
    "sg:address":"1413 Portland Rd",
    "sg:city":"Arundel",
    "sg:classifiers":[
        {
            "category":"Building & Trades",
            "subcategory":"Construction",
            "type":"Services"
        }
    ],
    "sg:phone":"+1 207 985 4101",
    "sg:postcode":"04046",
    "sg:province":"ME",
    "sg:tags":[
        "general",
        "contractor"
    ],
    "sg:website":"www.douston.com",
    "wof:name":"Douston Construction",
    "wof:placetype":"venue"
},
  "geometry": {"coordinates":[-70.522948,43.407678],"type":"Point"}
}