{
  "type": "Feature",
  "properties": {
    "addr:full":"200 Main St Westbrook ME 04092",
    "addr:housenumber":"200",
    "addr:postcode":"04092",
    "addr:street":"Main St",
    "iso:country":"US",
    "sg:address":"200 Main St",
    "sg:city":"Westbrook",
    "sg:classifiers":[
        {
            "category":"Retail",
            "subcategory":"Auto Repair",
            "type":"Services"
        }
    ],
    "sg:phone":"+1 207 856 6685",
    "sg:postcode":"04092",
    "sg:province":"ME",
    "sg:tags":[
        "repairing",
        "automobile"
    ],
    "wof:name":"Lee Auto Mall",
    "wof:placetype":"venue"
},
  "geometry": {"coordinates":[-70.337031,43.678295],"type":"Point"}
}