{
  "type": "Feature",
  "properties": {
    "addr:full":"20 College Ave Gorham ME 04038",
    "addr:housenumber":"20",
    "addr:postcode":"04038",
    "addr:street":"College Ave",
    "iso:country":"US",
    "sg:address":"20 College Ave",
    "sg:city":"Gorham",
    "sg:classifiers":[
        {
            "category":"Social Services",
            "type":"Services"
        }
    ],
    "sg:phone":"+1 207 839 4966",
    "sg:postcode":"04038",
    "sg:province":"ME",
    "sg:tags":[
        "health"
    ],
    "wof:name":"Carol F Curran",
    "wof:placetype":"venue"
},
  "geometry": {"coordinates":[-70.44548,43.68001],"type":"Point"}
}