{
  "type": "Feature",
  "properties": {
    "iso:country":"US",
    "sg:address":"25 Pleasant Vw",
    "sg:city":"Harrison",
    "sg:classifiers":[
        {
            "category":"Real Estate",
            "subcategory":"Architect",
            "type":"Services"
        }
    ],
    "sg:phone":"+1 207 647 4496",
    "sg:postcode":"04040",
    "sg:province":"ME",
    "sg:tags":[
        "architectural"
    ],
    "wof:name":"Jmg Design Inc",
    "wof:placetype":"venue"
},
  "geometry": {"coordinates":[-70.627991,44.055819],"type":"Point"}
}