{
  "type": "Feature",
  "properties": {
    "iso:country":"US",
    "sg:address":"9 Merriconeag Ln",
    "sg:city":"Harpswell",
    "sg:classifiers":[
        {
            "category":"Sports & Exercise",
            "subcategory":"Golf",
            "type":"Entertainment"
        }
    ],
    "sg:phone":"+1 207 721 9995",
    "sg:postcode":"04079",
    "sg:province":"ME",
    "sg:tags":[
        "course"
    ],
    "wof:name":"Mere Creek Golf Course",
    "wof:placetype":"venue"
},
  "geometry": {"coordinates":[-70.00755,43.747124],"type":"Point"}
}