{
  "type": "Feature",
  "properties": {
    "iso:country":"US",
    "sg:address":"194 Madison Ave",
    "sg:city":"Skowhegan",
    "sg:classifiers":[
        {
            "category":"Banks & Credit Unions",
            "subcategory":"Bank",
            "type":"Services"
        }
    ],
    "sg:phone":"+1 207 474 5574",
    "sg:postcode":"04976",
    "sg:province":"ME",
    "wof:name":"Franklin Savings Bank",
    "wof:placetype":"venue"
},
  "geometry": {"coordinates":[-69.72181,44.770112],"type":"Point"}
}