{
  "type": "Feature",
  "properties": {
    "addr:full":"6 Harvey Brook Dr Freeport ME 04032",
    "addr:housenumber":"6",
    "addr:postcode":"04032",
    "addr:street":"Harvey Brook Dr",
    "iso:country":"US",
    "sg:address":"6 Harvey Brook Dr",
    "sg:city":"Freeport",
    "sg:classifiers":[
        {
            "category":"Professional",
            "subcategory":"Research",
            "type":"Services"
        }
    ],
    "sg:phone":"+1 207 865 6445",
    "sg:postcode":"04032",
    "sg:province":"ME",
    "sg:tags":[
        "ergonomics"
    ],
    "sg:website":"www.morencyrest.com",
    "wof:name":"R & D Ergonomics",
    "wof:placetype":"venue"
},
  "geometry": {"coordinates":[-70.17034099999999,43.840124],"type":"Point"}
}