{
  "type": "Feature",
  "properties": {
    "iso:country":"US",
    "sg:address":"64 Park St",
    "sg:city":"Dover Foxcroft",
    "sg:classifiers":[
        {
            "category":"Manufacturing",
            "subcategory":"Electronics",
            "type":"Manufacturing & Wholesale Goods"
        }
    ],
    "sg:phone":"+1 207 564 7141",
    "sg:postcode":"04426",
    "sg:province":"ME",
    "sg:tags":[
        "semiconductor",
        "related",
        "devices"
    ],
    "wof:name":"P Q Controls Inc",
    "wof:placetype":"venue"
},
  "geometry": {"coordinates":[-69.23735499999999,45.191636],"type":"Point"}
}