{
  "type": "Feature",
  "properties": {
    "addr:full":"179 Lisbon St Lewiston ME 04240",
    "addr:housenumber":"179",
    "addr:postcode":"04240",
    "addr:street":"Lisbon St",
    "iso:country":"US",
    "sg:address":"179 Lisbon St",
    "sg:city":"Lewiston",
    "sg:classifiers":[
        {
            "category":"Real Estate",
            "subcategory":"Architect",
            "type":"Services"
        }
    ],
    "sg:phone":"+1 207 786 5623",
    "sg:postcode":"04240",
    "sg:province":"ME",
    "wof:name":"Smith Reuter Lull Architects",
    "wof:placetype":"venue"
},
  "geometry": {"coordinates":[-70.21679899999999,44.095886],"type":"Point"}
}