{
  "type": "Feature",
  "properties": {
    "iso:country":"US",
    "sg:address":"35 Kimball St",
    "sg:city":"Sanford",
    "sg:classifiers":[
        {
            "category":"Building & Trades",
            "subcategory":"Cleaning & Sanitation",
            "type":"Services"
        }
    ],
    "sg:phone":"+1 207 324 7651",
    "sg:postcode":"04073",
    "sg:province":"ME",
    "sg:tags":[
        "janitor"
    ],
    "wof:name":"Corliss Cleaning Svc",
    "wof:placetype":"venue"
},
  "geometry": {"coordinates":[-70.777584,43.437724],"type":"Point"}
}