{
  "type": "Feature",
  "properties": {
    "addr:full":"56 Roosevelt Trl Windham ME 04062",
    "addr:housenumber":"56",
    "addr:postcode":"04062",
    "addr:street":"Roosevelt Trl",
    "iso:country":"US",
    "sg:address":"56 Roosevelt Trl",
    "sg:city":"Windham",
    "sg:classifiers":[
        {
            "category":"Building & Trades",
            "subcategory":"Construction",
            "type":"Services"
        }
    ],
    "sg:phone":"+1 207 894 7283",
    "sg:postcode":"04062",
    "sg:province":"ME",
    "sg:tags":[
        "paving",
        "contractor"
    ],
    "wof:name":"Chase Paving Inc",
    "wof:placetype":"venue"
},
  "geometry": {"coordinates":[-70.370216,43.76092],"type":"Point"}
}