{
  "type": "Feature",
  "properties": {
    "iso:country":"US",
    "sg:address":"1 Main St",
    "sg:city":"Topsham",
    "sg:classifiers":[
        {
            "category":"Real Estate",
            "subcategory":"Real Estate Agent",
            "type":"Services"
        }
    ],
    "sg:phone":"+1 207 725 8505",
    "sg:postcode":"04086",
    "sg:province":"ME",
    "sg:website":"www.remax-riverside-maine.com",
    "wof:name":"Re/Max Riverside",
    "wof:placetype":"venue"
},
  "geometry": {"coordinates":[-69.963884,43.923894],"type":"Point"}
}