{
  "type": "Feature",
  "properties": {
    "iso:country":"US",
    "sg:address":"185 Harlow St",
    "sg:city":"Bangor",
    "sg:classifiers":[
        {
            "category":"Building & Trades",
            "subcategory":"Cleaning & Sanitation",
            "type":"Services"
        }
    ],
    "sg:phone":"+1 207 942 0261",
    "sg:postcode":"04401",
    "sg:province":"ME",
    "sg:tags":[
        "property",
        "maintenance"
    ],
    "wof:name":"Schoolhouse Maintenance",
    "wof:placetype":"venue"
},
  "geometry": {"coordinates":[-68.771628,44.803978],"type":"Point"}
}