{
  "type": "Feature",
  "properties": {
    "addr:full":"17 Brave Boat Harbor Rd York ME 03909",
    "addr:housenumber":"17",
    "addr:postcode":"03909",
    "addr:street":"Brave Boat Harbor Rd",
    "iso:country":"US",
    "sg:address":"17 Brave Boat Harbor Rd",
    "sg:city":"York",
    "sg:classifiers":[
        {
            "category":"Professional",
            "subcategory":"Art Services",
            "type":"Services"
        }
    ],
    "sg:phone":"+1 207 351 1731",
    "sg:postcode":"03909",
    "sg:province":"ME",
    "sg:tags":[
        "commercial",
        "design"
    ],
    "wof:name":"Cristofell Group Ltd",
    "wof:placetype":"venue"
},
  "geometry": {"coordinates":[-70.65483999999999,43.121288],"type":"Point"}
}