{
  "type": "Feature",
  "properties": {
    "iso:country":"US",
    "sg:address":"1356 County Rd",
    "sg:city":"New Limerick",
    "sg:classifiers":[
        {
            "category":"Building & Trades",
            "subcategory":"Construction",
            "type":"Services"
        }
    ],
    "sg:phone":"+1 207 532 9375",
    "sg:postcode":"04730",
    "sg:province":"ME",
    "sg:tags":[
        "carpentry",
        "contractor"
    ],
    "wof:name":"Calvin Bishop",
    "wof:placetype":"venue"
},
  "geometry": {"coordinates":[-67.976769,46.125351],"type":"Point"}
}