{
  "type": "Feature",
  "properties": {
    "addr:full":"56 Church St Ellsworth ME 04605",
    "addr:housenumber":"56",
    "addr:postcode":"04605",
    "addr:street":"Church St",
    "iso:country":"US",
    "sg:address":"56 Church St",
    "sg:city":"Ellsworth",
    "sg:classifiers":[
        {
            "category":"Real Estate",
            "subcategory":"Real Estate Agent",
            "type":"Services"
        }
    ],
    "sg:phone":"+1 207 667 7997",
    "sg:postcode":"04605",
    "sg:province":"ME",
    "wof:name":"Union River Realty",
    "wof:placetype":"venue"
},
  "geometry": {"coordinates":[-68.423147,44.543366],"type":"Point"}
}