{
  "type": "Feature",
  "properties": {
    "addr:full":"50 Industrial Dr Augusta ME 04330",
    "addr:housenumber":"50",
    "addr:postcode":"04330",
    "addr:street":"Industrial Dr",
    "iso:country":"US",
    "sg:address":"50 Industrial Dr",
    "sg:city":"Augusta",
    "sg:classifiers":[
        {
            "category":"Organizations",
            "subcategory":"Professional Association",
            "type":"Services"
        }
    ],
    "sg:phone":"+1 207 622 0217",
    "sg:postcode":"04330",
    "sg:province":"ME",
    "sg:website":"www.mpa.cc",
    "wof:name":"Maine Principals Assn",
    "wof:placetype":"venue"
},
  "geometry": {"coordinates":[-69.799809,44.355621],"type":"Point"}
}