{
  "type": "Feature",
  "properties": {
    "addr:full":"9 Industrial Way Boothbay ME 04530",
    "addr:housenumber":"9",
    "addr:postcode":"04530",
    "addr:street":"Industrial Way",
    "iso:country":"US",
    "sg:address":"9 Industrial Way",
    "sg:city":"Boothbay",
    "sg:classifiers":[
        {
            "category":"Health Services",
            "subcategory":"Clinic",
            "type":"Services"
        }
    ],
    "sg:phone":"+1 207 633 0555",
    "sg:postcode":"04530",
    "sg:province":"ME",
    "wof:name":"Creative Healthcare Services",
    "wof:placetype":"venue"
},
  "geometry": {"coordinates":[-69.85782399999999,43.904265],"type":"Point"}
}