{
  "type": "Feature",
  "properties": {
    "iso:country":"US",
    "sg:address":"71 Washington St",
    "sg:city":"Waterville",
    "sg:classifiers":[
        {
            "category":"Home & Garden",
            "subcategory":"Home Furnishings",
            "type":"Retail Goods"
        }
    ],
    "sg:phone":"+1 207 872 8914",
    "sg:postcode":"04901",
    "sg:province":"ME",
    "sg:tags":[
        "curtain",
        "made",
        "drapery"
    ],
    "wof:name":"Cutters Custom Draperies",
    "wof:placetype":"venue"
},
  "geometry": {"coordinates":[-69.67696599999999,44.550164],"type":"Point"}
}