{
  "type": "Feature",
  "properties": {
    "iso:country":"US",
    "sg:address":"27 Saco Rd",
    "sg:city":"Alfred",
    "sg:classifiers":[
        {
            "category":"Education",
            "subcategory":"Library",
            "type":"Public Place"
        }
    ],
    "sg:phone":"+1 207 324 2001",
    "sg:postcode":"04002",
    "sg:province":"ME",
    "wof:name":"Parsons Memorial Library",
    "wof:placetype":"venue"
},
  "geometry": {"coordinates":[-70.715672,43.47631],"type":"Point"}
}