{
  "type": "Feature",
  "properties": {
    "addr:full":"242 Saint John St Portland ME 04102",
    "addr:housenumber":"242",
    "addr:postcode":"04102",
    "addr:street":"Saint John St",
    "iso:country":"US",
    "sg:address":"242 Saint John St",
    "sg:city":"Portland",
    "sg:classifiers":[
        {
            "category":"Insurance",
            "subcategory":"Insurance Agent",
            "type":"Services"
        }
    ],
    "sg:phone":"+1 207 761 7000",
    "sg:postcode":"04102",
    "sg:province":"ME",
    "wof:name":"Hi Risk Auto Insurance",
    "wof:placetype":"venue"
},
  "geometry": {"coordinates":[-70.279366,43.652259],"type":"Point"}
}