{
  "type": "Feature",
  "properties": {
    "addr:full":"5 Dolloff Rd Thorndike ME 04986",
    "addr:housenumber":"5",
    "addr:postcode":"04986",
    "addr:street":"Dolloff Rd",
    "iso:country":"US",
    "sg:address":"5 Dolloff Rd",
    "sg:city":"Thorndike",
    "sg:classifiers":[
        {
            "category":"Retail",
            "subcategory":"Repair Shop",
            "type":"Services"
        }
    ],
    "sg:phone":"+1 207 568 3680",
    "sg:postcode":"04986",
    "sg:province":"ME",
    "sg:tags":[
        "welding"
    ],
    "sg:website":"www.acewroughtiron.com",
    "wof:name":"Ace Wrought Iron",
    "wof:placetype":"venue"
},
  "geometry": {"coordinates":[-69.230559,44.556123],"type":"Point"}
}