{
  "type": "Feature",
  "properties": {
    "addr:full":"120 Rogers Rd Kittery ME 03904",
    "addr:housenumber":"120",
    "addr:postcode":"03904",
    "addr:street":"Rogers Rd",
    "iso:country":"US",
    "sg:address":"120 Rogers Rd",
    "sg:city":"Kittery",
    "sg:classifiers":[
        {
            "category":"Education",
            "subcategory":"School",
            "type":"Public Place"
        }
    ],
    "sg:phone":"+1 207 439 1122",
    "sg:postcode":"03904",
    "sg:province":"ME",
    "wof:name":"Frisbee Elementary School",
    "wof:placetype":"venue"
},
  "geometry": {"coordinates":[-70.737655,43.094895],"type":"Point"}
}