{
  "type": "Feature",
  "properties": {
    "iso:country":"US",
    "sg:address":"17 Grover Ave",
    "sg:city":"Eliot",
    "sg:classifiers":[
        {
            "category":"Building & Trades",
            "subcategory":"Construction",
            "type":"Services"
        }
    ],
    "sg:phone":"+1 207 439 2995",
    "sg:postcode":"03903",
    "sg:province":"ME",
    "sg:tags":[
        "excavating",
        "contractor"
    ],
    "wof:name":"M K Murphy Inc",
    "wof:placetype":"venue"
},
  "geometry": {"coordinates":[-70.773086,43.09673],"type":"Point"}
}