{
  "type": "Feature",
  "properties": {
    "addr:full":"77 Summit Hill Rd Harrison ME 04040",
    "addr:housenumber":"77",
    "addr:postcode":"04040",
    "addr:street":"Summit Hill Rd",
    "iso:country":"US",
    "sg:address":"77 Summit Hill Rd",
    "sg:city":"Harrison",
    "sg:classifiers":[
        {
            "category":"Shopping",
            "subcategory":"Books",
            "type":"Retail Goods"
        }
    ],
    "sg:phone":"+1 207 693 7993",
    "sg:postcode":"04040",
    "sg:province":"ME",
    "wof:name":"Books Because",
    "wof:placetype":"venue"
},
  "geometry": {"coordinates":[-70.639932,44.128862],"type":"Point"}
}