{
  "type": "Feature",
  "properties": {
    "addr:full":"46 Leighton Rd Falmouth ME 04105",
    "addr:housenumber":"46",
    "addr:postcode":"04105",
    "addr:street":"Leighton Rd",
    "iso:country":"US",
    "sg:address":"46 Leighton Rd",
    "sg:city":"Falmouth",
    "sg:classifiers":[
        {
            "category":"Social Services",
            "subcategory":"Child Care",
            "type":"Services"
        }
    ],
    "sg:phone":"+1 207 878 3331",
    "sg:postcode":"04105",
    "sg:province":"ME",
    "wof:name":"Little Hands Daycare & Lrnng",
    "wof:placetype":"venue"
},
  "geometry": {"coordinates":[-70.29540900000001,43.736987],"type":"Point"}
}