{
  "type": "Feature",
  "properties": {
    "iso:country":"US",
    "sg:address":"803 Congress St",
    "sg:city":"Portland",
    "sg:classifiers":[
        {
            "category":"Restaurant",
            "type":"Food & Drink"
        }
    ],
    "sg:phone":"+1 207 775 0640",
    "sg:postcode":"04102",
    "sg:province":"ME",
    "sg:tags":[
        "shop",
        "coffee"
    ],
    "wof:name":"Youngo's",
    "wof:placetype":"venue"
},
  "geometry": {"coordinates":[-70.27371,43.654548],"type":"Point"}
}