{
  "type": "Feature",
  "properties": {
    "iso:country":"US",
    "sg:address":"693 Congress St",
    "sg:city":"Portland",
    "sg:classifiers":[
        {
            "category":"Shopping",
            "subcategory":"Used Merchandise",
            "type":"Retail Goods"
        }
    ],
    "sg:phone":"+1 207 772 4903",
    "sg:postcode":"04102",
    "sg:province":"ME",
    "sg:tags":[
        "shop",
        "thrift"
    ],
    "wof:name":"Good Cause Thrift Shop",
    "wof:placetype":"venue"
},
  "geometry": {"coordinates":[-70.267354,43.65318],"type":"Point"}
}