{
  "type": "Feature",
  "properties": {
    "iso:country":"US",
    "sg:address":"238 Roosevelt Trl",
    "sg:city":"Windham",
    "sg:classifiers":[
        {
            "category":"Restaurant",
            "type":"Food & Drink"
        }
    ],
    "sg:phone":"+1 207 892 9443",
    "sg:postcode":"04062",
    "sg:province":"ME",
    "sg:tags":[
        "beverage"
    ],
    "wof:name":"Windham Redemption Ctr",
    "wof:placetype":"venue"
},
  "geometry": {"coordinates":[-70.410167,43.806025],"type":"Point"}
}