{
  "type": "Feature",
  "properties": {
    "iso:country":"US",
    "sg:address":"41 Hood Dr",
    "sg:city":"Turner",
    "sg:classifiers":[
        {
            "category":"Freight",
            "type":"Transportation"
        }
    ],
    "sg:phone":"+1 207 225 2157",
    "sg:postcode":"04282",
    "sg:province":"ME",
    "sg:tags":[
        "truck"
    ],
    "wof:name":"A Hood & Son Inc",
    "wof:placetype":"venue"
},
  "geometry": {"coordinates":[-70.192773,44.289114],"type":"Point"}
}