{
  "type": "Feature",
  "properties": {
    "iso:country":"US",
    "sg:address":"389 Main St",
    "sg:city":"Rockland",
    "sg:classifiers":[
        {
            "category":"Personal",
            "subcategory":"Beauty Salon",
            "type":"Services"
        }
    ],
    "sg:phone":"+1 207 594 5077",
    "sg:postcode":"04841",
    "sg:province":"ME",
    "wof:name":"Nordstrom Skin Care Studio",
    "wof:placetype":"venue"
},
  "geometry": {"coordinates":[-69.109078,44.104032],"type":"Point"}
}