{
  "type": "Feature",
  "properties": {
    "iso:country":"US",
    "sg:address":"9 Westbrook St",
    "sg:city":"South Thomaston",
    "sg:classifiers":[
        {
            "category":"Retail",
            "subcategory":"Auto Repair",
            "type":"Services"
        }
    ],
    "sg:phone":"+1 207 594 8568",
    "sg:postcode":"04858",
    "sg:province":"ME",
    "sg:tags":[
        "body",
        "automobile",
        "painting"
    ],
    "wof:name":"Charlie's Body Shop",
    "wof:placetype":"venue"
},
  "geometry": {"coordinates":[-69.135879,44.053144],"type":"Point"}
}