{
  "type": "Feature",
  "properties": {
    "iso:country":"US",
    "sg:address":"11 Key Hill Rd",
    "sg:city":"Greene",
    "sg:classifiers":[
        {
            "category":"Shopping",
            "subcategory":"Used Merchandise",
            "type":"Retail Goods"
        }
    ],
    "sg:phone":"+1 207 946 5711",
    "sg:postcode":"04236",
    "sg:province":"ME",
    "sg:tags":[
        "antique"
    ],
    "wof:name":"Wilbur's Antiques",
    "wof:placetype":"venue"
},
  "geometry": {"coordinates":[-70.099508,44.20857],"type":"Point"}
}