{
  "type": "Feature",
  "properties": {
    "addr:full":"140 Ocean Ave Kennebunkport ME 04046",
    "addr:housenumber":"140",
    "addr:postcode":"04046",
    "addr:street":"Ocean Ave",
    "iso:country":"US",
    "sg:address":"140 Ocean Ave",
    "sg:city":"Kennebunkport",
    "sg:classifiers":[
        {
            "category":"Travel",
            "subcategory":"Hotels & Motels",
            "type":"Entertainment"
        }
    ],
    "sg:phone":"+1 207 967 3331",
    "sg:postcode":"04046",
    "sg:province":"ME",
    "sg:website":"www.thecolonyhotel.com",
    "wof:name":"Colony Hotel the",
    "wof:placetype":"venue"
},
  "geometry": {"coordinates":[-70.472553,43.348278],"type":"Point"}
}