{
  "type": "Feature",
  "properties": {
    "addr:full":"95 Main St Fryeburg ME 04037",
    "addr:housenumber":"95",
    "addr:postcode":"04037",
    "addr:street":"Main St",
    "iso:country":"US",
    "sg:address":"95 Main St",
    "sg:city":"Fryeburg",
    "sg:classifiers":[
        {
            "category":"Utilities",
            "subcategory":"Fuel Oil & Lpg",
            "type":"Services"
        }
    ],
    "sg:phone":"+1 207 935 2447",
    "sg:postcode":"04037",
    "sg:province":"ME",
    "sg:tags":[
        "dealer"
    ],
    "wof:name":"Red Shield Heating Oil",
    "wof:placetype":"venue"
},
  "geometry": {"coordinates":[-70.98403399999999,44.014102],"type":"Point"}
}