{
  "type": "Feature",
  "properties": {
    "iso:country":"US",
    "sg:address":"77 State St",
    "sg:city":"Ellsworth",
    "sg:classifiers":[
        {
            "category":"Professional",
            "subcategory":"Lawyer & Legal Services",
            "type":"Services"
        }
    ],
    "sg:phone":"+1 207 667 3005",
    "sg:postcode":"04605",
    "sg:province":"ME",
    "sg:tags":[
        "attorney"
    ],
    "wof:name":"Patterson Law Offices",
    "wof:placetype":"venue"
},
  "geometry": {"coordinates":[-68.42529,44.544278],"type":"Point"}
}