{
  "type": "Feature",
  "properties": {
    "addr:full":"190 Beechwood St Warren ME 04864",
    "addr:housenumber":"190",
    "addr:postcode":"04864",
    "addr:street":"Beechwood St",
    "iso:country":"US",
    "sg:address":"190 Beechwood St",
    "sg:city":"Warren",
    "sg:classifiers":[
        {
            "category":"Personal",
            "type":"Services"
        }
    ],
    "sg:phone":"+1 207 273 4301",
    "sg:postcode":"04864",
    "sg:province":"ME",
    "wof:name":"Papa Bears Odd Jobs",
    "wof:placetype":"venue"
},
  "geometry": {"coordinates":[-69.20425899999999,44.137306],"type":"Point"}
}