{
  "type": "Feature",
  "properties": {
    "iso:country":"US",
    "sg:address":"78 Bay St",
    "sg:city":"Winslow",
    "sg:classifiers":[
        {
            "category":"Autos & Motor Vehicles",
            "subcategory":"Auto Supplies",
            "type":"Retail Goods"
        }
    ],
    "sg:phone":"+1 207 873 2546",
    "sg:postcode":"04901",
    "sg:province":"ME",
    "sg:tags":[
        "tire"
    ],
    "wof:name":"VIP Discount Auto Ctr",
    "wof:placetype":"venue"
},
  "geometry": {"coordinates":[-69.627693,44.539568],"type":"Point"}
}