{
  "type": "Feature",
  "properties": {
    "iso:country":"US",
    "sg:address":"9 Chandler Rd",
    "sg:city":"Presque Isle",
    "sg:classifiers":[
        {
            "category":"Personal",
            "subcategory":"Shoe Repair & Shine",
            "type":"Services"
        }
    ],
    "sg:phone":"+1 207 764 8533",
    "sg:postcode":"04769",
    "sg:province":"ME",
    "sg:tags":[
        "parlor"
    ],
    "wof:name":"Coles Shoe Repair",
    "wof:placetype":"venue"
},
  "geometry": {"coordinates":[-68.04508800000001,46.759222],"type":"Point"}
}