{
  "type": "Feature",
  "properties": {
    "iso:country":"US",
    "sg:address":"87 Essex St",
    "sg:city":"Lewiston",
    "sg:classifiers":[
        {
            "category":"Insurance",
            "subcategory":"Insurance Agent",
            "type":"Services"
        }
    ],
    "sg:phone":"+1 207 784 5181",
    "sg:postcode":"04240",
    "sg:province":"ME",
    "wof:name":"Parent Insurance",
    "wof:placetype":"venue"
},
  "geometry": {"coordinates":[-70.206401,44.083383],"type":"Point"}
}