{
  "type": "Feature",
  "properties": {
    "addr:full":"45 Highland Ave Ogunquit ME 03907",
    "addr:housenumber":"45",
    "addr:postcode":"03907",
    "addr:street":"Highland Ave",
    "iso:country":"US",
    "sg:address":"45 Highland Ave",
    "sg:city":"Ogunquit",
    "sg:classifiers":[
        {
            "category":"Real Estate",
            "subcategory":"Real Estate Services",
            "type":"Services"
        }
    ],
    "sg:phone":"+1 207 646 1043",
    "sg:postcode":"03907",
    "sg:province":"ME",
    "sg:tags":[
        "company",
        "title"
    ],
    "wof:name":"Elliot Title Co",
    "wof:placetype":"venue"
},
  "geometry": {"coordinates":[-70.608428,43.24749],"type":"Point"}
}