{
  "type": "Feature",
  "properties": {
    "addr:full":"385 Main St South Portland ME 04106",
    "addr:housenumber":"385",
    "addr:postcode":"04106",
    "addr:street":"Main St",
    "iso:country":"US",
    "sg:address":"385 Main St",
    "sg:city":"South Portland",
    "sg:classifiers":[
        {
            "category":"Professional",
            "subcategory":"Business Services",
            "type":"Services"
        }
    ],
    "sg:phone":"+1 207 767 6004",
    "sg:postcode":"04106",
    "sg:province":"ME",
    "sg:tags":[
        "delivery",
        "courier"
    ],
    "sg:website":"www.generalcourier.com",
    "wof:name":"General Courier",
    "wof:placetype":"venue"
},
  "geometry": {"coordinates":[-70.29512200000001,43.62786],"type":"Point"}
}