{
  "type": "Feature",
  "properties": {
    "iso:country":"US",
    "sg:address":"5 Cole Rd",
    "sg:city":"Raymond",
    "sg:classifiers":[
        {
            "category":"Building & Trades",
            "subcategory":"Construction",
            "type":"Services"
        }
    ],
    "sg:phone":"+1 207 428 3370",
    "sg:postcode":"04071",
    "sg:province":"ME",
    "sg:tags":[
        "concrete",
        "contractor"
    ],
    "wof:name":"Metayer Foundation",
    "wof:placetype":"venue"
},
  "geometry": {"coordinates":[-70.417513,43.887463],"type":"Point"}
}