{
  "type": "Feature",
  "properties": {
    "iso:country":"US",
    "sg:address":"54 Centre St",
    "sg:city":"Bath",
    "sg:classifiers":[
        {
            "category":"Restaurant",
            "type":"Food & Drink"
        }
    ],
    "sg:phone":"+1 207 443 4126",
    "sg:postcode":"04530",
    "sg:province":"ME",
    "wof:name":"Mario's Pizza Of Bath",
    "wof:placetype":"venue"
},
  "geometry": {"coordinates":[-69.814163,43.912755],"type":"Point"}
}