{
  "type": "Feature",
  "properties": {
    "iso:country":"US",
    "sg:address":"5 Kimbal St",
    "sg:city":"Richmond",
    "sg:classifiers":[
        {
            "category":"Recreation",
            "subcategory":"Marina",
            "type":"Entertainment"
        }
    ],
    "sg:phone":"+1 207 737 8401",
    "sg:postcode":"04357",
    "sg:province":"ME",
    "sg:tags":[
        "yard",
        "boat"
    ],
    "wof:name":"Ideal Auto & Marine",
    "wof:placetype":"venue"
},
  "geometry": {"coordinates":[-69.798136,44.08923],"type":"Point"}
}