{
  "type": "Feature",
  "properties": {
    "iso:country":"US",
    "sg:address":"1743 Federal Rd",
    "sg:city":"Livermore",
    "sg:classifiers":[
        {
            "category":"Shopping",
            "subcategory":"Discount & Variety Stores",
            "type":"Retail Goods"
        }
    ],
    "sg:phone":"+1 207 897 2151",
    "sg:postcode":"04253",
    "sg:province":"ME",
    "wof:name":"Brettun's Variety",
    "wof:placetype":"venue"
},
  "geometry": {"coordinates":[-70.250387,44.37446],"type":"Point"}
}