{
  "type": "Feature",
  "properties": {
    "addr:full":"67 College Ave Orono ME 04473",
    "addr:housenumber":"67",
    "addr:postcode":"04473",
    "addr:street":"College Ave",
    "iso:country":"US",
    "sg:address":"67 College Ave",
    "sg:city":"Orono",
    "sg:classifiers":[
        {
            "category":"Education",
            "subcategory":"Dance Studio",
            "type":"Public Place"
        },
        {
            "category":"Organizations",
            "subcategory":"Religious Organization",
            "type":"Services"
        }
    ],
    "sg:phone":"+1 207 866 4227",
    "sg:postcode":"04473",
    "sg:province":"ME",
    "sg:tags":[
        "church"
    ],
    "wof:name":"Maine Christian Association",
    "wof:placetype":"venue"
},
  "geometry": {"coordinates":[-68.67115099999999,44.890477],"type":"Point"}
}