{
  "type": "Feature",
  "properties": {
    "addr:full":"349 Center Conway Rd Brownfield ME 04010",
    "addr:housenumber":"349",
    "addr:postcode":"04010",
    "addr:street":"Center Conway Rd",
    "iso:country":"US",
    "sg:address":"349 Center Conway Rd",
    "sg:city":"Brownfield",
    "sg:classifiers":[
        {
            "category":"Bakery",
            "type":"Food & Drink"
        }
    ],
    "sg:phone":"+1 207 935 7415",
    "sg:postcode":"04010",
    "sg:province":"ME",
    "sg:website":"www.grandyoats.com",
    "wof:name":"Grandy Oats",
    "wof:placetype":"venue"
},
  "geometry": {"coordinates":[-70.994698,43.9575],"type":"Point"}
}