{
  "type": "Feature",
  "properties": {
    "addr:full":"135 Walton St Portland ME 04103",
    "addr:housenumber":"135",
    "addr:postcode":"04103",
    "addr:street":"Walton St",
    "iso:country":"US",
    "sg:address":"135 Walton St",
    "sg:city":"Portland",
    "sg:classifiers":[
        {
            "category":"Real Estate",
            "subcategory":"Architect",
            "type":"Services"
        }
    ],
    "sg:phone":"+1 207 761 8436",
    "sg:postcode":"04103",
    "sg:province":"ME",
    "sg:tags":[
        "building",
        "construction"
    ],
    "wof:name":"Construction Administration",
    "wof:placetype":"venue"
},
  "geometry": {"coordinates":[-70.28695500000001,43.679325],"type":"Point"}
}