{
  "type": "Feature",
  "properties": {
    "addr:full":"159 Biddeford Rd Alfred ME 04002",
    "addr:housenumber":"159",
    "addr:postcode":"04002",
    "addr:street":"Biddeford Rd",
    "iso:country":"US",
    "sg:address":"159 Biddeford Rd",
    "sg:city":"Alfred",
    "sg:classifiers":[
        {
            "category":"Shopping",
            "subcategory":"Clothing, Apparel, & Fashions",
            "type":"Retail Goods"
        }
    ],
    "sg:phone":"+1 207 490 3763",
    "sg:postcode":"04002",
    "sg:province":"ME",
    "sg:tags":[
        "shop",
        "bridal"
    ],
    "wof:name":"Bridal's By Sandy",
    "wof:placetype":"venue"
},
  "geometry": {"coordinates":[-70.707887,43.475942],"type":"Point"}
}