{
  "type": "Feature",
  "properties": {
    "addr:full":"219 Mount Auburn Ave Auburn ME 04210",
    "addr:housenumber":"219",
    "addr:postcode":"04210",
    "addr:street":"Mount Auburn Ave",
    "iso:country":"US",
    "sg:address":"219 Mount Auburn Ave",
    "sg:city":"Auburn",
    "sg:classifiers":[
        {
            "category":"Insurance",
            "subcategory":"Insurance Agent",
            "type":"Services"
        }
    ],
    "sg:phone":"+1 207 777 7779",
    "sg:postcode":"04210",
    "sg:province":"ME",
    "wof:name":"Horace Mann Insurance Co",
    "wof:placetype":"venue"
},
  "geometry": {"coordinates":[-70.23694399999999,44.120988],"type":"Point"}
}