{
  "type": "Feature",
  "properties": {
    "addr:full":"143 Maverick St Rockland ME 04841",
    "addr:housenumber":"143",
    "addr:postcode":"04841",
    "addr:street":"Maverick St",
    "iso:country":"US",
    "sg:address":"143 Maverick St",
    "sg:city":"Rockland",
    "sg:classifiers":[
        {
            "category":"Shopping",
            "subcategory":"Bicycles & Sporting Goods",
            "type":"Retail Goods"
        }
    ],
    "sg:phone":"+1 207 596 1004",
    "sg:postcode":"04841",
    "sg:province":"ME",
    "wof:name":"Bikesenjava",
    "wof:placetype":"venue"
},
  "geometry": {"coordinates":[-69.110584,44.118875],"type":"Point"}
}