{
  "type": "Feature",
  "properties": {
    "addr:full":"61 Long Beach Ave York ME 03909",
    "addr:housenumber":"61",
    "addr:postcode":"03909",
    "addr:street":"Long Beach Ave",
    "iso:country":"US",
    "sg:address":"61 Long Beach Ave",
    "sg:city":"York",
    "sg:classifiers":[
        {
            "category":"Travel",
            "subcategory":"Hotels & Motels",
            "type":"Entertainment"
        }
    ],
    "sg:phone":"+1 207 363 5137",
    "sg:postcode":"03909",
    "sg:province":"ME",
    "wof:name":"Sea Turn Motel",
    "wof:placetype":"venue"
},
  "geometry": {"coordinates":[-70.61039700000001,43.170799],"type":"Point"}
}