{
  "type": "Feature",
  "properties": {
    "iso:country":"US",
    "sg:address":"67 Main St",
    "sg:city":"Mattawamkeag",
    "sg:classifiers":[
        {
            "category":"Retail",
            "subcategory":"Auto Repair",
            "type":"Services"
        }
    ],
    "sg:phone":"+1 207 736 4202",
    "sg:postcode":"04473",
    "sg:province":"ME",
    "sg:tags":[
        "repairing",
        "automobile"
    ],
    "wof:name":"Markie's Garage",
    "wof:placetype":"venue"
},
  "geometry": {"coordinates":[-68.67319500000001,44.882093],"type":"Point"}
}