{
  "type": "Feature",
  "properties": {
    "iso:country":"US",
    "sg:address":"8 Main St",
    "sg:city":"Newport",
    "sg:classifiers":[
        {
            "category":"Shopping",
            "subcategory":"Computers & Home Electronics",
            "type":"Retail Goods"
        }
    ],
    "sg:phone":"+1 207 368 4628",
    "sg:postcode":"04953",
    "sg:province":"ME",
    "sg:tags":[
        "software"
    ],
    "wof:name":"PHD Consulting",
    "wof:placetype":"venue"
},
  "geometry": {"coordinates":[-69.272909,44.835173],"type":"Point"}
}