{
  "type": "Feature",
  "properties": {
    "addr:full":"30 Pleasant Hill Rd Scarborough ME 04074",
    "addr:housenumber":"30",
    "addr:postcode":"04074",
    "addr:street":"Pleasant Hill Rd",
    "iso:country":"US",
    "sg:address":"30 Pleasant Hill Rd",
    "sg:city":"Scarborough",
    "sg:classifiers":[
        {
            "category":"Autos & Motor Vehicles",
            "subcategory":"Automobile Sales",
            "type":"Retail Goods"
        },
        {
            "category":"Airline",
            "type":"Transportation"
        }
    ],
    "sg:phone":"+1 207 883 0222",
    "sg:postcode":"04074",
    "sg:province":"ME",
    "sg:tags":[
        "shuttle",
        "airport",
        "limo"
    ],
    "wof:name":"Flo Hutchins Limousine Service",
    "wof:placetype":"venue"
},
  "geometry": {"coordinates":[-70.310303,43.609299],"type":"Point"}
}