{
  "type": "Feature",
  "properties": {
    "addr:full":"471 S Main St Brewer ME 04412",
    "addr:housenumber":"471",
    "addr:postcode":"04412",
    "addr:street":"S Main St",
    "iso:country":"US",
    "sg:address":"471 S Main St",
    "sg:city":"Brewer",
    "sg:classifiers":[
        {
            "category":"Banks & Credit Unions",
            "subcategory":"Bank",
            "type":"Services"
        }
    ],
    "sg:phone":"+1 207 989 7600",
    "sg:postcode":"04412",
    "sg:province":"ME",
    "sg:tags":[
        "loan",
        "real estate"
    ],
    "wof:name":"Innovative Home Mortgage",
    "wof:placetype":"venue"
},
  "geometry": {"coordinates":[-68.779421,44.774649],"type":"Point"}
}