{
  "type": "Feature",
  "properties": {
    "iso:country":"US",
    "sg:address":"40 S Main St",
    "sg:city":"Brewer",
    "sg:classifiers":[
        {
            "category":"Organizations",
            "subcategory":"Religious Organization",
            "type":"Services"
        }
    ],
    "sg:phone":"+1 207 989 7310",
    "sg:postcode":"04412",
    "sg:province":"ME",
    "sg:tags":[
        "church"
    ],
    "wof:name":"First United Methodist Church",
    "wof:placetype":"venue"
},
  "geometry": {"coordinates":[-68.76655100000001,44.794238],"type":"Point"}
}