{
  "type": "Feature",
  "properties": {
    "addr:full":"663 Stillwater Ave Bangor ME 04401",
    "addr:housenumber":"663",
    "addr:postcode":"04401",
    "addr:street":"Stillwater Ave",
    "iso:country":"US",
    "sg:address":"663 Stillwater Ave",
    "sg:city":"Bangor",
    "sg:classifiers":[
        {
            "category":"Restaurant",
            "type":"Food & Drink"
        }
    ],
    "sg:menulink":"http://www.allmenus.com/me/bangor/103689-ruby-tuesdays/menu/",
    "sg:phone":"+1 207 942 3442",
    "sg:postcode":"04401",
    "sg:province":"ME",
    "sg:tags":[
        "burger",
        "american"
    ],
    "wof:name":"Ruby Tuesdays",
    "wof:placetype":"venue"
},
  "geometry": {"coordinates":[-68.751597,44.832524],"type":"Point"}
}