{
  "type": "Feature",
  "properties": {
    "iso:country":"US",
    "sg:address":"5 Bennett Dr",
    "sg:city":"Caribou",
    "sg:classifiers":[
        {
            "category":"Manufacturing",
            "subcategory":"Printing",
            "type":"Manufacturing & Wholesale Goods"
        }
    ],
    "sg:phone":"+1 207 492 1228",
    "sg:postcode":"04736",
    "sg:province":"ME",
    "sg:tags":[
        "printer"
    ],
    "wof:name":"Gossamer Press",
    "wof:placetype":"venue"
},
  "geometry": {"coordinates":[-68.004701,46.862401],"type":"Point"}
}