{
  "type": "Feature",
  "properties": {
    "addr:full":"20 Pond Rd Newcastle ME 04553",
    "addr:housenumber":"20",
    "addr:postcode":"04553",
    "addr:street":"Pond Rd",
    "iso:country":"US",
    "sg:address":"20 Pond Rd",
    "sg:city":"Newcastle",
    "sg:classifiers":[
        {
            "category":"Professional",
            "subcategory":"Management & Consulting",
            "type":"Services"
        }
    ],
    "sg:phone":"+1 207 563 7695",
    "sg:postcode":"04553",
    "sg:province":"ME",
    "sg:tags":[
        "counselor",
        "public",
        "relations"
    ],
    "sg:website":"www.planetfriendlypr.com",
    "wof:name":"Planet Friendly Public Relatio",
    "wof:placetype":"venue"
},
  "geometry": {"coordinates":[-69.529633,44.061365],"type":"Point"}
}