{
  "type": "Feature",
  "properties": {
    "iso:country":"US",
    "sg:address":"14 Atlantic Hwy",
    "sg:city":"Waldoboro",
    "sg:classifiers":[
        {
            "category":"Retail",
            "subcategory":"Veterinary Services",
            "type":"Services"
        }
    ],
    "sg:phone":"+1 207 563 7786",
    "sg:postcode":"04572",
    "sg:province":"ME",
    "sg:tags":[
        "veterinarian"
    ],
    "wof:name":"Medomak Veterinary Svc",
    "wof:placetype":"venue"
},
  "geometry": {"coordinates":[-69.438104,44.103711],"type":"Point"}
}