{
  "type": "Feature",
  "properties": {
    "iso:country":"US",
    "sg:address":"1276 Bristol Rd",
    "sg:city":"Bristol",
    "sg:classifiers":[
        {
            "category":"Personal",
            "type":"Services"
        }
    ],
    "sg:phone":"+1 207 563 5329",
    "sg:postcode":"04539",
    "sg:province":"ME",
    "sg:tags":[
        "therapist",
        "massage"
    ],
    "wof:name":"Warner",
    "wof:placetype":"venue"
},
  "geometry": {"coordinates":[-69.509206,43.957504],"type":"Point"}
}