{
  "type": "Feature",
  "properties": {
    "iso:country":"US",
    "sg:address":"24 Manor Dr",
    "sg:city":"Ocean Park",
    "sg:classifiers":[
        {
            "category":"Government",
            "subcategory":"Office",
            "type":"Public Place"
        }
    ],
    "sg:phone":"+1 207 934 4416",
    "sg:postcode":"04090",
    "sg:province":"ME",
    "sg:tags":[
        "village"
    ],
    "wof:name":"Old Orchard Bch Sewerage Plant",
    "wof:placetype":"venue"
},
  "geometry": {"coordinates":[-70.720735,43.333738],"type":"Point"}
}