{
  "type": "Feature",
  "properties": {
    "addr:full":"21 Flat Rock Bridge Rd Lebanon ME 04027",
    "addr:housenumber":"21",
    "addr:postcode":"04027",
    "addr:street":"Flat Rock Bridge Rd",
    "iso:country":"US",
    "sg:address":"21 Flat Rock Bridge Rd",
    "sg:city":"Lebanon",
    "sg:classifiers":[
        {
            "category":"Travel",
            "subcategory":"Campground",
            "type":"Entertainment"
        }
    ],
    "sg:phone":"+1 207 339 9465",
    "sg:postcode":"04027",
    "sg:province":"ME",
    "sg:website":"www.kingsandqueenscamping.com",
    "wof:name":"Kings-Queens Court Resort",
    "wof:placetype":"venue"
},
  "geometry": {"coordinates":[-70.966117,43.345439],"type":"Point"}
}