{
  "type": "Feature",
  "properties": {
    "iso:country":"US",
    "sg:address":"262 Bath Rd",
    "sg:city":"Brunswick",
    "sg:classifiers":[
        {
            "category":"Autos & Motor Vehicles",
            "subcategory":"Automobile Sales",
            "type":"Retail Goods"
        }
    ],
    "sg:phone":"+1 207 729 6653",
    "sg:postcode":"04011",
    "sg:province":"ME",
    "sg:tags":[
        "car",
        "dealer"
    ],
    "wof:name":"Bill Dodge Oldsmobile Buick",
    "wof:placetype":"venue"
},
  "geometry": {"coordinates":[-69.907779,43.909469],"type":"Point"}
}