{
  "type": "Feature",
  "properties": {
    "iso:country":"US",
    "sg:address":"29 River St",
    "sg:city":"Houlton",
    "sg:classifiers":[
        {
            "category":"Retail",
            "subcategory":"Auto Repair",
            "type":"Services"
        }
    ],
    "sg:phone":"+1 207 532 2088",
    "sg:postcode":"04730",
    "sg:province":"ME",
    "sg:tags":[
        "shop",
        "automotive",
        "automobile",
        "repairing",
        "general"
    ],
    "wof:name":"Wiggin's Auto Repair",
    "wof:placetype":"venue"
},
  "geometry": {"coordinates":[-67.835037,46.130313],"type":"Point"}
}