{
  "type": "Feature",
  "properties": {
    "iso:country":"US",
    "sg:address":"36 Moosehead Rd",
    "sg:city":"Greenville",
    "sg:classifiers":[
        {
            "category":"Professional",
            "subcategory":"Management & Consulting",
            "type":"Services"
        }
    ],
    "sg:phone":"+1 207 695 3355",
    "sg:postcode":"04469",
    "sg:province":"ME",
    "sg:tags":[
        "consultant",
        "educational"
    ],
    "wof:name":"Evergreen Enrichment Cllbrtv",
    "wof:placetype":"venue"
},
  "geometry": {"coordinates":[-68.670152,44.898813],"type":"Point"}
}