{
  "type": "Feature",
  "properties": {
    "iso:country":"US",
    "sg:address":"2 High St",
    "sg:city":"Rangeley",
    "sg:classifiers":[
        {
            "category":"Organizations",
            "subcategory":"Religious Organization",
            "type":"Services"
        }
    ],
    "sg:phone":"+1 207 864 5966",
    "sg:postcode":"04970",
    "sg:province":"ME",
    "sg:tags":[
        "church"
    ],
    "wof:name":"Rangeley Congregational Church",
    "wof:placetype":"venue"
},
  "geometry": {"coordinates":[-70.644787,44.9672],"type":"Point"}
}