{
  "type": "Feature",
  "properties": {
    "addr:full":"2 Boynton Rd Mars Hill ME 04758",
    "addr:housenumber":"2",
    "addr:postcode":"04758",
    "addr:street":"Boynton Rd Mars Hill",
    "iso:country":"US",
    "sg:address":"2 Boynton Rd",
    "sg:city":"Mars Hill",
    "sg:classifiers":[
        {
            "category":"Retail",
            "subcategory":"Auto Repair",
            "type":"Services"
        }
    ],
    "sg:phone":"+1 207 429 9140",
    "sg:postcode":"04758",
    "sg:province":"ME",
    "sg:tags":[
        "repairing",
        "automobile"
    ],
    "wof:name":"A & M Auto Repair",
    "wof:placetype":"venue"
},
  "geometry": {"coordinates":[-67.85513,46.521536],"type":"Point"}
}