{
  "type": "Feature",
  "properties": {
    "addr:full":"1091 Congress St Portland ME 04102",
    "addr:housenumber":"1091",
    "addr:postcode":"04102",
    "addr:street":"Congress St",
    "iso:country":"US",
    "sg:address":"1091 Congress St",
    "sg:city":"Portland",
    "sg:classifiers":[
        {
            "category":"Restaurant",
            "type":"Food & Drink"
        }
    ],
    "sg:menulink":"http://www.allmenus.com/me/portland/11129-dennys/menu/",
    "sg:phone":"+1 207 774 1886",
    "sg:postcode":"04102",
    "sg:province":"ME",
    "sg:tags":[
        "american",
        "diner"
    ],
    "wof:name":"Denny's",
    "wof:placetype":"venue"
},
  "geometry": {"coordinates":[-70.283902,43.654143],"type":"Point"}
}