{
  "type": "Feature",
  "properties": {
    "addr:full":"100 Graham Rd Easton ME 04740",
    "addr:housenumber":"100",
    "addr:postcode":"04740",
    "addr:street":"Graham Rd",
    "iso:country":"US",
    "sg:address":"100 Graham Rd",
    "sg:city":"Easton",
    "sg:classifiers":[
        {
            "category":"Manufacturing",
            "subcategory":"Wood Products",
            "type":"Manufacturing & Wholesale Goods"
        }
    ],
    "sg:phone":"+1 207 488 5890",
    "sg:postcode":"04740",
    "sg:province":"ME",
    "sg:tags":[
        "mfg"
    ],
    "wof:name":"Vintage Candleworks",
    "wof:placetype":"venue"
},
  "geometry": {"coordinates":[-67.802533,46.635301],"type":"Point"}
}