{
  "type": "Feature",
  "properties": {
    "iso:country":"US",
    "sg:address":"885 Broadway",
    "sg:city":"Bangor",
    "sg:classifiers":[
        {
            "category":"Communications",
            "subcategory":"Radio Station",
            "type":"Services"
        }
    ],
    "sg:phone":"+1 207 947 1863",
    "sg:postcode":"04401",
    "sg:province":"ME",
    "sg:tags":[
        "company",
        "broadcasting"
    ],
    "wof:name":"Clear Channel Radio",
    "wof:placetype":"venue"
},
  "geometry": {"coordinates":[-68.784959,44.829447],"type":"Point"}
}