{
  "type": "Feature",
  "properties": {
    "addr:full":"1231 Maine St Poland ME 04274",
    "addr:housenumber":"1231",
    "addr:postcode":"04274",
    "addr:street":"Maine St",
    "iso:country":"US",
    "sg:address":"1231 Maine St",
    "sg:city":"Poland",
    "sg:classifiers":[
        {
            "category":"Government",
            "subcategory":"Office",
            "type":"Public Place"
        }
    ],
    "sg:phone":"+1 207 998 4601",
    "sg:postcode":"04274",
    "sg:province":"ME",
    "sg:tags":[
        "village"
    ],
    "sg:website":"www.polandtownoffice.org",
    "wof:name":"Poland Town Office",
    "wof:placetype":"venue"
},
  "geometry": {"coordinates":[-70.403909,44.068209],"type":"Point"}
}