{
  "type": "Feature",
  "properties": {
    "addr:full":"8 Holbrook St Freeport ME 04032",
    "addr:housenumber":"8",
    "addr:postcode":"04032",
    "addr:street":"Holbrook St",
    "iso:country":"US",
    "sg:address":"8 Holbrook St",
    "sg:city":"Freeport",
    "sg:classifiers":[
        {
            "category":"Travel",
            "subcategory":"Hotels & Motels",
            "type":"Entertainment"
        }
    ],
    "sg:phone":"+1 207 865 9705",
    "sg:postcode":"04032",
    "sg:province":"ME",
    "wof:name":"Applewood Inn",
    "wof:placetype":"venue"
},
  "geometry": {"coordinates":[-70.110596,43.857707],"type":"Point"}
}