{
  "type": "Feature",
  "properties": {
    "iso:country":"US",
    "sg:address":"27 Main St",
    "sg:city":"Damariscotta",
    "sg:classifiers":[
        {
            "category":"Organizations",
            "subcategory":"Community Association",
            "type":"Services"
        }
    ],
    "sg:phone":"+1 207 563 3132",
    "sg:postcode":"04543",
    "sg:province":"ME",
    "wof:name":"P A D R E",
    "wof:placetype":"venue"
},
  "geometry": {"coordinates":[-69.532105,44.03302],"type":"Point"}
}