{
  "type": "Feature",
  "properties": {
    "addr:full":"73 Powers Rd South Portland ME 04106",
    "addr:housenumber":"73",
    "addr:postcode":"04106",
    "addr:street":"Powers Rd",
    "iso:country":"US",
    "sg:address":"73 Powers Rd",
    "sg:city":"South Portland",
    "sg:classifiers":[
        {
            "category":"Building & Trades",
            "subcategory":"Construction",
            "type":"Services"
        }
    ],
    "sg:phone":"+1 207 774 1154",
    "sg:postcode":"04106",
    "sg:province":"ME",
    "sg:tags":[
        "carpentry",
        "contractor"
    ],
    "wof:name":"Charron Carpentry",
    "wof:placetype":"venue"
},
  "geometry": {"coordinates":[-70.31561600000001,43.640801],"type":"Point"}
}