{
  "type": "Feature",
  "properties": {
    "addr:full":"10 Andrew Ave Sanford ME 04073",
    "addr:housenumber":"10",
    "addr:postcode":"04073",
    "addr:street":"Andrew Ave",
    "iso:country":"US",
    "sg:address":"10 Andrew Ave",
    "sg:city":"Sanford",
    "sg:classifiers":[
        {
            "category":"Real Estate",
            "subcategory":"Real Estate Agent",
            "type":"Services"
        }
    ],
    "sg:phone":"+1 207 324 6073",
    "sg:postcode":"04073",
    "sg:province":"ME",
    "wof:name":"Diane Cote",
    "wof:placetype":"venue"
},
  "geometry": {"coordinates":[-70.760446,43.421126],"type":"Point"}
}