{
  "type": "Feature",
  "properties": {
    "iso:country":"US",
    "sg:address":"425 Wilson St",
    "sg:city":"Brewer",
    "sg:classifiers":[
        {
            "category":"Banks & Credit Unions",
            "subcategory":"Bank",
            "type":"Services"
        }
    ],
    "sg:phone":"+1 207 989 1944",
    "sg:postcode":"04412",
    "sg:province":"ME",
    "wof:name":"Bangor Savings Bank",
    "wof:placetype":"venue"
},
  "geometry": {"coordinates":[-68.750799,44.783749],"type":"Point"}
}