{
  "type": "Feature",
  "properties": {
    "iso:country":"US",
    "sg:address":"54 Maine St",
    "sg:city":"Brunswick",
    "sg:classifiers":[
        {
            "category":"Food & Beverages",
            "subcategory":"Bakery",
            "type":"Retail Goods"
        }
    ],
    "sg:phone":"+1 207 729 4258",
    "sg:postcode":"04011",
    "sg:province":"ME",
    "sg:tags":[
        "doughnut"
    ],
    "wof:name":"Frosty's Donut & Coffee Shop",
    "wof:placetype":"venue"
},
  "geometry": {"coordinates":[-69.966295,43.917113],"type":"Point"}
}