{
  "type": "Feature",
  "properties": {
    "addr:full":"65 State St Augusta ME 04330",
    "addr:housenumber":"65",
    "addr:postcode":"04330",
    "addr:street":"State St",
    "iso:country":"US",
    "sg:address":"65 State St",
    "sg:city":"Augusta",
    "sg:classifiers":[
        {
            "category":"Organizations",
            "subcategory":"Labor Organization",
            "type":"Services"
        }
    ],
    "sg:phone":"+1 207 622 3151",
    "sg:postcode":"04330",
    "sg:province":"ME",
    "sg:website":"www.mseaseiu.org",
    "wof:name":"Maine State Employees Assn",
    "wof:placetype":"venue"
},
  "geometry": {"coordinates":[-69.77676599999999,44.31689],"type":"Point"}
}