{
  "type": "Feature",
  "properties": {
    "iso:country":"US",
    "sg:address":"965 Minot Ave",
    "sg:city":"Auburn",
    "sg:classifiers":[
        {
            "category":"Home & Garden",
            "subcategory":"Hardware",
            "type":"Retail Goods"
        }
    ],
    "sg:phone":"+1 207 783 0447",
    "sg:postcode":"04210",
    "sg:province":"ME",
    "wof:name":"Minot Ace Hardware",
    "wof:placetype":"venue"
},
  "geometry": {"coordinates":[-70.268548,44.081071],"type":"Point"}
}