{
  "type": "Feature",
  "properties": {
    "iso:country":"US",
    "sg:address":"61 Oak Grove Dr",
    "sg:city":"Brewer",
    "sg:classifiers":[
        {
            "category":"Professional",
            "type":"Services"
        }
    ],
    "sg:phone":"+1 207 989 9948",
    "sg:postcode":"04412",
    "sg:province":"ME",
    "wof:name":"Wendy L Durrah",
    "wof:placetype":"venue"
},
  "geometry": {"coordinates":[-68.743582,44.796184],"type":"Point"}
}