{
  "type": "Feature",
  "properties": {
    "iso:country":"US",
    "sg:address":"5 Hillview Ave",
    "sg:city":"Houlton",
    "sg:classifiers":[
        {
            "category":"Wholesale",
            "subcategory":"Farm Supplies",
            "type":"Manufacturing & Wholesale Goods"
        }
    ],
    "sg:phone":"+1 207 532 6130",
    "sg:postcode":"04730",
    "sg:province":"ME",
    "sg:tags":[
        "feed"
    ],
    "wof:name":"Aroostook Milling Co",
    "wof:placetype":"venue"
},
  "geometry": {"coordinates":[-67.82762,46.12449],"type":"Point"}
}