{
  "type": "Feature",
  "properties": {
    "addr:full":"25 Two Rod Rd Scarborough ME 04074",
    "addr:housenumber":"25",
    "addr:postcode":"04074",
    "addr:street":"Two Rod Rd",
    "iso:country":"US",
    "sg:address":"25 Two Rod Rd",
    "sg:city":"Scarborough",
    "sg:classifiers":[
        {
            "category":"Building & Trades",
            "subcategory":"Construction",
            "type":"Services"
        }
    ],
    "sg:phone":"+1 207 883 9749",
    "sg:postcode":"04074",
    "sg:province":"ME",
    "sg:tags":[
        "mobile",
        "home"
    ],
    "wof:name":"Right-Way Mobile Home Svc",
    "wof:placetype":"venue"
},
  "geometry": {"coordinates":[-70.371341,43.589586],"type":"Point"}
}