{
  "type": "Feature",
  "properties": {
    "addr:full":"225 Two Lights Road Cape Elizabeth ME 04107",
    "addr:housenumber":"225",
    "addr:postcode":"04107",
    "addr:street":"Two Lights Road",
    "iso:country":"US",
    "sg:address":"225 Two Lights Road",
    "sg:city":"Cape Elizabeth",
    "sg:classifiers":[
        {
            "category":"Restaurant",
            "type":"Food & Drink"
        }
    ],
    "sg:phone":"+1 207 799 1677",
    "sg:postcode":"04107",
    "sg:province":"ME",
    "sg:tags":[
        "seafood"
    ],
    "wof:name":"The Lobster Shack",
    "wof:placetype":"venue"
},
  "geometry": {"coordinates":[-70.20030199999999,43.563599],"type":"Point"}
}