{
  "type": "Feature",
  "properties": {
    "iso:country":"US",
    "sg:address":"155 Dresden Ave",
    "sg:city":"Gardiner",
    "sg:classifiers":[
        {
            "category":"Professional",
            "type":"Services"
        }
    ],
    "sg:phone":"+1 207 582 1430",
    "sg:postcode":"04345",
    "sg:province":"ME",
    "wof:name":"New England Nuclear Servi",
    "wof:placetype":"venue"
},
  "geometry": {"coordinates":[-69.769808,44.22099],"type":"Point"}
}