{
  "type": "Feature",
  "properties": {
    "iso:country":"US",
    "sg:address":"202 Waldo St",
    "sg:city":"Rumford",
    "sg:classifiers":[
        {
            "category":"Real Estate",
            "subcategory":"Real Estate Agent",
            "type":"Services"
        }
    ],
    "sg:phone":"+1 207 364 4252",
    "sg:postcode":"04276",
    "sg:province":"ME",
    "wof:name":"Kersey Real Estate",
    "wof:placetype":"venue"
},
  "geometry": {"coordinates":[-70.548544,44.551388],"type":"Point"}
}