{
  "type": "Feature",
  "properties": {
    "addr:full":"202 Woodford St Portland ME 04103",
    "addr:housenumber":"202",
    "addr:postcode":"04103",
    "addr:street":"Woodford St",
    "iso:country":"US",
    "sg:address":"202 Woodford St",
    "sg:city":"Portland",
    "sg:classifiers":[
        {
            "category":"Social Services",
            "type":"Services"
        }
    ],
    "sg:phone":"+1 207 761 3920",
    "sg:postcode":"04103",
    "sg:province":"ME",
    "sg:tags":[
        "food",
        "banks"
    ],
    "wof:name":"Project FEED Inc",
    "wof:placetype":"venue"
},
  "geometry": {"coordinates":[-70.28824,43.6707],"type":"Point"}
}