{
  "type": "Feature",
  "properties": {
    "iso:country":"US",
    "sg:address":"72 Commercial St",
    "sg:city":"Portland",
    "sg:classifiers":[
        {
            "category":"Autos & Motor Vehicles",
            "subcategory":"Boat Sales",
            "type":"Retail Goods"
        }
    ],
    "sg:phone":"+1 207 772 6383",
    "sg:postcode":"04101",
    "sg:province":"ME",
    "sg:tags":[
        "equipment",
        "marine",
        "supply"
    ],
    "sg:website":"www.chaseleavitt.com",
    "wof:name":"Chase Leavitt & Co",
    "wof:placetype":"venue"
},
  "geometry": {"coordinates":[-70.249682,43.658082],"type":"Point"}
}