{
  "type": "Feature",
  "properties": {
    "addr:full":"28 State St Augusta ME 04330",
    "addr:housenumber":"28",
    "addr:postcode":"04330",
    "addr:street":"State St",
    "iso:country":"US",
    "sg:address":"28 State St",
    "sg:city":"Augusta",
    "sg:classifiers":[
        {
            "category":"Government",
            "subcategory":"Office",
            "type":"Public Place"
        }
    ],
    "sg:phone":"+1 207 287 3701",
    "sg:postcode":"04330",
    "sg:province":"ME",
    "sg:tags":[
        "state",
        "program"
    ],
    "sg:website":"www.maine.gov/agriculture/index.shtml",
    "wof:name":"Animal Health & Ind",
    "wof:placetype":"venue"
},
  "geometry": {"coordinates":[-69.775741,44.319342],"type":"Point"}
}