{
  "type": "Feature",
  "properties": {
    "iso:country":"US",
    "sg:address":"11 Sanborn St",
    "sg:city":"Portland",
    "sg:classifiers":[
        {
            "category":"Health Services",
            "subcategory":"Doctor",
            "type":"Services"
        }
    ],
    "sg:phone":"+1 207 797 4679",
    "sg:postcode":"04103",
    "sg:province":"ME",
    "sg:tags":[
        "dentist"
    ],
    "wof:name":"Charles G Drew Jr DDS",
    "wof:placetype":"venue"
},
  "geometry": {"coordinates":[-70.29124299999999,43.703878],"type":"Point"}
}