{
  "type": "Feature",
  "properties": {
    "addr:full":"23 Church St Calais ME 04619",
    "addr:housenumber":"23",
    "addr:postcode":"04619",
    "addr:street":"Church St",
    "iso:country":"US",
    "sg:address":"23 Church St",
    "sg:city":"Calais",
    "sg:classifiers":[
        {
            "category":"Manufacturing",
            "subcategory":"Printing",
            "type":"Manufacturing & Wholesale Goods"
        }
    ],
    "sg:phone":"+1 207 454 3561",
    "sg:postcode":"04619",
    "sg:province":"ME",
    "sg:tags":[
        "newspaper"
    ],
    "wof:name":"Calais Advertiser",
    "wof:placetype":"venue"
},
  "geometry": {"coordinates":[-67.277851,45.187045],"type":"Point"}
}