{
  "type": "Feature",
  "properties": {
    "addr:full":"803 Webster St Lewiston ME 04240",
    "addr:housenumber":"803",
    "addr:postcode":"04240",
    "addr:street":"Webster St",
    "iso:country":"US",
    "sg:address":"803 Webster St",
    "sg:city":"Lewiston",
    "sg:classifiers":[
        {
            "category":"Wholesale",
            "subcategory":"Medical Equipment & Supplies",
            "type":"Manufacturing & Wholesale Goods"
        }
    ],
    "sg:phone":"+1 207 786 7808",
    "sg:postcode":"04240",
    "sg:province":"ME",
    "sg:tags":[
        "physician",
        "surgeon"
    ],
    "sg:website":"www.micro-direct.com",
    "wof:name":"Micro Direct Inc",
    "wof:placetype":"venue"
},
  "geometry": {"coordinates":[-70.17072400000001,44.082264],"type":"Point"}
}