{
  "type": "Feature",
  "properties": {
    "addr:full":"31 Chestnut St Camden ME 04843",
    "addr:housenumber":"31",
    "addr:postcode":"04843",
    "addr:street":"Chestnut St",
    "iso:country":"US",
    "sg:address":"31 Chestnut St",
    "sg:city":"Camden",
    "sg:classifiers":[
        {
            "category":"Social Services",
            "type":"Services"
        }
    ],
    "sg:phone":"+1 207 236 2207",
    "sg:postcode":"04843",
    "sg:province":"ME",
    "sg:tags":[
        "instruction",
        "health",
        "care"
    ],
    "wof:name":"Sandra B Heimann",
    "wof:placetype":"venue"
},
  "geometry": {"coordinates":[-69.065088,44.209596],"type":"Point"}
}