{
  "type": "Feature",
  "properties": {
    "iso:country":"US",
    "sg:address":"158 Whichers Mill Rd",
    "sg:city":"Sanford",
    "sg:classifiers":[
        {
            "category":"Building & Trades",
            "subcategory":"Construction",
            "type":"Services"
        }
    ],
    "sg:phone":"+1 207 324 0603",
    "sg:postcode":"04073",
    "sg:province":"ME",
    "sg:tags":[
        "excavation",
        "contractor"
    ],
    "wof:name":"Lavigne Excavating Inc",
    "wof:placetype":"venue"
},
  "geometry": {"coordinates":[-70.670058,43.408782],"type":"Point"}
}