{
  "type": "Feature",
  "properties": {
    "addr:full":"139 Main St Biddeford ME 04005",
    "addr:housenumber":"139",
    "addr:postcode":"04005",
    "addr:street":"Main St",
    "iso:country":"US",
    "sg:address":"139 Main St",
    "sg:city":"Biddeford",
    "sg:classifiers":[
        {
            "category":"Restaurant",
            "type":"Food & Drink"
        }
    ],
    "sg:phone":"+1 207 282 5133",
    "sg:postcode":"04005",
    "sg:province":"ME",
    "sg:tags":[
        "shop",
        "coffee"
    ],
    "wof:name":"Cool Coffee",
    "wof:placetype":"venue"
},
  "geometry": {"coordinates":[-70.453456,43.492608],"type":"Point"}
}