{
  "type": "Feature",
  "properties": {
    "addr:full":"122 Main St Topsham ME 04086",
    "addr:housenumber":"122",
    "addr:postcode":"04086",
    "addr:street":"Main St",
    "iso:country":"US",
    "sg:address":"122 Main St",
    "sg:city":"Topsham",
    "sg:classifiers":[
        {
            "category":"Home & Garden",
            "subcategory":"Carpets & Floor Coverings",
            "type":"Retail Goods"
        }
    ],
    "sg:phone":"+1 207 729 3040",
    "sg:postcode":"04086",
    "sg:province":"ME",
    "sg:tags":[
        "material"
    ],
    "wof:name":"Top Grade Floors",
    "wof:placetype":"venue"
},
  "geometry": {"coordinates":[-69.968135,43.941209],"type":"Point"}
}