{
  "type": "Feature",
  "properties": {
    "iso:country":"US",
    "sg:address":"194 Turner St",
    "sg:city":"Auburn",
    "sg:classifiers":[
        {
            "category":"Professional",
            "subcategory":"Art Services",
            "type":"Services"
        }
    ],
    "sg:phone":"+1 207 753 0226",
    "sg:postcode":"04210",
    "sg:province":"ME",
    "sg:tags":[
        "graphic",
        "designer"
    ],
    "wof:name":"This N That Graphics",
    "wof:placetype":"venue"
},
  "geometry": {"coordinates":[-70.226836,44.10132],"type":"Point"}
}