{
  "type": "Feature",
  "properties": {
    "addr:full":"150 Coles Corner Rd Winterport ME 04496",
    "addr:housenumber":"150",
    "addr:postcode":"04496",
    "addr:street":"Coles Corner Rd",
    "iso:country":"US",
    "sg:address":"150 Coles Corner Rd",
    "sg:city":"Winterport",
    "sg:classifiers":[
        {
            "category":"Professional",
            "subcategory":"Accounting & Tax Preparation",
            "type":"Services"
        }
    ],
    "sg:phone":"+1 207 223 5733",
    "sg:postcode":"04496",
    "sg:province":"ME",
    "sg:tags":[
        "return"
    ],
    "wof:name":"Higgins Tg Tax Accounting Svcs",
    "wof:placetype":"venue"
},
  "geometry": {"coordinates":[-68.866749,44.663395],"type":"Point"}
}