{
  "type": "Feature",
  "properties": {
    "iso:country":"US",
    "sg:address":"24 Monroe Hwy",
    "sg:city":"Brooks",
    "sg:classifiers":[
        {
            "category":"Arts & Performance",
            "subcategory":"Theater",
            "type":"Entertainment"
        }
    ],
    "sg:phone":"+1 207 722 4110",
    "sg:postcode":"04921",
    "sg:province":"ME",
    "wof:name":"Marsh River Theater",
    "wof:placetype":"venue"
},
  "geometry": {"coordinates":[-69.116218,44.555164],"type":"Point"}
}