{
  "type": "Feature",
  "properties": {
    "addr:full":"472 Washington St Bath ME 04530",
    "addr:housenumber":"472",
    "addr:postcode":"04530",
    "addr:street":"Washington St",
    "iso:country":"US",
    "sg:address":"472 Washington St",
    "sg:city":"Bath",
    "sg:classifiers":[
        {
            "category":"Shopping",
            "subcategory":"Used Merchandise",
            "type":"Retail Goods"
        }
    ],
    "sg:phone":"+1 207 588 2065",
    "sg:postcode":"04530",
    "sg:province":"ME",
    "wof:name":"Dun Halsey Antq & Collectibles",
    "wof:placetype":"venue"
},
  "geometry": {"coordinates":[-69.816067,43.902101],"type":"Point"}
}