{
  "type": "Feature",
  "properties": {
    "addr:full":"89 Auburn St Portland ME 04103",
    "addr:housenumber":"89",
    "addr:postcode":"04103",
    "addr:street":"Auburn St",
    "iso:country":"US",
    "sg:address":"89 Auburn St",
    "sg:city":"Portland",
    "sg:classifiers":[
        {
            "category":"Professional",
            "subcategory":"Advertising",
            "type":"Services"
        }
    ],
    "sg:phone":"+1 207 878 3393",
    "sg:postcode":"04103",
    "sg:province":"ME",
    "sg:tags":[
        "mailing",
        "shipping"
    ],
    "wof:name":"UPS Store",
    "wof:placetype":"venue"
},
  "geometry": {"coordinates":[-70.288961,43.701727],"type":"Point"}
}