{
  "type": "Feature",
  "properties": {
    "iso:country":"US",
    "sg:address":"952 Kennebec Rd",
    "sg:city":"Hampden",
    "sg:classifiers":[
        {
            "category":"Building & Trades",
            "subcategory":"Construction",
            "type":"Services"
        }
    ],
    "sg:phone":"+1 207 862 4214",
    "sg:postcode":"04444",
    "sg:province":"ME",
    "sg:tags":[
        "glass"
    ],
    "wof:name":"Goodwin Glass",
    "wof:placetype":"venue"
},
  "geometry": {"coordinates":[-68.921177,44.706063],"type":"Point"}
}