{
  "type": "Feature",
  "properties": {
    "addr:full":"45 Main St Anson ME 04911",
    "addr:housenumber":"45",
    "addr:postcode":"04911",
    "addr:street":"Main St",
    "iso:country":"US",
    "sg:address":"45 Main St",
    "sg:city":"Anson",
    "sg:classifiers":[
        {
            "category":"Building & Trades",
            "subcategory":"Construction",
            "type":"Services"
        }
    ],
    "sg:phone":"+1 207 696 3084",
    "sg:postcode":"04911",
    "sg:province":"ME",
    "sg:tags":[
        "excavating",
        "contractor"
    ],
    "wof:name":"Merle Lloyd & Son Inc",
    "wof:placetype":"venue"
},
  "geometry": {"coordinates":[-69.894126,44.796406],"type":"Point"}
}