{
  "type": "Feature",
  "properties": {
    "iso:country":"US",
    "sg:address":"40 Salem St",
    "sg:city":"Portland",
    "sg:classifiers":[
        {
            "category":"Professional",
            "subcategory":"Engineering",
            "type":"Services"
        }
    ],
    "sg:phone":"+1 207 774 1203",
    "sg:postcode":"04102",
    "sg:province":"ME",
    "sg:tags":[
        "consulting",
        "management"
    ],
    "wof:name":"Norris Dale Inc",
    "wof:placetype":"venue"
},
  "geometry": {"coordinates":[-70.263537,43.64712],"type":"Point"}
}