{
  "type": "Feature",
  "properties": {
    "iso:country":"US",
    "sg:address":"88 Harpswell Rd",
    "sg:city":"Brunswick",
    "sg:classifiers":[
        {
            "category":"Professional",
            "subcategory":"Computer Services",
            "type":"Services"
        }
    ],
    "sg:phone":"+1 207 721 8598",
    "sg:postcode":"04011",
    "sg:province":"ME",
    "sg:tags":[
        "wiring"
    ],
    "wof:name":"Wavelength DCS",
    "wof:placetype":"venue"
},
  "geometry": {"coordinates":[-69.955062,43.900327],"type":"Point"}
}