{
  "type": "Feature",
  "properties": {
    "iso:country":"US",
    "sg:address":"10 Park St",
    "sg:city":"Milo",
    "sg:classifiers":[
        {
            "category":"Autos & Motor Vehicles",
            "subcategory":"Auto Supplies",
            "type":"Retail Goods"
        }
    ],
    "sg:phone":"+1 207 943 2636",
    "sg:postcode":"04463",
    "sg:province":"ME",
    "sg:tags":[
        "automobile",
        "parts"
    ],
    "wof:name":"S & L Auto Parts",
    "wof:placetype":"venue"
},
  "geometry": {"coordinates":[-68.98642100000001,45.253538],"type":"Point"}
}