{
  "type": "Feature",
  "properties": {
    "iso:country":"US",
    "sg:address":"398 Maine Ave",
    "sg:city":"Farmingdale",
    "sg:classifiers":[
        {
            "category":"Utilities",
            "subcategory":"Mobile Phone",
            "type":"Services"
        }
    ],
    "sg:phone":"+1 207 582 3600",
    "sg:postcode":"04344",
    "sg:province":"ME",
    "sg:tags":[
        "telephone",
        "cellular"
    ],
    "wof:name":"Air Time Cellular",
    "wof:placetype":"venue"
},
  "geometry": {"coordinates":[-69.78521499999999,44.265972],"type":"Point"}
}