{
  "type": "Feature",
  "properties": {
    "addr:full":"547 Congress St Portland ME 04101",
    "addr:housenumber":"547",
    "addr:postcode":"04101",
    "addr:street":"Congress St",
    "iso:country":"US",
    "sg:address":"547 Congress St",
    "sg:city":"Portland",
    "sg:classifiers":[
        {
            "category":"Wholesale",
            "subcategory":"Machinery & Supplies",
            "type":"Manufacturing & Wholesale Goods"
        },
        {
            "category":"Personal",
            "subcategory":"Beauty Salon",
            "type":"Services"
        }
    ],
    "sg:phone":"+1 207 879 1191",
    "sg:postcode":"04101",
    "sg:province":"ME",
    "sg:tags":[
        "shop",
        "equipment",
        "establishment"
    ],
    "wof:name":"Toni's Touch",
    "wof:placetype":"venue"
},
  "geometry": {"coordinates":[-70.26108000000001,43.655991],"type":"Point"}
}