{
  "type": "Feature",
  "properties": {
    "iso:country":"US",
    "sg:address":"375 US Hwy 1",
    "sg:city":"Kittery",
    "sg:classifiers":[
        {
            "category":"Shopping",
            "subcategory":"Clothing, Apparel, & Fashions",
            "type":"Retail Goods"
        }
    ],
    "sg:phone":"+1 207 439 5712",
    "sg:postcode":"03904",
    "sg:province":"ME",
    "wof:name":"Gap Outlet",
    "wof:placetype":"venue"
},
  "geometry": {"coordinates":[-70.726992,43.116745],"type":"Point"}
}