{
  "type": "Feature",
  "properties": {
    "addr:full":"106 Manson Ave Kittery ME 03904",
    "addr:housenumber":"106",
    "addr:postcode":"03904",
    "addr:street":"Manson Ave",
    "iso:country":"US",
    "sg:address":"106 Manson Ave",
    "sg:city":"Kittery",
    "sg:classifiers":[
        {
            "category":"Utilities",
            "subcategory":"Refuse",
            "type":"Services"
        }
    ],
    "sg:phone":"+1 207 439 2380",
    "sg:postcode":"03904",
    "sg:province":"ME",
    "sg:tags":[
        "garbage",
        "collection"
    ],
    "wof:name":"Leclair Hauling",
    "wof:placetype":"venue"
},
  "geometry": {"coordinates":[-70.732569,43.092114],"type":"Point"}
}