{
  "type": "Feature",
  "properties": {
    "iso:country":"US",
    "sg:address":"19 Elizabeth Ave",
    "sg:city":"Bangor",
    "sg:classifiers":[
        {
            "category":"Travel",
            "subcategory":"Travel Agent",
            "type":"Entertainment"
        }
    ],
    "sg:phone":"+1 207 947 3806",
    "sg:postcode":"04401",
    "sg:province":"ME",
    "sg:tags":[
        "agency",
        "bureau"
    ],
    "wof:name":"Paradise Cruise & Travel",
    "wof:placetype":"venue"
},
  "geometry": {"coordinates":[-68.78588000000001,44.804565],"type":"Point"}
}