{
  "type": "Feature",
  "properties": {
    "addr:full":"53 Lisbon St Lisbon ME 04250",
    "addr:housenumber":"53",
    "addr:postcode":"04250",
    "addr:street":"Lisbon St",
    "iso:country":"US",
    "sg:address":"53 Lisbon St",
    "sg:city":"Lisbon",
    "sg:classifiers":[
        {
            "category":"Autos & Motor Vehicles",
            "subcategory":"Automobile Sales",
            "type":"Retail Goods"
        }
    ],
    "sg:phone":"+1 207 353 4133",
    "sg:postcode":"04250",
    "sg:province":"ME",
    "sg:tags":[
        "car",
        "dealer"
    ],
    "wof:name":"Larry Stewart Auto Sales Shop",
    "wof:placetype":"venue"
},
  "geometry": {"coordinates":[-70.118864,44.047277],"type":"Point"}
}