{
  "type": "Feature",
  "properties": {
    "iso:country":"US",
    "sg:address":"85 Foye Rd",
    "sg:city":"Manchester",
    "sg:classifiers":[
        {
            "category":"Autos & Motor Vehicles",
            "subcategory":"Automobile Sales",
            "type":"Retail Goods"
        }
    ],
    "sg:phone":"+1 207 622 3836",
    "sg:postcode":"04351",
    "sg:province":"ME",
    "sg:tags":[
        "repair",
        "general"
    ],
    "wof:name":"Hilliards Garage",
    "wof:placetype":"venue"
},
  "geometry": {"coordinates":[-69.831898,44.318666],"type":"Point"}
}