{
  "type": "Feature",
  "properties": {
    "iso:country":"US",
    "sg:address":"11 Wayside Ave",
    "sg:city":"Bridgton",
    "sg:classifiers":[
        {
            "category":"Social Services",
            "type":"Services"
        }
    ],
    "sg:phone":"+1 207 647 4404",
    "sg:postcode":"04009",
    "sg:province":"ME",
    "sg:tags":[
        "organization",
        "welfare"
    ],
    "sg:website":"www.nfinorth.com",
    "wof:name":"NFI North",
    "wof:placetype":"venue"
},
  "geometry": {"coordinates":[-70.710551,44.059389],"type":"Point"}
}