{
  "type": "Feature",
  "properties": {
    "addr:full":"1300 Forest Ave Portland ME 04103",
    "addr:housenumber":"1300",
    "addr:postcode":"04103",
    "addr:street":"Forest Ave",
    "iso:country":"US",
    "sg:address":"1300 Forest Ave",
    "sg:city":"Portland",
    "sg:classifiers":[
        {
            "category":"Real Estate",
            "subcategory":"Real Estate Operator",
            "type":"Services"
        }
    ],
    "sg:phone":"+1 207 797 7102",
    "sg:postcode":"04103",
    "sg:province":"ME",
    "sg:tags":[
        "apartment"
    ],
    "wof:name":"Forest Avenue Apartments",
    "wof:placetype":"venue"
},
  "geometry": {"coordinates":[-70.29798599999999,43.69058],"type":"Point"}
}