{
  "type": "Feature",
  "properties": {
    "addr:full":"401 Norway Center Rd Norway ME 04268",
    "addr:housenumber":"401",
    "addr:postcode":"04268",
    "addr:street":"Norway Center Rd",
    "iso:country":"US",
    "sg:address":"401 Norway Center Rd",
    "sg:city":"Norway",
    "sg:classifiers":[
        {
            "category":"Freight",
            "type":"Transportation"
        }
    ],
    "sg:phone":"+1 207 527 2342",
    "sg:postcode":"04268",
    "sg:province":"ME",
    "sg:tags":[
        "operator",
        "local",
        "trucking"
    ],
    "wof:name":"Forestry Management & Trucking",
    "wof:placetype":"venue"
},
  "geometry": {"coordinates":[-70.60774499999999,44.233836],"type":"Point"}
}