{
  "type": "Feature",
  "properties": {
    "iso:country":"US",
    "sg:address":"5 Pine Rd",
    "sg:city":"Liberty",
    "sg:classifiers":[
        {
            "category":"Real Estate",
            "subcategory":"Real Estate Operator",
            "type":"Services"
        }
    ],
    "sg:phone":"+1 207 589 4198",
    "sg:postcode":"04952",
    "sg:province":"ME",
    "sg:tags":[
        "apartment"
    ],
    "wof:name":"Lake St George Apartments",
    "wof:placetype":"venue"
},
  "geometry": {"coordinates":[-69.112323,44.398669],"type":"Point"}
}