{
  "type": "Feature",
  "properties": {
    "addr:full":"121 Hutchins Dr Portland ME 04102",
    "addr:housenumber":"121",
    "addr:postcode":"04102",
    "addr:street":"Hutchins Dr",
    "iso:country":"US",
    "sg:address":"121 Hutchins Dr",
    "sg:city":"Portland",
    "sg:classifiers":[
        {
            "category":"Shopping",
            "type":"Retail Goods"
        }
    ],
    "sg:phone":"+1 207 772 7508",
    "sg:postcode":"04102",
    "sg:province":"ME",
    "sg:tags":[
        "trophy",
        "medal",
        "award"
    ],
    "sg:website":"www.sportlinetrophy.com",
    "wof:name":"Sportline Trophy",
    "wof:placetype":"venue"
},
  "geometry": {"coordinates":[-70.33914,43.655221],"type":"Point"}
}