{
  "type": "Feature",
  "properties": {
    "iso:country":"US",
    "sg:address":"40 Friendship Rd",
    "sg:city":"Waldoboro",
    "sg:classifiers":[
        {
            "category":"Health Services",
            "subcategory":"Doctor",
            "type":"Services"
        }
    ],
    "sg:phone":"+1 207 832 4521",
    "sg:postcode":"04572",
    "sg:province":"ME",
    "sg:tags":[
        "dentist"
    ],
    "wof:name":"Joseph Flanagan DDS",
    "wof:placetype":"venue"
},
  "geometry": {"coordinates":[-69.375113,44.094841],"type":"Point"}
}