{
  "type": "Feature",
  "properties": {
    "addr:full":"655 Pool St Biddeford ME 04005",
    "addr:housenumber":"655",
    "addr:postcode":"04005",
    "addr:street":"Pool St",
    "iso:country":"US",
    "sg:address":"655 Pool St",
    "sg:city":"Biddeford",
    "sg:classifiers":[
        {
            "category":"Health Services",
            "subcategory":"Doctor",
            "type":"Services"
        }
    ],
    "sg:phone":"+1 207 602 3587",
    "sg:postcode":"04005",
    "sg:province":"ME",
    "sg:website":"www.une.edu/Uhc",
    "wof:name":"University Health Care",
    "wof:placetype":"venue"
},
  "geometry": {"coordinates":[-70.383235,43.444657],"type":"Point"}
}