{
  "type": "Feature",
  "properties": {
    "iso:country":"US",
    "sg:address":"6 Park St",
    "sg:city":"Madison",
    "sg:classifiers":[
        {
            "category":"Building & Trades",
            "subcategory":"Construction",
            "type":"Services"
        }
    ],
    "sg:phone":"+1 207 696 4401",
    "sg:postcode":"04950",
    "sg:province":"ME",
    "sg:tags":[
        "utility",
        "contractor"
    ],
    "sg:website":"www.madisonelectricworks.com",
    "wof:name":"Madison Electric",
    "wof:placetype":"venue"
},
  "geometry": {"coordinates":[-69.874647,44.800546],"type":"Point"}
}