{
  "type": "Feature",
  "properties": {
    "iso:country":"US",
    "sg:address":"10 Union St",
    "sg:city":"Pittsfield",
    "sg:classifiers":[
        {
            "category":"Freight",
            "type":"Transportation"
        }
    ],
    "sg:phone":"+1 207 487 5581",
    "sg:postcode":"04967",
    "sg:province":"ME",
    "sg:tags":[
        "operator",
        "local",
        "trucking"
    ],
    "wof:name":"D Whitley Trucking",
    "wof:placetype":"venue"
},
  "geometry": {"coordinates":[-69.386297,44.787969],"type":"Point"}
}