{
  "type": "Feature",
  "properties": {
    "iso:country":"US",
    "sg:address":"4 Pleasant St",
    "sg:city":"Winthrop",
    "sg:classifiers":[
        {
            "category":"Organizations",
            "subcategory":"Religious Organization",
            "type":"Services"
        }
    ],
    "sg:phone":"+1 207 377 8634",
    "sg:postcode":"04364",
    "sg:province":"ME",
    "sg:tags":[
        "church"
    ],
    "wof:name":"Faith Alliance Church",
    "wof:placetype":"venue"
},
  "geometry": {"coordinates":[-69.96681100000001,44.305164],"type":"Point"}
}