{
  "type": "Feature",
  "properties": {
    "addr:full":"45 Main St Kennebunk ME 04043",
    "addr:housenumber":"45",
    "addr:postcode":"04043",
    "addr:street":"Main St",
    "iso:country":"US",
    "sg:address":"45 Main St",
    "sg:city":"Kennebunk",
    "sg:classifiers":[
        {
            "category":"Restaurant",
            "type":"Food & Drink"
        }
    ],
    "sg:menulink":"http://www.allmenus.com/me/kennebunk/267522-academe/menu/",
    "sg:phone":"+1 207 985 3351",
    "sg:postcode":"04043",
    "sg:province":"ME",
    "sg:tags":[
        "new",
        "american"
    ],
    "wof:name":"Academe",
    "wof:placetype":"venue"
},
  "geometry": {"coordinates":[-70.540396,43.385647],"type":"Point"}
}