{
  "type": "Feature",
  "properties": {
    "addr:full":"106 Holmes Rd Scarborough ME 04074",
    "addr:housenumber":"106",
    "addr:postcode":"04074",
    "addr:street":"Holmes Rd",
    "iso:country":"US",
    "sg:address":"106 Holmes Rd",
    "sg:city":"Scarborough",
    "sg:classifiers":[
        {
            "category":"Retail",
            "subcategory":"Auto Repair",
            "type":"Services"
        }
    ],
    "sg:phone":"+1 207 885 5906",
    "sg:postcode":"04074",
    "sg:province":"ME",
    "sg:tags":[
        "general"
    ],
    "wof:name":"Creative Car Care",
    "wof:placetype":"venue"
},
  "geometry": {"coordinates":[-70.389467,43.61032],"type":"Point"}
}