{
  "type": "Feature",
  "properties": {
    "iso:country":"US",
    "sg:address":"1 Paris Promenade",
    "sg:city":"South Paris",
    "sg:classifiers":[
        {
            "category":"Food & Beverages",
            "subcategory":"Groceries & Convenience Stores",
            "type":"Retail Goods"
        }
    ],
    "sg:phone":"+1 207 743 9212",
    "sg:postcode":"04281",
    "sg:province":"ME",
    "sg:website":"www.cnbrown.com",
    "wof:name":"C N Brown Co",
    "wof:placetype":"venue"
},
  "geometry": {"coordinates":[-70.517557,44.232963],"type":"Point"}
}