{
  "type": "Feature",
  "properties": {
    "iso:country":"US",
    "sg:address":"1137 Western Ave",
    "sg:city":"Hampden",
    "sg:classifiers":[
        {
            "category":"Real Estate",
            "subcategory":"Real Estate Agent",
            "type":"Services"
        }
    ],
    "sg:phone":"+1 207 862 3711",
    "sg:postcode":"04444",
    "sg:province":"ME",
    "sg:tags":[
        "appraiser"
    ],
    "sg:website":"www.mainecam.net",
    "wof:name":"Young & Assoc",
    "wof:placetype":"venue"
},
  "geometry": {"coordinates":[-68.942544,44.743215],"type":"Point"}
}