{
  "type": "Feature",
  "properties": {
    "iso:country":"US",
    "sg:address":"120 Old County Rd",
    "sg:city":"Rockland",
    "sg:classifiers":[
        {
            "category":"Building & Trades",
            "subcategory":"Construction",
            "type":"Services"
        }
    ],
    "sg:phone":"+1 207 542 7957",
    "sg:postcode":"04841",
    "sg:province":"ME",
    "sg:tags":[
        "work",
        "carpentry"
    ],
    "wof:name":"David Healey Construction",
    "wof:placetype":"venue"
},
  "geometry": {"coordinates":[-69.140472,44.103826],"type":"Point"}
}