{
  "type": "Feature",
  "properties": {
    "addr:full":"279 Main St Rockland ME 04841",
    "addr:housenumber":"279",
    "addr:postcode":"04841",
    "addr:street":"Main St",
    "iso:country":"US",
    "sg:address":"279 Main St",
    "sg:city":"Rockland",
    "sg:classifiers":[
        {
            "category":"Shopping",
            "subcategory":"Crafts & Fabrics",
            "type":"Retail Goods"
        }
    ],
    "sg:phone":"+1 207 594 2233",
    "sg:postcode":"04841",
    "sg:province":"ME",
    "sg:tags":[
        "monogram"
    ],
    "wof:name":"Maine Ly Monograms & Unique",
    "wof:placetype":"venue"
},
  "geometry": {"coordinates":[-69.10922100000001,44.100496],"type":"Point"}
}