{
  "type": "Feature",
  "properties": {
    "iso:country":"US",
    "sg:address":"25 Debra Ln",
    "sg:city":"Kittery",
    "sg:classifiers":[
        {
            "category":"Banks & Credit Unions",
            "subcategory":"Bank",
            "type":"Services"
        }
    ],
    "sg:phone":"+1 207 451 9444",
    "sg:postcode":"03904",
    "sg:province":"ME",
    "sg:tags":[
        "federal",
        "agency"
    ],
    "wof:name":"Oneil Trading Co",
    "wof:placetype":"venue"
},
  "geometry": {"coordinates":[-70.733662,43.095272],"type":"Point"}
}