{
  "type": "Feature",
  "properties": {
    "addr:full":"889 Roosevelt Trl Windham ME 04062",
    "addr:housenumber":"889",
    "addr:postcode":"04062",
    "addr:street":"Roosevelt Trl",
    "iso:country":"US",
    "sg:address":"889 Roosevelt Trl",
    "sg:city":"Windham",
    "sg:classifiers":[
        {
            "category":"Retail",
            "subcategory":"Animal Services",
            "type":"Services"
        }
    ],
    "sg:phone":"+1 207 892 5366",
    "sg:postcode":"04062",
    "sg:province":"ME",
    "sg:tags":[
        "pet"
    ],
    "wof:name":"Pawz & Clawz Petz",
    "wof:placetype":"venue"
},
  "geometry": {"coordinates":[-70.450109,43.850783],"type":"Point"}
}