{
  "type": "Feature",
  "properties": {
    "addr:full":"9 Parkman Rd Wellington ME 04942",
    "addr:housenumber":"9",
    "addr:postcode":"04942",
    "addr:street":"Parkman Rd",
    "iso:country":"US",
    "sg:address":"9 Parkman Rd",
    "sg:city":"Wellington",
    "sg:classifiers":[
        {
            "category":"Government",
            "subcategory":"Office",
            "type":"Public Place"
        }
    ],
    "sg:phone":"+1 207 683 2030",
    "sg:postcode":"04942",
    "sg:province":"ME",
    "sg:tags":[
        "village"
    ],
    "wof:name":"Wellington Town Office",
    "wof:placetype":"venue"
},
  "geometry": {"coordinates":[-69.59370699999999,45.040096],"type":"Point"}
}