{
  "type": "Feature",
  "properties": {
    "addr:full":"48 Columbia St Bangor ME 04401",
    "addr:housenumber":"48",
    "addr:postcode":"04401",
    "addr:street":"Columbia St",
    "iso:country":"US",
    "sg:address":"48 Columbia St",
    "sg:city":"Bangor",
    "sg:classifiers":[
        {
            "category":"Real Estate",
            "subcategory":"Real Estate Agent",
            "type":"Services"
        }
    ],
    "sg:phone":"+1 207 942 0659",
    "sg:postcode":"04401",
    "sg:province":"ME",
    "wof:name":"TFW Realty",
    "wof:placetype":"venue"
},
  "geometry": {"coordinates":[-68.772306,44.80128],"type":"Point"}
}