{
  "type": "Feature",
  "properties": {
    "addr:full":"88 Federal St Portland ME 04101",
    "addr:housenumber":"88",
    "addr:postcode":"04101",
    "addr:street":"Federal St",
    "iso:country":"US",
    "sg:address":"88 Federal St",
    "sg:city":"Portland",
    "sg:classifiers":[
        {
            "category":"Social Services",
            "type":"Services"
        }
    ],
    "sg:phone":"+1 207 774 4348",
    "sg:postcode":"04101",
    "sg:province":"ME",
    "sg:tags":[
        "organization",
        "welfare"
    ],
    "sg:website":"www.vlp.org",
    "wof:name":"Volunteer Lawyers Project",
    "wof:placetype":"venue"
},
  "geometry": {"coordinates":[-70.25199499999999,43.660893],"type":"Point"}
}