{
  "type": "Feature",
  "properties": {
    "iso:country":"US",
    "sg:address":"200 Stetson Rd",
    "sg:city":"Auburn",
    "sg:classifiers":[
        {
            "category":"Health Services",
            "subcategory":"Nursing And Care Facility",
            "type":"Services"
        }
    ],
    "sg:phone":"+1 207 784 2900",
    "sg:postcode":"04210",
    "sg:province":"ME",
    "sg:tags":[
        "home",
        "retirement",
        "community"
    ],
    "sg:website":"www.schoonerestates.com",
    "wof:name":"Schooner Estates",
    "wof:placetype":"venue"
},
  "geometry": {"coordinates":[-70.216743,44.127397],"type":"Point"}
}