{
  "type": "Feature",
  "properties": {
    "iso:country":"US",
    "sg:address":"94 Auburn St",
    "sg:city":"Portland",
    "sg:classifiers":[
        {
            "category":"Professional",
            "type":"Services"
        }
    ],
    "sg:phone":"+1 207 842 2988",
    "sg:postcode":"04103",
    "sg:province":"ME",
    "sg:tags":[
        "establishment"
    ],
    "wof:name":"Prop",
    "wof:placetype":"venue"
},
  "geometry": {"coordinates":[-70.288961,43.701727],"type":"Point"}
}