{
  "type": "Feature",
  "properties": {
    "addr:full":"49 Pleasant St Brunswick ME 04011",
    "addr:housenumber":"49",
    "addr:postcode":"04011",
    "addr:street":"Pleasant St",
    "iso:country":"US",
    "sg:address":"49 Pleasant St",
    "sg:city":"Brunswick",
    "sg:classifiers":[
        {
            "category":"Professional",
            "subcategory":"Management & Consulting",
            "type":"Services"
        }
    ],
    "sg:phone":"+1 207 729 0144",
    "sg:postcode":"04011",
    "sg:province":"ME",
    "sg:tags":[
        "consultant",
        "business"
    ],
    "sg:website":"www.mcbdp.org",
    "wof:name":"Mid-Coast Council For Business",
    "wof:placetype":"venue"
},
  "geometry": {"coordinates":[-69.97169100000001,43.913396],"type":"Point"}
}