{
  "type": "Feature",
  "properties": {
    "addr:full":"205 Deepwood Dr Portland ME 04103",
    "addr:housenumber":"205",
    "addr:postcode":"04103",
    "addr:street":"Deepwood Dr",
    "iso:country":"US",
    "sg:address":"205 Deepwood Dr",
    "sg:city":"Portland",
    "sg:classifiers":[
        {
            "category":"Professional",
            "subcategory":"Advertising",
            "type":"Services"
        }
    ],
    "sg:phone":"+1 207 878 7848",
    "sg:postcode":"04103",
    "sg:province":"ME",
    "sg:tags":[
        "distribution"
    ],
    "wof:name":"Simply Divine Brownies",
    "wof:placetype":"venue"
},
  "geometry": {"coordinates":[-70.28044800000001,43.714974],"type":"Point"}
}