{
  "type": "Feature",
  "properties": {
    "addr:full":"146 Gamage Ave Auburn ME 04210",
    "addr:housenumber":"146",
    "addr:postcode":"04210",
    "addr:street":"Gamage Ave",
    "iso:country":"US",
    "sg:address":"146 Gamage Ave",
    "sg:city":"Auburn",
    "sg:classifiers":[
        {
            "category":"Food & Beverages",
            "subcategory":"Specialty",
            "type":"Retail Goods"
        }
    ],
    "sg:phone":"+1 207 784 2476",
    "sg:postcode":"04210",
    "sg:province":"ME",
    "wof:name":"Home Business System Intl",
    "wof:placetype":"venue"
},
  "geometry": {"coordinates":[-70.241174,44.106103],"type":"Point"}
}