{
  "type": "Feature",
  "properties": {
    "iso:country":"US",
    "sg:address":"200 Congress Ave",
    "sg:city":"Bath",
    "sg:classifiers":[
        {
            "category":"Organizations",
            "subcategory":"Community Association",
            "type":"Services"
        }
    ],
    "sg:phone":"+1 207 443 9178",
    "sg:postcode":"04530",
    "sg:province":"ME",
    "sg:tags":[
        "military"
    ],
    "wof:name":"American Legion",
    "wof:placetype":"venue"
},
  "geometry": {"coordinates":[-69.826543,43.917905],"type":"Point"}
}