{
  "type": "Feature",
  "properties": {
    "iso:country":"US",
    "sg:address":"11 Portland St",
    "sg:city":"Fryeburg",
    "sg:classifiers":[
        {
            "category":"Organizations",
            "subcategory":"Community Association",
            "type":"Services"
        }
    ],
    "sg:phone":"+1 207 935 2341",
    "sg:postcode":"04037",
    "sg:province":"ME",
    "sg:tags":[
        "fraternal"
    ],
    "wof:name":"Pythagorean Lodge",
    "wof:placetype":"venue"
},
  "geometry": {"coordinates":[-70.980272,44.016554],"type":"Point"}
}