{
  "type": "Feature",
  "properties": {
    "addr:full":"15 Hannah Dr East Waterboro ME 04038",
    "addr:housenumber":"15",
    "addr:postcode":"04038",
    "addr:street":"Hannah Dr",
    "iso:country":"US",
    "sg:address":"15 Hannah Dr",
    "sg:city":"East Waterboro",
    "sg:classifiers":[
        {
            "category":"Building & Trades",
            "subcategory":"Construction",
            "type":"Services"
        }
    ],
    "sg:phone":"+1 207 247 5988",
    "sg:postcode":"04038",
    "sg:province":"ME",
    "sg:tags":[
        "hanging",
        "contractor"
    ],
    "wof:name":"Maurice A Auger",
    "wof:placetype":"venue"
},
  "geometry": {"coordinates":[-70.428799,43.730568],"type":"Point"}
}