{
  "type": "Feature",
  "properties": {
    "iso:country":"US",
    "sg:address":"20 Main St",
    "sg:city":"Mexico",
    "sg:classifiers":[
        {
            "category":"Banks & Credit Unions",
            "subcategory":"Bank",
            "type":"Services"
        }
    ],
    "sg:phone":"+1 207 364 4536",
    "sg:postcode":"04257",
    "sg:province":"ME",
    "wof:name":"Franklin Savings Bank",
    "wof:placetype":"venue"
},
  "geometry": {"coordinates":[-70.545405,44.555942],"type":"Point"}
}