{
  "type": "Feature",
  "properties": {
    "addr:full":"22 Pheasant Dr Rockland ME 04841",
    "addr:housenumber":"22",
    "addr:postcode":"04841",
    "addr:street":"Pheasant Dr",
    "iso:country":"US",
    "sg:address":"22 Pheasant Dr",
    "sg:city":"Rockland",
    "sg:classifiers":[
        {
            "category":"Retail",
            "subcategory":"Repair Shop",
            "type":"Services"
        }
    ],
    "sg:phone":"+1 207 594 7411",
    "sg:postcode":"04841",
    "sg:province":"ME",
    "sg:tags":[
        "kitchen",
        "cabinet"
    ],
    "wof:name":"Mor-Cabinet Fronts",
    "wof:placetype":"venue"
},
  "geometry": {"coordinates":[-69.111413,44.13061],"type":"Point"}
}