{
  "type": "Feature",
  "properties": {
    "iso:country":"US",
    "sg:address":"506 Main St",
    "sg:city":"Lewiston",
    "sg:classifiers":[
        {
            "category":"Building & Trades",
            "subcategory":"Construction",
            "type":"Services"
        }
    ],
    "sg:phone":"+1 207 784 8511",
    "sg:postcode":"04240",
    "sg:province":"ME",
    "sg:tags":[
        "new",
        "home"
    ],
    "wof:name":"LHeureux Michael RE & Develop",
    "wof:placetype":"venue"
},
  "geometry": {"coordinates":[-70.209502,44.10906],"type":"Point"}
}