{
  "type": "Feature",
  "properties": {
    "iso:country":"US",
    "sg:address":"39 White St",
    "sg:city":"Lewiston",
    "sg:classifiers":[
        {
            "category":"Insurance",
            "subcategory":"Insurance Agent",
            "type":"Services"
        }
    ],
    "sg:phone":"+1 207 782 9168",
    "sg:postcode":"04240",
    "sg:province":"ME",
    "wof:name":"Prudential",
    "wof:placetype":"venue"
},
  "geometry": {"coordinates":[-70.20902,44.105116],"type":"Point"}
}