{
  "type": "Feature",
  "properties": {
    "addr:full":"10 Howe St Augusta ME 04330",
    "addr:housenumber":"10",
    "addr:postcode":"04330",
    "addr:street":"Howe St",
    "iso:country":"US",
    "sg:address":"10 Howe St",
    "sg:city":"Augusta",
    "sg:classifiers":[
        {
            "category":"Building & Trades",
            "subcategory":"Plumbing",
            "type":"Services"
        }
    ],
    "sg:phone":"+1 207 622 3681",
    "sg:postcode":"04330",
    "sg:province":"ME",
    "sg:tags":[
        "conditioning",
        "air",
        "system",
        "contractor"
    ],
    "wof:name":"Pullen Brothers Inc",
    "wof:placetype":"venue"
},
  "geometry": {"coordinates":[-69.763087,44.322437],"type":"Point"}
}