{
  "type": "Feature",
  "properties": {
    "addr:full":"300 Sawyer Rd Hampden ME 04444",
    "addr:housenumber":"300",
    "addr:postcode":"04444",
    "addr:street":"Sawyer Rd",
    "iso:country":"US",
    "sg:address":"300 Sawyer Rd",
    "sg:city":"Hampden",
    "sg:classifiers":[
        {
            "category":"Manufacturing",
            "subcategory":"Printing",
            "type":"Manufacturing & Wholesale Goods"
        }
    ],
    "sg:phone":"+1 207 862 2160",
    "sg:postcode":"04444",
    "sg:province":"ME",
    "sg:tags":[
        "periodical"
    ],
    "wof:name":"Maine Outdoor Publications",
    "wof:placetype":"venue"
},
  "geometry": {"coordinates":[-68.93732300000001,44.727241],"type":"Point"}
}