{
  "type": "Feature",
  "properties": {
    "iso:country":"US",
    "sg:address":"142 Wilton Rd",
    "sg:city":"Dixfield",
    "sg:classifiers":[
        {
            "category":"Utilities",
            "subcategory":"Water",
            "type":"Services"
        }
    ],
    "sg:phone":"+1 207 562 4654",
    "sg:postcode":"04224",
    "sg:province":"ME",
    "sg:tags":[
        "company",
        "sewage"
    ],
    "wof:name":"Dixfield Sewer & Water Office",
    "wof:placetype":"venue"
},
  "geometry": {"coordinates":[-70.438074,44.524298],"type":"Point"}
}