{
  "type": "Feature",
  "properties": {
    "iso:country":"US",
    "sg:address":"39 Mayville Rd",
    "sg:city":"Bethel",
    "sg:classifiers":[
        {
            "category":"Personal",
            "subcategory":"Beauty Salon",
            "type":"Services"
        }
    ],
    "sg:phone":"+1 207 824 4834",
    "sg:postcode":"04217",
    "sg:province":"ME",
    "wof:name":"Jade's Salon",
    "wof:placetype":"venue"
},
  "geometry": {"coordinates":[-70.796225,44.414111],"type":"Point"}
}