{
  "type": "Feature",
  "properties": {
    "addr:full":"172 Hartland Ave Pittsfield ME 04967",
    "addr:housenumber":"172",
    "addr:postcode":"04967",
    "addr:street":"Hartland Ave",
    "iso:country":"US",
    "sg:address":"172 Hartland Ave",
    "sg:city":"Pittsfield",
    "sg:classifiers":[
        {
            "category":"Retail",
            "subcategory":"Animal Services",
            "type":"Services"
        }
    ],
    "sg:phone":"+1 207 487 3168",
    "sg:postcode":"04967",
    "sg:province":"ME",
    "sg:tags":[
        "pet",
        "grooming",
        "washing"
    ],
    "wof:name":"Sebasticook Farms Kennel",
    "wof:placetype":"venue"
},
  "geometry": {"coordinates":[-69.39272200000001,44.799426],"type":"Point"}
}