{
  "type": "Feature",
  "properties": {
    "iso:country":"US",
    "sg:address":"45 Portland Rd",
    "sg:city":"Kennebunk",
    "sg:classifiers":[
        {
            "category":"Banks & Credit Unions",
            "subcategory":"Bank",
            "type":"Services"
        }
    ],
    "sg:phone":"+1 207 985 5722",
    "sg:postcode":"04043",
    "sg:province":"ME",
    "wof:name":"Ocean Communities Federal CU",
    "wof:placetype":"venue"
},
  "geometry": {"coordinates":[-70.533204,43.393109],"type":"Point"}
}