{
  "type": "Feature",
  "properties": {
    "addr:full":"240 Maine St Brunswick ME 04011",
    "addr:housenumber":"240",
    "addr:postcode":"04011",
    "addr:street":"Maine St",
    "iso:country":"US",
    "sg:address":"240 Maine St",
    "sg:city":"Brunswick",
    "sg:classifiers":[
        {
            "category":"Professional",
            "subcategory":"Lawyer & Legal Services",
            "type":"Services"
        }
    ],
    "sg:phone":"+1 207 725 8412",
    "sg:postcode":"04011",
    "sg:province":"ME",
    "sg:tags":[
        "attorney"
    ],
    "wof:name":"E C Livesay",
    "wof:placetype":"venue"
},
  "geometry": {"coordinates":[-69.96463199999999,43.908377],"type":"Point"}
}