{
  "type": "Feature",
  "properties": {
    "iso:country":"US",
    "sg:address":"764 Atlantic Hwy",
    "sg:city":"Waldoboro",
    "sg:classifiers":[
        {
            "category":"Wholesale",
            "subcategory":"Seafood",
            "type":"Manufacturing & Wholesale Goods"
        }
    ],
    "sg:phone":"+1 207 832 8188",
    "sg:postcode":"04572",
    "sg:province":"ME",
    "wof:name":"Marina's Seafood",
    "wof:placetype":"venue"
},
  "geometry": {"coordinates":[-69.413484,44.099136],"type":"Point"}
}