{
  "type": "Feature",
  "properties": {
    "iso:country":"US",
    "sg:address":"41 Wight St",
    "sg:city":"Belfast",
    "sg:classifiers":[
        {
            "category":"Health Services",
            "subcategory":"Doctor",
            "type":"Services"
        }
    ],
    "sg:phone":"+1 207 548 6384",
    "sg:postcode":"04915",
    "sg:province":"ME",
    "sg:tags":[
        "physician",
        "surgeon"
    ],
    "sg:website":"www.seaportfamilypractice.com",
    "wof:name":"Seaport Family Practice",
    "wof:placetype":"venue"
},
  "geometry": {"coordinates":[-69.003102,44.413647],"type":"Point"}
}