{
  "type": "Feature",
  "properties": {
    "addr:full":"49 Old Calais Rd Hodgdon ME 04730",
    "addr:housenumber":"49",
    "addr:postcode":"04730",
    "addr:street":"Old Calais Rd",
    "iso:country":"US",
    "sg:address":"49 Old Calais Rd",
    "sg:city":"Hodgdon",
    "sg:classifiers":[
        {
            "category":"Shopping",
            "subcategory":"Florist",
            "type":"Retail Goods"
        }
    ],
    "sg:phone":"+1 207 532 2997",
    "sg:postcode":"04730",
    "sg:province":"ME",
    "wof:name":"Boutilier's Greenhouse",
    "wof:placetype":"venue"
},
  "geometry": {"coordinates":[-67.84064499999999,46.112058],"type":"Point"}
}