{
  "type": "Feature",
  "properties": {
    "iso:country":"US",
    "sg:address":"25 Merganser Way",
    "sg:city":"Freeport",
    "sg:classifiers":[
        {
            "category":"Building & Trades",
            "subcategory":"Plumbing",
            "type":"Services"
        }
    ],
    "sg:phone":"+1 207 865 4554",
    "sg:postcode":"04032",
    "sg:province":"ME",
    "sg:tags":[
        "product",
        "management",
        "energy",
        "system"
    ],
    "wof:name":"Acadia Bay Energy Co",
    "wof:placetype":"venue"
},
  "geometry": {"coordinates":[-70.068829,43.810261],"type":"Point"}
}