{
  "type": "Feature",
  "properties": {
    "addr:full":"3 Old Portland Rd Brunswick ME 04011",
    "addr:housenumber":"3",
    "addr:postcode":"04011",
    "addr:street":"Old Portland Rd",
    "iso:country":"US",
    "sg:address":"3 Old Portland Rd",
    "sg:city":"Brunswick",
    "sg:classifiers":[
        {
            "category":"Home & Garden",
            "subcategory":"Mobile Homes",
            "type":"Retail Goods"
        }
    ],
    "sg:phone":"+1 207 725 2733",
    "sg:postcode":"04011",
    "sg:province":"ME",
    "wof:name":"Linnhaven Mobile Home Sales",
    "wof:placetype":"venue"
},
  "geometry": {"coordinates":[-69.999787,43.912047],"type":"Point"}
}