{
  "type": "Feature",
  "properties": {
    "addr:full":"56 Alfred St Sanford ME 04073",
    "addr:housenumber":"56",
    "addr:postcode":"04073",
    "addr:street":"Alfred St",
    "iso:country":"US",
    "sg:address":"56 Alfred St",
    "sg:city":"Sanford",
    "sg:classifiers":[
        {
            "category":"Retail",
            "subcategory":"Auto Repair",
            "type":"Services"
        }
    ],
    "sg:phone":"+1 207 490 6884",
    "sg:postcode":"04073",
    "sg:province":"ME",
    "sg:tags":[
        "body",
        "automobile",
        "painting"
    ],
    "wof:name":"Auto Body Shop",
    "wof:placetype":"venue"
},
  "geometry": {"coordinates":[-70.73515999999999,43.421451],"type":"Point"}
}