{
  "type": "Feature",
  "properties": {
    "iso:country":"US",
    "sg:address":"88 Main St",
    "sg:city":"Old Town",
    "sg:classifiers":[
        {
            "category":"Shopping",
            "subcategory":"Used Merchandise",
            "type":"Retail Goods"
        }
    ],
    "sg:phone":"+1 207 827 8006",
    "sg:postcode":"04461",
    "sg:province":"ME",
    "sg:tags":[
        "second",
        "store",
        "hand"
    ],
    "wof:name":"Bob's Crazy Saver",
    "wof:placetype":"venue"
},
  "geometry": {"coordinates":[-68.644558,44.946237],"type":"Point"}
}