{
  "type": "Feature",
  "properties": {
    "iso:country":"US",
    "sg:address":"482 Stillwater Ave",
    "sg:city":"Old Town",
    "sg:classifiers":[
        {
            "category":"Cinema",
            "subcategory":"Movie Rental",
            "type":"Entertainment"
        }
    ],
    "sg:phone":"+1 207 827 3111",
    "sg:postcode":"04468",
    "sg:province":"ME",
    "sg:tags":[
        "leasing",
        "video",
        "disc",
        "tape"
    ],
    "wof:name":"Movie Gallery",
    "wof:placetype":"venue"
},
  "geometry": {"coordinates":[-68.66288299999999,44.929431],"type":"Point"}
}