{
  "type": "Feature",
  "properties": {
    "addr:full":"16 Earth Plz Bucksport ME 04472",
    "addr:housenumber":"16",
    "addr:postcode":"04472",
    "addr:street":"Earth Plz",
    "iso:country":"US",
    "sg:address":"16 Earth Plz",
    "sg:city":"Bucksport",
    "sg:classifiers":[
        {
            "category":"Wholesale",
            "subcategory":"Sporting Goods",
            "type":"Manufacturing & Wholesale Goods"
        }
    ],
    "sg:phone":"+1 207 469 9988",
    "sg:postcode":"04472",
    "sg:province":"ME",
    "wof:name":"Staatsburg Manufacturing",
    "wof:placetype":"venue"
},
  "geometry": {"coordinates":[-68.75787699999999,44.571929],"type":"Point"}
}