{
  "type": "Feature",
  "properties": {
    "iso:country":"US",
    "sg:address":"1206 Hammond St",
    "sg:city":"Bangor",
    "sg:classifiers":[
        {
            "category":"Autos & Motor Vehicles",
            "subcategory":"Recreational Vehicle Sales",
            "type":"Retail Goods"
        }
    ],
    "sg:phone":"+1 207 942 2900",
    "sg:postcode":"04401",
    "sg:province":"ME",
    "sg:website":"www.webbsrvcenter.com",
    "wof:name":"Webb's RV Ctr",
    "wof:placetype":"venue"
},
  "geometry": {"coordinates":[-68.82646099999999,44.792194],"type":"Point"}
}