{
  "type": "Feature",
  "properties": {
    "addr:full":"963 Main St Westbrook ME 04092",
    "addr:housenumber":"963",
    "addr:postcode":"04092",
    "addr:street":"Main St",
    "iso:country":"US",
    "sg:address":"963 Main St",
    "sg:city":"Westbrook",
    "sg:classifiers":[
        {
            "category":"Retail",
            "subcategory":"Repair Shop",
            "type":"Services"
        }
    ],
    "sg:phone":"+1 207 854 4991",
    "sg:postcode":"04092",
    "sg:province":"ME",
    "sg:tags":[
        "lock",
        "locksmith"
    ],
    "wof:name":"A-1 Lockbox Inc",
    "wof:placetype":"venue"
},
  "geometry": {"coordinates":[-70.37112999999999,43.677175],"type":"Point"}
}