{
  "type": "Feature",
  "properties": {
    "iso:country":"US",
    "sg:address":"355 Main St",
    "sg:city":"Fort Fairfield",
    "sg:classifiers":[
        {
            "category":"Shopping",
            "subcategory":"Pharmacy",
            "type":"Retail Goods"
        }
    ],
    "sg:phone":"+1 207 472 1191",
    "sg:postcode":"04742",
    "sg:province":"ME",
    "wof:name":"Rite Aid Pharmacy",
    "wof:placetype":"venue"
},
  "geometry": {"coordinates":[-67.83440299999999,46.772439],"type":"Point"}
}