{
  "type": "Feature",
  "properties": {
    "iso:country":"US",
    "sg:address":"863 Main St",
    "sg:city":"Westbrook",
    "sg:classifiers":[
        {
            "category":"Shopping",
            "type":"Retail Goods"
        }
    ],
    "sg:phone":"+1 207 856 7387",
    "sg:postcode":"04092",
    "sg:province":"ME",
    "sg:tags":[
        "pet",
        "shop"
    ],
    "wof:name":"Aquatic Concepts",
    "wof:placetype":"venue"
},
  "geometry": {"coordinates":[-70.365282,43.676455],"type":"Point"}
}