{
  "type": "Feature",
  "properties": {
    "addr:full":"Heather Cir Fryeburg ME 04037",
    "addr:postcode":"04037",
    "addr:street":"Heather Cir",
    "iso:country":"US",
    "sg:address":"Heather Cir",
    "sg:city":"Fryeburg",
    "sg:classifiers":[
        {
            "category":"Building & Trades",
            "subcategory":"Construction",
            "type":"Services"
        }
    ],
    "sg:phone":"+1 207 935 1103",
    "sg:postcode":"04037",
    "sg:province":"ME",
    "sg:tags":[
        "contractor"
    ],
    "wof:name":"Hague Bldg & Remodeling",
    "wof:placetype":"venue"
},
  "geometry": {"coordinates":[-70.975601,44.008999],"type":"Point"}
}