{
  "type": "Feature",
  "properties": {
    "iso:country":"US",
    "sg:address":"328 Main St",
    "sg:city":"Rockland",
    "sg:classifiers":[
        {
            "category":"Restaurant",
            "type":"Food & Drink"
        }
    ],
    "sg:phone":"+1 207 594 4123",
    "sg:postcode":"04841",
    "sg:province":"ME",
    "sg:tags":[
        "shop",
        "coffee"
    ],
    "sg:website":"www.secondreadbooks.com",
    "wof:name":"Second Read Books & Coffee",
    "wof:placetype":"venue"
},
  "geometry": {"coordinates":[-69.109202,44.103154],"type":"Point"}
}