{
  "type": "Feature",
  "properties": {
    "iso:country":"US",
    "sg:address":"45 High Holborn St",
    "sg:city":"Gardiner",
    "sg:classifiers":[
        {
            "category":"Professional",
            "subcategory":"Computer Services",
            "type":"Services"
        }
    ],
    "sg:phone":"+1 207 582 1193",
    "sg:postcode":"04345",
    "sg:province":"ME",
    "sg:tags":[
        "related"
    ],
    "wof:name":"Jean Glinz Rambo",
    "wof:placetype":"venue"
},
  "geometry": {"coordinates":[-69.781433,44.221249],"type":"Point"}
}