{
  "type": "Feature",
  "properties": {
    "addr:full":"2 Tanner St South Portland ME 04106",
    "addr:housenumber":"2",
    "addr:postcode":"04106",
    "addr:street":"Tanner St",
    "iso:country":"US",
    "sg:address":"2 Tanner St",
    "sg:city":"South Portland",
    "sg:classifiers":[
        {
            "category":"Retail",
            "subcategory":"Laundry & Dry Cleaning",
            "type":"Services"
        }
    ],
    "sg:phone":"+1 207 799 2239",
    "sg:postcode":"04106",
    "sg:province":"ME",
    "wof:name":"Aladdin Carpet Cleaning",
    "wof:placetype":"venue"
},
  "geometry": {"coordinates":[-70.26287000000001,43.631868],"type":"Point"}
}