{
  "type": "Feature",
  "properties": {
    "addr:full":"329 Bar Harbor Rd Trenton ME 04605",
    "addr:housenumber":"329",
    "addr:postcode":"04605",
    "addr:street":"Bar Harbor Rd",
    "iso:country":"US",
    "sg:address":"329 Bar Harbor Rd",
    "sg:city":"Trenton",
    "sg:classifiers":[
        {
            "category":"Travel",
            "subcategory":"Hotels & Motels",
            "type":"Entertainment"
        }
    ],
    "sg:phone":"+1 207 667 9458",
    "sg:postcode":"04605",
    "sg:province":"ME",
    "wof:name":"Acadia Gateway Motel",
    "wof:placetype":"venue"
},
  "geometry": {"coordinates":[-68.40123699999999,44.52669],"type":"Point"}
}