{
  "type": "Feature",
  "properties": {
    "addr:full":"559 Congress St Portland ME 04101",
    "addr:housenumber":"559",
    "addr:postcode":"04101",
    "addr:street":"Congress St",
    "iso:country":"US",
    "sg:address":"559 Congress St",
    "sg:city":"Portland",
    "sg:classifiers":[
        {
            "category":"Real Estate",
            "subcategory":"Real Estate Agent",
            "type":"Services"
        }
    ],
    "sg:phone":"+1 207 773 7676",
    "sg:postcode":"04101",
    "sg:province":"ME",
    "sg:tags":[
        "appraiser"
    ],
    "wof:name":"Titherington Associates",
    "wof:placetype":"venue"
},
  "geometry": {"coordinates":[-70.262281,43.654981],"type":"Point"}
}