{
  "type": "Feature",
  "properties": {
    "iso:country":"US",
    "sg:address":"15 Hillside Ave",
    "sg:city":"Old Town",
    "sg:classifiers":[
        {
            "category":"Restaurant",
            "type":"Food & Drink"
        }
    ],
    "sg:phone":"+1 207 827 7789",
    "sg:postcode":"04468",
    "sg:province":"ME",
    "sg:tags":[
        "eating"
    ],
    "wof:name":"Daniel Stirrupp",
    "wof:placetype":"venue"
},
  "geometry": {"coordinates":[-68.643057,44.921928],"type":"Point"}
}