{
  "type": "Feature",
  "properties": {
    "addr:full":"56 Gray Rd Falmouth ME 04105",
    "addr:housenumber":"56",
    "addr:postcode":"04105",
    "addr:street":"Gray Rd",
    "iso:country":"US",
    "sg:address":"56 Gray Rd",
    "sg:city":"Falmouth",
    "sg:phone":"+1 207 797 5691",
    "sg:postcode":"04105",
    "sg:province":"ME",
    "sg:tags":[
        "oil"
    ],
    "wof:name":"Elm Ice & Oil Co",
    "wof:placetype":"venue"
},
  "geometry": {"coordinates":[-70.296575,43.733554],"type":"Point"}
}