{
  "type": "Feature",
  "properties": {
    "addr:full":"14 E Main St Dover Foxcroft ME 04426",
    "addr:housenumber":"14",
    "addr:postcode":"04426",
    "addr:street":"E Main St",
    "iso:country":"US",
    "sg:address":"14 E Main St",
    "sg:city":"Dover Foxcroft",
    "sg:classifiers":[
        {
            "category":"Communications",
            "subcategory":"Radio Station",
            "type":"Services"
        }
    ],
    "sg:phone":"+1 207 564 2642",
    "sg:postcode":"04426",
    "sg:province":"ME",
    "sg:tags":[
        "company",
        "broadcasting"
    ],
    "wof:name":"WDME",
    "wof:placetype":"venue"
},
  "geometry": {"coordinates":[-69.22715700000001,45.183559],"type":"Point"}
}