{
  "type": "Feature",
  "properties": {
    "iso:country":"US",
    "sg:address":"118 Hollis Rd",
    "sg:city":"Hollis Center",
    "sg:classifiers":[
        {
            "category":"Manufacturing",
            "subcategory":"Metals",
            "type":"Manufacturing & Wholesale Goods"
        }
    ],
    "sg:phone":"+1 207 929 3700",
    "sg:postcode":"04093",
    "sg:province":"ME",
    "sg:tags":[
        "stamping"
    ],
    "sg:website":"www.eagleinds.com",
    "wof:name":"Eagle Industries Inc",
    "wof:placetype":"venue"
},
  "geometry": {"coordinates":[-70.560759,43.596833],"type":"Point"}
}