{
  "type": "Feature",
  "properties": {
    "iso:country":"US",
    "sg:address":"29 Edwards St",
    "sg:city":"Waterville",
    "sg:classifiers":[
        {
            "category":"Building & Trades",
            "subcategory":"Construction",
            "type":"Services"
        }
    ],
    "sg:phone":"+1 207 873 1070",
    "sg:postcode":"04901",
    "sg:province":"ME",
    "sg:tags":[
        "residential"
    ],
    "wof:name":"Richard Janreav Construction",
    "wof:placetype":"venue"
},
  "geometry": {"coordinates":[-69.633228,44.560738],"type":"Point"}
}