{
  "type": "Feature",
  "properties": {
    "addr:full":"369 Wilton Rd Farmington ME 04938",
    "addr:housenumber":"369",
    "addr:postcode":"04938",
    "addr:street":"Wilton Rd",
    "iso:country":"US",
    "sg:address":"369 Wilton Rd",
    "sg:city":"Farmington",
    "sg:classifiers":[
        {
            "category":"Restaurant",
            "type":"Food & Drink"
        }
    ],
    "sg:menulink":"http://www.allmenus.com/me/farmington/176327-kfc---kentucky-fried-chicken/menu/",
    "sg:phone":"+1 207 779 0504",
    "sg:postcode":"04938",
    "sg:province":"ME",
    "sg:tags":[
        "american",
        "chicken"
    ],
    "wof:name":"KFC - Kentucky Fried Chicken",
    "wof:placetype":"venue"
},
  "geometry": {"coordinates":[-70.16099699999999,44.62508],"type":"Point"}
}