{
  "type": "Feature",
  "properties": {
    "iso:country":"US",
    "sg:address":"6 Cornfield Hill Rd",
    "sg:city":"Brooksville",
    "sg:classifiers":[
        {
            "category":"Food & Beverages",
            "subcategory":"Groceries & Convenience Stores",
            "type":"Retail Goods"
        }
    ],
    "sg:phone":"+1 207 326 8683",
    "sg:postcode":"04617",
    "sg:province":"ME",
    "sg:tags":[
        "grocer"
    ],
    "wof:name":"Buck's Harbor Market",
    "wof:placetype":"venue"
},
  "geometry": {"coordinates":[-68.738082,44.343419],"type":"Point"}
}