{
  "type": "Feature",
  "properties": {
    "addr:full":"135 College Ave Waterville ME 04901",
    "addr:housenumber":"135",
    "addr:postcode":"04901",
    "addr:street":"College Ave",
    "iso:country":"US",
    "sg:address":"135 College Ave",
    "sg:city":"Waterville",
    "sg:classifiers":[
        {
            "category":"Manufacturing",
            "subcategory":"Food",
            "type":"Manufacturing & Wholesale Goods"
        }
    ],
    "sg:phone":"+1 207 872 7599",
    "sg:postcode":"04901",
    "sg:province":"ME",
    "sg:tags":[
        "confectionery",
        "candy"
    ],
    "wof:name":"Great Northern Fudge Co",
    "wof:placetype":"venue"
},
  "geometry": {"coordinates":[-69.62299,44.567494],"type":"Point"}
}