{
  "type": "Feature",
  "properties": {
    "addr:full":"250 Broad St Auburn ME 04210",
    "addr:housenumber":"250",
    "addr:postcode":"04210",
    "addr:street":"Broad St",
    "iso:country":"US",
    "sg:address":"250 Broad St",
    "sg:city":"Auburn",
    "sg:classifiers":[
        {
            "category":"Retail",
            "subcategory":"Auto Repair",
            "type":"Services"
        }
    ],
    "sg:phone":"+1 207 782 6400",
    "sg:postcode":"04210",
    "sg:province":"ME",
    "sg:tags":[
        "truck"
    ],
    "sg:website":"www.evmfire.com",
    "wof:name":"Emergency Vehicles Of Maine",
    "wof:placetype":"venue"
},
  "geometry": {"coordinates":[-70.233681,44.078593],"type":"Point"}
}