{
  "type": "Feature",
  "properties": {
    "addr:full":"93 Main St Kennebunk ME 04043",
    "addr:housenumber":"93",
    "addr:postcode":"04043",
    "addr:street":"Main St",
    "iso:country":"US",
    "sg:address":"93 Main St",
    "sg:city":"Kennebunk",
    "sg:classifiers":[
        {
            "category":"Professional",
            "subcategory":"Lawyer & Legal Services",
            "type":"Services"
        }
    ],
    "sg:phone":"+1 207 985 2326",
    "sg:postcode":"04043",
    "sg:province":"ME",
    "wof:name":"Shepard & Read",
    "wof:placetype":"venue"
},
  "geometry": {"coordinates":[-70.538597,43.387199],"type":"Point"}
}