{
  "type": "Feature",
  "properties": {
    "addr:full":"158 Centre Rd Wales ME 04280",
    "addr:housenumber":"158",
    "addr:postcode":"me 04280",
    "addr:street":"Centre Rd",
    "iso:country":"US",
    "sg:address":"158 Centre Rd",
    "sg:city":"Wales",
    "sg:classifiers":[
        {
            "category":"Wholesale",
            "subcategory":"Machinery & Supplies",
            "type":"Manufacturing & Wholesale Goods"
        }
    ],
    "sg:phone":"+1 207 375 6680",
    "sg:postcode":"04280",
    "sg:province":"ME",
    "sg:tags":[
        "farm",
        "equipment"
    ],
    "wof:name":"Foss & Sons",
    "wof:placetype":"venue"
},
  "geometry": {"coordinates":[-70.055577,44.167307],"type":"Point"}
}