{
  "type": "Feature",
  "properties": {
    "addr:full":"28 Byfield Rd Portland ME 04103",
    "addr:housenumber":"28",
    "addr:postcode":"04103",
    "addr:street":"Byfield Rd",
    "iso:country":"US",
    "sg:address":"28 Byfield Rd",
    "sg:city":"Portland",
    "sg:classifiers":[
        {
            "category":"Organizations",
            "subcategory":"Non-profit Organization",
            "type":"Services"
        }
    ],
    "sg:phone":"+1 207 773 6221",
    "sg:postcode":"04103",
    "sg:province":"ME",
    "wof:name":"Cleo Fund",
    "wof:placetype":"venue"
},
  "geometry": {"coordinates":[-70.26937599999999,43.687598],"type":"Point"}
}