{
  "type": "Feature",
  "properties": {
    "iso:country":"US",
    "sg:address":"290 Tuttle Rd",
    "sg:city":"Cumberland Ctr",
    "sg:classifiers":[
        {
            "category":"Government",
            "subcategory":"Office",
            "type":"Public Place"
        }
    ],
    "sg:phone":"+1 207 829 2207",
    "sg:postcode":"04021",
    "sg:province":"ME",
    "sg:tags":[
        "village"
    ],
    "wof:name":"Building Inspector",
    "wof:placetype":"venue"
},
  "geometry": {"coordinates":[-70.244046,43.789522],"type":"Point"}
}