{
  "type": "Feature",
  "properties": {
    "iso:country":"US",
    "sg:address":"22 Bramhall St",
    "sg:city":"Portland",
    "sg:classifiers":[
        {
            "category":"Health Services",
            "subcategory":"Medical Lab",
            "type":"Services"
        }
    ],
    "sg:phone":"+1 207 871 2711",
    "sg:postcode":"04102",
    "sg:province":"ME",
    "sg:tags":[
        "laboratory"
    ],
    "sg:website":"www.nordx.com",
    "wof:name":"Nordx",
    "wof:placetype":"venue"
},
  "geometry": {"coordinates":[-70.27592799999999,43.65167],"type":"Point"}
}