{
  "type": "Feature",
  "properties": {
    "iso:country":"US",
    "sg:address":"88 W Main St",
    "sg:city":"Fort Kent",
    "sg:classifiers":[
        {
            "category":"Personal",
            "subcategory":"Beauty Salon",
            "type":"Services"
        }
    ],
    "sg:phone":"+1 207 834 2339",
    "sg:postcode":"04743",
    "sg:province":"ME",
    "sg:tags":[
        "shop"
    ],
    "wof:name":"Cutting Edge",
    "wof:placetype":"venue"
},
  "geometry": {"coordinates":[-68.60243800000001,47.248262],"type":"Point"}
}