{
  "type": "Feature",
  "properties": {
    "addr:full":"473 Church Hill Rd Augusta ME 04330",
    "addr:housenumber":"473",
    "addr:postcode":"04330",
    "addr:street":"Church Hill Rd",
    "iso:country":"US",
    "sg:address":"473 Church Hill Rd",
    "sg:city":"Augusta",
    "sg:classifiers":[
        {
            "category":"Building & Trades",
            "subcategory":"Plumbing",
            "type":"Services"
        }
    ],
    "sg:phone":"+1 207 626 3371",
    "sg:postcode":"04330",
    "sg:province":"ME",
    "sg:tags":[
        "contractor"
    ],
    "wof:name":"Dufours Welding & Mech Svc",
    "wof:placetype":"venue"
},
  "geometry": {"coordinates":[-69.721509,44.345771],"type":"Point"}
}