{
  "type": "Feature",
  "properties": {
    "iso:country":"US",
    "sg:address":"4 Not A Rd",
    "sg:city":"Naples",
    "sg:classifiers":[
        {
            "category":"Retail",
            "subcategory":"Auto Repair",
            "type":"Services"
        }
    ],
    "sg:phone":"+1 207 693 3857",
    "sg:postcode":"04002",
    "sg:province":"ME",
    "sg:tags":[
        "wrecker"
    ],
    "wof:name":"Allen's Towing",
    "wof:placetype":"venue"
},
  "geometry": {"coordinates":[-70.614118,43.504766],"type":"Point"}
}