{
  "type": "Feature",
  "properties": {
    "iso:country":"US",
    "sg:address":"60 Steinmeyer Rd",
    "sg:city":"Washington",
    "sg:classifiers":[
        {
            "category":"Retail",
            "subcategory":"Auto Repair",
            "type":"Services"
        }
    ],
    "sg:phone":"+1 207 845 2590",
    "sg:postcode":"04574",
    "sg:province":"ME",
    "sg:tags":[
        "repairing",
        "automobile",
        "body"
    ],
    "wof:name":"M E Moore Auto Body",
    "wof:placetype":"venue"
},
  "geometry": {"coordinates":[-69.400762,44.247631],"type":"Point"}
}