{
  "type": "Feature",
  "properties": {
    "iso:country":"US",
    "sg:address":"75 River Rd",
    "sg:city":"Detroit",
    "sg:classifiers":[
        {
            "category":"Local Transit",
            "type":"Transportation"
        }
    ],
    "sg:phone":"+1 207 257 3257",
    "sg:postcode":"04929",
    "sg:province":"ME",
    "sg:tags":[
        "bus",
        "line"
    ],
    "wof:name":"Cyr Bus Line",
    "wof:placetype":"venue"
},
  "geometry": {"coordinates":[-69.33309199999999,44.777428],"type":"Point"}
}