{
  "type": "Feature",
  "properties": {
    "iso:country":"US",
    "sg:address":"249 Barker Rd",
    "sg:city":"Bethel",
    "sg:classifiers":[
        {
            "category":"Building & Trades",
            "subcategory":"Construction",
            "type":"Services"
        }
    ],
    "sg:phone":"+1 207 836 6025",
    "sg:postcode":"04217",
    "sg:province":"ME",
    "sg:tags":[
        "house"
    ],
    "wof:name":"Bennett Builders",
    "wof:placetype":"venue"
},
  "geometry": {"coordinates":[-70.846813,44.413347],"type":"Point"}
}