{
  "type": "Feature",
  "properties": {
    "iso:country":"US",
    "sg:address":"667 North Rd",
    "sg:city":"Leeds",
    "sg:classifiers":[
        {
            "category":"Building & Trades",
            "subcategory":"Construction",
            "type":"Services"
        }
    ],
    "sg:phone":"+1 207 524 3751",
    "sg:postcode":"04263",
    "sg:province":"ME",
    "sg:tags":[
        "concrete",
        "contractor"
    ],
    "wof:name":"Nutting Foundations",
    "wof:placetype":"venue"
},
  "geometry": {"coordinates":[-70.13858,44.302914],"type":"Point"}
}