{
  "type": "Feature",
  "properties": {
    "addr:full":"474 Main St Gorham ME 04038",
    "addr:housenumber":"474",
    "addr:postcode":"04038",
    "addr:street":"Main St",
    "iso:country":"US",
    "sg:address":"474 Main St",
    "sg:city":"Gorham",
    "sg:classifiers":[
        {
            "category":"Shopping",
            "subcategory":"Used Merchandise",
            "type":"Retail Goods"
        }
    ],
    "sg:phone":"+1 207 839 7839",
    "sg:postcode":"04038",
    "sg:province":"ME",
    "sg:tags":[
        "clothing"
    ],
    "wof:name":"Tots To Teens",
    "wof:placetype":"venue"
},
  "geometry": {"coordinates":[-70.40734999999999,43.69023],"type":"Point"}
}