{
  "type": "Feature",
  "properties": {
    "addr:full":"482 Congress St Portland ME 04101",
    "addr:housenumber":"482",
    "addr:postcode":"04101",
    "addr:street":"Congress St",
    "iso:country":"US",
    "sg:address":"482 Congress St",
    "sg:city":"Portland",
    "sg:classifiers":[
        {
            "category":"Professional",
            "subcategory":"Lawyer & Legal Services",
            "type":"Services"
        }
    ],
    "sg:phone":"+1 207 774 2651",
    "sg:postcode":"04101",
    "sg:province":"ME",
    "sg:tags":[
        "attorney"
    ],
    "wof:name":"Wilson Fernald & Foley",
    "wof:placetype":"venue"
},
  "geometry": {"coordinates":[-70.260205,43.656547],"type":"Point"}
}