{
  "type": "Feature",
  "properties": {
    "addr:full":"147 N Bath Rd West Bath ME 04530",
    "addr:housenumber":"147",
    "addr:postcode":"04530",
    "addr:street":"N Bath Rd",
    "iso:country":"US",
    "sg:address":"147 N Bath Rd",
    "sg:city":"West Bath",
    "sg:classifiers":[
        {
            "category":"Government",
            "subcategory":"Court House",
            "type":"Public Place"
        }
    ],
    "sg:phone":"+1 207 443 5104",
    "sg:postcode":"04530",
    "sg:province":"ME",
    "sg:tags":[
        "county",
        "counsel"
    ],
    "wof:name":"Cumberland Cnty Dist Attorney",
    "wof:placetype":"venue"
},
  "geometry": {"coordinates":[-69.838097,43.949365],"type":"Point"}
}