{
  "type": "Feature",
  "properties": {
    "addr:full":"18 Vine St Gardiner ME 04345",
    "addr:housenumber":"18",
    "addr:postcode":"04345",
    "addr:street":"Vine St",
    "iso:country":"US",
    "sg:address":"18 Vine St",
    "sg:city":"Gardiner",
    "sg:classifiers":[
        {
            "category":"Professional",
            "subcategory":"Business Services",
            "type":"Services"
        }
    ],
    "sg:phone":"+1 207 582 3617",
    "sg:postcode":"04345",
    "sg:province":"ME",
    "wof:name":"Maine Professional Inspections",
    "wof:placetype":"venue"
},
  "geometry": {"coordinates":[-69.77009099999999,44.227526],"type":"Point"}
}