{
  "type": "Feature",
  "properties": {
    "iso:country":"US",
    "sg:address":"320 Water St",
    "sg:city":"Augusta",
    "sg:classifiers":[
        {
            "category":"Professional",
            "subcategory":"Engineering",
            "type":"Services"
        }
    ],
    "sg:phone":"+1 207 626 0613",
    "sg:postcode":"04330",
    "sg:province":"ME",
    "sg:tags":[
        "engineer"
    ],
    "sg:website":"www.hillierinc.com",
    "wof:name":"Hillier & Assoc",
    "wof:placetype":"venue"
},
  "geometry": {"coordinates":[-69.774708,44.314126],"type":"Point"}
}