{
  "type": "Feature",
  "properties": {
    "iso:country":"US",
    "sg:address":"776 Odlin Rd",
    "sg:city":"Bangor",
    "sg:classifiers":[
        {
            "category":"Building & Trades",
            "subcategory":"Construction",
            "type":"Services"
        }
    ],
    "sg:phone":"+1 207 262 0154",
    "sg:postcode":"04401",
    "sg:province":"ME",
    "sg:tags":[
        "paving",
        "contractor"
    ],
    "wof:name":"Harvey Paving & Seal Coating",
    "wof:placetype":"venue"
},
  "geometry": {"coordinates":[-68.83142100000001,44.779888],"type":"Point"}
}