{
  "type": "Feature",
  "properties": {
    "addr:full":"178 Main St Jonesport ME 04609",
    "addr:housenumber":"178",
    "addr:postcode":"04609",
    "addr:street":"Main St",
    "iso:country":"US",
    "sg:address":"178 Main St",
    "sg:city":"Jonesport",
    "sg:classifiers":[
        {
            "category":"Real Estate",
            "subcategory":"Real Estate Agent",
            "type":"Services"
        }
    ],
    "sg:phone":"+1 207 497 2818",
    "sg:postcode":"04609",
    "sg:province":"ME",
    "wof:name":"Paul T Iossa Real Estate Agcy",
    "wof:placetype":"venue"
},
  "geometry": {"coordinates":[-68.204224,44.387727],"type":"Point"}
}