{
  "type": "Feature",
  "properties": {
    "addr:full":"264 Mitchell Rd Freedom ME 04941",
    "addr:housenumber":"264",
    "addr:postcode":"04941",
    "addr:street":"Mitchell Rd",
    "iso:country":"US",
    "sg:address":"264 Mitchell Rd",
    "sg:city":"Freedom",
    "sg:classifiers":[
        {
            "category":"Wholesale",
            "subcategory":"Plants",
            "type":"Manufacturing & Wholesale Goods"
        }
    ],
    "sg:phone":"+1 207 382 6225",
    "sg:postcode":"04941",
    "sg:province":"ME",
    "sg:tags":[
        "florist"
    ],
    "sg:website":"www.wreathsfrommaine.com",
    "wof:name":"Freedom Acres",
    "wof:placetype":"venue"
},
  "geometry": {"coordinates":[-69.319958,44.502986],"type":"Point"}
}