{
  "type": "Feature",
  "properties": {
    "addr:full":"77 Water St Hallowell ME 04347",
    "addr:housenumber":"77",
    "addr:postcode":"04347",
    "addr:street":"Water St",
    "iso:country":"US",
    "sg:address":"77 Water St",
    "sg:city":"Hallowell",
    "sg:classifiers":[
        {
            "category":"Organizations",
            "subcategory":"Professional Association",
            "type":"Services"
        }
    ],
    "sg:phone":"+1 207 623 3480",
    "sg:postcode":"04347",
    "sg:province":"ME",
    "wof:name":"Maine Apartment Owners",
    "wof:placetype":"venue"
},
  "geometry": {"coordinates":[-69.789813,44.288084],"type":"Point"}
}