{
  "type": "Feature",
  "properties": {
    "addr:full":"730 Union St Bangor ME 04401",
    "addr:housenumber":"730",
    "addr:postcode":"04401",
    "addr:street":"Union St",
    "iso:country":"US",
    "sg:address":"730 Union St",
    "sg:city":"Bangor",
    "sg:classifiers":[
        {
            "category":"Real Estate",
            "subcategory":"Real Estate Operator",
            "type":"Services"
        }
    ],
    "sg:phone":"+1 207 942 3152",
    "sg:postcode":"04401",
    "sg:province":"ME",
    "sg:tags":[
        "apartment"
    ],
    "wof:name":"Longrale Park Apartments",
    "wof:placetype":"venue"
},
  "geometry": {"coordinates":[-68.796162,44.810059],"type":"Point"}
}