{
  "type": "Feature",
  "properties": {
    "iso:country":"US",
    "sg:address":"248 Common Rd",
    "sg:city":"Dresden",
    "sg:classifiers":[
        {
            "category":"Building & Trades",
            "subcategory":"Plumbing",
            "type":"Services"
        }
    ],
    "sg:phone":"+1 207 737 8109",
    "sg:postcode":"04342",
    "sg:province":"ME",
    "sg:tags":[
        "plumbing",
        "contractor"
    ],
    "wof:name":"Stewart Plumbing & Heating",
    "wof:placetype":"venue"
},
  "geometry": {"coordinates":[-69.744142,44.105175],"type":"Point"}
}