{
  "type": "Feature",
  "properties": {
    "iso:country":"US",
    "sg:address":"25 Centre St",
    "sg:city":"Bath",
    "sg:classifiers":[
        {
            "category":"Personal",
            "subcategory":"Beauty Salon",
            "type":"Services"
        }
    ],
    "sg:phone":"+1 207 443 6164",
    "sg:postcode":"04530",
    "sg:province":"ME",
    "wof:name":"Shear Beauty",
    "wof:placetype":"venue"
},
  "geometry": {"coordinates":[-69.814851,43.912761],"type":"Point"}
}