{
  "type": "Feature",
  "properties": {
    "addr:full":"488 Hollis Rd Hollis Center ME 04042",
    "addr:housenumber":"488",
    "addr:postcode":"04042",
    "addr:street":"Hollis Rd",
    "iso:country":"US",
    "sg:address":"488 Hollis Rd",
    "sg:city":"Hollis Center",
    "sg:phone":"+1 207 929 5550",
    "sg:postcode":"04042",
    "sg:province":"ME",
    "sg:tags":[
        "oil"
    ],
    "wof:name":"Buxton Oil Co",
    "wof:placetype":"venue"
},
  "geometry": {"coordinates":[-70.605158,43.599581],"type":"Point"}
}