{
  "type": "Feature",
  "properties": {
    "addr:full":"7 Spring St Hallowell ME 04347",
    "addr:housenumber":"7",
    "addr:postcode":"04347",
    "addr:street":"Spring St",
    "iso:country":"US",
    "sg:address":"7 Spring St",
    "sg:city":"Hallowell",
    "sg:classifiers":[
        {
            "category":"Real Estate",
            "subcategory":"Surveying",
            "type":"Services"
        }
    ],
    "sg:phone":"+1 207 622 5937",
    "sg:postcode":"04347",
    "sg:province":"ME",
    "sg:tags":[
        "surveyor"
    ],
    "wof:name":"J Robert Curtis",
    "wof:placetype":"venue"
},
  "geometry": {"coordinates":[-69.79366899999999,44.287624],"type":"Point"}
}