{
  "type": "Feature",
  "properties": {
    "iso:country":"US",
    "sg:address":"1298 Main St",
    "sg:city":"Sanford",
    "sg:classifiers":[
        {
            "category":"Professional",
            "subcategory":"Computer Services",
            "type":"Services"
        }
    ],
    "sg:phone":"+1 207 490 5992",
    "sg:postcode":"04073",
    "sg:province":"ME",
    "wof:name":"Bmyster LLC",
    "wof:placetype":"venue"
},
  "geometry": {"coordinates":[-70.752634,43.416698],"type":"Point"}
}