{
  "type": "Feature",
  "properties": {
    "addr:full":"875 Lisbon St Lewiston ME 04240",
    "addr:housenumber":"875",
    "addr:postcode":"04240",
    "addr:street":"Lisbon St",
    "iso:country":"US",
    "sg:address":"875 Lisbon St",
    "sg:city":"Lewiston",
    "sg:classifiers":[
        {
            "category":"Restaurant",
            "type":"Food & Drink"
        }
    ],
    "sg:phone":"+1 207 782 7526",
    "sg:postcode":"04240",
    "sg:province":"ME",
    "wof:name":"Pepper & Spice",
    "wof:placetype":"venue"
},
  "geometry": {"coordinates":[-70.201792,44.083562],"type":"Point"}
}