{
  "type": "Feature",
  "properties": {
    "addr:full":"7 Hatch Dr Caribou ME 04736",
    "addr:housenumber":"7",
    "addr:postcode":"04736",
    "addr:street":"Hatch Dr",
    "iso:country":"US",
    "sg:address":"7 Hatch Dr",
    "sg:city":"Caribou",
    "sg:classifiers":[
        {
            "category":"Health Services",
            "subcategory":"Doctor",
            "type":"Services"
        }
    ],
    "sg:phone":"+1 207 498 3141",
    "sg:postcode":"04736",
    "sg:province":"ME",
    "sg:tags":[
        "physician",
        "surgeon"
    ],
    "wof:name":"Elizabeth S Quayle MD",
    "wof:placetype":"venue"
},
  "geometry": {"coordinates":[-68.015934,46.860011],"type":"Point"}
}