{
  "type": "Feature",
  "properties": {
    "iso:country":"US",
    "sg:address":"24 School St",
    "sg:city":"Milbridge",
    "sg:classifiers":[
        {
            "category":"Health Services",
            "subcategory":"Doctor",
            "type":"Services"
        }
    ],
    "sg:phone":"+1 207 546 2391",
    "sg:postcode":"04605",
    "sg:province":"ME",
    "sg:tags":[
        "physician",
        "surgeon"
    ],
    "wof:name":"Milbridge Medical Ctr",
    "wof:placetype":"venue"
},
  "geometry": {"coordinates":[-68.423915,44.544236],"type":"Point"}
}