{
  "type": "Feature",
  "properties": {
    "iso:country":"US",
    "sg:address":"16 Vose St",
    "sg:city":"Waterville",
    "sg:classifiers":[
        {
            "category":"Retail",
            "subcategory":"Repair Shop",
            "type":"Services"
        }
    ],
    "sg:phone":"+1 207 872 2850",
    "sg:postcode":"04901",
    "sg:province":"ME",
    "sg:tags":[
        "locksmith"
    ],
    "wof:name":"Aable Locksmith Services",
    "wof:placetype":"venue"
},
  "geometry": {"coordinates":[-69.646692,44.551503],"type":"Point"}
}