{
  "type": "Feature",
  "properties": {
    "iso:country":"US",
    "sg:address":"112 Ocean St",
    "sg:city":"South Portland",
    "sg:classifiers":[
        {
            "category":"Personal",
            "subcategory":"Beauty Salon",
            "type":"Services"
        }
    ],
    "sg:phone":"+1 207 767 6226",
    "sg:postcode":"04106",
    "sg:province":"ME",
    "wof:name":"Bayside Hair & Nail Salon",
    "wof:placetype":"venue"
},
  "geometry": {"coordinates":[-70.252595,43.636876],"type":"Point"}
}