{
  "type": "Feature",
  "properties": {
    "addr:full":"296 Stroudwater St Westbrook ME 04092",
    "addr:housenumber":"296",
    "addr:postcode":"04092",
    "addr:street":"Stroudwater St",
    "iso:country":"US",
    "sg:address":"296 Stroudwater St",
    "sg:city":"Westbrook",
    "sg:classifiers":[
        {
            "category":"Real Estate",
            "subcategory":"Developer",
            "type":"Services"
        }
    ],
    "sg:phone":"+1 207 856 6148",
    "sg:postcode":"04092",
    "sg:province":"ME",
    "sg:tags":[
        "cemetery"
    ],
    "wof:name":"St Hyacinth's Cemetery",
    "wof:placetype":"venue"
},
  "geometry": {"coordinates":[-70.348567,43.669924],"type":"Point"}
}