{
  "type": "Feature",
  "properties": {
    "addr:full":"327 Ocean House Rd Cape Eliz ME 04107",
    "addr:housenumber":"327",
    "addr:postcode":"04107",
    "addr:street":"Ocean House Rd",
    "iso:country":"US",
    "sg:address":"327 Ocean House Rd",
    "sg:city":"Cape Eliz",
    "sg:classifiers":[
        {
            "category":"Banks & Credit Unions",
            "subcategory":"Bank",
            "type":"Services"
        }
    ],
    "sg:phone":"+1 207 767 2501",
    "sg:postcode":"04107",
    "sg:province":"ME",
    "wof:name":"Greater Portland Municipal Federal Credit Union",
    "wof:placetype":"venue"
},
  "geometry": {"coordinates":[-70.226997,43.5942],"type":"Point"}
}