{
  "type": "Feature",
  "properties": {
    "iso:country":"US",
    "sg:address":"516 Princes Point Rd",
    "sg:city":"Yarmouth",
    "sg:classifiers":[
        {
            "category":"Restaurant",
            "type":"Food & Drink"
        }
    ],
    "sg:phone":"+1 207 729 1956",
    "sg:postcode":"04096",
    "sg:province":"ME",
    "sg:tags":[
        "eating",
        "gallery"
    ],
    "wof:name":"Thompson Ice Hse Prsrvtn Corp",
    "wof:placetype":"venue"
},
  "geometry": {"coordinates":[-70.172355,43.769649],"type":"Point"}
}