{
  "type": "Feature",
  "properties": {
    "addr:full":"97 Allen St Bangor ME 04401",
    "addr:housenumber":"97",
    "addr:postcode":"04401",
    "addr:street":"Allen St",
    "iso:country":"US",
    "sg:address":"97 Allen St",
    "sg:city":"Bangor",
    "sg:classifiers":[
        {
            "category":"Personal",
            "subcategory":"Beauty Salon",
            "type":"Services"
        }
    ],
    "sg:phone":"+1 207 945 6033",
    "sg:postcode":"04401",
    "sg:province":"ME",
    "wof:name":"Changes",
    "wof:placetype":"venue"
},
  "geometry": {"coordinates":[-68.794602,44.801064],"type":"Point"}
}