{
  "type": "Feature",
  "properties": {
    "addr:full":"509 Pendleton Point Rd Islesboro ME 04848",
    "addr:housenumber":"509",
    "addr:postcode":"04848",
    "addr:street":"Pendleton Point Rd",
    "iso:country":"US",
    "sg:address":"509 Pendleton Point Rd",
    "sg:city":"Islesboro",
    "sg:classifiers":[
        {
            "category":"Social Services",
            "type":"Services"
        }
    ],
    "sg:phone":"+1 207 734 8360",
    "sg:postcode":"04848",
    "sg:province":"ME",
    "sg:tags":[
        "youth",
        "organization",
        "center"
    ],
    "wof:name":"Islesboro Youth Ctr",
    "wof:placetype":"venue"
},
  "geometry": {"coordinates":[-68.912595,44.264883],"type":"Point"}
}