{
  "type": "Feature",
  "properties": {
    "addr:full":"17 Cobbossee Ave Gardiner ME 04345",
    "addr:housenumber":"17",
    "addr:postcode":"04345",
    "addr:street":"Cobbossee Ave",
    "iso:country":"US",
    "sg:address":"17 Cobbossee Ave",
    "sg:city":"Gardiner",
    "sg:phone":"+1 207 582 5712",
    "sg:postcode":"04345",
    "sg:province":"ME",
    "sg:tags":[
        "oil"
    ],
    "sg:website":"www.russwilliamsfuel.com",
    "wof:name":"Russ Williams Fuel Inc",
    "wof:placetype":"venue"
},
  "geometry": {"coordinates":[-69.807827,44.213228],"type":"Point"}
}