{
  "type": "Feature",
  "properties": {
    "addr:full":"458 Kennedy Memorial Dr Waterville ME 04901",
    "addr:housenumber":"458",
    "addr:postcode":"04901",
    "addr:street":"Kennedy Memorial Dr",
    "iso:country":"US",
    "sg:address":"458 Kennedy Memorial Dr",
    "sg:city":"Waterville",
    "sg:classifiers":[
        {
            "category":"Utilities",
            "subcategory":"Mobile Phone",
            "type":"Services"
        }
    ],
    "sg:phone":"+1 207 557 5525",
    "sg:postcode":"04901",
    "sg:province":"ME",
    "sg:tags":[
        "telephone",
        "cellular"
    ],
    "wof:name":"US Cellular",
    "wof:placetype":"venue"
},
  "geometry": {"coordinates":[-69.68131200000001,44.544737],"type":"Point"}
}