{
  "type": "Feature",
  "properties": {
    "addr:full":"Shore Rd Cape Neddick ME 03902",
    "addr:postcode":"03902",
    "addr:street":"Shore Rd",
    "iso:country":"US",
    "sg:address":"Shore Rd",
    "sg:city":"Cape Neddick",
    "sg:classifiers":[
        {
            "category":"Sports & Exercise",
            "subcategory":"Golf",
            "type":"Entertainment"
        }
    ],
    "sg:phone":"+1 207 361 2012",
    "sg:postcode":"03902",
    "sg:province":"ME",
    "sg:website":"www.capeneddickgolf.com",
    "wof:name":"Cape Neddick Country Club",
    "wof:placetype":"venue"
},
  "geometry": {"coordinates":[-70.610901,43.219299],"type":"Point"}
}