{
  "type": "Feature",
  "properties": {
    "iso:country":"US",
    "sg:address":"179 Lisbon St",
    "sg:city":"Lewiston",
    "sg:classifiers":[
        {
            "category":"Government",
            "subcategory":"Office",
            "type":"Public Place"
        }
    ],
    "sg:phone":"+1 207 782 3704",
    "sg:postcode":"04240",
    "sg:province":"ME",
    "wof:name":"Congressman Mike Michaud",
    "wof:placetype":"venue"
},
  "geometry": {"coordinates":[-70.21679899999999,44.095886],"type":"Point"}
}