{
  "type": "Feature",
  "properties": {
    "iso:country":"US",
    "sg:address":"76 Silver St",
    "sg:city":"Waterville",
    "sg:classifiers":[
        {
            "category":"Professional",
            "subcategory":"Accounting & Tax Preparation",
            "type":"Services"
        }
    ],
    "sg:phone":"+1 207 872 7077",
    "sg:postcode":"04901",
    "sg:province":"ME",
    "sg:tags":[
        "accountant"
    ],
    "sg:website":"www.nicholsoncpa.com",
    "wof:name":"Nicholson & Assoc",
    "wof:placetype":"venue"
},
  "geometry": {"coordinates":[-69.635607,44.546313],"type":"Point"}
}