{
  "type": "Feature",
  "properties": {
    "addr:full":"473 Monroe Rd Hampden ME 04444",
    "addr:housenumber":"473",
    "addr:postcode":"04444",
    "addr:street":"Monroe Rd",
    "iso:country":"US",
    "sg:address":"473 Monroe Rd",
    "sg:city":"Hampden",
    "sg:classifiers":[
        {
            "category":"Professional",
            "subcategory":"Management & Consulting",
            "type":"Services"
        }
    ],
    "sg:phone":"+1 207 862 3382",
    "sg:postcode":"04444",
    "sg:province":"ME",
    "sg:tags":[
        "environmental",
        "consultant"
    ],
    "wof:name":"Gayle B Zydlewski",
    "wof:placetype":"venue"
},
  "geometry": {"coordinates":[-68.904023,44.690529],"type":"Point"}
}