{
  "type": "Feature",
  "properties": {
    "addr:full":"200 Running Hill Rd South Portland ME 04106",
    "addr:housenumber":"200",
    "addr:postcode":"04106",
    "addr:street":"Running Hill Rd",
    "iso:country":"US",
    "sg:address":"200 Running Hill Rd",
    "sg:city":"South Portland",
    "sg:classifiers":[
        {
            "category":"Coffee & Tea",
            "type":"Food & Drink"
        }
    ],
    "sg:menulink":"http://www.allmenus.com/me/south-portland/113672-starbucks-coffee/menu/",
    "sg:phone":"+1 207 879 4380",
    "sg:postcode":"04106",
    "sg:province":"ME",
    "sg:tags":[
        "american"
    ],
    "wof:name":"Starbucks Coffee",
    "wof:placetype":"venue"
},
  "geometry": {"coordinates":[-70.350791,43.633269],"type":"Point"}
}