{
  "type": "Feature",
  "properties": {
    "iso:country":"US",
    "sg:address":"400 Allen Ave",
    "sg:city":"Portland",
    "sg:classifiers":[
        {
            "category":"Real Estate",
            "subcategory":"Real Estate Agent",
            "type":"Services"
        }
    ],
    "sg:phone":"+1 207 797 7777",
    "sg:postcode":"04103",
    "sg:province":"ME",
    "wof:name":"Greater Portland Realty",
    "wof:placetype":"venue"
},
  "geometry": {"coordinates":[-70.287772,43.700233],"type":"Point"}
}