{
  "type": "Feature",
  "properties": {
    "addr:full":"269 Ocean St South Portland ME 04106",
    "addr:housenumber":"269",
    "addr:postcode":"04106",
    "addr:street":"Ocean St",
    "iso:country":"US",
    "sg:address":"269 Ocean St",
    "sg:city":"South Portland",
    "sg:classifiers":[
        {
            "category":"Insurance",
            "subcategory":"Insurance Agent",
            "type":"Services"
        }
    ],
    "sg:phone":"+1 207 767 9120",
    "sg:postcode":"04106",
    "sg:province":"ME",
    "wof:name":"Le Mieux Planning Inc",
    "wof:placetype":"venue"
},
  "geometry": {"coordinates":[-70.25202899999999,43.633479],"type":"Point"}
}