{
  "type": "Feature",
  "properties": {
    "iso:country":"US",
    "sg:address":"6 School St",
    "sg:city":"Gorham",
    "sg:classifiers":[
        {
            "category":"Education",
            "subcategory":"Dance Studio",
            "type":"Public Place"
        }
    ],
    "sg:phone":"+1 207 839 6161",
    "sg:postcode":"04038",
    "sg:province":"ME",
    "wof:name":"Dance Studio",
    "wof:placetype":"venue"
},
  "geometry": {"coordinates":[-70.443055,43.679766],"type":"Point"}
}