{
  "type": "Feature",
  "properties": {
    "iso:country":"US",
    "sg:address":"16 Farm Rd",
    "sg:city":"Winthrop",
    "sg:classifiers":[
        {
            "category":"Shopping",
            "subcategory":"Pharmacy",
            "type":"Retail Goods"
        }
    ],
    "sg:phone":"+1 207 377 2279",
    "sg:postcode":"04342",
    "sg:province":"ME",
    "wof:name":"Rite Aid Pharmacy",
    "wof:placetype":"venue"
},
  "geometry": {"coordinates":[-69.77896,44.068977],"type":"Point"}
}