{
  "type": "Feature",
  "properties": {
    "addr:full":"19 West St Portland ME 04102",
    "addr:housenumber":"19",
    "addr:postcode":"04102",
    "addr:street":"West St",
    "iso:country":"US",
    "sg:address":"19 West St",
    "sg:city":"Portland",
    "sg:classifiers":[
        {
            "category":"Health Services",
            "subcategory":"Hospital",
            "type":"Services"
        }
    ],
    "sg:phone":"+1 207 871 2000",
    "sg:postcode":"04102",
    "sg:province":"ME",
    "wof:name":"Maine Kidney Transplant Prog",
    "wof:placetype":"venue"
},
  "geometry": {"coordinates":[-70.270579,43.650865],"type":"Point"}
}