{
  "type": "Feature",
  "properties": {
    "addr:full":"292 W Lebanon Rd East Lebanon ME 04027",
    "addr:housenumber":"292",
    "addr:postcode":"04027",
    "addr:street":"W Lebanon Rd",
    "iso:country":"US",
    "sg:address":"292 W Lebanon Rd",
    "sg:city":"East Lebanon",
    "sg:classifiers":[
        {
            "category":"Retail",
            "subcategory":"Repair Shop",
            "type":"Services"
        }
    ],
    "sg:phone":"+1 207 457 2068",
    "sg:postcode":"04027",
    "sg:province":"ME",
    "sg:tags":[
        "welding"
    ],
    "wof:name":"Daves Welding",
    "wof:placetype":"venue"
},
  "geometry": {"coordinates":[-70.94091899999999,43.373742],"type":"Point"}
}