{
  "type": "Feature",
  "properties": {
    "iso:country":"US",
    "sg:address":"104 Glenwood Ave",
    "sg:city":"Portland",
    "sg:classifiers":[
        {
            "category":"Building & Trades",
            "subcategory":"Cleaning & Sanitation",
            "type":"Services"
        }
    ],
    "sg:phone":"+1 207 772 1574",
    "sg:postcode":"04103",
    "sg:province":"ME",
    "sg:tags":[
        "janitor"
    ],
    "wof:name":"Heavenly Cleaners",
    "wof:placetype":"venue"
},
  "geometry": {"coordinates":[-70.291783,43.671847],"type":"Point"}
}