{
  "type": "Feature",
  "properties": {
    "addr:full":"38 Elm St Waterville ME 04901",
    "addr:housenumber":"38",
    "addr:postcode":"04901",
    "addr:street":"Elm St",
    "iso:country":"US",
    "sg:address":"38 Elm St",
    "sg:city":"Waterville",
    "sg:classifiers":[
        {
            "category":"Building & Trades",
            "subcategory":"Cleaning & Sanitation",
            "type":"Services"
        }
    ],
    "sg:phone":"+1 207 873 5270",
    "sg:postcode":"04901",
    "sg:province":"ME",
    "sg:tags":[
        "maintenance"
    ],
    "wof:name":"Custodial Power",
    "wof:placetype":"venue"
},
  "geometry": {"coordinates":[-69.634371,44.548594],"type":"Point"}
}