{
  "type": "Feature",
  "properties": {
    "iso:country":"US",
    "sg:address":"39 Beach St",
    "sg:city":"Ogunquit",
    "sg:classifiers":[
        {
            "category":"Travel",
            "subcategory":"Hotels & Motels",
            "type":"Entertainment"
        }
    ],
    "sg:phone":"+1 207 646 2632",
    "sg:postcode":"03907",
    "sg:province":"ME",
    "sg:website":"www.theneptuneinn.com",
    "wof:name":"Neptune Inn On The Beach",
    "wof:placetype":"venue"
},
  "geometry": {"coordinates":[-70.596469,43.250203],"type":"Point"}
}