{
  "type": "Feature",
  "properties": {
    "addr:full":"50 Dublin St Machias ME 04654",
    "addr:housenumber":"50",
    "addr:postcode":"04654",
    "addr:street":"Dublin St",
    "iso:country":"US",
    "sg:address":"50 Dublin St",
    "sg:city":"Machias",
    "sg:classifiers":[
        {
            "category":"Building & Trades",
            "subcategory":"Plumbing",
            "type":"Services"
        }
    ],
    "sg:phone":"+1 207 255 8033",
    "sg:postcode":"04654",
    "sg:province":"ME",
    "sg:tags":[
        "plumbing",
        "contractor"
    ],
    "wof:name":"J L Huntley Plumbing & Heating",
    "wof:placetype":"venue"
},
  "geometry": {"coordinates":[-67.460427,44.707813],"type":"Point"}
}