{
  "type": "Feature",
  "properties": {
    "addr:full":"517 Maine Mall South Portland ME 04106",
    "addr:housenumber":"517",
    "addr:postcode":"04106",
    "addr:street":"Maine Mall",
    "iso:country":"US",
    "sg:address":"517 Maine Mall",
    "sg:city":"South Portland",
    "sg:classifiers":[
        {
            "category":"Restaurant",
            "type":"Food & Drink"
        }
    ],
    "sg:menulink":"http://www.allmenus.com/me/south-portland/104381-old-country-buffet/menu/",
    "sg:phone":"+1 207 775 2956",
    "sg:postcode":"04106",
    "sg:province":"ME",
    "sg:tags":[
        "american"
    ],
    "wof:name":"Old Country Buffet",
    "wof:placetype":"venue"
},
  "geometry": {"coordinates":[-70.337237,43.634471],"type":"Point"}
}