{
  "type": "Feature",
  "properties": {
    "addr:full":"400 Hodsdon Rd Pownal ME 04069",
    "addr:housenumber":"400",
    "addr:postcode":"04069",
    "addr:street":"Hodsdon Rd",
    "iso:country":"US",
    "sg:address":"400 Hodsdon Rd",
    "sg:city":"Pownal",
    "sg:classifiers":[
        {
            "category":"Farming",
            "subcategory":"Farm",
            "type":"Manufacturing & Wholesale Goods"
        }
    ],
    "sg:phone":"+1 207 688 4117",
    "sg:postcode":"04069",
    "sg:province":"ME",
    "sg:tags":[
        "crop",
        "general"
    ],
    "wof:name":"Venture Farm LLC",
    "wof:placetype":"venue"
},
  "geometry": {"coordinates":[-70.18206600000001,43.872801],"type":"Point"}
}