{
  "type": "Feature",
  "properties": {
    "iso:country":"US",
    "sg:address":"315 Marginal Way",
    "sg:city":"Portland",
    "sg:classifiers":[
        {
            "category":"Shopping",
            "subcategory":"Bicycles & Sporting Goods",
            "type":"Retail Goods"
        }
    ],
    "sg:phone":"+1 207 773 6063",
    "sg:postcode":"04101",
    "sg:province":"ME",
    "wof:name":"Play It Again Sports",
    "wof:placetype":"venue"
},
  "geometry": {"coordinates":[-70.25827,43.668631],"type":"Point"}
}