{
  "type": "Feature",
  "properties": {
    "iso:country":"US",
    "sg:address":"65 Ridge Rd",
    "sg:city":"Belmont",
    "sg:classifiers":[
        {
            "category":"Building & Trades",
            "subcategory":"Construction",
            "type":"Services"
        }
    ],
    "sg:phone":"+1 207 342 2041",
    "sg:postcode":"04952",
    "sg:province":"ME",
    "sg:tags":[
        "general",
        "contractor"
    ],
    "wof:name":"Elwell Construction",
    "wof:placetype":"venue"
},
  "geometry": {"coordinates":[-69.086339,44.382157],"type":"Point"}
}