{
  "type": "Feature",
  "properties": {
    "iso:country":"US",
    "sg:address":"4 Walter St",
    "sg:city":"Bangor",
    "sg:classifiers":[
        {
            "category":"Restaurant",
            "type":"Food & Drink"
        }
    ],
    "sg:phone":"+1 207 941 8626",
    "sg:postcode":"04401",
    "sg:province":"ME",
    "sg:tags":[
        "pizza"
    ],
    "wof:name":"Spanky's Pizza",
    "wof:placetype":"venue"
},
  "geometry": {"coordinates":[-68.77636699999999,44.792494],"type":"Point"}
}