{
  "type": "Feature",
  "properties": {
    "addr:full":"1465 E Conway Rd North Conway ME 03813",
    "addr:housenumber":"1465",
    "addr:postcode":"03813",
    "addr:street":"E Conway Rd",
    "iso:country":"US",
    "sg:address":"1465 E Conway Rd",
    "sg:city":"North Conway",
    "sg:classifiers":[
        {
            "category":"Food & Beverages",
            "subcategory":"Groceries & Convenience Stores",
            "type":"Retail Goods"
        }
    ],
    "sg:phone":"+1 603 356 5097",
    "sg:postcode":"03813",
    "sg:province":"ME",
    "wof:name":"North Conway Irving Mainway",
    "wof:placetype":"venue"
},
  "geometry": {"coordinates":[-71.059523,44.011292],"type":"Point"}
}