{
  "type": "Feature",
  "properties": {
    "addr:full":"48 Leander Harmon Rd Harrison ME 04040",
    "addr:housenumber":"48",
    "addr:postcode":"04040",
    "addr:street":"Leander Harmon Rd",
    "iso:country":"US",
    "sg:address":"48 Leander Harmon Rd",
    "sg:city":"Harrison",
    "sg:classifiers":[
        {
            "category":"Building & Trades",
            "subcategory":"Plumbing",
            "type":"Services"
        }
    ],
    "sg:phone":"+1 207 583 2204",
    "sg:postcode":"04040",
    "sg:province":"ME",
    "sg:tags":[
        "tank",
        "septic"
    ],
    "wof:name":"Mc Win Inc",
    "wof:placetype":"venue"
},
  "geometry": {"coordinates":[-70.65611699999999,44.094817],"type":"Point"}
}