{
  "type": "Feature",
  "properties": {
    "iso:country":"US",
    "sg:address":"3025 Washington Rd",
    "sg:city":"Waldoboro",
    "sg:classifiers":[
        {
            "category":"Shopping",
            "subcategory":"Used Merchandise",
            "type":"Retail Goods"
        }
    ],
    "sg:phone":"+1 207 832 4404",
    "sg:postcode":"04572",
    "sg:province":"ME",
    "sg:tags":[
        "antique"
    ],
    "wof:name":"Maple Grange Antiques",
    "wof:placetype":"venue"
},
  "geometry": {"coordinates":[-69.375772,44.177878],"type":"Point"}
}