{
  "type": "Feature",
  "properties": {
    "iso:country":"US",
    "sg:address":"206 Main St",
    "sg:city":"Fort Fairfield",
    "sg:classifiers":[
        {
            "category":"Health Services",
            "subcategory":"Doctor",
            "type":"Services"
        }
    ],
    "sg:phone":"+1 207 473 7723",
    "sg:postcode":"04742",
    "sg:province":"ME",
    "sg:tags":[
        "dentist"
    ],
    "wof:name":"Palwinder Kaur-Panefar DDS",
    "wof:placetype":"venue"
},
  "geometry": {"coordinates":[-67.823895,46.769464],"type":"Point"}
}