{
  "type": "Feature",
  "properties": {
    "addr:full":"1 Farwell Ave Cumberland Ctr ME 04021",
    "addr:housenumber":"1",
    "addr:postcode":"04021",
    "addr:street":"Farwell Ave",
    "iso:country":"US",
    "sg:address":"1 Farwell Ave",
    "sg:city":"Cumberland Ctr",
    "sg:classifiers":[
        {
            "category":"Government",
            "subcategory":"Post Office",
            "type":"Public Place"
        }
    ],
    "sg:phone":"+1 207 829 3661",
    "sg:postcode":"04021",
    "sg:province":"ME",
    "wof:name":"US Post Office",
    "wof:placetype":"venue"
},
  "geometry": {"coordinates":[-70.251741,43.799125],"type":"Point"}
}