{
  "type": "Feature",
  "properties": {
    "addr:full":"55 Congress Ave Bath ME 04530",
    "addr:housenumber":"55",
    "addr:postcode":"04530",
    "addr:street":"Congress Ave",
    "iso:country":"US",
    "sg:address":"55 Congress Ave",
    "sg:city":"Bath",
    "sg:classifiers":[
        {
            "category":"Health Services",
            "subcategory":"Health Practitioner",
            "type":"Services"
        }
    ],
    "sg:phone":"+1 207 386 0351",
    "sg:postcode":"04530",
    "sg:province":"ME",
    "sg:tags":[
        "therapist",
        "physical"
    ],
    "wof:name":"Riverview Physical Thrpy Bath",
    "wof:placetype":"venue"
},
  "geometry": {"coordinates":[-69.832843,43.910925],"type":"Point"}
}