{
  "type": "Feature",
  "properties": {
    "iso:country":"US",
    "sg:address":"4 Bradley Rd",
    "sg:city":"Milford",
    "sg:classifiers":[
        {
            "category":"Autos & Motor Vehicles",
            "subcategory":"Automobile Sales",
            "type":"Retail Goods"
        }
    ],
    "sg:phone":"+1 207 827 5304",
    "sg:postcode":"04461",
    "sg:province":"ME",
    "sg:tags":[
        "car",
        "dealer"
    ],
    "wof:name":"Drinkwater's Auto Sales",
    "wof:placetype":"venue"
},
  "geometry": {"coordinates":[-68.640483,44.939031],"type":"Point"}
}