{
  "type": "Feature",
  "properties": {
    "iso:country":"US",
    "sg:address":"39 Wentworth Rd",
    "sg:city":"Berwick",
    "sg:classifiers":[
        {
            "category":"Building & Trades",
            "subcategory":"Cleaning & Sanitation",
            "type":"Services"
        }
    ],
    "sg:phone":"+1 207 698 4694",
    "sg:postcode":"03901",
    "sg:province":"ME",
    "sg:tags":[
        "maintenance"
    ],
    "wof:name":"B P S Power Spraying",
    "wof:placetype":"venue"
},
  "geometry": {"coordinates":[-70.789573,43.286419],"type":"Point"}
}