{
  "type": "Feature",
  "properties": {
    "iso:country":"US",
    "sg:address":"14 Sweden St",
    "sg:city":"Caribou",
    "sg:classifiers":[
        {
            "category":"Shopping",
            "subcategory":"Jewelry",
            "type":"Retail Goods"
        }
    ],
    "sg:phone":"+1 207 498 8778",
    "sg:postcode":"04736",
    "sg:province":"ME",
    "sg:tags":[
        "jeweler"
    ],
    "wof:name":"Freme's Jewelry",
    "wof:placetype":"venue"
},
  "geometry": {"coordinates":[-68.01367,46.860191],"type":"Point"}
}