{
  "type": "Feature",
  "properties": {
    "addr:full":"133 Gray Rd Gorham ME 04038",
    "addr:housenumber":"133",
    "addr:postcode":"04038",
    "addr:street":"Gray Rd",
    "iso:country":"US",
    "sg:address":"133 Gray Rd",
    "sg:city":"Gorham",
    "sg:classifiers":[
        {
            "category":"Retail",
            "subcategory":"Auto Repair",
            "type":"Services"
        }
    ],
    "sg:phone":"+1 207 839 4975",
    "sg:postcode":"04038",
    "sg:province":"ME",
    "sg:tags":[
        "body",
        "automobile",
        "painting"
    ],
    "wof:name":"Phillips & Sons Body Shop",
    "wof:placetype":"venue"
},
  "geometry": {"coordinates":[-70.42976,43.693957],"type":"Point"}
}