{
  "type": "Feature",
  "properties": {
    "addr:full":"537 Congress St Portland ME 04101",
    "addr:housenumber":"537",
    "addr:postcode":"04101",
    "addr:street":"Congress St",
    "iso:country":"US",
    "sg:address":"537 Congress St",
    "sg:city":"Portland",
    "sg:classifiers":[
        {
            "category":"Shopping",
            "subcategory":"Hobbies, Toys, & Games",
            "type":"Retail Goods"
        }
    ],
    "sg:phone":"+1 207 828 8213",
    "sg:postcode":"04101",
    "sg:province":"ME",
    "sg:tags":[
        "craft"
    ],
    "wof:name":"Client Craft Inc",
    "wof:placetype":"venue"
},
  "geometry": {"coordinates":[-70.261561,43.655745],"type":"Point"}
}