{
  "type": "Feature",
  "properties": {
    "iso:country":"US",
    "sg:address":"170 Anderson St",
    "sg:city":"Portland",
    "sg:classifiers":[
        {
            "category":"Organizations",
            "subcategory":"Non-profit Organization",
            "type":"Services"
        }
    ],
    "sg:phone":"+1 207 774 0682",
    "sg:postcode":"04101",
    "sg:province":"ME",
    "wof:name":"Compass Project",
    "wof:placetype":"venue"
},
  "geometry": {"coordinates":[-70.25584,43.668465],"type":"Point"}
}