{
  "type": "Feature",
  "properties": {
    "addr:full":"936 Roosevelt Trl Windham ME 04062",
    "addr:housenumber":"936",
    "addr:postcode":"04062",
    "addr:street":"Roosevelt Trl",
    "iso:country":"US",
    "sg:address":"936 Roosevelt Trl",
    "sg:city":"Windham",
    "sg:classifiers":[
        {
            "category":"Health Services",
            "subcategory":"Chiropractor",
            "type":"Services"
        }
    ],
    "sg:phone":"+1 207 892 8356",
    "sg:postcode":"04062",
    "sg:province":"ME",
    "wof:name":"Moore Chiropractic Ctr",
    "wof:placetype":"venue"
},
  "geometry": {"coordinates":[-70.450445,43.85105],"type":"Point"}
}