{
  "type": "Feature",
  "properties": {
    "iso:country":"US",
    "sg:address":"124 Maine St",
    "sg:city":"Brunswick",
    "sg:classifiers":[
        {
            "category":"Social Services",
            "type":"Services"
        }
    ],
    "sg:phone":"+1 207 729 1305",
    "sg:postcode":"04011",
    "sg:province":"ME",
    "sg:tags":[
        "worker"
    ],
    "wof:name":"Judy Maloney Lcsw",
    "wof:placetype":"venue"
},
  "geometry": {"coordinates":[-69.965354,43.915332],"type":"Point"}
}