{
  "type": "Feature",
  "properties": {
    "iso:country":"US",
    "sg:address":"32 Valley Rd",
    "sg:city":"Bath",
    "sg:classifiers":[
        {
            "category":"Building & Trades",
            "subcategory":"Landscaping Services",
            "type":"Services"
        }
    ],
    "sg:phone":"+1 207 442 7839",
    "sg:postcode":"04530",
    "sg:province":"ME",
    "sg:tags":[
        "landscape"
    ],
    "wof:name":"Just US",
    "wof:placetype":"venue"
},
  "geometry": {"coordinates":[-69.817967,43.926906],"type":"Point"}
}