{
  "type": "Feature",
  "properties": {
    "iso:country":"US",
    "sg:address":"24 Sweden St",
    "sg:city":"Caribou",
    "sg:classifiers":[
        {
            "category":"Government",
            "subcategory":"Office",
            "type":"Public Place"
        }
    ],
    "sg:phone":"+1 207 493 4233",
    "sg:postcode":"04736",
    "sg:province":"ME",
    "sg:tags":[
        "city",
        "program",
        "adm"
    ],
    "wof:name":"Caribou Development Corp",
    "wof:placetype":"venue"
},
  "geometry": {"coordinates":[-68.013778,46.860177],"type":"Point"}
}