{
  "type": "Feature",
  "properties": {
    "addr:full":"13 Church St Wallagrass ME 04758",
    "addr:housenumber":"13",
    "addr:postcode":"04758",
    "addr:street":"Church St",
    "iso:country":"US",
    "sg:address":"13 Church St",
    "sg:city":"Wallagrass",
    "sg:classifiers":[
        {
            "category":"Building & Trades",
            "subcategory":"Construction",
            "type":"Services"
        }
    ],
    "sg:phone":"+1 207 834 2600",
    "sg:postcode":"04758",
    "sg:province":"ME",
    "sg:tags":[
        "general",
        "contractor"
    ],
    "wof:name":"Eagle Construction",
    "wof:placetype":"venue"
},
  "geometry": {"coordinates":[-67.863355,46.518695],"type":"Point"}
}