{
  "type": "Feature",
  "properties": {
    "addr:full":"43 Baxter Blvd Portland ME 04101",
    "addr:housenumber":"43",
    "addr:postcode":"04101",
    "addr:street":"Baxter Blvd",
    "iso:country":"US",
    "sg:address":"43 Baxter Blvd",
    "sg:city":"Portland",
    "sg:classifiers":[
        {
            "category":"Health Services",
            "subcategory":"Doctor",
            "type":"Services"
        }
    ],
    "sg:phone":"+1 207 775 6381",
    "sg:postcode":"04101",
    "sg:province":"ME",
    "sg:tags":[
        "physician",
        "surgeon"
    ],
    "sg:website":"www.mkkent.com",
    "wof:name":"Maxwell Kluger & Makaretz-Ent",
    "wof:placetype":"venue"
},
  "geometry": {"coordinates":[-70.271902,43.663525],"type":"Point"}
}