{
  "type": "Feature",
  "properties": {
    "addr:full":"569 Skyway St Presque Isle ME 04769",
    "addr:housenumber":"569",
    "addr:postcode":"04769",
    "addr:street":"Skyway St;Isle",
    "iso:country":"US",
    "sg:address":"569 Skyway St",
    "sg:city":"Presque Isle",
    "sg:classifiers":[
        {
            "category":"Education",
            "subcategory":"School",
            "type":"Public Place"
        }
    ],
    "sg:phone":"+1 207 764 4474",
    "sg:postcode":"04769",
    "sg:province":"ME",
    "wof:name":"Skyway Middle School",
    "wof:placetype":"venue"
},
  "geometry": {"coordinates":[-68.035247,46.699375],"type":"Point"}
}