{
  "type": "Feature",
  "properties": {
    "addr:full":"17 Cole Field Rd Cape Elizabeth ME 04107",
    "addr:housenumber":"17",
    "addr:postcode":"04107",
    "addr:street":"Cole Field Rd",
    "iso:country":"US",
    "sg:address":"17 Cole Field Rd",
    "sg:city":"Cape Elizabeth",
    "sg:classifiers":[
        {
            "category":"Health Services",
            "subcategory":"Doctor",
            "type":"Services"
        }
    ],
    "sg:phone":"+1 207 767 1042",
    "sg:postcode":"04107",
    "sg:province":"ME",
    "sg:tags":[
        "physician",
        "surgeon"
    ],
    "wof:name":"Bard Group",
    "wof:placetype":"venue"
},
  "geometry": {"coordinates":[-70.268337,43.599193],"type":"Point"}
}