{
  "type": "Feature",
  "properties": {
    "iso:country":"US",
    "sg:address":"254 N Buckfield Rd",
    "sg:city":"Buckfield",
    "sg:classifiers":[
        {
            "category":"Professional",
            "subcategory":"Management & Consulting",
            "type":"Services"
        }
    ],
    "sg:phone":"+1 207 740 3805",
    "sg:postcode":"04220",
    "sg:province":"ME",
    "sg:tags":[
        "training",
        "safety"
    ],
    "wof:name":"Steven Campbell Jr",
    "wof:placetype":"venue"
},
  "geometry": {"coordinates":[-70.38858999999999,44.298929],"type":"Point"}
}