{
  "type": "Feature",
  "properties": {
    "addr:full":"159 Cash St South Portland ME 04106",
    "addr:housenumber":"159",
    "addr:postcode":"04106",
    "addr:street":"Cash St",
    "iso:country":"US",
    "sg:address":"159 Cash St",
    "sg:city":"South Portland",
    "sg:classifiers":[
        {
            "category":"Wholesale",
            "subcategory":"Auto Parts",
            "type":"Manufacturing & Wholesale Goods"
        }
    ],
    "sg:phone":"+1 207 767 7431",
    "sg:postcode":"04106",
    "sg:province":"ME",
    "sg:tags":[
        "equipment",
        "truck"
    ],
    "wof:name":"Brake Service & Parts",
    "wof:placetype":"venue"
},
  "geometry": {"coordinates":[-70.289424,43.625288],"type":"Point"}
}