{
  "type": "Feature",
  "properties": {
    "iso:country":"US",
    "sg:address":"108 New Hampshire St",
    "sg:city":"Millinocket",
    "sg:classifiers":[
        {
            "category":"Home & Garden",
            "subcategory":"Furniture",
            "type":"Retail Goods"
        }
    ],
    "sg:phone":"+1 207 723 6838",
    "sg:postcode":"04462",
    "sg:province":"ME",
    "wof:name":"Wild Flower Gazebos Inc",
    "wof:placetype":"venue"
},
  "geometry": {"coordinates":[-68.692666,45.666706],"type":"Point"}
}