{
  "type": "Feature",
  "properties": {
    "addr:full":"2 Waterboro Rd Alfred ME 04002",
    "addr:housenumber":"2",
    "addr:postcode":"04002",
    "addr:street":"Waterboro Rd",
    "iso:country":"US",
    "sg:address":"2 Waterboro Rd",
    "sg:city":"Alfred",
    "sg:classifiers":[
        {
            "category":"Shopping",
            "subcategory":"Used Merchandise",
            "type":"Retail Goods"
        }
    ],
    "sg:phone":"+1 207 490 5572",
    "sg:postcode":"04002",
    "sg:province":"ME",
    "sg:tags":[
        "book",
        "rare",
        "dealer"
    ],
    "sg:website":"www.dwbooks.com",
    "wof:name":"De Wolfe & Wood",
    "wof:placetype":"venue"
},
  "geometry": {"coordinates":[-70.71767699999999,43.481183],"type":"Point"}
}