{
  "type": "Feature",
  "properties": {
    "iso:country":"US",
    "sg:address":"11 Spring St",
    "sg:city":"Lisbon",
    "sg:classifiers":[
        {
            "category":"Arts & Performance",
            "subcategory":"Theater",
            "type":"Entertainment"
        }
    ],
    "sg:phone":"+1 207 353 2205",
    "sg:postcode":"04250",
    "sg:province":"ME",
    "sg:tags":[
        "group"
    ],
    "wof:name":"B & D Music Services",
    "wof:placetype":"venue"
},
  "geometry": {"coordinates":[-70.105927,44.031079],"type":"Point"}
}