{
  "type": "Feature",
  "properties": {
    "iso:country":"US",
    "sg:address":"744 Stillwater Ave",
    "sg:city":"Old Town",
    "sg:classifiers":[
        {
            "category":"Organizations",
            "subcategory":"Religious Organization",
            "type":"Services"
        }
    ],
    "sg:phone":"+1 207 827 3559",
    "sg:postcode":"04468",
    "sg:province":"ME",
    "sg:tags":[
        "church"
    ],
    "wof:name":"United Methodist Church",
    "wof:placetype":"venue"
},
  "geometry": {"coordinates":[-68.677809,44.919541],"type":"Point"}
}