{
  "type": "Feature",
  "properties": {
    "iso:country":"US",
    "sg:address":"24 School Rd",
    "sg:city":"Windham",
    "sg:classifiers":[
        {
            "category":"Retail",
            "subcategory":"Auto Repair",
            "type":"Services"
        }
    ],
    "sg:phone":"+1 207 894 7878",
    "sg:postcode":"04062",
    "sg:province":"ME",
    "sg:tags":[
        "transmission"
    ],
    "wof:name":"John Stiles Transmission",
    "wof:placetype":"venue"
},
  "geometry": {"coordinates":[-70.408995,43.792724],"type":"Point"}
}