{
  "type": "Feature",
  "properties": {
    "addr:full":"72 North Rd Detroit ME 04929",
    "addr:housenumber":"72",
    "addr:postcode":"04929",
    "addr:street":"North Rd",
    "iso:country":"US",
    "sg:address":"72 North Rd",
    "sg:city":"Detroit",
    "sg:classifiers":[
        {
            "category":"Health Services",
            "subcategory":"Doctor",
            "type":"Services"
        }
    ],
    "sg:phone":"+1 207 487 0981",
    "sg:postcode":"04929",
    "sg:province":"ME",
    "sg:tags":[
        "physician",
        "surgeon"
    ],
    "wof:name":"Sebasticook Family Doctors",
    "wof:placetype":"venue"
},
  "geometry": {"coordinates":[-69.336219,44.794838],"type":"Point"}
}