{
  "type": "Feature",
  "properties": {
    "iso:country":"US",
    "sg:address":"242 State St",
    "sg:city":"Bangor",
    "sg:classifiers":[
        {
            "category":"Shopping",
            "subcategory":"Computers & Home Electronics",
            "type":"Retail Goods"
        }
    ],
    "sg:phone":"+1 207 941 0264",
    "sg:postcode":"04401",
    "sg:province":"ME",
    "sg:tags":[
        "equipment",
        "dealer"
    ],
    "sg:website":"www.sjrollins.com",
    "wof:name":"S J Rollins Technologies",
    "wof:placetype":"venue"
},
  "geometry": {"coordinates":[-68.760716,44.80574],"type":"Point"}
}