{
  "type": "Feature",
  "properties": {
    "addr:full":"4 Old Orchard St Old Orchard Bch ME 04064",
    "addr:housenumber":"4",
    "addr:postcode":"04064",
    "addr:street":"Old Orchard St",
    "iso:country":"US",
    "sg:address":"4 Old Orchard St",
    "sg:city":"Old Orchard Bch",
    "sg:classifiers":[
        {
            "category":"Restaurant",
            "type":"Food & Drink"
        }
    ],
    "sg:phone":"+1 207 934 3100",
    "sg:postcode":"04064",
    "sg:province":"ME",
    "wof:name":"Park Fries",
    "wof:placetype":"venue"
},
  "geometry": {"coordinates":[-70.377353,43.51747],"type":"Point"}
}