{
  "type": "Feature",
  "properties": {
    "iso:country":"US",
    "sg:address":"83 Market St",
    "sg:city":"Portland",
    "sg:classifiers":[
        {
            "category":"Personal",
            "subcategory":"Beauty Salon",
            "type":"Services"
        }
    ],
    "sg:phone":"+1 207 828 2939",
    "sg:postcode":"04101",
    "sg:province":"ME",
    "sg:tags":[
        "shop",
        "manicuring"
    ],
    "wof:name":"Personal Touch Nail Skin Care",
    "wof:placetype":"venue"
},
  "geometry": {"coordinates":[-70.254656,43.658198],"type":"Point"}
}