{
  "type": "Feature",
  "properties": {
    "iso:country":"US",
    "sg:address":"110 Front St",
    "sg:city":"Bath",
    "sg:classifiers":[
        {
            "category":"Real Estate",
            "subcategory":"Real Estate Agent",
            "type":"Services"
        }
    ],
    "sg:phone":"+1 207 443 9516",
    "sg:postcode":"04530",
    "sg:province":"ME",
    "sg:tags":[
        "cooperative"
    ],
    "wof:name":"Front Street Co Op",
    "wof:placetype":"venue"
},
  "geometry": {"coordinates":[-69.814296,43.913617],"type":"Point"}
}