{
  "type": "Feature",
  "properties": {
    "iso:country":"US",
    "sg:address":"47 Cedar St",
    "sg:city":"East Millinocket",
    "sg:classifiers":[
        {
            "category":"Building & Trades",
            "subcategory":"Construction",
            "type":"Services"
        }
    ],
    "sg:phone":"+1 207 746 5670",
    "sg:postcode":"04430",
    "sg:province":"ME",
    "sg:tags":[
        "home",
        "improvement"
    ],
    "wof:name":"Lovely Home Improvement",
    "wof:placetype":"venue"
},
  "geometry": {"coordinates":[-68.575148,45.631886],"type":"Point"}
}