{
  "type": "Feature",
  "properties": {
    "addr:full":"271 Waldoboro Rd Jefferson ME 04348",
    "addr:housenumber":"271",
    "addr:postcode":"04348",
    "addr:street":"Waldoboro Rd",
    "iso:country":"US",
    "sg:address":"271 Waldoboro Rd",
    "sg:city":"Jefferson",
    "sg:classifiers":[
        {
            "category":"Social Services",
            "subcategory":"Child Care",
            "type":"Services"
        }
    ],
    "sg:phone":"+1 207 549 3923",
    "sg:postcode":"04348",
    "sg:province":"ME",
    "wof:name":"YMCA Childcare Ctr",
    "wof:placetype":"venue"
},
  "geometry": {"coordinates":[-69.452195,44.198959],"type":"Point"}
}