{
  "type": "Feature",
  "properties": {
    "addr:full":"338 Broadway Rockland ME 04841",
    "addr:housenumber":"338",
    "addr:postcode":"04841",
    "addr:street":"Broadway",
    "iso:country":"US",
    "sg:address":"338 Broadway",
    "sg:city":"Rockland",
    "sg:classifiers":[
        {
            "category":"Education",
            "subcategory":"School",
            "type":"Public Place"
        }
    ],
    "sg:phone":"+1 207 596 2005",
    "sg:postcode":"04841",
    "sg:province":"ME",
    "wof:name":"Mac Dougal School",
    "wof:placetype":"venue"
},
  "geometry": {"coordinates":[-69.114814,44.112331],"type":"Point"}
}