{
  "type": "Feature",
  "properties": {
    "iso:country":"US",
    "sg:address":"25 W Main St",
    "sg:city":"Milo",
    "sg:classifiers":[
        {
            "category":"Retail",
            "subcategory":"Repair Shop",
            "type":"Services"
        }
    ],
    "sg:phone":"+1 207 943 7323",
    "sg:postcode":"04463",
    "sg:province":"ME",
    "sg:tags":[
        "repairing",
        "saw"
    ],
    "wof:name":"Patient Valley Saw Techs",
    "wof:placetype":"venue"
},
  "geometry": {"coordinates":[-68.990906,45.250121],"type":"Point"}
}