{
  "type": "Feature",
  "properties": {
    "iso:country":"US",
    "sg:address":"85 Exchange St",
    "sg:city":"Portland",
    "sg:classifiers":[
        {
            "category":"Professional",
            "subcategory":"Lawyer & Legal Services",
            "type":"Services"
        }
    ],
    "sg:phone":"+1 207 775 3101",
    "sg:postcode":"04101",
    "sg:province":"ME",
    "sg:tags":[
        "attorney"
    ],
    "wof:name":"Jonathon L Goldberg",
    "wof:placetype":"venue"
},
  "geometry": {"coordinates":[-70.254935,43.657911],"type":"Point"}
}