{
  "type": "Feature",
  "properties": {
    "addr:full":"82 Sweden St Caribou ME 04736",
    "addr:housenumber":"82",
    "addr:postcode":"04736",
    "addr:street":"Sweden St",
    "iso:country":"US",
    "sg:address":"82 Sweden St",
    "sg:city":"Caribou",
    "sg:classifiers":[
        {
            "category":"Travel",
            "subcategory":"Travel Agent",
            "type":"Entertainment"
        }
    ],
    "sg:phone":"+1 207 498 8171",
    "sg:postcode":"04736",
    "sg:province":"ME",
    "sg:tags":[
        "agency",
        "bureau"
    ],
    "wof:name":"American International Travel",
    "wof:placetype":"venue"
},
  "geometry": {"coordinates":[-68.01601700000001,46.860044],"type":"Point"}
}