{
  "type": "Feature",
  "properties": {
    "addr:full":"938 Forest Ave Portland ME 04103",
    "addr:housenumber":"938",
    "addr:postcode":"04103",
    "addr:street":"Forest Ave",
    "iso:country":"US",
    "sg:address":"938 Forest Ave",
    "sg:city":"Portland",
    "sg:classifiers":[
        {
            "category":"Professional",
            "subcategory":"Management & Consulting",
            "type":"Services"
        }
    ],
    "sg:phone":"+1 207 797 3771",
    "sg:postcode":"04103",
    "sg:province":"ME",
    "wof:name":"Ruth Matt Cfp",
    "wof:placetype":"venue"
},
  "geometry": {"coordinates":[-70.288785,43.679019],"type":"Point"}
}