{
  "type": "Feature",
  "properties": {
    "addr:full":"2270 Post Rd Wells ME 04090",
    "addr:housenumber":"2270",
    "addr:postcode":"04090",
    "addr:street":"Post Rd",
    "iso:country":"US",
    "sg:address":"2270 Post Rd",
    "sg:city":"Wells",
    "sg:classifiers":[
        {
            "category":"Restaurant",
            "type":"Food & Drink"
        }
    ],
    "sg:menulink":"http://www.allmenus.com/me/wells/236807-bull-and-claw/menu/",
    "sg:phone":"+1 207 646 8467",
    "sg:postcode":"04090",
    "sg:province":"ME",
    "sg:tags":[
        "american"
    ],
    "wof:name":"Bull and Claw",
    "wof:placetype":"venue"
},
  "geometry": {"coordinates":[-70.563425,43.342068],"type":"Point"}
}