{
  "type": "Feature",
  "properties": {
    "addr:full":"240 Main St Winter Harbor ME 04693",
    "addr:housenumber":"240",
    "addr:postcode":"04693",
    "addr:street":"Main St",
    "iso:country":"US",
    "sg:address":"240 Main St",
    "sg:city":"Winter Harbor",
    "sg:classifiers":[
        {
            "category":"Retail",
            "subcategory":"Auto Repair",
            "type":"Services"
        }
    ],
    "sg:phone":"+1 207 963 7329",
    "sg:postcode":"04693",
    "sg:province":"ME",
    "sg:tags":[
        "general"
    ],
    "wof:name":"Winter Harbor Garage",
    "wof:placetype":"venue"
},
  "geometry": {"coordinates":[-68.083231,44.395112],"type":"Point"}
}