{
  "type": "Feature",
  "properties": {
    "iso:country":"US",
    "sg:address":"4 Wingate Ct",
    "sg:city":"Bangor",
    "sg:classifiers":[
        {
            "category":"Real Estate",
            "subcategory":"Real Estate Agent",
            "type":"Services"
        }
    ],
    "sg:phone":"+1 207 942 3514",
    "sg:postcode":"04401",
    "sg:province":"ME",
    "sg:tags":[
        "inspection"
    ],
    "wof:name":"Harrisons Home Inspections",
    "wof:placetype":"venue"
},
  "geometry": {"coordinates":[-68.759398,44.806778],"type":"Point"}
}