{
  "type": "Feature",
  "properties": {
    "addr:full":"188 Keller Pt Rd Islesboro ME 04848",
    "addr:housenumber":"188",
    "addr:postcode":"04848",
    "addr:street":"Keller Pt Rd",
    "iso:country":"US",
    "sg:address":"188 Keller Pt Rd",
    "sg:city":"Islesboro",
    "sg:classifiers":[
        {
            "category":"Wholesale",
            "subcategory":"Machinery & Supplies",
            "type":"Manufacturing & Wholesale Goods"
        }
    ],
    "sg:phone":"+1 207 734 6961",
    "sg:postcode":"04848",
    "sg:province":"ME",
    "sg:tags":[
        "equipment"
    ],
    "wof:name":"Sunsite Design",
    "wof:placetype":"venue"
},
  "geometry": {"coordinates":[-68.901428,44.332062],"type":"Point"}
}