{
  "type": "Feature",
  "properties": {
    "iso:country":"US",
    "sg:address":"148 Middle St",
    "sg:city":"Portland",
    "sg:classifiers":[
        {
            "category":"Restaurant",
            "type":"Food & Drink"
        }
    ],
    "sg:phone":"+1 207 772 0075",
    "sg:postcode":"04101",
    "sg:province":"ME",
    "sg:tags":[
        "eating"
    ],
    "wof:name":"TGI Fridays",
    "wof:placetype":"venue"
},
  "geometry": {"coordinates":[-70.253607,43.658202],"type":"Point"}
}