{
  "type": "Feature",
  "properties": {
    "addr:full":"105 Ocean St South Portland ME 04106",
    "addr:housenumber":"105",
    "addr:postcode":"04106",
    "addr:street":"Ocean St",
    "iso:country":"US",
    "sg:address":"105 Ocean St",
    "sg:city":"South Portland",
    "sg:classifiers":[
        {
            "category":"Home & Garden",
            "subcategory":"Building Materials",
            "type":"Retail Goods"
        }
    ],
    "sg:phone":"+1 207 799 9159",
    "sg:postcode":"04106",
    "sg:province":"ME",
    "sg:tags":[
        "equipment",
        "fixture",
        "lighting"
    ],
    "wof:name":"Polishing Shop the",
    "wof:placetype":"venue"
},
  "geometry": {"coordinates":[-70.253047,43.63841],"type":"Point"}
}