{
  "type": "Feature",
  "properties": {
    "addr:full":"115 State St Bangor ME 04401",
    "addr:housenumber":"115",
    "addr:postcode":"04401",
    "addr:street":"State St",
    "iso:country":"US",
    "sg:address":"115 State St",
    "sg:city":"Bangor",
    "sg:classifiers":[
        {
            "category":"Bars & Pubs",
            "type":"Food & Drink"
        }
    ],
    "sg:phone":"+1 207 947 3972",
    "sg:postcode":"04401",
    "sg:province":"ME",
    "wof:name":"Pat's Tavern Inc",
    "wof:placetype":"venue"
},
  "geometry": {"coordinates":[-68.766102,44.803587],"type":"Point"}
}