{
  "type": "Feature",
  "properties": {
    "addr:full":"192 W Limestone Rd Fort Fairfield ME 04742",
    "addr:housenumber":"192",
    "addr:postcode":"04742",
    "addr:street":"W Limestone Rd",
    "iso:country":"US",
    "sg:address":"192 W Limestone Rd",
    "sg:city":"Fort Fairfield",
    "sg:classifiers":[
        {
            "category":"Retail",
            "subcategory":"Auto Repair",
            "type":"Services"
        }
    ],
    "sg:phone":"+1 207 473 7557",
    "sg:postcode":"04742",
    "sg:province":"ME",
    "sg:tags":[
        "repairing",
        "automobile"
    ],
    "wof:name":"Mc Laughlin's Auto Repair",
    "wof:placetype":"venue"
},
  "geometry": {"coordinates":[-67.83647999999999,46.795699],"type":"Point"}
}