{
  "type": "Feature",
  "properties": {
    "addr:full":"537 Congress St Portland ME 04101",
    "addr:housenumber":"537",
    "addr:postcode":"04101",
    "addr:street":"Congress St",
    "iso:country":"US",
    "sg:address":"537 Congress St",
    "sg:city":"Portland",
    "sg:classifiers":[
        {
            "category":"Organizations",
            "subcategory":"Non-profit Organization",
            "type":"Services"
        }
    ],
    "sg:phone":"+1 207 553 2095",
    "sg:postcode":"04101",
    "sg:province":"ME",
    "wof:name":"Common Good Ventures",
    "wof:placetype":"venue"
},
  "geometry": {"coordinates":[-70.261561,43.655745],"type":"Point"}
}