{
  "type": "Feature",
  "properties": {
    "addr:full":"98 Waldo Ave Belfast ME 04915",
    "addr:housenumber":"98",
    "addr:postcode":"04915",
    "addr:street":"Waldo Ave",
    "iso:country":"US",
    "sg:address":"98 Waldo Ave",
    "sg:city":"Belfast",
    "sg:classifiers":[
        {
            "category":"Education",
            "subcategory":"School",
            "type":"Public Place"
        }
    ],
    "sg:phone":"+1 207 338 1790",
    "sg:postcode":"04915",
    "sg:province":"ME",
    "wof:name":"Belfast Area High School",
    "wof:placetype":"venue"
},
  "geometry": {"coordinates":[-69.018029,44.431332],"type":"Point"}
}