{
  "type": "Feature",
  "properties": {
    "iso:country":"US",
    "sg:address":"34 Turner St",
    "sg:city":"Buckfield",
    "sg:classifiers":[
        {
            "category":"Government",
            "subcategory":"Office",
            "type":"Public Place"
        }
    ],
    "sg:phone":"+1 207 336 2521",
    "sg:postcode":"04220",
    "sg:province":"ME",
    "sg:tags":[
        "village"
    ],
    "wof:name":"Buckfield Selectmens Office",
    "wof:placetype":"venue"
},
  "geometry": {"coordinates":[-70.36265299999999,44.288577],"type":"Point"}
}