{
  "type": "Feature",
  "properties": {
    "iso:country":"US",
    "sg:address":"204 New Sweden Rd",
    "sg:city":"New Sweden",
    "sg:classifiers":[
        {
            "category":"Shopping",
            "subcategory":"Discount & Variety Stores",
            "type":"Retail Goods"
        }
    ],
    "sg:phone":"+1 207 896 3239",
    "sg:postcode":"04762",
    "sg:province":"ME",
    "wof:name":"Northstar Variety",
    "wof:placetype":"venue"
},
  "geometry": {"coordinates":[-68.11984099999999,46.930214],"type":"Point"}
}