{
  "type": "Feature",
  "properties": {
    "addr:full":"100 Ridgewood Dr Bangor ME 04401",
    "addr:housenumber":"100",
    "addr:postcode":"04401",
    "addr:street":"Ridgewood Dr",
    "iso:country":"US",
    "sg:address":"100 Ridgewood Dr",
    "sg:city":"Bangor",
    "sg:classifiers":[
        {
            "category":"Social Services",
            "type":"Services"
        }
    ],
    "sg:phone":"+1 207 942 7211",
    "sg:postcode":"04401",
    "sg:province":"ME",
    "sg:tags":[
        "agency",
        "adoption"
    ],
    "wof:name":"Good Samaritan Agency",
    "wof:placetype":"venue"
},
  "geometry": {"coordinates":[-68.74142399999999,44.845024],"type":"Point"}
}