{
  "type": "Feature",
  "properties": {
    "addr:full":"1008 W Main St Dover Foxcroft ME 04426",
    "addr:housenumber":"1008",
    "addr:postcode":"04426",
    "addr:street":"W Main St",
    "iso:country":"US",
    "sg:address":"1008 W Main St",
    "sg:city":"Dover Foxcroft",
    "sg:classifiers":[
        {
            "category":"Restaurant",
            "type":"Food & Drink"
        }
    ],
    "sg:menulink":"http://www.allmenus.com/me/dover-foxcroft/119800-subway/menu/",
    "sg:phone":"+1 207 564 0088",
    "sg:postcode":"04426",
    "sg:province":"ME",
    "sg:tags":[
        "american",
        "sandwich"
    ],
    "wof:name":"Subway",
    "wof:placetype":"venue"
},
  "geometry": {"coordinates":[-69.258056,45.18152],"type":"Point"}
}