{
  "type": "Feature",
  "properties": {
    "addr:full":"1544 Portland Rd Arundel ME 04046",
    "addr:housenumber":"1544",
    "addr:postcode":"04046",
    "addr:street":"Portland Rd",
    "iso:country":"US",
    "sg:address":"1544 Portland Rd",
    "sg:city":"Arundel",
    "sg:classifiers":[
        {
            "category":"Retail",
            "subcategory":"Auto Repair",
            "type":"Services"
        }
    ],
    "sg:phone":"+1 207 985 6125",
    "sg:postcode":"04046",
    "sg:province":"ME",
    "sg:tags":[
        "repairing",
        "automobile"
    ],
    "wof:name":"Garage Inc",
    "wof:placetype":"venue"
},
  "geometry": {"coordinates":[-70.522948,43.407678],"type":"Point"}
}