{
  "type": "Feature",
  "properties": {
    "addr:full":"816 Atlantic Hwy Waldoboro ME 04572",
    "addr:housenumber":"816",
    "addr:postcode":"04572",
    "addr:street":"Atlantic Hwy",
    "iso:country":"US",
    "sg:address":"816 Atlantic Hwy",
    "sg:city":"Waldoboro",
    "sg:classifiers":[
        {
            "category":"Restaurant",
            "type":"Food & Drink"
        }
    ],
    "sg:phone":"+1 207 832 5555",
    "sg:postcode":"04572",
    "sg:province":"ME",
    "wof:name":"Chinese Jade Restaurant",
    "wof:placetype":"venue"
},
  "geometry": {"coordinates":[-69.411624,44.098804],"type":"Point"}
}