{
  "type": "Feature",
  "properties": {
    "iso:country":"US",
    "sg:address":"35 Water St",
    "sg:city":"Eastport",
    "sg:classifiers":[
        {
            "category":"Restaurant",
            "type":"Food & Drink"
        }
    ],
    "sg:phone":"+1 207 853 9400",
    "sg:postcode":"04631",
    "sg:province":"ME",
    "wof:name":"Happy Crab",
    "wof:placetype":"venue"
},
  "geometry": {"coordinates":[-66.985013,44.903383],"type":"Point"}
}