{
  "type": "Feature",
  "properties": {
    "iso:country":"US",
    "sg:address":"245 Commercial St",
    "sg:city":"Portland",
    "sg:classifiers":[
        {
            "category":"Professional",
            "subcategory":"Employment Agencies",
            "type":"Services"
        }
    ],
    "sg:phone":"+1 207 772 2882",
    "sg:postcode":"04101",
    "sg:province":"ME",
    "sg:tags":[
        "opportunity"
    ],
    "wof:name":"Adecco",
    "wof:placetype":"venue"
},
  "geometry": {"coordinates":[-70.25476,43.654721],"type":"Point"}
}