{
  "type": "Feature",
  "properties": {
    "iso:country":"US",
    "sg:address":"195 Main St",
    "sg:city":"Calais",
    "sg:classifiers":[
        {
            "category":"Restaurant",
            "type":"Food & Drink"
        }
    ],
    "sg:phone":"+1 207 454 8400",
    "sg:postcode":"04619",
    "sg:province":"ME",
    "wof:name":"Carmen's Hometown Pizzeria Inc",
    "wof:placetype":"venue"
},
  "geometry": {"coordinates":[-67.276067,45.188757],"type":"Point"}
}