{
  "type": "Feature",
  "properties": {
    "addr:full":"350 Water St Waterville ME 04901",
    "addr:housenumber":"350",
    "addr:postcode":"04901",
    "addr:street":"Water St",
    "iso:country":"US",
    "sg:address":"350 Water St",
    "sg:city":"Waterville",
    "sg:classifiers":[
        {
            "category":"Building & Trades",
            "subcategory":"Construction",
            "type":"Services"
        }
    ],
    "sg:phone":"+1 207 873 3870",
    "sg:postcode":"04901",
    "sg:province":"ME",
    "sg:tags":[
        "hanging",
        "painter",
        "contractor"
    ],
    "wof:name":"Kelly's Painting",
    "wof:placetype":"venue"
},
  "geometry": {"coordinates":[-69.65351200000001,44.527245],"type":"Point"}
}