{
  "type": "Feature",
  "properties": {
    "iso:country":"US",
    "sg:address":"209 Eddy Rd",
    "sg:city":"Edgecomb",
    "sg:classifiers":[
        {
            "category":"Shopping",
            "subcategory":"Used Merchandise",
            "type":"Retail Goods"
        }
    ],
    "sg:phone":"+1 207 882 5595",
    "sg:postcode":"04556",
    "sg:province":"ME",
    "sg:tags":[
        "antique"
    ],
    "wof:name":"Anchorage Tools",
    "wof:placetype":"venue"
},
  "geometry": {"coordinates":[-69.65119,43.996527],"type":"Point"}
}