{
  "type": "Feature",
  "properties": {
    "addr:full":"187 Spring St Gardiner ME 04345",
    "addr:housenumber":"187",
    "addr:postcode":"04345",
    "addr:street":"Spring St",
    "iso:country":"US",
    "sg:address":"187 Spring St",
    "sg:city":"Gardiner",
    "sg:classifiers":[
        {
            "category":"Building & Trades",
            "subcategory":"Electrical",
            "type":"Services"
        }
    ],
    "sg:phone":"+1 207 582 7964",
    "sg:postcode":"04345",
    "sg:province":"ME",
    "sg:tags":[
        "electric",
        "contractor"
    ],
    "wof:name":"Don Mc Farland Electrical Svc",
    "wof:placetype":"venue"
},
  "geometry": {"coordinates":[-69.783126,44.235446],"type":"Point"}
}