{
  "type": "Feature",
  "properties": {
    "addr:full":"358 Emerson Mill Rd Hampden ME 04444",
    "addr:housenumber":"358",
    "addr:postcode":"04444",
    "addr:street":"Emerson Mill Rd",
    "iso:country":"US",
    "sg:address":"358 Emerson Mill Rd",
    "sg:city":"Hampden",
    "sg:classifiers":[
        {
            "category":"Organizations",
            "subcategory":"Community Association",
            "type":"Services"
        }
    ],
    "sg:phone":"+1 207 862 4200",
    "sg:postcode":"04444",
    "sg:province":"ME",
    "sg:tags":[
        "environmental",
        "org"
    ],
    "wof:name":"Pine Tree Landfill Facility",
    "wof:placetype":"venue"
},
  "geometry": {"coordinates":[-68.869415,44.772799],"type":"Point"}
}