{
  "type": "Feature",
  "properties": {
    "iso:country":"US",
    "sg:address":"41 Canoe Club Rd",
    "sg:city":"Hampden",
    "sg:classifiers":[
        {
            "category":"Recreation",
            "type":"Entertainment"
        }
    ],
    "sg:phone":"+1 207 862 2553",
    "sg:postcode":"04444",
    "sg:province":"ME",
    "sg:tags":[
        "hall",
        "auditorium"
    ],
    "wof:name":"VFW Hall",
    "wof:placetype":"venue"
},
  "geometry": {"coordinates":[-68.83214,44.743994],"type":"Point"}
}