{
  "type": "Feature",
  "properties": {
    "addr:full":"33 Elm St Winslow ME 04901",
    "addr:housenumber":"33",
    "addr:postcode":"04901",
    "addr:street":"Elm St",
    "iso:country":"US",
    "sg:address":"33 Elm St",
    "sg:city":"Winslow",
    "sg:phone":"+1 207 872 7408",
    "sg:postcode":"04901",
    "sg:province":"ME",
    "sg:tags":[
        "oil"
    ],
    "wof:name":"C N Brown Heating Oil",
    "wof:placetype":"venue"
},
  "geometry": {"coordinates":[-69.633692,44.54941],"type":"Point"}
}