{
  "type": "Feature",
  "properties": {
    "addr:full":"222 College Ave Waterville ME 04901",
    "addr:housenumber":"222",
    "addr:postcode":"04901",
    "addr:street":"College Ave",
    "iso:country":"US",
    "sg:address":"222 College Ave",
    "sg:city":"Waterville",
    "sg:classifiers":[
        {
            "category":"Banks & Credit Unions",
            "subcategory":"Bank",
            "type":"Services"
        }
    ],
    "sg:phone":"+1 207 872 5602",
    "sg:postcode":"04901",
    "sg:province":"ME",
    "sg:website":"www.kswfcu.org",
    "wof:name":"Ksw Federal Credit Union",
    "wof:placetype":"venue"
},
  "geometry": {"coordinates":[-69.615426,44.57354],"type":"Point"}
}