{
  "type": "Feature",
  "properties": {
    "addr:full":"33 Dexter Rd Corinna ME 04923",
    "addr:housenumber":"33",
    "addr:postcode":"04923",
    "addr:street":"Dexter Rd",
    "iso:country":"US",
    "sg:address":"33 Dexter Rd",
    "sg:city":"Corinna",
    "sg:classifiers":[
        {
            "category":"Shopping",
            "subcategory":"Bicycles & Sporting Goods",
            "type":"Retail Goods"
        }
    ],
    "sg:phone":"+1 207 278 5875",
    "sg:postcode":"04923",
    "sg:province":"ME",
    "wof:name":"Woodard's Pit Stop-Nascar",
    "wof:placetype":"venue"
},
  "geometry": {"coordinates":[-69.471598,45.024802],"type":"Point"}
}