{
  "type": "Feature",
  "properties": {
    "addr:full":"1653 Forest Ave Portland ME 04103",
    "addr:housenumber":"1653",
    "addr:postcode":"04103",
    "addr:street":"Forest Ave",
    "iso:country":"US",
    "sg:address":"1653 Forest Ave",
    "sg:city":"Portland",
    "sg:classifiers":[
        {
            "category":"Professional",
            "subcategory":"Business Services",
            "type":"Services"
        },
        {
            "category":"Government",
            "subcategory":"Court House",
            "type":"Public Place"
        }
    ],
    "sg:phone":"+1 207 797 6650",
    "sg:postcode":"04103",
    "sg:province":"ME",
    "sg:tags":[
        "personal",
        "notary"
    ],
    "wof:name":"A Beautiful Celebration Love",
    "wof:placetype":"venue"
},
  "geometry": {"coordinates":[-70.30895099999999,43.698035],"type":"Point"}
}