{
  "type": "Feature",
  "properties": {
    "iso:country":"US",
    "sg:address":"333 Brunswick St",
    "sg:city":"Old Town",
    "sg:classifiers":[
        {
            "category":"Building & Trades",
            "subcategory":"Construction",
            "type":"Services"
        }
    ],
    "sg:phone":"+1 207 827 6475",
    "sg:postcode":"04468",
    "sg:province":"ME",
    "sg:tags":[
        "contractor"
    ],
    "wof:name":"Doug Cyr Ceramic",
    "wof:placetype":"venue"
},
  "geometry": {"coordinates":[-68.64406099999999,44.920373],"type":"Point"}
}