{
  "type": "Feature",
  "properties": {
    "iso:country":"US",
    "sg:address":"127 Middle St",
    "sg:city":"Portland",
    "sg:classifiers":[
        {
            "category":"Personal",
            "subcategory":"Beauty Salon",
            "type":"Services"
        }
    ],
    "sg:phone":"+1 207 775 9111",
    "sg:postcode":"04101",
    "sg:province":"ME",
    "wof:name":"Liquid Hair Studio",
    "wof:placetype":"venue"
},
  "geometry": {"coordinates":[-70.253417,43.658362],"type":"Point"}
}