{
  "type": "Feature",
  "properties": {
    "addr:full":"34 Elm St Waterville ME 04901",
    "addr:housenumber":"34",
    "addr:postcode":"04901",
    "addr:street":"Elm St",
    "iso:country":"US",
    "sg:address":"34 Elm St",
    "sg:city":"Waterville",
    "sg:classifiers":[
        {
            "category":"Retail",
            "subcategory":"Auto Rental",
            "type":"Services"
        }
    ],
    "sg:phone":"+1 207 873 6171",
    "sg:postcode":"04901",
    "sg:province":"ME",
    "sg:tags":[
        "renting",
        "truck",
        "leasing"
    ],
    "wof:name":"U-Haul Co",
    "wof:placetype":"venue"
},
  "geometry": {"coordinates":[-69.634261,44.548788],"type":"Point"}
}