{
  "type": "Feature",
  "properties": {
    "iso:country":"US",
    "sg:address":"20 Great Falls Plz",
    "sg:city":"Auburn",
    "sg:classifiers":[
        {
            "category":"Real Estate",
            "subcategory":"Real Estate Agent",
            "type":"Services"
        }
    ],
    "sg:phone":"+1 207 784 7351",
    "sg:postcode":"04210",
    "sg:province":"ME",
    "sg:tags":[
        "authorities",
        "housing"
    ],
    "wof:name":"Auburn Housing Authority",
    "wof:placetype":"venue"
},
  "geometry": {"coordinates":[-70.22599599999999,44.099104],"type":"Point"}
}