{
  "type": "Feature",
  "properties": {
    "iso:country":"US",
    "sg:address":"468 Forest Ave",
    "sg:city":"Portland",
    "sg:classifiers":[
        {
            "category":"Recreation",
            "type":"Entertainment"
        }
    ],
    "sg:phone":"+1 207 712 5955",
    "sg:postcode":"04101",
    "sg:province":"ME",
    "sg:tags":[
        "martial",
        "arts",
        "instruction"
    ],
    "wof:name":"Academy Of Mixed Martial Arts",
    "wof:placetype":"venue"
},
  "geometry": {"coordinates":[-70.277824,43.666573],"type":"Point"}
}