{
  "type": "Feature",
  "properties": {
    "addr:full":"366 US Hwy 1 Columbia ME 04605",
    "addr:housenumber":"366",
    "addr:postcode":"04605",
    "addr:street":"Us Hwy 1",
    "iso:country":"US",
    "sg:address":"366 US Hwy 1",
    "sg:city":"Columbia",
    "sg:classifiers":[
        {
            "category":"Building & Trades",
            "subcategory":"Equipment Rental",
            "type":"Services"
        }
    ],
    "sg:phone":"+1 207 483 2267",
    "sg:postcode":"04605",
    "sg:province":"ME",
    "sg:tags":[
        "yard"
    ],
    "wof:name":"U-Haul Co",
    "wof:placetype":"venue"
},
  "geometry": {"coordinates":[-68.43393399999999,44.539022],"type":"Point"}
}