{
  "type": "Feature",
  "properties": {
    "addr:full":"227 W Main St Searsport ME 04974",
    "addr:housenumber":"227",
    "addr:postcode":"04974",
    "addr:street":"W Main St",
    "iso:country":"US",
    "sg:address":"227 W Main St",
    "sg:city":"Searsport",
    "sg:classifiers":[
        {
            "category":"Food & Beverages",
            "subcategory":"Bakery",
            "type":"Retail Goods"
        }
    ],
    "sg:phone":"+1 207 548 9910",
    "sg:postcode":"04974",
    "sg:province":"ME",
    "sg:tags":[
        "baker"
    ],
    "wof:name":"Periwinkles Bakery",
    "wof:placetype":"venue"
},
  "geometry": {"coordinates":[-68.935889,44.442897],"type":"Point"}
}