{
  "type": "Feature",
  "properties": {
    "iso:country":"US",
    "sg:address":"767 Lewiston Rd",
    "sg:city":"Topsham",
    "sg:classifiers":[
        {
            "category":"Retail",
            "subcategory":"Laundry & Dry Cleaning",
            "type":"Services"
        }
    ],
    "sg:phone":"+1 207 725 7277",
    "sg:postcode":"04086",
    "sg:province":"ME",
    "sg:tags":[
        "cleaners",
        "rug",
        "carpet"
    ],
    "wof:name":"Allclean Carpet Care",
    "wof:placetype":"venue"
},
  "geometry": {"coordinates":[-70.009342,43.961083],"type":"Point"}
}