{
  "type": "Feature",
  "properties": {
    "iso:country":"US",
    "sg:address":"183 Augusta Rd",
    "sg:city":"Whitefield",
    "sg:classifiers":[
        {
            "category":"Building & Trades",
            "subcategory":"Construction",
            "type":"Services"
        }
    ],
    "sg:phone":"+1 207 549 3190",
    "sg:postcode":"04353",
    "sg:province":"ME",
    "sg:tags":[
        "general",
        "contractor"
    ],
    "wof:name":"Frank Monroe Construction",
    "wof:placetype":"venue"
},
  "geometry": {"coordinates":[-69.648575,44.274692],"type":"Point"}
}