{
  "type": "Feature",
  "properties": {
    "addr:full":"207 S High St Bridgton ME 04009",
    "addr:housenumber":"207",
    "addr:postcode":"04009",
    "addr:street":"S High St",
    "iso:country":"US",
    "sg:address":"207 S High St",
    "sg:city":"Bridgton",
    "sg:classifiers":[
        {
            "category":"Retail",
            "subcategory":"Laundry & Dry Cleaning",
            "type":"Services"
        }
    ],
    "sg:phone":"+1 207 647 2822",
    "sg:postcode":"04009",
    "sg:province":"ME",
    "sg:tags":[
        "cleaners",
        "rug",
        "carpet"
    ],
    "wof:name":"Mc Hatton's Cleaning Svc",
    "wof:placetype":"venue"
},
  "geometry": {"coordinates":[-70.70820999999999,44.03429],"type":"Point"}
}