{
  "type": "Feature",
  "properties": {
    "iso:country":"US",
    "sg:address":"15 Bangor St",
    "sg:city":"Augusta",
    "sg:classifiers":[
        {
            "category":"Restaurant",
            "type":"Food & Drink"
        }
    ],
    "sg:phone":"+1 207 621 0599",
    "sg:postcode":"04330",
    "sg:province":"ME",
    "wof:name":"Bravo's Bar & Grille",
    "wof:placetype":"venue"
},
  "geometry": {"coordinates":[-69.766956,44.318062],"type":"Point"}
}