{
  "type": "Feature",
  "properties": {
    "iso:country":"US",
    "sg:address":"456 Portland Rd",
    "sg:city":"Bridgton",
    "sg:classifiers":[
        {
            "category":"Autos & Motor Vehicles",
            "subcategory":"Automobile Sales",
            "type":"Retail Goods"
        }
    ],
    "sg:phone":"+1 207 647 3304",
    "sg:postcode":"04009",
    "sg:province":"ME",
    "sg:tags":[
        "car",
        "dealer"
    ],
    "sg:website":"www.macdonaldmotors.com",
    "wof:name":"Mac Donald Motors",
    "wof:placetype":"venue"
},
  "geometry": {"coordinates":[-70.70114,44.04782],"type":"Point"}
}