{
  "type": "Feature",
  "properties": {
    "iso:country":"US",
    "sg:address":"1250 Forest Ave",
    "sg:city":"Portland",
    "sg:classifiers":[
        {
            "category":"Manufacturing",
            "subcategory":"Lumber",
            "type":"Manufacturing & Wholesale Goods"
        }
    ],
    "sg:phone":"+1 207 797 6278",
    "sg:postcode":"04103",
    "sg:province":"ME",
    "sg:tags":[
        "forester"
    ],
    "wof:name":"Forest Avenue Pro Building",
    "wof:placetype":"venue"
},
  "geometry": {"coordinates":[-70.295324,43.689333],"type":"Point"}
}