{
  "type": "Feature",
  "properties": {
    "iso:country":"US",
    "sg:address":"102 Bangor St",
    "sg:city":"Augusta",
    "sg:classifiers":[
        {
            "category":"Shopping",
            "subcategory":"Bicycles & Sporting Goods",
            "type":"Retail Goods"
        }
    ],
    "sg:phone":"+1 207 621 9968",
    "sg:postcode":"04330",
    "sg:province":"ME",
    "wof:name":"Play It Again Sports",
    "wof:placetype":"venue"
},
  "geometry": {"coordinates":[-69.764031,44.32401],"type":"Point"}
}