{
  "type": "Feature",
  "properties": {
    "addr:full":"325 Gorham Rd South Portland ME 04106",
    "addr:housenumber":"325",
    "addr:postcode":"04106",
    "addr:street":"Gorham Rd",
    "iso:country":"US",
    "sg:address":"325 Gorham Rd",
    "sg:city":"South Portland",
    "sg:classifiers":[
        {
            "category":"Bakery",
            "type":"Food & Drink"
        },
        {
            "category":"Coffee & Tea",
            "type":"Food & Drink"
        },
        {
            "category":"Bagels",
            "type":"Food & Drink"
        },
        {
            "category":"Donuts",
            "type":"Food & Drink"
        }
    ],
    "sg:menulink":"http://www.allmenus.com/me/south-portland/149090-dunkin-donuts/menu/",
    "sg:phone":"+1 207 874 9600",
    "sg:postcode":"04106",
    "sg:province":"ME",
    "sg:tags":[
        "wrap",
        "american",
        "sandwich",
        "pastry"
    ],
    "wof:name":"Dunkin' Donuts",
    "wof:placetype":"venue"
},
  "geometry": {"coordinates":[-70.328283,43.635217],"type":"Point"}
}