{
  "type": "Feature",
  "properties": {
    "addr:full":"107 Cambridge Rd Harmony ME 04942",
    "addr:housenumber":"107",
    "addr:postcode":"04942",
    "addr:street":"Cambridge Rd",
    "iso:country":"US",
    "sg:address":"107 Cambridge Rd",
    "sg:city":"Harmony",
    "sg:classifiers":[
        {
            "category":"Freight",
            "type":"Transportation"
        }
    ],
    "sg:phone":"+1 207 683 5910",
    "sg:postcode":"04942",
    "sg:province":"ME",
    "sg:tags":[
        "commercial",
        "storage"
    ],
    "wof:name":"Harmony Self Storage",
    "wof:placetype":"venue"
},
  "geometry": {"coordinates":[-69.527128,44.989592],"type":"Point"}
}