{
  "type": "Feature",
  "properties": {
    "iso:country":"US",
    "sg:address":"859 Main St",
    "sg:city":"Sanford",
    "sg:classifiers":[
        {
            "category":"Personal",
            "subcategory":"Beauty Salon",
            "type":"Services"
        }
    ],
    "sg:phone":"+1 207 324 9800",
    "sg:postcode":"04073",
    "sg:province":"ME",
    "sg:tags":[
        "shop"
    ],
    "wof:name":"A Style For You",
    "wof:placetype":"venue"
},
  "geometry": {"coordinates":[-70.77854499999999,43.441483],"type":"Point"}
}