{
  "type": "Feature",
  "properties": {
    "iso:country":"US",
    "sg:address":"1 Balsam Dr",
    "sg:city":"Cumberland Ctr",
    "sg:classifiers":[
        {
            "category":"Professional",
            "subcategory":"Computer Services",
            "type":"Services"
        }
    ],
    "sg:phone":"+1 207 829 6553",
    "sg:postcode":"04021",
    "sg:province":"ME",
    "sg:tags":[
        "consultant",
        "designer"
    ],
    "wof:name":"Datasmith Services",
    "wof:placetype":"venue"
},
  "geometry": {"coordinates":[-70.24502,43.797889],"type":"Point"}
}