{
  "type": "Feature",
  "properties": {
    "iso:country":"US",
    "sg:address":"252 Bolsters Mills Rd",
    "sg:city":"Harrison",
    "sg:classifiers":[
        {
            "category":"Shopping",
            "subcategory":"Gifts & Souvenirs",
            "type":"Retail Goods"
        }
    ],
    "sg:phone":"+1 207 583 4477",
    "sg:postcode":"04040",
    "sg:province":"ME",
    "wof:name":"Peter Card",
    "wof:placetype":"venue"
},
  "geometry": {"coordinates":[-70.61836,44.132193],"type":"Point"}
}