{
  "type": "Feature",
  "properties": {
    "addr:full":"374 Main St Lewiston ME 04240",
    "addr:housenumber":"374",
    "addr:postcode":"04240",
    "addr:street":"Main St",
    "iso:country":"US",
    "sg:address":"374 Main St",
    "sg:city":"Lewiston",
    "sg:classifiers":[
        {
            "category":"Professional",
            "subcategory":"Lawyer & Legal Services",
            "type":"Services"
        }
    ],
    "sg:phone":"+1 207 784 3401",
    "sg:postcode":"04240",
    "sg:province":"ME",
    "wof:name":"Baker Weston",
    "wof:placetype":"venue"
},
  "geometry": {"coordinates":[-70.212566,44.103464],"type":"Point"}
}