{
  "type": "Feature",
  "properties": {
    "iso:country":"US",
    "sg:address":"1600 Atlantic Hwy",
    "sg:city":"Waldoboro",
    "sg:classifiers":[
        {
            "category":"Government",
            "subcategory":"Police Station",
            "type":"Public Place"
        }
    ],
    "sg:phone":"+1 207 832 4500",
    "sg:postcode":"04572",
    "sg:province":"ME",
    "sg:tags":[
        "department"
    ],
    "wof:name":"Town Police Dept",
    "wof:placetype":"venue"
},
  "geometry": {"coordinates":[-69.378378,44.102317],"type":"Point"}
}