{
  "type": "Feature",
  "properties": {
    "addr:full":"3 Knox St Thomaston ME 04861",
    "addr:housenumber":"3",
    "addr:postcode":"04861",
    "addr:street":"Knox St",
    "iso:country":"US",
    "sg:address":"3 Knox St",
    "sg:city":"Thomaston",
    "sg:classifiers":[
        {
            "category":"Government",
            "subcategory":"Police Station",
            "type":"Public Place"
        }
    ],
    "sg:phone":"+1 207 354 2511",
    "sg:postcode":"04861",
    "sg:province":"ME",
    "sg:tags":[
        "department"
    ],
    "wof:name":"Town Police Dept",
    "wof:placetype":"venue"
},
  "geometry": {"coordinates":[-69.18247100000001,44.078753],"type":"Point"}
}