{
  "type": "Feature",
  "properties": {
    "iso:country":"US",
    "sg:address":"1246 Roosevelt Trl",
    "sg:city":"Raymond",
    "sg:classifiers":[
        {
            "category":"Shopping",
            "type":"Retail Goods"
        }
    ],
    "sg:phone":"+1 207 655 2520",
    "sg:postcode":"04071",
    "sg:province":"ME",
    "sg:tags":[
        "candle"
    ],
    "sg:website":"www.candlecompany.com",
    "wof:name":"Cabin Candlery Factory Store",
    "wof:placetype":"venue"
},
  "geometry": {"coordinates":[-70.465419,43.882748],"type":"Point"}
}