{
  "type": "Feature",
  "properties": {
    "iso:country":"US",
    "sg:address":"7 Vesper St",
    "sg:city":"Scarborough",
    "sg:classifiers":[
        {
            "category":"Professional",
            "subcategory":"Business Services",
            "type":"Services"
        }
    ],
    "sg:phone":"+1 207 883 3196",
    "sg:postcode":"04074",
    "sg:province":"ME",
    "sg:tags":[
        "interior",
        "consultant",
        "design",
        "decorator"
    ],
    "wof:name":"Julie A Brown Certified",
    "wof:placetype":"venue"
},
  "geometry": {"coordinates":[-70.276577,43.561204],"type":"Point"}
}