{
  "type": "Feature",
  "properties": {
    "iso:country":"US",
    "sg:address":"148 Augusta Rd",
    "sg:city":"Washington",
    "sg:classifiers":[
        {
            "category":"Restaurant",
            "type":"Food & Drink"
        }
    ],
    "sg:phone":"+1 207 845 2964",
    "sg:postcode":"04574",
    "sg:province":"ME",
    "sg:tags":[
        "out"
    ],
    "wof:name":"Country Cupboard",
    "wof:placetype":"venue"
},
  "geometry": {"coordinates":[-69.364981,44.239584],"type":"Point"}
}