{
  "type": "Feature",
  "properties": {
    "addr:full":"146 Highland Cliff Rd Windham ME 04062",
    "addr:housenumber":"146",
    "addr:postcode":"04062",
    "addr:street":"Highland Cliff Rd",
    "iso:country":"US",
    "sg:address":"146 Highland Cliff Rd",
    "sg:city":"Windham",
    "sg:classifiers":[
        {
            "category":"Building & Trades",
            "subcategory":"Construction",
            "type":"Services"
        }
    ],
    "sg:phone":"+1 207 892 5191",
    "sg:postcode":"04062",
    "sg:province":"ME",
    "sg:tags":[
        "house"
    ],
    "wof:name":"David R Weeks Construction",
    "wof:placetype":"venue"
},
  "geometry": {"coordinates":[-70.39308699999999,43.727851],"type":"Point"}
}