{
  "type": "Feature",
  "properties": {
    "iso:country":"US",
    "sg:address":"108 Maine St",
    "sg:city":"Brunswick",
    "sg:classifiers":[
        {
            "category":"Professional",
            "subcategory":"Business Services",
            "type":"Services"
        }
    ],
    "sg:phone":"+1 207 729 7694",
    "sg:postcode":"04011",
    "sg:province":"ME",
    "sg:tags":[
        "consulting"
    ],
    "wof:name":"Brunswick Topsham Land Trust",
    "wof:placetype":"venue"
},
  "geometry": {"coordinates":[-69.965682,43.915813],"type":"Point"}
}