{
  "type": "Feature",
  "properties": {
    "iso:country":"US",
    "sg:address":"536 Main St",
    "sg:city":"Bridgewater",
    "sg:classifiers":[
        {
            "category":"Shopping",
            "subcategory":"Jewelry",
            "type":"Retail Goods"
        }
    ],
    "sg:phone":"+1 207 425 7113",
    "sg:postcode":"04756",
    "sg:province":"ME",
    "sg:tags":[
        "jeweler"
    ],
    "wof:name":"Goldmasters",
    "wof:placetype":"venue"
},
  "geometry": {"coordinates":[-68.327736,47.356038],"type":"Point"}
}