{
  "type": "Feature",
  "properties": {
    "addr:full":"213 Main St Presque Isle ME 04769",
    "addr:housenumber":"213",
    "addr:postcode":"04769",
    "addr:street":"Main St",
    "iso:country":"US",
    "sg:address":"213 Main St",
    "sg:city":"Presque Isle",
    "sg:classifiers":[
        {
            "category":"Restaurant",
            "type":"Food & Drink"
        }
    ],
    "sg:phone":"+1 207 769 2700",
    "sg:postcode":"04769",
    "sg:province":"ME",
    "wof:name":"Quiznos Sub",
    "wof:placetype":"venue"
},
  "geometry": {"coordinates":[-68.016169,46.674223],"type":"Point"}
}