{
  "type": "Feature",
  "properties": {
    "iso:country":"US",
    "sg:address":"8 Zoar St",
    "sg:city":"Auburn",
    "sg:classifiers":[
        {
            "category":"Professional",
            "subcategory":"Computer Services",
            "type":"Services"
        }
    ],
    "sg:phone":"+1 207 753 6363",
    "sg:postcode":"04210",
    "sg:province":"ME",
    "sg:tags":[
        "related"
    ],
    "wof:name":"Renaissance Enterprises",
    "wof:placetype":"venue"
},
  "geometry": {"coordinates":[-70.244725,44.080582],"type":"Point"}
}