{
  "type": "Feature",
  "properties": {
    "iso:country":"US",
    "sg:address":"196 Main St",
    "sg:city":"Greenwood",
    "sg:classifiers":[
        {
            "category":"Restaurant",
            "type":"Food & Drink"
        }
    ],
    "sg:phone":"+1 207 875 2726",
    "sg:postcode":"04292",
    "sg:province":"ME",
    "wof:name":"Cinnamon Stick Cafe",
    "wof:placetype":"venue"
},
  "geometry": {"coordinates":[-70.393379,44.366739],"type":"Point"}
}