{
  "type": "Feature",
  "properties": {
    "addr:full":"1485 Lisbon St Lewiston ME 04240",
    "addr:housenumber":"1485",
    "addr:postcode":"04240",
    "addr:street":"Lisbon St",
    "iso:country":"US",
    "sg:address":"1485 Lisbon St",
    "sg:city":"Lewiston",
    "sg:classifiers":[
        {
            "category":"Restaurant",
            "type":"Food & Drink"
        }
    ],
    "sg:phone":"+1 207 782 3305",
    "sg:postcode":"04240",
    "sg:province":"ME",
    "wof:name":"Fast Breaks",
    "wof:placetype":"venue"
},
  "geometry": {"coordinates":[-70.175907,44.072896],"type":"Point"}
}