{
  "type": "Feature",
  "properties": {
    "addr:full":"50 School St Saco ME 04072",
    "addr:housenumber":"50",
    "addr:postcode":"04072",
    "addr:street":"School St",
    "iso:country":"US",
    "sg:address":"50 School St",
    "sg:city":"Saco",
    "sg:classifiers":[
        {
            "category":"Building & Trades",
            "subcategory":"Construction",
            "type":"Services"
        }
    ],
    "sg:phone":"+1 207 284 9262",
    "sg:postcode":"04072",
    "sg:province":"ME",
    "sg:tags":[
        "painter"
    ],
    "wof:name":"Clint's Painting",
    "wof:placetype":"venue"
},
  "geometry": {"coordinates":[-70.442222,43.497511],"type":"Point"}
}