{
  "type": "Feature",
  "properties": {
    "iso:country":"US",
    "sg:address":"64 Birch Ave",
    "sg:city":"Ellsworth",
    "sg:classifiers":[
        {
            "category":"Professional",
            "subcategory":"Art Services",
            "type":"Services"
        }
    ],
    "sg:phone":"+1 207 667 0073",
    "sg:postcode":"04605",
    "sg:province":"ME",
    "sg:tags":[
        "commercial",
        "design"
    ],
    "wof:name":"K M W Design",
    "wof:placetype":"venue"
},
  "geometry": {"coordinates":[-68.422313,44.547912],"type":"Point"}
}