{
  "type": "Feature",
  "properties": {
    "iso:country":"US",
    "sg:address":"1 Lincoln St",
    "sg:city":"South Portland",
    "sg:classifiers":[
        {
            "category":"Wholesale",
            "subcategory":"Machinery & Supplies",
            "type":"Manufacturing & Wholesale Goods"
        }
    ],
    "sg:phone":"+1 207 775 1516",
    "sg:postcode":"04106",
    "sg:province":"ME",
    "sg:tags":[
        "car"
    ],
    "wof:name":"Maintenance Tech Inc",
    "wof:placetype":"venue"
},
  "geometry": {"coordinates":[-70.28993699999999,43.638593],"type":"Point"}
}