{
  "type": "Feature",
  "properties": {
    "iso:country":"US",
    "sg:address":"1413 Main St",
    "sg:city":"Sanford",
    "sg:classifiers":[
        {
            "category":"Autos & Motor Vehicles",
            "subcategory":"Automobile Sales",
            "type":"Retail Goods"
        }
    ],
    "sg:phone":"+1 207 490 5202",
    "sg:postcode":"04073",
    "sg:province":"ME",
    "wof:name":"Motorhead Trdg Post & Hobbies",
    "wof:placetype":"venue"
},
  "geometry": {"coordinates":[-70.74463799999999,43.412358],"type":"Point"}
}