{
  "type": "Feature",
  "properties": {
    "iso:country":"US",
    "sg:address":"228 Atlantic Ave",
    "sg:city":"Boothbay Harbor",
    "sg:classifiers":[
        {
            "category":"Manufacturing",
            "subcategory":"Furniture",
            "type":"Manufacturing & Wholesale Goods"
        }
    ],
    "sg:phone":"+1 207 633 4460",
    "sg:postcode":"04538",
    "sg:province":"ME",
    "sg:tags":[
        "upholstered",
        "household",
        "mfg"
    ],
    "wof:name":"Atlantic Upholstery",
    "wof:placetype":"venue"
},
  "geometry": {"coordinates":[-69.62665,43.8365],"type":"Point"}
}