{
  "type": "Feature",
  "properties": {
    "addr:full":"130 Wardtown Rd Freeport ME 04032",
    "addr:housenumber":"130",
    "addr:postcode":"04032",
    "addr:street":"Wardtown Rd",
    "iso:country":"US",
    "sg:address":"130 Wardtown Rd",
    "sg:city":"Freeport",
    "sg:classifiers":[
        {
            "category":"Shopping",
            "subcategory":"Discount & Variety Stores",
            "type":"Retail Goods"
        }
    ],
    "sg:phone":"+1 207 865 4429",
    "sg:postcode":"04032",
    "sg:province":"ME",
    "sg:tags":[
        "merchandise",
        "general"
    ],
    "wof:name":"Doherty's North Freeport Store",
    "wof:placetype":"venue"
},
  "geometry": {"coordinates":[-70.090947,43.912607],"type":"Point"}
}