{
  "type": "Feature",
  "properties": {
    "addr:full":"575 River Rd Orrington ME 04474",
    "addr:housenumber":"575",
    "addr:postcode":"04474",
    "addr:street":"River Rd",
    "iso:country":"US",
    "sg:address":"575 River Rd",
    "sg:city":"Orrington",
    "sg:classifiers":[
        {
            "category":"Professional",
            "subcategory":"Business Services",
            "type":"Services"
        }
    ],
    "sg:phone":"+1 207 825 4964",
    "sg:postcode":"04474",
    "sg:province":"ME",
    "sg:tags":[
        "water",
        "treatment"
    ],
    "wof:name":"Norlen's Water Treatment Svc",
    "wof:placetype":"venue"
},
  "geometry": {"coordinates":[-68.82036100000001,44.737393],"type":"Point"}
}