{
  "type": "Feature",
  "properties": {
    "addr:full":"973 Forest Ave Portland ME 04103",
    "addr:housenumber":"973",
    "addr:postcode":"04103",
    "addr:street":"Forest Ave",
    "iso:country":"US",
    "sg:address":"973 Forest Ave",
    "sg:city":"Portland",
    "sg:classifiers":[
        {
            "category":"Retail",
            "subcategory":"Animal Services",
            "type":"Services"
        }
    ],
    "sg:phone":"+1 207 797 7509",
    "sg:postcode":"04103",
    "sg:province":"ME",
    "sg:tags":[
        "pet",
        "boarding",
        "sitting"
    ],
    "wof:name":"Forest Avenue Veterinary Hosp",
    "wof:placetype":"venue"
},
  "geometry": {"coordinates":[-70.289129,43.680178],"type":"Point"}
}