{
  "type": "Feature",
  "properties": {
    "iso:country":"US",
    "sg:address":"11 Foley Ave",
    "sg:city":"Saco",
    "sg:classifiers":[
        {
            "category":"Professional",
            "subcategory":"Business Services",
            "type":"Services"
        }
    ],
    "sg:phone":"+1 207 284 7920",
    "sg:postcode":"04072",
    "sg:province":"ME",
    "wof:name":"Swift Brushes Painting",
    "wof:placetype":"venue"
},
  "geometry": {"coordinates":[-70.445752,43.507268],"type":"Point"}
}