{
  "type": "Feature",
  "properties": {
    "addr:full":"155 Hogan Rd Lewiston ME 04240",
    "addr:housenumber":"155",
    "addr:postcode":"04240",
    "addr:street":"Hogan Rd",
    "iso:country":"US",
    "sg:address":"155 Hogan Rd",
    "sg:city":"Lewiston",
    "sg:classifiers":[
        {
            "category":"Organizations",
            "subcategory":"Religious Organization",
            "type":"Services"
        }
    ],
    "sg:phone":"+1 207 783 6795",
    "sg:postcode":"04240",
    "sg:province":"ME",
    "sg:tags":[
        "church"
    ],
    "sg:website":"www.holytrinitymaine.org",
    "wof:name":"Greek Orthodox Church",
    "wof:placetype":"venue"
},
  "geometry": {"coordinates":[-70.178549,44.125257],"type":"Point"}
}