{
  "type": "Feature",
  "properties": {
    "addr:full":"155 Kennedy Memorial Dr Waterville ME 04901",
    "addr:housenumber":"155",
    "addr:postcode":"04901",
    "addr:street":"Kennedy Memorial Dr",
    "iso:country":"US",
    "sg:address":"155 Kennedy Memorial Dr",
    "sg:city":"Waterville",
    "sg:classifiers":[
        {
            "category":"Health Services",
            "subcategory":"Health Practitioner",
            "type":"Services"
        }
    ],
    "sg:phone":"+1 207 872 5775",
    "sg:postcode":"04901",
    "sg:province":"ME",
    "sg:tags":[
        "pathologist",
        "speech"
    ],
    "wof:name":"Adams Speech Therapy",
    "wof:placetype":"venue"
},
  "geometry": {"coordinates":[-69.658182,44.542234],"type":"Point"}
}