{
  "type": "Feature",
  "properties": {
    "iso:country":"US",
    "sg:address":"289 Broadway",
    "sg:city":"Bangor",
    "sg:classifiers":[
        {
            "category":"Building & Trades",
            "subcategory":"Landscaping Services",
            "type":"Services"
        }
    ],
    "sg:phone":"+1 207 990 2212",
    "sg:postcode":"04401",
    "sg:province":"ME",
    "sg:tags":[
        "lawn",
        "maintenance",
        "grounds"
    ],
    "wof:name":"Pete's Lawn Care",
    "wof:placetype":"venue"
},
  "geometry": {"coordinates":[-68.770291,44.812663],"type":"Point"}
}