{
  "type": "Feature",
  "properties": {
    "addr:full":"11 Oxbow Cir Naples ME 04055",
    "addr:housenumber":"11",
    "addr:postcode":"04055",
    "addr:street":"Oxbow Cir",
    "iso:country":"US",
    "sg:address":"11 Oxbow Cir",
    "sg:city":"Naples",
    "sg:classifiers":[
        {
            "category":"Freight",
            "type":"Transportation"
        }
    ],
    "sg:phone":"+1 207 693 3435",
    "sg:postcode":"04055",
    "sg:province":"ME",
    "wof:name":"TS Harmon Inc",
    "wof:placetype":"venue"
},
  "geometry": {"coordinates":[-70.570897,43.958487],"type":"Point"}
}