{
  "type": "Feature",
  "properties": {
    "addr:full":"87 Portland Street Pier South Portland ME 04106",
    "addr:housenumber":"87",
    "addr:postcode":"04106",
    "addr:street":"Portland Street Pier",
    "iso:country":"US",
    "sg:address":"87 Portland Street Pier",
    "sg:city":"South Portland",
    "sg:classifiers":[
        {
            "category":"Home & Garden",
            "subcategory":"Household Appliances",
            "type":"Retail Goods"
        }
    ],
    "sg:phone":"+1 207 791 2775",
    "sg:postcode":"04106",
    "sg:province":"ME",
    "wof:name":"Mr Appliance",
    "wof:placetype":"venue"
},
  "geometry": {"coordinates":[-70.241985,43.649592],"type":"Point"}
}