{
  "type": "Feature",
  "properties": {
    "iso:country":"US",
    "sg:address":"613 Congress St",
    "sg:city":"Portland",
    "sg:classifiers":[
        {
            "category":"Shopping",
            "subcategory":"Music",
            "type":"Retail Goods"
        }
    ],
    "sg:phone":"+1 207 773 7672",
    "sg:postcode":"04101",
    "sg:province":"ME",
    "sg:tags":[
        "compact",
        "record",
        "disc",
        "tape"
    ],
    "wof:name":"Enterprise Records",
    "wof:placetype":"venue"
},
  "geometry": {"coordinates":[-70.263521,43.653842],"type":"Point"}
}