{
  "type": "Feature",
  "properties": {
    "addr:full":"190 Lincoln St Bath ME 04530",
    "addr:housenumber":"190",
    "addr:postcode":"04530",
    "addr:street":"Lincoln St",
    "iso:country":"US",
    "sg:address":"190 Lincoln St",
    "sg:city":"Bath",
    "sg:classifiers":[
        {
            "category":"Shopping",
            "subcategory":"Florist",
            "type":"Retail Goods"
        }
    ],
    "sg:phone":"+1 207 443 4111",
    "sg:postcode":"04530",
    "sg:province":"ME",
    "wof:name":"Westgate Flower Shoppe",
    "wof:placetype":"venue"
},
  "geometry": {"coordinates":[-69.82653000000001,43.917823],"type":"Point"}
}