{
  "type": "Feature",
  "properties": {
    "addr:full":"30 Industrial Plaza Dr Brewer ME 04412",
    "addr:housenumber":"30",
    "addr:postcode":"04412",
    "addr:street":"Industrial Plaza Dr",
    "iso:country":"US",
    "sg:address":"30 Industrial Plaza Dr",
    "sg:city":"Brewer",
    "sg:classifiers":[
        {
            "category":"Retail",
            "subcategory":"Repair Shop",
            "type":"Services"
        }
    ],
    "sg:phone":"+1 207 548 2474",
    "sg:postcode":"04412",
    "sg:province":"ME",
    "sg:tags":[
        "oil",
        "burner"
    ],
    "wof:name":"Irving Heating Oil",
    "wof:placetype":"venue"
},
  "geometry": {"coordinates":[-68.76382099999999,44.780765],"type":"Point"}
}