{
  "type": "Feature",
  "properties": {
    "iso:country":"US",
    "sg:address":"28 Oak Hill Ter",
    "sg:city":"Scarborough",
    "sg:classifiers":[
        {
            "category":"Banks & Credit Unions",
            "subcategory":"Investment Brokerage",
            "type":"Services"
        }
    ],
    "sg:phone":"+1 207 885 5522",
    "sg:postcode":"04074",
    "sg:province":"ME",
    "sg:tags":[
        "security"
    ],
    "sg:website":"www.innovafinancial.com",
    "wof:name":"Innova Financial Svc",
    "wof:placetype":"venue"
},
  "geometry": {"coordinates":[-70.333776,43.591304],"type":"Point"}
}