{
  "type": "Feature",
  "properties": {
    "addr:full":"436 Main St Presque Isle ME 04769",
    "addr:housenumber":"436",
    "addr:postcode":"04769",
    "addr:street":"Main St",
    "iso:country":"US",
    "sg:address":"436 Main St",
    "sg:city":"Presque Isle",
    "sg:classifiers":[
        {
            "category":"Professional",
            "subcategory":"Management & Consulting",
            "type":"Services"
        }
    ],
    "sg:phone":"+1 207 762 6096",
    "sg:postcode":"04769",
    "sg:province":"ME",
    "sg:tags":[
        "communications",
        "consultant"
    ],
    "wof:name":"Taylor Network Comm Inc",
    "wof:placetype":"venue"
},
  "geometry": {"coordinates":[-68.015502,46.680346],"type":"Point"}
}