{
  "type": "Feature",
  "properties": {
    "addr:full":"3 Flagg St Bangor ME 04401",
    "addr:housenumber":"3",
    "addr:postcode":"04401",
    "addr:street":"Flagg St",
    "iso:country":"US",
    "sg:address":"3 Flagg St",
    "sg:city":"Bangor",
    "sg:classifiers":[
        {
            "category":"Banks & Credit Unions",
            "subcategory":"Financial Services",
            "type":"Services"
        }
    ],
    "sg:phone":"+1 207 942 4510",
    "sg:postcode":"04401",
    "sg:province":"ME",
    "sg:tags":[
        "disabled",
        "work",
        "for"
    ],
    "wof:name":"Ability Consultants Inc",
    "wof:placetype":"venue"
},
  "geometry": {"coordinates":[-68.705018,44.837372],"type":"Point"}
}