{
  "type": "Feature",
  "properties": {
    "addr:full":"46 Waltham St. 4th Floor Boston ME 02118",
    "addr:housenumber":"46;4th floor",
    "addr:postcode":"02118",
    "addr:street":"Waltham St.",
    "iso:country":"US",
    "sg:address":"46 Waltham St. 4th Floor",
    "sg:city":"Boston",
    "sg:classifiers":[
        {
            "category":"Professional",
            "subcategory":"Advertising",
            "type":"Services"
        }
    ],
    "sg:phone":"+1 617 956 5050",
    "sg:postcode":"02118",
    "sg:province":"ME",
    "sg:website":"http://www.connellypartners.com/",
    "wof:name":"Connelly Partners",
    "wof:placetype":"venue"
},
  "geometry": {"coordinates":[-71.06953300000001,42.342256],"type":"Point"}
}