{
  "type": "Feature",
  "properties": {
    "iso:country":"US",
    "sg:address":"546 Sutherland Pond Rd",
    "sg:city":"Sabattus",
    "sg:classifiers":[
        {
            "category":"Home & Garden",
            "subcategory":"Building Materials",
            "type":"Retail Goods"
        }
    ],
    "sg:phone":"+1 207 375 8728",
    "sg:postcode":"04280",
    "sg:province":"ME",
    "sg:tags":[
        "lumber"
    ],
    "wof:name":"Thick-N-Thin Logging Co",
    "wof:placetype":"venue"
},
  "geometry": {"coordinates":[-70.070035,44.071894],"type":"Point"}
}