{
  "type": "Feature",
  "properties": {
    "iso:country":"US",
    "sg:address":"105 Old Webster Rd",
    "sg:city":"Lewiston",
    "sg:classifiers":[
        {
            "category":"Government",
            "subcategory":"Court House",
            "type":"Public Place"
        }
    ],
    "sg:phone":"+1 207 782 6561",
    "sg:postcode":"04240",
    "sg:province":"ME",
    "sg:tags":[
        "reporting"
    ],
    "wof:name":"A McLean Court Reporting Svcs",
    "wof:placetype":"venue"
},
  "geometry": {"coordinates":[-70.147948,44.076878],"type":"Point"}
}